Workbook

Sheet Jan
A1: PHILIPPINE INVESTMENT FUNDS ASSOCIATION, INC.
A2: MUTUAL FUNDS STATISTICAL REPORT
A3: Month of January 2022
A4: (Amounts in Peso)
I5: F O R - T H E - M O N T H | L5: Y E A R - T O - D A T E
A6: Fund Category | C6: Fund Name | D6: ASSETS | E6: LIABILITIES | F6: NET ASSETS | G6: EQUITY INV. | H6: NO. OF A/C | I6: SALES | J6: REDEMPTIONS | K6: NET SALES | L6: TOTAL SALES | M6: TOTAL REDEMPTIONS | N6: TOTAL NET SALES
A7: Stock Funds
A8: Primarily invested in Peso Securities (shares)
B9: 1 | C9: ALFM Growth Fund, Inc. | D9: 5.5179892e+09 | E9: 17386841 | F9: =D9-E9 -> 5500602324 | G9: 5221517716 | H9: 7670 | I9: 16578719 | J9: 59527096 | K9: =I9-J9 -> -42948377 | L9: =I9 -> 16578719 | M9: =J9 -> 59527096 | N9: =L9-M9 -> -42948377
B10: 2 | C10: ATRAM Alpha Opportunity Fund, Inc. (formerly, ATRKE Alpha Opportunity Fund, Inc.) | D10: 8.3966205e+08 | E10: 14606381 | F10: =D10-E10 -> 8.2505567e+08 | G10: 7.7282253e+08 | H10: 4318 | I10: 26363298 | J10: 12448817 | K10: =I10-J10 -> 13914480 | L10: =I10 -> 26363298 | M10: =J10 -> 12448817 | N10: =L10-M10 -> 13914480
B11: 3 | C11: ATRAM Phil. Equity Opportunity Fund, Inc. (formerly, ATRKE Equity Opportunity Fund, Inc.) | D11: 1.181147e+09 | E11: 3602939.4 | F11: =D11-E11 -> 1177544093 | G11: 1.1169147e+09 | H11: 2920 | I11: 19336344 | J11: 20237651 | K11: =I11-J11 -> -901307.42 | L11: =I11 -> 19336344 | M11: =J11 -> 20237651 | N11: =L11-M11 -> -901307.42
B12: 4 | C12: Climbs Share Capital Equity Investment Fund Corp. | D12: 3.6089249e+08 | E12: 8768078.7 | F12: =D12-E12 -> 3.5212441e+08 | G12: 1.1124367e+08 | H12: 1621 | I12: 1239934.8 | J12: 5155350.7 | K12: =I12-J12 -> -3915415.9 | L12: =I12 -> 1239934.8 | M12: =J12 -> 5155350.7 | N12: =L12-M12 -> -3915415.9
B13: 5 | C13: First Metro Consumer Fund on MSCI Phils. IMI, Inc. | D13: 6.0724955e+08 | E13: 22638785 | F13: =D13-E13 -> 5.8461076e+08 | G13: 5.3069916e+08 | H13: 1536 | I13: 1506512.2 | J13: 6275249.8 | K13: =I13-J13 -> -4768737.6 | L13: =I13 -> 1506512.2 | M13: =J13 -> 6275249.8 | N13: =L13-M13 -> -4768737.6
B14: 6 | C14: First Metro Save and Learn Equity Fund, Inc. | D14: 4.5966022e+09 | E14: 2.1260095e+08 | F14: =D14-E14 -> 4384001270 | G14: 3.9845724e+09 | H14: 16626 | I14: 42273854 | J14: 1.2164963e+08 | K14: =I14-J14 -> -79375779 | L14: =I14 -> 42273854 | M14: =J14 -> 1.2164963e+08 | N14: =L14-M14 -> -79375779
B15: 7 | C15: First Metro Save and Learn Phil. Index Fund, Inc. (formerly, One Wealthy Nation Fund, Inc.) | D15: 95793097 | E15: 627634.54 | F15: =D15-E15 -> 95165462 | G15: 92036632 | H15: 522 | I15: 1179498.6 | J15: 427978 | K15: =I15-J15 -> 751520.59 | L15: =I15 -> 1179498.6 | M15: =J15 -> 427978 | N15: =L15-M15 -> 751520.59
B16: 8 | C16: MBG Equity Investment Fund, Inc. | D16: 1.5160231e+08 | E16: 748143.77 | F16: =D16-E16 -> 1.5085417e+08 | G16: 1.4266239e+08 | H16: 50 | I16: 0 | J16: 0 | K16: =I16-J16 -> 0 | L16: =I16 -> 0 | M16: =J16 -> 0 | N16: =L16-M16 -> 0
B17: 9 | C17: PAMI Equity Index Fund, Inc. | D17: 1.7617541e+10 | E17: 1.08597e+08 | F17: =D17-E17 -> 17508943754 | G17: 1.7421561e+10 | H17: 12906 | I17: 2.306412e+08 | J17: 20341527 | K17: =I17-J17 -> 2.1029967e+08 | L17: =I17 -> 2.306412e+08 | M17: =J17 -> 20341527 | N17: =L17-M17 -> 2.1029967e+08
B18: 10 | C18: Philam Strategic Growth Fund, Inc. | D18: 3.6417171e+10 | E18: 1.3766723e+08 | F18: =D18-E18 -> 36279503946 | G18: 3.437328e+10 | H18: 12741 | I18: 90692795 | J18: 43775263 | K18: =I18-J18 -> 46917531 | L18: =I18 -> 90692795 | M18: =J18 -> 43775263 | N18: =L18-M18 -> 46917531
B19: 11 | C19: Philequity Dividend Yield Fund, Inc. | D19: 2.5451253e+09 | E19: 5184306.3 | F19: =D19-E19 -> 2539941020 | G19: 2.3826987e+09 | H19: 4697 | I19: 14697247 | J19: 60946454 | K19: =I19-J19 -> -46249207 | L19: =I19 -> 14697247 | M19: =J19 -> 60946454 | N19: =L19-M19 -> -46249207
B20: 12 | C20: Philequity Fund, Inc. | D20: 1.1195866e+10 | E20: 93886822 | F20: =D20-E20 -> 11101978939 | G20: 1.0336527e+10 | H20: 37263 | I20: 37032105 | J20: 34967192 | K20: =I20-J20 -> 2064913 | L20: =I20 -> 37032105 | M20: =J20 -> 34967192 | N20: =L20-M20 -> 2064913
... B27: 19 | C27: United Fund, Inc. | D27: 6.5910108e+08 | E27: 6989710.8 | F27: =D27-E27 -> 652111369 | G27: 5.8379131e+08 | H27: 1300 | I27: 976063.74 | J27: 477744.54 | K27: =I27-J27 -> 498319.2 | L27: =I27 -> 976063.74 | M27: =J27 -> 477744.54 | N27: =L27-M27 -> 498319.2
A28: Primarily invested in Peso Securities (units)
B29: 20 | C29: Philequity Alpha One Fund, Inc. | D29: 3.4147679e+08 | E29: 999989.53 | F29: =D29-E29 -> 3.404768e+08 | G29: 3.1221962e+08 | H29: 1042 | I29: 8239126.5 | J29: 4679932.7 | K29: =I29-J29 -> 3559193.8 | L29: =I29 -> 8239126.5 | M29: =J29 -> 4679932.7 | N29: =L29-M29 -> 3559193.8
B30: 21 | C30: Philippine Stock Index Fund Corp. | D30: 1.5393858e+08 | E30: 7577262.4 | F30: =D30-E30 -> 1.4636132e+08 | G30: 146293913 | H30: 120934 | I30: 1.6089645e+08 | J30: 13339551 | K30: =I30-J30 -> 1.475569e+08 | L30: =I30 -> 1.6089645e+08 | M30: =J30 -> 13339551 | N30: =L30-M30 -> 1.475569e+08
A31: Exchange Traded Fund
B32: 22 | C32: First Metro Phil. Equity Exchange Traded Fund, Inc. | D32: 2.2732739e+09 | E32: 6053519.2 | F32: =D32-E32 -> 2267220339 | G32: 2.2600147e+09 | H32: 3043 | I32: 10880756 | J32: 3331959 | K32: =I32-J32 -> 7548797 | L32: =I32 -> 10880756 | M32: =J32 -> 3331959 | N32: =L32-M32 -> 7548797
A33: Sub total - Peso Currency | D33: =SUM(D9:D32) -> 123021176865 | E33: =SUM(E9:E32) -> 8.1280275e+08 | F33: =SUM(F9:F32) -> 122208374115 | G33: =SUM(G9:G32) -> 117484683786 | H33: =SUM(H9:H32) -> 405474 | I33: =SUM(I9:I32) -> 948068606 | J33: =SUM(J9:J32) -> 8.1973635e+08 | K33: =SUM(K9:K32) -> 128332254 | ... N33: =SUM(N9:N32) -> 128332254
A34: Primarily invested in foreign currency securities (shares)
B35: 23 | C35: ATRAM AsiaPlus Equity Fund, Inc. (formerly, ATR KimEng AsiaPlus Recovery Fund, Inc.) | D35: 50202171 | E35: 1011746.4 | F35: =D35-E35 -> 49190425 | G35: 0 | H35: 57 | I35: 99.77 | J35: 3932.8 | K35: =I35-J35 -> -3833.03 | L35: =I35 -> 99.77 | M35: =J35 -> 3932.8 | N35: =L35-M35 -> -3833.03
B36: 24 | C36: Sun Life Prosperity World Voyager Fund, Inc. | D36: =50.95*38310707.15 -> 1951930529 | E36: =50.95*962842.17 -> 49056809 | F36: =D36-E36 -> 1902873721 | G36: 0 | H36: 2718 | I36: =50.95*517309.67 -> 26356928 | J36: =50.95*2016259.18 -> 1.0272841e+08 | K36: =I36-J36 -> -76371478 | L36: =I36 -> 26356928 | M36: =J36 -> 1.0272841e+08 | N36: =L36-M36 -> -76371478
A37: Sub total - US Currency | D37: =SUM(D35:D36) -> 2002132700 | E37: =SUM(E35:E36) -> 50068555 | F37: =SUM(F35:F36) -> 1952064145 | G37: =SUM(G35:G36) -> 0 | H37: =SUM(H35:H36) -> 2775 | I37: =SUM(I35:I36) -> 26357027 | J37: =SUM(J35:J36) -> 102732338 | K37: =SUM(K35:K36) -> -76375311 | ... N37: =SUM(N35:N36) -> -76375311
A38: Sub total - stock funds | D38: =D33+D37 -> 125023309566 | E38: =E33+E37 -> 8.6287131e+08 | F38: =F33+F37 -> 124160438260 | G38: =G33+G37 -> 117484683786 | H38: =H33+H37 -> 408249 | I38: =I33+I37 -> 9.7442563e+08 | J38: =J33+J37 -> 9.2246869e+08 | K38: =K33+K37 -> 51956943 | ... N38: =N33+N37 -> 51956943
A39: Balanced Funds
A40: Primarily invested in Peso Securities (shares)
B41: 25 | C41: ATRAM Dynamic Allocation Fund, Inc. (formerly, Optima Balanced Fund, Inc.) | D41: 1.3206969e+08 | E41: 3492791.5 | F41: =D41-E41 -> 1.285769e+08 | G41: 51581471 | H41: 747 | I41: 4280453.3 | J41: 651534.23 | K41: =I41-J41 -> 3628919.1 | L41: =I41 -> 4280453.3 | M41: =J41 -> 651534.23 | N41: =L41-M41 -> 3628919.1
B42: 26 | C42: ATRAM Philippine Balanced Fund, Inc. (formerly, ATRKE Philippine Balanced Fund, Inc.) | D42: 7.2513203e+08 | E42: 24440745 | F42: =D42-E42 -> 7.0069128e+08 | G42: 4.4385314e+08 | H42: 2502 | I42: 1461165.2 | J42: 5139792.9 | K42: =I42-J42 -> -3678627.7 | L42: =I42 -> 1461165.2 | M42: =J42 -> 5139792.9 | N42: =L42-M42 -> -3678627.7
B43: 27 | C43: First Metro Save and Learn Balanced Fund, Inc. | D43: 1.380406e+09 | E43: 63202847 | F43: =D43-E43 -> 1317203199 | G43: 8.0577773e+08 | H43: 4939 | I43: 2329359.7 | J43: 2786616.8 | K43: =I43-J43 -> -457257.08 | L43: =I43 -> 2329359.7 | M43: =J43 -> 2786616.8 | N43: =L43-M43 -> -457257.08
B44: 28 | C44: First Metro Save and Learn F.O.C.C.U.S. Dynamic Fund, Inc. | D44: 1.3671436e+08 | E44: 8732703.8 | F44: =D44-E44 -> 1.2798165e+08 | G44: 2.2600147e+09 | H44: 70 | I44: 98260869 | J44: 0 | K44: =I44-J44 -> 98260869 | L44: =I44 -> 98260869 | M44: =J44 -> 0 | N44: =L44-M44 -> 98260869
B45: 29 | C45: NCM Mutual Fund of the Phils., Inc. | D45: 3.6303231e+08 | E45: 1312853.8 | F45: =D45-E45 -> 361719457 | G45: 1.7603567e+08 | H45: 57 | I45: 0 | J45: 0 | K45: =I45-J45 -> 0 | L45: =I45 -> 0 | M45: =J45 -> 0 | N45: =L45-M45 -> 0
B46: 30 | C46: PAMI Horizon Fund, Inc. | D46: 6.5565586e+08 | E46: 16576585 | F46: =D46-E46 -> 6.3907927e+08 | G46: 3.5663041e+08 | H46: 10279 | I46: 253166.07 | J46: 8386100.3 | K46: =I46-J46 -> -8132934.2 | L46: =I46 -> 253166.07 | M46: =J46 -> 8386100.3 | N46: =L46-M46 -> -8132934.2
B47: 31 | C47: Philam Fund, Inc. | D47: 1.1395744e+10 | E47: 35536918 | F47: =D47-E47 -> 11360206941 | G47: 6211333357 | H47: 8406 | I47: 41269829 | J47: 22007006 | K47: =I47-J47 -> 19262823 | L47: =I47 -> 41269829 | M47: =J47 -> 22007006 | N47: =L47-M47 -> 19262823
B48: 32 | C48: Solidaritas Fund, Inc. (formerly, Bahay Pari Solidaritas Fund, Inc.) | D48: 1.4783804e+08 | E48: 320253.76 | F48: =D48-E48 -> 1.4751778e+08 | G48: 89579838 | H48: 196 | I48: 45991.71 | J48: 3215520 | K48: =I48-J48 -> -3169528.3 | L48: =I48 -> 45991.71 | M48: =J48 -> 3215520 | N48: =L48-M48 -> -3169528.3
B49: 33 | C49: Sun Life Prosperity Balanced Fund, Inc. | D49: 8.3030768e+09 | E49: 42234693 | F49: =D49-E49 -> 8260842097 | G49: 4994675097 | H49: 52918 | I49: 15220183 | J49: 66057466 | K49: =I49-J49 -> -50837283 | L49: =I49 -> 15220183 | M49: =J49 -> 66057466 | N49: =L49-M49 -> -50837283
B50: 34 | C50: Sun Life Prosperity Dynamic Fund, Inc. | D50: 1.3685021e+09 | E50: 40568508 | F50: =D50-E50 -> 1327933581 | G50: 1.1128918e+09 | H50: 4995 | I50: 0 | J50: 23784106 | K50: =I50-J50 -> -23784106 | L50: =I50 -> 0 | M50: =J50 -> 23784106 | N50: =L50-M50 -> -23784106
A51: Primarily invested in Peso Securities (units)
B52: 35 | C52: Sun Life Prosperity Achiever Fund 2028, Inc. | D52: 74261761 | E52: 251771.37 | F52: =D52-E52 -> 74009989 | G52: 27159507 | H52: 867 | I52: 1474283.4 | J52: 206099.56 | K52: =I52-J52 -> 1268183.9 | L52: =I52 -> 1474283.4 | M52: =J52 -> 206099.56 | N52: =L52-M52 -> 1268183.9
B53: 36 | C53: Sun Life Prosperity Achiever Fund 2038, Inc. | D53: 59477674 | E53: 228745.24 | F53: =D53-E53 -> 59248929 | G53: 46781714 | H53: 310 | I53: 2556421.4 | J53: 112777.68 | K53: =I53-J53 -> 2443643.7 | L53: =I53 -> 2556421.4 | M53: =J53 -> 112777.68 | N53: =L53-M53 -> 2443643.7
B54: 37 | C54: Sun Life Prosperity Achiever Fund 2048, Inc. | D54: 51593758 | E54: 199129.48 | F54: =D54-E54 -> 51394629 | G54: 43709574 | H54: 148 | I54: 950275.15 | J54: 43438.56 | K54: =I54-J54 -> 906836.59 | L54: =I54 -> 950275.15 | M54: =J54 -> 43438.56 | N54: =L54-M54 -> 906836.59
A55: Sub total - Peso Currency | D55: =SUM(D41:D54) -> 24793504259 | E55: =SUM(E41:E54) -> 237098546 | F55: =SUM(F41:F54) -> 24556405713 | G55: =SUM(G41:G54) -> 16620024042 | H55: =SUM(H41:H54) -> 86434 | I55: =SUM(I41:I54) -> 1.68102e+08 | J55: =SUM(J41:J54) -> 1.3239046e+08 | K55: =SUM(K41:K54) -> 35711539 | ... N55: =SUM(N41:N54) -> 35711539
A56: Primarily invested in foreign currency securities (shares)
B57: 38 | C57: Cocolife Dollar Fund Builder, Inc. | D57: =50.95*1445571.03 -> 73651844 | E57: =50.95*10868.95 -> 553773 | F57: =D57-E57 -> 73098071 | G57: 0 | H57: 56 | I57: =50.95*562.98 -> 28683.831 | J57: 0 | K57: =I57-J57 -> 28683.831 | L57: =I57 -> 28683.831 | M57: =J57 -> 0 | N57: =L57-M57 -> 28683.831
B58: 39 | C58: PAMI Asia Balanced Fund, Inc. | D58: =50.95*7636829.04 -> 3.8909644e+08 | E58: =50.95*422646.49 -> 21533839 | F58: =D58-E58 -> 3.675626e+08 | G58: =50.95*3827598.67 -> 1.9501615e+08 | H58: 279 | I58: 0 | J58: =50.95*5589.48 -> 284784.01 | K58: =I58-J58 -> -284784.01 | L58: =I58 -> 0 | M58: =J58 -> 284784.01 | N58: =L58-M58 -> -284784.01
B59: 40 | C59: Sun Life Prosperity Dollar Advantage Fund, Inc. | D59: =50.95*34474384.38 -> 1756469884 | E59: =50.95*141266.14 -> 7197509.8 | F59: =D59-E59 -> 1749272374 | G59: 0 | H59: 4096 | I59: =50.95*420717.21 -> 21435542 | J59: =50.95*1079251.05 -> 54987841 | K59: =I59-J59 -> -33552299 | L59: =I59 -> 21435542 | M59: =J59 -> 54987841 | N59: =L59-M59 -> -33552299
B60: 41 | C60: Sun Life Prosperity Dollar Wellspring Fund, Inc. | D60: =50.95*6831156.24 -> 3.4804741e+08 | E60: =50.95*48554.84 -> 2473869.1 | F60: =D60-E60 -> 3.4557354e+08 | G60: 0 | H60: 698 | I60: =50.95*15879.84 -> 809077.85 | J60: =50.95*100861.88 -> 5138912.8 | K60: =I60-J60 -> -4329834.9 | L60: =I60 -> 809077.85 | M60: =J60 -> 5138912.8 | N60: =L60-M60 -> -4329834.9
A61: Sub total - US Currency | D61: =SUM(D57:D60) -> 2567265578 | E61: =SUM(E57:E60) -> 31758991 | F61: =SUM(F57:F60) -> 2535506588 | G61: =SUM(G57:G60) -> 1.9501615e+08 | H61: =SUM(H57:H60) -> 5129 | I61: =SUM(I57:I60) -> 22273304 | J61: =SUM(J57:J60) -> 60411538 | K61: =SUM(K57:K60) -> -38138234 | ... N61: =SUM(N57:N60) -> -38138234
A62: Sub total - balanced funds | D62: =D55+D61 -> 27360769837 | E62: =E55+E61 -> 2.6885754e+08 | F62: =F55+F61 -> 27091912301 | G62: =G55+G61 -> 16815040194 | H62: =H55+H61 -> 91563 | I62: =I55+I61 -> 1.903753e+08 | J62: =J55+J61 -> 192801996 | K62: =K55+K61 -> -2426695.1 | ... N62: =N55+N61 -> -2426695.1
A63: Bond Funds
A64: Primarily invested in Peso Securities (shares)
B65: 42 | C65: ALFM Peso Bond Fund, Inc. | D65: 4.414936e+10 | E65: 2.7338569e+08 | F65: =D65-E65 -> 43875974347 | G65: 1207682360 | H65: 26784 | I65: 2.4003898e+08 | J65: 4.7615671e+08 | K65: =I65-J65 -> -2.3611773e+08 | L65: =I65 -> 2.4003898e+08 | M65: =J65 -> 4.7615671e+08 | N65: =L65-M65 -> -2.3611773e+08
B66: 43 | C66: ATRAM Corporate Bond Fund, Inc. (formerly, Prudentialife Fixed Income Fund, Inc.) | D66: 2.9515997e+08 | E66: 1035949.7 | F66: =D66-E66 -> 2.9412402e+08 | G66: 0 | H66: 1044 | I66: 1277555.4 | J66: 220778.64 | K66: =I66-J66 -> 1056776.7 | L66: =I66 -> 1277555.4 | M66: =J66 -> 220778.64 | N66: =L66-M66 -> 1056776.7
B67: 44 | C67: Cocolife Fixed Income Fund, Inc. | D67: 1.3535941e+09 | E67: 29243612 | F67: =D67-E67 -> 1324350487 | G67: 0 | H67: 2001 | I67: 1.0779884e+08 | J67: 10373563 | K67: =I67-J67 -> 97425282 | L67: =I67 -> 1.0779884e+08 | M67: =J67 -> 10373563 | N67: =L67-M67 -> 97425282
B68: 45 | C68: Ekklesia Mutual Fund, Inc. | D68: 2.0413105e+08 | E68: 307870.25 | F68: =D68-E68 -> 2.0382318e+08 | G68: 1.8181545e+08 | H68: 130 | I68: 752485.19 | J68: 35057.25 | K68: =I68-J68 -> 717427.94 | L68: =I68 -> 752485.19 | M68: =J68 -> 35057.25 | N68: =L68-M68 -> 717427.94
B69: 46 | C69: First Metro Save and Learn Fixed Income Fund, Inc. | D69: 1.549743e+09 | E69: 59630686 | F69: =D69-E69 -> 1490112353 | G69: 0 | H69: 1913 | I69: 6324282.5 | J69: 46179597 | K69: =I69-J69 -> -39855315 | L69: =I69 -> 6324282.5 | M69: =J69 -> 46179597 | N69: =L69-M69 -> -39855315
B70: 47 | C70: Philam Managed Income Fund, Inc. | D70: 1.0282665e+09 | E70: 37832587 | F70: =D70-E70 -> 9.9043387e+08 | G70: 0 | H70: 547 | I70: 1697418.4 | J70: 4337617.5 | K70: =I70-J70 -> -2640199.2 | L70: =I70 -> 1697418.4 | M70: =J70 -> 4337617.5 | N70: =L70-M70 -> -2640199.2
B71: 48 | C71: Philam Bond Fund, Inc. | D71: 6.7979344e+09 | E71: 17780889 | F71: =D71-E71 -> 6780153486 | G71: 0 | H71: 5196 | I71: 32178019 | J71: 17255010 | K71: =I71-J71 -> 14923009 | L71: =I71 -> 32178019 | M71: =J71 -> 17255010 | N71: =L71-M71 -> 14923009
B72: 49 | C72: Philequity Peso Bond Fund, Inc. | D72: 3.2315131e+08 | E72: 697163.25 | F72: =D72-E72 -> 3.2245415e+08 | G72: 17269670 | H72: 4123 | I72: 9932203.4 | J72: 1199347.8 | K72: =I72-J72 -> 8732855.6 | L72: =I72 -> 9932203.4 | M72: =J72 -> 1199347.8 | N72: =L72-M72 -> 8732855.6
B73: 50 | C73: Soldivo Bond Fund, Inc. | D73: 921918996 | E73: 3509162 | F73: =D73-E73 -> 918409834 | G73: 0 | H73: 782 | I73: 3312063.6 | J73: 1444824.7 | K73: =I73-J73 -> 1867238.9 | L73: =I73 -> 3312063.6 | M73: =J73 -> 1444824.7 | N73: =L73-M73 -> 1867238.9
B74: 51 | C74: Sun Life Prosperity Bond Fund, Inc. | D74: 4.7018794e+09 | E74: 7853815.8 | F74: =D74-E74 -> 4694025597 | G74: 0 | H74: 15929 | I74: 46651128 | J74: 49166770 | K74: =I74-J74 -> -2515641.9 | L74: =I74 -> 46651128 | M74: =J74 -> 49166770 | N74: =L74-M74 -> -2515641.9
B75: 52 | C75: Sun Life Prosperity GS Fund, Inc. | D75: 1.6086135e+08 | E75: 336668.09 | F75: =D75-E75 -> 160524682 | G75: 0 | H75: 2517 | I75: 820324.04 | J75: 2456729.5 | K75: =I75-J75 -> -1636405.5 | L75: =I75 -> 820324.04 | M75: =J75 -> 2456729.5 | N75: =L75-M75 -> -1636405.5
A76: Sub total - Peso Currency | D76: =SUM(D65:D75) -> 61486000081 | E76: =SUM(E65:E75) -> 4.3161409e+08 | F76: =SUM(F65:F75) -> 61054385991 | G76: =SUM(G65:G75) -> 1406767480 | H76: =SUM(H65:H75) -> 60966 | I76: =SUM(I65:I75) -> 4.507833e+08 | J76: =SUM(J65:J75) -> 6.0882601e+08 | K76: =SUM(K65:K75) -> -158042705 | ... N76: =SUM(N65:N75) -> -158042705
A77: Primarily invested in foreign currency securities (shares)
B78: 53 | C78: ALFM Dollar Bond Fund, Inc. | D78: =50.95*295072707.85 -> 15033954465 | E78: =50.95*1227917.47 -> 62562395 | F78: =D78-E78 -> 14971392070 | G78: 0 | H78: 10081 | I78: =50.95*2086366.04 -> 1.0630035e+08 | J78: =50.95*51622151.07 -> 2630148597 | K78: =I78-J78 -> -2523848247 | L78: =I78 -> 1.0630035e+08 | M78: =J78 -> 2630148597 | N78: =L78-M78 -> -2523848247
B79: 54 | C79: ATRAM Total Return Dollar Bond Fund, Inc. (formerly, ATR KimEng Total Return Bond Fund, Inc.) | D79: 7.9915032e+08 | E79: 2760788.3 | F79: =D79-E79 -> 7.9638954e+08 | G79: 0 | H79: 201 | I79: 85334.22 | J79: 75905.56 | K79: =I79-J79 -> 9428.66 | L79: =I79 -> 85334.22 | M79: =J79 -> 75905.56 | N79: =L79-M79 -> 9428.66
B80: 55 | C80: First Metro Save and Learn Dollar Bond Fund, Inc. | D80: 7.3327076e+08 | E80: 3017814.9 | F80: =D80-E80 -> 7.3025294e+08 | G80: 0 | H80: 157 | I80: 318126.19 | J80: 4584199.1 | K80: =I80-J80 -> -4266072.9 | L80: =I80 -> 318126.19 | M80: =J80 -> 4584199.1 | N80: =L80-M80 -> -4266072.9
B81: 56 | C81: PAMI Global Bond Fund Phils., Inc. | D81: =50.95*1283295.6 -> 65383911 | E81: =50.95*223818.76 -> 11403566 | F81: =D81-E81 -> 53980345 | G81: 0 | H81: 28 | I81: 0 | J81: 0 | K81: =I81-J81 -> 0 | L81: =I81 -> 0 | M81: =J81 -> 0 | N81: =L81-M81 -> 0
B82: 57 | C82: Philam Dollar Bond Fund, Inc. | D82: =50.95*45642288.19 -> 2325474583 | E82: =50.95*-224942.87 -> -11460839 | F82: =D82-E82 -> 2336935423 | G82: 0 | H82: 2068 | I82: =50.95*198.1 -> 10093.195 | J82: =50.95*77248.53 -> 3935812.6 | K82: =I82-J82 -> -3925719.4 | L82: =I82 -> 10093.195 | M82: =J82 -> 3935812.6 | N82: =L82-M82 -> -3925719.4
B83: 58 | C83: Philequity Dollar Income Fund, Inc. | D83: 2.2388048e+08 | E83: 869170.26 | F83: =D83-E83 -> 2.2301131e+08 | G83: 0 | H83: 131 | I83: 25475 | J83: 37628.103 | K83: =I83-J83 -> -12153.103 | L83: =I83 -> 25475 | M83: =J83 -> 37628.103 | N83: =L83-M83 -> -12153.103
B84: 59 | C84: Sun Life Prosperity Dollar Abundance Fund, Inc. | D84: =50.95*10608443.76 -> 5.4050021e+08 | E84: =50.95*500275.45 -> 25489034 | F84: =D84-E84 -> 5.1501118e+08 | G84: 0 | H84: 2512 | I84: =50.95*27473.37 -> 1399768.2 | J84: =50.95*46371.24 -> 2362614.7 | K84: =I84-J84 -> -962846.48 | L84: =I84 -> 1399768.2 | M84: =J84 -> 2362614.7 | N84: =L84-M84 -> -962846.48
A85: Sub total - US Currency | D85: =SUM(D78:D84) -> 19721614731 | E85: =SUM(E78:E84) -> 94641929 | F85: =SUM(F78:F84) -> 19626972802 | G85: =SUM(G78:G84) -> 0 | H85: =SUM(H78:H84) -> 15178 | I85: =SUM(I78:I84) -> 1.0813915e+08 | J85: =SUM(J78:J84) -> 2641144757 | K85: =SUM(K78:K84) -> -2533005611 | ... N85: =SUM(N78:N84) -> -2533005611
B86: 60 | C86: ALFM Euro Bond Fund, Inc. | D86: =56.967195*17167713.89 -> 9.779965e+08 | E86: =56.967195*75661.66 -> 4310232.5 | F86: =D86-E86 -> 9.7368627e+08 | G86: 0 | H86: 688 | I86: =56.967195*12726.21 -> 724976.49 | J86: =56.967195*34885.28 -> 1987316.5 | K86: =I86-J86 -> -1262340.1 | L86: =I86 -> 724976.49 | M86: =J86 -> 1987316.5 | N86: =L86-M86 -> -1262340.1
A87: Sub total - Euro Currency | D87: =SUM(D86) -> 9.779965e+08 | E87: =SUM(E86) -> 4310232.5 | F87: =SUM(F86) -> 9.7368627e+08 | G87: =SUM(G86) -> 0 | H87: =SUM(H86) -> 688 | I87: =SUM(I86) -> 724976.49 | J87: =SUM(J86) -> 1987316.5 | K87: =SUM(K86) -> -1262340.1 | ... N87: =SUM(N86) -> -1262340.1
A88: Sub total - bond funds | D88: =D76+D85+D87 -> 82185611317 | E88: =E76+E85+E87 -> 5.3056625e+08 | F88: =F76+F85+F87 -> 81655045066 | G88: =G76+G85+G87 -> 1406767480 | H88: =H76+H85+H87 -> 76832 | I88: =I76+I85+I87 -> 5.5964742e+08 | J88: =J76+J85+J87 -> 3251958080 | K88: =K76+K85+K87 -> -2692310656 | ... N88: =N76+N85+N87 -> -2692310656
A89: Money Market Funds
A90: Primarily invested in Peso Securities (shares)
B91: 61 | C91: ALFM Money Market Fund, Inc. | D91: 5.835833e+10 | E91: 47495416 | F91: =D91-E91 -> 58310834480 | G91: 0 | H91: 32146 | I91: 3.9226081e+09 | J91: 3.7262292e+09 | K91: =I91-J91 -> 1.9637887e+08 | L91: =I91 -> 3922608052 | M91: =J91 -> 3726229178 | N91: =L91-M91 -> 1.9637887e+08
B92: 62 | C92: First Metro Save and Learn Money Market Fund, Inc. | D92: 3.0973696e+09 | E92: 44032102 | F92: =D92-E92 -> 3053337515 | G92: 0 | H92: 505 | I92: 4.9708224e+08 | J92: 2.1701611e+08 | K92: =I92-J92 -> 280066128 | L92: =I92 -> 4.9708224e+08 | M92: =J92 -> 2.1701611e+08 | N92: =L92-M92 -> 280066128
B93: 63 | C93: Sun Life Prosperity Peso Starter Fund, Inc. | D93: 1.300865e+11 | E93: 6.3140151e+08 | F93: =D93-E93 -> 129455098363 | G93: 0 | H93: 57996 | I93: 1.7479567e+10 | J93: 1.5281567e+10 | K93: =I93-J93 -> 2198000070 | L93: =I93 -> 17479567004 | M93: =J93 -> 15281566934 | N93: =L93-M93 -> 2198000070
A94: Sub total - Peso Currency | D94: =SUM(D91:D93) -> 191542199390 | E94: =SUM(E91:E93) -> 722929032 | F94: =SUM(F91:F93) -> 190819270358 | G94: =SUM(G91:G93) -> 0 | H94: =SUM(H91:H93) -> 90647 | I94: =SUM(I91:I93) -> 21899257294 | J94: =SUM(J91:J93) -> 19224812222 | K94: =SUM(K91:K93) -> 2674445073 | ... N94: =SUM(N91:N93) -> 2674445073
A95: Primarily invested in foreign currency securities (shares)
B96: 64 | C96: Sun Life Prosperity Dollar Starter Fund, Inc. | D96: =50.95*181783499.39 -> 9261869294 | E96: =50.95*455733.9 -> 23219642 | F96: =D96-E96 -> 9238649652 | G96: 0 | H96: 2586 | I96: =50.95*28992800.5 -> 1477183185 | J96: =50.95*33426661.15 -> 1703088386 | K96: =I96-J96 -> -2.259052e+08 | L96: =I96 -> 1477183185 | M96: =J96 -> 1703088386 | N96: =L96-M96 -> -2.259052e+08
A97: Sub total - US Currency | D97: =SUM(D96) -> 9261869294 | E97: =SUM(E96) -> 23219642 | F97: =SUM(F96) -> 9238649652 | G97: =SUM(G96) -> 0 | H97: =SUM(H96) -> 2586 | I97: =SUM(I96) -> 1477183185 | J97: =SUM(J96) -> 1703088386 | K97: =SUM(K96) -> -2.259052e+08 | ... N97: =SUM(N96) -> -2.259052e+08
A98: Sub total - money market funds | D98: =D94+D97 -> 200804068684 | E98: =E94+E97 -> 7.4614867e+08 | F98: =F94+F97 -> 200057920010 | G98: =G94+G97 -> 0 | H98: =H94+H97 -> 93233 | I98: =I94+I97 -> 23376440480 | J98: =J94+J97 -> 20927900607 | K98: =K94+K97 -> 2448539872 | ... N98: =N94+N97 -> 2448539872
A99: Feeder Fund
A100: Primarily invested in Peso securities (units)
B101: 65 | C101: ALFM Global Multi-Asset Income Fund Inc. | D101: 8.1529972e+09 | E101: 161401919 | F101: =D101-E101 -> 7991595311 | G101: 0 | H101: 3189 | I101: 8.0997977e+08 | J101: 27840555 | K101: =I101-J101 -> 7.8213922e+08 | L101: =I101 -> 809979773 | M101: =J101 -> 27840555 | N101: =L101-M101 -> 7.8213922e+08
B102: 66 | C102: Sun Life Prosperity World Equity Index Feeder Fund, Inc. | D102: 3.5734428e+09 | E102: 78286856 | F102: =D102-E102 -> 3495155927 | G102: 0 | H102: 4702 | I102: 1.5534157e+08 | J102: 2.0479427e+08 | K102: =I102-J102 -> -49452705 | L102: =I102 -> 1.5534157e+08 | M102: =J102 -> 2.0479427e+08 | N102: =L102-M102 -> -49452705
A103: Sub total - Peso Currency | D103: =D101+D102 -> 11726440013 | E103: =E101+E102 -> 239688775 | F103: =F101+F102 -> 11486751238 | G103: =G101+G102 -> 0 | H103: =H101+H102 -> 7891 | I103: =I101+I102 -> 9.6532134e+08 | J103: =J101+J102 -> 2.3263483e+08 | K103: =K101+K102 -> 7.3268651e+08 | ... N103: =N101+N102 -> 7.3268651e+08
A104: Primarily invested in foreign currency securities (units)
B105: 67 | C105: ALFM Global Multi-Asset Income Fund, Inc. | D105: =50.95*200489206.92 -> 10214925093 | E105: =50.95*1438849.65 -> 73309390 | F105: =D105-E105 -> 10141615703 | G105: 0 | H105: 8321 | I105: =50.95*3819929.56 -> 1.9462541e+08 | J105: =50.95*2484464.52 -> 1.2658347e+08 | K105: =I105-J105 -> 68041944 | L105: =I105 -> 1.9462541e+08 | M105: =J105 -> 1.2658347e+08 | N105: =L105-M105 -> 68041944
A106: Sub total - US Currency | D106: =SUM(D105) -> 10214925093 | E106: =SUM(E105) -> 73309390 | F106: =SUM(F105) -> 10141615703 | G106: =SUM(G105) -> 0 | H106: =SUM(H105) -> 8321 | I106: =SUM(I105) -> 1.9462541e+08 | J106: =SUM(J105) -> 1.2658347e+08 | K106: =SUM(K105) -> 68041944 | ... N106: =SUM(N105) -> 68041944
...

Sheet Feb
A1: PHILIPPINE INVESTMENT FUNDS ASSOCIATION, INC.
A2: MUTUAL FUNDS STATISTICAL REPORT
A3: Month of February 2022
A4: (Amounts in Peso)
I5: F O R - T H E - M O N T H | L5: Y E A R - T O - D A T E
A6: Fund Category | C6: Fund Name | D6: ASSETS | E6: LIABILITIES | F6: NET ASSETS | G6: EQUITY INV. | H6: NO. OF A/C | I6: SALES | J6: REDEMPTIONS | K6: NET SALES | L6: TOTAL SALES | M6: TOTAL REDEMPTIONS | N6: TOTAL NET SALES
A7: Stock Funds
A8: Primarily invested in Peso Securities (shares)
B9: 1 | C9: ALFM Growth Fund, Inc. | D9: 5.5023457e+09 | E9: 41795235 | F9: =D9-E9 -> 5460550495 | G9: 5.1599286e+09 | H9: 7601 | I9: 16600435 | J9: 44507421 | K9: =I9-J9 -> -27906986 | L9: =I9+Jan!L9 -> 33179154 | M9: =J9+Jan!M9 -> 104034517 | N9: =L9-M9 -> -70855363
B10: 2 | C10: ATRAM Alpha Opportunity Fund, Inc. (formerly, ATRKE Alpha Opportunity Fund, Inc.) | D10: 9.0302162e+08 | E10: 46247536 | F10: =D10-E10 -> 8.5677408e+08 | G10: 7.5178026e+08 | H10: 4346 | I10: 98900298 | J10: 45823349 | K10: =I10-J10 -> 53076949 | L10: =I10+Jan!L10 -> 1.252636e+08 | M10: =J10+Jan!M10 -> 58272166 | N10: =L10-M10 -> 66991429
B11: 3 | C11: ATRAM Phil. Equity Opportunity Fund, Inc. (formerly, ATRKE Equity Opportunity Fund, Inc.) | D11: 1.2057533e+09 | E11: 20249179 | F11: =D11-E11 -> 1185504155 | G11: 1.125418e+09 | H11: 2934 | I11: 13774681 | J11: 5637747.8 | K11: =I11-J11 -> 8136932.8 | L11: =I11+Jan!L11 -> 33111025 | M11: =J11+Jan!M11 -> 25875399 | N11: =L11-M11 -> 7235625.4
B12: 4 | C12: Climbs Share Capital Equity Investment Fund Corp. | D12: 3.5901243e+08 | E12: 6112033.5 | F12: =D12-E12 -> 3.5290039e+08 | G12: 1.1949881e+08 | H12: 1645 | I12: 1434327.4 | J12: 303337.57 | K12: =I12-J12 -> 1130989.9 | L12: =I12+Jan!L12 -> 2674262.2 | M12: =J12+Jan!M12 -> 5458688.3 | N12: =L12-M12 -> -2784426.1
B13: 5 | C13: First Metro Consumer Fund on MSCI Phils. IMI, Inc. | D13: 5.7876478e+08 | E13: 1066443.3 | F13: =D13-E13 -> 5.7769833e+08 | G13: 4.4216959e+08 | H13: 1528 | I13: 13064894 | J13: 2483026.1 | K13: =I13-J13 -> 10581868 | L13: =I13+Jan!L13 -> 14571406 | M13: =J13+Jan!M13 -> 8758275.9 | N13: =L13-M13 -> 5813130
B14: 6 | C14: First Metro Save and Learn Equity Fund, Inc. | D14: 4.398399e+09 | E14: 65528050 | F14: =D14-E14 -> 4332870927 | G14: 4.0242637e+09 | H14: 16569 | I14: 42563072 | J14: 99409339 | K14: =I14-J14 -> -56846267 | L14: =I14+Jan!L14 -> 84836926 | M14: =J14+Jan!M14 -> 2.2105897e+08 | N14: =L14-M14 -> -1.3622205e+08
B15: 7 | C15: First Metro Save and Learn Phil. Index Fund, Inc. (formerly, One Wealthy Nation Fund, Inc.) | D15: 95296341 | E15: 1085574.4 | F15: =D15-E15 -> 94210767 | G15: 91097740 | H15: 525 | I15: 2260130.8 | J15: 2664832.1 | K15: =I15-J15 -> -404701.26 | L15: =I15+Jan!L15 -> 3439629.4 | M15: =J15+Jan!M15 -> 3092810.1 | N15: =L15-M15 -> 346819.33
B16: 8 | C16: MBG Equity Investment Fund, Inc. | D16: 1.5231995e+08 | E16: 788522.83 | F16: =D16-E16 -> 151531431 | G16: 1.4341738e+08 | H16: 50 | I16: 1500000 | J16: 950000 | K16: =I16-J16 -> 550000 | L16: =I16+Jan!L16 -> 1500000 | M16: =J16+Jan!M16 -> 950000 | N16: =L16-M16 -> 550000
B17: 9 | C17: PAMI Equity Index Fund, Inc. | D17: 1.7611372e+10 | E17: 38875099 | F17: =D17-E17 -> 17572497138 | G17: 1.7441594e+10 | H17: 12841 | I17: 2.1841968e+08 | J17: 12600102 | K17: =I17-J17 -> 2.0581958e+08 | L17: =I17+Jan!L17 -> 4.4906088e+08 | M17: =J17+Jan!M17 -> 32941629 | N17: =L17-M17 -> 4.1611925e+08
B18: 10 | C18: Philam Strategic Growth Fund, Inc. | D18: 3.6258664e+10 | E18: 2.3708773e+08 | F18: =D18-E18 -> 36021576552 | G18: 3.3963108e+10 | H18: 12681 | I18: 1.195454e+08 | J18: 2.807745e+08 | K18: =I18-J18 -> -1.612291e+08 | L18: =I18+Jan!L18 -> 2.1023819e+08 | M18: =J18+Jan!M18 -> 3.2454976e+08 | N18: =L18-M18 -> -1.1431157e+08
B19: 11 | C19: Philequity Dividend Yield Fund, Inc. | D19: 2.5453655e+09 | E19: 10292568 | F19: =D19-E19 -> 2535072969 | G19: 2.3363814e+09 | H19: 5127 | I19: 42284892 | J19: 13422890 | K19: =I19-J19 -> 28862002 | L19: =I19+Jan!L19 -> 56982138 | M19: =J19+Jan!M19 -> 74369343 | N19: =L19-M19 -> -17387205
B20: 12 | C20: Philequity Fund, Inc. | D20: 1.1071211e+10 | E20: 80060697 | F20: =D20-E20 -> 10991150660 | G20: 1.0167479e+10 | H20: 37169 | I20: 19886753 | J20: 52198284 | K20: =I20-J20 -> -32311531 | L20: =I20+Jan!L20 -> 56918857 | M20: =J20+Jan!M20 -> 87165476 | N20: =L20-M20 -> -30246618
... B27: 19 | C27: United Fund, Inc. | D27: 6.6871624e+08 | E27: 5676745.1 | F27: =D27-E27 -> 6.6303949e+08 | G27: 5.9165654e+08 | H27: 1303 | I27: 7901800.6 | J27: 307375.51 | K27: =I27-J27 -> 7594425.1 | L27: =I27+Jan!L27 -> 8877864.4 | M27: =J27+Jan!M27 -> 785120.05 | N27: =L27-M27 -> 8092744.3
A28: Primarily invested in Peso Securities (units)
B29: 20 | C29: Philequity Alpha One Fund, Inc. | D29: 3.6784988e+08 | E29: 6639840.3 | F29: =D29-E29 -> 3.6121004e+08 | G29: 3.1323153e+08 | H29: 1189 | I29: 18892860 | J29: 3320308.6 | K29: =I29-J29 -> 15572552 | L29: =I29+Jan!L29 -> 27131987 | M29: =J29+Jan!M29 -> 8000241.3 | N29: =L29-M29 -> 19131745
B30: 21 | C30: Philippine Stock Index Fund Corp. | D30: 2.0859375e+08 | E30: 17685844 | F30: =D30-E30 -> 1.9090791e+08 | G30: 190309510 | H30: 223356.55 | I30: 54985282 | J30: 8160245.7 | K30: =I30-J30 -> 46825036 | L30: =I30+Jan!L30 -> 2.1588173e+08 | M30: =J30+Jan!M30 -> 21499797 | N30: =L30-M30 -> 1.9438194e+08
A31: Exchange Traded Fund
B32: 22 | C32: First Metro Phil. Equity Exchange Traded Fund, Inc. | D32: 2.2703183e+09 | E32: 4918758.2 | F32: =D32-E32 -> 2265399587 | G32: 2.2435504e+09 | H32: 3087 | I32: 13570706 | J32: 0 | K32: =I32-J32 -> 13570706 | L32: =I32+Jan!L32 -> 24451462 | M32: =J32+Jan!M32 -> 3331959 | N32: =L32-M32 -> 21119503
A33: Sub total - Peso Currency | D33: =SUM(D9:D32) -> 122538486394 | E33: =SUM(E9:E32) -> 873652877 | F33: =SUM(F9:F32) -> 121664833517 | G33: =SUM(G9:G32) -> 116728959129 | H33: =SUM(H9:H32) -> 503500.55 | I33: =SUM(I9:I32) -> 1333415858 | J33: =SUM(J9:J32) -> 1240231063 | K33: =SUM(K9:K32) -> 93184795 | ... N33: =SUM(N9:N32) -> 2.2151705e+08
A34: Primarily invested in foreign currency securities (shares)
B35: 23 | C35: ATRAM AsiaPlus Equity Fund, Inc. (formerly, ATR KimEng AsiaPlus Recovery Fund, Inc.) | D35: 48507171 | E35: 870845.56 | F35: =D35-E35 -> 47636326 | G35: 0 | H35: 57 | I35: 66487.45 | J35: 0 | K35: =I35-J35 -> 66487.45 | L35: =I35+Jan!L35 -> 66587.22 | M35: =J35+Jan!M35 -> 3932.8 | N35: =L35-M35 -> 62654.42
B36: 24 | C36: Sun Life Prosperity World Voyager Fund, Inc. | D36: =51.27*38407946.19 -> 1969175401 | E36: =51.27*456910.44 -> 23425798 | F36: =D36-E36 -> 1945749603 | G36: 0 | H36: 2737 | I36: =51.27*1708172.56 -> 87578007 | J36: =51.27*827089.28 -> 42404867 | K36: =I36-J36 -> 45173140 | L36: =I36+Jan!L36 -> 1.1393493e+08 | M36: =J36+Jan!M36 -> 1.4513327e+08 | N36: =L36-M36 -> -31198338
A37: Sub total - US Currency | D37: =SUM(D35:D36) -> 2017682573 | E37: =SUM(E35:E36) -> 24296644 | F37: =SUM(F35:F36) -> 1993385929 | G37: =SUM(G35:G36) -> 0 | H37: =SUM(H35:H36) -> 2794 | I37: =SUM(I35:I36) -> 87644495 | J37: =SUM(J35:J36) -> 42404867 | K37: =SUM(K35:K36) -> 45239627 | ... N37: =SUM(N35:N36) -> -31135683
A38: Sub total - stock funds | D38: =D33+D37 -> 124556168967 | E38: =E33+E37 -> 8.9794952e+08 | F38: =F33+F37 -> 123658219446 | G38: =G33+G37 -> 116728959129 | H38: =H33+H37 -> 506294.55 | I38: =I33+I37 -> 1421060353 | J38: =J33+J37 -> 1282635931 | K38: =K33+K37 -> 1.3842442e+08 | ... N38: =N33+N37 -> 1.9038137e+08
A39: Balanced Funds
A40: Primarily invested in Peso Securities (shares)
B41: 25 | C41: ATRAM Dynamic Allocation Fund, Inc. (formerly, Optima Balanced Fund, Inc.) | D41: 1.3571173e+08 | E41: 7767502.2 | F41: =D41-E41 -> 1.2794423e+08 | G41: 44100274 | H41: 737 | I41: 640001.5 | J41: 408396.7 | K41: =I41-J41 -> 231604.8 | L41: =I41+Jan!L41 -> 4920454.8 | M41: =J41+Jan!M41 -> 1059930.9 | N41: =L41-M41 -> 3860523.9
B42: 26 | C42: ATRAM Philippine Balanced Fund, Inc. (formerly, ATRKE Philippine Balanced Fund, Inc.) | D42: 766179756 | E42: 77996203 | F42: =D42-E42 -> 6.8818355e+08 | G42: 3.6708896e+08 | H42: 2496 | I42: 2834082 | J42: 6744427.5 | K42: =I42-J42 -> -3910345.5 | L42: =I42+Jan!L42 -> 4295247.2 | M42: =J42+Jan!M42 -> 11884220 | N42: =L42-M42 -> -7588973.2
B43: 27 | C43: First Metro Save and Learn Balanced Fund, Inc. | D43: 1.2214972e+09 | E43: 15082503 | F43: =D43-E43 -> 1206414713 | G43: 7.5770798e+08 | H43: 4915 | I43: 2980749.5 | J43: 1.1344169e+08 | K43: =I43-J43 -> -1.1046094e+08 | L43: =I43+Jan!L43 -> 5310109.2 | M43: =J43+Jan!M43 -> 1.1622831e+08 | N43: =L43-M43 -> -1.109182e+08
B44: 28 | C44: First Metro Save and Learn F.O.C.C.U.S. Dynamic Fund, Inc. | D44: 2.0210034e+08 | E44: 2656225.7 | F44: =D44-E44 -> 1.9944412e+08 | G44: 1.5564739e+08 | H44: 117 | I44: 72806828 | J44: 9966.8754 | K44: =I44-J44 -> 72796861 | L44: =I44+Jan!L44 -> 1.710677e+08 | M44: =J44+Jan!M44 -> 9966.8754 | N44: =L44-M44 -> 1.7105773e+08
B45: 29 | C45: NCM Mutual Fund of the Phils., Inc. | D45: 3.6011492e+08 | E45: 1580349.6 | F45: =D45-E45 -> 3.5853457e+08 | G45: 1.7487343e+08 | H45: 57 | I45: 0 | J45: 1017100 | K45: =I45-J45 -> -1017100 | L45: =I45+Jan!L45 -> 0 | M45: =J45+Jan!M45 -> 1017100 | N45: =L45-M45 -> -1017100
B46: 30 | C46: PAMI Horizon Fund, Inc. | D46: 6.6010759e+08 | E46: 27068236 | F46: =D46-E46 -> 6.3303935e+08 | G46: 3.6444768e+08 | H46: 10272 | I46: 857580.44 | J46: 6899852.4 | K46: =I46-J46 -> -6042272 | L46: =I46+Jan!L46 -> 1110746.5 | M46: =J46+Jan!M46 -> 15285953 | N46: =L46-M46 -> -14175206
B47: 31 | C47: Philam Fund, Inc. | D47: 1.1439067e+10 | E47: 1.3671762e+08 | F47: =D47-E47 -> 11302349808 | G47: 6451520638 | H47: 8384 | I47: 30304316 | J47: 11544994 | K47: =I47-J47 -> 18759322 | L47: =I47+Jan!L47 -> 71574146 | M47: =J47+Jan!M47 -> 33552000 | N47: =L47-M47 -> 38022145
B48: 32 | C48: Solidaritas Fund, Inc. (formerly, Bahay Pari Solidaritas Fund, Inc.) | D48: 1.4782266e+08 | E48: 228418.95 | F48: =D48-E48 -> 1.4759424e+08 | G48: 93151779 | H48: 196 | I48: 210993.86 | J48: 0 | K48: =I48-J48 -> 210993.86 | L48: =I48+Jan!L48 -> 256985.57 | M48: =J48+Jan!M48 -> 3215520 | N48: =L48-M48 -> -2958534.4
B49: 33 | C49: Sun Life Prosperity Balanced Fund, Inc. | D49: 8.6952483e+09 | E49: 5.0024716e+08 | F49: =D49-E49 -> 8195001185 | G49: 4.9370881e+09 | H49: 52988 | I49: 13629410 | J49: 44305354 | K49: =I49-J49 -> -30675943 | L49: =I49+Jan!L49 -> 28849594 | M49: =J49+Jan!M49 -> 1.1036282e+08 | N49: =L49-M49 -> -81513227
B50: 34 | C50: Sun Life Prosperity Dynamic Fund, Inc. | D50: 1.3952951e+09 | E50: 85779714 | F50: =D50-E50 -> 1309515356 | G50: 1.0040864e+09 | H50: 4996 | I50: 0 | J50: 9843032.2 | K50: =I50-J50 -> -9843032.2 | L50: =I50+Jan!L50 -> 0 | M50: =J50+Jan!M50 -> 33627138 | N50: =L50-M50 -> -33627138
A51: Primarily invested in Peso Securities (units)
B52: 35 | C52: Sun Life Prosperity Achiever Fund 2028, Inc. | D52: 73972842 | E52: 140385.24 | F52: =D52-E52 -> 73832456 | G52: 27064186 | H52: 893 | I52: 795442.23 | J52: 55983.53 | K52: =I52-J52 -> 739458.7 | L52: =I52+Jan!L52 -> 2269725.6 | M52: =J52+Jan!M52 -> 262083.09 | N52: =L52-M52 -> 2007642.6
B53: 36 | C53: Sun Life Prosperity Achiever Fund 2038, Inc. | D53: 58869360 | E53: 253448.77 | F53: =D53-E53 -> 58615911 | G53: 46453070 | H53: 326 | I53: 552858.79 | J53: 91978.15 | K53: =I53-J53 -> 460880.64 | L53: =I53+Jan!L53 -> 3109280.2 | M53: =J53+Jan!M53 -> 204755.83 | N53: =L53-M53 -> 2904524.4
B54: 37 | C54: Sun Life Prosperity Achiever Fund 2048, Inc. | D54: 50869433 | E54: 233861.55 | F54: =D54-E54 -> 50635572 | G54: 43196271 | H54: 153 | I54: 137041.16 | J54: 39081.62 | K54: =I54-J54 -> 97959.54 | L54: =I54+Jan!L54 -> 1087316.3 | M54: =J54+Jan!M54 -> 82520.18 | N54: =L54-M54 -> 1004796.1
A55: Sub total - Peso Currency | D55: =SUM(D41:D54) -> 25206856684 | E55: =SUM(E41:E54) -> 8.5575163e+08 | F55: =SUM(F41:F54) -> 24351105055 | G55: =SUM(G41:G54) -> 14466426221 | H55: =SUM(H41:H54) -> 86530 | I55: =SUM(I41:I54) -> 125749304 | J55: =SUM(J41:J54) -> 194401857 | K55: =SUM(K41:K54) -> -68652553 | ... N55: =SUM(N41:N54) -> -32941014
A56: Primarily invested in foreign currency securities (shares)
B57: 38 | C57: Cocolife Dollar Fund Builder, Inc. | D57: =51.27*1503845.87 -> 77102178 | E57: =51.27*9096.86 -> 466396.01 | F57: =D57-E57 -> 76635782 | G57: 0 | H57: 56 | I57: =51.27*100896.29 -> 5172952.8 | J57: =51.27*10398.848 -> 533148.94 | K57: =I57-J57 -> 4639803.9 | L57: =I57+Jan!L57 -> 5201636.6 | M57: =J57+Jan!M57 -> 533148.94 | N57: =L57-M57 -> 4668487.7
B58: 39 | C58: PAMI Asia Balanced Fund, Inc. | D58: =51.27*7585920.03 -> 3.8893012e+08 | E58: =51.27*503821.89 -> 25830948 | F58: =D58-E58 -> 3.6309917e+08 | G58: =51.27*3772046.63 -> 1.9339283e+08 | H58: 278 | I58: =51.27*9199.76 -> 471671.7 | J58: =51.27*92278.24 -> 4731105.4 | K58: =I58-J58 -> -4259433.7 | L58: =I58+Jan!L58 -> 471671.7 | M58: =J58+Jan!M58 -> 5015889.4 | N58: =L58-M58 -> -4544217.7
B59: 40 | C59: Sun Life Prosperity Dollar Advantage Fund, Inc. | D59: =51.27*34335445.82 -> 1760378307 | E59: =51.27*285678.01 -> 14646712 | F59: =D59-E59 -> 1745731596 | G59: 0 | H59: 4102 | I59: =51.27*567357.63 -> 29088426 | J59: =51.27*440481.78 -> 22583501 | K59: =I59-J59 -> 6504924.8 | L59: =I59+Jan!L59 -> 50523968 | M59: =J59+Jan!M59 -> 77571342 | N59: =L59-M59 -> -27047374
B60: 41 | C60: Sun Life Prosperity Dollar Wellspring Fund, Inc. | D60: =51.27*6687874.34 -> 3.4288732e+08 | E60: =51.27*14869.39 -> 762353.63 | F60: =D60-E60 -> 3.4212496e+08 | G60: 0 | H60: 698 | I60: =51.27*8000 -> 410160 | J60: =51.27*11473.11 -> 588226.35 | K60: =I60-J60 -> -178066.35 | L60: =I60+Jan!L60 -> 1219237.8 | M60: =J60+Jan!M60 -> 5727139.1 | N60: =L60-M60 -> -4507901.3
A61: Sub total - US Currency | D61: =SUM(D57:D60) -> 2569297922 | E61: =SUM(E57:E60) -> 41706410 | F61: =SUM(F57:F60) -> 2527591513 | G61: =SUM(G57:G60) -> 1.9339283e+08 | H61: =SUM(H57:H60) -> 5134 | I61: =SUM(I57:I60) -> 35143210 | J61: =SUM(J57:J60) -> 28435982 | K61: =SUM(K57:K60) -> 6707228.7 | ... N61: =SUM(N57:N60) -> -31431006
A62: Sub total - balanced funds | D62: =D55+D61 -> 27776154606 | E62: =E55+E61 -> 8.9745804e+08 | F62: =F55+F61 -> 26878696568 | G62: =G55+G61 -> 14659819052 | H62: =H55+H61 -> 91664 | I62: =I55+I61 -> 1.6089251e+08 | J62: =J55+J61 -> 2.2283784e+08 | K62: =K55+K61 -> -61945324 | ... N62: =N55+N61 -> -64372020
A63: Bond Funds
A64: Primarily invested in Peso Securities (shares)
B65: 42 | C65: ALFM Peso Bond Fund, Inc. | D65: 4.3404098e+10 | E65: 2.2615649e+08 | F65: =D65-E65 -> 43177941750 | G65: 1188846160 | H65: 26665 | I65: 2.7659391e+08 | J65: 8.8444716e+08 | K65: =I65-J65 -> -6.0785325e+08 | L65: =I65+Jan!L65 -> 5.1663289e+08 | M65: =J65+Jan!M65 -> 1360603874 | N65: =L65-M65 -> -8.4397099e+08
B66: 43 | C66: ATRAM Corporate Bond Fund, Inc. (formerly, Prudentialife Fixed Income Fund, Inc.) | D66: 3.3300126e+08 | E66: 33626112 | F66: =D66-E66 -> 2.9937515e+08 | G66: 0 | H66: 1048 | I66: 7000503.9 | J66: 1651569.6 | K66: =I66-J66 -> 5348934.3 | L66: =I66+Jan!L66 -> 8278059.3 | M66: =J66+Jan!M66 -> 1872348.3 | N66: =L66-M66 -> 6405711
B67: 44 | C67: Cocolife Fixed Income Fund, Inc. | D67: 1.3474219e+09 | E67: 18887830 | F67: =D67-E67 -> 1328534083 | G67: 0 | H67: 2011 | I67: 7048275.7 | J67: 1249200.9 | K67: =I67-J67 -> 5799074.9 | L67: =I67+Jan!L67 -> 1.1484712e+08 | M67: =J67+Jan!M67 -> 11622764 | N67: =L67-M67 -> 1.0322436e+08
B68: 45 | C68: Ekklesia Mutual Fund, Inc. | D68: 2.02264e+08 | E68: 277862.29 | F68: =D68-E68 -> 2.0198614e+08 | G68: 4965000 | H68: 126 | I68: 329484.35 | J68: 45745.44 | K68: =I68-J68 -> 283738.91 | L68: =I68+Jan!L68 -> 1081969.5 | M68: =J68+Jan!M68 -> 80802.69 | N68: =L68-M68 -> 1001166.8
B69: 46 | C69: First Metro Save and Learn Fixed Income Fund, Inc. | D69: 1.5381565e+09 | E69: 58975454 | F69: =D69-E69 -> 1479181071 | G69: 0 | H69: 1907 | I69: 1689985.5 | J69: 7119695.2 | K69: =I69-J69 -> -5429709.7 | L69: =I69+Jan!L69 -> 8014268 | M69: =J69+Jan!M69 -> 53299292 | N69: =L69-M69 -> -45285024
B70: 47 | C70: Philam Managed Income Fund, Inc. | D70: 9.9478556e+08 | E70: 38277540 | F70: =D70-E70 -> 9.5650802e+08 | G70: 0 | H70: 543 | I70: 4381318.9 | J70: 34905707 | K70: =I70-J70 -> -30524388 | L70: =I70+Jan!L70 -> 6078737.2 | M70: =J70+Jan!M70 -> 39243324 | N70: =L70-M70 -> -33164587
B71: 48 | C71: Philam Bond Fund, Inc. | D71: 6.6640314e+09 | E71: 19787237 | F71: =D71-E71 -> 6644244200 | G71: 0 | H71: 5177 | I71: 30906977 | J71: 56337473 | K71: =I71-J71 -> -25430496 | L71: =I71+Jan!L71 -> 63084996 | M71: =J71+Jan!M71 -> 73592483 | N71: =L71-M71 -> -10507487
B72: 49 | C72: Philequity Peso Bond Fund, Inc. | D72: 3.1614425e+08 | E72: 1195062 | F72: =D72-E72 -> 3.1494918e+08 | G72: 17187040 | H72: 4159 | I72: 2133699 | J72: 5486864.9 | K72: =I72-J72 -> -3353165.9 | L72: =I72+Jan!L72 -> 12065902 | M72: =J72+Jan!M72 -> 6686212.6 | N72: =L72-M72 -> 5379689.8
B73: 50 | C73: Soldivo Bond Fund, Inc. | D73: 1.1610123e+09 | E73: 2.4923196e+08 | F73: =D73-E73 -> 9.1178034e+08 | G73: 0 | H73: 855 | I73: 354760.93 | J73: 155741.13 | K73: =I73-J73 -> 199019.8 | L73: =I73+Jan!L73 -> 3666824.6 | M73: =J73+Jan!M73 -> 1600565.8 | N73: =L73-M73 -> 2066258.7
B74: 51 | C74: Sun Life Prosperity Bond Fund, Inc. | D74: 5.2304944e+09 | E74: 5.8635846e+08 | F74: =D74-E74 -> 4644135971 | G74: 0 | H74: 15981 | I74: 36758397 | J74: 50528611 | K74: =I74-J74 -> -13770214 | L74: =I74+Jan!L74 -> 83409525 | M74: =J74+Jan!M74 -> 99695381 | N74: =L74-M74 -> -16285856
B75: 52 | C75: Sun Life Prosperity GS Fund, Inc. | D75: 1.7694257e+08 | E75: 18544514 | F75: =D75-E75 -> 1.5839806e+08 | G75: 0 | H75: 2529 | I75: 629646.59 | J75: 1179774.6 | K75: =I75-J75 -> -550128.06 | L75: =I75+Jan!L75 -> 1449970.6 | M75: =J75+Jan!M75 -> 3636504.2 | N75: =L75-M75 -> -2186533.5
A76: Sub total - Peso Currency | D76: =SUM(D65:D75) -> 61368352483 | E76: =SUM(E65:E75) -> 1251318520 | F76: =SUM(F65:F75) -> 60117033962 | G76: =SUM(G65:G75) -> 1210998200 | H76: =SUM(H65:H75) -> 61001 | I76: =SUM(I65:I75) -> 3.6782696e+08 | J76: =SUM(J65:J75) -> 1043107546 | K76: =SUM(K65:K75) -> -6.7528059e+08 | ... N76: =SUM(N65:N75) -> -8.3332329e+08
A77: Primarily invested in foreign currency securities (shares)
B78: 53 | C78: ALFM Dollar Bond Fund, Inc. | D78: =51.27*292286349.75 -> 14985521152 | E78: =51.27*823292.42 -> 42210202 | F78: =D78-E78 -> 14943310949 | G78: 0 | H78: 9984 | I78: =51.27*2626128.9 -> 1.3464163e+08 | J78: =51.27*3859795 -> 1.9789169e+08 | K78: =I78-J78 -> -63250061 | L78: =I78+Jan!L78 -> 2.4094198e+08 | M78: =J78+Jan!M78 -> 2828040287 | N78: =L78-M78 -> -2587098308
B79: 54 | C79: ATRAM Total Return Dollar Bond Fund, Inc. (formerly, ATR KimEng Total Return Bond Fund, Inc.) | D79: 7.5949707e+08 | E79: 2670206.7 | F79: =D79-E79 -> 7.5682687e+08 | G79: 0 | H79: 204 | I79: 5983702.7 | J79: 10430382 | K79: =I79-J79 -> -4446679.4 | L79: =I79+Jan!L79 -> 6069037 | M79: =J79+Jan!M79 -> 10506288 | N79: =L79-M79 -> -4437250.7
B80: 55 | C80: First Metro Save and Learn Dollar Bond Fund, Inc. | D80: 7.1749005e+08 | E80: 2944348 | F80: =D80-E80 -> 7.145457e+08 | G80: 0 | H80: 156 | I80: 471918.43 | J80: 982244.51 | K80: =I80-J80 -> -510326.08 | L80: =I80+Jan!L80 -> 790044.62 | M80: =J80+Jan!M80 -> 5566443.6 | N80: =L80-M80 -> -4776399
B81: 56 | C81: PAMI Global Bond Fund Phils., Inc. | D81: =51.27*1259120.11 -> 64555088 | E81: =51.27*235558.67 -> 12077093 | F81: =D81-E81 -> 52477995 | G81: 0 | H81: 27 | I81: 0 | J81: =51.27*7046.39 -> 361268.42 | K81: =I81-J81 -> -361268.42 | L81: =I81+Jan!L81 -> 0 | M81: =J81+Jan!M81 -> 361268.42 | N81: =L81-M81 -> -361268.42
B82: 57 | C82: Philam Dollar Bond Fund, Inc. | D82: =51.27*44208629.73 -> 2266576446 | E82: =51.27*-234373.79 -> -12016344 | F82: =D82-E82 -> 2278592790 | G82: 0 | H82: 2061 | I82: =51.27*3099444.38 -> 1.5890851e+08 | J82: =51.27*78833.53 -> 4041795.1 | K82: =I82-J82 -> 1.5486672e+08 | L82: =I82+Jan!L82 -> 1.5891861e+08 | M82: =J82+Jan!M82 -> 7977607.7 | N82: =L82-M82 -> 1.50941e+08
B83: 58 | C83: Philequity Dollar Income Fund, Inc. | D83: 2.2255149e+08 | E83: 2013320.8 | F83: =D83-E83 -> 2.2053817e+08 | G83: 0 | H83: 129 | I83: 968050 | J83: 1422475.1 | K83: =I83-J83 -> -454425.09 | L83: =I83+Jan!L83 -> 993525 | M83: =J83+Jan!M83 -> 1460103.2 | N83: =L83-M83 -> -466578.19
B84: 59 | C84: Sun Life Prosperity Dollar Abundance Fund, Inc. | D84: =51.27*9712979.15 -> 497984441 | E84: =51.27*65724.44 -> 3369692 | F84: =D84-E84 -> 494614749 | G84: 0 | H84: 2512 | I84: =51.27*2643.36 -> 135525.07 | J84: =51.27*77224.55 -> 3959302.7 | K84: =I84-J84 -> -3823777.6 | L84: =I84+Jan!L84 -> 1535293.3 | M84: =J84+Jan!M84 -> 6321917.4 | N84: =L84-M84 -> -4786624.1
A85: Sub total - US Currency | D85: =SUM(D78:D84) -> 19514175739 | E85: =SUM(E78:E84) -> 53268519 | F85: =SUM(F78:F84) -> 19460907221 | G85: =SUM(G78:G84) -> 0 | H85: =SUM(H78:H84) -> 15073 | I85: =SUM(I78:I84) -> 3.0110934e+08 | J85: =SUM(J78:J84) -> 2.1908916e+08 | K85: =SUM(K78:K84) -> 82020181 | ... N85: =SUM(N78:N84) -> -2450985430
B86: 60 | C86: ALFM Euro Bond Fund, Inc. | D86: =57.330114*16855953.59 -> 9.6635374e+08 | E86: =57.330114*19792.6 -> 1134712 | F86: =D86-E86 -> 9.6521903e+08 | G86: 0 | H86: 684 | I86: =57.330114*17644.67 -> 1011570.9 | J86: =57.330114*99717.35 -> 5716807 | K86: =I86-J86 -> -4705236.1 | L86: =I86+Jan!L86 -> 1736547.4 | M86: =J86+Jan!M86 -> 7704123.6 | N86: =L86-M86 -> -5967576.2
A87: Sub total - Euro Currency | D87: =SUM(D86) -> 9.6635374e+08 | E87: =SUM(E86) -> 1134712 | F87: =SUM(F86) -> 9.6521903e+08 | G87: =SUM(G86) -> 0 | H87: =SUM(H86) -> 684 | I87: =SUM(I86) -> 1011570.9 | J87: =SUM(J86) -> 5716807 | K87: =SUM(K86) -> -4705236.1 | ... N87: =SUM(N86) -> -5967576.2
A88: Sub total - bond funds | D88: =D76+D85+D87 -> 81848881963 | E88: =E76+E85+E87 -> 1305721751 | F88: =F76+F85+F87 -> 80543160212 | G88: =G76+G85+G87 -> 1210998200 | H88: =H76+H85+H87 -> 76758 | I88: =I76+I85+I87 -> 6.6994787e+08 | J88: =J76+J85+J87 -> 1267913511 | K88: =K76+K85+K87 -> -597965643 | ... N88: =N76+N85+N87 -> -3290276299
A89: Money Market Funds
A90: Primarily invested in Peso Securities (shares)
B91: 61 | C91: ALFM Money Market Fund, Inc. | D91: 5.9244956e+10 | E91: 63688599 | F91: =D91-E91 -> 59181267496 | G91: 0 | H91: 32471 | I91: 3.2591828e+09 | J91: 2.4372119e+09 | K91: =I91-J91 -> 8.2197093e+08 | L91: =I91+Jan!L91 -> 7181790853 | M91: =J91+Jan!M91 -> 6163441052 | N91: =L91-M91 -> 1018349801
B92: 62 | C92: First Metro Save and Learn Money Market Fund, Inc. | D92: 3.1484894e+09 | E92: 93262720 | F92: =D92-E92 -> 3055226642 | G92: 0 | H92: 525 | I92: 1.8008736e+08 | J92: 1.8035248e+08 | K92: =I92-J92 -> -265122.72 | L92: =I92+Jan!L92 -> 6.7716959e+08 | M92: =J92+Jan!M92 -> 3.9736859e+08 | N92: =L92-M92 -> 2.7980101e+08
B93: 63 | C93: Sun Life Prosperity Peso Starter Fund, Inc. | D93: 1.2958133e+11 | E93: 4.1415173e+09 | F93: =D93-E93 -> 125439812917 | G93: 0 | H93: 58488 | I93: 1.364982e+10 | J93: 1.7825124e+10 | K93: =I93-J93 -> -4175304185 | L93: =I93+Jan!L93 -> 31129386949 | M93: =J93+Jan!M93 -> 33106691063 | N93: =L93-M93 -> -1977304115
A94: Sub total - Peso Currency | D94: =SUM(D91:D93) -> 191974775639 | E94: =SUM(E91:E93) -> 4298468584 | F94: =SUM(F91:F93) -> 187676307054 | G94: =SUM(G91:G93) -> 0 | H94: =SUM(H91:H93) -> 91484 | I94: =SUM(I91:I93) -> 17089090102 | J94: =SUM(J91:J93) -> 20442688483 | K94: =SUM(K91:K93) -> -3353598381 | ... N94: =SUM(N91:N93) -> -6.7915331e+08
A95: Primarily invested in foreign currency securities (shares)
B96: 64 | C96: Sun Life Prosperity Dollar Starter Fund, Inc. | D96: =51.27*206051018.02 -> 10564235694 | E96: =51.27*4552977.59 -> 233431161 | F96: =D96-E96 -> 10330804533 | G96: 0 | H96: 2669 | I96: =51.27*55107428.18 -> 2825357843 | J96: =51.27*35060953.03 -> 1797575062 | K96: =I96-J96 -> 1027782781 | L96: =I96+Jan!L96 -> 4302541028 | M96: =J96+Jan!M96 -> 3500663447 | N96: =L96-M96 -> 8.0187758e+08
A97: Sub total - US Currency | D97: =SUM(D96) -> 10564235694 | E97: =SUM(E96) -> 233431161 | F97: =SUM(F96) -> 10330804533 | G97: =SUM(G96) -> 0 | H97: =SUM(H96) -> 2669 | I97: =SUM(I96) -> 2825357843 | J97: =SUM(J96) -> 1797575062 | K97: =SUM(K96) -> 1027782781 | ... N97: =SUM(N96) -> 8.0187758e+08
A98: Sub total - money market funds | D98: =D94+D97 -> 202539011332 | E98: =E94+E97 -> 4531899745 | F98: =F94+F97 -> 198007111587 | G98: =G94+G97 -> 0 | H98: =H94+H97 -> 94153 | I98: =I94+I97 -> 19914447945 | J98: =J94+J97 -> 22240263545 | K98: =K94+K97 -> -2325815600 | ... N98: =N94+N97 -> 1.2272427e+08
A99: Feeder Fund
A100: Primarily invested in Peso securities (units)
B101: 65 | C101: ALFM Global Multi-Asset Income Fund Inc. | D101: 8.3745357e+09 | E101: 25540108 | F101: =D101-E101 -> 8348995610 | G101: 0 | H101: 3189 | I101: 5.3424461e+08 | J101: 23804911 | K101: =I101-J101 -> 5.104397e+08 | L101: =I101+Jan!L101 -> 1344224387 | M101: =J101+Jan!M101 -> 51645466 | N101: =L101-M101 -> 1292578921
B102: 66 | C102: Sun Life Prosperity World Equity Index Feeder Fund, Inc. | D102: 3.6869531e+09 | E102: 96739363 | F102: =D102-E102 -> 3590213776 | G102: 0 | H102: 4911 | I102: 3.2329087e+08 | J102: 2.380437e+08 | K102: =I102-J102 -> 85247161 | L102: =I102+Jan!L102 -> 4.7863243e+08 | M102: =J102+Jan!M102 -> 4.4283798e+08 | N102: =L102-M102 -> 35794456
A103: Sub total - Peso Currency | D103: =D101+D102 -> 12061488856 | E103: =E101+E102 -> 1.2227947e+08 | F103: =F101+F102 -> 11939209385 | G103: =G101+G102 -> 0 | H103: =H101+H102 -> 8100 | I103: =I101+I102 -> 857535480 | J103: =J101+J102 -> 2.6184862e+08 | K103: =K101+K102 -> 5.9568686e+08 | ... N103: =N101+N102 -> 1328373377
A104: Primarily invested in foreign currency securities (units)
B105: 67 | C105: ALFM Global Multi-Asset Income Fund, Inc. | D105: =51.27*199681751.74 -> 10237683412 | E105: =51.27*774149.44 -> 39690642 | F105: =D105-E105 -> 10197992770 | G105: 0 | H105: 8321 | I105: =51.27*5906252.64 -> 3.0281357e+08 | J105: =51.27*1145674.37 -> 58738725 | K105: =I105-J105 -> 2.4407485e+08 | L105: =I105+Jan!L105 -> 4.9743898e+08 | M105: =J105+Jan!M105 -> 1.8532219e+08 | N105: =L105-M105 -> 3.1211679e+08
A106: Sub total - US Currency | D106: =SUM(D105) -> 10237683412 | E106: =SUM(E105) -> 39690642 | F106: =SUM(F105) -> 10197992770 | G106: =SUM(G105) -> 0 | H106: =SUM(H105) -> 8321 | I106: =SUM(I105) -> 3.0281357e+08 | J106: =SUM(J105) -> 58738725 | K106: =SUM(K105) -> 2.4407485e+08 | ... N106: =SUM(N105) -> 3.1211679e+08
...

Sheet Mar
A1: PHILIPPINE INVESTMENT FUNDS ASSOCIATION, INC.
A2: MUTUAL FUNDS STATISTICAL REPORT
A3: Month of March 2022
A4: (Amounts in Peso)
I5: F O R - T H E - M O N T H | L5: Y E A R - T O - D A T E
A6: Fund Category | C6: Fund Name | D6: ASSETS | E6: LIABILITIES | F6: NET ASSETS | G6: EQUITY INV. | H6: NO. OF A/C | I6: SALES | J6: REDEMPTIONS | K6: NET SALES | L6: TOTAL SALES | M6: TOTAL REDEMPTIONS | N6: TOTAL NET SALES
A7: Stock Funds
A8: Primarily invested in Peso Securities (shares)
B9: 1 | C9: ALFM Growth Fund, Inc. | D9: 5.4255175e+09 | E9: 28682990 | F9: =D9-E9 -> 5396834531 | G9: 5102527402 | H9: 7552 | I9: 20452327 | J9: 46191957 | K9: =I9-J9 -> -25739631 | L9: =I9+Feb!L9 -> 53631481 | M9: =J9+Feb!M9 -> 1.5022647e+08 | N9: =L9-M9 -> -96594994
B10: 2 | C10: ATRAM Alpha Opportunity Fund, Inc. (formerly, ATRKE Alpha Opportunity Fund, Inc.) | D10: 8.3970022e+08 | E10: 2668826.9 | F10: =D10-E10 -> 837031397 | G10: 7.6814084e+08 | H10: 4365 | I10: 20098937 | J10: 15697829 | K10: =I10-J10 -> 4401107.6 | L10: =I10+Feb!L10 -> 1.4536253e+08 | M10: =J10+Feb!M10 -> 73969996 | N10: =L10-M10 -> 71392537
B11: 3 | C11: ATRAM Phil. Equity Opportunity Fund, Inc. (formerly, ATRKE Equity Opportunity Fund, Inc.) | D11: 1.1818333e+09 | E11: 4636608 | F11: =D11-E11 -> 1177196657 | G11: 1.1173972e+09 | H11: 2926 | I11: 13437584 | J11: 7523678.8 | K11: =I11-J11 -> 5913904.8 | L11: =I11+Feb!L11 -> 46548608 | M11: =J11+Feb!M11 -> 33399078 | N11: =L11-M11 -> 13149530
B12: 4 | C12: Climbs Share Capital Equity Investment Fund Corp. | D12: 3.5764422e+08 | E12: 6277681.5 | F12: =D12-E12 -> 3.5136654e+08 | G12: 1.3690588e+08 | H12: 1637 | I12: 2392431.6 | J12: 828815.08 | K12: =I12-J12 -> 1563616.6 | L12: =I12+Feb!L12 -> 5066693.8 | M12: =J12+Feb!M12 -> 6287503.3 | N12: =L12-M12 -> -1220809.5
B13: 5 | C13: First Metro Consumer Fund on MSCI Phils. IMI, Inc. | D13: 5.4189985e+08 | E13: 2088591.7 | F13: =D13-E13 -> 5.3981126e+08 | G13: 3.2308374e+08 | H13: 1516 | I13: 3394080.8 | J13: 1336116.5 | K13: =I13-J13 -> 2057964.3 | L13: =I13+Feb!L13 -> 17965487 | M13: =J13+Feb!M13 -> 10094392 | N13: =L13-M13 -> 7871094.3
B14: 6 | C14: First Metro Save and Learn Equity Fund, Inc. | D14: 4.5297684e+09 | E14: 90400916 | F14: =D14-E14 -> 4439367518 | G14: 4.16045e+09 | H14: 16549 | I14: 1.589971e+08 | J14: 26955818 | K14: =I14-J14 -> 1.3204129e+08 | L14: =I14+Feb!L14 -> 2.4383403e+08 | M14: =J14+Feb!M14 -> 2.4801479e+08 | N14: =L14-M14 -> -4180760.9
B15: 7 | C15: First Metro Save and Learn Phil. Index Fund, Inc. (formerly, One Wealthy Nation Fund, Inc.) | D15: 95537171 | E15: 673071.94 | F15: =D15-E15 -> 94864099 | G15: 92658060 | H15: 528 | I15: 2452560.8 | J15: 1045150.3 | K15: =I15-J15 -> 1407410.5 | L15: =I15+Feb!L15 -> 5892190.2 | M15: =J15+Feb!M15 -> 4137960.4 | N15: =L15-M15 -> 1754229.8
B16: 8 | C16: MBG Equity Investment Fund, Inc. | D16: 1.4503946e+08 | E16: 1321641.8 | F16: =D16-E16 -> 1.4371782e+08 | G16: 1.3588403e+08 | H16: 51 | I16: 100000 | J16: 0 | K16: =I16-J16 -> 100000 | L16: =I16+Feb!L16 -> 1600000 | M16: =J16+Feb!M16 -> 950000 | N16: =L16-M16 -> 650000
B17: 9 | C17: PAMI Equity Index Fund, Inc. | D17: 1.7734575e+10 | E17: 1.1436651e+08 | F17: =D17-E17 -> 17620208196 | G17: 1.7409542e+10 | H17: 12653 | I17: 2.0349806e+08 | J17: 19417689 | K17: =I17-J17 -> 1.8408037e+08 | L17: =I17+Feb!L17 -> 6.5255894e+08 | M17: =J17+Feb!M17 -> 52359318 | N17: =L17-M17 -> 6.0019962e+08
B18: 10 | C18: Philam Strategic Growth Fund, Inc. | D18: 3.6072818e+10 | E18: 2.3966711e+08 | F18: =D18-E18 -> 35833150750 | G18: 3.3811235e+10 | H18: 12509 | I18: 1.0984326e+08 | J18: 49551411 | K18: =I18-J18 -> 60291849 | L18: =I18+Feb!L18 -> 3.2008145e+08 | M18: =J18+Feb!M18 -> 3.7410117e+08 | N18: =L18-M18 -> -54019718
B19: 11 | C19: Philequity Dividend Yield Fund, Inc. | D19: 2.4315306e+09 | E19: 8614573.5 | F19: =D19-E19 -> 2422915983 | G19: 2.2154061e+09 | H19: 5440 | I19: 7939366 | J19: 1.3200375e+08 | K19: =I19-J19 -> -1.2406438e+08 | L19: =I19+Feb!L19 -> 64921504 | M19: =J19+Feb!M19 -> 2.0637309e+08 | N19: =L19-M19 -> -1.4145159e+08
B20: 12 | C20: Philequity Fund, Inc. | D20: 1.0987251e+10 | E20: 55251287 | F20: =D20-E20 -> 10932000014 | G20: 1.0234858e+10 | H20: 37125 | I20: 43254081 | J20: 97810271 | K20: =I20-J20 -> -54556190 | L20: =I20+Feb!L20 -> 100172938 | M20: =J20+Feb!M20 -> 1.8497575e+08 | N20: =L20-M20 -> -84802809
... B27: 19 | C27: United Fund, Inc. | D27: 6.5564841e+08 | E27: 2533259.3 | F27: =D27-E27 -> 6.5311515e+08 | G27: 5.8535425e+08 | H27: 1305 | I27: 856512.45 | J27: 2625310 | K27: =I27-J27 -> -1768797.5 | L27: =I27+Feb!L27 -> 9734376.8 | M27: =J27+Feb!M27 -> 3410430 | N27: =L27-M27 -> 6323946.8
A28: Primarily invested in Peso Securities (units)
B29: 20 | C29: Philequity Alpha One Fund, Inc. | D29: 3.8454509e+08 | E29: 1490616 | F29: =D29-E29 -> 3.8305447e+08 | G29: 3.2953919e+08 | H29: 1381 | I29: 23361793 | J29: 1374530.4 | K29: =I29-J29 -> 21987262 | L29: =I29+Feb!L29 -> 50493779 | M29: =J29+Feb!M29 -> 9374771.7 | N29: =L29-M29 -> 41119008
B30: 21 | C30: Philippine Stock Index Fund Corp. | D30: 2.6831137e+08 | E30: 8129778.2 | F30: =D30-E30 -> 2.6018159e+08 | G30: 257930952 | H30: 262090 | I30: 76075942 | J30: 5716365.5 | K30: =I30-J30 -> 70359576 | L30: =I30+Feb!L30 -> 2.9195767e+08 | M30: =J30+Feb!M30 -> 27216162 | N30: =L30-M30 -> 2.6474151e+08
A31: Exchange Traded Fund
B32: 22 | C32: First Metro Phil. Equity Exchange Traded Fund, Inc. | D32: 2.2667763e+09 | E32: 4989457.7 | F32: =D32-E32 -> 2261786813 | G32: 2.2396655e+09 | H32: 3147 | I32: 12829924 | J32: 1110966 | K32: =I32-J32 -> 11718958 | L32: =I32+Feb!L32 -> 37281386 | M32: =J32+Feb!M32 -> 4442925 | N32: =L32-M32 -> 32838461
A33: Sub total - Peso Currency | D33: =SUM(D9:D32) -> 121832814330 | E33: =SUM(E9:E32) -> 8.6269359e+08 | F33: =SUM(F9:F32) -> 120970120741 | G33: =SUM(G9:G32) -> 115973117152 | H33: =SUM(H9:H32) -> 548400 | I33: =SUM(I9:I32) -> 1182359131 | J33: =SUM(J9:J32) -> 9.8425006e+08 | K33: =SUM(K9:K32) -> 1.9810907e+08 | ... N33: =SUM(N9:N32) -> 4.1962612e+08
A34: Primarily invested in foreign currency securities (shares)
B35: 23 | C35: ATRAM AsiaPlus Equity Fund, Inc. (formerly, ATR KimEng AsiaPlus Recovery Fund, Inc.) | D35: 46768822 | E35: 6166296.6 | F35: =D35-E35 -> 40602526 | G35: 0 | H35: 55 | I35: 265868.06 | J35: 5524304.1 | K35: =I35-J35 -> -5258436.1 | L35: =I35+Feb!L35 -> 332455.28 | M35: =J35+Feb!M35 -> 5528236.9 | N35: =L35-M35 -> -5195781.6
B36: 24 | C36: Sun Life Prosperity World Voyager Fund, Inc. | D36: =51.74*40944318.38 -> 2118459033 | E36: =51.74*166192.94 -> 8598822.7 | F36: =D36-E36 -> 2109860210 | G36: 0 | H36: 2764 | I36: =51.74*1960281.65 -> 1.0142497e+08 | J36: =51.74*543941.09 -> 28143512 | K36: =I36-J36 -> 73281461 | L36: =I36+Feb!L36 -> 2.1535991e+08 | M36: =J36+Feb!M36 -> 1.7327678e+08 | N36: =L36-M36 -> 42083123
A37: Sub total - US Currency | D37: =SUM(D35:D36) -> 2165227855 | E37: =SUM(E35:E36) -> 14765119 | F37: =SUM(F35:F36) -> 2150462736 | G37: =SUM(G35:G36) -> 0 | H37: =SUM(H35:H36) -> 2819 | I37: =SUM(I35:I36) -> 1.0169084e+08 | J37: =SUM(J35:J36) -> 33667816 | K37: =SUM(K35:K36) -> 68023025 | ... N37: =SUM(N35:N36) -> 36887341
A38: Sub total - stock funds | D38: =D33+D37 -> 123998042185 | E38: =E33+E37 -> 8.7745871e+08 | F38: =F33+F37 -> 123120583477 | G38: =G33+G37 -> 115973117152 | H38: =H33+H37 -> 551219 | I38: =I33+I37 -> 1284049972 | J38: =J33+J37 -> 1017917877 | K38: =K33+K37 -> 2.6613209e+08 | ... N38: =N33+N37 -> 4.5651346e+08
A39: Balanced Funds
A40: Primarily invested in Peso Securities (shares)
B41: 25 | C41: ATRAM Dynamic Allocation Fund, Inc. (formerly, Optima Balanced Fund, Inc.) | D41: 1.2696265e+08 | E41: 1383198.2 | F41: =D41-E41 -> 1.2557945e+08 | G41: 26371510 | H41: 732 | I41: 651643.41 | J41: 1441232.7 | K41: =I41-J41 -> -789589.26 | L41: =I41+Feb!L41 -> 5572098.2 | M41: =J41+Feb!M41 -> 2501163.6 | N41: =L41-M41 -> 3070934.6
B42: 26 | C42: ATRAM Philippine Balanced Fund, Inc. (formerly, ATRKE Philippine Balanced Fund, Inc.) | D42: 6.7250306e+08 | E42: 7174557.7 | F42: =D42-E42 -> 6.653285e+08 | G42: 2.8338959e+08 | H42: 2495 | I42: 1747521.9 | J42: 13626132 | K42: =I42-J42 -> -11878610 | L42: =I42+Feb!L42 -> 6042769.1 | M42: =J42+Feb!M42 -> 25510352 | N42: =L42-M42 -> -19467583
B43: 27 | C43: First Metro Save and Learn Balanced Fund, Inc. | D43: 1.2182981e+09 | E43: 19534120 | F43: =D43-E43 -> 1198763973 | G43: 7.6569518e+08 | H43: 4893 | I43: 4957005.9 | J43: 7163798.2 | K43: =I43-J43 -> -2206792.3 | L43: =I43+Feb!L43 -> 10267115 | M43: =J43+Feb!M43 -> 123392105 | N43: =L43-M43 -> -1.1312499e+08
B44: 28 | C44: First Metro Save and Learn F.O.C.C.U.S. Dynamic Fund, Inc. | D44: 2.5287461e+08 | E44: 7299630.1 | F44: =D44-E44 -> 2.4557498e+08 | G44: 1.8250664e+08 | H44: 149 | I44: 59037067 | J44: 11371674 | K44: =I44-J44 -> 47665393 | L44: =I44+Feb!L44 -> 2.3010476e+08 | M44: =J44+Feb!M44 -> 11381641 | N44: =L44-M44 -> 2.1872312e+08
B45: 29 | C45: NCM Mutual Fund of the Phils., Inc. | D45: 3.5850689e+08 | E45: 1627177.6 | F45: =D45-E45 -> 3.5687971e+08 | G45: 1.7236078e+08 | H45: 57 | I45: 0 | J45: 0 | K45: =I45-J45 -> 0 | L45: =I45+Feb!L45 -> 0 | M45: =J45+Feb!M45 -> 1017100 | N45: =L45-M45 -> -1017100
B46: 30 | C46: PAMI Horizon Fund, Inc. | D46: 6.3515457e+08 | E46: 11829793 | F46: =D46-E46 -> 6.2332478e+08 | G46: 361984395 | H46: 10165 | I46: 360586.55 | J46: 6995274.6 | K46: =I46-J46 -> -6634688.1 | L46: =I46+Feb!L46 -> 1471333.1 | M46: =J46+Feb!M46 -> 22281227 | N46: =L46-M46 -> -20809894
B47: 31 | C47: Philam Fund, Inc. | D47: 1.1295683e+10 | E47: 40136018 | F47: =D47-E47 -> 11255547324 | G47: 6444223272 | H47: 8296 | I47: 27161296 | J47: 20370592 | K47: =I47-J47 -> 6790704.6 | L47: =I47+Feb!L47 -> 98735442 | M47: =J47+Feb!M47 -> 53922592 | N47: =L47-M47 -> 44812850
B48: 32 | C48: Solidaritas Fund, Inc. (formerly, Bahay Pari Solidaritas Fund, Inc.) | D48: 1.4789848e+08 | E48: 429328.78 | F48: =D48-E48 -> 1.4746915e+08 | G48: 92865536 | H48: 197 | I48: 52990.86 | J48: 0 | K48: =I48-J48 -> 52990.86 | L48: =I48+Feb!L48 -> 309976.43 | M48: =J48+Feb!M48 -> 3215520 | N48: =L48-M48 -> -2905543.5
B49: 33 | C49: Sun Life Prosperity Balanced Fund, Inc. | D49: 8.2173379e+09 | E49: 1.1393224e+08 | F49: =D49-E49 -> 8103405693 | G49: 4.9011811e+09 | H49: 53077 | I49: 24490969 | J49: 61406480 | K49: =I49-J49 -> -36915511 | L49: =I49+Feb!L49 -> 53340563 | M49: =J49+Feb!M49 -> 1.717693e+08 | N49: =L49-M49 -> -1.1842874e+08
B50: 34 | C50: Sun Life Prosperity Dynamic Fund, Inc. | D50: 1.2996623e+09 | E50: 15349962 | F50: =D50-E50 -> 1284312307 | G50: 9.1155601e+08 | H50: 4997 | I50: 0 | J50: 5004190.6 | K50: =I50-J50 -> -5004190.6 | L50: =I50+Feb!L50 -> 0 | M50: =J50+Feb!M50 -> 38631328 | N50: =L50-M50 -> -38631328
A51: Primarily invested in Peso Securities (units)
B52: 35 | C52: Sun Life Prosperity Achiever Fund 2028, Inc. | D52: 73387625 | E52: 54004.21 | F52: =D52-E52 -> 73333621 | G52: 26976163 | H52: 914 | I52: 547642.22 | J52: 289756.08 | K52: =I52-J52 -> 257886.14 | L52: =I52+Feb!L52 -> 2817367.9 | M52: =J52+Feb!M52 -> 551839.17 | N52: =L52-M52 -> 2265528.7
B53: 36 | C53: Sun Life Prosperity Achiever Fund 2038, Inc. | D53: 58756310 | E53: 140445.17 | F53: =D53-E53 -> 58615865 | G53: 46563313 | H53: 338 | I53: 382210.92 | J53: 9816.1 | K53: =I53-J53 -> 372394.82 | L53: =I53+Feb!L53 -> 3491491.1 | M53: =J53+Feb!M53 -> 214571.93 | N53: =L53-M53 -> 3276919.2
B54: 37 | C54: Sun Life Prosperity Achiever Fund 2048, Inc. | D54: 50568402 | E54: 124646.21 | F54: =D54-E54 -> 50443756 | G54: 43036694 | H54: 158 | I54: 164369.06 | J54: 14521.26 | K54: =I54-J54 -> 149847.8 | L54: =I54+Feb!L54 -> 1251685.4 | M54: =J54+Feb!M54 -> 97041.44 | N54: =L54-M54 -> 1154643.9
A55: Sub total - Peso Currency | D55: =SUM(D41:D54) -> 24407594241 | E55: =SUM(E41:E54) -> 2.1901512e+08 | F55: =SUM(F41:F54) -> 24188579121 | G55: =SUM(G41:G54) -> 14258710196 | H55: =SUM(H41:H54) -> 86468 | I55: =SUM(I41:I54) -> 1.195533e+08 | J55: =SUM(J41:J54) -> 1.2769347e+08 | K55: =SUM(K41:K54) -> -8140164 | ... N55: =SUM(N41:N54) -> -41081178
A56: Primarily invested in foreign currency securities (shares)
B57: 38 | C57: Cocolife Dollar Fund Builder, Inc. | D57: =51.74*1482133.68 -> 76685597 | E57: =51.74*8375.65 -> 433356.13 | F57: =D57-E57 -> 76252240 | G57: 0 | H57: 58 | I57: =51.74*5.38 -> 278.3612 | J57: 0 | K57: =I57-J57 -> 278.3612 | L57: =I57+Feb!L57 -> 5201915 | M57: =J57+Feb!M57 -> 533148.94 | N57: =L57-M57 -> 4668766
B58: 39 | C58: PAMI Asia Balanced Fund, Inc. | D58: =51.74*7328674.74 -> 379185631 | E58: =51.74*435712.59 -> 22543769 | F58: =D58-E58 -> 3.5664186e+08 | G58: =51.74*3666097.71 -> 1.896839e+08 | H58: 271 | I58: =51.74*1370.01 -> 70884.317 | J58: =51.74*57748.43 -> 2987903.8 | K58: =I58-J58 -> -2917019.5 | L58: =I58+Feb!L58 -> 542556.01 | M58: =J58+Feb!M58 -> 8003793.1 | N58: =L58-M58 -> -7461237.1
B59: 40 | C59: Sun Life Prosperity Dollar Advantage Fund, Inc. | D59: =51.74*34393030.33 -> 1779495389 | E59: =51.74*184357.15 -> 9538638.9 | F59: =D59-E59 -> 1769956750 | G59: 0 | H59: 4109 | I59: =51.74*46070.94 -> 2383710.4 | J59: =51.74*370916 -> 19191194 | K59: =I59-J59 -> -16807483 | L59: =I59+Feb!L59 -> 52907678 | M59: =J59+Feb!M59 -> 96762536 | N59: =L59-M59 -> -43854858
B60: 41 | C60: Sun Life Prosperity Dollar Wellspring Fund, Inc. | D60: =51.74*6655754.49 -> 3.4436874e+08 | E60: =51.74*54366.07 -> 2812900.5 | F60: =D60-E60 -> 3.4155584e+08 | G60: 0 | H60: 701 | I60: =51.74*10923.68 -> 565191.2 | J60: =51.74*54340.04 -> 2811553.7 | K60: =I60-J60 -> -2246362.5 | L60: =I60+Feb!L60 -> 1784429.1 | M60: =J60+Feb!M60 -> 8538692.8 | N60: =L60-M60 -> -6754263.8
A61: Sub total - US Currency | D61: =SUM(D57:D60) -> 2579735354 | E61: =SUM(E57:E60) -> 35328665 | F61: =SUM(F57:F60) -> 2544406689 | G61: =SUM(G57:G60) -> 1.896839e+08 | H61: =SUM(H57:H60) -> 5139 | I61: =SUM(I57:I60) -> 3020064.3 | J61: =SUM(J57:J60) -> 24990651 | K61: =SUM(K57:K60) -> -21970587 | ... N61: =SUM(N57:N60) -> -53401593
A62: Sub total - balanced funds | D62: =D55+D61 -> 26987329595 | E62: =E55+E61 -> 254343785 | F62: =F55+F61 -> 26732985810 | G62: =G55+G61 -> 14448394092 | H62: =H55+H61 -> 91607 | I62: =I55+I61 -> 1.2257337e+08 | J62: =J55+J61 -> 1.5268412e+08 | K62: =K55+K61 -> -30110751 | ... N62: =N55+N61 -> -94482770
A63: Bond Funds
A64: Primarily invested in Peso Securities (shares)
B65: 42 | C65: ALFM Peso Bond Fund, Inc. | D65: 4.3185819e+10 | E65: 2.3997053e+08 | F65: =D65-E65 -> 42945848338 | G65: 1220720800 | H65: 26461 | I65: 3.8574399e+08 | J65: 6.3527424e+08 | K65: =I65-J65 -> -2.4953025e+08 | L65: =I65+Feb!L65 -> 902376876 | M65: =J65+Feb!M65 -> 1995878119 | N65: =L65-M65 -> -1093501243
B66: 43 | C66: ATRAM Corporate Bond Fund, Inc. (formerly, Prudentialife Fixed Income Fund, Inc.) | D66: 3.0911155e+08 | E66: 8015049.2 | F66: =D66-E66 -> 3.010965e+08 | G66: 0 | H66: 1056 | I66: 8118886.5 | J66: 6613203.3 | K66: =I66-J66 -> 1505683.2 | L66: =I66+Feb!L66 -> 16396946 | M66: =J66+Feb!M66 -> 8485551.5 | N66: =L66-M66 -> 7911394.3
B67: 44 | C67: Cocolife Fixed Income Fund, Inc. | D67: 1.322327e+09 | E67: 20381163 | F67: =D67-E67 -> 1301945837 | G67: 0 | H67: 2074 | I67: 3729750.7 | J67: 29080462 | K67: =I67-J67 -> -25350711 | L67: =I67+Feb!L67 -> 1.1857687e+08 | M67: =J67+Feb!M67 -> 40703225 | N67: =L67-M67 -> 77873646
B68: 45 | C68: Ekklesia Mutual Fund, Inc. | D68: 2.0105611e+08 | E68: 304222.97 | F68: =D68-E68 -> 2.0075189e+08 | G68: 5175000 | H68: 136 | I68: 342474.52 | J68: 1037414.3 | K68: =I68-J68 -> -694939.82 | L68: =I68+Feb!L68 -> 1424444.1 | M68: =J68+Feb!M68 -> 1118217 | N68: =L68-M68 -> 306227.03
B69: 46 | C69: First Metro Save and Learn Fixed Income Fund, Inc. | D69: 1.493759e+09 | E69: 9831051.7 | F69: =D69-E69 -> 1483927985 | G69: 0 | H69: 1902 | I69: 11293477 | J69: 5938161.3 | K69: =I69-J69 -> 5355315.5 | L69: =I69+Feb!L69 -> 19307745 | M69: =J69+Feb!M69 -> 59237454 | N69: =L69-M69 -> -39929709
B70: 47 | C70: Philam Managed Income Fund, Inc. | D70: 9.7601637e+08 | E70: 37651206 | F70: =D70-E70 -> 9.3836516e+08 | G70: 0 | H70: 533 | I70: 913844.69 | J70: 17503028 | K70: =I70-J70 -> -16589183 | L70: =I70+Feb!L70 -> 6992581.9 | M70: =J70+Feb!M70 -> 56746352 | N70: =L70-M70 -> -49753770
B71: 48 | C71: Philam Bond Fund, Inc. | D71: 6.5618147e+09 | E71: 20183699 | F71: =D71-E71 -> 6541630964 | G71: 0 | H71: 5124 | I71: 54588468 | J71: 1.3136345e+08 | K71: =I71-J71 -> -76774981 | L71: =I71+Feb!L71 -> 1.1767346e+08 | M71: =J71+Feb!M71 -> 2.0495593e+08 | N71: =L71-M71 -> -87282469
B72: 49 | C72: Philequity Peso Bond Fund, Inc. | D72: 3.1719001e+08 | E72: 985201.63 | F72: =D72-E72 -> 3.1620481e+08 | G72: 17352300 | H72: 4180 | I72: 2868471.1 | J72: 1246491.6 | K72: =I72-J72 -> 1621979.5 | L72: =I72+Feb!L72 -> 14934374 | M72: =J72+Feb!M72 -> 7932704.2 | N72: =L72-M72 -> 7001669.3
B73: 50 | C73: Soldivo Bond Fund, Inc. | D73: 9.1980503e+08 | E73: 12165936 | F73: =D73-E73 -> 9.0763909e+08 | G73: 0 | H73: 852 | I73: 3158489.6 | J73: 347108.39 | K73: =I73-J73 -> 2811381.2 | L73: =I73+Feb!L73 -> 6825314.2 | M73: =J73+Feb!M73 -> 1947674.2 | N73: =L73-M73 -> 4877640
B74: 51 | C74: Sun Life Prosperity Bond Fund, Inc. | D74: 4.6055209e+09 | E74: 10414584 | F74: =D74-E74 -> 4595106282 | G74: 0 | H74: 16025 | I74: 48389340 | J74: 91789840 | K74: =I74-J74 -> -43400500 | L74: =I74+Feb!L74 -> 1.3179887e+08 | M74: =J74+Feb!M74 -> 1.9148522e+08 | N74: =L74-M74 -> -59686356
B75: 52 | C75: Sun Life Prosperity GS Fund, Inc. | D75: 1.5512183e+08 | E75: 540211.13 | F75: =D75-E75 -> 1.5458162e+08 | G75: 0 | H75: 2543 | I75: 1625156.5 | J75: 5257075.7 | K75: =I75-J75 -> -3631919.2 | L75: =I75+Feb!L75 -> 3075127.1 | M75: =J75+Feb!M75 -> 8893579.8 | N75: =L75-M75 -> -5818452.7
A76: Sub total - Peso Currency | D76: =SUM(D65:D75) -> 60047541342 | E76: =SUM(E65:E75) -> 3.6044285e+08 | F76: =SUM(F65:F75) -> 59687098488 | G76: =SUM(G65:G75) -> 1243248100 | H76: =SUM(H65:H75) -> 60886 | I76: =SUM(I65:I75) -> 5.2077235e+08 | J76: =SUM(J65:J75) -> 9.2545048e+08 | K76: =SUM(K65:K75) -> -4.0467813e+08 | ... N76: =SUM(N65:N75) -> -1238001422
A77: Primarily invested in foreign currency securities (shares)
B78: 53 | C78: ALFM Dollar Bond Fund, Inc. | D78: =51.74*284086480.64 -> 14698634508 | E78: =51.74*1229342.79 -> 63606196 | F78: =D78-E78 -> 14635028312 | G78: 0 | H78: 9820 | I78: =51.74*2123970.23 -> 1.0989422e+08 | J78: =51.74*9888564.97 -> 5.1163435e+08 | K78: =I78-J78 -> -4.0174013e+08 | L78: =I78+Feb!L78 -> 3.508362e+08 | M78: =J78+Feb!M78 -> 3339674638 | N78: =L78-M78 -> -2988838440
B79: 54 | C79: ATRAM Total Return Dollar Bond Fund, Inc. (formerly, ATR KimEng Total Return Bond Fund, Inc.) | D79: 6.2235408e+08 | E79: 10481103 | F79: =D79-E79 -> 6.1187298e+08 | G79: 0 | H79: 202 | I79: 3015059 | J79: 1.4784065e+08 | K79: =I79-J79 -> -1.4482559e+08 | L79: =I79+Feb!L79 -> 9084095.9 | M79: =J79+Feb!M79 -> 1.5834694e+08 | N79: =L79-M79 -> -1.4926284e+08
B80: 55 | C80: First Metro Save and Learn Dollar Bond Fund, Inc. | D80: 7.2295221e+08 | E80: 3084677.7 | F80: =D80-E80 -> 7.1986753e+08 | G80: 0 | H80: 157 | I80: 261784.47 | J80: 0 | K80: =I80-J80 -> 261784.47 | L80: =I80+Feb!L80 -> 1051829.1 | M80: =J80+Feb!M80 -> 5566443.6 | N80: =L80-M80 -> -4514614.5
B81: 56 | C81: PAMI Global Bond Fund Phils., Inc. | D81: =51.74*1244354.91 -> 64382923 | E81: =51.74*232880.6 -> 12049242 | F81: =D81-E81 -> 52333681 | G81: 0 | H81: 27 | I81: 0 | J81: 0 | K81: =I81-J81 -> 0 | L81: =I81+Feb!L81 -> 0 | M81: =J81+Feb!M81 -> 361268.42 | N81: =L81-M81 -> -361268.42
B82: 57 | C82: Philam Dollar Bond Fund, Inc. | D82: =51.74*43632359.07 -> 2257538258 | E82: =51.74*-245161.62 -> -12684662 | F82: =D82-E82 -> 2270222921 | G82: 0 | H82: 2031 | I82: =51.74*2106979.35 -> 1.0901511e+08 | J82: =51.74*337930.1 -> 17484503 | K82: =I82-J82 -> 91530608 | L82: =I82+Feb!L82 -> 2.6793372e+08 | M82: =J82+Feb!M82 -> 25462111 | N82: =L82-M82 -> 2.4247161e+08
B83: 58 | C83: Philequity Dollar Income Fund, Inc. | D83: 2.2397123e+08 | E83: 1036531.7 | F83: =D83-E83 -> 2.229347e+08 | G83: 0 | H83: 129 | I83: 25870 | J83: 107827.71 | K83: =I83-J83 -> -81957.712 | L83: =I83+Feb!L83 -> 1019395 | M83: =J83+Feb!M83 -> 1567930.9 | N83: =L83-M83 -> -548535.9
B84: 59 | C84: Sun Life Prosperity Dollar Abundance Fund, Inc. | D84: =51.74*9579571.56 -> 4.9564703e+08 | E84: =51.74*74783.55 -> 3869300.9 | F84: =D84-E84 -> 4.9177773e+08 | G84: 0 | H84: 2514 | I84: =51.74*329741.23 -> 17060811 | J84: =51.74*489565.96 -> 25330143 | K84: =I84-J84 -> -8269331.5 | L84: =I84+Feb!L84 -> 18596105 | M84: =J84+Feb!M84 -> 31652060 | N84: =L84-M84 -> -13055956
A85: Sub total - US Currency | D85: =SUM(D78:D84) -> 19085480243 | E85: =SUM(E78:E84) -> 81442390 | F85: =SUM(F78:F84) -> 19004037854 | G85: =SUM(G78:G84) -> 0 | H85: =SUM(H78:H84) -> 14880 | I85: =SUM(I78:I84) -> 239272856 | J85: =SUM(J78:J84) -> 7.0239748e+08 | K85: =SUM(K78:K84) -> -4.6312462e+08 | ... N85: =SUM(N78:N84) -> -2914110050
B86: 60 | C86: ALFM Euro Bond Fund, Inc. | D86: =57.576272*16633892.01 -> 9.5771749e+08 | E86: =57.576272*64344.29 -> 3704704.3 | F86: =D86-E86 -> 9.5401279e+08 | G86: 0 | H86: 678 | I86: =57.576272*60252.43 -> 3469110.3 | J86: =57.576272*245682.77 -> 14145498 | K86: =I86-J86 -> -10676388 | L86: =I86+Feb!L86 -> 5205657.7 | M86: =J86+Feb!M86 -> 21849622 | N86: =L86-M86 -> -16643964
A87: Sub total - Euro Currency | D87: =SUM(D86) -> 9.5771749e+08 | E87: =SUM(E86) -> 3704704.3 | F87: =SUM(F86) -> 9.5401279e+08 | G87: =SUM(G86) -> 0 | H87: =SUM(H86) -> 678 | I87: =SUM(I86) -> 3469110.3 | J87: =SUM(J86) -> 14145498 | K87: =SUM(K86) -> -10676388 | ... N87: =SUM(N86) -> -16643964
A88: Sub total - bond funds | D88: =D76+D85+D87 -> 80090739076 | E88: =E76+E85+E87 -> 4.4558995e+08 | F88: =F76+F85+F87 -> 79645149128 | G88: =G76+G85+G87 -> 1243248100 | H88: =H76+H85+H87 -> 76444 | I88: =I76+I85+I87 -> 7.6351431e+08 | J88: =J76+J85+J87 -> 1641993452 | K88: =K76+K85+K87 -> -8.7847914e+08 | ... N88: =N76+N85+N87 -> -4168755436
A89: Money Market Funds
A90: Primarily invested in Peso Securities (shares)
B91: 61 | C91: ALFM Money Market Fund, Inc. | D91: 6.0151577e+10 | E91: 4.4272095e+08 | F91: =D91-E91 -> 59708855915 | G91: 0 | H91: 32751 | I91: 3.456624e+09 | J91: 2.971829e+09 | K91: =I91-J91 -> 4.8479497e+08 | L91: =I91+Feb!L91 -> 10638414869 | M91: =J91+Feb!M91 -> 9135270097 | N91: =L91-M91 -> 1503144772
B92: 62 | C92: First Metro Save and Learn Money Market Fund, Inc. | D92: 3.0824429e+09 | E92: 4901694.3 | F92: =D92-E92 -> 3077541180 | G92: 0 | H92: 549 | I92: 1.6857855e+08 | J92: 1.4901986e+08 | K92: =I92-J92 -> 19558689 | L92: =I92+Feb!L92 -> 8.4574815e+08 | M92: =J92+Feb!M92 -> 5.4638845e+08 | N92: =L92-M92 -> 2.9935969e+08
B93: 63 | C93: Sun Life Prosperity Peso Starter Fund, Inc. | D93: 1.2695163e+11 | E93: 8.2707409e+08 | F93: =D93-E93 -> 126124555685 | G93: 0 | H93: 59133 | I93: 1.9941509e+10 | J93: 1.9414079e+10 | K93: =I93-J93 -> 5.2743057e+08 | L93: =I93+Feb!L93 -> 51070896033 | M93: =J93+Feb!M93 -> 52520769582 | N93: =L93-M93 -> -1449873549
A94: Sub total - Peso Currency | D94: =SUM(D91:D93) -> 190185649505 | E94: =SUM(E91:E93) -> 1274696726 | F94: =SUM(F91:F93) -> 188910952779 | G94: =SUM(G91:G93) -> 0 | H94: =SUM(H91:H93) -> 92433 | I94: =SUM(I91:I93) -> 23566711650 | J94: =SUM(J91:J93) -> 22534927425 | K94: =SUM(K91:K93) -> 1031784226 | ... N94: =SUM(N91:N93) -> 3.5263092e+08
A95: Primarily invested in foreign currency securities (shares)
B96: 64 | C96: Sun Life Prosperity Dollar Starter Fund, Inc. | D96: =51.74*211324281.4 -> 10933918320 | E96: =51.74*1147767.22 -> 59385476 | F96: =D96-E96 -> 10874532844 | G96: 0 | H96: 2778 | I96: =51.74*55718684.9 -> 2882884757 | J96: =51.74*47126601.06 -> 2438330339 | K96: =I96-J96 -> 4.4455442e+08 | L96: =I96+Feb!L96 -> 7185425785 | M96: =J96+Feb!M96 -> 5938993786 | N96: =L96-M96 -> 1246431999
A97: Sub total - US Currency | D97: =SUM(D96) -> 10933918320 | E97: =SUM(E96) -> 59385476 | F97: =SUM(F96) -> 10874532844 | G97: =SUM(G96) -> 0 | H97: =SUM(H96) -> 2778 | I97: =SUM(I96) -> 2882884757 | J97: =SUM(J96) -> 2438330339 | K97: =SUM(K96) -> 4.4455442e+08 | ... N97: =SUM(N96) -> 1246431999
A98: Sub total - money market funds | D98: =D94+D97 -> 201119567824 | E98: =E94+E97 -> 1334082201 | F98: =F94+F97 -> 199785485623 | G98: =G94+G97 -> 0 | H98: =H94+H97 -> 95211 | I98: =I94+I97 -> 26449596407 | J98: =J94+J97 -> 24973257764 | K98: =K94+K97 -> 1476338643 | ... N98: =N94+N97 -> 1599062916
A99: Feeder Fund
A100: Primarily invested in Peso securities (units)
B101: 65 | C101: ALFM Global Multi-Asset Income Fund Inc. | D101: 8.8546235e+09 | E101: 15547264 | F101: =D101-E101 -> 8839076225 | G101: 0 | H101: 3425 | I101: 4.5872862e+08 | J101: 57842212 | K101: =I101-J101 -> 4.0088641e+08 | L101: =I101+Feb!L101 -> 1802953008 | M101: =J101+Feb!M101 -> 1.0948768e+08 | N101: =L101-M101 -> 1693465330
B102: 66 | C102: Sun Life Prosperity World Equity Index Feeder Fund, Inc. | D102: 3.79635e+09 | E102: 39516515 | F102: =D102-E102 -> 3756833514 | G102: 0 | H102: 5073 | I102: 1.8670816e+08 | J102: 1.8278552e+08 | K102: =I102-J102 -> 3922638.4 | L102: =I102+Feb!L102 -> 6.653406e+08 | M102: =J102+Feb!M102 -> 6.256235e+08 | N102: =L102-M102 -> 39717094
A103: Sub total - Peso Currency | D103: =D101+D102 -> 12650973518 | E103: =E101+E102 -> 55063779 | F103: =F101+F102 -> 12595909739 | G103: =G101+G102 -> 0 | H103: =H101+H102 -> 8498 | I103: =I101+I102 -> 6.4543678e+08 | J103: =J101+J102 -> 2.4062773e+08 | K103: =K101+K102 -> 4.0480905e+08 | ... N103: =N101+N102 -> 1733182424
A104: Primarily invested in foreign currency securities (units)
B105: 67 | C105: ALFM Global Multi-Asset Income Fund, Inc. | D105: =51.74*200211733.86 -> 10358955110 | E105: =51.74*393795.07 -> 20374957 | F105: =D105-E105 -> 10338580153 | G105: 0 | H105: 8384 | I105: =51.74*3415504.01 -> 1.7671818e+08 | J105: =51.74*2905876.82 -> 1.5035007e+08 | K105: =I105-J105 -> 26368111 | L105: =I105+Feb!L105 -> 6.7415716e+08 | M105: =J105+Feb!M105 -> 3.3567226e+08 | N105: =L105-M105 -> 3.384849e+08
A106: Sub total - US Currency | D106: =SUM(D105) -> 10358955110 | E106: =SUM(E105) -> 20374957 | F106: =SUM(F105) -> 10338580153 | G106: =SUM(G105) -> 0 | H106: =SUM(H105) -> 8384 | I106: =SUM(I105) -> 1.7671818e+08 | J106: =SUM(J105) -> 1.5035007e+08 | K106: =SUM(K105) -> 26368111 | ... N106: =SUM(N105) -> 3.384849e+08
...

Sheet Q1
A1: PHILIPPINE INVESTMENT FUNDS ASSOCIATION, INC.
A2: MUTUAL FUNDS STATISTICAL REPORT
A3: As of the First Quarter of 2022
A4: (Amounts in Peso)
A6: Fund Category | C6: Fund Name | D6: NET ASSETS | E6: TOTAL SALES | F6: TOTAL REDEMPTIONS | G6: NET SALES
A7: Stock Funds
A8: Primarily invested in Peso Securities (shares)
B9: 1 | C9: ALFM Growth Fund, Inc. | D9: =Mar!F9 -> 5396834531 | E9: =Jan!I9+Feb!I9+Mar!I9 -> 53631481 | F9: =Jan!J9+Feb!J9+Mar!J9 -> 1.5022647e+08 | G9: =E9-F9 -> -96594994
B10: 2 | C10: ATRAM Alpha Opportunity Fund, Inc. (formerly, ATRKE Alpha Opportunity Fund, Inc.) | D10: =Mar!F10 -> 837031397 | E10: =Jan!I10+Feb!I10+Mar!I10 -> 1.4536253e+08 | F10: =Jan!J10+Feb!J10+Mar!J10 -> 73969996 | G10: =E10-F10 -> 71392537
B11: 3 | C11: ATRAM Phil. Equity Opportunity Fund, Inc. (formerly, ATRKE Equity Opportunity Fund, Inc.) | D11: =Mar!F11 -> 1177196657 | E11: =Jan!I11+Feb!I11+Mar!I11 -> 46548608 | F11: =Jan!J11+Feb!J11+Mar!J11 -> 33399078 | G11: =E11-F11 -> 13149530
B12: 4 | C12: Climbs Share Capital Equity Investment Fund Corp. | D12: =Mar!F12 -> 3.5136654e+08 | E12: =Jan!I12+Feb!I12+Mar!I12 -> 5066693.8 | F12: =Jan!J12+Feb!J12+Mar!J12 -> 6287503.3 | G12: =E12-F12 -> -1220809.5
B13: 5 | C13: First Metro Consumer Fund on MSCI Phils. IMI, Inc. | D13: =Mar!F13 -> 5.3981126e+08 | E13: =Jan!I13+Feb!I13+Mar!I13 -> 17965487 | F13: =Jan!J13+Feb!J13+Mar!J13 -> 10094392 | G13: =E13-F13 -> 7871094.3
B14: 6 | C14: First Metro Save and Learn Equity Fund, Inc. | D14: =Mar!F14 -> 4439367518 | E14: =Jan!I14+Feb!I14+Mar!I14 -> 2.4383403e+08 | F14: =Jan!J14+Feb!J14+Mar!J14 -> 2.4801479e+08 | G14: =E14-F14 -> -4180760.9
B15: 7 | C15: First Metro Save and Learn Phil. Index Fund, Inc. (formerly, One Wealthy Nation Fund, Inc.) | D15: =Mar!F15 -> 94864099 | E15: =Jan!I15+Feb!I15+Mar!I15 -> 5892190.2 | F15: =Jan!J15+Feb!J15+Mar!J15 -> 4137960.4 | G15: =E15-F15 -> 1754229.8
B16: 8 | C16: MBG Equity Investment Fund, Inc. | D16: =Mar!F16 -> 1.4371782e+08 | E16: =Jan!I16+Feb!I16+Mar!I16 -> 1600000 | F16: =Jan!J16+Feb!J16+Mar!J16 -> 950000 | G16: =E16-F16 -> 650000
B17: 9 | C17: PAMI Equity Index Fund, Inc. | D17: =Mar!F17 -> 17620208196 | E17: =Jan!I17+Feb!I17+Mar!I17 -> 6.5255894e+08 | F17: =Jan!J17+Feb!J17+Mar!J17 -> 52359318 | G17: =E17-F17 -> 6.0019962e+08
B18: 10 | C18: Philam Strategic Growth Fund, Inc. | D18: =Mar!F18 -> 35833150750 | E18: =Jan!I18+Feb!I18+Mar!I18 -> 3.2008145e+08 | F18: =Jan!J18+Feb!J18+Mar!J18 -> 3.7410117e+08 | G18: =E18-F18 -> -54019718
B19: 11 | C19: Philequity Dividend Yield Fund, Inc. | D19: =Mar!F19 -> 2422915983 | E19: =Jan!I19+Feb!I19+Mar!I19 -> 64921504 | F19: =Jan!J19+Feb!J19+Mar!J19 -> 2.0637309e+08 | G19: =E19-F19 -> -1.4145159e+08
B20: 12 | C20: Philequity Fund, Inc. | D20: =Mar!F20 -> 10932000014 | E20: =Jan!I20+Feb!I20+Mar!I20 -> 100172938 | F20: =Jan!J20+Feb!J20+Mar!J20 -> 1.8497575e+08 | G20: =E20-F20 -> -84802809
... B27: 19 | C27: United Fund, Inc. | D27: =Mar!F27 -> 6.5311515e+08 | E27: =Jan!I27+Feb!I27+Mar!I27 -> 9734376.8 | F27: =Jan!J27+Feb!J27+Mar!J27 -> 3410430 | G27: =E27-F27 -> 6323946.8
A28: Primarily invested in Peso Securities (units)
B29: 20 | C29: Philequity Alpha One Fund, Inc. | D29: =Mar!F29 -> 3.8305447e+08 | E29: =Jan!I29+Feb!I29+Mar!I29 -> 50493779 | F29: =Jan!J29+Feb!J29+Mar!J29 -> 9374771.7 | G29: =E29-F29 -> 41119008
B30: 21 | C30: Philippine Stock Index Fund Corp. | D30: =Mar!F30 -> 2.6018159e+08 | E30: =Jan!I30+Feb!I30+Mar!I30 -> 2.9195767e+08 | F30: =Jan!J30+Feb!J30+Mar!J30 -> 27216162 | G30: =E30-F30 -> 2.6474151e+08
A31: Exchange Traded Fund
B32: 22 | C32: First Metro Phil. Equity Exchange Traded Fund, Inc. | D32: =Mar!F32 -> 2261786813 | E32: =Jan!I32+Feb!I32+Mar!I32 -> 37281386 | F32: =Jan!J32+Feb!J32+Mar!J32 -> 4442925 | G32: =E32-F32 -> 32838461
A33: Sub total - Peso Currency | D33: =SUM(D9:D32) -> 120970120741 | E33: =SUM(E9:E32) -> 3463843595 | F33: =SUM(F9:F32) -> 3044217476 | G33: =SUM(G9:G32) -> 4.1962612e+08
A34: Primarily invested in foreign currency securities (shares)
B35: 23 | C35: ATRAM AsiaPlus Equity Fund, Inc. (formerly, ATR KimEng AsiaPlus Recovery Fund, Inc.) | D35: =Mar!F35 -> 40602526 | E35: =Jan!I35+Feb!I35+Mar!I35 -> 332455.28 | F35: =Jan!J35+Feb!J35+Mar!J35 -> 5528236.9 | G35: =E35-F35 -> -5195781.6
B36: 24 | C36: Sun Life Prosperity World Voyager Fund, Inc. | D36: =Mar!F36 -> 2109860210 | E36: =Jan!I36+Feb!I36+Mar!I36 -> 2.1535991e+08 | F36: =Jan!J36+Feb!J36+Mar!J36 -> 1.7327678e+08 | G36: =E36-F36 -> 42083123
A37: Sub total - US Currency | D37: =SUM(D35:D36) -> 2150462736 | E37: =SUM(E35:E36) -> 2.1569236e+08 | F37: =SUM(F35:F36) -> 1.7880502e+08 | G37: =SUM(G35:G36) -> 36887341
A38: Sub total - stock funds | D38: =D33+D37 -> 123120583477 | E38: =E33+E37 -> 3679535958 | F38: =F33+F37 -> 3223022498 | G38: =G33+G37 -> 4.5651346e+08
A39: Balanced Funds
A40: Primarily invested in Peso Securities (shares)
B41: 25 | C41: ATRAM Dynamic Allocation Fund, Inc. (formerly, Optima Balanced Fund, Inc.) | D41: =Mar!F41 -> 1.2557945e+08 | E41: =Jan!I41+Feb!I41+Mar!I41 -> 5572098.2 | F41: =Jan!J41+Feb!J41+Mar!J41 -> 2501163.6 | G41: =E41-F41 -> 3070934.6
B42: 26 | C42: ATRAM Philippine Balanced Fund, Inc. (formerly, ATRKE Philippine Balanced Fund, Inc.) | D42: =Mar!F42 -> 6.653285e+08 | E42: =Jan!I42+Feb!I42+Mar!I42 -> 6042769.1 | F42: =Jan!J42+Feb!J42+Mar!J42 -> 25510352 | G42: =E42-F42 -> -19467583
B43: 27 | C43: First Metro Save and Learn Balanced Fund, Inc. | D43: =Mar!F43 -> 1198763973 | E43: =Jan!I43+Feb!I43+Mar!I43 -> 10267115 | F43: =Jan!J43+Feb!J43+Mar!J43 -> 123392105 | G43: =E43-F43 -> -1.1312499e+08
B44: 28 | C44: First Metro Save and Learn F.O.C.C.U.S. Dynamic Fund, Inc. | D44: =Mar!F44 -> 2.4557498e+08 | E44: =Jan!I44+Feb!I44+Mar!I44 -> 2.3010476e+08 | F44: =Jan!J44+Feb!J44+Mar!J44 -> 11381641 | G44: =E44-F44 -> 2.1872312e+08
B45: 29 | C45: NCM Mutual Fund of the Phils., Inc. | D45: =Mar!F45 -> 3.5687971e+08 | E45: =Jan!I45+Feb!I45+Mar!I45 -> 0 | F45: =Jan!J45+Feb!J45+Mar!J45 -> 1017100 | G45: =E45-F45 -> -1017100
B46: 30 | C46: PAMI Horizon Fund, Inc. | D46: =Mar!F46 -> 6.2332478e+08 | E46: =Jan!I46+Feb!I46+Mar!I46 -> 1471333.1 | F46: =Jan!J46+Feb!J46+Mar!J46 -> 22281227 | G46: =E46-F46 -> -20809894
B47: 31 | C47: Philam Fund, Inc. | D47: =Mar!F47 -> 11255547324 | E47: =Jan!I47+Feb!I47+Mar!I47 -> 98735442 | F47: =Jan!J47+Feb!J47+Mar!J47 -> 53922592 | G47: =E47-F47 -> 44812850
B48: 32 | C48: Solidaritas Fund, Inc. (formerly, Bahay Pari Solidaritas Fund, Inc.) | D48: =Mar!F48 -> 1.4746915e+08 | E48: =Jan!I48+Feb!I48+Mar!I48 -> 309976.43 | F48: =Jan!J48+Feb!J48+Mar!J48 -> 3215520 | G48: =E48-F48 -> -2905543.5
B49: 33 | C49: Sun Life Prosperity Balanced Fund, Inc. | D49: =Mar!F49 -> 8103405693 | E49: =Jan!I49+Feb!I49+Mar!I49 -> 53340563 | F49: =Jan!J49+Feb!J49+Mar!J49 -> 1.717693e+08 | G49: =E49-F49 -> -1.1842874e+08
B50: 34 | C50: Sun Life Prosperity Dynamic Fund, Inc. | D50: =Mar!F50 -> 1284312307 | E50: =Jan!I50+Feb!I50+Mar!I50 -> 0 | F50: =Jan!J50+Feb!J50+Mar!J50 -> 38631328 | G50: =E50-F50 -> -38631328
A51: Primarily invested in Peso Securities (units)
B52: 35 | C52: Sun Life Prosperity Achiever Fund 2028, Inc. | D52: =Mar!F52 -> 73333621 | E52: =Jan!I52+Feb!I52+Mar!I52 -> 2817367.9 | F52: =Jan!J52+Feb!J52+Mar!J52 -> 551839.17 | G52: =E52-F52 -> 2265528.7
B53: 36 | C53: Sun Life Prosperity Achiever Fund 2038, Inc. | D53: =Mar!F53 -> 58615865 | E53: =Jan!I53+Feb!I53+Mar!I53 -> 3491491.1 | F53: =Jan!J53+Feb!J53+Mar!J53 -> 214571.93 | G53: =E53-F53 -> 3276919.2
B54: 37 | C54: Sun Life Prosperity Achiever Fund 2048, Inc. | D54: =Mar!F54 -> 50443756 | E54: =Jan!I54+Feb!I54+Mar!I54 -> 1251685.4 | F54: =Jan!J54+Feb!J54+Mar!J54 -> 97041.44 | G54: =E54-F54 -> 1154643.9
A55: Sub total - Peso Currency | D55: =SUM(D41:D54) -> 24188579121 | E55: =SUM(E41:E54) -> 4.134046e+08 | F55: =SUM(F41:F54) -> 4.5448578e+08 | G55: =SUM(G41:G54) -> -41081178
A56: Primarily invested in foreign currency securities (shares)
B57: 38 | C57: Cocolife Dollar Fund Builder, Inc. | D57: =Mar!F57 -> 76252240 | E57: =Jan!I57+Feb!I57+Mar!I57 -> 5201915 | F57: =Jan!J57+Feb!J57+Mar!J57 -> 533148.94 | G57: =E57-F57 -> 4668766
B58: 39 | C58: PAMI Asia Balanced Fund, Inc. | D58: =Mar!F58 -> 3.5664186e+08 | E58: =Jan!I58+Feb!I58+Mar!I58 -> 542556.01 | F58: =Jan!J58+Feb!J58+Mar!J58 -> 8003793.1 | G58: =E58-F58 -> -7461237.1
B59: 40 | C59: Sun Life Prosperity Dollar Advantage Fund, Inc. | D59: =Mar!F59 -> 1769956750 | E59: =Jan!I59+Feb!I59+Mar!I59 -> 52907678 | F59: =Jan!J59+Feb!J59+Mar!J59 -> 96762536 | G59: =E59-F59 -> -43854858
B60: 41 | C60: Sun Life Prosperity Dollar Wellspring Fund, Inc. | D60: =Mar!F60 -> 3.4155584e+08 | E60: =Jan!I60+Feb!I60+Mar!I60 -> 1784429.1 | F60: =Jan!J60+Feb!J60+Mar!J60 -> 8538692.8 | G60: =E60-F60 -> -6754263.8
A61: Sub total - US Currency | D61: =SUM(D57:D60) -> 2544406689 | E61: =SUM(E57:E60) -> 60436578 | F61: =SUM(F57:F60) -> 1.1383817e+08 | G61: =SUM(G57:G60) -> -53401593
A62: Sub total - balanced funds | D62: =D55+D61 -> 26732985810 | E62: =E55+E61 -> 4.7384118e+08 | F62: =F55+F61 -> 568323953 | G62: =G55+G61 -> -94482770
A63: Bond Funds
A64: Primarily invested in Peso Securities (shares)
B65: 42 | C65: ALFM Peso Bond Fund, Inc. | D65: =Mar!F65 -> 42945848338 | E65: =Jan!I65+Feb!I65+Mar!I65 -> 902376876 | F65: =Jan!J65+Feb!J65+Mar!J65 -> 1995878119 | G65: =E65-F65 -> -1093501243
B66: 43 | C66: ATRAM Corporate Bond Fund, Inc. (formerly, Prudentialife Fixed Income Fund, Inc.) | D66: =Mar!F66 -> 3.010965e+08 | E66: =Jan!I66+Feb!I66+Mar!I66 -> 16396946 | F66: =Jan!J66+Feb!J66+Mar!J66 -> 8485551.5 | G66: =E66-F66 -> 7911394.3
B67: 44 | C67: Cocolife Fixed Income Fund, Inc. | D67: =Mar!F67 -> 1301945837 | E67: =Jan!I67+Feb!I67+Mar!I67 -> 1.1857687e+08 | F67: =Jan!J67+Feb!J67+Mar!J67 -> 40703225 | G67: =E67-F67 -> 77873646
B68: 45 | C68: Ekklesia Mutual Fund, Inc. | D68: =Mar!F68 -> 2.0075189e+08 | E68: =Jan!I68+Feb!I68+Mar!I68 -> 1424444.1 | F68: =Jan!J68+Feb!J68+Mar!J68 -> 1118217 | G68: =E68-F68 -> 306227.03
B69: 46 | C69: First Metro Save and Learn Fixed Income Fund, Inc. | D69: =Mar!F69 -> 1483927985 | E69: =Jan!I69+Feb!I69+Mar!I69 -> 19307745 | F69: =Jan!J69+Feb!J69+Mar!J69 -> 59237454 | G69: =E69-F69 -> -39929709
B70: 47 | C70: Philam Managed Income Fund, Inc. | D70: =Mar!F70 -> 9.3836516e+08 | E70: =Jan!I70+Feb!I70+Mar!I70 -> 6992581.9 | F70: =Jan!J70+Feb!J70+Mar!J70 -> 56746352 | G70: =E70-F70 -> -49753770
B71: 48 | C71: Philam Bond Fund, Inc. | D71: =Mar!F71 -> 6541630964 | E71: =Jan!I71+Feb!I71+Mar!I71 -> 1.1767346e+08 | F71: =Jan!J71+Feb!J71+Mar!J71 -> 2.0495593e+08 | G71: =E71-F71 -> -87282469
B72: 49 | C72: Philequity Peso Bond Fund, Inc. | D72: =Mar!F72 -> 3.1620481e+08 | E72: =Jan!I72+Feb!I72+Mar!I72 -> 14934374 | F72: =Jan!J72+Feb!J72+Mar!J72 -> 7932704.2 | G72: =E72-F72 -> 7001669.3
B73: 50 | C73: Soldivo Bond Fund, Inc. | D73: =Mar!F73 -> 9.0763909e+08 | E73: =Jan!I73+Feb!I73+Mar!I73 -> 6825314.2 | F73: =Jan!J73+Feb!J73+Mar!J73 -> 1947674.2 | G73: =E73-F73 -> 4877640
B74: 51 | C74: Sun Life Prosperity Bond Fund, Inc. | D74: =Mar!F74 -> 4595106282 | E74: =Jan!I74+Feb!I74+Mar!I74 -> 1.3179887e+08 | F74: =Jan!J74+Feb!J74+Mar!J74 -> 1.9148522e+08 | G74: =E74-F74 -> -59686356
B75: 52 | C75: Sun Life Prosperity GS Fund, Inc. | D75: =Mar!F75 -> 1.5458162e+08 | E75: =Jan!I75+Feb!I75+Mar!I75 -> 3075127.1 | F75: =Jan!J75+Feb!J75+Mar!J75 -> 8893579.8 | G75: =E75-F75 -> -5818452.7
A76: Sub total - Peso Currency | D76: =SUM(D65:D75) -> 59687098488 | E76: =SUM(E65:E75) -> 1339382608 | F76: =SUM(F65:F75) -> 2577384030 | G76: =SUM(G65:G75) -> -1238001422
A77: Primarily invested in foreign currency securities (shares)
B78: 53 | C78: ALFM Dollar Bond Fund, Inc. | D78: =Mar!F78 -> 14635028312 | E78: =Jan!I78+Feb!I78+Mar!I78 -> 3.508362e+08 | F78: =Jan!J78+Feb!J78+Mar!J78 -> 3339674638 | G78: =E78-F78 -> -2988838440
B79: 54 | C79: ATRAM Total Return Dollar Bond Fund, Inc. (formerly, ATR KimEng Total Return Bond Fund, Inc.) | D79: =Mar!F79 -> 6.1187298e+08 | E79: =Jan!I79+Feb!I79+Mar!I79 -> 9084095.9 | F79: =Jan!J79+Feb!J79+Mar!J79 -> 1.5834694e+08 | G79: =E79-F79 -> -1.4926284e+08
B80: 55 | C80: First Metro Save and Learn Dollar Bond Fund, Inc. | D80: =Mar!F80 -> 7.1986753e+08 | E80: =Jan!I80+Feb!I80+Mar!I80 -> 1051829.1 | F80: =Jan!J80+Feb!J80+Mar!J80 -> 5566443.6 | G80: =E80-F80 -> -4514614.5
B81: 56 | C81: PAMI Global Bond Fund Phils., Inc. | D81: =Mar!F81 -> 52333681 | E81: =Jan!I81+Feb!I81+Mar!I81 -> 0 | F81: =Jan!J81+Feb!J81+Mar!J81 -> 361268.42 | G81: =E81-F81 -> -361268.42
B82: 57 | C82: Philam Dollar Bond Fund, Inc. | D82: =Mar!F82 -> 2270222921 | E82: =Jan!I82+Feb!I82+Mar!I82 -> 2.6793372e+08 | F82: =Jan!J82+Feb!J82+Mar!J82 -> 25462111 | G82: =E82-F82 -> 2.4247161e+08
B83: 58 | C83: Philequity Dollar Income Fund, Inc. | D83: =Mar!F83 -> 2.229347e+08 | E83: =Jan!I83+Feb!I83+Mar!I83 -> 1019395 | F83: =Jan!J83+Feb!J83+Mar!J83 -> 1567930.9 | G83: =E83-F83 -> -548535.9
B84: 59 | C84: Sun Life Prosperity Dollar Abundance Fund, Inc. | D84: =Mar!F84 -> 4.9177773e+08 | E84: =Jan!I84+Feb!I84+Mar!I84 -> 18596105 | F84: =Jan!J84+Feb!J84+Mar!J84 -> 31652060 | G84: =E84-F84 -> -13055956
A85: Sub total - US Currency | D85: =SUM(D78:D84) -> 19004037854 | E85: =SUM(E78:E84) -> 6.4852134e+08 | F85: =SUM(F78:F84) -> 3562631391 | G85: =SUM(G78:G84) -> -2914110050
B86: 60 | C86: ALFM Euro Bond Fund, Inc. | D86: =Mar!F86 -> 9.5401279e+08 | E86: =Jan!I86+Feb!I86+Mar!I86 -> 5205657.7 | F86: =Jan!J86+Feb!J86+Mar!J86 -> 21849622 | G86: =E86-F86 -> -16643964
A87: Sub total - Euro Currency | D87: =SUM(D86) -> 9.5401279e+08 | E87: =SUM(E86) -> 5205657.7 | F87: =SUM(F86) -> 21849622 | G87: =SUM(G86) -> -16643964
A88: Sub total - bond funds | D88: =D76+D85+D87 -> 79645149128 | E88: =E76+E85+E87 -> 1993109606 | F88: =F76+F85+F87 -> 6161865043 | G88: =G76+G85+G87 -> -4168755436
A89: Money Market Funds
A90: Primarily invested in Peso Securities (shares)
B91: 61 | C91: ALFM Money Market Fund, Inc. | D91: =Mar!F91 -> 59708855915 | E91: =Jan!I91+Feb!I91+Mar!I91 -> 10638414869 | F91: =Jan!J91+Feb!J91+Mar!J91 -> 9135270097 | G91: =E91-F91 -> 1503144772
B92: 62 | C92: First Metro Save and Learn Money Market Fund, Inc. | D92: =Mar!F92 -> 3077541180 | E92: =Jan!I92+Feb!I92+Mar!I92 -> 8.4574815e+08 | F92: =Jan!J92+Feb!J92+Mar!J92 -> 5.4638845e+08 | G92: =E92-F92 -> 2.9935969e+08
B93: 63 | C93: Sun Life Prosperity Peso Starter Fund, Inc. | D93: =Mar!F93 -> 126124555685 | E93: =Jan!I93+Feb!I93+Mar!I93 -> 51070896033 | F93: =Jan!J93+Feb!J93+Mar!J93 -> 52520769582 | G93: =E93-F93 -> -1449873549
A94: Sub total - Peso Currency | D94: =SUM(D91:D93) -> 188910952779 | E94: =SUM(E91:E93) -> 62555059047 | F94: =SUM(F91:F93) -> 62202428130 | G94: =SUM(G91:G93) -> 3.5263092e+08
A95: Primarily invested in foreign currency securities (shares)
B96: 64 | C96: Sun Life Prosperity Dollar Starter Fund, Inc. | D96: =Mar!F96 -> 10874532844 | E96: =Jan!I96+Feb!I96+Mar!I96 -> 7185425785 | F96: =Jan!J96+Feb!J96+Mar!J96 -> 5938993786 | G96: =E96-F96 -> 1246431999
A97: Sub total - US Currency | D97: =SUM(D96) -> 10874532844 | E97: =SUM(E96) -> 7185425785 | F97: =SUM(F96) -> 5938993786 | G97: =SUM(G96) -> 1246431999
A98: Sub total - money market funds | D98: =D94+D97 -> 199785485623 | E98: =E94+E97 -> 69740484832 | F98: =F94+F97 -> 68141421916 | G98: =G94+G97 -> 1599062916
A99: Feeder Fund
A100: Primarily invested in Peso securities (units)
B101: 65 | C101: ALFM Global Multi-Asset Income Fund Inc. | D101: =Mar!F101 -> 8839076225 | E101: =Jan!I101+Feb!I101+Mar!I101 -> 1802953008 | F101: =Jan!J101+Feb!J101+Mar!J101 -> 1.0948768e+08 | G101: =E101-F101 -> 1693465330
B102: 66 | C102: Sun Life Prosperity World Equity Index Feeder Fund, Inc. | D102: =Mar!F102 -> 3756833514 | E102: =Jan!I102+Feb!I102+Mar!I102 -> 6.653406e+08 | F102: =Jan!J102+Feb!J102+Mar!J102 -> 6.256235e+08 | G102: =E102-F102 -> 39717094
A103: Sub total - Peso Currency | D103: =SUM(D101:D102) -> 12595909739 | E103: =SUM(E101:E102) -> 2468293603 | F103: =SUM(F101:F102) -> 7.3511118e+08 | G103: =SUM(G101:G102) -> 1733182424
A104: Primarily invested in foreign currency securities (units)
B105: 67 | C105: ALFM Global Multi-Asset Income Fund, Inc. | D105: =Mar!F105 -> 10338580153 | E105: =Jan!I105+Feb!I105+Mar!I105 -> 6.7415716e+08 | F105: =Jan!J105+Feb!J105+Mar!J105 -> 3.3567226e+08 | G105: =E105-F105 -> 3.384849e+08
A106: Sub total - US Currency | D106: =SUM(D105) -> 10338580153 | E106: =SUM(E105) -> 6.7415716e+08 | F106: =SUM(F105) -> 3.3567226e+08 | G106: =SUM(G105) -> 3.384849e+08
A107: Sub total - feeder fund | D107: =D103+D106 -> 22934489892 | E107: =E103+E106 -> 3142450765 | F107: =F103+F106 -> 1070783438 | G107: =G103+G106 -> 2071667327
...

Sheet Apr
A1: PHILIPPINE INVESTMENT FUNDS ASSOCIATION, INC.
A2: MUTUAL FUNDS STATISTICAL REPORT
A3: Month of April 2022
A4: (Amounts in Peso)
I5: F O R - T H E - M O N T H | L5: Y E A R - T O - D A T E
A6: Fund Category | C6: Fund Name | D6: ASSETS | E6: LIABILITIES | F6: NET ASSETS | G6: EQUITY INV. | H6: NO. OF A/C | I6: SALES | J6: REDEMPTIONS | K6: NET SALES | L6: TOTAL SALES | M6: TOTAL REDEMPTIONS | N6: TOTAL NET SALES
A7: Stock Funds
A8: Primarily invested in Peso Securities (shares)
B9: 1 | C9: ALFM Growth Fund, Inc. | D9: 5.0665058e+09 | E9: 48029314 | F9: =D9-E9 -> 5018476476 | G9: 4538049056 | H9: 7521 | I9: 12419129 | J9: 35604983 | K9: =I9-J9 -> -23185854 | L9: =I9+Mar!L9 -> 66050609 | M9: =J9+Mar!M9 -> 1.8583146e+08 | N9: =L9-M9 -> -1.1978085e+08
B10: 2 | C10: ATRAM Alpha Opportunity Fund, Inc. (formerly, ATRKE Alpha Opportunity Fund, Inc.) | D10: 7.9023011e+08 | E10: 3471619.1 | F10: =D10-E10 -> 7.8675849e+08 | G10: 7.1142735e+08 | H10: 4302 | I10: 18285444 | J10: 30400784 | K10: =I10-J10 -> -12115341 | L10: =I10+Mar!L10 -> 1.6364798e+08 | M10: =J10+Mar!M10 -> 104370780 | N10: =L10-M10 -> 59277196
B11: 3 | C11: ATRAM Phil. Equity Opportunity Fund, Inc. (formerly, ATRKE Equity Opportunity Fund, Inc.) | D11: 1.0514034e+09 | E11: 2896197.8 | F11: =D11-E11 -> 1048507204 | G11: 9.9227865e+08 | H11: 2790 | I11: 9371667.6 | J11: 62776067 | K11: =I11-J11 -> -53404400 | L11: =I11+Mar!L11 -> 55920276 | M11: =J11+Mar!M11 -> 96175146 | N11: =L11-M11 -> -40254870
B12: 4 | C12: Climbs Share Capital Equity Investment Fund Corp. | D12: 3.5728097e+08 | E12: 10503458 | F12: =D12-E12 -> 3.4677751e+08 | G12: 1.61718e+08 | H12: 1647 | I12: 5929188.2 | J12: 327919.81 | K12: =I12-J12 -> 5601268.4 | L12: =I12+Mar!L12 -> 10995882 | M12: =J12+Mar!M12 -> 6615423.2 | N12: =L12-M12 -> 4380458.9
B13: 5 | C13: First Metro Consumer Fund on MSCI Phils. IMI, Inc. | D13: 5.421278e+08 | E13: 13646273 | F13: =D13-E13 -> 5.2848153e+08 | G13: 285219813 | H13: 1509 | I13: 2466414.5 | J13: 657838.7 | K13: =I13-J13 -> 1808575.8 | L13: =I13+Mar!L13 -> 20431901 | M13: =J13+Mar!M13 -> 10752231 | N13: =L13-M13 -> 9679670.1
B14: 6 | C14: First Metro Save and Learn Equity Fund, Inc. | D14: 4.3204525e+09 | E14: 1.140337e+08 | F14: =D14-E14 -> 4206418803 | G14: 3.6076096e+09 | H14: 16521 | I14: 68128268 | J14: 38996181 | K14: =I14-J14 -> 29132086 | L14: =I14+Mar!L14 -> 3.119623e+08 | M14: =J14+Mar!M14 -> 2.8701097e+08 | N14: =L14-M14 -> 24951326
B15: 7 | C15: First Metro Save and Learn Phil. Index Fund, Inc. (formerly, One Wealthy Nation Fund, Inc.) | D15: 92403107 | E15: 2330194.4 | F15: =D15-E15 -> 90072912 | G15: 88213491 | H15: 533 | I15: 1995715.7 | J15: 475006.28 | K15: =I15-J15 -> 1520709.4 | L15: =I15+Mar!L15 -> 7887905.8 | M15: =J15+Mar!M15 -> 4612966.7 | N15: =L15-M15 -> 3274939.2
B16: 8 | C16: MBG Equity Investment Fund, Inc. | D16: 1.3908794e+08 | E16: 1368397.5 | F16: =D16-E16 -> 137719545 | G16: 1.2918488e+08 | H16: 51 | I16: 0 | J16: 0 | K16: =I16-J16 -> 0 | L16: =I16+Mar!L16 -> 1600000 | M16: =J16+Mar!M16 -> 950000 | N16: =L16-M16 -> 650000
B17: 9 | C17: PAMI Equity Index Fund, Inc. | D17: 1.6712619e+10 | E17: 1.053246e+08 | F17: =D17-E17 -> 16607294092 | G17: 1.6500662e+10 | H17: 12720 | I17: 1.6300182e+08 | J17: 6331981.9 | K17: =I17-J17 -> 1.5666984e+08 | L17: =I17+Mar!L17 -> 8.1556076e+08 | M17: =J17+Mar!M17 -> 58691300 | N17: =L17-M17 -> 7.5686946e+08
B18: 10 | C18: Philam Strategic Growth Fund, Inc. | D18: 3.3686368e+10 | E18: 2.1088593e+08 | F18: =D18-E18 -> 33475482285 | G18: 3.0849602e+10 | H18: 12574 | I18: 80647561 | J18: 55872262 | K18: =I18-J18 -> 24775299 | L18: =I18+Mar!L18 -> 4.0072901e+08 | M18: =J18+Mar!M18 -> 4.2997343e+08 | N18: =L18-M18 -> -29244419
B19: 11 | C19: Philequity Dividend Yield Fund, Inc. | D19: 2.3330496e+09 | E19: 36031659 | F19: =D19-E19 -> 2297017959 | G19: 2.0670896e+09 | H19: 5674 | I19: 9033937.2 | J19: 23684862 | K19: =I19-J19 -> -14650925 | L19: =I19+Mar!L19 -> 73955442 | M19: =J19+Mar!M19 -> 2.3005795e+08 | N19: =L19-M19 -> -1.5610251e+08
B20: 12 | C20: Philequity Fund, Inc. | D20: 1.0232577e+10 | E20: 36345336 | F20: =D20-E20 -> 10196231269 | G20: 9.5202036e+09 | H20: 37059 | I20: 16398998 | J20: 58978880 | K20: =I20-J20 -> -42579882 | L20: =I20+Mar!L20 -> 1.1657194e+08 | M20: =J20+Mar!M20 -> 2.4395463e+08 | N20: =L20-M20 -> -1.2738269e+08
... B27: 19 | C27: United Fund, Inc. | D27: 6.1629966e+08 | E27: 1827281 | F27: =D27-E27 -> 6.1447238e+08 | G27: 5.5029376e+08 | H27: 1307 | I27: 831472.44 | J27: 321301.97 | K27: =I27-J27 -> 510170.47 | L27: =I27+Mar!L27 -> 10565849 | M27: =J27+Mar!M27 -> 3731732 | N27: =L27-M27 -> 6834117.3
A28: Primarily invested in Peso Securities (units)
B29: 20 | C29: Philequity Alpha One Fund, Inc. | D29: 3.7018298e+08 | E29: 786131.53 | F29: =D29-E29 -> 3.6939684e+08 | G29: 3.1405409e+08 | H29: 1475 | I29: 6278896.7 | J29: 512339.96 | K29: =I29-J29 -> 5766556.7 | L29: =I29+Mar!L29 -> 56772676 | M29: =J29+Mar!M29 -> 9887111.7 | N29: =L29-M29 -> 46885564
B30: 21 | C30: Philippine Stock Index Fund Corp. | D30: 2.8775254e+08 | E30: 1290731.9 | F30: =D30-E30 -> 2.8646181e+08 | G30: 281220153 | H30: 269922 | I30: 51346167 | J30: 6338777.3 | K30: =I30-J30 -> 45007390 | L30: =I30+Mar!L30 -> 343303841 | M30: =J30+Mar!M30 -> 33554940 | N30: =L30-M30 -> 3.097489e+08
A31: Exchange Traded Fund
B32: 22 | C32: First Metro Phil. Equity Exchange Traded Fund, Inc. | D32: 2.139491e+09 | E32: 6323546.1 | F32: =D32-E32 -> 2133167442 | G32: 2.1094449e+09 | H32: 3162 | I32: 19322915 | J32: 0 | K32: =I32-J32 -> 19322915 | L32: =I32+Mar!L32 -> 56604301 | M32: =J32+Mar!M32 -> 4442925 | N32: =L32-M32 -> 52161376
A33: Sub total - Peso Currency | D33: =SUM(D9:D32) -> 114191281501 | E33: =SUM(E9:E32) -> 9.3974639e+08 | F33: =SUM(F9:F32) -> 113251535113 | G33: =SUM(G9:G32) -> 107371982344 | H33: =SUM(H9:H32) -> 556666 | I33: =SUM(I9:I32) -> 1012469250 | J33: =SUM(J9:J32) -> 8.5423638e+08 | K33: =SUM(K9:K32) -> 158232870 | ... N33: =SUM(N9:N32) -> 5.7785899e+08
A34: Primarily invested in foreign currency securities (shares)
B35: 23 | C35: ATRAM AsiaPlus Equity Fund, Inc. (formerly, ATR KimEng AsiaPlus Recovery Fund, Inc.) | D35: 39840171 | E35: 940783.16 | F35: =D35-E35 -> 38899388 | G35: 0 | H35: 56 | I35: 234923.86 | J35: 0 | K35: =I35-J35 -> 234923.86 | L35: =I35+Mar!L35 -> 567379.14 | M35: =J35+Mar!M35 -> 5528236.9 | N35: =L35-M35 -> -4960857.8
B36: 24 | C36: Sun Life Prosperity World Voyager Fund, Inc. | D36: =52.19*37783866.49 -> 1971939992 | E36: =52.19*319576.01 -> 16678672 | F36: =D36-E36 -> 1955261320 | G36: 0 | H36: 2776 | I36: =52.19*292433.69 -> 15262114 | J36: =52.19*329735.99 -> 17208921 | K36: =I36-J36 -> -1946807 | L36: =I36+Mar!L36 -> 2.3062202e+08 | M36: =J36+Mar!M36 -> 1.9048571e+08 | N36: =L36-M36 -> 40136316
A37: Sub total - US Currency | D37: =SUM(D35:D36) -> 2011780163 | E37: =SUM(E35:E36) -> 17619455 | F37: =SUM(F35:F36) -> 1994160708 | G37: =SUM(G35:G36) -> 0 | H37: =SUM(H35:H36) -> 2832 | I37: =SUM(I35:I36) -> 15497038 | J37: =SUM(J35:J36) -> 17208921 | K37: =SUM(K35:K36) -> -1711883.2 | ... N37: =SUM(N35:N36) -> 35175458
A38: Sub total - stock funds | D38: =D33+D37 -> 116203061664 | E38: =E33+E37 -> 9.5736584e+08 | F38: =F33+F37 -> 115245695821 | G38: =G33+G37 -> 107371982344 | H38: =H33+H37 -> 559498 | I38: =I33+I37 -> 1027966288 | J38: =J33+J37 -> 8.714453e+08 | K38: =K33+K37 -> 1.5652099e+08 | ... N38: =N33+N37 -> 6.1303445e+08
A39: Balanced Funds
A40: Primarily invested in Peso Securities (shares)
B41: 25 | C41: ATRAM Dynamic Allocation Fund, Inc. (formerly, Optima Balanced Fund, Inc.) | D41: 1.0349471e+08 | E41: 819797.76 | F41: =D41-E41 -> 1.0267491e+08 | G41: 24025361 | H41: 735 | I41: 2418966.7 | J41: 378590.13 | K41: =I41-J41 -> 2040376.5 | L41: =I41+Mar!L41 -> 7991064.9 | M41: =J41+Mar!M41 -> 2879753.7 | N41: =L41-M41 -> 5111311.2
B42: 26 | C42: ATRAM Philippine Balanced Fund, Inc. (formerly, ATRKE Philippine Balanced Fund, Inc.) | D42: 6.4902713e+08 | E42: 4804901.5 | F42: =D42-E42 -> 6.4422223e+08 | G42: 2.3800128e+08 | H42: 2488 | I42: 958800.7 | J42: 2889665.5 | K42: =I42-J42 -> -1930864.8 | L42: =I42+Mar!L42 -> 7001569.8 | M42: =J42+Mar!M42 -> 28400018 | N42: =L42-M42 -> -21398448
B43: 27 | C43: First Metro Save and Learn Balanced Fund, Inc. | D43: 1.1449038e+09 | E43: 23394482 | F43: =D43-E43 -> 1121509363 | G43: 5.6427714e+08 | H43: 4866 | I43: 2862232.2 | J43: 34256866 | K43: =I43-J43 -> -31394634 | L43: =I43+Mar!L43 -> 13129347 | M43: =J43+Mar!M43 -> 1.5764897e+08 | N43: =L43-M43 -> -1.4451962e+08
B44: 28 | C44: First Metro Save and Learn F.O.C.C.U.S. Dynamic Fund, Inc. | D44: 2.7813192e+08 | E44: 7874836 | F44: =D44-E44 -> 2.7025708e+08 | G44: 1.6114661e+08 | H44: 170 | I44: 35227627 | J44: 202855.27 | K44: =I44-J44 -> 35024772 | L44: =I44+Mar!L44 -> 265332390 | M44: =J44+Mar!M44 -> 11584496 | N44: =L44-M44 -> 2.5374789e+08
B45: 29 | C45: NCM Mutual Fund of the Phils., Inc. | D45: 3.4656339e+08 | E45: 1437574.4 | F45: =D45-E45 -> 3.4512581e+08 | G45: 1.619019e+08 | H45: 57 | I45: 0 | J45: 0 | K45: =I45-J45 -> 0 | L45: =I45+Mar!L45 -> 0 | M45: =J45+Mar!M45 -> 1017100 | N45: =L45-M45 -> -1017100
B46: 30 | C46: PAMI Horizon Fund, Inc. | D46: 6.0552407e+08 | E46: 12363241 | F46: =D46-E46 -> 5.9316083e+08 | G46: 3.2958554e+08 | H46: 10239 | I46: 231515.65 | J46: 3766449.7 | K46: =I46-J46 -> -3534934 | L46: =I46+Mar!L46 -> 1702848.7 | M46: =J46+Mar!M46 -> 26047677 | N46: =L46-M46 -> -24344828
B47: 31 | C47: Philam Fund, Inc. | D47: 1.0816397e+10 | E47: 54329834 | F47: =D47-E47 -> 10762066895 | G47: 5919119587 | H47: 8339 | I47: 14857567 | J47: 24879114 | K47: =I47-J47 -> -10021547 | L47: =I47+Mar!L47 -> 1.1359301e+08 | M47: =J47+Mar!M47 -> 78801706 | N47: =L47-M47 -> 34791303
B48: 32 | C48: Solidaritas Fund, Inc. (formerly, Bahay Pari Solidaritas Fund, Inc.) | D48: 1.4207604e+08 | E48: 587260.94 | F48: =D48-E48 -> 1.4148878e+08 | G48: 85318553 | H48: 199 | I48: 33899.76 | J48: 0 | K48: =I48-J48 -> 33899.76 | L48: =I48+Mar!L48 -> 343876.19 | M48: =J48+Mar!M48 -> 3215520 | N48: =L48-M48 -> -2871643.8
B49: 33 | C49: Sun Life Prosperity Balanced Fund, Inc. | D49: 7.7392852e+09 | E49: 59047979 | F49: =D49-E49 -> 7680237229 | G49: 4.6578436e+09 | H49: 53148 | I49: 12925749 | J49: 50643389 | K49: =I49-J49 -> -37717639 | L49: =I49+Mar!L49 -> 66266312 | M49: =J49+Mar!M49 -> 2.2241269e+08 | N49: =L49-M49 -> -1.5614638e+08
B50: 34 | C50: Sun Life Prosperity Dynamic Fund, Inc. | D50: 1.2728366e+09 | E50: 54282875 | F50: =D50-E50 -> 1218553719 | G50: 8.6079196e+08 | H50: 4998 | I50: 0 | J50: 2259356.1 | K50: =I50-J50 -> -2259356.1 | L50: =I50+Mar!L50 -> 0 | M50: =J50+Mar!M50 -> 40890684 | N50: =L50-M50 -> -40890684
A51: Primarily invested in Peso Securities (units)
B52: 35 | C52: Sun Life Prosperity Achiever Fund 2028, Inc. | D52: 72137528 | E52: 637265.63 | F52: =D52-E52 -> 71500262 | G52: 25615093 | H52: 924 | I52: 388416.21 | J52: 102677.31 | K52: =I52-J52 -> 285738.9 | L52: =I52+Mar!L52 -> 3205784.1 | M52: =J52+Mar!M52 -> 654516.48 | N52: =L52-M52 -> 2551267.6
B53: 36 | C53: Sun Life Prosperity Achiever Fund 2038, Inc. | D53: 56029563 | E53: 795978.97 | F53: =D53-E53 -> 55233584 | G53: 43414332 | H53: 345 | I53: 154956.48 | J53: 0 | K53: =I53-J53 -> 154956.48 | L53: =I53+Mar!L53 -> 3646447.6 | M53: =J53+Mar!M53 -> 214571.93 | N53: =L53-M53 -> 3431875.7
B54: 37 | C54: Sun Life Prosperity Achiever Fund 2048, Inc. | D54: 48236621 | E54: 842984.84 | F54: =D54-E54 -> 47393636 | G54: 40067970 | H54: 163 | I54: 114500 | J54: 0 | K54: =I54-J54 -> 114500 | L54: =I54+Mar!L54 -> 1366185.4 | M54: =J54+Mar!M54 -> 97041.44 | N54: =L54-M54 -> 1269143.9
A55: Sub total - Peso Currency | D55: =SUM(D41:D54) -> 23274643341 | E55: =SUM(E41:E54) -> 2.2121901e+08 | F55: =SUM(F41:F54) -> 23053424329 | G55: =SUM(G41:G54) -> 13111108968 | H55: =SUM(H41:H54) -> 86671 | I55: =SUM(I41:I54) -> 70174231 | J55: =SUM(J41:J54) -> 1.1937896e+08 | K55: =SUM(K41:K54) -> -49204731 | ... N55: =SUM(N41:N54) -> -90285909
A56: Primarily invested in foreign currency securities (shares)
B57: 38 | C57: Cocolife Dollar Fund Builder, Inc. | D57: =52.19*1355400.81 -> 70738368 | E57: =52.19*8232.35 -> 429646.35 | F57: =D57-E57 -> 70308722 | G57: 0 | H57: 55 | I57: 0 | J57: =52.19*68102.01 -> 3554243.9 | K57: =I57-J57 -> -3554243.9 | L57: =I57+Mar!L57 -> 5201915 | M57: =J57+Mar!M57 -> 4087392.8 | N57: =L57-M57 -> 1114522.1
B58: 39 | C58: PAMI Asia Balanced Fund, Inc. | D58: =52.19*6954036.77 -> 362931179 | E58: =52.19*392656.73 -> 20492755 | F58: =D58-E58 -> 3.4243842e+08 | G58: =52.19*3500288.1 -> 1.8268004e+08 | H58: 276 | I58: 0 | J58: =52.19*15284.28 -> 797686.57 | K58: =I58-J58 -> -797686.57 | L58: =I58+Mar!L58 -> 542556.01 | M58: =J58+Mar!M58 -> 8801479.7 | N58: =L58-M58 -> -8258923.7
B59: 40 | C59: Sun Life Prosperity Dollar Advantage Fund, Inc. | D59: =52.19*32024704.14 -> 1671369309 | E59: =52.19*484968.22 -> 25310491 | F59: =D59-E59 -> 1646058818 | G59: 0 | H59: 4112 | I59: =52.19*63503.09 -> 3314226.3 | J59: =52.19*540524.44 -> 28209971 | K59: =I59-J59 -> -24895744 | L59: =I59+Mar!L59 -> 56221904 | M59: =J59+Mar!M59 -> 1.2497251e+08 | N59: =L59-M59 -> -68750602
B60: 41 | C60: Sun Life Prosperity Dollar Wellspring Fund, Inc. | D60: =52.19*6306496.41 -> 3.2913605e+08 | E60: =52.19*84182.19 -> 4393468.5 | F60: =D60-E60 -> 3.2474258e+08 | G60: 0 | H60: 702 | I60: =52.19*10250 -> 534947.5 | J60: =52.19*45575.93 -> 2378607.8 | K60: =I60-J60 -> -1843660.3 | L60: =I60+Mar!L60 -> 2319376.6 | M60: =J60+Mar!M60 -> 10917301 | N60: =L60-M60 -> -8597924
A61: Sub total - US Currency | D61: =SUM(D57:D60) -> 2434174904 | E61: =SUM(E57:E60) -> 50626361 | F61: =SUM(F57:F60) -> 2383548543 | G61: =SUM(G57:G60) -> 1.8268004e+08 | H61: =SUM(H57:H60) -> 5145 | I61: =SUM(I57:I60) -> 3849173.8 | J61: =SUM(J57:J60) -> 34940509 | K61: =SUM(K57:K60) -> -31091335 | ... N61: =SUM(N57:N60) -> -84492928
A62: Sub total - balanced funds | D62: =D55+D61 -> 25708818245 | E62: =E55+E61 -> 2.7184537e+08 | F62: =F55+F61 -> 25436972872 | G62: =G55+G61 -> 13293789004 | H62: =H55+H61 -> 91816 | I62: =I55+I61 -> 74023405 | J62: =J55+J61 -> 1.5431947e+08 | K62: =K55+K61 -> -80296066 | ... N62: =N55+N61 -> -1.7477884e+08
A63: Bond Funds
A64: Primarily invested in Peso Securities (shares)
B65: 42 | C65: ALFM Peso Bond Fund, Inc. | D65: 4.2962768e+10 | E65: 2.7561308e+08 | F65: =D65-E65 -> 42687154702 | G65: 1210597140 | H65: 26329 | I65: 2.5396564e+08 | J65: 4.7506206e+08 | K65: =I65-J65 -> -2.2109641e+08 | L65: =I65+Mar!L65 -> 1156342519 | M65: =J65+Mar!M65 -> 2470940177 | N65: =L65-M65 -> -1314597658
B66: 43 | C66: ATRAM Corporate Bond Fund, Inc. (formerly, Prudentialife Fixed Income Fund, Inc.) | D66: 3.0516126e+08 | E66: 1114048.6 | F66: =D66-E66 -> 3.0404721e+08 | G66: 0 | H66: 1048 | I66: 3526721.4 | J66: 580032.99 | K66: =I66-J66 -> 2946688.4 | L66: =I66+Mar!L66 -> 19923667 | M66: =J66+Mar!M66 -> 9065584.5 | N66: =L66-M66 -> 10858083
B67: 44 | C67: Cocolife Fixed Income Fund, Inc. | D67: 1.2934243e+09 | E67: 19873684 | F67: =D67-E67 -> 1273550616 | G67: 0 | H67: 2076 | I67: 1813022.6 | J67: 31526356 | K67: =I67-J67 -> -29713334 | L67: =I67+Mar!L67 -> 1.2038989e+08 | M67: =J67+Mar!M67 -> 72229582 | N67: =L67-M67 -> 48160312
B68: 45 | C68: Ekklesia Mutual Fund, Inc. | D68: 2.0018617e+08 | E68: 293830.5 | F68: =D68-E68 -> 1.9989234e+08 | G68: 5050000 | H68: 145 | I68: 182392.25 | J68: 0 | K68: =I68-J68 -> 182392.25 | L68: =I68+Mar!L68 -> 1606836.3 | M68: =J68+Mar!M68 -> 1118217 | N68: =L68-M68 -> 488619.28
B69: 46 | C69: First Metro Save and Learn Fixed Income Fund, Inc. | D69: 1.4914251e+09 | E69: 9946572.4 | F69: =D69-E69 -> 1481478547 | G69: 0 | H69: 1900 | I69: 1058986.5 | J69: 2911951.2 | K69: =I69-J69 -> -1852964.6 | L69: =I69+Mar!L69 -> 20366731 | M69: =J69+Mar!M69 -> 62149405 | N69: =L69-M69 -> -41782674
B70: 47 | C70: Philam Managed Income Fund, Inc. | D70: 9.7484222e+08 | E70: 36483777 | F70: =D70-E70 -> 9.3835844e+08 | G70: 0 | H70: 539 | I70: 945937.83 | J70: 1990978.6 | K70: =I70-J70 -> -1045040.8 | L70: =I70+Mar!L70 -> 7938519.7 | M70: =J70+Mar!M70 -> 58737331 | N70: =L70-M70 -> -50798811
B71: 48 | C71: Philam Bond Fund, Inc. | D71: 6.5222116e+09 | E71: 34416252 | F71: =D71-E71 -> 6487795376 | G71: 0 | H71: 5150 | I71: 28152443 | J71: 36974034 | K71: =I71-J71 -> -8821590.9 | L71: =I71+Mar!L71 -> 1.4582591e+08 | M71: =J71+Mar!M71 -> 2.4192997e+08 | N71: =L71-M71 -> -96104059
B72: 49 | C72: Philequity Peso Bond Fund, Inc. | D72: 3.1690974e+08 | E72: 526352.74 | F72: =D72-E72 -> 3.1638339e+08 | G72: 16972202 | H72: 4201 | I72: 870648.26 | J72: 602311.44 | K72: =I72-J72 -> 268336.82 | L72: =I72+Mar!L72 -> 15805022 | M72: =J72+Mar!M72 -> 8535015.7 | N72: =L72-M72 -> 7270006.1
B73: 50 | C73: Soldivo Bond Fund, Inc. | D73: 9.7517643e+08 | E73: 3712053 | F73: =D73-E73 -> 9.7146437e+08 | G73: 0 | H73: 846 | I73: 65154501 | J73: 1453193.4 | K73: =I73-J73 -> 63701307 | L73: =I73+Mar!L73 -> 71979815 | M73: =J73+Mar!M73 -> 3400867.7 | N73: =L73-M73 -> 68578947
B74: 51 | C74: Sun Life Prosperity Bond Fund, Inc. | D74: 4.5428772e+09 | E74: 9142632.6 | F74: =D74-E74 -> 4533734566 | G74: 0 | H74: 16062 | I74: 38137468 | J74: 97896894 | K74: =I74-J74 -> -59759425 | L74: =I74+Mar!L74 -> 169936334 | M74: =J74+Mar!M74 -> 2.8938211e+08 | N74: =L74-M74 -> -1.1944578e+08
B75: 52 | C75: Sun Life Prosperity GS Fund, Inc. | D75: 1.5459512e+08 | E75: 284317.16 | F75: =D75-E75 -> 1.543108e+08 | G75: 0 | H75: 2557 | I75: 460454.35 | J75: 800670.82 | K75: =I75-J75 -> -340216.47 | L75: =I75+Mar!L75 -> 3535581.5 | M75: =J75+Mar!M75 -> 9694250.7 | N75: =L75-M75 -> -6158669.2
A76: Sub total - Peso Currency | D76: =SUM(D65:D75) -> 59739576958 | E76: =SUM(E65:E75) -> 3.914066e+08 | F76: =SUM(F65:F75) -> 59348170356 | G76: =SUM(G65:G75) -> 1232619342 | H76: =SUM(H65:H75) -> 60853 | I76: =SUM(I65:I75) -> 3.9426822e+08 | J76: =SUM(J65:J75) -> 6.4979848e+08 | K76: =SUM(K65:K75) -> -2.5553026e+08 | ... N76: =SUM(N65:N75) -> -1493531684
A77: Primarily invested in foreign currency securities (shares)
B78: 53 | C78: ALFM Dollar Bond Fund, Inc. | D78: =52.19*280423542.68 -> 14635304692 | E78: =52.19*1053846.44 -> 55000246 | F78: =D78-E78 -> 14580304447 | G78: 0 | H78: 9721 | I78: =52.19*1697195.86 -> 88576652 | J78: =52.19*3591553.81 -> 1.8744319e+08 | K78: =I78-J78 -> -98866541 | L78: =I78+Mar!L78 -> 4.3941285e+08 | M78: =J78+Mar!M78 -> 3527117832 | N78: =L78-M78 -> -3087704981
B79: 54 | C79: ATRAM Total Return Dollar Bond Fund, Inc. (formerly, ATR KimEng Total Return Bond Fund, Inc.) | D79: 5.9600819e+08 | E79: 2548020.8 | F79: =D79-E79 -> 5.9346017e+08 | G79: 0 | H79: 201 | I79: 2876794.4 | J79: 4199954.1 | K79: =I79-J79 -> -1323159.6 | L79: =I79+Mar!L79 -> 11960890 | M79: =J79+Mar!M79 -> 1.6254689e+08 | N79: =L79-M79 -> -1.50586e+08
B80: 55 | C80: First Metro Save and Learn Dollar Bond Fund, Inc. | D80: 7.1186692e+08 | E80: 3350385.1 | F80: =D80-E80 -> 7.0851654e+08 | G80: 0 | H80: 155 | I80: 0 | J80: 8999278.7 | K80: =I80-J80 -> -8999278.7 | L80: =I80+Mar!L80 -> 1051829.1 | M80: =J80+Mar!M80 -> 14565722 | N80: =L80-M80 -> -13513893
B81: 56 | C81: PAMI Global Bond Fund Phils., Inc. | D81: =52.19*1179601.24 -> 61563389 | E81: =52.19*212503.57 -> 11090561 | F81: =D81-E81 -> 50472827 | G81: 0 | H81: 27 | I81: 0 | J81: 0 | K81: =I81-J81 -> 0 | L81: =I81+Mar!L81 -> 0 | M81: =J81+Mar!M81 -> 361268.42 | N81: =L81-M81 -> -361268.42
B82: 57 | C82: Philam Dollar Bond Fund, Inc. | D82: =52.19*41480761.4 -> 2164880937 | E82: =52.19*-241452.01 -> -12601380 | F82: =D82-E82 -> 2177482318 | G82: 0 | H82: 2035 | I82: =52.19*1481.77 -> 77333.576 | J82: =52.19*474316.88 -> 24754598 | K82: =I82-J82 -> -24677264 | L82: =I82+Mar!L82 -> 2.6801105e+08 | M82: =J82+Mar!M82 -> 50216709 | N82: =L82-M82 -> 2.1779434e+08
B83: 58 | C83: Philequity Dollar Income Fund, Inc. | D83: 2.2523897e+08 | E83: 703645.87 | F83: =D83-E83 -> 224535323 | G83: 0 | H83: 129 | I83: 130475 | J83: 0 | K83: =I83-J83 -> 130475 | L83: =I83+Mar!L83 -> 1149870 | M83: =J83+Mar!M83 -> 1567930.9 | N83: =L83-M83 -> -418060.9
B84: 59 | C84: Sun Life Prosperity Dollar Abundance Fund, Inc. | D84: =52.19*9009888.88 -> 4.702261e+08 | E84: =52.19*98094.53 -> 5119553.5 | F84: =D84-E84 -> 4.6510655e+08 | G84: 0 | H84: 2514 | I84: =52.19*8947.12 -> 466950.19 | J84: =52.19*61681.05 -> 3219134 | K84: =I84-J84 -> -2752183.8 | L84: =I84+Mar!L84 -> 19063055 | M84: =J84+Mar!M84 -> 34871194 | N84: =L84-M84 -> -15808139
A85: Sub total - US Currency | D85: =SUM(D78:D84) -> 18865089207 | E85: =SUM(E78:E84) -> 65211032 | F85: =SUM(F78:F84) -> 18799878175 | G85: =SUM(G78:G84) -> 0 | H85: =SUM(H78:H84) -> 14782 | I85: =SUM(I78:I84) -> 92128205 | J85: =SUM(J78:J84) -> 2.2861616e+08 | K85: =SUM(K78:K84) -> -136487953 | ... N85: =SUM(N78:N84) -> -3050598003
B86: 60 | C86: ALFM Euro Bond Fund, Inc. | D86: =55.201363*16236923.6 -> 8.9630031e+08 | E86: =55.201363*39211.64 -> 2164536 | F86: =D86-E86 -> 8.9413578e+08 | G86: 0 | H86: 673 | I86: =55.201363*5803.86 -> 320380.98 | J86: =55.201363*232575.17 -> 12838466 | K86: =I86-J86 -> -12518085 | L86: =I86+Mar!L86 -> 5526038.7 | M86: =J86+Mar!M86 -> 34688088 | N86: =L86-M86 -> -29162049
A87: Sub total - Euro Currency | D87: =SUM(D86) -> 8.9630031e+08 | E87: =SUM(E86) -> 2164536 | F87: =SUM(F86) -> 8.9413578e+08 | G87: =SUM(G86) -> 0 | H87: =SUM(H86) -> 673 | I87: =SUM(I86) -> 320380.98 | J87: =SUM(J86) -> 12838466 | K87: =SUM(K86) -> -12518085 | ... N87: =SUM(N86) -> -29162049
A88: Sub total - bond funds | D88: =D76+D85+D87 -> 79500966479 | E88: =E76+E85+E87 -> 458782170 | F88: =F76+F85+F87 -> 79042184309 | G88: =G76+G85+G87 -> 1232619342 | H88: =H76+H85+H87 -> 76308 | I88: =I76+I85+I87 -> 4.867168e+08 | J88: =J76+J85+J87 -> 8.912531e+08 | K88: =K76+K85+K87 -> -404536300 | ... N88: =N76+N85+N87 -> -4573291736
A89: Money Market Funds
A90: Primarily invested in Peso Securities (shares)
B91: 61 | C91: ALFM Money Market Fund, Inc. | D91: 6.0529609e+10 | E91: 39341518 | F91: =D91-E91 -> 60490267773 | G91: 0 | H91: 32990 | I91: 2.7300133e+09 | J91: 2.744422e+09 | K91: =I91-J91 -> -14408686 | L91: =I91+Mar!L91 -> 13368428195 | M91: =J91+Mar!M91 -> 11879692109 | N91: =L91-M91 -> 1488736086
B92: 62 | C92: First Metro Save and Learn Money Market Fund, Inc. | D92: 2.8937322e+09 | E92: 12136772 | F92: =D92-E92 -> 2881595408 | G92: 0 | H92: 560 | I92: 1.0082635e+08 | J92: 2.9965212e+08 | K92: =I92-J92 -> -1.9882577e+08 | L92: =I92+Mar!L92 -> 9.4657449e+08 | M92: =J92+Mar!M92 -> 8.4604057e+08 | N92: =L92-M92 -> 1.0053392e+08
B93: 63 | C93: Sun Life Prosperity Peso Starter Fund, Inc. | D93: 1.3100677e+11 | E93: 9.3303338e+08 | F93: =D93-E93 -> 130073734082 | G93: 0 | H93: 59586 | I93: 2.0642481e+10 | J93: 1.6860254e+10 | K93: =I93-J93 -> 3782227054 | L93: =I93+Mar!L93 -> 71713376920 | M93: =J93+Mar!M93 -> 69381023415 | N93: =L93-M93 -> 2332353505
A94: Sub total - Peso Currency | D94: =SUM(D91:D93) -> 194430108929 | E94: =SUM(E91:E93) -> 9.8451167e+08 | F94: =SUM(F91:F93) -> 193445597263 | G94: =SUM(G91:G93) -> 0 | H94: =SUM(H91:H93) -> 93136 | I94: =SUM(I91:I93) -> 23473320561 | J94: =SUM(J91:J93) -> 19904327965 | K94: =SUM(K91:K93) -> 3568992596 | ... N94: =SUM(N91:N93) -> 3921623512
A95: Primarily invested in foreign currency securities (shares)
B96: 64 | C96: Sun Life Prosperity Dollar Starter Fund, Inc. | D96: =52.19*212556948.97 -> 11093347167 | E96: =52.19*1409327.34 -> 73552794 | F96: =D96-E96 -> 11019794373 | G96: 0 | H96: 2851 | I96: =52.19*40847033.89 -> 2131806699 | J96: =52.19*39996801.99 -> 2087433096 | K96: =I96-J96 -> 44373603 | L96: =I96+Mar!L96 -> 9317232484 | M96: =J96+Mar!M96 -> 8026426882 | N96: =L96-M96 -> 1290805602
A97: Sub total - US Currency | D97: =SUM(D96) -> 11093347167 | E97: =SUM(E96) -> 73552794 | F97: =SUM(F96) -> 11019794373 | G97: =SUM(G96) -> 0 | H97: =SUM(H96) -> 2851 | I97: =SUM(I96) -> 2131806699 | J97: =SUM(J96) -> 2087433096 | K97: =SUM(K96) -> 44373603 | ... N97: =SUM(N96) -> 1290805602
A98: Sub total - money market funds | D98: =D94+D97 -> 205523456095 | E98: =E94+E97 -> 1058064459 | F98: =F94+F97 -> 204465391636 | G98: =G94+G97 -> 0 | H98: =H94+H97 -> 95987 | I98: =I94+I97 -> 25605127260 | J98: =J94+J97 -> 21991761061 | K98: =K94+K97 -> 3613366198 | ... N98: =N94+N97 -> 5212429114
A99: Feeder Fund
A100: Primarily invested in Peso securities (units)
B101: 65 | C101: ALFM Global Multi-Asset Income Fund Inc. | D101: 8.9900398e+09 | E101: 92787118 | F101: =D101-E101 -> 8897252667 | G101: 0 | H101: 3554 | I101: 3.5245636e+08 | J101: 25234535 | K101: =I101-J101 -> 3.2722183e+08 | L101: =I101+Mar!L101 -> 2155409372 | M101: =J101+Mar!M101 -> 1.3472221e+08 | N101: =L101-M101 -> 2020687159
B102: 66 | C102: Sun Life Prosperity World Equity Index Feeder Fund, Inc. | D102: 3.5308476e+09 | E102: 15569822 | F102: =D102-E102 -> 3515277799 | G102: 0 | H102: 5190 | I102: 1.0357553e+08 | J102: 52195485 | K102: =I102-J102 -> 51380045 | L102: =I102+Mar!L102 -> 7.6891613e+08 | M102: =J102+Mar!M102 -> 6.7781899e+08 | N102: =L102-M102 -> 91097140
A103: Sub total - Peso Currency | D103: =D101+D102 -> 12520887406 | E103: =E101+E102 -> 1.0835694e+08 | F103: =F101+F102 -> 12412530466 | G103: =G101+G102 -> 0 | H103: =H101+H102 -> 8744 | I103: =I101+I102 -> 4.5603189e+08 | J103: =J101+J102 -> 77430020 | K103: =K101+K102 -> 3.7860187e+08 | ... N103: =N101+N102 -> 2111784299
A104: Primarily invested in foreign currency securities (units)
B105: 67 | C105: ALFM Global Multi-Asset Income Fund, Inc. | D105: =52.19*195203758.3 -> 10187684146 | E105: =52.19*414386.37 -> 21626825 | F105: =D105-E105 -> 10166057321 | G105: 0 | H105: 8474 | I105: =52.19*4015378 -> 2.0956258e+08 | J105: =52.19*657223.74 -> 34300507 | K105: =I105-J105 -> 1.7526207e+08 | L105: =I105+Mar!L105 -> 8.8371974e+08 | M105: =J105+Mar!M105 -> 3.6997277e+08 | N105: =L105-M105 -> 5.1374697e+08
A106: Sub total - US Currency | D106: =SUM(D105) -> 10187684146 | E106: =SUM(E105) -> 21626825 | F106: =SUM(F105) -> 10166057321 | G106: =SUM(G105) -> 0 | H106: =SUM(H105) -> 8474 | I106: =SUM(I105) -> 2.0956258e+08 | J106: =SUM(J105) -> 34300507 | K106: =SUM(K105) -> 1.7526207e+08 | ... N106: =SUM(N105) -> 5.1374697e+08
...

Sheet May
A1: PHILIPPINE INVESTMENT FUNDS ASSOCIATION, INC.
A2: MUTUAL FUNDS STATISTICAL REPORT
A3: Month of May 2022
A4: (Amounts in Peso)
I5: F O R - T H E - M O N T H | L5: Y E A R - T O - D A T E
A6: Fund Category | C6: Fund Name | D6: ASSETS | E6: LIABILITIES | F6: NET ASSETS | G6: EQUITY INV. | H6: NO. OF A/C | I6: SALES | J6: REDEMPTIONS | K6: NET SALES | L6: TOTAL SALES | M6: TOTAL REDEMPTIONS | N6: TOTAL NET SALES
A7: Stock Funds
A8: Primarily invested in Peso Securities (shares)
B9: 1 | C9: ALFM Growth Fund, Inc. | D9: 5.0663093e+09 | E9: 20667545 | F9: =D9-E9 -> 5045641707 | G9: 4569765363 | H9: 7467 | I9: 21536666 | J9: 45324980 | K9: =I9-J9 -> -23788314 | L9: =I9+Apr!L9 -> 87587275 | M9: =J9+Apr!M9 -> 2.3115644e+08 | N9: =L9-M9 -> -1.4356916e+08
B10: 2 | C10: ATRAM Alpha Opportunity Fund, Inc. (formerly, ATRKE Alpha Opportunity Fund, Inc.) | D10: 7.6089647e+08 | E10: 1923291.4 | F10: =D10-E10 -> 7.5897318e+08 | G10: 6.7521392e+08 | H10: 4295 | I10: 7952178.5 | J10: 11459317 | K10: =I10-J10 -> -3507138.1 | L10: =I10+Apr!L10 -> 1.7160015e+08 | M10: =J10+Apr!M10 -> 1.158301e+08 | N10: =L10-M10 -> 55770058
B11: 3 | C11: ATRAM Phil. Equity Opportunity Fund, Inc. (formerly, ATRKE Equity Opportunity Fund, Inc.) | D11: 1.0575983e+09 | E11: 2841553.6 | F11: =D11-E11 -> 1054756745 | G11: 9.9142116e+08 | H11: 2776 | I11: 6538160.7 | J11: 5612004 | K11: =I11-J11 -> 926156.64 | L11: =I11+Apr!L11 -> 62458437 | M11: =J11+Apr!M11 -> 1.0178715e+08 | N11: =L11-M11 -> -39328713
B12: 4 | C12: Climbs Share Capital Equity Investment Fund Corp. | D12: 3.612235e+08 | E12: 11549675 | F12: =D12-E12 -> 3.4967382e+08 | G12: 1.9944071e+08 | H12: 1668 | I12: 6045012.9 | J12: 1488209 | K12: =I12-J12 -> 4556803.9 | L12: =I12+Apr!L12 -> 17040895 | M12: =J12+Apr!M12 -> 8103632.2 | N12: =L12-M12 -> 8937262.8
B13: 5 | C13: First Metro Consumer Fund on MSCI Phils. IMI, Inc. | D13: 5.3358044e+08 | E13: 10444506 | F13: =D13-E13 -> 5.2313593e+08 | G13: 2.8813241e+08 | H13: 1501 | I13: 945891.77 | J13: 875055.7 | K13: =I13-J13 -> 70836.07 | L13: =I13+Apr!L13 -> 21377793 | M13: =J13+Apr!M13 -> 11627287 | N13: =L13-M13 -> 9750506.2
B14: 6 | C14: First Metro Save and Learn Equity Fund, Inc. | D14: 4.4352128e+09 | E14: 1.0911912e+08 | F14: =D14-E14 -> 4326093705 | G14: 3.7587172e+09 | H14: 16518 | I14: 1.2071828e+08 | J14: 14902248 | K14: =I14-J14 -> 1.0581603e+08 | L14: =I14+Apr!L14 -> 4.3268058e+08 | M14: =J14+Apr!M14 -> 3.0191322e+08 | N14: =L14-M14 -> 130767357
B15: 7 | C15: First Metro Save and Learn Phil. Index Fund, Inc. (formerly, One Wealthy Nation Fund, Inc.) | D15: 92739581 | E15: 681524.52 | F15: =D15-E15 -> 92058056 | G15: 89717218 | H15: 537 | I15: 3040101.7 | J15: 1690864.3 | K15: =I15-J15 -> 1349237.5 | L15: =I15+Apr!L15 -> 10928008 | M15: =J15+Apr!M15 -> 6303830.9 | N15: =L15-M15 -> 4624176.6
B16: 8 | C16: MBG Equity Investment Fund, Inc. | D16: 1.2960905e+08 | E16: 1031234 | F16: =D16-E16 -> 1.2857782e+08 | G16: 1.1991046e+08 | H16: 51 | I16: 0 | J16: 0 | K16: =I16-J16 -> 0 | L16: =I16+Apr!L16 -> 1600000 | M16: =J16+Apr!M16 -> 950000 | N16: =L16-M16 -> 650000
B17: 9 | C17: PAMI Equity Index Fund, Inc. | D17: 1.7147595e+10 | E17: 1.967699e+08 | F17: =D17-E17 -> 16950824816 | G17: 1.6848975e+10 | H17: 12428 | I17: 1.8792179e+08 | J17: 16741785 | K17: =I17-J17 -> 1.7118001e+08 | L17: =I17+Apr!L17 -> 1003482556 | M17: =J17+Apr!M17 -> 75433085 | N17: =L17-M17 -> 9.2804947e+08
B18: 10 | C18: Philam Strategic Growth Fund, Inc. | D18: 3.4071644e+10 | E18: 2.2642636e+08 | F18: =D18-E18 -> 33845217621 | G18: 3.0120423e+10 | H18: 12424 | I18: 1.0363244e+08 | J18: 36657818 | K18: =I18-J18 -> 66974618 | L18: =I18+Apr!L18 -> 5.0436145e+08 | M18: =J18+Apr!M18 -> 4.6663125e+08 | N18: =L18-M18 -> 37730199
B19: 11 | C19: Philequity Dividend Yield Fund, Inc. | D19: 2.3126048e+09 | E19: 16508957 | F19: =D19-E19 -> 2296095795 | G19: 2.0179858e+09 | H19: 5693 | I19: 17351207 | J19: 27041524 | K19: =I19-J19 -> -9690317.4 | L19: =I19+Apr!L19 -> 91306649 | M19: =J19+Apr!M19 -> 2.5709948e+08 | N19: =L19-M19 -> -1.6579283e+08
B20: 12 | C20: Philequity Fund, Inc. | D20: 1.0288366e+10 | E20: 65290340 | F20: =D20-E20 -> 10223075867 | G20: 9.6511799e+09 | H20: 36942 | I20: 47705834 | J20: 56509683 | K20: =I20-J20 -> -8803848.1 | L20: =I20+Apr!L20 -> 1.6427777e+08 | M20: =J20+Apr!M20 -> 3.0046431e+08 | N20: =L20-M20 -> -1.3618654e+08
... B27: 19 | C27: United Fund, Inc. | D27: 6.1555765e+08 | E27: 2711557.9 | F27: =D27-E27 -> 6.1284609e+08 | G27: 5.5541166e+08 | H27: 1306 | I27: 666991.43 | J27: 3234532.1 | K27: =I27-J27 -> -2567540.6 | L27: =I27+Apr!L27 -> 11232841 | M27: =J27+Apr!M27 -> 6966264.1 | N27: =L27-M27 -> 4266576.6
A28: Primarily invested in Peso Securities (units)
B29: 20 | C29: Philequity Alpha One Fund, Inc. | D29: 3.7799177e+08 | E29: 6640875.4 | F29: =D29-E29 -> 3.7135089e+08 | G29: 3.1764789e+08 | H29: 1479 | I29: 11023362 | J29: 3495515 | K29: =I29-J29 -> 7527846.5 | L29: =I29+Apr!L29 -> 67796038 | M29: =J29+Apr!M29 -> 13382627 | N29: =L29-M29 -> 54413411
B30: 21 | C30: Philippine Stock Index Fund Corp. | D30: 3.3700795e+08 | E30: 16779625 | F30: =D30-E30 -> 320228328 | G30: 3.1822412e+08 | H30: 275893 | I30: 65114204 | J30: 34277166 | K30: =I30-J30 -> 30837039 | L30: =I30+Apr!L30 -> 4.0841805e+08 | M30: =J30+Apr!M30 -> 67832105 | N30: =L30-M30 -> 3.4058594e+08
A31: Exchange Traded Fund
B32: 22 | C32: First Metro Phil. Equity Exchange Traded Fund, Inc. | D32: 2.1685273e+09 | E32: 4962134.9 | F32: =D32-E32 -> 2163565138 | G32: 2.1597662e+09 | H32: 3142 | I32: 19098124 | J32: 9240460 | K32: =I32-J32 -> 9857664 | L32: =I32+Apr!L32 -> 75702425 | M32: =J32+Apr!M32 -> 13683385 | N32: =L32-M32 -> 62019040
A33: Sub total - Peso Currency | D33: =SUM(D9:D32) -> 115879772249 | E33: =SUM(E9:E32) -> 9.0144768e+08 | F33: =SUM(F9:F32) -> 114978324568 | G33: =SUM(G9:G32) -> 108087231027 | H33: =SUM(H9:H32) -> 556529 | I33: =SUM(I9:I32) -> 1416307827 | J33: =SUM(J9:J32) -> 5.6954732e+08 | K33: =SUM(K9:K32) -> 8.4676051e+08 | ... N33: =SUM(N9:N32) -> 1424619500
A34: Primarily invested in foreign currency securities (shares)
B35: 23 | C35: ATRAM AsiaPlus Equity Fund, Inc. (formerly, ATR KimEng AsiaPlus Recovery Fund, Inc.) | D35: 40439759 | E35: 943443.46 | F35: =D35-E35 -> 39496316 | G35: 0 | H35: 57 | I35: 292627.85 | J35: 4725.87 | K35: =I35-J35 -> 287901.98 | L35: =I35+Apr!L35 -> 860006.99 | M35: =J35+Apr!M35 -> 5532962.8 | N35: =L35-M35 -> -4672955.8
B36: 24 | C36: Sun Life Prosperity World Voyager Fund, Inc. | D36: =52.37*37237603.84 -> 1950133313 | E36: =52.37*251879.39 -> 13190924 | F36: =D36-E36 -> 1936942389 | G36: 0 | H36: 2797 | I36: =52.37*270477.02 -> 14164882 | J36: =52.37*439889.89 -> 23037034 | K36: =I36-J36 -> -8872152 | L36: =I36+Apr!L36 -> 2.447869e+08 | M36: =J36+Apr!M36 -> 2.1352274e+08 | N36: =L36-M36 -> 31264164
A37: Sub total - US Currency | D37: =SUM(D35:D36) -> 1990573073 | E37: =SUM(E35:E36) -> 14134367 | F37: =SUM(F35:F36) -> 1976438705 | G37: =SUM(G35:G36) -> 0 | H37: =SUM(H35:H36) -> 2854 | I37: =SUM(I35:I36) -> 14457509 | J37: =SUM(J35:J36) -> 23041759 | K37: =SUM(K35:K36) -> -8584250 | ... N37: =SUM(N35:N36) -> 26591208
A38: Sub total - stock funds | D38: =D33+D37 -> 117870345322 | E38: =E33+E37 -> 9.1558205e+08 | F38: =F33+F37 -> 116954763273 | G38: =G33+G37 -> 108087231027 | H38: =H33+H37 -> 559383 | I38: =I33+I37 -> 1430765336 | J38: =J33+J37 -> 592589075 | K38: =K33+K37 -> 8.3817626e+08 | ... N38: =N33+N37 -> 1451210708
A39: Balanced Funds
A40: Primarily invested in Peso Securities (shares)
B41: 25 | C41: ATRAM Dynamic Allocation Fund, Inc. (formerly, Optima Balanced Fund, Inc.) | D41: 1.2351406e+08 | E41: 377187.72 | F41: =D41-E41 -> 1.2313687e+08 | G41: 26599529 | H41: 736 | I41: 645791.3 | J41: 259818.16 | K41: =I41-J41 -> 385973.14 | L41: =I41+Apr!L41 -> 8636856.2 | M41: =J41+Apr!M41 -> 3139571.9 | N41: =L41-M41 -> 5497284.3
B42: 26 | C42: ATRAM Philippine Balanced Fund, Inc. (formerly, ATRKE Philippine Balanced Fund, Inc.) | D42: 6.3766838e+08 | E42: 1923693.4 | F42: =D42-E42 -> 6.3574468e+08 | G42: 2.3499689e+08 | H42: 2479 | I42: 759091.28 | J42: 5529011.7 | K42: =I42-J42 -> -4769920.4 | L42: =I42+Apr!L42 -> 7760661.1 | M42: =J42+Apr!M42 -> 33929029 | N42: =L42-M42 -> -26168368
B43: 27 | C43: First Metro Save and Learn Balanced Fund, Inc. | D43: 1.1369879e+09 | E43: 16832001 | F43: =D43-E43 -> 1120155925 | G43: 5.7741168e+08 | H43: 4847 | I43: 1686071.3 | J43: 4333048.1 | K43: =I43-J43 -> -2646976.7 | L43: =I43+Apr!L43 -> 14815419 | M43: =J43+Apr!M43 -> 1.6198202e+08 | N43: =L43-M43 -> -1.471666e+08
B44: 28 | C44: First Metro Save and Learn F.O.C.C.U.S. Dynamic Fund, Inc. | D44: 2.8401796e+08 | E44: 4440600.1 | F44: =D44-E44 -> 2.7957736e+08 | G44: 1.6743062e+08 | H44: 186 | I44: 9359995.1 | J44: 61205.31 | K44: =I44-J44 -> 9298789.8 | L44: =I44+Apr!L44 -> 2.7469239e+08 | M44: =J44+Apr!M44 -> 11645701 | N44: =L44-M44 -> 263046684
B45: 29 | C45: NCM Mutual Fund of the Phils., Inc. | D45: 3.4718152e+08 | E45: 1751900.6 | F45: =D45-E45 -> 3.4542962e+08 | G45: 1.6310316e+08 | H45: 57 | I45: 0 | J45: 0 | K45: =I45-J45 -> 0 | L45: =I45+Apr!L45 -> 0 | M45: =J45+Apr!M45 -> 1017100 | N45: =L45-M45 -> -1017100
B46: 30 | C46: PAMI Horizon Fund, Inc. | D46: 6.0467418e+08 | E46: 12584014 | F46: =D46-E46 -> 5.9209016e+08 | G46: 3.1221278e+08 | H46: 10005 | I46: 2236451.9 | J46: 3894280.6 | K46: =I46-J46 -> -1657828.7 | L46: =I46+Apr!L46 -> 3939300.6 | M46: =J46+Apr!M46 -> 29941958 | N46: =L46-M46 -> -26002657
B47: 31 | C47: Philam Fund, Inc. | D47: 1.0827835e+10 | E47: 54911388 | F47: =D47-E47 -> 10772923719 | G47: 5.64243e+09 | H47: 8195 | I47: 23172313 | J47: 13856592 | K47: =I47-J47 -> 9315720.9 | L47: =I47+Apr!L47 -> 1.3676532e+08 | M47: =J47+Apr!M47 -> 92658298 | N47: =L47-M47 -> 44107024
B48: 32 | C48: Solidaritas Fund, Inc. (formerly, Bahay Pari Solidaritas Fund, Inc.) | D48: 1.3872776e+08 | E48: 332525.88 | F48: =D48-E48 -> 1.3839524e+08 | G48: 74922126 | H48: 197 | I48: 8498.02 | J48: 3370506.3 | K48: =I48-J48 -> -3362008.3 | L48: =I48+Apr!L48 -> 352374.21 | M48: =J48+Apr!M48 -> 6586026.3 | N48: =L48-M48 -> -6233652.1
B49: 33 | C49: Sun Life Prosperity Balanced Fund, Inc. | D49: 7.6881071e+09 | E49: 30089037 | F49: =D49-E49 -> 7658018057 | G49: 4.6804037e+09 | H49: 53212 | I49: 22310811 | J49: 43330834 | K49: =I49-J49 -> -21020023 | L49: =I49+Apr!L49 -> 88577123 | M49: =J49+Apr!M49 -> 2.6574352e+08 | N49: =L49-M49 -> -1.771664e+08
B50: 34 | C50: Sun Life Prosperity Dynamic Fund, Inc. | D50: 1.2404242e+09 | E50: 22069644 | F50: =D50-E50 -> 1218354593 | G50: 8.6141198e+08 | H50: 4998 | I50: 0 | J50: 2417607.1 | K50: =I50-J50 -> -2417607.1 | L50: =I50+Apr!L50 -> 0 | M50: =J50+Apr!M50 -> 43308292 | N50: =L50-M50 -> -43308292
A51: Primarily invested in Peso Securities (units)
B52: 35 | C52: Sun Life Prosperity Achiever Fund 2028, Inc. | D52: 71703223 | E52: 286823.12 | F52: =D52-E52 -> 71416400 | G52: 26565828 | H52: 938 | I52: 609447.22 | J52: 92668.04 | K52: =I52-J52 -> 516779.18 | L52: =I52+Apr!L52 -> 3815231.3 | M52: =J52+Apr!M52 -> 747184.52 | N52: =L52-M52 -> 3068046.8
B53: 36 | C53: Sun Life Prosperity Achiever Fund 2038, Inc. | D53: 55617801 | E53: 252294.69 | F53: =D53-E53 -> 55365507 | G53: 43610216 | H53: 353 | I53: 284000 | J53: 13376.79 | K53: =I53-J53 -> 270623.21 | L53: =I53+Apr!L53 -> 3930447.6 | M53: =J53+Apr!M53 -> 227948.72 | N53: =L53-M53 -> 3702498.9
B54: 37 | C54: Sun Life Prosperity Achiever Fund 2048, Inc. | D54: 47746232 | E54: 237937.31 | F54: =D54-E54 -> 47508295 | G54: 40350505 | H54: 166 | I54: 147581.3 | J54: 0 | K54: =I54-J54 -> 147581.3 | L54: =I54+Apr!L54 -> 1513766.7 | M54: =J54+Apr!M54 -> 97041.44 | N54: =L54-M54 -> 1416725.2
A55: Sub total - Peso Currency | D55: =SUM(D41:D54) -> 23204205482 | E55: =SUM(E41:E54) -> 1.4608905e+08 | F55: =SUM(F41:F54) -> 23058116436 | G55: =SUM(G41:G54) -> 12851448987 | H55: =SUM(H41:H54) -> 86369 | I55: =SUM(I41:I54) -> 61220052 | J55: =SUM(J41:J54) -> 77158949 | K55: =SUM(K41:K54) -> -15938897 | ... N55: =SUM(N41:N54) -> -1.0622481e+08
A56: Primarily invested in foreign currency securities (shares)
B57: 38 | C57: Cocolife Dollar Fund Builder, Inc. | D57: =52.37*1364307.62 -> 71448790 | E57: =52.37*6629.59 -> 347191.63 | F57: =D57-E57 -> 71101598 | G57: 0 | H57: 55 | I57: 0 | J57: 0 | K57: =I57-J57 -> 0 | L57: =I57+Apr!L57 -> 5201915 | M57: =J57+Apr!M57 -> 4087392.8 | N57: =L57-M57 -> 1114522.1
B58: 39 | C58: PAMI Asia Balanced Fund, Inc. | D58: =52.37*7328674.74 -> 3.838027e+08 | E58: =52.37*435712.59 -> 22818268 | F58: =D58-E58 -> 3.6098443e+08 | G58: =52.37*3666097.71 -> 1.9199354e+08 | H58: 253 | I58: =52.37*400.14 -> 20955.332 | J58: =52.37*993.16 -> 52011.789 | K58: =I58-J58 -> -31056.457 | L58: =I58+Apr!L58 -> 563511.34 | M58: =J58+Apr!M58 -> 8853491.5 | N58: =L58-M58 -> -8289980.2
B59: 40 | C59: Sun Life Prosperity Dollar Advantage Fund, Inc. | D59: =52.37*31182687.91 -> 1633037366 | E59: =52.37*107543.79 -> 5632068.3 | F59: =D59-E59 -> 1627405298 | G59: 0 | H59: 4118 | I59: =52.37*29715.74 -> 1556213.3 | J59: =52.37*258950.34 -> 13561229 | K59: =I59-J59 -> -12005016 | L59: =I59+Apr!L59 -> 57778118 | M59: =J59+Apr!M59 -> 1.3853374e+08 | N59: =L59-M59 -> -80755618
B60: 41 | C60: Sun Life Prosperity Dollar Wellspring Fund, Inc. | D60: =52.37*6257045.48 -> 3.2768147e+08 | E60: =52.37*43884.16 -> 2298213.5 | F60: =D60-E60 -> 3.2538326e+08 | G60: 0 | H60: 703 | I60: =52.37*134892.08 -> 7064298.2 | J60: =52.37*109392.37 -> 5728878.4 | K60: =I60-J60 -> 1335419.8 | L60: =I60+Apr!L60 -> 9383674.8 | M60: =J60+Apr!M60 -> 16646179 | N60: =L60-M60 -> -7262504.2
A61: Sub total - US Currency | D61: =SUM(D57:D60) -> 2415970324 | E61: =SUM(E57:E60) -> 31095742 | F61: =SUM(F57:F60) -> 2384874582 | G61: =SUM(G57:G60) -> 1.9199354e+08 | H61: =SUM(H57:H60) -> 5129 | I61: =SUM(I57:I60) -> 8641466.9 | J61: =SUM(J57:J60) -> 19342120 | K61: =SUM(K57:K60) -> -10700653 | ... N61: =SUM(N57:N60) -> -95193580
A62: Sub total - balanced funds | D62: =D55+D61 -> 25620175806 | E62: =E55+E61 -> 1.7718479e+08 | F62: =F55+F61 -> 25442991018 | G62: =G55+G61 -> 13043442524 | H62: =H55+H61 -> 91498 | I62: =I55+I61 -> 69861519 | J62: =J55+J61 -> 96501068 | K62: =K55+K61 -> -26639550 | ... N62: =N55+N61 -> -2.0141839e+08
A63: Bond Funds
A64: Primarily invested in Peso Securities (shares)
B65: 42 | C65: ALFM Peso Bond Fund, Inc. | D65: 4.2342941e+10 | E65: 2.6166669e+08 | F65: =D65-E65 -> 42081274385 | G65: 1183730440 | H65: 26057 | I65: 2.1430974e+08 | J65: 6.8189629e+08 | K65: =I65-J65 -> -467586557 | L65: =I65+Apr!L65 -> 1370652256 | M65: =J65+Apr!M65 -> 3152836471 | N65: =L65-M65 -> -1782184215
B66: 43 | C66: ATRAM Corporate Bond Fund, Inc. (formerly, Prudentialife Fixed Income Fund, Inc.) | D66: 3.0462807e+08 | E66: 789975.9 | F66: =D66-E66 -> 3.0383809e+08 | G66: 0 | H66: 1050 | I66: 4091568.1 | J66: 4700751.3 | K66: =I66-J66 -> -609183.22 | L66: =I66+Apr!L66 -> 24015235 | M66: =J66+Apr!M66 -> 13766336 | N66: =L66-M66 -> 10248899
B67: 44 | C67: Cocolife Fixed Income Fund, Inc. | D67: 1.1950708e+09 | E67: 24309527 | F67: =D67-E67 -> 1170761296 | G67: 0 | H67: 2055 | I67: 2507075.2 | J67: 1.0310076e+08 | K67: =I67-J67 -> -1.0059368e+08 | L67: =I67+Apr!L67 -> 1.2289697e+08 | M67: =J67+Apr!M67 -> 1.7533034e+08 | N67: =L67-M67 -> -52433371
B68: 45 | C68: Ekklesia Mutual Fund, Inc. | D68: 1.9688954e+08 | E68: 301725.36 | F68: =D68-E68 -> 1.9658782e+08 | G68: 4975000 | H68: 147 | I68: 263983.71 | J68: 1174437.8 | K68: =I68-J68 -> -910454.04 | L68: =I68+Apr!L68 -> 1870820 | M68: =J68+Apr!M68 -> 2292654.8 | N68: =L68-M68 -> -421834.76
B69: 46 | C69: First Metro Save and Learn Fixed Income Fund, Inc. | D69: 1.4569777e+09 | E69: 10679521 | F69: =D69-E69 -> 1446298166 | G69: 0 | H69: 1890 | I69: 3581223.8 | J69: 35396513 | K69: =I69-J69 -> -31815289 | L69: =I69+Apr!L69 -> 23947955 | M69: =J69+Apr!M69 -> 97545917 | N69: =L69-M69 -> -73597962
B70: 47 | C70: Philam Managed Income Fund, Inc. | D70: 9.7583676e+08 | E70: 36845757 | F70: =D70-E70 -> 9.38991e+08 | G70: 0 | H70: 527 | I70: 9579416.2 | J70: 4543940.8 | K70: =I70-J70 -> 5035475.4 | L70: =I70+Apr!L70 -> 17517936 | M70: =J70+Apr!M70 -> 63281271 | N70: =L70-M70 -> -45763335
B71: 48 | C71: Philam Bond Fund, Inc. | D71: 6.3231596e+09 | E71: 21624645 | F71: =D71-E71 -> 6301534952 | G71: 0 | H71: 5032 | I71: 21643338 | J71: 1.1536076e+08 | K71: =I71-J71 -> -93717417 | L71: =I71+Apr!L71 -> 1.6746924e+08 | M71: =J71+Apr!M71 -> 3.5729072e+08 | N71: =L71-M71 -> -1.8982148e+08
B72: 49 | C72: Philequity Peso Bond Fund, Inc. | D72: 3.1619917e+08 | E72: 1402839.9 | F72: =D72-E72 -> 3.1479633e+08 | G72: 16856520 | H72: 4180 | I72: 10094890 | J72: 8446343.7 | K72: =I72-J72 -> 1648546.3 | L72: =I72+Apr!L72 -> 25899912 | M72: =J72+Apr!M72 -> 16981359 | N72: =L72-M72 -> 8918552.4
B73: 50 | C73: Soldivo Bond Fund, Inc. | D73: 9.9750786e+08 | E73: 2545848.1 | F73: =D73-E73 -> 9.9496201e+08 | G73: 0 | H73: 846 | I73: 29545377 | J73: 0 | K73: =I73-J73 -> 29545377 | L73: =I73+Apr!L73 -> 1.0152519e+08 | M73: =J73+Apr!M73 -> 3400867.7 | N73: =L73-M73 -> 98124324
B74: 51 | C74: Sun Life Prosperity Bond Fund, Inc. | D74: 4.4747579e+09 | E74: 11958925 | F74: =D74-E74 -> 4462799012 | G74: 0 | H74: 16110 | I74: 36889132 | J74: 79587274 | K74: =I74-J74 -> -42698142 | L74: =I74+Apr!L74 -> 2.0682547e+08 | M74: =J74+Apr!M74 -> 3.6896939e+08 | N74: =L74-M74 -> -1.6214392e+08
B75: 52 | C75: Sun Life Prosperity GS Fund, Inc. | D75: 1.510237e+08 | E75: 10534281 | F75: =D75-E75 -> 1.4048942e+08 | G75: 0 | H75: 2567 | I75: 450697.5 | J75: 13105372 | K75: =I75-J75 -> -12654674 | L75: =I75+Apr!L75 -> 3986279 | M75: =J75+Apr!M75 -> 22799622 | N75: =L75-M75 -> -18813343
A76: Sub total - Peso Currency | D76: =SUM(D65:D75) -> 58734992225 | E76: =SUM(E65:E75) -> 3.8265974e+08 | F76: =SUM(F65:F75) -> 58352332484 | G76: =SUM(G65:G75) -> 1205561960 | H76: =SUM(H65:H75) -> 60461 | I76: =SUM(I65:I75) -> 3.3295644e+08 | J76: =SUM(J65:J75) -> 1047312440 | K76: =SUM(K65:K75) -> -714356002 | ... N76: =SUM(N65:N75) -> -2207887686
A77: Primarily invested in foreign currency securities (shares)
B78: 53 | C78: ALFM Dollar Bond Fund, Inc. | D78: =52.37*276183086.39 -> 14463708234 | E78: =52.37*1066392.84 -> 55846993 | F78: =D78-E78 -> 14407861241 | G78: 0 | H78: 9609 | I78: =52.37*2199081.76 -> 1.1516591e+08 | J78: =52.37*6794066.01 -> 3.5580524e+08 | K78: =I78-J78 -> -2.4063933e+08 | L78: =I78+Apr!L78 -> 5.5457876e+08 | M78: =J78+Apr!M78 -> 3882923069 | N78: =L78-M78 -> -3328344307
B79: 54 | C79: ATRAM Total Return Dollar Bond Fund, Inc. (formerly, ATR KimEng Total Return Bond Fund, Inc.) | D79: 5.2140713e+08 | E79: 80304590 | F79: =D79-E79 -> 441102544 | G79: 0 | H79: 200 | I79: 7004256 | J79: 1.6296659e+08 | K79: =I79-J79 -> -1.5596234e+08 | L79: =I79+Apr!L79 -> 18965146 | M79: =J79+Apr!M79 -> 3.2551349e+08 | N79: =L79-M79 -> -3.0654834e+08
B80: 55 | C80: First Metro Save and Learn Dollar Bond Fund, Inc. | D80: 7.1145451e+08 | E80: 3257391 | F80: =D80-E80 -> 7.0819712e+08 | G80: 0 | H80: 157 | I80: 257465.93 | J80: 0 | K80: =I80-J80 -> 257465.93 | L80: =I80+Apr!L80 -> 1309295 | M80: =J80+Apr!M80 -> 14565722 | N80: =L80-M80 -> -13256427
B81: 56 | C81: PAMI Global Bond Fund Phils., Inc. | D81: =52.37*1174945.72 -> 61531907 | E81: =52.37*216758.96 -> 11351667 | F81: =D81-E81 -> 50180241 | G81: 0 | H81: 22 | I81: =52.37*13078.29 -> 684910.05 | J81: =52.37*15794.32 -> 827148.54 | K81: =I81-J81 -> -142238.49 | L81: =I81+Apr!L81 -> 684910.05 | M81: =J81+Apr!M81 -> 1188417 | N81: =L81-M81 -> -503506.91
B82: 57 | C82: Philam Dollar Bond Fund, Inc. | D82: =52.37*41485439.77 -> 2172592481 | E82: =52.37*-243687.12 -> -12761894 | F82: =D82-E82 -> 2185354375 | G82: 0 | H82: 1985 | I82: =52.37*1488.09 -> 77931.273 | J82: =52.37*142349.43 -> 7454839.6 | K82: =I82-J82 -> -7376908.4 | L82: =I82+Apr!L82 -> 268088983 | M82: =J82+Apr!M82 -> 57671549 | N82: =L82-M82 -> 2.1041743e+08
B83: 58 | C83: Philequity Dollar Income Fund, Inc. | D83: 2.2555243e+08 | E83: 899844.38 | F83: =D83-E83 -> 2.2465259e+08 | G83: 0 | H83: 127 | I83: 130925 | J83: 427761.3 | K83: =I83-J83 -> -296836.3 | L83: =I83+Apr!L83 -> 1280795 | M83: =J83+Apr!M83 -> 1995692.2 | N83: =L83-M83 -> -714897.21
B84: 59 | C84: Sun Life Prosperity Dollar Abundance Fund, Inc. | D84: =52.37*9936774.74 -> 5.2038889e+08 | E84: =52.37*899368.15 -> 47099910 | F84: =D84-E84 -> 4.7328898e+08 | G84: 0 | H84: 2514 | I84: 0 | J84: =52.37*21327.12 -> 1116901.3 | K84: =I84-J84 -> -1116901.3 | L84: =I84+Apr!L84 -> 19063055 | M84: =J84+Apr!M84 -> 35988095 | N84: =L84-M84 -> -16925041
A85: Sub total - US Currency | D85: =SUM(D78:D84) -> 18676635589 | E85: =SUM(E78:E84) -> 1.859985e+08 | F85: =SUM(F78:F84) -> 18490637088 | G85: =SUM(G78:G84) -> 0 | H85: =SUM(H78:H84) -> 14614 | I85: =SUM(I78:I84) -> 123321400 | J85: =SUM(J78:J84) -> 5.2859848e+08 | K85: =SUM(K78:K84) -> -4.0527708e+08 | ... N85: =SUM(N78:N84) -> -3455875085
B86: 60 | C86: ALFM Euro Bond Fund, Inc. | D86: =56.261091*16158637.49 -> 9.0910257e+08 | E86: =56.261091*50638.96 -> 2849003.1 | F86: =D86-E86 -> 9.0625357e+08 | G86: 0 | H86: 672 | I86: =56.261091*114550.26 -> 6444722.6 | J86: =56.261091*155767.37 -> 8763642.2 | K86: =I86-J86 -> -2318919.6 | L86: =I86+Apr!L86 -> 11970761 | M86: =J86+Apr!M86 -> 43451730 | N86: =L86-M86 -> -31480969
A87: Sub total - Euro Currency | D87: =SUM(D86) -> 9.0910257e+08 | E87: =SUM(E86) -> 2849003.1 | F87: =SUM(F86) -> 9.0625357e+08 | G87: =SUM(G86) -> 0 | H87: =SUM(H86) -> 672 | I87: =SUM(I86) -> 6444722.6 | J87: =SUM(J86) -> 8763642.2 | K87: =SUM(K86) -> -2318919.6 | ... N87: =SUM(N86) -> -31480969
A88: Sub total - bond funds | D88: =D76+D85+D87 -> 78320730388 | E88: =E76+E85+E87 -> 5.7150724e+08 | F88: =F76+F85+F87 -> 77749223143 | G88: =G76+G85+G87 -> 1205561960 | H88: =H76+H85+H87 -> 75747 | I88: =I76+I85+I87 -> 462722561 | J88: =J76+J85+J87 -> 1584674565 | K88: =K76+K85+K87 -> -1121952004 | ... N88: =N76+N85+N87 -> -5695243740
A89: Money Market Funds
A90: Primarily invested in Peso Securities (shares)
B91: 61 | C91: ALFM Money Market Fund, Inc. | D91: 6.0237095e+10 | E91: 35740581 | F91: =D91-E91 -> 60201354260 | G91: 0 | H91: 33158 | I91: 3.1636421e+09 | J91: 3.1695884e+09 | K91: =I91-J91 -> -5946331.6 | L91: =I91+Apr!L91 -> 16532070300 | M91: =J91+Apr!M91 -> 15049280547 | N91: =L91-M91 -> 1482789754
B92: 62 | C92: First Metro Save and Learn Money Market Fund, Inc. | D92: 2.883422e+09 | E92: 5273545 | F92: =D92-E92 -> 2878148432 | G92: 0 | H92: 584 | I92: 1.5736823e+08 | J92: 1.6367595e+08 | K92: =I92-J92 -> -6307726.8 | L92: =I92+Apr!L92 -> 1103942720 | M92: =J92+Apr!M92 -> 1009716525 | N92: =L92-M92 -> 94226196
B93: 63 | C93: Sun Life Prosperity Peso Starter Fund, Inc. | D93: 1.3023586e+11 | E93: 1.2818443e+09 | F93: =D93-E93 -> 128954012726 | G93: 0 | H93: 60096 | I93: 1.570633e+10 | J93: 1.6996239e+10 | K93: =I93-J93 -> -1289909486 | L93: =I93+Apr!L93 -> 87419706697 | M93: =J93+Apr!M93 -> 86377262679 | N93: =L93-M93 -> 1042444019
A94: Sub total - Peso Currency | D94: =SUM(D91:D93) -> 193356373816 | E94: =SUM(E91:E93) -> 1322858398 | F94: =SUM(F91:F93) -> 192033515418 | G94: =SUM(G91:G93) -> 0 | H94: =SUM(H91:H93) -> 93838 | I94: =SUM(I91:I93) -> 19027340111 | J94: =SUM(J91:J93) -> 20329503655 | K94: =SUM(K91:K93) -> -1302163544 | ... N94: =SUM(N91:N93) -> 2619459968
A95: Primarily invested in foreign currency securities (shares)
B96: 64 | C96: Sun Life Prosperity Dollar Starter Fund, Inc. | D96: =52.37*255585860.53 -> 13385031516 | E96: =52.37*2267800.56 -> 1.1876472e+08 | F96: =D96-E96 -> 13266266801 | G96: 0 | H96: 2960 | I96: =52.37*85640613.96 -> 4484998953 | J96: =52.37*43575610.56 -> 2282054725 | K96: =I96-J96 -> 2202944228 | L96: =I96+Apr!L96 -> 13802231437 | M96: =J96+Apr!M96 -> 10308481607 | N96: =L96-M96 -> 3493749830
A97: Sub total - US Currency | D97: =SUM(D96) -> 13385031516 | E97: =SUM(E96) -> 1.1876472e+08 | F97: =SUM(F96) -> 13266266801 | G97: =SUM(G96) -> 0 | H97: =SUM(H96) -> 2960 | I97: =SUM(I96) -> 4484998953 | J97: =SUM(J96) -> 2282054725 | K97: =SUM(K96) -> 2202944228 | ... N97: =SUM(N96) -> 3493749830
A98: Sub total - money market funds | D98: =D94+D97 -> 206741405332 | E98: =E94+E97 -> 1441623113 | F98: =F94+F97 -> 205299782218 | G98: =G94+G97 -> 0 | H98: =H94+H97 -> 96798 | I98: =I94+I97 -> 23512339064 | J98: =J94+J97 -> 22611558380 | K98: =K94+K97 -> 9.0078068e+08 | ... N98: =N94+N97 -> 6113209798
A99: Feeder Fund
A100: Primarily invested in Peso securities (units)
B101: 65 | C101: ALFM Global Multi-Asset Income Fund Inc. | D101: 8.9313411e+09 | E101: 63877561 | F101: =D101-E101 -> 8867463493 | G101: 0 | H101: 3585 | I101: 2.690576e+08 | J101: 1.3668927e+08 | K101: =I101-J101 -> 1.3236833e+08 | L101: =I101+Apr!L101 -> 2424466967 | M101: =J101+Apr!M101 -> 271411480 | N101: =L101-M101 -> 2153055487
B102: 66 | C102: Sun Life Prosperity World Equity Index Feeder Fund, Inc. | D102: 3.6298673e+09 | E102: 81901248 | F102: =D102-E102 -> 3547966005 | G102: 0 | H102: 5190 | I102: 58488696 | J102: 47198468 | K102: =I102-J102 -> 11290228 | L102: =I102+Apr!L102 -> 8.2740482e+08 | M102: =J102+Apr!M102 -> 7.2501745e+08 | N102: =L102-M102 -> 1.0238737e+08
A103: Sub total - Peso Currency | D103: =D101+D102 -> 12561208308 | E103: =E101+E102 -> 1.4577881e+08 | F103: =F101+F102 -> 12415429498 | G103: =G101+G102 -> 0 | H103: =H101+H102 -> 8775 | I103: =I101+I102 -> 3.2754629e+08 | J103: =J101+J102 -> 1.8388774e+08 | K103: =K101+K102 -> 1.4365856e+08 | ... N103: =N101+N102 -> 2255442855
A104: Primarily invested in foreign currency securities (units)
B105: 67 | C105: ALFM Global Multi-Asset Income Fund, Inc. | D105: =52.37*195353968.99 -> 10230687356 | E105: =52.37*2736499.42 -> 1.4331047e+08 | F105: =D105-E105 -> 10087376881 | G105: 0 | H105: 8439 | I105: =52.37*4679781.73 -> 2.4508017e+08 | J105: =52.37*2441109.07 -> 127840882 | K105: =I105-J105 -> 1.1723929e+08 | L105: =I105+Apr!L105 -> 1128799908 | M105: =J105+Apr!M105 -> 4.9781365e+08 | N105: =L105-M105 -> 6.3098626e+08
A106: Sub total - US Currency | D106: =SUM(D105) -> 10230687356 | E106: =SUM(E105) -> 1.4331047e+08 | F106: =SUM(F105) -> 10087376881 | G106: =SUM(G105) -> 0 | H106: =SUM(H105) -> 8439 | I106: =SUM(I105) -> 2.4508017e+08 | J106: =SUM(J105) -> 127840882 | K106: =SUM(K105) -> 1.1723929e+08 | ... N106: =SUM(N105) -> 6.3098626e+08
...

Sheet June
A1: PHILIPPINE INVESTMENT FUNDS ASSOCIATION, INC.
A2: MUTUAL FUNDS STATISTICAL REPORT
A3: Month of June 2022
A4: (Amounts in Peso)
I5: F O R - T H E - M O N T H | L5: Y E A R - T O - D A T E
A6: Fund Category | C6: Fund Name | D6: ASSETS | E6: LIABILITIES | F6: NET ASSETS | G6: EQUITY INV. | H6: NO. OF A/C | I6: SALES | J6: REDEMPTIONS | K6: NET SALES | L6: TOTAL SALES | M6: TOTAL REDEMPTIONS | N6: TOTAL NET SALES
A7: Stock Funds
A8: Primarily invested in Peso Securities (shares)
B9: 1 | C9: ALFM Growth Fund, Inc. | D9: 4.5803566e+09 | E9: 23785456 | F9: =D9-E9 -> 4556571107 | G9: 4.0897858e+09 | H9: 7497 | I9: 14802824 | J9: 26848823 | K9: =I9-J9 -> -12045999 | L9: =I9+May!L9 -> 1.023901e+08 | M9: =J9+May!M9 -> 258005260 | N9: =L9-M9 -> -1.5561516e+08
B10: 2 | C10: ATRAM Alpha Opportunity Fund, Inc. (formerly, ATRKE Alpha Opportunity Fund, Inc.) | D10: 7.0908328e+08 | E10: 2072831.4 | F10: =D10-E10 -> 7.0701045e+08 | G10: 6.048486e+08 | H10: 4285 | I10: 9288046.8 | J10: 7843672.4 | K10: =I10-J10 -> 1444374.4 | L10: =I10+May!L10 -> 1.808882e+08 | M10: =J10+May!M10 -> 123673769 | N10: =L10-M10 -> 57214432
B11: 3 | C11: ATRAM Phil. Equity Opportunity Fund, Inc. (formerly, ATRKE Equity Opportunity Fund, Inc.) | D11: 9.5218227e+08 | E11: 2599216.7 | F11: =D11-E11 -> 9.4958306e+08 | G11: 8.5539511e+08 | H11: 2771 | I11: 11847676 | J11: 12853522 | K11: =I11-J11 -> -1005846.2 | L11: =I11+May!L11 -> 74306113 | M11: =J11+May!M11 -> 114640672 | N11: =L11-M11 -> -40334559
B12: 4 | C12: Climbs Share Capital Equity Investment Fund Corp. | D12: 3.3719981e+08 | E12: 4004739.3 | F12: =D12-E12 -> 3.3319507e+08 | G12: 2.0678089e+08 | H12: 1652 | I12: 3410015.8 | J12: 2008534.6 | K12: =I12-J12 -> 1401481.2 | L12: =I12+May!L12 -> 20450911 | M12: =J12+May!M12 -> 10112167 | N12: =L12-M12 -> 10338744
B13: 5 | C13: First Metro Consumer Fund on MSCI Phils. IMI, Inc. | D13: 5.039934e+08 | E13: 1736315.9 | F13: =D13-E13 -> 5.0225709e+08 | G13: 2.3069467e+08 | H13: 1492 | I13: 866737.92 | J13: 2381109.7 | K13: =I13-J13 -> -1514371.8 | L13: =I13+May!L13 -> 22244531 | M13: =J13+May!M13 -> 14008396 | N13: =L13-M13 -> 8236134.4
B14: 6 | C14: First Metro Save and Learn Equity Fund, Inc. | D14: 4.110085e+09 | E14: 99953188 | F14: =D14-E14 -> 4010131781 | G14: 2.9668759e+09 | H14: 16497 | I14: 66089718 | J14: 15666842 | K14: =I14-J14 -> 50422877 | L14: =I14+May!L14 -> 4.9877029e+08 | M14: =J14+May!M14 -> 317580061 | N14: =L14-M14 -> 1.8119023e+08
B15: 7 | C15: First Metro Save and Learn Phil. Index Fund, Inc. (formerly, One Wealthy Nation Fund, Inc.) | D15: 87880005 | E15: 676406.51 | F15: =D15-E15 -> 87203598 | G15: 81511975 | H15: 554 | I15: 3748480.9 | J15: 125576 | K15: =I15-J15 -> 3622904.9 | L15: =I15+May!L15 -> 14676488 | M15: =J15+May!M15 -> 6429406.9 | N15: =L15-M15 -> 8247081.6
B16: 8 | C16: MBG Equity Investment Fund, Inc. | D16: 1.2681866e+08 | E16: 8244887.2 | F16: =D16-E16 -> 1.1857377e+08 | G16: 112058432 | H16: 51 | I16: 0 | J16: 6470778.8 | K16: =I16-J16 -> -6470778.8 | L16: =I16+May!L16 -> 1600000 | M16: =J16+May!M16 -> 7420778.8 | N16: =L16-M16 -> -5820778.8
B17: 9 | C17: PAMI Equity Index Fund, Inc. | D17: 1.5697676e+10 | E17: 1.3185222e+08 | F17: =D17-E17 -> 15565823898 | G17: 1.5484781e+10 | H17: 12626 | I17: 1.9043018e+08 | J17: 7081494.4 | K17: =I17-J17 -> 1.8334869e+08 | L17: =I17+May!L17 -> 1193912738 | M17: =J17+May!M17 -> 82514579 | N17: =L17-M17 -> 1111398159
B18: 10 | C18: Philam Strategic Growth Fund, Inc. | D18: 3.0999083e+10 | E18: 2.3316964e+08 | F18: =D18-E18 -> 30765913816 | G18: 2.7016509e+10 | H18: 12524 | I18: 1.1106147e+08 | J18: 29231977 | K18: =I18-J18 -> 81829490 | L18: =I18+May!L18 -> 6.1542292e+08 | M18: =J18+May!M18 -> 4.9586323e+08 | N18: =L18-M18 -> 1.1955969e+08
B19: 11 | C19: Philequity Dividend Yield Fund, Inc. | D19: 2.1078107e+09 | E19: 3294491 | F19: =D19-E19 -> 2104516217 | G19: 1.8761679e+09 | H19: 5694 | I19: 6681157.8 | J19: 7895348.7 | K19: =I19-J19 -> -1214190.9 | L19: =I19+May!L19 -> 97987806 | M19: =J19+May!M19 -> 2.6499483e+08 | N19: =L19-M19 -> -1.6700702e+08
B20: 12 | C20: Philequity Fund, Inc. | D20: 9.2939301e+09 | E20: 58678028 | F20: =D20-E20 -> 9235252023 | G20: 8.5040068e+09 | H20: 36879 | I20: 21557154 | J20: 27119110 | K20: =I20-J20 -> -5561955.6 | L20: =I20+May!L20 -> 1.8583492e+08 | M20: =J20+May!M20 -> 3.2758342e+08 | N20: =L20-M20 -> -1.4174849e+08
... B27: 19 | C27: United Fund, Inc. | D27: 5.684599e+08 | E27: 2614322.1 | F27: =D27-E27 -> 5.6584558e+08 | G27: 5.0873575e+08 | H27: 1307 | I27: 1530588.9 | J27: 220703.76 | K27: =I27-J27 -> 1309885.1 | L27: =I27+May!L27 -> 12763430 | M27: =J27+May!M27 -> 7186967.8 | N27: =L27-M27 -> 5576461.7
A28: Primarily invested in Peso Securities (units)
B29: 20 | C29: Philequity Alpha One Fund, Inc. | D29: 3.2903298e+08 | E29: 1748543.4 | F29: =D29-E29 -> 3.2728444e+08 | G29: 2.7560446e+08 | H29: 1462 | I29: 5745438.6 | J29: 12522358 | K29: =I29-J29 -> -6776919 | L29: =I29+May!L29 -> 73541476 | M29: =J29+May!M29 -> 25904984 | N29: =L29-M29 -> 47636492
B30: 21 | C30: Philippine Stock Index Fund Corp. | D30: 3.5968187e+08 | E30: 15259664 | F30: =D30-E30 -> 3.444222e+08 | G30: 3.4051191e+08 | H30: 284367 | I30: 64935543 | J30: 8915103.1 | K30: =I30-J30 -> 56020440 | L30: =I30+May!L30 -> 4.7335359e+08 | M30: =J30+May!M30 -> 76747208 | N30: =L30-M30 -> 3.9660638e+08
A31: Exchange Traded Fund
B32: 22 | C32: First Metro Phil. Equity Exchange Traded Fund, Inc. | D32: 2.0012374e+09 | E32: 6100193.7 | F32: =D32-E32 -> 1995137252 | G32: 1.9929227e+09 | H32: 3213 | I32: 31371140 | J32: 0 | K32: =I32-J32 -> 31371140 | L32: =I32+May!L32 -> 107073565 | M32: =J32+May!M32 -> 13683385 | N32: =L32-M32 -> 93390180
A33: Sub total - Peso Currency | D33: =SUM(D9:D32) -> 105648247107 | E33: =SUM(E9:E32) -> 7.4056906e+08 | F33: =SUM(F9:F32) -> 104907678044 | G33: =SUM(G9:G32) -> 97282688780 | H33: =SUM(H9:H32) -> 573714 | I33: =SUM(I9:I32) -> 9.3544514e+08 | J33: =SUM(J9:J32) -> 3.9812045e+08 | K33: =SUM(K9:K32) -> 5.3732469e+08 | ... N33: =SUM(N9:N32) -> 1961944194
A34: Primarily invested in foreign currency securities (shares)
B35: 23 | C35: ATRAM AsiaPlus Equity Fund, Inc. (formerly, ATR KimEng AsiaPlus Recovery Fund, Inc.) | D35: 41164913 | E35: 927726.76 | F35: =D35-E35 -> 40237187 | G35: 0 | H35: 57 | I35: 68596.71 | J35: 7245.16 | K35: =I35-J35 -> 61351.55 | L35: =I35+May!L35 -> 928603.7 | M35: =J35+May!M35 -> 5540208 | N35: =L35-M35 -> -4611604.2
B36: 24 | C36: Sun Life Prosperity World Voyager Fund, Inc. | D36: =54.975*34495275.92 -> 1896377794 | E36: =54.975*127473.32 -> 7007845.8 | F36: =D36-E36 -> 1889369948 | G36: 0 | H36: 2809 | I36: =54.975*118144.34 -> 6494985.1 | J36: =54.975*143712.12 -> 7900573.8 | K36: =I36-J36 -> -1405588.7 | L36: =I36+May!L36 -> 2.5128189e+08 | M36: =J36+May!M36 -> 2.2142331e+08 | N36: =L36-M36 -> 29858575
A37: Sub total - US Currency | D37: =SUM(D35:D36) -> 1937542707 | E37: =SUM(E35:E36) -> 7935572.5 | F37: =SUM(F35:F36) -> 1929607134 | G37: =SUM(G35:G36) -> 0 | H37: =SUM(H35:H36) -> 2866 | I37: =SUM(I35:I36) -> 6563581.8 | J37: =SUM(J35:J36) -> 7907819 | K37: =SUM(K35:K36) -> -1344237.2 | ... N37: =SUM(N35:N36) -> 25246971
A38: Sub total - stock funds | D38: =D33+D37 -> 107585789814 | E38: =E33+E37 -> 7.4850464e+08 | F38: =F33+F37 -> 106837285179 | G38: =G33+G37 -> 97282688780 | H38: =H33+H37 -> 576580 | I38: =I33+I37 -> 9.4200873e+08 | J38: =J33+J37 -> 4.0602827e+08 | K38: =K33+K37 -> 5.3598046e+08 | ... N38: =N33+N37 -> 1987191165
A39: Balanced Funds
A40: Primarily invested in Peso Securities (shares)
B41: 25 | C41: ATRAM Dynamic Allocation Fund, Inc. (formerly, Optima Balanced Fund, Inc.) | D41: 1.2190369e+08 | E41: 2674350.5 | F41: =D41-E41 -> 1.1922934e+08 | G41: 22373551 | H41: 733 | I41: 429125.86 | J41: 484552.07 | K41: =I41-J41 -> -55426.21 | L41: =I41+May!L41 -> 9065982.1 | M41: =J41+May!M41 -> 3624124 | N41: =L41-M41 -> 5441858.1
B42: 26 | C42: ATRAM Philippine Balanced Fund, Inc. (formerly, ATRKE Philippine Balanced Fund, Inc.) | D42: 6.102226e+08 | E42: 1556261.2 | F42: =D42-E42 -> 6.0866634e+08 | G42: 2.0846799e+08 | H42: 2474 | I42: 3049905.4 | J42: 1749546.4 | K42: =I42-J42 -> 1300359 | L42: =I42+May!L42 -> 10810566 | M42: =J42+May!M42 -> 35678576 | N42: =L42-M42 -> -24868009
B43: 27 | C43: First Metro Save and Learn Balanced Fund, Inc. | D43: 1.086176e+09 | E43: 21133959 | F43: =D43-E43 -> 1065042000 | G43: 4.2547136e+08 | H43: 4832 | I43: 2627147.6 | J43: 2630987.7 | K43: =I43-J43 -> -3840.078 | L43: =I43+May!L43 -> 17442566 | M43: =J43+May!M43 -> 1.6461301e+08 | N43: =L43-M43 -> -1.4717044e+08
B44: 28 | C44: First Metro Save and Learn F.O.C.C.U.S. Dynamic Fund, Inc. | D44: 2.8838934e+08 | E44: 4240304.6 | F44: =D44-E44 -> 2.8414903e+08 | G44: 1.1273864e+08 | H44: 206 | I44: 22412793 | J44: 2391805.4 | K44: =I44-J44 -> 20020987 | L44: =I44+May!L44 -> 2.9710518e+08 | M44: =J44+May!M44 -> 14037507 | N44: =L44-M44 -> 2.8306767e+08
B45: 29 | C45: NCM Mutual Fund of the Phils., Inc. | D45: 3.2962475e+08 | E45: 1622636.4 | F45: =D45-E45 -> 3.2800211e+08 | G45: 1.4839281e+08 | H45: 56 | I45: 0 | J45: 1772670.4 | K45: =I45-J45 -> -1772670.4 | L45: =I45+May!L45 -> 0 | M45: =J45+May!M45 -> 2789770.4 | N45: =L45-M45 -> -2789770.4
B46: 30 | C46: PAMI Horizon Fund, Inc. | D46: 5.6958433e+08 | E46: 13529181 | F46: =D46-E46 -> 5.5605515e+08 | G46: 2.6722364e+08 | H46: 10209 | I46: 374150.28 | J46: 3423050 | K46: =I46-J46 -> -3048899.7 | L46: =I46+May!L46 -> 4313450.9 | M46: =J46+May!M46 -> 33365008 | N46: =L46-M46 -> -29051557
B47: 31 | C47: Philam Fund, Inc. | D47: 1.0257354e+10 | E47: 80298416 | F47: =D47-E47 -> 10177055214 | G47: 4.8476034e+09 | H47: 8325 | I47: 27703312 | J47: 20800070 | K47: =I47-J47 -> 6903242.4 | L47: =I47+May!L47 -> 1.6446863e+08 | M47: =J47+May!M47 -> 113458368 | N47: =L47-M47 -> 51010266
B48: 32 | C48: Solidaritas Fund, Inc. (formerly, Bahay Pari Solidaritas Fund, Inc.) | D48: 1.3407847e+08 | E48: 328317.24 | F48: =D48-E48 -> 133750155 | G48: 68539423 | H48: 196 | I48: 3020495 | J48: 44793.9 | K48: =I48-J48 -> 2975701.1 | L48: =I48+May!L48 -> 3372869.3 | M48: =J48+May!M48 -> 6630820.2 | N48: =L48-M48 -> -3257950.9
B49: 33 | C49: Sun Life Prosperity Balanced Fund, Inc. | D49: 7.2230246e+09 | E49: 43024783 | F49: =D49-E49 -> 7179999857 | G49: 3.8608375e+09 | H49: 53270 | I49: 10853090 | J49: 31821716 | K49: =I49-J49 -> -20968627 | L49: =I49+May!L49 -> 99430213 | M49: =J49+May!M49 -> 2.9756524e+08 | N49: =L49-M49 -> -1.9813503e+08
B50: 34 | C50: Sun Life Prosperity Dynamic Fund, Inc. | D50: 1.1326522e+09 | E50: 9482363.2 | F50: =D50-E50 -> 1123169883 | G50: 7.002513e+08 | H50: 4998 | I50: 0 | J50: 10436866 | K50: =I50-J50 -> -10436866 | L50: =I50+May!L50 -> 0 | M50: =J50+May!M50 -> 53745157 | N50: =L50-M50 -> -53745157
A51: Primarily invested in Peso Securities (units)
B52: 35 | C52: Sun Life Prosperity Achiever Fund 2028, Inc. | D52: 69147632 | E52: 345820.35 | F52: =D52-E52 -> 68801812 | G52: 24771855 | H52: 949 | I52: 557124.48 | J52: 404505.84 | K52: =I52-J52 -> 152618.64 | L52: =I52+May!L52 -> 4372355.8 | M52: =J52+May!M52 -> 1151690.4 | N52: =L52-M52 -> 3220665.4
B53: 36 | C53: Sun Life Prosperity Achiever Fund 2038, Inc. | D53: 51845995 | E53: 321199.18 | F53: =D53-E53 -> 51524796 | G53: 40507054 | H53: 363 | I53: 571740.94 | J53: 142391.09 | K53: =I53-J53 -> 429349.85 | L53: =I53+May!L53 -> 4502188.5 | M53: =J53+May!M53 -> 370339.81 | N53: =L53-M53 -> 4131848.7
B54: 37 | C54: Sun Life Prosperity Achiever Fund 2048, Inc. | D54: 43943597 | E54: 293751.84 | F54: =D54-E54 -> 43649846 | G54: 37073094 | H54: 170 | I54: 104000 | J54: 61571.83 | K54: =I54-J54 -> 42428.17 | L54: =I54+May!L54 -> 1617766.7 | M54: =J54+May!M54 -> 158613.27 | N54: =L54-M54 -> 1459153.4
A55: Sub total - Peso Currency | D55: =SUM(D41:D54) -> 21917946873 | E55: =SUM(E41:E54) -> 1.7885134e+08 | F55: =SUM(F41:F54) -> 21739095531 | G55: =SUM(G41:G54) -> 10764251546 | H55: =SUM(H41:H54) -> 86781 | I55: =SUM(I41:I54) -> 71702884 | J55: =SUM(J41:J54) -> 76164527 | K55: =SUM(K41:K54) -> -4461642.7 | ... N55: =SUM(N41:N54) -> -110686449
A56: Primarily invested in foreign currency securities (shares)
B57: 38 | C57: Cocolife Dollar Fund Builder, Inc. | D57: =54.975*1315496.84 -> 72319439 | E57: =54.975*6816.93 -> 374760.73 | F57: =D57-E57 -> 71944678 | G57: 0 | H57: 55 | I57: 0 | J57: 0 | K57: =I57-J57 -> 0 | L57: =I57+May!L57 -> 5201915 | M57: =J57+May!M57 -> 4087392.8 | N57: =L57-M57 -> 1114522.1
B58: 39 | C58: PAMI Asia Balanced Fund, Inc. | D58: =54.975*6609844.89 -> 3.6337622e+08 | E58: =54.975*432437.04 -> 23773226 | F58: =D58-E58 -> 3.39603e+08 | G58: =54.975*3248297.47 -> 1.7857515e+08 | H58: 274 | I58: 0 | J58: =54.975*61485.55 -> 3380168.1 | K58: =I58-J58 -> -3380168.1 | L58: =I58+May!L58 -> 563511.34 | M58: =J58+May!M58 -> 12233660 | N58: =L58-M58 -> -11670148
B59: 40 | C59: Sun Life Prosperity Dollar Advantage Fund, Inc. | D59: =54.975*29431606.62 -> 1618002574 | E59: =54.975*94971.62 -> 5221064.8 | F59: =D59-E59 -> 1612781509 | G59: 0 | H59: 4120 | I59: =54.975*6139.44 -> 337515.71 | J59: =54.975*77587.72 -> 4265384.9 | K59: =I59-J59 -> -3927869.2 | L59: =I59+May!L59 -> 58115633 | M59: =J59+May!M59 -> 1.4279912e+08 | N59: =L59-M59 -> -84683487
B60: 41 | C60: Sun Life Prosperity Dollar Wellspring Fund, Inc. | D60: =54.975*5962282.82 -> 327776498 | E60: =54.975*24652.67 -> 1355280.5 | F60: =D60-E60 -> 3.2642122e+08 | G60: 0 | H60: 705 | I60: =54.975*10400 -> 571740 | J60: =54.975*14491.51 -> 796670.76 | K60: =I60-J60 -> -224930.76 | L60: =I60+May!L60 -> 9955414.8 | M60: =J60+May!M60 -> 17442850 | N60: =L60-M60 -> -7487435
A61: Sub total - US Currency | D61: =SUM(D57:D60) -> 2381474734 | E61: =SUM(E57:E60) -> 30724332 | F61: =SUM(F57:F60) -> 2350750401 | G61: =SUM(G57:G60) -> 1.7857515e+08 | H61: =SUM(H57:H60) -> 5154 | I61: =SUM(I57:I60) -> 909255.71 | J61: =SUM(J57:J60) -> 8442223.8 | K61: =SUM(K57:K60) -> -7532968.1 | ... N61: =SUM(N57:N60) -> -1.0272655e+08
A62: Sub total - balanced funds | D62: =D55+D61 -> 24299421607 | E62: =E55+E61 -> 2.0957568e+08 | F62: =F55+F61 -> 24089845932 | G62: =G55+G61 -> 10942826699 | H62: =H55+H61 -> 91935 | I62: =I55+I61 -> 72612140 | J62: =J55+J61 -> 84606750 | K62: =K55+K61 -> -11994611 | ... N62: =N55+N61 -> -2.13413e+08
A63: Bond Funds
A64: Primarily invested in Peso Securities (shares)
B65: 42 | C65: ALFM Peso Bond Fund, Inc. | D65: 4.1846062e+10 | E65: 2.8485591e+08 | F65: =D65-E65 -> 41561205652 | G65: 1163175720 | H65: 26216 | I65: 2.3187153e+08 | J65: 8.3122331e+08 | K65: =I65-J65 -> -5.9935178e+08 | L65: =I65+May!L65 -> 1602523790 | M65: =J65+May!M65 -> 3984059785 | N65: =L65-M65 -> -2381535995
B66: 43 | C66: ATRAM Corporate Bond Fund, Inc. (formerly, Prudentialife Fixed Income Fund, Inc.) | D66: 3.0362448e+08 | E66: 639973.64 | F66: =D66-E66 -> 3.0298451e+08 | G66: 0 | H66: 1046 | I66: 381404.78 | J66: 1263361.1 | K66: =I66-J66 -> -881956.33 | L66: =I66+May!L66 -> 24396640 | M66: =J66+May!M66 -> 15029697 | N66: =L66-M66 -> 9366943.1
B67: 44 | C67: Cocolife Fixed Income Fund, Inc. | D67: 1.1882459e+09 | E67: 23497336 | F67: =D67-E67 -> 1164748569 | G67: 0 | H67: 2055 | I67: 1507788.5 | J67: 4281729.2 | K67: =I67-J67 -> -2773940.6 | L67: =I67+May!L67 -> 1.2440476e+08 | M67: =J67+May!M67 -> 1.7961207e+08 | N67: =L67-M67 -> -55207312
B68: 45 | C68: Ekklesia Mutual Fund, Inc. | D68: 1.9522177e+08 | E68: 287743.47 | F68: =D68-E68 -> 1.9493402e+08 | G68: 4800000 | H68: 151 | I68: 166478.46 | J68: 544886.71 | K68: =I68-J68 -> -378408.25 | L68: =I68+May!L68 -> 2037298.5 | M68: =J68+May!M68 -> 2837541.5 | N68: =L68-M68 -> -800243.01
B69: 46 | C69: First Metro Save and Learn Fixed Income Fund, Inc. | D69: 1.3815668e+09 | E69: 3189231.4 | F69: =D69-E69 -> 1378377558 | G69: 0 | H69: 1875 | I69: 2585636.4 | J69: 62585939 | K69: =I69-J69 -> -60000302 | L69: =I69+May!L69 -> 26533591 | M69: =J69+May!M69 -> 1.6013186e+08 | N69: =L69-M69 -> -1.3359826e+08
B70: 47 | C70: Philam Managed Income Fund, Inc. | D70: 9.8047799e+08 | E70: 36139716 | F70: =D70-E70 -> 9.4433827e+08 | G70: 0 | H70: 536 | I70: 3042410.6 | J70: 4481728.7 | K70: =I70-J70 -> -1439318.2 | L70: =I70+May!L70 -> 20560347 | M70: =J70+May!M70 -> 67763000 | N70: =L70-M70 -> -47202654
B71: 48 | C71: Philam Bond Fund, Inc. | D71: 6278649452 | E71: 38418196 | F71: =D71-E71 -> 6240231256 | G71: 0 | H71: 5122 | I71: 22406966 | J71: 39216683 | K71: =I71-J71 -> -16809717 | L71: =I71+May!L71 -> 1.8987621e+08 | M71: =J71+May!M71 -> 3.965074e+08 | N71: =L71-M71 -> -2.0663119e+08
B72: 49 | C72: Philequity Peso Bond Fund, Inc. | D72: 3.1698649e+08 | E72: 468658.78 | F72: =D72-E72 -> 3.1651783e+08 | G72: 16443370 | H72: 4180 | I72: 3117097.4 | J72: 1110162.1 | K72: =I72-J72 -> 2006935.3 | L72: =I72+May!L72 -> 29017009 | M72: =J72+May!M72 -> 18091522 | N72: =L72-M72 -> 10925488
B73: 50 | C73: Soldivo Bond Fund, Inc. | D73: 1.0018752e+09 | E73: 2495402 | F73: =D73-E73 -> 9.9937976e+08 | G73: 0 | H73: 842 | I73: 4614966.8 | J73: 569140.95 | K73: =I73-J73 -> 4045825.9 | L73: =I73+May!L73 -> 1.0614016e+08 | M73: =J73+May!M73 -> 3970008.6 | N73: =L73-M73 -> 1.0217015e+08
B74: 51 | C74: Sun Life Prosperity Bond Fund, Inc. | D74: 4.3911149e+09 | E74: 11946368 | F74: =D74-E74 -> 4379168565 | G74: 0 | H74: 16151 | I74: 34280583 | J74: 1.0209861e+08 | K74: =I74-J74 -> -67818022 | L74: =I74+May!L74 -> 241106049 | M74: =J74+May!M74 -> 4.7106799e+08 | N74: =L74-M74 -> -2.2996195e+08
B75: 52 | C75: Sun Life Prosperity GS Fund, Inc. | D75: 1.4041298e+08 | E75: 407889.82 | F75: =D75-E75 -> 1.4000509e+08 | G75: 0 | H75: 2576 | I75: 561064.81 | J75: 547170.74 | K75: =I75-J75 -> 13894.07 | L75: =I75+May!L75 -> 4547343.8 | M75: =J75+May!M75 -> 23346793 | N75: =L75-M75 -> -18799449
A76: Sub total - Peso Currency | D76: =SUM(D65:D75) -> 58024237514 | E76: =SUM(E65:E75) -> 4.0234643e+08 | F76: =SUM(F65:F75) -> 57621891083 | G76: =SUM(G65:G75) -> 1184419090 | H76: =SUM(H65:H75) -> 60750 | I76: =SUM(I65:I75) -> 3.0453593e+08 | J76: =SUM(J65:J75) -> 1047922721 | K76: =SUM(K65:K75) -> -7.4338679e+08 | ... N76: =SUM(N65:N75) -> -2951274476
A77: Primarily invested in foreign currency securities (shares)
B78: 53 | C78: ALFM Dollar Bond Fund, Inc. | D78: =54.975*270943301.93 -> 14895108024 | E78: =54.975*784537.12 -> 43129928 | F78: =D78-E78 -> 14851978095 | G78: 0 | H78: 9547 | I78: =54.975*1738116.03 -> 95552929 | J78: =54.975*5765242.5 -> 3.1694421e+08 | K78: =I78-J78 -> -2.2139128e+08 | L78: =I78+May!L78 -> 6.5013169e+08 | M78: =J78+May!M78 -> 4199867275 | N78: =L78-M78 -> -3549735584
B79: 54 | C79: ATRAM Total Return Dollar Bond Fund, Inc. (formerly, ATR KimEng Total Return Bond Fund, Inc.) | D79: 5.7955619e+08 | E79: 1.7804221e+08 | F79: =D79-E79 -> 4.0151398e+08 | G79: 0 | H79: 198 | I79: 0 | J79: 56924524 | K79: =I79-J79 -> -56924524 | L79: =I79+May!L79 -> 18965146 | M79: =J79+May!M79 -> 3.8243801e+08 | N79: =L79-M79 -> -3.6347286e+08
B80: 55 | C80: First Metro Save and Learn Dollar Bond Fund, Inc. | D80: 7.3901231e+08 | E80: 3392875 | F80: =D80-E80 -> 7.3561944e+08 | G80: 0 | H80: 157 | I80: 2.09 | J80: 2.09 | K80: =I80-J80 -> 0 | L80: =I80+May!L80 -> 1309297.1 | M80: =J80+May!M80 -> 14565724 | N80: =L80-M80 -> -13256427
B81: 56 | C81: PAMI Global Bond Fund Phils., Inc. | D81: =54.975*1156107.86 -> 63557030 | E81: =54.975*220963.59 -> 12147473 | F81: =D81-E81 -> 51409556 | G81: 0 | H81: 26 | I81: 0 | J81: 0 | K81: =I81-J81 -> 0 | L81: =I81+May!L81 -> 684910.05 | M81: =J81+May!M81 -> 1188417 | N81: =L81-M81 -> -503506.91
B82: 57 | C82: Philam Dollar Bond Fund, Inc. | D82: =54.975*40139041.8 -> 2206643823 | E82: =54.975*-211994.07 -> -11654374 | F82: =D82-E82 -> 2218298197 | G82: 0 | H82: 2019 | I82: =54.975*1184.48 -> 65116.788 | J82: =54.975*241500.65 -> 13276498 | K82: =I82-J82 -> -13211381 | L82: =I82+May!L82 -> 2.681541e+08 | M82: =J82+May!M82 -> 70948047 | N82: =L82-M82 -> 1.9720605e+08
B83: 58 | C83: Philequity Dollar Income Fund, Inc. | D83: 2.3574076e+08 | E83: 567039.57 | F83: =D83-E83 -> 2.3517372e+08 | G83: 0 | H83: 127 | I83: 0 | J83: 0 | K83: =I83-J83 -> 0 | L83: =I83+May!L83 -> 1280795 | M83: =J83+May!M83 -> 1995692.2 | N83: =L83-M83 -> -714897.21
B84: 59 | C84: Sun Life Prosperity Dollar Abundance Fund, Inc. | D84: =54.975*9042762.56 -> 4.9712587e+08 | E84: =54.975*407647.78 -> 22410437 | F84: =D84-E84 -> 474715435 | G84: 0 | H84: 2514 | I84: =54.975*4500 -> 247387.5 | J84: =54.975*101360.86 -> 5572313.3 | K84: =I84-J84 -> -5324925.8 | L84: =I84+May!L84 -> 19310442 | M84: =J84+May!M84 -> 41560409 | N84: =L84-M84 -> -22249966
A85: Sub total - US Currency | D85: =SUM(D78:D84) -> 19216744012 | E85: =SUM(E78:E84) -> 2.4803559e+08 | F85: =SUM(F78:F84) -> 18968708419 | G85: =SUM(G78:G84) -> 0 | H85: =SUM(H78:H84) -> 14588 | I85: =SUM(I78:I84) -> 95865435 | J85: =SUM(J78:J84) -> 392717544 | K85: =SUM(K78:K84) -> -2.9685211e+08 | ... N85: =SUM(N78:N84) -> -3752727194
B86: 60 | C86: ALFM Euro Bond Fund, Inc. | D86: =57.4103925*15690542.49 -> 9.008002e+08 | E86: =57.4103925*12305.08 -> 706439.47 | F86: =D86-E86 -> 9.0009376e+08 | G86: 0 | H86: 676 | I86: =57.4103925*129296.71 -> 7422974.9 | J86: =57.4103925*351214.57 -> 20163366 | K86: =I86-J86 -> -12740391 | L86: =I86+May!L86 -> 19393736 | M86: =J86+May!M86 -> 63615096 | N86: =L86-M86 -> -44221360
A87: Sub total - Euro Currency | D87: =SUM(D86) -> 9.008002e+08 | E87: =SUM(E86) -> 706439.47 | F87: =SUM(F86) -> 9.0009376e+08 | G87: =SUM(G86) -> 0 | H87: =SUM(H86) -> 676 | I87: =SUM(I86) -> 7422974.9 | J87: =SUM(J86) -> 20163366 | K87: =SUM(K86) -> -12740391 | ... N87: =SUM(N86) -> -44221360
A88: Sub total - bond funds | D88: =D76+D85+D87 -> 78141781728 | E88: =E76+E85+E87 -> 6.5108846e+08 | F88: =F76+F85+F87 -> 77490693266 | G88: =G76+G85+G87 -> 1184419090 | H88: =H76+H85+H87 -> 76014 | I88: =I76+I85+I87 -> 4.0782434e+08 | J88: =J76+J85+J87 -> 1460803631 | K88: =K76+K85+K87 -> -1052979290 | ... N88: =N76+N85+N87 -> -6748223030
A89: Money Market Funds
A90: Primarily invested in Peso Securities (shares)
B91: 61 | C91: ALFM Money Market Fund, Inc. | D91: 6.0816478e+10 | E91: 38342497 | F91: =D91-E91 -> 60778135599 | G91: 0 | H91: 33756 | I91: 2.7794127e+09 | J91: 2.7950842e+09 | K91: =I91-J91 -> -15671534 | L91: =I91+May!L91 -> 19311482958 | M91: =J91+May!M91 -> 17844364738 | N91: =L91-M91 -> 1467118220
B92: 62 | C92: First Metro Save and Learn Money Market Fund, Inc. | D92: 2.7413651e+09 | E92: 2674853.8 | F92: =D92-E92 -> 2738690211 | G92: 0 | H92: 608 | I92: 2.1216779e+08 | J92: 3.5437285e+08 | K92: =I92-J92 -> -1.4220506e+08 | L92: =I92+May!L92 -> 1316110513 | M92: =J92+May!M92 -> 1364089377 | N92: =L92-M92 -> -47978865
B93: 63 | C93: Sun Life Prosperity Peso Starter Fund, Inc. | D93: 1.2847746e+11 | E93: 4.776316e+08 | F93: =D93-E93 -> 127999826131 | G93: 0 | H93: 60593 | I93: 1.8638553e+10 | J93: 1.975838e+10 | K93: =I93-J93 -> -1119827480 | L93: =I93+May!L93 -> 106058259692 | M93: =J93+May!M93 -> 106135643154 | N93: =L93-M93 -> -77383462
A94: Sub total - Peso Currency | D94: =SUM(D91:D93) -> 192035300887 | E94: =SUM(E91:E93) -> 5.1864895e+08 | F94: =SUM(F91:F93) -> 191516651940 | G94: =SUM(G91:G93) -> 0 | H94: =SUM(H91:H93) -> 94957 | I94: =SUM(I91:I93) -> 21630133445 | J94: =SUM(J91:J93) -> 22907837519 | K94: =SUM(K91:K93) -> -1277704074 | ... N94: =SUM(N91:N93) -> 1341755894
A95: Primarily invested in foreign currency securities (shares)
B96: 64 | C96: Sun Life Prosperity Dollar Starter Fund, Inc. | D96: =54.975*252359648.8 -> 13873471693 | E96: =54.975*2275669.07 -> 1.2510491e+08 | F96: =D96-E96 -> 13748366786 | G96: 0 | H96: 3028 | I96: =54.975*66823653.37 -> 3673630344 | J96: =54.975*70216706.82 -> 3860163457 | K96: =I96-J96 -> -1.8653311e+08 | L96: =I96+May!L96 -> 17475861781 | M96: =J96+May!M96 -> 14168645065 | N96: =L96-M96 -> 3307216716
A97: Sub total - US Currency | D97: =SUM(D96) -> 13873471693 | E97: =SUM(E96) -> 1.2510491e+08 | F97: =SUM(F96) -> 13748366786 | G97: =SUM(G96) -> 0 | H97: =SUM(H96) -> 3028 | I97: =SUM(I96) -> 3673630344 | J97: =SUM(J96) -> 3860163457 | K97: =SUM(K96) -> -1.8653311e+08 | ... N97: =SUM(N96) -> 3307216716
A98: Sub total - money market funds | D98: =D94+D97 -> 205908772579 | E98: =E94+E97 -> 6.4375385e+08 | F98: =F94+F97 -> 205265018726 | G98: =G94+G97 -> 0 | H98: =H94+H97 -> 97985 | I98: =I94+I97 -> 25303763789 | J98: =J94+J97 -> 26768000977 | K98: =K94+K97 -> -1464237188 | ... N98: =N94+N97 -> 4648972610
A99: Feeder Fund
A100: Primarily invested in Peso securities (units)
B101: 65 | C101: ALFM Global Multi-Asset Income Fund Inc. | D101: 8.8531944e+09 | E101: 11584856 | F101: =D101-E101 -> 8841609520 | G101: 0 | H101: 3671 | I101: 1.6893335e+08 | J101: 1.2346046e+08 | K101: =I101-J101 -> 45472883 | L101: =I101+May!L101 -> 2593400314 | M101: =J101+May!M101 -> 3.9487194e+08 | N101: =L101-M101 -> 2198528371
B102: 66 | C102: Sun Life Prosperity World Equity Index Feeder Fund, Inc. | D102: 3.3200603e+09 | E102: 11665950 | F102: =D102-E102 -> 3308394352 | G102: 0 | H102: 5488 | I102: 86330669 | J102: 1.7948995e+08 | K102: =I102-J102 -> -93159279 | L102: =I102+May!L102 -> 9.1373549e+08 | M102: =J102+May!M102 -> 9.045074e+08 | N102: =L102-M102 -> 9228088.7
A103: Sub total - Peso Currency | D103: =D101+D102 -> 12173254678 | E103: =E101+E102 -> 23250806 | F103: =F101+F102 -> 12150003872 | G103: =G101+G102 -> 0 | H103: =H101+H102 -> 9159 | I103: =I101+I102 -> 2.5526402e+08 | J103: =J101+J102 -> 3.0295041e+08 | K103: =K101+K102 -> -47686396 | ... N103: =N101+N102 -> 2207756460
A104: Primarily invested in foreign currency securities (units)
B105: 67 | C105: ALFM Global Multi-Asset Income Fund, Inc. | D105: =54.975*182718975.16 -> 10044975659 | E105: =54.975*798142.19 -> 43877867 | F105: =D105-E105 -> 10001097793 | G105: 0 | H105: 8406 | I105: =54.975*3039067.7 -> 1.6707275e+08 | J105: =54.975*2912898.94 -> 1.6013662e+08 | K105: =I105-J105 -> 6936127.6 | L105: =I105+May!L105 -> 1295872655 | M105: =J105+May!M105 -> 6.5795027e+08 | N105: =L105-M105 -> 6.3792239e+08
A106: Sub total - US Currency | D106: =SUM(D105) -> 10044975659 | E106: =SUM(E105) -> 43877867 | F106: =SUM(F105) -> 10001097793 | G106: =SUM(G105) -> 0 | H106: =SUM(H105) -> 8406 | I106: =SUM(I105) -> 1.6707275e+08 | J106: =SUM(J105) -> 1.6013662e+08 | K106: =SUM(K105) -> 6936127.6 | ... N106: =SUM(N105) -> 6.3792239e+08
...

Sheet Q2
A1: PHILIPPINE INVESTMENT FUNDS ASSOCIATION, INC.
A2: MUTUAL FUNDS STATISTICAL REPORT
A3: As of the Second Quarter of 2022
A4: (Amounts in Peso)
A6: Fund Category | C6: Fund Name | D6: NET ASSETS | E6: TOTAL SALES | F6: TOTAL REDEMPTIONS | G6: NET SALES
A7: Stock Funds
A8: Primarily invested in Peso Securities (shares)
B9: 1 | C9: ALFM Growth Fund, Inc. | D9: =June!F9 -> 4556571107 | E9: =Apr!I9+May!I9+June!I9 -> 48758619 | F9: =Apr!J9+May!J9+June!J9 -> 1.0777879e+08 | G9: =E9-F9 -> -59020166
B10: 2 | C10: ATRAM Alpha Opportunity Fund, Inc. (formerly, ATRKE Alpha Opportunity Fund, Inc.) | D10: =June!F10 -> 7.0701045e+08 | E10: =Apr!I10+May!I10+June!I10 -> 35525669 | F10: =Apr!J10+May!J10+June!J10 -> 49703773 | G10: =E10-F10 -> -14178104
B11: 3 | C11: ATRAM Phil. Equity Opportunity Fund, Inc. (formerly, ATRKE Equity Opportunity Fund, Inc.) | D11: =June!F11 -> 9.4958306e+08 | E11: =Apr!I11+May!I11+June!I11 -> 27757504 | F11: =Apr!J11+May!J11+June!J11 -> 81241594 | G11: =E11-F11 -> -53484089
B12: 4 | C12: Climbs Share Capital Equity Investment Fund Corp. | D12: =June!F12 -> 3.3319507e+08 | E12: =Apr!I12+May!I12+June!I12 -> 15384217 | F12: =Apr!J12+May!J12+June!J12 -> 3824663.4 | G12: =E12-F12 -> 11559554
B13: 5 | C13: First Metro Consumer Fund on MSCI Phils. IMI, Inc. | D13: =June!F13 -> 5.0225709e+08 | E13: =Apr!I13+May!I13+June!I13 -> 4279044.2 | F13: =Apr!J13+May!J13+June!J13 -> 3914004.1 | G13: =E13-F13 -> 365040.12
B14: 6 | C14: First Metro Save and Learn Equity Fund, Inc. | D14: =June!F14 -> 4010131781 | E14: =Apr!I14+May!I14+June!I14 -> 2.5493627e+08 | F14: =Apr!J14+May!J14+June!J14 -> 69565271 | G14: =E14-F14 -> 1.8537099e+08
B15: 7 | C15: First Metro Save and Learn Phil. Index Fund, Inc. (formerly, One Wealthy Nation Fund, Inc.) | D15: =June!F15 -> 87203598 | E15: =Apr!I15+May!I15+June!I15 -> 8784298.3 | F15: =Apr!J15+May!J15+June!J15 -> 2291446.5 | G15: =E15-F15 -> 6492851.8
B16: 8 | C16: MBG Equity Investment Fund, Inc. | D16: =June!F16 -> 1.1857377e+08 | E16: =Apr!I16+May!I16+June!I16 -> 0 | F16: =Apr!J16+May!J16+June!J16 -> 6470778.8 | G16: =E16-F16 -> -6470778.8
B17: 9 | C17: PAMI Equity Index Fund, Inc. | D17: =June!F17 -> 15565823898 | E17: =Apr!I17+May!I17+June!I17 -> 5.413538e+08 | F17: =Apr!J17+May!J17+June!J17 -> 30155261 | G17: =E17-F17 -> 5.1119854e+08
B18: 10 | C18: Philam Strategic Growth Fund, Inc. | D18: =June!F18 -> 30765913816 | E18: =Apr!I18+May!I18+June!I18 -> 2.9534146e+08 | F18: =Apr!J18+May!J18+June!J18 -> 1.2176206e+08 | G18: =E18-F18 -> 1.7357941e+08
B19: 11 | C19: Philequity Dividend Yield Fund, Inc. | D19: =June!F19 -> 2104516217 | E19: =Apr!I19+May!I19+June!I19 -> 33066302 | F19: =Apr!J19+May!J19+June!J19 -> 58621735 | G19: =E19-F19 -> -25555433
B20: 12 | C20: Philequity Fund, Inc. | D20: =June!F20 -> 9235252023 | E20: =Apr!I20+May!I20+June!I20 -> 85661987 | F20: =Apr!J20+May!J20+June!J20 -> 1.4260767e+08 | G20: =E20-F20 -> -56945686
... B27: 19 | C27: United Fund, Inc. | D27: =June!F27 -> 5.6584558e+08 | E27: =Apr!I27+May!I27+June!I27 -> 3029052.7 | F27: =Apr!J27+May!J27+June!J27 -> 3776537.8 | G27: =E27-F27 -> -747485.09
A28: Primarily invested in Peso Securities (units) | F28: =Apr!J28+May!J28+June!J28 -> 0
B29: 20 | C29: Philequity Alpha One Fund, Inc. | D29: =June!F29 -> 3.2728444e+08 | E29: =Apr!I29+May!I29+June!I29 -> 23047697 | F29: =Apr!J29+May!J29+June!J29 -> 16530213 | G29: =E29-F29 -> 6517484.2
B30: 21 | C30: Philippine Stock Index Fund Corp. | D30: =June!F30 -> 3.444222e+08 | E30: =Apr!I30+May!I30+June!I30 -> 1.8139591e+08 | F30: =Apr!J30+May!J30+June!J30 -> 49531046 | G30: =E30-F30 -> 1.3186487e+08
A31: Exchange Traded Fund | F31: =Apr!J31+May!J31+June!J31 -> 0
B32: 22 | C32: First Metro Phil. Equity Exchange Traded Fund, Inc. | D32: =June!F32 -> 1995137252 | E32: =Apr!I32+May!I32+June!I32 -> 69792179 | F32: =Apr!J32+May!J32+June!J32 -> 9240460 | G32: =E32-F32 -> 60551719
A33: Sub total - Peso Currency | D33: =SUM(D9:D32) -> 104907678044 | E33: =SUM(E9:E32) -> 3364222220 | F33: =SUM(F9:F32) -> 1821904145 | G33: =SUM(G9:G32) -> 1542318075
A34: Primarily invested in foreign currency securities (shares)
B35: 23 | C35: ATRAM AsiaPlus Equity Fund, Inc. (formerly, ATR KimEng AsiaPlus Recovery Fund, Inc.) | D35: =June!F35 -> 40237187 | E35: =Apr!I35+May!I35+June!I35 -> 596148.42 | F35: =Apr!J35+May!J35+June!J35 -> 11971.03 | G35: =E35-F35 -> 584177.39
B36: 24 | C36: Sun Life Prosperity World Voyager Fund, Inc. | D36: =June!F36 -> 1889369948 | E36: =Apr!I36+May!I36+June!I36 -> 35921981 | F36: =Apr!J36+May!J36+June!J36 -> 48146529 | G36: =E36-F36 -> -12224548
A37: Sub total - US Currency | D37: =SUM(D35:D36) -> 1929607134 | E37: =SUM(E35:E36) -> 36518129 | F37: =SUM(F35:F36) -> 48158500 | G37: =SUM(G35:G36) -> -11640370
A38: Sub total - stock funds | D38: =D33+D37 -> 106837285179 | E38: =E33+E37 -> 3400740349 | F38: =F33+F37 -> 1870062645 | G38: =G33+G37 -> 1530677705
A39: Balanced Funds
A40: Primarily invested in Peso Securities (shares)
B41: 25 | C41: ATRAM Dynamic Allocation Fund, Inc. (formerly, Optima Balanced Fund, Inc.) | D41: =June!F41 -> 1.1922934e+08 | E41: =Apr!I41+May!I41+June!I41 -> 3493883.8 | F41: =Apr!J41+May!J41+June!J41 -> 1122960.4 | G41: =E41-F41 -> 2370923.5
B42: 26 | C42: ATRAM Philippine Balanced Fund, Inc. (formerly, ATRKE Philippine Balanced Fund, Inc.) | D42: =June!F42 -> 6.0866634e+08 | E42: =Apr!I42+May!I42+June!I42 -> 4767797.4 | F42: =Apr!J42+May!J42+June!J42 -> 10168224 | G42: =E42-F42 -> -5400426.2
B43: 27 | C43: First Metro Save and Learn Balanced Fund, Inc. | D43: =June!F43 -> 1065042000 | E43: =Apr!I43+May!I43+June!I43 -> 7175451.1 | F43: =Apr!J43+May!J43+June!J43 -> 41220902 | G43: =E43-F43 -> -34045450
B44: 28 | C44: First Metro Save and Learn F.O.C.C.U.S. Dynamic Fund, Inc. | D44: =June!F44 -> 2.8414903e+08 | E44: =Apr!I44+May!I44+June!I44 -> 67000415 | F44: =Apr!J44+May!J44+June!J44 -> 2655866 | G44: =E44-F44 -> 64344549
B45: 29 | C45: NCM Mutual Fund of the Phils., Inc. | D45: =June!F45 -> 3.2800211e+08 | E45: =Apr!I45+May!I45+June!I45 -> 0 | F45: =Apr!J45+May!J45+June!J45 -> 1772670.4 | G45: =E45-F45 -> -1772670.4
B46: 30 | C46: PAMI Horizon Fund, Inc. | D46: =June!F46 -> 5.5605515e+08 | E46: =Apr!I46+May!I46+June!I46 -> 2842117.8 | F46: =Apr!J46+May!J46+June!J46 -> 11083780 | G46: =E46-F46 -> -8241662.5
B47: 31 | C47: Philam Fund, Inc. | D47: =June!F47 -> 10177055214 | E47: =Apr!I47+May!I47+June!I47 -> 65733192 | F47: =Apr!J47+May!J47+June!J47 -> 59535776 | G47: =E47-F47 -> 6197416.5
B48: 32 | C48: Solidaritas Fund, Inc. (formerly, Bahay Pari Solidaritas Fund, Inc.) | D48: =June!F48 -> 133750155 | E48: =Apr!I48+May!I48+June!I48 -> 3062892.8 | F48: =Apr!J48+May!J48+June!J48 -> 3415300.2 | G48: =E48-F48 -> -352407.39
B49: 33 | C49: Sun Life Prosperity Balanced Fund, Inc. | D49: =June!F49 -> 7179999857 | E49: =Apr!I49+May!I49+June!I49 -> 46089650 | F49: =Apr!J49+May!J49+June!J49 -> 1.2579594e+08 | G49: =E49-F49 -> -79706289
B50: 34 | C50: Sun Life Prosperity Dynamic Fund, Inc. | D50: =June!F50 -> 1123169883 | E50: =Apr!I50+May!I50+June!I50 -> 0 | F50: =Apr!J50+May!J50+June!J50 -> 15113829 | G50: =E50-F50 -> -15113829
A51: Primarily invested in Peso Securities (units)
B52: 35 | C52: Sun Life Prosperity Achiever Fund 2028, Inc. | D52: =June!F52 -> 68801812 | E52: =Apr!I52+May!I52+June!I52 -> 1554987.9 | F52: =Apr!J52+May!J52+June!J52 -> 599851.19 | G52: =E52-F52 -> 955136.72
B53: 36 | C53: Sun Life Prosperity Achiever Fund 2038, Inc. | D53: =June!F53 -> 51524796 | E53: =Apr!I53+May!I53+June!I53 -> 1010697.4 | F53: =Apr!J53+May!J53+June!J53 -> 155767.88 | G53: =E53-F53 -> 854929.54
B54: 37 | C54: Sun Life Prosperity Achiever Fund 2048, Inc. | D54: =June!F54 -> 43649846 | E54: =Apr!I54+May!I54+June!I54 -> 366081.3 | F54: =Apr!J54+May!J54+June!J54 -> 61571.83 | G54: =E54-F54 -> 304509.47
A55: Sub total - Peso Currency | D55: =SUM(D41:D54) -> 21739095531 | E55: =SUM(E41:E54) -> 2.0309717e+08 | F55: =SUM(F41:F54) -> 2.7270244e+08 | G55: =SUM(G41:G54) -> -69605271
A56: Primarily invested in foreign currency securities (shares)
B57: 38 | C57: Cocolife Dollar Fund Builder, Inc. | D57: =June!F57 -> 71944678 | E57: =Apr!I57+May!I57+June!I57 -> 0 | F57: =Apr!J57+May!J57+June!J57 -> 3554243.9 | G57: =E57-F57 -> -3554243.9
B58: 39 | C58: PAMI Asia Balanced Fund, Inc. | D58: =June!F58 -> 3.39603e+08 | E58: =Apr!I58+May!I58+June!I58 -> 20955.332 | F58: =Apr!J58+May!J58+June!J58 -> 4229866.5 | G58: =E58-F58 -> -4208911.1
B59: 40 | C59: Sun Life Prosperity Dollar Advantage Fund, Inc. | D59: =June!F59 -> 1612781509 | E59: =Apr!I59+May!I59+June!I59 -> 5207955.3 | F59: =Apr!J59+May!J59+June!J59 -> 46036585 | G59: =E59-F59 -> -40828629
B60: 41 | C60: Sun Life Prosperity Dollar Wellspring Fund, Inc. | D60: =June!F60 -> 3.2642122e+08 | E60: =Apr!I60+May!I60+June!I60 -> 8170985.7 | F60: =Apr!J60+May!J60+June!J60 -> 8904157 | G60: =E60-F60 -> -733171.24
A61: Sub total - US Currency | D61: =SUM(D57:D60) -> 2350750401 | E61: =SUM(E57:E60) -> 13399896 | F61: =SUM(F57:F60) -> 62724852 | G61: =SUM(G57:G60) -> -49324956
A62: Sub total - balanced funds | D62: =D55+D61 -> 24089845932 | E62: =E55+E61 -> 2.1649706e+08 | F62: =F55+F61 -> 3.3542729e+08 | G62: =G55+G61 -> -1.1893023e+08
A63: Bond Funds
A64: Primarily invested in Peso Securities (shares)
B65: 42 | C65: ALFM Peso Bond Fund, Inc. | D65: =June!F65 -> 41561205652 | E65: =Apr!I65+May!I65+June!I65 -> 7.0014691e+08 | F65: =Apr!J65+May!J65+June!J65 -> 1988181666 | G65: =E65-F65 -> -1288034752
B66: 43 | C66: ATRAM Corporate Bond Fund, Inc. (formerly, Prudentialife Fixed Income Fund, Inc.) | D66: =June!F66 -> 3.0298451e+08 | E66: =Apr!I66+May!I66+June!I66 -> 7999694.3 | F66: =Apr!J66+May!J66+June!J66 -> 6544145.4 | G66: =E66-F66 -> 1455548.9
B67: 44 | C67: Cocolife Fixed Income Fund, Inc. | D67: =June!F67 -> 1164748569 | E67: =Apr!I67+May!I67+June!I67 -> 5827886.3 | F67: =Apr!J67+May!J67+June!J67 -> 138908844 | G67: =E67-F67 -> -1.3308096e+08
B68: 45 | C68: Ekklesia Mutual Fund, Inc. | D68: =June!F68 -> 1.9493402e+08 | E68: =Apr!I68+May!I68+June!I68 -> 612854.42 | F68: =Apr!J68+May!J68+June!J68 -> 1719324.5 | G68: =E68-F68 -> -1106470
B69: 46 | C69: First Metro Save and Learn Fixed Income Fund, Inc. | D69: =June!F69 -> 1378377558 | E69: =Apr!I69+May!I69+June!I69 -> 7225846.7 | F69: =Apr!J69+May!J69+June!J69 -> 1.008944e+08 | G69: =E69-F69 -> -93668556
B70: 47 | C70: Philam Managed Income Fund, Inc. | D70: =June!F70 -> 9.4433827e+08 | E70: =Apr!I70+May!I70+June!I70 -> 13567765 | F70: =Apr!J70+May!J70+June!J70 -> 11016648 | G70: =E70-F70 -> 2551116.4
B71: 48 | C71: Philam Bond Fund, Inc. | D71: =June!F71 -> 6240231256 | E71: =Apr!I71+May!I71+June!I71 -> 72202747 | F71: =Apr!J71+May!J71+June!J71 -> 1.9155147e+08 | G71: =E71-F71 -> -1.1934873e+08
B72: 49 | C72: Philequity Peso Bond Fund, Inc. | D72: =June!F72 -> 3.1651783e+08 | E72: =Apr!I72+May!I72+June!I72 -> 14082636 | F72: =Apr!J72+May!J72+June!J72 -> 10158817 | G72: =E72-F72 -> 3923818.4
B73: 50 | C73: Soldivo Bond Fund, Inc. | D73: =June!F73 -> 9.9937976e+08 | E73: =Apr!I73+May!I73+June!I73 -> 99314844 | F73: =Apr!J73+May!J73+June!J73 -> 2022334.4 | G73: =E73-F73 -> 97292510
B74: 51 | C74: Sun Life Prosperity Bond Fund, Inc. | D74: =June!F74 -> 4379168565 | E74: =Apr!I74+May!I74+June!I74 -> 1.0930718e+08 | F74: =Apr!J74+May!J74+June!J74 -> 2.7958277e+08 | G74: =E74-F74 -> -1.7027559e+08
B75: 52 | C75: Sun Life Prosperity GS Fund, Inc. | D75: =June!F75 -> 1.4000509e+08 | E75: =Apr!I75+May!I75+June!I75 -> 1472216.7 | F75: =Apr!J75+May!J75+June!J75 -> 14453213 | G75: =E75-F75 -> -12980997
A76: Sub total - Peso Currency | D76: =SUM(D65:D75) -> 57621891083 | E76: =SUM(E65:E75) -> 1031760588 | F76: =SUM(F65:F75) -> 2745033641 | G76: =SUM(G65:G75) -> -1713273053
A77: Primarily invested in foreign currency securities (shares)
B78: 53 | C78: ALFM Dollar Bond Fund, Inc. | D78: =June!F78 -> 14851978095 | E78: =Apr!I78+May!I78+June!I78 -> 2.9929549e+08 | F78: =Apr!J78+May!J78+June!J78 -> 8.6019264e+08 | G78: =E78-F78 -> -5.6089714e+08
B79: 54 | C79: ATRAM Total Return Dollar Bond Fund, Inc. (formerly, ATR KimEng Total Return Bond Fund, Inc.) | D79: =June!F79 -> 4.0151398e+08 | E79: =Apr!I79+May!I79+June!I79 -> 9881050.5 | F79: =Apr!J79+May!J79+June!J79 -> 2.2409107e+08 | G79: =E79-F79 -> -2.1421002e+08
B80: 55 | C80: First Metro Save and Learn Dollar Bond Fund, Inc. | D80: =June!F80 -> 7.3561944e+08 | E80: =Apr!I80+May!I80+June!I80 -> 257468.02 | F80: =Apr!J80+May!J80+June!J80 -> 8999280.8 | G80: =E80-F80 -> -8741812.8
B81: 56 | C81: PAMI Global Bond Fund Phils., Inc. | D81: =June!F81 -> 51409556 | E81: =Apr!I81+May!I81+June!I81 -> 684910.05 | F81: =Apr!J81+May!J81+June!J81 -> 827148.54 | G81: =E81-F81 -> -142238.49
B82: 57 | C82: Philam Dollar Bond Fund, Inc. | D82: =June!F82 -> 2218298197 | E82: =Apr!I82+May!I82+June!I82 -> 220381.64 | F82: =Apr!J82+May!J82+June!J82 -> 45485936 | G82: =E82-F82 -> -45265554
B83: 58 | C83: Philequity Dollar Income Fund, Inc. | D83: =June!F83 -> 2.3517372e+08 | E83: =Apr!I83+May!I83+June!I83 -> 261400 | F83: =Apr!J83+May!J83+June!J83 -> 427761.3 | G83: =E83-F83 -> -166361.3
B84: 59 | C84: Sun Life Prosperity Dollar Abundance Fund, Inc. | D84: =June!F84 -> 474715435 | E84: =Apr!I84+May!I84+June!I84 -> 714337.69 | F84: =Apr!J84+May!J84+June!J84 -> 9908348.6 | G84: =E84-F84 -> -9194010.9
A85: Sub total - US Currency | D85: =SUM(D78:D84) -> 18968708419 | E85: =SUM(E78:E84) -> 3.1131504e+08 | F85: =SUM(F78:F84) -> 1149932185 | G85: =SUM(G78:G84) -> -8.3861714e+08
B86: 60 | C86: ALFM Euro Bond Fund, Inc. | D86: =June!F86 -> 9.0009376e+08 | E86: =Apr!I86+May!I86+June!I86 -> 14188078 | F86: =Apr!J86+May!J86+June!J86 -> 41765475 | G86: =E86-F86 -> -27577396
A87: Sub total - Euro Currency | D87: =SUM(D86) -> 9.0009376e+08 | E87: =SUM(E86) -> 14188078 | F87: =SUM(F86) -> 41765475 | G87: =SUM(G86) -> -27577396
A88: Sub total - bond funds | D88: =D76+D85+D87 -> 77490693266 | E88: =E76+E85+E87 -> 1357263707 | F88: =F76+F85+F87 -> 3936731301 | G88: =G76+G85+G87 -> -2579467594
A89: Money Market Funds
A90: Primarily invested in Peso Securities (shares)
B91: 61 | C91: ALFM Money Market Fund, Inc. | D91: =June!F91 -> 60778135599 | E91: =Apr!I91+May!I91+June!I91 -> 8673068090 | F91: =Apr!J91+May!J91+June!J91 -> 8709094641 | G91: =E91-F91 -> -36026552
B92: 62 | C92: First Metro Save and Learn Money Market Fund, Inc. | D92: =June!F92 -> 2738690211 | E92: =Apr!I92+May!I92+June!I92 -> 4.7036237e+08 | F92: =Apr!J92+May!J92+June!J92 -> 8.1770093e+08 | G92: =E92-F92 -> -347338559
B93: 63 | C93: Sun Life Prosperity Peso Starter Fund, Inc. | D93: =June!F93 -> 127999826131 | E93: =Apr!I93+May!I93+June!I93 -> 54987363659 | F93: =Apr!J93+May!J93+June!J93 -> 53614873572 | G93: =E93-F93 -> 1372490088
A94: Sub total - Peso Currency | D94: =SUM(D91:D93) -> 191516651940 | E94: =SUM(E91:E93) -> 64130794117 | F94: =SUM(F91:F93) -> 63141669139 | G94: =SUM(G91:G93) -> 989124977
A95: Primarily invested in foreign currency securities (shares)
B96: 64 | C96: Sun Life Prosperity Dollar Starter Fund, Inc. | D96: =June!F96 -> 13748366786 | E96: =Apr!I96+May!I96+June!I96 -> 10290435996 | F96: =Apr!J96+May!J96+June!J96 -> 8229651278 | G96: =E96-F96 -> 2060784718
A97: Sub total - US Currency | D97: =SUM(D96) -> 13748366786 | E97: =SUM(E96) -> 10290435996 | F97: =SUM(F96) -> 8229651278 | G97: =SUM(G96) -> 2060784718
A98: Sub total - money market funds | D98: =D94+D97 -> 205265018726 | E98: =E94+E97 -> 74421230112 | F98: =F94+F97 -> 71371320418 | G98: =G94+G97 -> 3049909695
A99: Feeder Fund
A100: Primarily invested in Peso securities (units)
B101: 65 | C101: ALFM Global Multi-Asset Income Fund Inc. | D101: =June!F101 -> 8841609520 | E101: =Apr!I101+May!I101+June!I101 -> 7.9044731e+08 | F101: =Apr!J101+May!J101+June!J101 -> 2.8538427e+08 | G101: =E101-F101 -> 505063041
B102: 66 | C102: Sun Life Prosperity World Equity Index Feeder Fund, Inc. | D102: =June!F102 -> 3308394352 | E102: =Apr!I102+May!I102+June!I102 -> 2.483949e+08 | F102: =Apr!J102+May!J102+June!J102 -> 2.788839e+08 | G102: =E102-F102 -> -30489006
A103: Sub total - Peso Currency | D103: =SUM(D101:D102) -> 12150003872 | E103: =SUM(E101:E102) -> 1038842202 | F103: =SUM(F101:F102) -> 564268167 | G103: =SUM(G101:G102) -> 4.7457404e+08
A104: Primarily invested in foreign currency securities (units)
B105: 67 | C105: ALFM Global Multi-Asset Income Fund, Inc. | D105: =June!F105 -> 10001097793 | E105: =Apr!I105+May!I105+June!I105 -> 6.2171549e+08 | F105: =Apr!J105+May!J105+June!J105 -> 3.2227801e+08 | G105: =E105-F105 -> 2.9943749e+08
A106: Sub total - US Currency | D106: =SUM(D105) -> 10001097793 | E106: =SUM(E105) -> 6.2171549e+08 | F106: =SUM(F105) -> 3.2227801e+08 | G106: =SUM(G105) -> 2.9943749e+08
A107: Sub total - feeder fund | D107: =D103+D106 -> 22151101664 | E107: =E103+E106 -> 1660557696 | F107: =F103+F106 -> 8.8654618e+08 | G107: =G103+G106 -> 774011521
...

Sheet July
A1: PHILIPPINE INVESTMENT FUNDS ASSOCIATION, INC.
A2: MUTUAL FUNDS STATISTICAL REPORT
A3: Month of July 2022
A4: (Amounts in Peso)
I5: F O R - T H E - M O N T H | L5: Y E A R - T O - D A T E
A6: Fund Category | C6: Fund Name | D6: ASSETS | E6: LIABILITIES | F6: NET ASSETS | G6: EQUITY INV. | H6: NO. OF A/C | I6: SALES | J6: REDEMPTIONS | K6: NET SALES | L6: TOTAL SALES | M6: TOTAL REDEMPTIONS | N6: TOTAL NET SALES
A7: Stock Funds
A8: Primarily invested in Peso Securities (shares)
B9: 1 | C9: ALFM Growth Fund, Inc. | D9: 4.6725879e+09 | E9: 46785048 | F9: =D9-E9 -> 4625802887 | G9: 4.1001639e+09 | H9: 7495 | I9: 14921777 | J9: 28610311 | K9: =I9-J9 -> -13688535 | L9: =I9+June!L9 -> 1.1731188e+08 | M9: =J9+June!M9 -> 2.8661557e+08 | N9: =L9-M9 -> -169303695
B10: 2 | C10: ATRAM Alpha Opportunity Fund, Inc. (formerly, ATRKE Alpha Opportunity Fund, Inc.) | D10: 7.2764796e+08 | E10: 17125744 | F10: =D10-E10 -> 7.1052221e+08 | G10: 6.7250829e+08 | H10: 4271 | I10: 4854823.1 | J10: 3935400.5 | K10: =I10-J10 -> 919422.59 | L10: =I10+June!L10 -> 1.8574302e+08 | M10: =J10+June!M10 -> 1.2760917e+08 | N10: =L10-M10 -> 58133855
B11: 3 | C11: ATRAM Phil. Equity Opportunity Fund, Inc. (formerly, ATRKE Equity Opportunity Fund, Inc.) | D11: 9.874183e+08 | E11: 19034864 | F11: =D11-E11 -> 9.6838344e+08 | G11: 905084674 | H11: 2770 | I11: 8490138.3 | J11: 8399410 | K11: =I11-J11 -> 90728.31 | L11: =I11+June!L11 -> 82796251 | M11: =J11+June!M11 -> 1.2304008e+08 | N11: =L11-M11 -> -40243831
B12: 4 | C12: Climbs Share Capital Equity Investment Fund Corp. | D12: 3.4211828e+08 | E12: 6736945.2 | F12: =D12-E12 -> 3.3538133e+08 | G12: 2.0878393e+08 | H12: 1659 | I12: 1086468.4 | J12: 234551.84 | K12: =I12-J12 -> 851916.59 | L12: =I12+June!L12 -> 21537379 | M12: =J12+June!M12 -> 10346719 | N12: =L12-M12 -> 11190661
B13: 5 | C13: First Metro Consumer Fund on MSCI Phils. IMI, Inc. | D13: 5.1569046e+08 | E13: 5713271.2 | F13: =D13-E13 -> 5.0997719e+08 | G13: 2.4063669e+08 | H13: 1484 | I13: 646345.05 | J13: 271003.1 | K13: =I13-J13 -> 375341.95 | L13: =I13+June!L13 -> 22890876 | M13: =J13+June!M13 -> 14279400 | N13: =L13-M13 -> 8611476.4
B14: 6 | C14: First Metro Save and Learn Equity Fund, Inc. | D14: 4.1894627e+09 | E14: 1.0028313e+08 | F14: =D14-E14 -> 4089179587 | G14: 3.1696036e+09 | H14: 16471 | I14: 9142275.7 | J14: 6714863.6 | K14: =I14-J14 -> 2427412.1 | L14: =I14+June!L14 -> 5.0791257e+08 | M14: =J14+June!M14 -> 3.2429492e+08 | N14: =L14-M14 -> 1.8361765e+08
B15: 7 | C15: First Metro Save and Learn Phil. Index Fund, Inc. (formerly, One Wealthy Nation Fund, Inc.) | D15: 91485525 | E15: 555198.47 | F15: =D15-E15 -> 90930327 | G15: 87223624 | H15: 557 | I15: 1981424 | J15: 224716.12 | K15: =I15-J15 -> 1756707.9 | L15: =I15+June!L15 -> 16657912 | M15: =J15+June!M15 -> 6654123 | N15: =L15-M15 -> 10003789
B16: 8 | C16: MBG Equity Investment Fund, Inc. | D16: 1.2037608e+08 | E16: 1729784.7 | F16: =D16-E16 -> 1.1864629e+08 | G16: 1.1027767e+08 | H16: 52 | I16: 200100 | J16: 660645.85 | K16: =I16-J16 -> -460545.85 | L16: =I16+June!L16 -> 1800100 | M16: =J16+June!M16 -> 8081424.7 | N16: =L16-M16 -> -6281324.7
B17: 9 | C17: PAMI Equity Index Fund, Inc. | D17: 1.6030918e+10 | E17: 1.4412111e+10 | F17: =D17-E17 -> 1618807305 | G17: 1.6484806e+09 | H17: 12626 | I17: 1.4974655e+08 | J17: 1.4294588e+10 | K17: =I17-J17 -> -14144841341 | L17: =I17+June!L17 -> 1343659286 | M17: =J17+June!M17 -> 14377102468 | N17: =L17-M17 -> -13033443182
B18: 10 | C18: Philam Strategic Growth Fund, Inc. | D18: 8.7441107e+09 | E18: 2.0994938e+08 | F18: =D18-E18 -> 8534161344 | G18: 7.6285938e+09 | H18: 12524 | I18: 68741469 | J18: 2.2475328e+10 | K18: =I18-J18 -> -22406586387 | L18: =I18+June!L18 -> 6.8416439e+08 | M18: =J18+June!M18 -> 22971191084 | N18: =L18-M18 -> -22287026698
B19: 11 | C19: Philequity Dividend Yield Fund, Inc. | D19: 2.0976082e+09 | E19: 2443473.9 | F19: =D19-E19 -> 2095164676 | G19: 1.8306797e+09 | H19: 5700 | I19: 3284269 | J19: 1827411.6 | K19: =I19-J19 -> 1456857.4 | L19: =I19+June!L19 -> 1.0127208e+08 | M19: =J19+June!M19 -> 2.6682224e+08 | N19: =L19-M19 -> -1.6555016e+08
B20: 12 | C20: Philequity Fund, Inc. | D20: 9.4558387e+09 | E20: 18287972 | F20: =D20-E20 -> 9437550718 | G20: 8.6451516e+09 | H20: 36841 | I20: 14894752 | J20: 20810715 | K20: =I20-J20 -> -5915962.9 | L20: =I20+June!L20 -> 2.0072968e+08 | M20: =J20+June!M20 -> 3.4839413e+08 | N20: =L20-M20 -> -1.4766446e+08
... B27: 19 | C27: United Fund, Inc. | D27: 5.773233e+08 | E27: 3017516.6 | F27: =D27-E27 -> 5.7430578e+08 | G27: 5.2194445e+08 | H27: 1306 | I27: 455145.05 | J27: 864618.78 | K27: =I27-J27 -> -409473.73 | L27: =I27+June!L27 -> 13218575 | M27: =J27+June!M27 -> 8051586.6 | N27: =L27-M27 -> 5166988
A28: Primarily invested in Peso Securities (units)
B29: 20 | C29: Philequity Alpha One Fund, Inc. | D29: 3.4068633e+08 | E29: 12982570 | F29: =D29-E29 -> 3.2770376e+08 | G29: 2.7615957e+08 | H29: 1449 | I29: 1448764.9 | J29: 229880.08 | K29: =I29-J29 -> 1218884.8 | L29: =I29+June!L29 -> 74990241 | M29: =J29+June!M29 -> 26134864 | N29: =L29-M29 -> 48855377
B30: 21 | C30: Philippine Stock Index Fund Corp. | D30: 3.9897923e+08 | E30: 9089782.3 | F30: =D30-E30 -> 389889447 | G30: 3.8846575e+08 | H30: 248138 | I30: 42670507 | J30: 6086609.7 | K30: =I30-J30 -> 36583897 | L30: =I30+June!L30 -> 5.1602409e+08 | M30: =J30+June!M30 -> 82833818 | N30: =L30-M30 -> 4.3319028e+08
A31: Exchange Traded Fund
B32: 22 | C32: First Metro Phil. Equity Exchange Traded Fund, Inc. | D32: 2.4016807e+09 | E32: 1.7503103e+08 | F32: =D32-E32 -> 2226649697 | G32: 2.2296456e+09 | H32: 3261 | I32: 184437940 | J32: 960464 | K32: =I32-J32 -> 183477476 | L32: =I32+June!L32 -> 291511505 | M32: =J32+June!M32 -> 14643849 | N32: =L32-M32 -> 276867656
A33: Sub total - Peso Currency | D33: =SUM(D9:D32) -> 85534586830 | E33: =SUM(E9:E32) -> 15332957829 | F33: =SUM(F9:F32) -> 70201629001 | G33: =SUM(G9:G32) -> 65804131654 | H33: =SUM(H9:H32) -> 531381 | I33: =SUM(I9:I32) -> 7.9225334e+08 | J33: =SUM(J9:J32) -> 37073978042 | K33: =SUM(K9:K32) -> -36281724699 | ... N33: =SUM(N9:N32) -> -34319780505
A34: Primarily invested in foreign currency securities (shares)
B35: 23 | C35: ATRAM AsiaPlus Equity Fund, Inc. (formerly, ATR KimEng AsiaPlus Recovery Fund, Inc.) | D35: 40156086 | E35: 929467.54 | F35: =D35-E35 -> 39226619 | G35: 0 | H35: 57 | I35: 32985.38 | J35: 0 | K35: =I35-J35 -> 32985.38 | L35: =I35+June!L35 -> 961589.08 | M35: =J35+June!M35 -> 5540208 | N35: =L35-M35 -> -4578618.9
B36: 24 | C36: Sun Life Prosperity World Voyager Fund, Inc. | D36: =55.13*35950246.72 -> 1981937102 | E36: =55.13*1384465.85 -> 76325602 | F36: =D36-E36 -> 1905611499 | G36: 0 | H36: 2819 | I36: =55.13*87975.77 -> 4850104.2 | J36: =55.13*690439.65 -> 38063938 | K36: =I36-J36 -> -33213834 | L36: =I36+June!L36 -> 2.5613199e+08 | M36: =J36+June!M36 -> 2.5948725e+08 | N36: =L36-M36 -> -3355258.6
A37: Sub total - US Currency | D37: =SUM(D35:D36) -> 2022093188 | E37: =SUM(E35:E36) -> 77255070 | F37: =SUM(F35:F36) -> 1944838118 | G37: =SUM(G35:G36) -> 0 | H37: =SUM(H35:H36) -> 2876 | I37: =SUM(I35:I36) -> 4883089.6 | J37: =SUM(J35:J36) -> 38063938 | K37: =SUM(K35:K36) -> -33180848 | ... N37: =SUM(N35:N36) -> -7933877.5
A38: Sub total - stock funds | D38: =D33+D37 -> 87556680018 | E38: =E33+E37 -> 15410212899 | F38: =F33+F37 -> 72146467119 | G38: =G33+G37 -> 65804131654 | H38: =H33+H37 -> 534257 | I38: =I33+I37 -> 7.9713643e+08 | J38: =J33+J37 -> 37112041980 | K38: =K33+K37 -> -36314905547 | ... N38: =N33+N37 -> -34327714382
A39: Balanced Funds
A40: Primarily invested in Peso Securities (shares)
B41: 25 | C41: ATRAM Dynamic Allocation Fund, Inc. (formerly, Optima Balanced Fund, Inc.) | D41: 1.2377735e+08 | E41: 917736.31 | F41: =D41-E41 -> 1.2285962e+08 | G41: 30025270 | H41: 729 | I41: 398023.58 | J41: 272293.83 | K41: =I41-J41 -> 125729.75 | L41: =I41+June!L41 -> 9464005.7 | M41: =J41+June!M41 -> 3896417.8 | N41: =L41-M41 -> 5567587.9
B42: 26 | C42: ATRAM Philippine Balanced Fund, Inc. (formerly, ATRKE Philippine Balanced Fund, Inc.) | D42: 6.2924423e+08 | E42: 1501038.2 | F42: =D42-E42 -> 6.2774319e+08 | G42: 2.3202781e+08 | H42: 2461 | I42: 701595.17 | J42: 1121767.9 | K42: =I42-J42 -> -420172.7 | L42: =I42+June!L42 -> 11512162 | M42: =J42+June!M42 -> 36800344 | N42: =L42-M42 -> -25288182
B43: 27 | C43: First Metro Save and Learn Balanced Fund, Inc. | D43: 1.1001868e+09 | E43: 13927892 | F43: =D43-E43 -> 1086258870 | G43: 4.556804e+08 | H43: 4811 | I43: 10347262 | J43: 2900083.2 | K43: =I43-J43 -> 7447178.5 | L43: =I43+June!L43 -> 27789828 | M43: =J43+June!M43 -> 1.6751309e+08 | N43: =L43-M43 -> -1.3972326e+08
B44: 28 | C44: First Metro Save and Learn F.O.C.C.U.S. Dynamic Fund, Inc. | D44: 2.9952912e+08 | E44: 6080191 | F44: =D44-E44 -> 2.9344893e+08 | G44: 1.2386342e+08 | H44: 208 | I44: 3210470.1 | J44: 24530.75 | K44: =I44-J44 -> 3185939.4 | L44: =I44+June!L44 -> 300315648 | M44: =J44+June!M44 -> 14062037 | N44: =L44-M44 -> 2.8625361e+08
B45: 29 | C45: NCM Mutual Fund of the Phils., Inc. | D45: 3.3250175e+08 | E45: 1335752.3 | F45: =D45-E45 -> 331166002 | G45: 152026791 | H45: 56 | I45: 0 | J45: 0 | K45: =I45-J45 -> 0 | L45: =I45+June!L45 -> 0 | M45: =J45+June!M45 -> 2789770.4 | N45: =L45-M45 -> -2789770.4
B46: 30 | C46: PAMI Horizon Fund, Inc. | D46: 5.7254368e+08 | E46: 18407383 | F46: =D46-E46 -> 5.541363e+08 | G46: 2.7090523e+08 | H46: 10209 | I46: 393991.6 | J46: 2636019 | K46: =I46-J46 -> -2242027.4 | L46: =I46+June!L46 -> 4707442.5 | M46: =J46+June!M46 -> 36001027 | N46: =L46-M46 -> -31293584
B47: 31 | C47: Philam Fund, Inc. | D47: 2.6267297e+09 | E47: 5.2421717e+08 | F47: =D47-E47 -> 2102512560 | G47: 5.6177332e+08 | H47: 8325 | I47: 25916868 | J47: 8.1137203e+09 | K47: =I47-J47 -> -8087803417 | L47: =I47+June!L47 -> 1.903855e+08 | M47: =J47+June!M47 -> 8227178653 | N47: =L47-M47 -> -8036793150
B48: 32 | C48: Solidaritas Fund, Inc. (formerly, Bahay Pari Solidaritas Fund, Inc.) | D48: 1.3618179e+08 | E48: 864066.18 | F48: =D48-E48 -> 1.3531772e+08 | G48: 70384454 | H48: 197 | I48: 13493.99 | J48: 5565.43 | K48: =I48-J48 -> 7928.56 | L48: =I48+June!L48 -> 3386363.2 | M48: =J48+June!M48 -> 6636385.6 | N48: =L48-M48 -> -3250022.4
