Workbook

Sheet Jan
A1: PHILIPPINE INVESTMENT FUNDS ASSOCIATION, INC.
A2: MUTUAL FUNDS STATISTICAL REPORT
A3: Month of January 2023
A4: (Amounts in Peso)
I5: F O R - T H E - M O N T H | L5: Y E A R - T O - D A T E
A6: Fund Category | C6: Fund Name | D6: ASSETS | E6: LIABILITIES | F6: NET ASSETS | G6: EQUITY INV. | H6: NO. OF A/C | I6: SALES | J6: REDEMPTIONS | K6: NET SALES | L6: TOTAL SALES | M6: TOTAL REDEMPTIONS | N6: TOTAL NET SALES
A7: Stock Funds
A8: Primarily invested in Peso Securities (shares)
B9: 1 | C9: ALFM Growth Fund, Inc. | D9: 4.7822898e+09 | E9: 22866144 | F9: =D9-E9 -> 4759423672 | G9: 4444566800 | H9: 7266 | I9: 6706839.1 | J9: 75206133 | K9: =I9-J9 -> -68499294 | L9: =I9 -> 6706839.1 | M9: =J9 -> 75206133 | N9: =L9-M9 -> -68499294
B10: 2 | C10: ATRAM Alpha Opportunity Fund, Inc. | D10: 7.9233593e+08 | E10: 15870067 | F10: =D10-E10 -> 776465859 | G10: 7.2170991e+08 | H10: 4230 | I10: 4499756.3 | J10: 16217191 | K10: =I10-J10 -> -11717435 | L10: =I10 -> 4499756.2 | M10: =J10 -> 16217191 | N10: =L10-M10 -> -11717435
B11: 3 | C11: ATRAM Phil. Equity Opportunity Fund, Inc. | D11: 1.5556866e+09 | E11: 11754287 | F11: =D11-E11 -> 1543932337 | G11: 1.4656305e+09 | H11: 2882 | I11: 1.8795634e+08 | J11: 10251679 | K11: =I11-J11 -> 1.7770466e+08 | L11: =I11 -> 1.8795634e+08 | M11: =J11 -> 10251679 | N11: =L11-M11 -> 1.7770466e+08
B12: 4 | C12: Climbs Share Capital Equity Investment Fund Corp. | D12: 3.5654467e+08 | E12: 10854564 | F12: =D12-E12 -> 3.4569011e+08 | G12: 1.729918e+08 | H12: 1719 | I12: 541004.5 | J12: 108166.61 | K12: =I12-J12 -> 432837.89 | L12: =I12 -> 541004.5 | M12: =J12 -> 108166.61 | N12: =L12-M12 -> 432837.89
B13: 5 | C13: First Metro Consumer Fund, Inc. | D13: 5.4004161e+08 | E13: 1254131.9 | F13: =D13-E13 -> 5.3878748e+08 | G13: 5.2880601e+08 | H13: 1434 | I13: 763858.11 | J13: 3298867.6 | K13: =I13-J13 -> -2535009.5 | L13: =I13 -> 763858.11 | M13: =J13 -> 3298867.6 | N13: =L13-M13 -> -2535009.5
B14: 6 | C14: First Metro Save and Learn Equity Fund, Inc. | D14: 4.3893954e+09 | E14: 56878998 | F14: =D14-E14 -> 4332516360 | G14: 4.2483787e+09 | H14: 16239 | I14: 19313813 | J14: 54006004 | K14: =I14-J14 -> -34692191 | L14: =I14 -> 19313813 | M14: =J14 -> 54006004 | N14: =L14-M14 -> -34692191
B15: 7 | C15: First Metro Save and Learn Phil. Index Fund, Inc. | D15: 1.0356468e+08 | E15: 1636633.3 | F15: =D15-E15 -> 1.0192804e+08 | G15: 1.0169772e+08 | H15: 556 | I15: 760936.48 | J15: 3170318.6 | K15: =I15-J15 -> -2409382.1 | L15: =I15 -> 760936.48 | M15: =J15 -> 3170318.6 | N15: =L15-M15 -> -2409382.1
B16: 8 | C16: MBG Equity Investment Fund, Inc. | D16: 1.2257233e+08 | E16: 1973258.4 | F16: =D16-E16 -> 1.2059907e+08 | G16: 93684327 | H16: 51 | I16: 0 | J16: 0 | K16: =I16-J16 -> 0 | L16: =I16 -> 0 | M16: =J16 -> 0 | N16: =L16-M16 -> 0
B17: 9 | C17: PAMI Equity Index Fund, Inc. | D17: 1.4143032e+09 | E17: 77183575 | F17: =D17-E17 -> 1337119599 | G17: 1.3559362e+09 | H17: 12264 | I17: 0 | J17: 22214781 | K17: =I17-J17 -> -22214781 | L17: =I17 -> 0 | M17: =J17 -> 22214781 | N17: =L17-M17 -> -22214781
B18: 10 | C18: Philam Strategic Growth Fund, Inc. | D18: 4.0324245e+09 | E18: 1.6336035e+08 | F18: =D18-E18 -> 3869064193 | G18: 3.5538122e+09 | H18: 12231 | I18: 4691707 | J18: 23242525 | K18: =I18-J18 -> -18550818 | L18: =I18 -> 4691707 | M18: =J18 -> 23242525 | N18: =L18-M18 -> -18550818
B19: 11 | C19: Philequity Dividend Yield Fund, Inc. | D19: 2.2049397e+09 | E19: 36620940 | F19: =D19-E19 -> 2168318719 | G19: 1.8965229e+09 | H19: 5629 | I19: 71593884 | J19: 4276017.4 | K19: =I19-J19 -> 67317866 | L19: =I19 -> 71593884 | M19: =J19 -> 4276017.4 | N19: =L19-M19 -> 67317866
B20: 12 | C20: Philequity Fund, Inc. | D20: 1.0039293e+10 | E20: 34899213 | F20: =D20-E20 -> 10004393473 | G20: 9.2304504e+09 | H20: 36180 | I20: 10633658 | J20: 45139938 | K20: =I20-J20 -> -34506280 | L20: =I20 -> 10633658 | M20: =J20 -> 45139938 | N20: =L20-M20 -> -34506280
... B27: 19 | C27: United Fund, Inc. | D27: 6.0788571e+08 | E27: 2758899.5 | F27: =D27-E27 -> 6.0512681e+08 | G27: 5.2895313e+08 | H27: 1304 | I27: 297833.86 | J27: 3606632.7 | K27: =I27-J27 -> -3308798.8 | L27: =I27 -> 297833.86 | M27: =J27 -> 3606632.7 | N27: =L27-M27 -> -3308798.8
A28: Primarily invested in Peso Securities (units)
B29: 20 | C29: COL Equity Index Unitized Mutual Fund, Inc. | D29: 1.334247e+08 | E29: 1368336.6 | F29: =D29-E29 -> 1.3205637e+08 | G29: 1.2990052e+08 | H29: 1222 | I29: 18662319 | J29: 1531528.5 | K29: =I29-J29 -> 17130791 | L29: =I29 -> 18662319 | M29: =J29 -> 1531528.5 | N29: =L29-M29 -> 17130791
B30: 21 | C30: Philequity Alpha One Fund, Inc. | D30: 3.4194384e+08 | E30: 1226623.2 | F30: =D30-E30 -> 3.4071722e+08 | G30: 3.1886116e+08 | H30: 1425 | I30: 1357758.3 | J30: 9542216.7 | K30: =I30-J30 -> -8184458.3 | L30: =I30 -> 1357758.3 | M30: =J30 -> 9542216.7 | N30: =L30-M30 -> -8184458.3
B31: 22 | C31: Philippine Stock Index Fund Corp. | D31: 4.8721803e+08 | E31: 15335630 | F31: =D31-E31 -> 4.718824e+08 | G31: 4.8025628e+08 | H31: 328363 | I31: 33306036 | J31: 54543447 | K31: =I31-J31 -> -21237411 | L31: =I31 -> 33306036 | M31: =J31 -> 54543447 | N31: =L31-M31 -> -21237411
A32: Exchange Traded Fund
B33: 23 | C33: First Metro Phil. Equity Exchange Traded Fund, Inc. | D33: 2.210282e+09 | E33: 1638636.6 | F33: =D33-E33 -> 2208643351 | G33: 2.2049191e+09 | H33: 3231 | I33: 1034532 | J33: 73813261 | K33: =I33-J33 -> -72778729 | L33: =I33 -> 1034532 | M33: =J33 -> 73813261 | N33: =L33-M33 -> -72778729
A34: Sub total - Peso Currency | D34: =SUM(D9:D33) -> 70670056765 | E34: =SUM(E9:E33) -> 9.0150261e+08 | F34: =SUM(F9:F33) -> 69768554152 | G34: =SUM(G9:G33) -> 66981970552 | H34: =SUM(H9:H33) -> 614666 | I34: =SUM(I9:I33) -> 9.5589796e+08 | J34: =SUM(J9:J33) -> 1386801971 | K34: =SUM(K9:K33) -> -4.3090401e+08 | ... N34: =SUM(N9:N33) -> -4.3090401e+08
A35: Primarily invested in foreign currency securities (shares)
B36: 24 | C36: ATRAM AsiaPlus Equity Fund, Inc. | D36: 38273149 | E36: 879713.29 | F36: =D36-E36 -> 37393436 | G36: 0 | H36: 55 | I36: 199.54 | J36: 0 | K36: =I36-J36 -> 199.54 | L36: =I36 -> 199.54 | M36: =J36 -> 0 | N36: =L36-M36 -> 199.54
B37: 25 | C37: Sun Life Prosperity World Voyager Fund, Inc. | D37: =54.64*34312196.64 -> 1874818424 | E37: =54.64*440448.86 -> 24066126 | F37: =D37-E37 -> 1850752299 | G37: 0 | H37: 2871 | I37: =54.64*240117.89 -> 13120042 | J37: =54.64*555198.89 -> 30336067 | K37: =I37-J37 -> -17216026 | L37: =I37 -> 13120042 | M37: =J37 -> 30336067 | N37: =L37-M37 -> -17216026
A38: Sub total - US Currency | D38: =SUM(D36:D37) -> 1913091573 | E38: =SUM(E36:E37) -> 24945839 | F38: =SUM(F36:F37) -> 1888145734 | G38: =SUM(G36:G37) -> 0 | H38: =SUM(H36:H37) -> 2926 | I38: =SUM(I36:I37) -> 13120241 | J38: =SUM(J36:J37) -> 30336067 | K38: =SUM(K36:K37) -> -17215826 | ... N38: =SUM(N36:N37) -> -17215826
A39: Sub total - stock funds | D39: =D34+D38 -> 72583148338 | E39: =E34+E38 -> 9.2644845e+08 | F39: =F34+F38 -> 71656699887 | G39: =G34+G38 -> 66981970552 | H39: =H34+H38 -> 617592 | I39: =I34+I38 -> 969018201 | J39: =J34+J38 -> 1417138038 | K39: =K34+K38 -> -4.4811984e+08 | ... N39: =N34+N38 -> -4.4811984e+08
A40: Balanced Funds
A41: Primarily invested in Peso Securities (shares)
B42: 26 | C42: ATRAM Dynamic Allocation Fund, Inc. | D42: 1.2619964e+08 | E42: 9166770.6 | F42: =D42-E42 -> 1.1703287e+08 | G42: 27577738 | H42: 722 | I42: 318249.68 | J42: 266687.3 | K42: =I42-J42 -> 51562.38 | L42: =I42 -> 318249.68 | M42: =J42 -> 266687.3 | N42: =L42-M42 -> 51562.38
B43: 27 | C43: ATRAM Philippine Balanced Fund, Inc. | D43: 6.677692e+08 | E43: 83820160 | F43: =D43-E43 -> 5.8394904e+08 | G43: 2.137249e+08 | H43: 2440 | I43: 1047414.5 | J43: 1930071.6 | K43: =I43-J43 -> -882657.13 | L43: =I43 -> 1047414.5 | M43: =J43 -> 1930071.6 | N43: =L43-M43 -> -882657.13
B44: 28 | C44: First Metro Save and Learn Balanced Fund, Inc. | D44: 1.0923571e+09 | E44: 11264935 | F44: =D44-E44 -> 1081092202 | G44: 6.8939087e+08 | H44: 4704 | I44: 1335330.8 | J44: 5135919.7 | K44: =I44-J44 -> -3800588.8 | L44: =I44 -> 1335330.8 | M44: =J44 -> 5135919.7 | N44: =L44-M44 -> -3800588.8
B45: 29 | C45: First Metro Save and Learn F.O.C.C.U.S. Dynamic Fund, Inc. | D45: 3.0862544e+08 | E45: 10753626 | F45: =D45-E45 -> 2.9787182e+08 | G45: 2.4309859e+08 | H45: 237 | I45: 4604623.3 | J45: 11846152 | K45: =I45-J45 -> -7241529 | L45: =I45 -> 4604623.3 | M45: =J45 -> 11846152 | N45: =L45-M45 -> -7241529
B46: 30 | C46: NCM Mutual Fund of the Phils., Inc. | D46: 3.5711594e+08 | E46: 4143976.5 | F46: =D46-E46 -> 3.5297197e+08 | G46: 1.619854e+08 | H46: 56 | I46: 0 | J46: 0 | K46: =I46-J46 -> 0 | L46: =I46 -> 0 | M46: =J46 -> 0 | N46: =L46-M46 -> 0
B47: 31 | C47: PAMI Horizon Fund, Inc. | D47: 5.7811698e+08 | E47: 18677829 | F47: =D47-E47 -> 5.5943915e+08 | G47: 317695053 | H47: 10102 | I47: 1412333.9 | J47: 3559268.9 | K47: =I47-J47 -> -2146935 | L47: =I47 -> 1412333.9 | M47: =J47 -> 3559268.9 | N47: =L47-M47 -> -2146935
B48: 32 | C48: Philam Fund, Inc. | D48: 2.1487826e+09 | E48: 53191972 | F48: =D48-E48 -> 2095590610 | G48: 1.1297017e+09 | H48: 8191 | I48: 2288846.4 | J48: 24576810 | K48: =I48-J48 -> -22287963 | L48: =I48 -> 2288846.4 | M48: =J48 -> 24576810 | N48: =L48-M48 -> -22287963
B49: 33 | C49: Solidaritas Fund, Inc. | D49: 1.3957754e+08 | E49: 179389.35 | F49: =D49-E49 -> 1.3939815e+08 | G49: 86057497 | H49: 197 | I49: 11298.64 | J49: 505614.82 | K49: =I49-J49 -> -494316.18 | L49: =I49 -> 11298.64 | M49: =J49 -> 505614.82 | N49: =L49-M49 -> -494316.18
B50: 34 | C50: Sun Life Prosperity Balanced Fund, Inc. | D50: 7.4409662e+09 | E50: 57092367 | F50: =D50-E50 -> 7383873806 | G50: 3.8579976e+09 | H50: 53657 | I50: 9276468.2 | J50: 70591644 | K50: =I50-J50 -> -61315176 | L50: =I50 -> 9276468.2 | M50: =J50 -> 70591644 | N50: =L50-M50 -> -61315176
B51: 35 | C51: Sun Life Prosperity Dynamic Fund, Inc. | D51: 1.2129815e+09 | E51: 18955012 | F51: =D51-E51 -> 1194026484 | G51: 6.8099147e+08 | H51: 4998 | I51: 0 | J51: 4573571.8 | K51: =I51-J51 -> -4573571.8 | L51: =I51 -> 0 | M51: =J51 -> 4573571.8 | N51: =L51-M51 -> -4573571.8
A52: Primarily invested in Peso Securities (units)
B53: 36 | C53: Sun Life Prosperity Achiever Fund 2028, Inc. | D53: 77069137 | E53: 298127.43 | F53: =D53-E53 -> 76771009 | G53: 22973119 | H53: 1055 | I53: 511305.2 | J53: 80492.55 | K53: =I53-J53 -> 430812.65 | L53: =I53 -> 511305.2 | M53: =J53 -> 80492.55 | N53: =L53-M53 -> 430812.65
B54: 37 | C54: Sun Life Prosperity Achiever Fund 2038, Inc. | D54: 57793560 | E54: 369224.54 | F54: =D54-E54 -> 57424336 | G54: 44613619 | H54: 410 | I54: 452055 | J54: 140300.19 | K54: =I54-J54 -> 311754.81 | L54: =I54 -> 452055 | M54: =J54 -> 140300.19 | N54: =L54-M54 -> 311754.81
B55: 38 | C55: Sun Life Prosperity Achiever Fund 2048, Inc. | D55: 48431764 | E55: 260874 | F55: =D55-E55 -> 48170890 | G55: 40734100 | H55: 191 | I55: 69478 | J55: 91381.96 | K55: =I55-J55 -> -21903.96 | L55: =I55 -> 69478 | M55: =J55 -> 91381.96 | N55: =L55-M55 -> -21903.96
A56: Sub total - Peso Currency | D56: =SUM(D42:D55) -> 14255786593 | E56: =SUM(E42:E55) -> 268174263 | F56: =SUM(F42:F55) -> 13987612330 | G56: =SUM(G42:G55) -> 7516541747 | H56: =SUM(H42:H55) -> 86960 | I56: =SUM(I42:I55) -> 21327404 | J56: =SUM(J42:J55) -> 123297915 | K56: =SUM(K42:K55) -> -1.0197051e+08 | ... N56: =SUM(N42:N55) -> -1.0197051e+08
A57: Primarily invested in foreign currency securities (shares)
B58: 39 | C58: Cocolife Dollar Fund Builder, Inc. | D58: =54.64*1309550.34 -> 71553831 | E58: =54.64*8501.69 -> 464532.34 | F58: =D58-E58 -> 71089298 | G58: 0 | H58: 53 | I58: 0 | J58: =54.64*905.53 -> 49478.159 | K58: =I58-J58 -> -49478.159 | L58: =I58 -> 0 | M58: =J58 -> 49478.159 | N58: =L58-M58 -> -49478.159
B59: 40 | C59: PAMI Asia Balanced Fund, Inc. | D59: =54.64*6773298.91 -> 3.7009305e+08 | E59: =54.64*459683.99 -> 25117133 | F59: =D59-E59 -> 3.4497592e+08 | G59: =54.64*3501696.82 -> 1.9133271e+08 | H59: 264 | I59: =54.64*98.2 -> 5365.648 | J59: =54.64*54108.64 -> 2956496.1 | K59: =I59-J59 -> -2951130.4 | L59: =I59 -> 5365.648 | M59: =J59 -> 2956496.1 | N59: =L59-M59 -> -2951130.4
B60: 41 | C60: Sun Life Prosperity Dollar Advantage Fund, Inc. | D60: =54.64*29204466.31 -> 1595732039 | E60: =54.64*603855.9 -> 32994686 | F60: =D60-E60 -> 1562737353 | G60: 0 | H60: 4137 | I60: =54.64*16340.4 -> 892839.46 | J60: =54.64*42879.72 -> 2342947.9 | K60: =I60-J60 -> -1450108.4 | L60: =I60 -> 892839.46 | M60: =J60 -> 2342947.9 | N60: =L60-M60 -> -1450108.4
B61: 42 | C61: Sun Life Prosperity Dollar Wellspring Fund, Inc. | D61: =54.64*5029466.83 -> 2.7481007e+08 | E61: =54.64*114699.82 -> 6267198.2 | F61: =D61-E61 -> 2.6854287e+08 | G61: 0 | H61: 715 | I61: =54.64*1177.6 -> 64344.064 | J61: =54.64*534064.29 -> 29181273 | K61: =I61-J61 -> -29116929 | L61: =I61 -> 64344.064 | M61: =J61 -> 29181273 | N61: =L61-M61 -> -29116929
A62: Sub total - US Currency | D62: =SUM(D58:D61) -> 2312188990 | E62: =SUM(E58:E61) -> 64843550 | F62: =SUM(F58:F61) -> 2247345440 | G62: =SUM(G58:G61) -> 1.9133271e+08 | H62: =SUM(H58:H61) -> 5169 | I62: =SUM(I58:I61) -> 962549.17 | J62: =SUM(J58:J61) -> 34530195 | K62: =SUM(K58:K61) -> -33567646 | ... N62: =SUM(N58:N61) -> -33567646
A63: Sub total - balanced funds | D63: =D56+D62 -> 16567975583 | E63: =E56+E62 -> 3.3301781e+08 | F63: =F56+F62 -> 16234957770 | G63: =G56+G62 -> 7707874461 | H63: =H56+H62 -> 92129 | I63: =I56+I62 -> 22289953 | J63: =J56+J62 -> 157828110 | K63: =K56+K62 -> -1.3553816e+08 | ... N63: =N56+N62 -> -1.3553816e+08
A64: Bond Funds
A65: Primarily invested in Peso Securities (shares)
B66: 43 | C66: ALFM Peso Bond Fund, Inc. | D66: 3.986693e+10 | E66: 3.0613874e+08 | F66: =D66-E66 -> 39560791129 | G66: 924686400 | H66: 25042 | I66: 3.0267525e+08 | J66: 6.9322417e+08 | K66: =I66-J66 -> -390548920 | L66: =I66 -> 3.0267525e+08 | M66: =J66 -> 6.9322417e+08 | N66: =L66-M66 -> -390548920
B67: 44 | C67: ATRAM Corporate Bond Fund, Inc. | D67: 4.6376101e+08 | E67: 1128505.1 | F67: =D67-E67 -> 4.626325e+08 | G67: 0 | H67: 1085 | I67: 9254522.8 | J67: 11940399 | K67: =I67-J67 -> -2685875.8 | L67: =I67 -> 9254522.8 | M67: =J67 -> 11940399 | N67: =L67-M67 -> -2685875.8
B68: 45 | C68: Cocolife Fixed Income Fund, Inc. | D68: 1.0167645e+09 | E68: 14564668 | F68: =D68-E68 -> 1002199801 | G68: 0 | H68: 1980 | I68: 1496351.9 | J68: 3534355.6 | K68: =I68-J68 -> -2038003.7 | L68: =I68 -> 1496351.9 | M68: =J68 -> 3534355.6 | N68: =L68-M68 -> -2038003.7
B69: 46 | C69: Ekklesia Mutual Fund, Inc. | D69: 1.9757825e+08 | E69: 297225.9 | F69: =D69-E69 -> 1.9728102e+08 | G69: 4875000 | H69: 183 | I69: 576977.99 | J69: 65104.65 | K69: =I69-J69 -> 511873.34 | L69: =I69 -> 576977.99 | M69: =J69 -> 65104.65 | N69: =L69-M69 -> 511873.34
B70: 47 | C70: First Metro Save and Learn Fixed Income Fund, Inc. | D70: 1.2992817e+09 | E70: 2547752.9 | F70: =D70-E70 -> 1296733962 | G70: 0 | H70: 1812 | I70: 1136527 | J70: 3258190.2 | K70: =I70-J70 -> -2121663.2 | L70: =I70 -> 1136527 | M70: =J70 -> 3258190.2 | N70: =L70-M70 -> -2121663.2
B71: 48 | C71: Philam Managed Income Fund, Inc. | D71: 8.606294e+08 | E71: 36972996 | F71: =D71-E71 -> 823656401 | G71: 0 | H71: 504 | I71: 3835006.8 | J71: 994028.32 | K71: =I71-J71 -> 2840978.4 | L71: =I71 -> 3835006.8 | M71: =J71 -> 994028.32 | N71: =L71-M71 -> 2840978.4
B72: 49 | C72: Philam Bond Fund, Inc. | D72: 1.7460492e+09 | E72: 24263382 | F72: =D72-E72 -> 1721785791 | G72: 0 | H72: 5040 | I72: 3332061.4 | J72: 3298829 | K72: =I72-J72 -> 33232.41 | L72: =I72 -> 3332061.4 | M72: =J72 -> 3298829 | N72: =L72-M72 -> 33232.41
B73: 50 | C73: Philequity Peso Bond Fund, Inc. | D73: 3.0871269e+08 | E73: 547631.46 | F73: =D73-E73 -> 3.0816506e+08 | G73: 0 | H73: 4147 | I73: 607368.18 | J73: 1699352.2 | K73: =I73-J73 -> -1091984 | L73: =I73 -> 607368.18 | M73: =J73 -> 1699352.2 | N73: =L73-M73 -> -1091984
B74: 51 | C74: Soldivo Bond Fund, Inc. | D74: 1.2600245e+09 | E74: 2779212.1 | F74: =D74-E74 -> 1257245291 | G74: 0 | H74: 752 | I74: 25076914 | J74: 86377.19 | K74: =I74-J74 -> 24990537 | L74: =I74 -> 25076914 | M74: =J74 -> 86377.19 | N74: =L74-M74 -> 24990537
B75: 52 | C75: Sun Life Prosperity Bond Fund, Inc. | D75: 4.671494e+09 | E75: 7656668.9 | F75: =D75-E75 -> 4663837293 | G75: 0 | H75: 16653 | I75: 1.6229656e+08 | J75: 49576365 | K75: =I75-J75 -> 112720199 | L75: =I75 -> 162296564 | M75: =J75 -> 49576365 | N75: =L75-M75 -> 112720199
B76: 53 | C76: Sun Life Prosperity GS Fund, Inc. | D76: 1.4053813e+08 | E76: 442129.35 | F76: =D76-E76 -> 1.4009601e+08 | G76: 0 | H76: 2647 | I76: 521808.44 | J76: 523771.71 | K76: =I76-J76 -> -1963.27 | L76: =I76 -> 521808.44 | M76: =J76 -> 523771.71 | N76: =L76-M76 -> -1963.27
A77: Sub total - Peso Currency | D77: =SUM(D66:D76) -> 51831763165 | E77: =SUM(E66:E76) -> 3.9733891e+08 | F77: =SUM(F66:F76) -> 51434424256 | G77: =SUM(G66:G76) -> 929561400 | H77: =SUM(H66:H76) -> 59845 | I77: =SUM(I66:I76) -> 5.1080936e+08 | J77: =SUM(J66:J76) -> 7.6820095e+08 | K77: =SUM(K66:K76) -> -2.5739159e+08 | ... N77: =SUM(N66:N76) -> -2.5739159e+08
A78: Primarily invested in foreign currency securities (shares)
B79: 54 | C79: ALFM Dollar Bond Fund, Inc. | D79: =54.64*250683072.7 -> 13697323092 | E79: =54.64*2181930.88 -> 1.192207e+08 | F79: =D79-E79 -> 13578102389 | G79: 0 | H79: 8736 | I79: =54.64*980951.84 -> 53599209 | J79: =54.64*1860000.71 -> 1.0163044e+08 | K79: =I79-J79 -> -48031230 | L79: =I79 -> 53599209 | M79: =J79 -> 1.0163044e+08 | N79: =L79-M79 -> -48031230
B80: 55 | C80: ATRAM Total Return Dollar Bond Fund, Inc. | D80: 2.6184269e+08 | E80: 2209688.6 | F80: =D80-E80 -> 2.5963301e+08 | G80: 0 | H80: 174 | I80: 0 | J80: 515175.43 | K80: =I80-J80 -> -515175.43 | L80: =I80 -> 0 | M80: =J80 -> 515175.43 | N80: =L80-M80 -> -515175.43
B81: 56 | C81: First Metro Save and Learn Dollar Bond Fund, Inc. | D81: 4.2822875e+08 | E81: 3019811.8 | F81: =D81-E81 -> 4.2520894e+08 | G81: 0 | H81: 147 | I81: 1406288.2 | J81: 5011682.9 | K81: =I81-J81 -> -3605394.6 | L81: =I81 -> 1406288.2 | M81: =J81 -> 5011682.9 | N81: =L81-M81 -> -3605394.6
B82: 57 | C82: PAMI Global Bond Fund Phils., Inc. | D82: =54.64*1168062.5 -> 63822935 | E82: =54.64*245881.27 -> 13434953 | F82: =D82-E82 -> 50387982 | G82: 0 | H82: 26 | I82: 0 | J82: 0 | K82: =I82-J82 -> 0 | L82: =I82 -> 0 | M82: =J82 -> 0 | N82: =L82-M82 -> 0
B83: 58 | C83: Philam Dollar Bond Fund, Inc. | D83: =54.64*36988300.73 -> 2021040752 | E83: =54.64*422882.93 -> 23106323 | F83: =D83-E83 -> 1997934429 | G83: 0 | H83: 1924 | I83: =54.64*1390.08 -> 75953.971 | J83: =54.64*267635.59 -> 14623609 | K83: =I83-J83 -> -14547655 | L83: =I83 -> 75953.971 | M83: =J83 -> 14623609 | N83: =L83-M83 -> -14547655
B84: 59 | C84: Philequity Dollar Income Fund, Inc. | D84: 4232253.4 | E84: 22979.564 | F84: =D84-E84 -> 4209273.9 | G84: 0 | H84: 123 | I84: 174848 | J84: 0 | K84: =I84-J84 -> 174848 | L84: =I84 -> 174848 | M84: =J84 -> 0 | N84: =L84-M84 -> 174848
B85: 60 | C85: Sun Life Prosperity Dollar Abundance Fund, Inc. | D85: =54.64*9824643.47 -> 5.3681852e+08 | E85: =54.64*54338.59 -> 2969060.6 | F85: =D85-E85 -> 5.3384946e+08 | G85: 0 | H85: 2531 | I85: =54.64*1681600.76 -> 91882666 | J85: =54.64*107515.79 -> 5874662.8 | K85: =I85-J85 -> 86008003 | L85: =I85 -> 91882666 | M85: =J85 -> 5874662.8 | N85: =L85-M85 -> 86008003
A86: Sub total - US Currency | D86: =SUM(D79:D85) -> 17013308995 | E86: =SUM(E79:E85) -> 1.6398352e+08 | F86: =SUM(F79:F85) -> 16849325476 | G86: =SUM(G79:G85) -> 0 | H86: =SUM(H79:H85) -> 13661 | I86: =SUM(I79:I85) -> 1.4713896e+08 | J86: =SUM(J79:J85) -> 1.2765557e+08 | K86: =SUM(K79:K85) -> 19483396 | ... N86: =SUM(N79:N85) -> 19483396
B87: 61 | C87: ALFM Euro Bond Fund, Inc. | D87: =15709493.66*59.098624 -> 928409459 | E87: =170101.96*59.098624 -> 10052792 | F87: =D87-E87 -> 9.1835667e+08 | G87: 0 | H87: 658 | I87: =111553.94*59.098624 -> 6592684.4 | J87: =19958.15*59.098624 -> 1179499.2 | K87: =I87-J87 -> 5413185.2 | L87: =I87 -> 6592684.4 | M87: =J87 -> 1179499.2 | N87: =L87-M87 -> 5413185.2
A88: Sub total - Euro Currency | D88: =SUM(D87) -> 928409459 | E88: =SUM(E87) -> 10052792 | F88: =SUM(F87) -> 9.1835667e+08 | G88: =SUM(G87) -> 0 | H88: =SUM(H87) -> 658 | I88: =SUM(I87) -> 6592684.4 | J88: =SUM(J87) -> 1179499.2 | K88: =SUM(K87) -> 5413185.2 | ... N88: =SUM(N87) -> 5413185.2
A89: Sub total - bond funds | D89: =D77+D86+D88 -> 69773481620 | E89: =E77+E86+E88 -> 5.7137522e+08 | F89: =F77+F86+F88 -> 69202106399 | G89: =G77+G86+G88 -> 929561400 | H89: =H77+H86+H88 -> 74164 | I89: =I77+I86+I88 -> 6.64541e+08 | J89: =J77+J86+J88 -> 8.9703601e+08 | K89: =K77+K86+K88 -> -2.3249501e+08 | ... N89: =N77+N86+N88 -> -2.3249501e+08
A90: Money Market Funds
A91: Primarily invested in Peso Securities (shares)
B92: 62 | C92: ALFM Money Market Fund, Inc. | D92: 4.0787037e+10 | E92: 24413454 | F92: =D92-E92 -> 40762623233 | G92: 0 | H92: 30748 | I92: 3.0260461e+09 | J92: 2.7870736e+09 | K92: =I92-J92 -> 2.3897257e+08 | L92: =I92 -> 3026046131 | M92: =J92 -> 2787073566 | N92: =L92-M92 -> 2.3897257e+08
B93: 63 | C93: First Metro Save and Learn Money Market Fund, Inc. | D93: 2.7887696e+09 | E93: 6912922.4 | F93: =D93-E93 -> 2781856708 | G93: 0 | H93: 724 | I93: 1.1960677e+08 | J93: 1.708689e+08 | K93: =I93-J93 -> -51262130 | L93: =I93 -> 119606766 | M93: =J93 -> 1.708689e+08 | N93: =L93-M93 -> -51262130
B94: 64 | C94: Sun Life Prosperity Peso Starter Fund, Inc. | D94: 4.6335275e+10 | E94: 2.7667125e+08 | F94: =D94-E94 -> 46058603905 | G94: 0 | H94: 66029 | I94: 2.7293822e+09 | J94: 9.0043578e+09 | K94: =I94-J94 -> -6274975535 | L94: =I94 -> 2729382244 | M94: =J94 -> 9004357779 | N94: =L94-M94 -> -6274975535
A95: Primarily invested in Peso Securities (units)
B96: 65 | C96: ALFM Money Market Fund, Inc. | D96: 4.5189436e+09 | E96: 3245316.4 | F96: =D96-E96 -> 4515698296 | G96: 0 | H96: 4174 | I96: 1.5842774e+09 | J96: 5.9882374e+08 | K96: =I96-J96 -> 9.8545362e+08 | L96: =I96 -> 1584277361 | M96: =J96 -> 5.9882374e+08 | N96: =L96-M96 -> 9.8545362e+08
A97: Sub total - Peso Currency | D97: =SUM(D92:D94)+D96 -> 94430025082 | E97: =SUM(E92:E94)+E96 -> 3.1124294e+08 | F97: =SUM(F92:F94)+F96 -> 94118782142 | G97: =SUM(G92:G94)+G96 -> 0 | H97: =SUM(H92:H94)+H96 -> 101675 | I97: =SUM(I92:I94)+I96 -> 7459312502 | J97: =SUM(J92:J94)+J96 -> 12561123979 | K97: =SUM(K92:K94)+K96 -> -5101811477 | ... N97: =SUM(N92:N94)+N96 -> -5101811477
A98: Primarily invested in foreign currency securities (shares)
B99: 66 | C99: Sun Life Prosperity Dollar Starter Fund, Inc. | D99: =54.64*91978325.38 -> 5025695699 | E99: =54.64*1241135.85 -> 67815663 | F99: =D99-E99 -> 4957880036 | G99: 0 | H99: 3421 | I99: =54.64*24060314.32 -> 1314655574 | J99: =54.64*36576277.42 -> 1998527798 | K99: =I99-J99 -> -6.8387222e+08 | L99: =I99 -> 1314655574 | M99: =J99 -> 1998527798 | N99: =L99-M99 -> -6.8387222e+08
A100: Sub total - US Currency | D100: =SUM(D99) -> 5025695699 | E100: =SUM(E99) -> 67815663 | F100: =SUM(F99) -> 4957880036 | G100: =SUM(G99) -> 0 | H100: =SUM(H99) -> 3421 | I100: =SUM(I99) -> 1314655574 | J100: =SUM(J99) -> 1998527798 | K100: =SUM(K99) -> -6.8387222e+08 | ... N100: =SUM(N99) -> -6.8387222e+08
A101: Sub total - money market funds | D101: =D97+D100 -> 99455720781 | E101: =E97+E100 -> 3.790586e+08 | F101: =F97+F100 -> 99076662178 | G101: =G97+G100 -> 0 | H101: =H97+H100 -> 105096 | I101: =I97+I100 -> 8773968076 | J101: =J97+J100 -> 14559651777 | K101: =K97+K100 -> -5785683701 | ... N101: =N97+N100 -> -5785683701
A102: Feeder Fund
A103: Primarily invested in Peso securities (units)
B104: 67 | C104: ALFM Global Multi-Asset Income Fund Inc. | D104: 9.5349309e+09 | E104: 84178642 | F104: =D104-E104 -> 9450752279 | G104: 0 | H104: 66422 | I104: 2.0403477e+08 | J104: 78931136 | K104: =I104-J104 -> 1.2510363e+08 | L104: =I104 -> 2.0403477e+08 | M104: =J104 -> 78931136 | N104: =L104-M104 -> 1.2510363e+08
B105: 68 | C105: Sun Life Prosperity World Equity Index Feeder Fund, Inc. | D105: 3.4070574e+09 | E105: 12884397 | F105: =D105-E105 -> 3394172988 | G105: 0 | H105: 5938 | I105: 26160058 | J105: 57063239 | K105: =I105-J105 -> -30903181 | L105: =I105 -> 26160058 | M105: =J105 -> 57063239 | N105: =L105-M105 -> -30903181
A106: Sub total - Peso Currency | D106: =D104+D105 -> 12941988307 | E106: =E104+E105 -> 97063039 | F106: =F104+F105 -> 12844925268 | G106: =G104+G105 -> 0 | H106: =H104+H105 -> 72360 | I106: =I104+I105 -> 2.3019483e+08 | J106: =J104+J105 -> 1.3599438e+08 | K106: =K104+K105 -> 94200451 | ... N106: =N104+N105 -> 94200451
...

Sheet Feb
A1: PHILIPPINE INVESTMENT FUNDS ASSOCIATION, INC.
A2: MUTUAL FUNDS STATISTICAL REPORT
A3: Month of February 2023
A4: (Amounts in Peso)
I5: F O R - T H E - M O N T H | L5: Y E A R - T O - D A T E
A6: Fund Category | C6: Fund Name | D6: ASSETS | E6: LIABILITIES | F6: NET ASSETS | G6: EQUITY INV. | H6: NO. OF A/C | I6: SALES | J6: REDEMPTIONS | K6: NET SALES | L6: TOTAL SALES | M6: TOTAL REDEMPTIONS | N6: TOTAL NET SALES
A7: Stock Funds
A8: Primarily invested in Peso Securities (shares)
B9: 1 | C9: ALFM Growth Fund, Inc. | D9: 4593872904 | E9: 12038727 | F9: =D9-E9 -> 4581834177 | G9: 4291574273 | H9: 7236 | I9: 5275082 | J9: 24704237 | K9: =I9-J9 -> -19429155 | L9: =I9+Jan!L9 -> 11981921 | M9: =J9+Jan!M9 -> 99910370 | N9: =L9-M9 -> -87928449
B10: 2 | C10: ATRAM Alpha Opportunity Fund, Inc. | D10: 7.8551118e+08 | E10: 21049873 | F10: =D10-E10 -> 7.6446131e+08 | G10: 7.1177413e+08 | H10: 4221 | I10: 5560274.9 | J10: 12336999 | K10: =I10-J10 -> -6776724.6 | L10: =I10+Jan!L10 -> 10060031 | M10: =J10+Jan!M10 -> 28554190 | N10: =L10-M10 -> -18494159
B11: 3 | C11: ATRAM Phil. Equity Opportunity Fund, Inc. | D11: 1.6316838e+09 | E11: 1.0575227e+08 | F11: =D11-E11 -> 1525931484 | G11: 1.4548882e+09 | H11: 2874 | I11: 1.8514609e+08 | J11: 1.2266104e+08 | K11: =I11-J11 -> 62485054 | L11: =I11+Jan!L11 -> 3.7310243e+08 | M11: =J11+Jan!M11 -> 1.3291271e+08 | N11: =L11-M11 -> 2.4018971e+08
B12: 4 | C12: Climbs Share Capital Equity Investment Fund Corp. | D12: 3.6020278e+08 | E12: 17762394 | F12: =D12-E12 -> 3.4244039e+08 | G12: 2.0451595e+08 | H12: 1743 | I12: 588897.45 | J12: 71172.65 | K12: =I12-J12 -> 517724.8 | L12: =I12+Jan!L12 -> 1129901.9 | M12: =J12+Jan!M12 -> 179339.26 | N12: =L12-M12 -> 950562.69
B13: 5 | C13: First Metro Consumer Fund, Inc. | D13: 5.3822817e+08 | E13: 1229091.1 | F13: =D13-E13 -> 5.3699908e+08 | G13: 4.2599787e+08 | H13: 1428 | I13: 539284.43 | J13: 284725.86 | K13: =I13-J13 -> 254558.57 | L13: =I13+Jan!L13 -> 1303142.5 | M13: =J13+Jan!M13 -> 3583593.4 | N13: =L13-M13 -> -2280450.9
B14: 6 | C14: First Metro Save and Learn Equity Fund, Inc. | D14: 4.2099549e+09 | E14: 21850252 | F14: =D14-E14 -> 4188104604 | G14: 3.4415412e+09 | H14: 16190 | I14: 13071496 | J14: 17052745 | K14: =I14-J14 -> -3981249.8 | L14: =I14+Jan!L14 -> 32385308 | M14: =J14+Jan!M14 -> 71058749 | N14: =L14-M14 -> -38673441
B15: 7 | C15: First Metro Save and Learn Phil. Index Fund, Inc. | D15: 99621798 | E15: 1254140.8 | F15: =D15-E15 -> 98367658 | G15: 96925675 | H15: 554 | I15: 728740.25 | J15: 676891.31 | K15: =I15-J15 -> 51848.94 | L15: =I15+Jan!L15 -> 1489676.7 | M15: =J15+Jan!M15 -> 3847209.9 | N15: =L15-M15 -> -2357533.2
B16: 8 | C16: MBG Equity Investment Fund, Inc. | D16: 119846366 | E16: 2353974 | F16: =D16-E16 -> 117492392 | G16: 106689337 | H16: 50 | I16: 0 | J16: 496031 | K16: =I16-J16 -> -496031 | L16: =I16+Jan!L16 -> 0 | M16: =J16+Jan!M16 -> 496031 | N16: =L16-M16 -> -496031
B17: 9 | C17: PAMI Equity Index Fund, Inc. | D17: 1356343217 | E17: 74584016 | F17: =D17-E17 -> 1281759201 | G17: 1301656259 | H17: 12224 | I17: 0 | J17: 6972690 | K17: =I17-J17 -> -6972690 | L17: =I17+Jan!L17 -> 0 | M17: =J17+Jan!M17 -> 29187471 | N17: =L17-M17 -> -29187471
B18: 10 | C18: Philam Strategic Growth Fund, Inc. | D18: 3876027145 | E18: 161955174 | F18: =D18-E18 -> 3714071971 | G18: 3424225386 | H18: 12187 | I18: 3137498 | J18: 24799237 | K18: =I18-J18 -> -21661739 | L18: =I18+Jan!L18 -> 7829205 | M18: =J18+Jan!M18 -> 48041762 | N18: =L18-M18 -> -40212557
B19: 11 | C19: Philequity Dividend Yield Fund, Inc. | D19: 2.2240016e+09 | E19: 16490897 | F19: =D19-E19 -> 2207510676 | G19: 1.8905677e+09 | H19: 5618 | I19: 62015147 | J19: 3355607.8 | K19: =I19-J19 -> 58659539 | L19: =I19+Jan!L19 -> 1.3360903e+08 | M19: =J19+Jan!M19 -> 7631625.2 | N19: =L19-M19 -> 1.259774e+08
B20: 12 | C20: Philequity Fund, Inc. | D20: 9.9096779e+09 | E20: 1.7157781e+08 | F20: =D20-E20 -> 9738100086 | G20: 9.0494972e+09 | H20: 36023 | I20: 9950257.6 | J20: 21788683 | K20: =I20-J20 -> -11838425 | L20: =I20+Jan!L20 -> 20583916 | M20: =J20+Jan!M20 -> 66928621 | N20: =L20-M20 -> -46344705
... B27: 19 | C27: United Fund, Inc. | D27: 5.9229189e+08 | E27: 1560024.1 | F27: =D27-E27 -> 5.9073187e+08 | G27: 5.2026323e+08 | H27: 1303 | I27: 263765.73 | J27: 314979.52 | K27: =I27-J27 -> -51213.79 | L27: =I27+Jan!L27 -> 561599.59 | M27: =J27+Jan!M27 -> 3921612.2 | N27: =L27-M27 -> -3360012.6
A28: Primarily invested in Peso Securities (units)
B29: 20 | C29: COL Equity Index Unitized Mutual Fund, Inc. | D29: 1.7671353e+08 | E29: 2246958.8 | F29: =D29-E29 -> 1.7446658e+08 | G29: 1.7137742e+08 | H29: 1465 | I29: 45551836 | J29: 557412.75 | K29: =I29-J29 -> 44994424 | L29: =I29+Jan!L29 -> 64214155 | M29: =J29+Jan!M29 -> 2088941.2 | N29: =L29-M29 -> 62125214
B30: 21 | C30: Philequity Alpha One Fund, Inc. | D30: 3.4782165e+08 | E30: 10344952 | F30: =D30-E30 -> 3.3747669e+08 | G30: 3.1460403e+08 | H30: 1429 | I30: 3264446.1 | J30: 2521190.8 | K30: =I30-J30 -> 743255.36 | L30: =I30+Jan!L30 -> 4622204.5 | M30: =J30+Jan!M30 -> 12063407 | N30: =L30-M30 -> -7441203
B31: 22 | C31: Philippine Stock Index Fund Corp. | D31: 4.6996851e+08 | E31: 7064764.4 | F31: =D31-E31 -> 4.6290375e+08 | G31: 4.5824565e+08 | H31: 434548 | I31: 25170461 | J31: 17366285 | K31: =I31-J31 -> 7804176.4 | L31: =I31+Jan!L31 -> 58476497 | M31: =J31+Jan!M31 -> 71909731 | N31: =L31-M31 -> -13433235
A32: Exchange Traded Fund
B33: 23 | C33: First Metro Phil. Equity Exchange Traded Fund, Inc. | D33: 2.1365612e+09 | E33: 3745023.1 | F33: =D33-E33 -> 2132816191 | G33: 2.1297303e+09 | H33: 3245 | I33: 2057862 | J33: 0 | K33: =I33-J33 -> 2057862 | L33: =I33+Jan!L33 -> 3092394 | M33: =J33+Jan!M33 -> 73813261 | N33: =L33-M33 -> -70720867
A34: Sub total - Peso Currency | D34: =SUM(D9:D33) -> 68675584847 | E34: =SUM(E9:E33) -> 8.7031038e+08 | F34: =SUM(F9:F33) -> 67805274464 | G34: =SUM(G9:G33) -> 64436560313 | H34: =SUM(H9:H33) -> 721047 | I34: =SUM(I9:I33) -> 9.74199e+08 | J34: =SUM(J9:J33) -> 6.4554395e+08 | K34: =SUM(K9:K33) -> 3.2865505e+08 | ... N34: =SUM(N9:N33) -> -1.0224896e+08
A35: Primarily invested in foreign currency securities (shares)
B36: 24 | C36: ATRAM AsiaPlus Equity Fund, Inc. | D36: 36002947 | E36: 910124.83 | F36: =D36-E36 -> 35092822 | G36: 0 | H36: 54 | I36: 67873.86 | J36: 0 | K36: =I36-J36 -> 67873.86 | L36: =I36+Jan!L36 -> 68073.4 | M36: =J36+Jan!M36 -> 0 | N36: =L36-M36 -> 68073.4
B37: 25 | C37: Sun Life Prosperity World Voyager Fund, Inc. | D37: 1.8279623e+09 | E37: 8697686.8 | F37: =D37-E37 -> 1819264644 | G37: 0 | H37: 2879 | I37: 3800636 | J37: 19577478 | K37: =I37-J37 -> -15776842 | L37: =I37+Jan!L37 -> 16920677 | M37: =J37+Jan!M37 -> 49913545 | N37: =L37-M37 -> -32992868
A38: Sub total - US Currency | D38: =SUM(D36:D37) -> 1863965278 | E38: =SUM(E36:E37) -> 9607811.6 | F38: =SUM(F36:F37) -> 1854357466 | G38: =SUM(G36:G37) -> 0 | H38: =SUM(H36:H37) -> 2933 | I38: =SUM(I36:I37) -> 3868509.8 | J38: =SUM(J36:J37) -> 19577478 | K38: =SUM(K36:K37) -> -15708968 | ... N38: =SUM(N36:N37) -> -32924795
A39: Sub total - stock funds | D39: =D34+D38 -> 70539550125 | E39: =E34+E38 -> 879918195 | F39: =F34+F38 -> 69659631930 | G39: =G34+G38 -> 64436560313 | H39: =H34+H38 -> 723980 | I39: =I34+I38 -> 9.7806751e+08 | J39: =J34+J38 -> 665121432 | K39: =K34+K38 -> 3.1294608e+08 | ... N39: =N34+N38 -> -1.3517376e+08
A40: Balanced Funds
A41: Primarily invested in Peso Securities (shares)
B42: 26 | C42: ATRAM Dynamic Allocation Fund, Inc. | D42: 1.1782494e+08 | E42: 2052775 | F42: =D42-E42 -> 1.1577217e+08 | G42: 29155169 | H42: 722 | I42: 294604.87 | J42: 165504.09 | K42: =I42-J42 -> 129100.78 | L42: =I42+Jan!L42 -> 612854.55 | M42: =J42+Jan!M42 -> 432191.39 | N42: =L42-M42 -> 180663.16
B43: 27 | C43: ATRAM Philippine Balanced Fund, Inc. | D43: 5.8733469e+08 | E43: 11120079 | F43: =D43-E43 -> 5.7621461e+08 | G43: 2.3992904e+08 | H43: 2429 | I43: 1058123.5 | J43: 10518807 | K43: =I43-J43 -> -9460683.7 | L43: =I43+Jan!L43 -> 2105538 | M43: =J43+Jan!M43 -> 12448879 | N43: =L43-M43 -> -10343341
B44: 28 | C44: First Metro Save and Learn Balanced Fund, Inc. | D44: 1.0609576e+09 | E44: 6332406.8 | F44: =D44-E44 -> 1054625155 | G44: 5.5201376e+08 | H44: 4688 | I44: 1163040.7 | J44: 4113169.4 | K44: =I44-J44 -> -2950128.7 | L44: =I44+Jan!L44 -> 2498371.5 | M44: =J44+Jan!M44 -> 9249089.1 | N44: =L44-M44 -> -6750717.5
B45: 29 | C45: First Metro Save and Learn F.O.C.C.U.S. Dynamic Fund, Inc. | D45: 2.8443675e+08 | E45: 1055455.5 | F45: =D45-E45 -> 283381291 | G45: 1.7929856e+08 | H45: 237 | I45: 4505725.9 | J45: 16492535 | K45: =I45-J45 -> -11986809 | L45: =I45+Jan!L45 -> 9110349.3 | M45: =J45+Jan!M45 -> 28338687 | N45: =L45-M45 -> -19228338
B46: 30 | C46: NCM Mutual Fund of the Phils., Inc. | D46: 3.5178492e+08 | E46: 4220203.5 | F46: =D46-E46 -> 3.4756472e+08 | G46: 1.5637283e+08 | H46: 55 | I46: 0 | J46: 168529 | K46: =I46-J46 -> -168529 | L46: =I46+Jan!L46 -> 0 | M46: =J46+Jan!M46 -> 168529 | N46: =L46-M46 -> -168529
B47: 31 | C47: PAMI Horizon Fund, Inc. | D47: 564076019 | E47: 18049588 | F47: =D47-E47 -> 546026431 | G47: 306332735 | H47: 10092 | I47: 300871 | J47: 1650087 | K47: =I47-J47 -> -1349216 | L47: =I47+Jan!L47 -> 1713204.9 | M47: =J47+Jan!M47 -> 5209355.9 | N47: =L47-M47 -> -3496151
B48: 32 | C48: Philam Fund, Inc. | D48: 2096410633 | E48: 52703577 | F48: =D48-E48 -> 2043707056 | G48: 1790795424 | H48: 8175 | I48: 1749857 | J48: 6492626 | K48: =I48-J48 -> -4742769 | L48: =I48+Jan!L48 -> 4038703.4 | M48: =J48+Jan!M48 -> 31069436 | N48: =L48-M48 -> -27030732
B49: 33 | C49: Solidaritas Fund, Inc. | D49: 136914104 | E49: 160986 | F49: =D49-E49 -> 136753118 | G49: 83431779 | H49: 196 | I49: 10000 | J49: 43771 | K49: =I49-J49 -> -33771 | L49: =I49+Jan!L49 -> 21298.64 | M49: =J49+Jan!M49 -> 549385.82 | N49: =L49-M49 -> -528087.18
B50: 34 | C50: Sun Life Prosperity Balanced Fund, Inc. | D50: 7214953701 | E50: 40277844 | F50: =D50-E50 -> 7174675857 | G50: 3963500503 | H50: 53691 | I50: 7388076 | J50: 53931125 | K50: =I50-J50 -> -46543049 | L50: =I50+Jan!L50 -> 16664544 | M50: =J50+Jan!M50 -> 1.2452277e+08 | N50: =L50-M50 -> -1.0785823e+08
B51: 35 | C51: Sun Life Prosperity Dynamic Fund, Inc. | D51: 1165671247 | E51: 10912187 | F51: =D51-E51 -> 1154759060 | G51: 671160748 | H51: 4998 | I51: 0 | J51: 9387859 | K51: =I51-J51 -> -9387859 | L51: =I51+Jan!L51 -> 0 | M51: =J51+Jan!M51 -> 13961431 | N51: =L51-M51 -> -13961431
A52: Primarily invested in Peso Securities (units)
B53: 36 | C53: Sun Life Prosperity Achiever Fund 2028, Inc. | D53: 76254665 | E53: 336932 | F53: =D53-E53 -> 75917733 | G53: 21644500 | H53: 1066 | I53: 432120 | J53: 90647 | K53: =I53-J53 -> 341473 | L53: =I53+Jan!L53 -> 943425.2 | M53: =J53+Jan!M53 -> 171139.55 | N53: =L53-M53 -> 772285.65
B54: 37 | C54: Sun Life Prosperity Achiever Fund 2038, Inc. | D54: 56064518 | E54: 348141 | F54: =D54-E54 -> 55716377 | G54: 43479171 | H54: 415 | I54: 114547 | J54: 46389 | K54: =I54-J54 -> 68158 | L54: =I54+Jan!L54 -> 566602 | M54: =J54+Jan!M54 -> 186689.19 | N54: =L54-M54 -> 379912.81
B55: 38 | C55: Sun Life Prosperity Achiever Fund 2048, Inc. | D55: 46991363 | E55: 290656 | F55: =D55-E55 -> 46700707 | G55: 39341893 | H55: 194 | I55: 63937 | J55: 0 | K55: =I55-J55 -> 63937 | L55: =I55+Jan!L55 -> 133415 | M55: =J55+Jan!M55 -> 91381.96 | N55: =L55-M55 -> 42033.04
A56: Sub total - Peso Currency | D56: =SUM(D42:D55) -> 13759675114 | E56: =SUM(E42:E55) -> 1.4786083e+08 | F56: =SUM(F42:F55) -> 13611814283 | G56: =SUM(G42:G55) -> 8076456110 | H56: =SUM(H42:H55) -> 86958 | I56: =SUM(I42:I55) -> 17080903 | J56: =SUM(J42:J55) -> 1.0310105e+08 | K56: =SUM(K42:K55) -> -86020146 | ... N56: =SUM(N42:N55) -> -187990657
A57: Primarily invested in foreign currency securities (shares)
B58: 39 | C58: Cocolife Dollar Fund Builder, Inc. | D58: 71093821 | E58: 346255.14 | F58: =D58-E58 -> 70747566 | G58: 0 | H58: 52 | I58: 0 | J58: 57147.59 | K58: =I58-J58 -> -57147.59 | L58: =I58+Jan!L58 -> 0 | M58: =J58+Jan!M58 -> 106625.75 | N58: =L58-M58 -> -106625.75
B59: 40 | C59: PAMI Asia Balanced Fund, Inc. | D59: 348260441 | E59: 23496914 | F59: =D59-E59 -> 324763527 | G59: 174989281 | H59: 261 | I59: 0 | J59: 379026 | K59: =I59-J59 -> -379026 | L59: =I59+Jan!L59 -> 5365.648 | M59: =J59+Jan!M59 -> 3335522.1 | N59: =L59-M59 -> -3330156.4
B60: 41 | C60: Sun Life Prosperity Dollar Advantage Fund, Inc. | D60: 1.5383281e+09 | E60: 4112839.4 | F60: =D60-E60 -> 1534215300 | G60: 0 | H60: 4140 | I60: 1427065.8 | J60: 10046836 | K60: =I60-J60 -> -8619770.5 | L60: =I60+Jan!L60 -> 2319905.3 | M60: =J60+Jan!M60 -> 12389784 | N60: =L60-M60 -> -10069879
B61: 42 | C61: Sun Life Prosperity Dollar Wellspring Fund, Inc. | D61: 2.6439595e+08 | E61: 893040.03 | F61: =D61-E61 -> 263502912 | G61: 0 | H61: 716 | I61: 580965 | J61: 1447451.6 | K61: =I61-J61 -> -866486.61 | L61: =I61+Jan!L61 -> 645309.06 | M61: =J61+Jan!M61 -> 30628724 | N61: =L61-M61 -> -29983415
A62: Sub total - US Currency | D62: =SUM(D58:D61) -> 2222078353 | E62: =SUM(E58:E61) -> 28849049 | F62: =SUM(F58:F61) -> 2193229305 | G62: =SUM(G58:G61) -> 174989281 | H62: =SUM(H58:H61) -> 5169 | I62: =SUM(I58:I61) -> 2008030.8 | J62: =SUM(J58:J61) -> 11930462 | K62: =SUM(K58:K61) -> -9922430.7 | ... N62: =SUM(N58:N61) -> -43490076
A63: Sub total - balanced funds | D63: =D56+D62 -> 15981753467 | E63: =E56+E62 -> 1.7670988e+08 | F63: =F56+F62 -> 15805043587 | G63: =G56+G62 -> 8251445391 | H63: =H56+H62 -> 92127 | I63: =I56+I62 -> 19088934 | J63: =J56+J62 -> 1.1503151e+08 | K63: =K56+K62 -> -95942576 | ... N63: =N56+N62 -> -2.3148073e+08
A64: Bond Funds
A65: Primarily invested in Peso Securities (shares)
B66: 43 | C66: ALFM Peso Bond Fund, Inc. | D66: 39557541588 | E66: 249478809 | F66: =D66-E66 -> 39308062779 | G66: 928536400 | H66: 24899 | I66: 242673218 | J66: 552573883 | K66: =I66-J66 -> -309900665 | L66: =I66+Jan!L66 -> 5.4534847e+08 | M66: =J66+Jan!M66 -> 1245798056 | N66: =L66-M66 -> -700449585
B67: 44 | C67: ATRAM Corporate Bond Fund, Inc. | D67: 4.7195289e+08 | E67: 4094797.9 | F67: =D67-E67 -> 4.6785809e+08 | G67: 0 | H67: 1087 | I67: 8935649.5 | J67: 4390252 | K67: =I67-J67 -> 4545397.6 | L67: =I67+Jan!L67 -> 18190172 | M67: =J67+Jan!M67 -> 16330651 | N67: =L67-M67 -> 1859521.8
B68: 45 | C68: Cocolife Fixed Income Fund, Inc. | D68: 1.0224006e+09 | E68: 13728789 | F68: =D68-E68 -> 1008671767 | G68: 0 | H68: 1977 | I68: 8811746.7 | J68: 1727581.8 | K68: =I68-J68 -> 7084164.9 | L68: =I68+Jan!L68 -> 10308099 | M68: =J68+Jan!M68 -> 5261937.4 | N68: =L68-M68 -> 5046161.2
B69: 46 | C69: Ekklesia Mutual Fund, Inc. | D69: 197146258 | E69: 162819 | F69: =D69-E69 -> 196983439 | G69: 4925000 | H69: 188 | I69: 654486 | J69: 269367 | K69: =I69-J69 -> 385119 | L69: =I69+Jan!L69 -> 1231464 | M69: =J69+Jan!M69 -> 334471.65 | N69: =L69-M69 -> 896992.34
B70: 47 | C70: First Metro Save and Learn Fixed Income Fund, Inc. | D70: 1.350534e+09 | E70: 3855272.8 | F70: =D70-E70 -> 1346678717 | G70: 0 | H70: 1819 | I70: 60147068 | J70: 7860566.5 | K70: =I70-J70 -> 52286502 | L70: =I70+Jan!L70 -> 61283595 | M70: =J70+Jan!M70 -> 11118757 | N70: =L70-M70 -> 50164838
B71: 48 | C71: Philam Managed Income Fund, Inc. | D71: 762866999 | E71: 36936390 | F71: =D71-E71 -> 725930609 | G71: 0 | H71: 504 | I71: 1589421 | J71: 100348887 | K71: =I71-J71 -> -98759466 | L71: =I71+Jan!L71 -> 5424427.8 | M71: =J71+Jan!M71 -> 1.0134292e+08 | N71: =L71-M71 -> -95918488
B72: 49 | C72: Philam Bond Fund, Inc. | D72: 1731138338 | E72: 25064687 | F72: =D72-E72 -> 1706073651 | G72: 0 | H72: 5021 | I72: 3956151 | J72: 10358312 | K72: =I72-J72 -> -6402161 | L72: =I72+Jan!L72 -> 7288212.4 | M72: =J72+Jan!M72 -> 13657141 | N72: =L72-M72 -> -6368928.6
B73: 50 | C73: Philequity Peso Bond Fund, Inc. | D73: 3.0849286e+08 | E73: 785011.88 | F73: =D73-E73 -> 3.0770785e+08 | G73: 0 | H73: 4155 | I73: 1787242.8 | J73: 1988795.6 | K73: =I73-J73 -> -201552.72 | L73: =I73+Jan!L73 -> 2394611 | M73: =J73+Jan!M73 -> 3688147.8 | N73: =L73-M73 -> -1293536.7
B74: 51 | C74: Soldivo Bond Fund, Inc. | D74: 1.3105121e+09 | E74: 2707380.5 | F74: =D74-E74 -> 1307804768 | G74: 0 | H74: 826 | I74: 51850394 | J74: 2615076.6 | K74: =I74-J74 -> 49235317 | L74: =I74+Jan!L74 -> 76927308 | M74: =J74+Jan!M74 -> 2701453.8 | N74: =L74-M74 -> 74225854
B75: 52 | C75: Sun Life Prosperity Bond Fund, Inc. | D75: 4929364845 | E75: 107367033 | F75: =D75-E75 -> 4821997812 | G75: 0 | H75: 16766 | I75: 300277807 | J75: 133438808 | K75: =I75-J75 -> 166838999 | L75: =I75+Jan!L75 -> 462574371 | M75: =J75+Jan!M75 -> 183015173 | N75: =L75-M75 -> 279559198
B76: 53 | C76: Sun Life Prosperity GS Fund, Inc. | D76: 139753544 | E76: 476194 | F76: =D76-E76 -> 139277350 | G76: 0 | H76: 2655 | I76: 472411 | J76: 1014697 | K76: =I76-J76 -> -542286 | L76: =I76+Jan!L76 -> 994219.44 | M76: =J76+Jan!M76 -> 1538468.7 | N76: =L76-M76 -> -544249.27
A77: Sub total - Peso Currency | D77: =SUM(D66:D76) -> 51781704017 | E77: =SUM(E66:E76) -> 4.4465718e+08 | F77: =SUM(F66:F76) -> 51337046833 | G77: =SUM(G66:G76) -> 933461400 | H77: =SUM(H66:H76) -> 59897 | I77: =SUM(I66:I76) -> 6.811556e+08 | J77: =SUM(J66:J76) -> 8.1658623e+08 | K77: =SUM(K66:K76) -> -1.3543063e+08 | ... N77: =SUM(N66:N76) -> -3.9282222e+08
A78: Primarily invested in foreign currency securities (shares)
B79: 54 | C79: ALFM Dollar Bond Fund, Inc. | D79: 13761133166 | E79: 119318293 | F79: =D79-E79 -> 13641814873 | G79: 0 | H79: 8684 | I79: 51611027 | J79: 137086523 | K79: =I79-J79 -> -85475496 | L79: =I79+Jan!L79 -> 1.0521024e+08 | M79: =J79+Jan!M79 -> 2.3871696e+08 | N79: =L79-M79 -> -1.3350673e+08
B80: 55 | C80: ATRAM Total Return Dollar Bond Fund, Inc. | D80: 2.6073555e+08 | E80: 3215448.7 | F80: =D80-E80 -> 2.575201e+08 | G80: 0 | H80: 178 | I80: 982824.58 | J80: 1635325.7 | K80: =I80-J80 -> -652501.15 | L80: =I80+Jan!L80 -> 982824.58 | M80: =J80+Jan!M80 -> 2150501.2 | N80: =L80-M80 -> -1167676.6
B81: 56 | C81: First Metro Save and Learn Dollar Bond Fund, Inc. | D81: 4.3658613e+08 | E81: 3062843 | F81: =D81-E81 -> 4.3352329e+08 | G81: 0 | H81: 154 | I81: 4453005.2 | J81: 49640.08 | K81: =I81-J81 -> 4403365.1 | L81: =I81+Jan!L81 -> 5859293.5 | M81: =J81+Jan!M81 -> 5061323 | N81: =L81-M81 -> 797970.5
B82: 57 | C82: PAMI Global Bond Fund, Inc. | D82: 63460767 | E82: 13746483 | F82: =D82-E82 -> 49714284 | G82: 0 | H82: 27 | I82: 0 | J82: 0 | K82: =I82-J82 -> 0 | L82: =I82+Jan!L82 -> 0 | M82: =J82+Jan!M82 -> 0 | N82: =L82-M82 -> 0
B83: 58 | C83: Philam Dollar Bond Fund, Inc. | D83: 2007898828 | E83: 23177564 | F83: =D83-E83 -> 1984721264 | G83: 0 | H83: 1912 | I83: 21884 | J83: 3700611 | K83: =I83-J83 -> -3678727 | L83: =I83+Jan!L83 -> 97837.971 | M83: =J83+Jan!M83 -> 18324220 | N83: =L83-M83 -> -18226382
B84: 59 | C84: Philequity Dollar Income Fund, Inc. | D84: 2.3418504e+08 | E84: 1445677.4 | F84: =D84-E84 -> 2.3273937e+08 | G84: 0 | H84: 123 | I84: 5533 | J84: 0 | K84: =I84-J84 -> 5533 | L84: =I84+Jan!L84 -> 180381 | M84: =J84+Jan!M84 -> 0 | N84: =L84-M84 -> 180381
B85: 60 | C85: Sun Life Prosperity Dollar Abundance Fund, Inc. | D85: 5.2785099e+08 | E85: 2875234.5 | F85: =D85-E85 -> 5.2497576e+08 | G85: 0 | H85: 2532 | I85: 2207211.6 | J85: 2118507.1 | K85: =I85-J85 -> 88704.5 | L85: =I85+Jan!L85 -> 94089877 | M85: =J85+Jan!M85 -> 7993169.9 | N85: =L85-M85 -> 86096707
A86: Sub total - US Currency | D86: =SUM(D79:D85) -> 17291850477 | E86: =SUM(E79:E85) -> 1.6684154e+08 | F86: =SUM(F79:F85) -> 17125008934 | G86: =SUM(G79:G85) -> 0 | H86: =SUM(H79:H85) -> 13610 | I86: =SUM(I79:I85) -> 59281485 | J86: =SUM(J79:J85) -> 1.4459061e+08 | K86: =SUM(K79:K85) -> -85309122 | ... N86: =SUM(N79:N85) -> -65825726
B87: 61 | C87: ALFM Euro Bond Fund, Inc. | D87: 921604036 | E87: 7077020 | F87: =D87-E87 -> 914527016 | G87: 0 | H87: 655 | I87: 8706183 | J87: 3045328 | K87: =I87-J87 -> 5660855 | L87: =I87+Jan!L87 -> 15298867 | M87: =J87+Jan!M87 -> 4224827.2 | N87: =L87-M87 -> 11074040
A88: Sub total - Euro Currency | D88: =SUM(D87) -> 921604036 | E88: =SUM(E87) -> 7077020 | F88: =SUM(F87) -> 914527016 | G88: =SUM(G87) -> 0 | H88: =SUM(H87) -> 655 | I88: =SUM(I87) -> 8706183 | J88: =SUM(J87) -> 3045328 | K88: =SUM(K87) -> 5660855 | ... N88: =SUM(N87) -> 11074040
A89: Sub total - bond funds | D89: =D77+D86+D88 -> 69995158530 | E89: =E77+E86+E88 -> 6.1857575e+08 | F89: =F77+F86+F88 -> 69376582783 | G89: =G77+G86+G88 -> 933461400 | H89: =H77+H86+H88 -> 74162 | I89: =I77+I86+I88 -> 7.4914326e+08 | J89: =J77+J86+J88 -> 9.6422216e+08 | K89: =K77+K86+K88 -> -2.150789e+08 | ... N89: =N77+N86+N88 -> -4.4757391e+08
A90: Money Market Funds
A91: Primarily invested in Peso Securities (shares)
B92: 62 | C92: ALFM Money Market Fund, Inc. | D92: 39244415346 | E92: 22048133 | F92: =D92-E92 -> 39222367213 | G92: 0 | H92: 30173 | I92: 2124597522 | J92: 1956896351 | K92: =I92-J92 -> 167701171 | L92: =I92+Jan!L92 -> 5150643653 | M92: =J92+Jan!M92 -> 4743969917 | N92: =L92-M92 -> 4.0667374e+08
B93: 63 | C93: First Metro Save and Learn Money Market Fund, Inc. | D93: 2.6714801e+09 | E93: 77894931 | F93: =D93-E93 -> 2593585129 | G93: 0 | H93: 738 | I93: 33438758 | J93: 227804546 | K93: =I93-J93 -> -1.9436579e+08 | L93: =I93+Jan!L93 -> 1.5304552e+08 | M93: =J93+Jan!M93 -> 3.9867344e+08 | N93: =L93-M93 -> -2.4562792e+08
B94: 64 | C94: Sun Life Prosperity Peso Starter Fund, Inc. | D94: 43458718901 | E94: 428199966 | F94: =D94-E94 -> 43030518935 | G94: 0 | H94: 66321 | I94: 2503012141 | J94: 5624319829 | K94: =I94-J94 -> -3121307688 | L94: =I94+Jan!L94 -> 5232394385 | M94: =J94+Jan!M94 -> 14628677608 | N94: =L94-M94 -> -9396283223
A95: Primarily invested in Peso Securities (units)
B96: 65 | C96: ALFM Money Market Fund, Inc. | D96: 5.6836368e+09 | E96: 3332829.9 | F96: =D96-E96 -> 5680304006 | G96: 0 | H96: 4634 | I96: 1.6926897e+09 | J96: 5.4229828e+08 | K96: =I96-J96 -> 1150391411 | L96: =I96+Jan!L96 -> 3276967055 | M96: =J96+Jan!M96 -> 1141122022 | N96: =L96-M96 -> 2135845033
A97: Sub total - Peso Currency | D97: =SUM(D92:D94)+D96 -> 91058251142 | E97: =SUM(E92:E94)+E96 -> 5.3147586e+08 | F97: =SUM(F92:F94)+F96 -> 90526775282 | G97: =SUM(G92:G94)+G96 -> 0 | H97: =SUM(H92:H94)+H96 -> 101866 | I97: =SUM(I92:I94)+I96 -> 6353738115 | J97: =SUM(J92:J94)+J96 -> 8351319010 | K97: =SUM(K92:K94)+K96 -> -1997580895 | ... N97: =SUM(N92:N94)+N96 -> -7099392372
A98: Primarily invested in foreign currency securities (shares)
B99: 66 | C99: Sun Life Prosperity Dollar Starter Fund, Inc. | D99: 4.8058774e+09 | E99: 45259958 | F99: =D99-E99 -> 4760617410 | G99: 0 | H99: 3451 | I99: 8.2106291e+08 | J99: 1.0898046e+09 | K99: =I99-J99 -> -2.6874167e+08 | L99: =I99+Jan!L99 -> 2135718487 | M99: =J99+Jan!M99 -> 3088332386 | N99: =L99-M99 -> -9.526139e+08
A100: Sub total - US Currency | D100: =SUM(D99) -> 4805877368 | E100: =SUM(E99) -> 45259958 | F100: =SUM(F99) -> 4760617410 | G100: =SUM(G99) -> 0 | H100: =SUM(H99) -> 3451 | I100: =SUM(I99) -> 8.2106291e+08 | J100: =SUM(J99) -> 1089804587 | K100: =SUM(K99) -> -2.6874167e+08 | ... N100: =SUM(N99) -> -9.526139e+08
A101: Sub total - money market funds | D101: =D97+D100 -> 95864128510 | E101: =E97+E100 -> 5.7673582e+08 | F101: =F97+F100 -> 95287392693 | G101: =G97+G100 -> 0 | H101: =H97+H100 -> 105317 | I101: =I97+I100 -> 7174801028 | J101: =J97+J100 -> 9441123597 | K101: =K97+K100 -> -2266322569 | ... N101: =N97+N100 -> -8052006270
A102: Feeder Fund
A103: Primarily invested in Peso securities (units)
B104: 67 | C104: ALFM Global Multi-Asset Income Fund Inc. | D104: 9.347224e+09 | E104: 20388806 | F104: =D104-E104 -> 9326835215 | G104: 0 | H104: 88186 | I104: 87140372 | J104: 2.2659742e+08 | K104: =I104-J104 -> -1.3945704e+08 | L104: =I104+Jan!L104 -> 2.9117514e+08 | M104: =J104+Jan!M104 -> 3.0552855e+08 | N104: =L104-M104 -> -14353413
B105: 68 | C105: Sun Life Prosperity World Equity Index Feeder Fund, Inc. | D105: 3344004435 | E105: 12944973 | F105: =D105-E105 -> 3331059462 | G105: 0 | H105: 6016 | I105: 21802260 | J105: 39290342 | K105: =I105-J105 -> -17488082 | L105: =I105+Jan!L105 -> 47962318 | M105: =J105+Jan!M105 -> 96353581 | N105: =L105-M105 -> -48391263
A106: Sub total - Peso Currency | D106: =D104+D105 -> 12691228456 | E106: =E104+E105 -> 33333779 | F106: =F104+F105 -> 12657894677 | G106: =G104+G105 -> 0 | H106: =H104+H105 -> 94202 | I106: =I104+I105 -> 1.0894263e+08 | J106: =J104+J105 -> 2.6588776e+08 | K106: =K104+K105 -> -1.5694513e+08 | ... N106: =N104+N105 -> -62744676
...

Sheet Feb UPDATED
A1: PHILIPPINE INVESTMENT FUNDS ASSOCIATION, INC.
A2: MUTUAL FUNDS STATISTICAL REPORT
A3: Month of February 2023
A4: (Amounts in Peso)
I5: F O R - T H E - M O N T H | L5: Y E A R - T O - D A T E
A6: Fund Category | C6: Fund Name | D6: ASSETS | E6: LIABILITIES | F6: NET ASSETS | G6: EQUITY INV. | H6: NO. OF A/C | I6: SALES | J6: REDEMPTIONS | K6: NET SALES | L6: TOTAL SALES | M6: TOTAL REDEMPTIONS | N6: TOTAL NET SALES
A7: Stock Funds
A8: Primarily invested in Peso Securities (shares)
B9: 1 | C9: ALFM Growth Fund, Inc. | D9: 4593872904 | E9: 12038727 | F9: =D9-E9 -> 4581834177 | G9: 4291574273 | H9: 7236 | I9: 5275082 | J9: 24704237 | K9: =I9-J9 -> -19429155 | L9: =I9+Jan!L9 -> 11981921 | M9: =J9+Jan!M9 -> 99910370 | N9: =L9-M9 -> -87928449
B10: 2 | C10: ATRAM Alpha Opportunity Fund, Inc. | D10: 7.8551118e+08 | E10: 21049873 | F10: =D10-E10 -> 7.6446131e+08 | G10: 7.1177413e+08 | H10: 4221 | I10: 5560274.9 | J10: 12336999 | K10: =I10-J10 -> -6776724.6 | L10: =I10+Jan!L10 -> 10060031 | M10: =J10+Jan!M10 -> 28554190 | N10: =L10-M10 -> -18494159
B11: 3 | C11: ATRAM Phil. Equity Opportunity Fund, Inc. | D11: 1.6316838e+09 | E11: 1.0575227e+08 | F11: =D11-E11 -> 1525931484 | G11: 1.4548882e+09 | H11: 2874 | I11: 1.8514609e+08 | J11: 1.2266104e+08 | K11: =I11-J11 -> 62485054 | L11: =I11+Jan!L11 -> 3.7310243e+08 | M11: =J11+Jan!M11 -> 1.3291271e+08 | N11: =L11-M11 -> 2.4018971e+08
B12: 4 | C12: Climbs Share Capital Equity Investment Fund Corp. | D12: 3.6020278e+08 | E12: 17762394 | F12: =D12-E12 -> 3.4244039e+08 | G12: 2.0451595e+08 | H12: 1743 | I12: 588897.45 | J12: 71172.65 | K12: =I12-J12 -> 517724.8 | L12: =I12+Jan!L12 -> 1129901.9 | M12: =J12+Jan!M12 -> 179339.26 | N12: =L12-M12 -> 950562.69
B13: 5 | C13: First Metro Consumer Fund, Inc. | D13: 5.3822817e+08 | E13: 1229091.1 | F13: =D13-E13 -> 5.3699908e+08 | G13: 4.2599787e+08 | H13: 1428 | I13: 539284.43 | J13: 284725.86 | K13: =I13-J13 -> 254558.57 | L13: =I13+Jan!L13 -> 1303142.5 | M13: =J13+Jan!M13 -> 3583593.4 | N13: =L13-M13 -> -2280450.9
B14: 6 | C14: First Metro Save and Learn Equity Fund, Inc. | D14: 4.2099549e+09 | E14: 21850252 | F14: =D14-E14 -> 4188104604 | G14: 3.4415412e+09 | H14: 16190 | I14: 13071496 | J14: 17052745 | K14: =I14-J14 -> -3981249.8 | L14: =I14+Jan!L14 -> 32385308 | M14: =J14+Jan!M14 -> 71058749 | N14: =L14-M14 -> -38673441
B15: 7 | C15: First Metro Save and Learn Phil. Index Fund, Inc. | D15: 99621798 | E15: 1254140.8 | F15: =D15-E15 -> 98367658 | G15: 96925675 | H15: 554 | I15: 728740.25 | J15: 676891.31 | K15: =I15-J15 -> 51848.94 | L15: =I15+Jan!L15 -> 1489676.7 | M15: =J15+Jan!M15 -> 3847209.9 | N15: =L15-M15 -> -2357533.2
B16: 8 | C16: MBG Equity Investment Fund, Inc. | D16: 119846366 | E16: 2353974 | F16: =D16-E16 -> 117492392 | G16: 106689337 | H16: 50 | I16: 0 | J16: 496031 | K16: =I16-J16 -> -496031 | L16: =I16+Jan!L16 -> 0 | M16: =J16+Jan!M16 -> 496031 | N16: =L16-M16 -> -496031
B17: 9 | C17: PAMI Equity Index Fund, Inc. | D17: 1356343217 | E17: 74584016 | F17: =D17-E17 -> 1281759201 | G17: 1301656259 | H17: 12224 | I17: 0 | J17: 6972690 | K17: =I17-J17 -> -6972690 | L17: =I17+Jan!L17 -> 0 | M17: =J17+Jan!M17 -> 29187471 | N17: =L17-M17 -> -29187471
B18: 10 | C18: Philam Strategic Growth Fund, Inc. | D18: 3876027145 | E18: 161955174 | F18: =D18-E18 -> 3714071971 | G18: 3424225386 | H18: 12187 | I18: 3137498 | J18: 24799237 | K18: =I18-J18 -> -21661739 | L18: =I18+Jan!L18 -> 7829205 | M18: =J18+Jan!M18 -> 48041762 | N18: =L18-M18 -> -40212557
B19: 11 | C19: Philequity Dividend Yield Fund, Inc. | D19: 2.2240016e+09 | E19: 16490897 | F19: =D19-E19 -> 2207510676 | G19: 1.8905677e+09 | H19: 5618 | I19: 62015147 | J19: 3355607.8 | K19: =I19-J19 -> 58659539 | L19: =I19+Jan!L19 -> 1.3360903e+08 | M19: =J19+Jan!M19 -> 7631625.2 | N19: =L19-M19 -> 1.259774e+08
B20: 12 | C20: Philequity Fund, Inc. | D20: 9.9096779e+09 | E20: 1.7157781e+08 | F20: =D20-E20 -> 9738100086 | G20: 9.0494972e+09 | H20: 36023 | I20: 9950257.6 | J20: 21788683 | K20: =I20-J20 -> -11838425 | L20: =I20+Jan!L20 -> 20583916 | M20: =J20+Jan!M20 -> 66928621 | N20: =L20-M20 -> -46344705
... B27: 19 | C27: United Fund, Inc. | D27: 5.9229189e+08 | E27: 1560024.1 | F27: =D27-E27 -> 5.9073187e+08 | G27: 5.2026323e+08 | H27: 1303 | I27: 263765.73 | J27: 314979.52 | K27: =I27-J27 -> -51213.79 | L27: =I27+Jan!L27 -> 561599.59 | M27: =J27+Jan!M27 -> 3921612.2 | N27: =L27-M27 -> -3360012.6
A28: Primarily invested in Peso Securities (units)
B29: 20 | C29: COL Equity Index Unitized Mutual Fund, Inc. * | D29: 1.7671353e+08 | E29: 2246958.8 | F29: =D29-E29 -> 1.7446658e+08 | G29: 1.7137742e+08 | H29: 1465 | I29: 49591258 | J29: 608149.37 | K29: =I29-J29 -> 48983109 | L29: =I29+Jan!L29 -> 68253577 | M29: =J29+Jan!M29 -> 2139677.8 | N29: =L29-M29 -> 66113899
B30: 21 | C30: Philequity Alpha One Fund, Inc. | D30: 3.4782165e+08 | E30: 10344952 | F30: =D30-E30 -> 3.3747669e+08 | G30: 3.1460403e+08 | H30: 1429 | I30: 3264446.1 | J30: 2521190.8 | K30: =I30-J30 -> 743255.36 | L30: =I30+Jan!L30 -> 4622204.5 | M30: =J30+Jan!M30 -> 12063407 | N30: =L30-M30 -> -7441203
B31: 22 | C31: Philippine Stock Index Fund Corp. | D31: 4.6996851e+08 | E31: 7064764.4 | F31: =D31-E31 -> 4.6290375e+08 | G31: 4.5824565e+08 | H31: 434548 | I31: 25170461 | J31: 17366285 | K31: =I31-J31 -> 7804176.4 | L31: =I31+Jan!L31 -> 58476497 | M31: =J31+Jan!M31 -> 71909731 | N31: =L31-M31 -> -13433235
A32: Exchange Traded Fund
B33: 23 | C33: First Metro Phil. Equity Exchange Traded Fund, Inc. | D33: 2.1365612e+09 | E33: 3745023.1 | F33: =D33-E33 -> 2132816191 | G33: 2.1297303e+09 | H33: 3245 | I33: 2057862 | J33: 0 | K33: =I33-J33 -> 2057862 | L33: =I33+Jan!L33 -> 3092394 | M33: =J33+Jan!M33 -> 73813261 | N33: =L33-M33 -> -70720867
A34: Sub total - Peso Currency | D34: =SUM(D9:D33) -> 68675584847 | E34: =SUM(E9:E33) -> 8.7031038e+08 | F34: =SUM(F9:F33) -> 67805274464 | G34: =SUM(G9:G33) -> 64436560313 | H34: =SUM(H9:H33) -> 721047 | I34: =SUM(I9:I33) -> 9.7823842e+08 | J34: =SUM(J9:J33) -> 6.4559469e+08 | K34: =SUM(K9:K33) -> 332643732 | ... N34: =SUM(N9:N33) -> -98260279
A35: Primarily invested in foreign currency securities (shares)
B36: 24 | C36: ATRAM AsiaPlus Equity Fund, Inc. | D36: 36002947 | E36: 910124.83 | F36: =D36-E36 -> 35092822 | G36: 0 | H36: 54 | I36: 67873.86 | J36: 0 | K36: =I36-J36 -> 67873.86 | L36: =I36+Jan!L36 -> 68073.4 | M36: =J36+Jan!M36 -> 0 | N36: =L36-M36 -> 68073.4
B37: 25 | C37: Sun Life Prosperity World Voyager Fund, Inc. | D37: 1.8279623e+09 | E37: 8697686.8 | F37: =D37-E37 -> 1819264644 | G37: 0 | H37: 2879 | I37: 3800636 | J37: 19577478 | K37: =I37-J37 -> -15776842 | L37: =I37+Jan!L37 -> 16920677 | M37: =J37+Jan!M37 -> 49913545 | N37: =L37-M37 -> -32992868
A38: Sub total - US Currency | D38: =SUM(D36:D37) -> 1863965278 | E38: =SUM(E36:E37) -> 9607811.6 | F38: =SUM(F36:F37) -> 1854357466 | G38: =SUM(G36:G37) -> 0 | H38: =SUM(H36:H37) -> 2933 | I38: =SUM(I36:I37) -> 3868509.8 | J38: =SUM(J36:J37) -> 19577478 | K38: =SUM(K36:K37) -> -15708968 | ... N38: =SUM(N36:N37) -> -32924795
A39: Sub total - stock funds | D39: =D34+D38 -> 70539550125 | E39: =E34+E38 -> 879918195 | F39: =F34+F38 -> 69659631930 | G39: =G34+G38 -> 64436560313 | H39: =H34+H38 -> 723980 | I39: =I34+I38 -> 9.8210693e+08 | J39: =J34+J38 -> 6.6517217e+08 | K39: =K34+K38 -> 3.1693476e+08 | ... N39: =N34+N38 -> -1.3118507e+08
A40: Balanced Funds
A41: Primarily invested in Peso Securities (shares)
B42: 26 | C42: ATRAM Dynamic Allocation Fund, Inc. | D42: 1.1782494e+08 | E42: 2052775 | F42: =D42-E42 -> 1.1577217e+08 | G42: 29155169 | H42: 722 | I42: 294604.87 | J42: 165504.09 | K42: =I42-J42 -> 129100.78 | L42: =I42+Jan!L42 -> 612854.55 | M42: =J42+Jan!M42 -> 432191.39 | N42: =L42-M42 -> 180663.16
B43: 27 | C43: ATRAM Philippine Balanced Fund, Inc. | D43: 5.8733469e+08 | E43: 11120079 | F43: =D43-E43 -> 5.7621461e+08 | G43: 2.3992904e+08 | H43: 2429 | I43: 1058123.5 | J43: 10518807 | K43: =I43-J43 -> -9460683.7 | L43: =I43+Jan!L43 -> 2105538 | M43: =J43+Jan!M43 -> 12448879 | N43: =L43-M43 -> -10343341
B44: 28 | C44: First Metro Save and Learn Balanced Fund, Inc. | D44: 1.0609576e+09 | E44: 6332406.8 | F44: =D44-E44 -> 1054625155 | G44: 5.5201376e+08 | H44: 4688 | I44: 1163040.7 | J44: 4113169.4 | K44: =I44-J44 -> -2950128.7 | L44: =I44+Jan!L44 -> 2498371.5 | M44: =J44+Jan!M44 -> 9249089.1 | N44: =L44-M44 -> -6750717.5
B45: 29 | C45: First Metro Save and Learn F.O.C.C.U.S. Dynamic Fund, Inc. | D45: 2.8443675e+08 | E45: 1055455.5 | F45: =D45-E45 -> 283381291 | G45: 1.7929856e+08 | H45: 237 | I45: 4505725.9 | J45: 16492535 | K45: =I45-J45 -> -11986809 | L45: =I45+Jan!L45 -> 9110349.3 | M45: =J45+Jan!M45 -> 28338687 | N45: =L45-M45 -> -19228338
B46: 30 | C46: NCM Mutual Fund of the Phils., Inc. | D46: 3.5178492e+08 | E46: 4220203.5 | F46: =D46-E46 -> 3.4756472e+08 | G46: 1.5637283e+08 | H46: 55 | I46: 0 | J46: 168529 | K46: =I46-J46 -> -168529 | L46: =I46+Jan!L46 -> 0 | M46: =J46+Jan!M46 -> 168529 | N46: =L46-M46 -> -168529
B47: 31 | C47: PAMI Horizon Fund, Inc. | D47: 564076019 | E47: 18049588 | F47: =D47-E47 -> 546026431 | G47: 306332735 | H47: 10092 | I47: 300871 | J47: 1650087 | K47: =I47-J47 -> -1349216 | L47: =I47+Jan!L47 -> 1713204.9 | M47: =J47+Jan!M47 -> 5209355.9 | N47: =L47-M47 -> -3496151
B48: 32 | C48: Philam Fund, Inc. | D48: 2096410633 | E48: 52703577 | F48: =D48-E48 -> 2043707056 | G48: 1790795424 | H48: 8175 | I48: 1749857 | J48: 6492626 | K48: =I48-J48 -> -4742769 | L48: =I48+Jan!L48 -> 4038703.4 | M48: =J48+Jan!M48 -> 31069436 | N48: =L48-M48 -> -27030732
B49: 33 | C49: Solidaritas Fund, Inc. | D49: 136914104 | E49: 160986 | F49: =D49-E49 -> 136753118 | G49: 83431779 | H49: 196 | I49: 10000 | J49: 43771 | K49: =I49-J49 -> -33771 | L49: =I49+Jan!L49 -> 21298.64 | M49: =J49+Jan!M49 -> 549385.82 | N49: =L49-M49 -> -528087.18
B50: 34 | C50: Sun Life Prosperity Balanced Fund, Inc. | D50: 7214953701 | E50: 40277844 | F50: =D50-E50 -> 7174675857 | G50: 3963500503 | H50: 53691 | I50: 7388076 | J50: 53931125 | K50: =I50-J50 -> -46543049 | L50: =I50+Jan!L50 -> 16664544 | M50: =J50+Jan!M50 -> 1.2452277e+08 | N50: =L50-M50 -> -1.0785823e+08
B51: 35 | C51: Sun Life Prosperity Dynamic Fund, Inc. | D51: 1165671247 | E51: 10912187 | F51: =D51-E51 -> 1154759060 | G51: 671160748 | H51: 4998 | I51: 0 | J51: 9387859 | K51: =I51-J51 -> -9387859 | L51: =I51+Jan!L51 -> 0 | M51: =J51+Jan!M51 -> 13961431 | N51: =L51-M51 -> -13961431
A52: Primarily invested in Peso Securities (units)
B53: 36 | C53: Sun Life Prosperity Achiever Fund 2028, Inc. | D53: 76254665 | E53: 336932 | F53: =D53-E53 -> 75917733 | G53: 21644500 | H53: 1066 | I53: 432120 | J53: 90647 | K53: =I53-J53 -> 341473 | L53: =I53+Jan!L53 -> 943425.2 | M53: =J53+Jan!M53 -> 171139.55 | N53: =L53-M53 -> 772285.65
B54: 37 | C54: Sun Life Prosperity Achiever Fund 2038, Inc. | D54: 56064518 | E54: 348141 | F54: =D54-E54 -> 55716377 | G54: 43479171 | H54: 415 | I54: 114547 | J54: 46389 | K54: =I54-J54 -> 68158 | L54: =I54+Jan!L54 -> 566602 | M54: =J54+Jan!M54 -> 186689.19 | N54: =L54-M54 -> 379912.81
B55: 38 | C55: Sun Life Prosperity Achiever Fund 2048, Inc. | D55: 46991363 | E55: 290656 | F55: =D55-E55 -> 46700707 | G55: 39341893 | H55: 194 | I55: 63937 | J55: 0 | K55: =I55-J55 -> 63937 | L55: =I55+Jan!L55 -> 133415 | M55: =J55+Jan!M55 -> 91381.96 | N55: =L55-M55 -> 42033.04
A56: Sub total - Peso Currency | D56: =SUM(D42:D55) -> 13759675114 | E56: =SUM(E42:E55) -> 1.4786083e+08 | F56: =SUM(F42:F55) -> 13611814283 | G56: =SUM(G42:G55) -> 8076456110 | H56: =SUM(H42:H55) -> 86958 | I56: =SUM(I42:I55) -> 17080903 | J56: =SUM(J42:J55) -> 1.0310105e+08 | K56: =SUM(K42:K55) -> -86020146 | ... N56: =SUM(N42:N55) -> -187990657
A57: Primarily invested in foreign currency securities (shares)
B58: 39 | C58: Cocolife Dollar Fund Builder, Inc. | D58: 71093821 | E58: 346255.14 | F58: =D58-E58 -> 70747566 | G58: 0 | H58: 52 | I58: 0 | J58: 57147.59 | K58: =I58-J58 -> -57147.59 | L58: =I58+Jan!L58 -> 0 | M58: =J58+Jan!M58 -> 106625.75 | N58: =L58-M58 -> -106625.75
B59: 40 | C59: PAMI Asia Balanced Fund, Inc. | D59: 348260441 | E59: 23496914 | F59: =D59-E59 -> 324763527 | G59: 174989281 | H59: 261 | I59: 0 | J59: 379026 | K59: =I59-J59 -> -379026 | L59: =I59+Jan!L59 -> 5365.648 | M59: =J59+Jan!M59 -> 3335522.1 | N59: =L59-M59 -> -3330156.4
B60: 41 | C60: Sun Life Prosperity Dollar Advantage Fund, Inc. | D60: 1.5383281e+09 | E60: 4112839.4 | F60: =D60-E60 -> 1534215300 | G60: 0 | H60: 4140 | I60: 1427065.8 | J60: 10046836 | K60: =I60-J60 -> -8619770.5 | L60: =I60+Jan!L60 -> 2319905.3 | M60: =J60+Jan!M60 -> 12389784 | N60: =L60-M60 -> -10069879
B61: 42 | C61: Sun Life Prosperity Dollar Wellspring Fund, Inc. | D61: 2.6439595e+08 | E61: 893040.03 | F61: =D61-E61 -> 263502912 | G61: 0 | H61: 716 | I61: 580965 | J61: 1447451.6 | K61: =I61-J61 -> -866486.61 | L61: =I61+Jan!L61 -> 645309.06 | M61: =J61+Jan!M61 -> 30628724 | N61: =L61-M61 -> -29983415
A62: Sub total - US Currency | D62: =SUM(D58:D61) -> 2222078353 | E62: =SUM(E58:E61) -> 28849049 | F62: =SUM(F58:F61) -> 2193229305 | G62: =SUM(G58:G61) -> 174989281 | H62: =SUM(H58:H61) -> 5169 | I62: =SUM(I58:I61) -> 2008030.8 | J62: =SUM(J58:J61) -> 11930462 | K62: =SUM(K58:K61) -> -9922430.7 | ... N62: =SUM(N58:N61) -> -43490076
A63: Sub total - balanced funds | D63: =D56+D62 -> 15981753467 | E63: =E56+E62 -> 1.7670988e+08 | F63: =F56+F62 -> 15805043587 | G63: =G56+G62 -> 8251445391 | H63: =H56+H62 -> 92127 | I63: =I56+I62 -> 19088934 | J63: =J56+J62 -> 1.1503151e+08 | K63: =K56+K62 -> -95942576 | ... N63: =N56+N62 -> -2.3148073e+08
A64: Bond Funds
A65: Primarily invested in Peso Securities (shares)
B66: 43 | C66: ALFM Peso Bond Fund, Inc. | D66: 39557541588 | E66: 249478809 | F66: =D66-E66 -> 39308062779 | G66: 928536400 | H66: 24899 | I66: 242673218 | J66: 552573883 | K66: =I66-J66 -> -309900665 | L66: =I66+Jan!L66 -> 5.4534847e+08 | M66: =J66+Jan!M66 -> 1245798056 | N66: =L66-M66 -> -700449585
B67: 44 | C67: ATRAM Corporate Bond Fund, Inc. | D67: 4.7195289e+08 | E67: 4094797.9 | F67: =D67-E67 -> 4.6785809e+08 | G67: 0 | H67: 1087 | I67: 8935649.5 | J67: 4390252 | K67: =I67-J67 -> 4545397.6 | L67: =I67+Jan!L67 -> 18190172 | M67: =J67+Jan!M67 -> 16330651 | N67: =L67-M67 -> 1859521.8
B68: 45 | C68: Cocolife Fixed Income Fund, Inc. | D68: 1.0224006e+09 | E68: 13728789 | F68: =D68-E68 -> 1008671767 | G68: 0 | H68: 1977 | I68: 8811746.7 | J68: 1727581.8 | K68: =I68-J68 -> 7084164.9 | L68: =I68+Jan!L68 -> 10308099 | M68: =J68+Jan!M68 -> 5261937.4 | N68: =L68-M68 -> 5046161.2
B69: 46 | C69: Ekklesia Mutual Fund, Inc. | D69: 197146258 | E69: 162819 | F69: =D69-E69 -> 196983439 | G69: 4925000 | H69: 188 | I69: 654486 | J69: 269367 | K69: =I69-J69 -> 385119 | L69: =I69+Jan!L69 -> 1231464 | M69: =J69+Jan!M69 -> 334471.65 | N69: =L69-M69 -> 896992.34
B70: 47 | C70: First Metro Save and Learn Fixed Income Fund, Inc. | D70: 1.350534e+09 | E70: 3855272.8 | F70: =D70-E70 -> 1346678717 | G70: 0 | H70: 1819 | I70: 60147068 | J70: 7860566.5 | K70: =I70-J70 -> 52286502 | L70: =I70+Jan!L70 -> 61283595 | M70: =J70+Jan!M70 -> 11118757 | N70: =L70-M70 -> 50164838
B71: 48 | C71: Philam Managed Income Fund, Inc. | D71: 762866999 | E71: 36936390 | F71: =D71-E71 -> 725930609 | G71: 0 | H71: 504 | I71: 1589421 | J71: 100348887 | K71: =I71-J71 -> -98759466 | L71: =I71+Jan!L71 -> 5424427.8 | M71: =J71+Jan!M71 -> 1.0134292e+08 | N71: =L71-M71 -> -95918488
B72: 49 | C72: Philam Bond Fund, Inc. | D72: 1731138338 | E72: 25064687 | F72: =D72-E72 -> 1706073651 | G72: 0 | H72: 5021 | I72: 3956151 | J72: 10358312 | K72: =I72-J72 -> -6402161 | L72: =I72+Jan!L72 -> 7288212.4 | M72: =J72+Jan!M72 -> 13657141 | N72: =L72-M72 -> -6368928.6
B73: 50 | C73: Philequity Peso Bond Fund, Inc. | D73: 3.0849286e+08 | E73: 785011.88 | F73: =D73-E73 -> 3.0770785e+08 | G73: 0 | H73: 4155 | I73: 1787242.8 | J73: 1988795.6 | K73: =I73-J73 -> -201552.72 | L73: =I73+Jan!L73 -> 2394611 | M73: =J73+Jan!M73 -> 3688147.8 | N73: =L73-M73 -> -1293536.7
B74: 51 | C74: Soldivo Bond Fund, Inc. | D74: 1.3105121e+09 | E74: 2707380.5 | F74: =D74-E74 -> 1307804768 | G74: 0 | H74: 826 | I74: 51850394 | J74: 2615076.6 | K74: =I74-J74 -> 49235317 | L74: =I74+Jan!L74 -> 76927308 | M74: =J74+Jan!M74 -> 2701453.8 | N74: =L74-M74 -> 74225854
B75: 52 | C75: Sun Life Prosperity Bond Fund, Inc. | D75: 4929364845 | E75: 107367033 | F75: =D75-E75 -> 4821997812 | G75: 0 | H75: 16766 | I75: 300277807 | J75: 133438808 | K75: =I75-J75 -> 166838999 | L75: =I75+Jan!L75 -> 462574371 | M75: =J75+Jan!M75 -> 183015173 | N75: =L75-M75 -> 279559198
B76: 53 | C76: Sun Life Prosperity GS Fund, Inc. | D76: 139753544 | E76: 476194 | F76: =D76-E76 -> 139277350 | G76: 0 | H76: 2655 | I76: 472411 | J76: 1014697 | K76: =I76-J76 -> -542286 | L76: =I76+Jan!L76 -> 994219.44 | M76: =J76+Jan!M76 -> 1538468.7 | N76: =L76-M76 -> -544249.27
A77: Sub total - Peso Currency | D77: =SUM(D66:D76) -> 51781704017 | E77: =SUM(E66:E76) -> 4.4465718e+08 | F77: =SUM(F66:F76) -> 51337046833 | G77: =SUM(G66:G76) -> 933461400 | H77: =SUM(H66:H76) -> 59897 | I77: =SUM(I66:I76) -> 6.811556e+08 | J77: =SUM(J66:J76) -> 8.1658623e+08 | K77: =SUM(K66:K76) -> -1.3543063e+08 | ... N77: =SUM(N66:N76) -> -3.9282222e+08
A78: Primarily invested in foreign currency securities (shares)
B79: 54 | C79: ALFM Dollar Bond Fund, Inc. | D79: 13761133166 | E79: 119318293 | F79: =D79-E79 -> 13641814873 | G79: 0 | H79: 8684 | I79: 51611027 | J79: 137086523 | K79: =I79-J79 -> -85475496 | L79: =I79+Jan!L79 -> 1.0521024e+08 | M79: =J79+Jan!M79 -> 2.3871696e+08 | N79: =L79-M79 -> -1.3350673e+08
B80: 55 | C80: ATRAM Total Return Dollar Bond Fund, Inc. | D80: 2.6073555e+08 | E80: 3215448.7 | F80: =D80-E80 -> 2.575201e+08 | G80: 0 | H80: 178 | I80: 982824.58 | J80: 1635325.7 | K80: =I80-J80 -> -652501.15 | L80: =I80+Jan!L80 -> 982824.58 | M80: =J80+Jan!M80 -> 2150501.2 | N80: =L80-M80 -> -1167676.6
B81: 56 | C81: First Metro Save and Learn Dollar Bond Fund, Inc. | D81: 4.3658613e+08 | E81: 3062843 | F81: =D81-E81 -> 4.3352329e+08 | G81: 0 | H81: 154 | I81: 4453005.2 | J81: 49640.08 | K81: =I81-J81 -> 4403365.1 | L81: =I81+Jan!L81 -> 5859293.5 | M81: =J81+Jan!M81 -> 5061323 | N81: =L81-M81 -> 797970.5
B82: 57 | C82: PAMI Global Bond Fund, Inc. | D82: 63460767 | E82: 13746483 | F82: =D82-E82 -> 49714284 | G82: 0 | H82: 27 | I82: 0 | J82: 0 | K82: =I82-J82 -> 0 | L82: =I82+Jan!L82 -> 0 | M82: =J82+Jan!M82 -> 0 | N82: =L82-M82 -> 0
B83: 58 | C83: Philam Dollar Bond Fund, Inc. | D83: 2007898828 | E83: 23177564 | F83: =D83-E83 -> 1984721264 | G83: 0 | H83: 1912 | I83: 21884 | J83: 3700611 | K83: =I83-J83 -> -3678727 | L83: =I83+Jan!L83 -> 97837.971 | M83: =J83+Jan!M83 -> 18324220 | N83: =L83-M83 -> -18226382
B84: 59 | C84: Philequity Dollar Income Fund, Inc. | D84: 2.3418504e+08 | E84: 1445677.4 | F84: =D84-E84 -> 2.3273937e+08 | G84: 0 | H84: 123 | I84: 5533 | J84: 0 | K84: =I84-J84 -> 5533 | L84: =I84+Jan!L84 -> 180381 | M84: =J84+Jan!M84 -> 0 | N84: =L84-M84 -> 180381
B85: 60 | C85: Sun Life Prosperity Dollar Abundance Fund, Inc. | D85: 5.2785099e+08 | E85: 2875234.5 | F85: =D85-E85 -> 5.2497576e+08 | G85: 0 | H85: 2532 | I85: 2207211.6 | J85: 2118507.1 | K85: =I85-J85 -> 88704.5 | L85: =I85+Jan!L85 -> 94089877 | M85: =J85+Jan!M85 -> 7993169.9 | N85: =L85-M85 -> 86096707
A86: Sub total - US Currency | D86: =SUM(D79:D85) -> 17291850477 | E86: =SUM(E79:E85) -> 1.6684154e+08 | F86: =SUM(F79:F85) -> 17125008934 | G86: =SUM(G79:G85) -> 0 | H86: =SUM(H79:H85) -> 13610 | I86: =SUM(I79:I85) -> 59281485 | J86: =SUM(J79:J85) -> 1.4459061e+08 | K86: =SUM(K79:K85) -> -85309122 | ... N86: =SUM(N79:N85) -> -65825726
B87: 61 | C87: ALFM Euro Bond Fund, Inc. | D87: 921604036 | E87: 7077020 | F87: =D87-E87 -> 914527016 | G87: 0 | H87: 655 | I87: 8706183 | J87: 3045328 | K87: =I87-J87 -> 5660855 | L87: =I87+Jan!L87 -> 15298867 | M87: =J87+Jan!M87 -> 4224827.2 | N87: =L87-M87 -> 11074040
A88: Sub total - Euro Currency | D88: =SUM(D87) -> 921604036 | E88: =SUM(E87) -> 7077020 | F88: =SUM(F87) -> 914527016 | G88: =SUM(G87) -> 0 | H88: =SUM(H87) -> 655 | I88: =SUM(I87) -> 8706183 | J88: =SUM(J87) -> 3045328 | K88: =SUM(K87) -> 5660855 | ... N88: =SUM(N87) -> 11074040
A89: Sub total - bond funds | D89: =D77+D86+D88 -> 69995158530 | E89: =E77+E86+E88 -> 6.1857575e+08 | F89: =F77+F86+F88 -> 69376582783 | G89: =G77+G86+G88 -> 933461400 | H89: =H77+H86+H88 -> 74162 | I89: =I77+I86+I88 -> 7.4914326e+08 | J89: =J77+J86+J88 -> 9.6422216e+08 | K89: =K77+K86+K88 -> -2.150789e+08 | ... N89: =N77+N86+N88 -> -4.4757391e+08
A90: Money Market Funds
A91: Primarily invested in Peso Securities (shares)
B92: 62 | C92: ALFM Money Market Fund, Inc. | D92: 39244415346 | E92: 22048133 | F92: =D92-E92 -> 39222367213 | G92: 0 | H92: 30173 | I92: 2124597522 | J92: 1956896351 | K92: =I92-J92 -> 167701171 | L92: =I92+Jan!L92 -> 5150643653 | M92: =J92+Jan!M92 -> 4743969917 | N92: =L92-M92 -> 4.0667374e+08
B93: 63 | C93: First Metro Save and Learn Money Market Fund, Inc. | D93: 2.6714801e+09 | E93: 77894931 | F93: =D93-E93 -> 2593585129 | G93: 0 | H93: 738 | I93: 33438758 | J93: 227804546 | K93: =I93-J93 -> -1.9436579e+08 | L93: =I93+Jan!L93 -> 1.5304552e+08 | M93: =J93+Jan!M93 -> 3.9867344e+08 | N93: =L93-M93 -> -2.4562792e+08
B94: 64 | C94: Sun Life Prosperity Peso Starter Fund, Inc. | D94: 43458718901 | E94: 428199966 | F94: =D94-E94 -> 43030518935 | G94: 0 | H94: 66321 | I94: 2503012141 | J94: 5624319829 | K94: =I94-J94 -> -3121307688 | L94: =I94+Jan!L94 -> 5232394385 | M94: =J94+Jan!M94 -> 14628677608 | N94: =L94-M94 -> -9396283223
A95: Primarily invested in Peso Securities (units)
B96: 65 | C96: ALFM Money Market Fund, Inc. | D96: 5.6836368e+09 | E96: 3332829.9 | F96: =D96-E96 -> 5680304006 | G96: 0 | H96: 4634 | I96: 1.6926897e+09 | J96: 5.4229828e+08 | K96: =I96-J96 -> 1150391411 | L96: =I96+Jan!L96 -> 3276967055 | M96: =J96+Jan!M96 -> 1141122022 | N96: =L96-M96 -> 2135845033
A97: Sub total - Peso Currency | D97: =SUM(D92:D94)+D96 -> 91058251142 | E97: =SUM(E92:E94)+E96 -> 5.3147586e+08 | F97: =SUM(F92:F94)+F96 -> 90526775282 | G97: =SUM(G92:G94)+G96 -> 0 | H97: =SUM(H92:H94)+H96 -> 101866 | I97: =SUM(I92:I94)+I96 -> 6353738115 | J97: =SUM(J92:J94)+J96 -> 8351319010 | K97: =SUM(K92:K94)+K96 -> -1997580895 | ... N97: =SUM(N92:N94)+N96 -> -7099392372
A98: Primarily invested in foreign currency securities (shares)
B99: 66 | C99: Sun Life Prosperity Dollar Starter Fund, Inc. | D99: 4.8058774e+09 | E99: 45259958 | F99: =D99-E99 -> 4760617410 | G99: 0 | H99: 3451 | I99: 8.2106291e+08 | J99: 1.0898046e+09 | K99: =I99-J99 -> -2.6874167e+08 | L99: =I99+Jan!L99 -> 2135718487 | M99: =J99+Jan!M99 -> 3088332386 | N99: =L99-M99 -> -9.526139e+08
A100: Sub total - US Currency | D100: =SUM(D99) -> 4805877368 | E100: =SUM(E99) -> 45259958 | F100: =SUM(F99) -> 4760617410 | G100: =SUM(G99) -> 0 | H100: =SUM(H99) -> 3451 | I100: =SUM(I99) -> 8.2106291e+08 | J100: =SUM(J99) -> 1089804587 | K100: =SUM(K99) -> -2.6874167e+08 | ... N100: =SUM(N99) -> -9.526139e+08
A101: Sub total - money market funds | D101: =D97+D100 -> 95864128510 | E101: =E97+E100 -> 5.7673582e+08 | F101: =F97+F100 -> 95287392693 | G101: =G97+G100 -> 0 | H101: =H97+H100 -> 105317 | I101: =I97+I100 -> 7174801028 | J101: =J97+J100 -> 9441123597 | K101: =K97+K100 -> -2266322569 | ... N101: =N97+N100 -> -8052006270
A102: Feeder Fund
A103: Primarily invested in Peso securities (units)
B104: 67 | C104: ALFM Global Multi-Asset Income Fund Inc. | D104: 9.347224e+09 | E104: 20388806 | F104: =D104-E104 -> 9326835215 | G104: 0 | H104: 88186 | I104: 87140372 | J104: 2.2659742e+08 | K104: =I104-J104 -> -1.3945704e+08 | L104: =I104+Jan!L104 -> 2.9117514e+08 | M104: =J104+Jan!M104 -> 3.0552855e+08 | N104: =L104-M104 -> -14353413
B105: 68 | C105: Sun Life Prosperity World Equity Index Feeder Fund, Inc. | D105: 3344004435 | E105: 12944973 | F105: =D105-E105 -> 3331059462 | G105: 0 | H105: 6016 | I105: 21802260 | J105: 39290342 | K105: =I105-J105 -> -17488082 | L105: =I105+Jan!L105 -> 47962318 | M105: =J105+Jan!M105 -> 96353581 | N105: =L105-M105 -> -48391263
A106: Sub total - Peso Currency | D106: =D104+D105 -> 12691228456 | E106: =E104+E105 -> 33333779 | F106: =F104+F105 -> 12657894677 | G106: =G104+G105 -> 0 | H106: =H104+H105 -> 94202 | I106: =I104+I105 -> 1.0894263e+08 | J106: =J104+J105 -> 2.6588776e+08 | K106: =K104+K105 -> -1.5694513e+08 | ... N106: =N104+N105 -> -62744676
...

Sheet Mar
A1: PHILIPPINE INVESTMENT FUNDS ASSOCIATION, INC.
A2: MUTUAL FUNDS STATISTICAL REPORT
A3: Month of March 2023
A4: (Amounts in Peso)
I5: F O R - T H E - M O N T H | L5: Y E A R - T O - D A T E
A6: Fund Category | C6: Fund Name | D6: ASSETS | E6: LIABILITIES | F6: NET ASSETS | G6: EQUITY INV. | H6: NO. OF A/C | I6: SALES | J6: REDEMPTIONS | K6: NET SALES | L6: TOTAL SALES | M6: TOTAL REDEMPTIONS | N6: TOTAL NET SALES
A7: Stock Funds
A8: Primarily invested in Peso Securities (shares)
B9: 1 | C9: ALFM Growth Fund, Inc. | D9: 4.5930377e+09 | E9: 13267230 | F9: =D9-E9 -> 4579770512 | G9: 4.1517953e+09 | H9: 7209 | I9: 7212185.2 | J9: 51464462 | K9: =I9-J9 -> -44252276 | L9: =I9+'Feb UPDATED'!L9 -> 19194106 | M9: =J9+'Feb UPDATED'!M9 -> 151374832 | N9: =L9-M9 -> -1.3218073e+08
B10: 2 | C10: ATRAM Alpha Opportunity Fund, Inc. | D10: 7.6055047e+08 | E10: 2013776.8 | F10: =D10-E10 -> 7.5853669e+08 | G10: 7.1270159e+08 | H10: 4236 | I10: 5649888.2 | J10: 7842522.9 | K10: =I10-J10 -> -2192634.8 | L10: =I10+'Feb UPDATED'!L10 -> 15709919 | M10: =J10+'Feb UPDATED'!M10 -> 36396713 | N10: =L10-M10 -> -20686794
B11: 3 | C11: ATRAM Phil. Equity Opportunity Fund, Inc. | D11: 1.5343198e+09 | E11: 10438363 | F11: =D11-E11 -> 1523881453 | G11: 1.4512293e+09 | H11: 2853 | I11: 13436930 | J11: 30540757 | K11: =I11-J11 -> -17103827 | L11: =I11+'Feb UPDATED'!L11 -> 3.8653936e+08 | M11: =J11+'Feb UPDATED'!M11 -> 1.6345347e+08 | N11: =L11-M11 -> 223085885
B12: 4 | C12: Climbs Share Capital Equity Investment Fund Corp. | D12: 348883651 | E12: 8791778 | F12: =D12-E12 -> 340091873 | G12: 220716415 | H12: 1764 | I12: 536436 | J12: 1007506 | K12: =I12-J12 -> -471070 | L12: =I12+'Feb UPDATED'!L12 -> 1666337.9 | M12: =J12+'Feb UPDATED'!M12 -> 1186845.3 | N12: =L12-M12 -> 479492.69
B13: 5 | C13: First Metro Consumer Fund, Inc. | D13: 541654128 | E13: 16316480 | F13: =D13-E13 -> 525337648 | G13: 406134465 | H13: 1417 | I13: 704602 | J13: 1284122 | K13: =I13-J13 -> -579520 | L13: =I13+'Feb UPDATED'!L13 -> 2007744.5 | M13: =J13+'Feb UPDATED'!M13 -> 4867715.4 | N13: =L13-M13 -> -2859970.9
B14: 6 | C14: First Metro Save and Learn Equity Fund, Inc. | D14: 4294125331 | E14: 54589409 | F14: =D14-E14 -> 4239535922 | G14: 3446659166 | H14: 16139 | I14: 53938628 | J14: 17662981 | K14: =I14-J14 -> 36275647 | L14: =I14+'Feb UPDATED'!L14 -> 86323936 | M14: =J14+'Feb UPDATED'!M14 -> 88721730 | N14: =L14-M14 -> -2397794
B15: 7 | C15: First Metro Save and Learn Phil. Index Fund, Inc. | D15: 102660882 | E15: 1124945 | F15: =D15-E15 -> 101535937 | G15: 98641450 | H15: 549 | I15: 3956298 | J15: 959993 | K15: =I15-J15 -> 2996305 | L15: =I15+'Feb UPDATED'!L15 -> 5445974.7 | M15: =J15+'Feb UPDATED'!M15 -> 4807202.9 | N15: =L15-M15 -> 638771.8
B16: 8 | C16: MBG Equity Investment Fund, Inc. | D16: 1.2168999e+08 | E16: 1062505 | F16: =D16-E16 -> 1.2062748e+08 | G16: 105391640 | H16: 51 | I16: 241.49 | J16: 268193.93 | K16: =I16-J16 -> -267952.44 | L16: =I16+'Feb UPDATED'!L16 -> 241.49 | M16: =J16+'Feb UPDATED'!M16 -> 764224.93 | N16: =L16-M16 -> -763983.44
B17: 9 | C17: PAMI Equity Index Fund, Inc. | D17: 1.3464719e+09 | E17: 79787345 | F17: =D17-E17 -> 1266684572 | G17: 1.281623e+09 | H17: 12183 | I17: 0 | J17: 20483067 | K17: =I17-J17 -> -20483067 | L17: =I17+'Feb UPDATED'!L17 -> 0 | M17: =J17+'Feb UPDATED'!M17 -> 49670539 | N17: =L17-M17 -> -49670539
B18: 10 | C18: Philam Strategic Growth Fund, Inc. | D18: 3.8702801e+09 | E18: 1.6238491e+08 | F18: =D18-E18 -> 3707895226 | G18: 3.3366802e+09 | H18: 12130 | I18: 2454163.6 | J18: 39361027 | K18: =I18-J18 -> -36906863 | L18: =I18+'Feb UPDATED'!L18 -> 10283369 | M18: =J18+'Feb UPDATED'!M18 -> 87402788 | N18: =L18-M18 -> -77119420
B19: 11 | C19: Philequity Dividend Yield Fund, Inc. | D19: 2324690919 | E19: 67392048 | F19: =D19-E19 -> 2257298871 | G19: 2002288623 | H19: 5565 | I19: 1859089 | J19: 3785416 | K19: =I19-J19 -> -1926327 | L19: =I19+'Feb UPDATED'!L19 -> 1.3546812e+08 | M19: =J19+'Feb UPDATED'!M19 -> 11417041 | N19: =L19-M19 -> 1.2405108e+08
B20: 12 | C20: Philequity Fund, Inc. | D20: 9851454792 | E20: 48552221 | F20: =D20-E20 -> 9802902571 | G20: 9048438933 | H20: 35874 | I20: 43035302 | J20: 88408991 | K20: =I20-J20 -> -45373689 | L20: =I20+'Feb UPDATED'!L20 -> 63619218 | M20: =J20+'Feb UPDATED'!M20 -> 1.5533761e+08 | N20: =L20-M20 -> -91718394
... B27: 19 | C27: United Fund, Inc. | D27: 593533972 | E27: 1520125 | F27: =D27-E27 -> 592013847 | G27: 520375775 | H27: 1302 | I27: 3393106 | J27: 219792 | K27: =I27-J27 -> 3173314 | L27: =I27+'Feb UPDATED'!L27 -> 3954705.6 | M27: =J27+'Feb UPDATED'!M27 -> 4141404.2 | N27: =L27-M27 -> -186698.59
A28: Primarily invested in Peso Securities (units)
B29: 20 | C29: COL Equity Index Unitized Mutual Fund, Inc. | D29: 188703003 | E29: 1910155 | F29: =D29-E29 -> 186792848 | G29: 182350549 | H29: 1715 | I29: 14561464 | J29: 1720354 | K29: =I29-J29 -> 12841110 | L29: =I29+'Feb UPDATED'!L29 -> 82815041 | M29: =J29+'Feb UPDATED'!M29 -> 3860031.8 | N29: =L29-M29 -> 78955009
B30: 21 | C30: Philequity Alpha One Fund, Inc. | D30: 344864889 | E30: 915563 | F30: =D30-E30 -> 343949326 | G30: 309407557 | H30: 1423 | I30: 3497496 | J30: 778190 | K30: =I30-J30 -> 2719306 | L30: =I30+'Feb UPDATED'!L30 -> 8119700.5 | M30: =J30+'Feb UPDATED'!M30 -> 12841597 | N30: =L30-M30 -> -4721897
B31: 22 | C31: Philippine Stock Index Fund Corp. | D31: 4.9618635e+08 | E31: 7396072.5 | F31: =D31-E31 -> 4.8879028e+08 | G31: 4.8592705e+08 | H31: 370846 | I31: 39144887 | J31: 15349031 | K31: =I31-J31 -> 23795856 | L31: =I31+'Feb UPDATED'!L31 -> 97621384 | M31: =J31+'Feb UPDATED'!M31 -> 87258762 | N31: =L31-M31 -> 10362622
A32: Exchange Traded Fund
B33: 23 | C33: First Metro Phil. Equity Exchange Traded Fund, Inc. | D33: 2163447240 | E33: 1898036 | F33: =D33-E33 -> 2161549204 | G33: 2129490212 | H33: 3275 | I33: 21164197 | J33: 3087328 | K33: =I33-J33 -> 18076869 | L33: =I33+'Feb UPDATED'!L33 -> 24256591 | M33: =J33+'Feb UPDATED'!M33 -> 76900589 | N33: =L33-M33 -> -52643998
A34: Sub total - Peso Currency | D34: =SUM(D9:D33) -> 68839892558 | E34: =SUM(E9:E33) -> 7.4316658e+08 | F34: =SUM(F9:F33) -> 68096725981 | G34: =SUM(G9:G33) -> 64102287028 | H34: =SUM(H9:H33) -> 657161 | I34: =SUM(I9:I33) -> 4.5161649e+08 | J34: =SUM(J9:J33) -> 5.8120572e+08 | K34: =SUM(K9:K33) -> -1.2958923e+08 | ... N34: =SUM(N9:N33) -> -2.278495e+08
A35: Primarily invested in foreign currency securities (shares)
B36: 24 | C36: ATRAM AsiaPlus Equity Fund, Inc. | D36: 35712481 | E36: 1261270.5 | F36: =D36-E36 -> 34451210 | G36: 0 | H36: 54 | I36: 10806.22 | J36: 19382.09 | K36: =I36-J36 -> -8575.87 | L36: =I36+'Feb UPDATED'!L36 -> 78879.62 | M36: =J36+'Feb UPDATED'!M36 -> 19382.09 | N36: =L36-M36 -> 59497.53
B37: 25 | C37: Sun Life Prosperity World Voyager Fund, Inc. | D37: 1796930439 | E37: 27142106 | F37: =D37-E37 -> 1769788333 | G37: 0 | H37: 2880 | I37: 1554385 | J37: 27846024 | K37: =I37-J37 -> -26291639 | L37: =I37+'Feb UPDATED'!L37 -> 18475062 | M37: =J37+'Feb UPDATED'!M37 -> 77759569 | N37: =L37-M37 -> -59284507
A38: Sub total - US Currency | D38: =SUM(D36:D37) -> 1832642920 | E38: =SUM(E36:E37) -> 28403376 | F38: =SUM(F36:F37) -> 1804239543 | G38: =SUM(G36:G37) -> 0 | H38: =SUM(H36:H37) -> 2934 | I38: =SUM(I36:I37) -> 1565191.2 | J38: =SUM(J36:J37) -> 27865406 | K38: =SUM(K36:K37) -> -26300215 | ... N38: =SUM(N36:N37) -> -59225009
A39: Sub total - stock funds | D39: =D34+D38 -> 70672535478 | E39: =E34+E38 -> 7.7156995e+08 | F39: =F34+F38 -> 69900965524 | G39: =G34+G38 -> 64102287028 | H39: =H34+H38 -> 660095 | I39: =I34+I38 -> 4.5318168e+08 | J39: =J34+J38 -> 6.0907112e+08 | K39: =K34+K38 -> -1.5588944e+08 | ... N39: =N34+N38 -> -2.8707451e+08
A40: Balanced Funds
A41: Primarily invested in Peso Securities (shares)
B42: 26 | C42: ATRAM Dynamic Allocation Fund, Inc. | D42: 1.2098976e+08 | E42: 4620873.4 | F42: =D42-E42 -> 116368890 | G42: 38906616 | H42: 721 | I42: 477641.51 | J42: 307049.61 | K42: =I42-J42 -> 170591.9 | L42: =I42+'Feb UPDATED'!L42 -> 1090496.1 | M42: =J42+'Feb UPDATED'!M42 -> 739241 | N42: =L42-M42 -> 351255.06
B43: 27 | C43: ATRAM Philippine Balanced Fund, Inc. | D43: 6.1051091e+08 | E43: 29223817 | F43: =D43-E43 -> 5.812871e+08 | G43: 3.0887455e+08 | H43: 2421 | I43: 1018084.1 | J43: 3716688.6 | K43: =I43-J43 -> -2698604.5 | L43: =I43+'Feb UPDATED'!L43 -> 3123622.1 | M43: =J43+'Feb UPDATED'!M43 -> 16165567 | N43: =L43-M43 -> -13041945
B44: 28 | C44: First Metro Save and Learn Balanced Fund, Inc. | D44: 1066573414 | E44: 10403781 | F44: =D44-E44 -> 1056169633 | G44: 491266510 | H44: 4666 | I44: 3988943 | J44: 5214011 | K44: =I44-J44 -> -1225068 | L44: =I44+'Feb UPDATED'!L44 -> 6487314.5 | M44: =J44+'Feb UPDATED'!M44 -> 14463100 | N44: =L44-M44 -> -7975785.5
B45: 29 | C45: First Metro Save and Learn F.O.C.C.U.S. Dynamic Fund, Inc. | D45: 275364511 | E45: 5099873 | F45: =D45-E45 -> 270264638 | G45: 127721725 | H45: 242 | I45: 561245 | J45: 14197748 | K45: =I45-J45 -> -13636503 | L45: =I45+'Feb UPDATED'!L45 -> 9671594.3 | M45: =J45+'Feb UPDATED'!M45 -> 42536435 | N45: =L45-M45 -> -32864841
B46: 30 | C46: NCM Mutual Fund of the Phils., Inc. | D46: 348826992 | E46: 4210140 | F46: =D46-E46 -> 344616852 | G46: 154934365 | H46: 54 | I46: 0 | J46: 1339656 | K46: =I46-J46 -> -1339656 | L46: =I46+'Feb UPDATED'!L46 -> 0 | M46: =J46+'Feb UPDATED'!M46 -> 1508185 | N46: =L46-M46 -> -1508185
B47: 31 | C47: PAMI Horizon Fund, Inc. | D47: 5.6385721e+08 | E47: 20204359 | F47: =D47-E47 -> 5.4365285e+08 | G47: 3.0579294e+08 | H47: 10074 | I47: 215789.38 | J47: 6913739.3 | K47: =I47-J47 -> -6697949.9 | L47: =I47+'Feb UPDATED'!L47 -> 1928994.3 | M47: =J47+'Feb UPDATED'!M47 -> 12123095 | N47: =L47-M47 -> -10194101
B48: 32 | C48: Philam Fund, Inc. | D48: 2.1100465e+09 | E48: 69105628 | F48: =D48-E48 -> 2040940824 | G48: 1.0466916e+09 | H48: 8155 | I48: 2603529.8 | J48: 17599054 | K48: =I48-J48 -> -14995524 | L48: =I48+'Feb UPDATED'!L48 -> 6642233.2 | M48: =J48+'Feb UPDATED'!M48 -> 48668489 | N48: =L48-M48 -> -42026256
B49: 33 | C49: Solidaritas Fund, Inc. | D49: 1.3688718e+08 | E49: 175395.72 | F49: =D49-E49 -> 1.3671178e+08 | G49: 76744985 | H49: 198 | I49: 189997.69 | J49: 1083116.3 | K49: =I49-J49 -> -893118.63 | L49: =I49+'Feb UPDATED'!L49 -> 211296.33 | M49: =J49+'Feb UPDATED'!M49 -> 1632502.1 | N49: =L49-M49 -> -1421205.8
B50: 34 | C50: Sun Life Prosperity Balanced Fund, Inc. | D50: 7375675892 | E50: 198603406 | F50: =D50-E50 -> 7177072486 | G50: 3589499495 | H50: 53735 | I50: 9233564 | J50: 41999437 | K50: =I50-J50 -> -32765873 | L50: =I50+'Feb UPDATED'!L50 -> 25898108 | M50: =J50+'Feb UPDATED'!M50 -> 1.6652221e+08 | N50: =L50-M50 -> -1.406241e+08
B51: 35 | C51: Sun Life Prosperity Dynamic Fund, Inc. | D51: 1163857508 | E51: 5762876 | F51: =D51-E51 -> 1158094632 | G51: 601738295 | H51: 4998 | I51: 0 | J51: 1812809 | K51: =I51-J51 -> -1812809 | L51: =I51+'Feb UPDATED'!L51 -> 0 | M51: =J51+'Feb UPDATED'!M51 -> 15774240 | N51: =L51-M51 -> -15774240
A52: Primarily invested in Peso Securities (units)
B53: 36 | C53: Sun Life Prosperity Achiever Fund 2028, Inc. | D53: 77087833 | E53: 263561 | F53: =D53-E53 -> 76824272 | G53: 22733718 | H53: 1076 | I53: 693746 | J53: 160402 | K53: =I53-J53 -> 533344 | L53: =I53+'Feb UPDATED'!L53 -> 1637171.2 | M53: =J53+'Feb UPDATED'!M53 -> 331541.55 | N53: =L53-M53 -> 1305629.6
B54: 37 | C54: Sun Life Prosperity Achiever Fund 2038, Inc. | D54: 56229131 | E54: 286320 | F54: =D54-E54 -> 55942811 | G54: 43989740 | H54: 418 | I54: 119139 | J54: 134976 | K54: =I54-J54 -> -15837 | L54: =I54+'Feb UPDATED'!L54 -> 685741 | M54: =J54+'Feb UPDATED'!M54 -> 321665.19 | N54: =L54-M54 -> 364075.81
B55: 38 | C55: Sun Life Prosperity Achiever Fund 2048, Inc. | D55: 47437164 | E55: 553991 | F55: =D55-E55 -> 46883173 | G55: 39614389 | H55: 196 | I55: 48535 | J55: 0 | K55: =I55-J55 -> 48535 | L55: =I55+'Feb UPDATED'!L55 -> 181950 | M55: =J55+'Feb UPDATED'!M55 -> 91381.96 | N55: =L55-M55 -> 90568.04
A56: Sub total - Peso Currency | D56: =SUM(D42:D55) -> 13953343963 | E56: =SUM(E42:E55) -> 3.4851402e+08 | F56: =SUM(F42:F55) -> 13604829942 | G56: =SUM(G42:G55) -> 6848508926 | H56: =SUM(H42:H55) -> 86954 | I56: =SUM(I42:I55) -> 19150215 | J56: =SUM(J42:J55) -> 94478687 | K56: =SUM(K42:K55) -> -75328472 | ... N56: =SUM(N42:N55) -> -2.6331913e+08
A57: Primarily invested in foreign currency securities (shares)
B58: 39 | C58: Cocolife Dollar Fund Builder, Inc. | D58: 70617171 | E58: 405074 | F58: =D58-E58 -> 70212097 | G58: 0 | H58: 51 | I58: 0 | J58: 341250 | K58: =I58-J58 -> -341250 | L58: =I58+'Feb UPDATED'!L58 -> 0 | M58: =J58+'Feb UPDATED'!M58 -> 447875.75 | N58: =L58-M58 -> -447875.75
B59: 40 | C59: PAMI Asia Balanced Fund, Inc. | D59: 3.4893296e+08 | E59: 27256048 | F59: =D59-E59 -> 3.2167691e+08 | G59: 1.7359193e+08 | H59: 259 | I59: 265.8204 | J59: 6403718.4 | K59: =I59-J59 -> -6403452.5 | L59: =I59+'Feb UPDATED'!L59 -> 5631.4684 | M59: =J59+'Feb UPDATED'!M59 -> 9739240.4 | N59: =L59-M59 -> -9733609
B60: 41 | C60: Sun Life Prosperity Dollar Advantage Fund, Inc. | D60: 1514624970 | E60: 25346512 | F60: =D60-E60 -> 1489278458 | G60: 0 | H60: 4142 | I60: 447058 | J60: 31627503 | K60: =I60-J60 -> -31180445 | L60: =I60+'Feb UPDATED'!L60 -> 2766963.3 | M60: =J60+'Feb UPDATED'!M60 -> 44017287 | N60: =L60-M60 -> -41250324
B61: 42 | C61: Sun Life Prosperity Dollar Wellspring Fund, Inc. | D61: 262558618 | E61: 713341 | F61: =D61-E61 -> 261845277 | G61: 0 | H61: 717 | I61: 0 | J61: 328480 | K61: =I61-J61 -> -328480 | L61: =I61+'Feb UPDATED'!L61 -> 645309.06 | M61: =J61+'Feb UPDATED'!M61 -> 30957204 | N61: =L61-M61 -> -30311895
A62: Sub total - US Currency | D62: =SUM(D58:D61) -> 2196733714 | E62: =SUM(E58:E61) -> 53720975 | F62: =SUM(F58:F61) -> 2143012739 | G62: =SUM(G58:G61) -> 173591933 | H62: =SUM(H58:H61) -> 5169 | I62: =SUM(I58:I61) -> 447323.82 | J62: =SUM(J58:J61) -> 38700951 | K62: =SUM(K58:K61) -> -38253628 | ... N62: =SUM(N58:N61) -> -81743704
A63: Sub total - balanced funds | D63: =D56+D62 -> 16150077677 | E63: =E56+E62 -> 4.02235e+08 | F63: =F56+F62 -> 15747842682 | G63: =G56+G62 -> 7022100859 | H63: =H56+H62 -> 92123 | I63: =I56+I62 -> 19597538 | J63: =J56+J62 -> 133179638 | K63: =K56+K62 -> -1.135821e+08 | ... N63: =N56+N62 -> -3.4506283e+08
A64: Bond Funds
A65: Primarily invested in Peso Securities (shares)
B66: 43 | C66: ALFM Peso Bond Fund, Inc. | D66: 3.9023613e+10 | E66: 2.55668e+08 | F66: =D66-E66 -> 38767945220 | G66: 909705300 | H66: 24750 | I66: 2.9249279e+08 | J66: 9.1148191e+08 | K66: =I66-J66 -> -6.1898912e+08 | L66: =I66+'Feb UPDATED'!L66 -> 8.3784126e+08 | M66: =J66+'Feb UPDATED'!M66 -> 2157279967 | N66: =L66-M66 -> -1319438706
B67: 44 | C67: ATRAM Corporate Bond Fund, Inc. | D67: 5.0559738e+08 | E67: 28237222 | F67: =D67-E67 -> 4.7736016e+08 | G67: 0 | H67: 1086 | I67: 14384133 | J67: 6057351.7 | K67: =I67-J67 -> 8326781.5 | L67: =I67+'Feb UPDATED'!L67 -> 32574306 | M67: =J67+'Feb UPDATED'!M67 -> 22388002 | N67: =L67-M67 -> 10186303
B68: 45 | C68: Cocolife Fixed Income Fund, Inc. | D68: 999932385 | E68: 15829484 | F68: =D68-E68 -> 984102901 | G68: 0 | H68: 1967 | I68: 11166158 | J68: 37405552 | K68: =I68-J68 -> -26239394 | L68: =I68+'Feb UPDATED'!L68 -> 21474257 | M68: =J68+'Feb UPDATED'!M68 -> 42667489 | N68: =L68-M68 -> -21193233
B69: 46 | C69: Ekklesia Mutual Fund, Inc. | D69: 1.9592637e+08 | E69: 175364.13 | F69: =D69-E69 -> 1.95751e+08 | G69: 4752500 | H69: 189 | I69: 1866573.8 | J69: 3837803.5 | K69: =I69-J69 -> -1971229.7 | L69: =I69+'Feb UPDATED'!L69 -> 3098037.8 | M69: =J69+'Feb UPDATED'!M69 -> 4172275.1 | N69: =L69-M69 -> -1074237.3
B70: 47 | C70: First Metro Save and Learn Fixed Income Fund, Inc. | D70: 1354566325 | E70: 2607981 | F70: =D70-E70 -> 1351958344 | G70: 0 | H70: 1823 | I70: 8425000 | J70: 5135947 | K70: =I70-J70 -> 3289053 | L70: =I70+'Feb UPDATED'!L70 -> 69708595 | M70: =J70+'Feb UPDATED'!M70 -> 16254704 | N70: =L70-M70 -> 53453891
B71: 48 | C71: Philam Managed Income Fund, Inc. | D71: 7.6218494e+08 | E71: 36561526 | F71: =D71-E71 -> 7.2562342e+08 | G71: 0 | H71: 501 | I71: 1014356.1 | J71: 2814741.7 | K71: =I71-J71 -> -1800385.6 | L71: =I71+'Feb UPDATED'!L71 -> 6438783.8 | M71: =J71+'Feb UPDATED'!M71 -> 104157657 | N71: =L71-M71 -> -97718873
B72: 49 | C72: Philam Bond Fund, Inc. | D72: 1.712865e+09 | E72: 23614170 | F72: =D72-E72 -> 1689250788 | G72: 0 | H72: 4998 | I72: 4850303.5 | J72: 24642394 | K72: =I72-J72 -> -19792090 | L72: =I72+'Feb UPDATED'!L72 -> 12138516 | M72: =J72+'Feb UPDATED'!M72 -> 38299535 | N72: =L72-M72 -> -26161019
B73: 50 | C73: Philequity Peso Bond Fund, Inc. | D73: 308100325 | E73: 427721 | F73: =D73-E73 -> 307672604 | G73: 0 | H73: 4173 | I73: 12940326 | J73: 12906021 | K73: =I73-J73 -> 34305 | L73: =I73+'Feb UPDATED'!L73 -> 15334937 | M73: =J73+'Feb UPDATED'!M73 -> 16594169 | N73: =L73-M73 -> -1259231.7
B74: 51 | C74: Soldivo Bond Fund, Inc. | D74: 1.3981806e+09 | E74: 61036557 | F74: =D74-E74 -> 1337144081 | G74: 0 | H74: 822 | I74: 26111027 | J74: 295505.17 | K74: =I74-J74 -> 25815522 | L74: =I74+'Feb UPDATED'!L74 -> 1.0303834e+08 | M74: =J74+'Feb UPDATED'!M74 -> 2996959 | N74: =L74-M74 -> 1.0004138e+08
B75: 52 | C75: Sun Life Prosperity Bond Fund, Inc. | D75: 5086325900 | E75: 185866981 | F75: =D75-E75 -> 4900458919 | G75: 0 | H75: 16870 | I75: 102473415 | J75: 36252255 | K75: =I75-J75 -> 66221160 | L75: =I75+'Feb UPDATED'!L75 -> 565047786 | M75: =J75+'Feb UPDATED'!M75 -> 219267428 | N75: =L75-M75 -> 345780358
B76: 53 | C76: Sun Life Prosperity GS Fund, Inc. | D76: 145878002 | E76: 6512823 | F76: =D76-E76 -> 139365179 | G76: 0 | H76: 2668 | I76: 493913 | J76: 707155 | K76: =I76-J76 -> -213242 | L76: =I76+'Feb UPDATED'!L76 -> 1488132.4 | M76: =J76+'Feb UPDATED'!M76 -> 2245623.7 | N76: =L76-M76 -> -757491.27
A77: Sub total - Peso Currency | D77: =SUM(D66:D76) -> 51493170444 | E77: =SUM(E66:E76) -> 6.1653783e+08 | F77: =SUM(F66:F76) -> 50876632615 | G77: =SUM(G66:G76) -> 914457800 | H77: =SUM(H66:H76) -> 59847 | I77: =SUM(I66:I76) -> 4.76218e+08 | J77: =SUM(J66:J76) -> 1041536637 | K77: =SUM(K66:K76) -> -5.6531864e+08 | ... N77: =SUM(N66:N76) -> -9.5814086e+08
A78: Primarily invested in foreign currency securities (shares)
B79: 54 | C79: ALFM Dollar Bond Fund, Inc. | D79: 1.349551e+10 | E79: 1.2173712e+08 | F79: =D79-E79 -> 13373773161 | G79: 0 | H79: 8595 | I79: 1.1593348e+08 | J79: 1.8994179e+08 | K79: =I79-J79 -> -74008309 | L79: =I79+'Feb UPDATED'!L79 -> 221143714 | M79: =J79+'Feb UPDATED'!M79 -> 4.2865875e+08 | N79: =L79-M79 -> -2.0751504e+08
B80: 55 | C80: ATRAM Total Return Dollar Bond Fund, Inc. | D80: 2.839857e+08 | E80: 30192723 | F80: =D80-E80 -> 2.5379297e+08 | G80: 0 | H80: 166 | I80: 215613.5 | J80: 1960325.4 | K80: =I80-J80 -> -1744711.9 | L80: =I80+'Feb UPDATED'!L80 -> 1198438.1 | M80: =J80+'Feb UPDATED'!M80 -> 4110826.6 | N80: =L80-M80 -> -2912388.5
B81: 56 | C81: First Metro Save and Learn Dollar Bond Fund, Inc. | D81: 432729055 | E81: 3049547 | F81: =D81-E81 -> 429679508 | G81: 0 | H81: 157 | I81: 1863619 | J81: 548133 | K81: =I81-J81 -> 1315486 | L81: =I81+'Feb UPDATED'!L81 -> 7722912.5 | M81: =J81+'Feb UPDATED'!M81 -> 5609456 | N81: =L81-M81 -> 2113456.5
B82: 57 | C82: PAMI Global Bond Fund, Inc. | D82: 62649406 | E82: 13648513 | F82: =D82-E82 -> 49000893 | G82: 0 | H82: 27 | I82: 0 | J82: 0 | K82: =I82-J82 -> 0 | L82: =I82+'Feb UPDATED'!L82 -> 0 | M82: =J82+'Feb UPDATED'!M82 -> 0 | N82: =L82-M82 -> 0
B83: 58 | C83: Philam Dollar Bond Fund, Inc. | D83: 1.967407e+09 | E83: 22898812 | F83: =D83-E83 -> 1944508226 | G83: 0 | H83: 1893 | I83: 183005.11 | J83: 32318678 | K83: =I83-J83 -> -32135673 | L83: =I83+'Feb UPDATED'!L83 -> 280843.09 | M83: =J83+'Feb UPDATED'!M83 -> 50642898 | N83: =L83-M83 -> -50362055
B84: 59 | C84: Philequity Dollar Income Fund, Inc. | D84: 229947188 | E84: 1279774 | F84: =D84-E84 -> 228667414 | G84: 0 | H84: 122 | I84: 238912 | J84: 427057 | K84: =I84-J84 -> -188145 | L84: =I84+'Feb UPDATED'!L84 -> 419293 | M84: =J84+'Feb UPDATED'!M84 -> 427057 | N84: =L84-M84 -> -7764
B85: 60 | C85: Sun Life Prosperity Dollar Abundance Fund, Inc. | D85: 547684209 | E85: 19810406 | F85: =D85-E85 -> 527873803 | G85: 0 | H85: 2535 | I85: 2027444 | J85: 2165189 | K85: =I85-J85 -> -137745 | L85: =I85+'Feb UPDATED'!L85 -> 96117321 | M85: =J85+'Feb UPDATED'!M85 -> 10158359 | N85: =L85-M85 -> 85958962
A86: Sub total - US Currency | D86: =SUM(D79:D85) -> 17019912873 | E86: =SUM(E79:E85) -> 2.1261689e+08 | F86: =SUM(F79:F85) -> 16807295980 | G86: =SUM(G79:G85) -> 0 | H86: =SUM(H79:H85) -> 13495 | I86: =SUM(I79:I85) -> 1.2046207e+08 | J86: =SUM(J79:J85) -> 2.2736117e+08 | K86: =SUM(K79:K85) -> -1.068991e+08 | ... N86: =SUM(N79:N85) -> -172724824
B87: 61 | C87: ALFM Euro Bond Fund, Inc. | D87: 9.3038999e+08 | E87: 7294637.6 | F87: =D87-E87 -> 9.2309535e+08 | G87: 0 | H87: 649 | I87: 2985794 | J87: 4407086.3 | K87: =I87-J87 -> -1421292.3 | L87: =I87+'Feb UPDATED'!L87 -> 18284661 | M87: =J87+'Feb UPDATED'!M87 -> 8631913.5 | N87: =L87-M87 -> 9652747.9
A88: Sub total - Euro Currency | D88: =SUM(D87) -> 930389988 | E88: =SUM(E87) -> 7294637.6 | F88: =SUM(F87) -> 9.2309535e+08 | G88: =SUM(G87) -> 0 | H88: =SUM(H87) -> 649 | I88: =SUM(I87) -> 2985794 | J88: =SUM(J87) -> 4407086.3 | K88: =SUM(K87) -> -1421292.3 | ... N88: =SUM(N87) -> 9652747.9
A89: Sub total - bond funds | D89: =D77+D86+D88 -> 69443473305 | E89: =E77+E86+E88 -> 8.3644936e+08 | F89: =F77+F86+F88 -> 68607023945 | G89: =G77+G86+G88 -> 914457800 | H89: =H77+H86+H88 -> 73991 | I89: =I77+I86+I88 -> 5.9966586e+08 | J89: =J77+J86+J88 -> 1273304893 | K89: =K77+K86+K88 -> -6.7363903e+08 | ... N89: =N77+N86+N88 -> -1121212938
A90: Money Market Funds
A91: Primarily invested in Peso Securities (shares)
B92: 62 | C92: ALFM Money Market Fund, Inc. | D92: 3.6764208e+10 | E92: 26102244 | F92: =D92-E92 -> 36738105513 | G92: 0 | H92: 29515 | I92: 2.5608818e+09 | J92: 2.5312668e+09 | K92: =I92-J92 -> 29614949 | L92: =I92+'Feb UPDATED'!L92 -> 7711525429 | M92: =J92+'Feb UPDATED'!M92 -> 7275236743 | N92: =L92-M92 -> 4.3628869e+08
B93: 63 | C93: First Metro Save and Learn Money Market Fund, Inc. | D93: 2603016622 | E93: 39479253 | F93: =D93-E93 -> 2563537369 | G93: 0 | H93: 766 | I93: 95191265 | J93: 131610780 | K93: =I93-J93 -> -36419515 | L93: =I93+'Feb UPDATED'!L93 -> 2.4823679e+08 | M93: =J93+'Feb UPDATED'!M93 -> 5.3028422e+08 | N93: =L93-M93 -> -2.8204743e+08
B94: 64 | C94: Sun Life Prosperity Peso Starter Fund, Inc. | D94: 39761049435 | E94: 160208047 | F94: =D94-E94 -> 39600841388 | G94: 0 | H94: 66658 | I94: 1353192019 | J94: 4881411618 | K94: =I94-J94 -> -3528219599 | L94: =I94+'Feb UPDATED'!L94 -> 6585586404 | M94: =J94+'Feb UPDATED'!M94 -> 19510089226 | N94: =L94-M94 -> -12924502822
A95: Primarily invested in Peso Securities (units)
B96: 65 | C96: ALFM Money Market Fund, Inc. | D96: 4.9112758e+09 | E96: 4463036.7 | F96: =D96-E96 -> 4906812744 | G96: 0 | H96: 5336 | I96: 1.8890753e+09 | J96: 2.6786565e+09 | K96: =I96-J96 -> -7.8958126e+08 | L96: =I96+'Feb UPDATED'!L96 -> 5166042319 | M96: =J96+'Feb UPDATED'!M96 -> 3819778545 | N96: =L96-M96 -> 1346263774
A97: Sub total - Peso Currency | D97: =SUM(D92:D94)+D96 -> 84039549595 | E97: =SUM(E92:E94)+E96 -> 2.3025258e+08 | F97: =SUM(F92:F94)+F96 -> 83809297014 | G97: =SUM(G92:G94)+G96 -> 0 | H97: =SUM(H92:H94)+H96 -> 102275 | I97: =SUM(I92:I94)+I96 -> 5898340324 | J97: =SUM(J92:J94)+J96 -> 10222945747 | K97: =SUM(K92:K94)+K96 -> -4324605423 | ... N97: =SUM(N92:N94)+N96 -> -11423997795
A98: Primarily invested in foreign currency securities (shares)
B99: 66 | C99: Sun Life Prosperity Dollar Starter Fund, Inc. | D99: 4036351491 | E99: 18329670 | F99: =D99-E99 -> 4018021821 | G99: 0 | H99: 3490 | I99: 7893594 | J99: 1589356322 | K99: =I99-J99 -> -1581462728 | L99: =I99+'Feb UPDATED'!L99 -> 2143612081 | M99: =J99+'Feb UPDATED'!M99 -> 4677688708 | N99: =L99-M99 -> -2534076627
A100: Sub total - US Currency | D100: =SUM(D99) -> 4036351491 | E100: =SUM(E99) -> 18329670 | F100: =SUM(F99) -> 4018021821 | G100: =SUM(G99) -> 0 | H100: =SUM(H99) -> 3490 | I100: =SUM(I99) -> 7893594 | J100: =SUM(J99) -> 1589356322 | K100: =SUM(K99) -> -1581462728 | ... N100: =SUM(N99) -> -2534076627
A101: Sub total - money market funds | D101: =D97+D100 -> 88075901086 | E101: =E97+E100 -> 2.4858225e+08 | F101: =F97+F100 -> 87827318835 | G101: =G97+G100 -> 0 | H101: =H97+H100 -> 105765 | I101: =I97+I100 -> 5906233918 | J101: =J97+J100 -> 11812302069 | K101: =K97+K100 -> -5906068151 | ... N101: =N97+N100 -> -13958074422
A102: Feeder Fund
A103: Primarily invested in Peso securities (units)
B104: 67 | C104: ALFM Global Multi-Asset Income Fund Inc. | D104: 9.0972551e+09 | E104: 12874051 | F104: =D104-E104 -> 9084381006 | G104: 0 | H104: 74470 | I104: 90939888 | J104: 1.1172318e+08 | K104: =I104-J104 -> -20783296 | L104: =I104+'Feb UPDATED'!L104 -> 3.8211503e+08 | M104: =J104+'Feb UPDATED'!M104 -> 4.1725174e+08 | N104: =L104-M104 -> -35136709
B105: 68 | C105: Sun Life Prosperity World Equity Index Feeder Fund, Inc. | D105: 3318316248 | E105: 8021173 | F105: =D105-E105 -> 3310295075 | G105: 0 | H105: 6057 | I105: 17345566 | J105: 32444385 | K105: =I105-J105 -> -15098819 | L105: =I105+'Feb UPDATED'!L105 -> 65307884 | M105: =J105+'Feb UPDATED'!M105 -> 1.2879797e+08 | N105: =L105-M105 -> -63490082
A106: Sub total - Peso Currency | D106: =D104+D105 -> 12415571304 | E106: =E104+E105 -> 20895224 | F106: =F104+F105 -> 12394676081 | G106: =G104+G105 -> 0 | H106: =H104+H105 -> 80527 | I106: =I104+I105 -> 1.0828545e+08 | J106: =J104+J105 -> 1.4416757e+08 | K106: =K104+K105 -> -35882115 | ... N106: =N104+N105 -> -98626791
...

Sheet Q1
A1: PHILIPPINE INVESTMENT FUNDS ASSOCIATION, INC.
A2: MUTUAL FUNDS STATISTICAL REPORT
A3: As of the First Quarter of 2023
A4: (Amounts in Peso)
A6: Fund Category | C6: Fund Name | D6: NET ASSETS | E6: TOTAL SALES | F6: TOTAL REDEMPTIONS | G6: NET SALES
A7: Stock Funds
A8: Primarily invested in Peso Securities (shares)
B9: 1 | C9: ALFM Growth Fund, Inc. | D9: =Mar!F9 -> 4579770512 | E9: =Jan!I9+'Feb UPDATED'!I9+Mar!I9 -> 19194106 | F9: =Jan!J9+'Feb UPDATED'!J9+Mar!J9 -> 151374832 | G9: =E9-F9 -> -1.3218073e+08
B10: 2 | C10: ATRAM Alpha Opportunity Fund, Inc. | D10: =Mar!F10 -> 7.5853669e+08 | E10: =Jan!I10+'Feb UPDATED'!I10+Mar!I10 -> 15709919 | F10: =Jan!J10+'Feb UPDATED'!J10+Mar!J10 -> 36396713 | G10: =E10-F10 -> -20686794
B11: 3 | C11: ATRAM Phil. Equity Opportunity Fund, Inc. | D11: =Mar!F11 -> 1523881453 | E11: =Jan!I11+'Feb UPDATED'!I11+Mar!I11 -> 3.8653936e+08 | F11: =Jan!J11+'Feb UPDATED'!J11+Mar!J11 -> 1.6345347e+08 | G11: =E11-F11 -> 223085885
B12: 4 | C12: Climbs Share Capital Equity Investment Fund Corp. | D12: =Mar!F12 -> 340091873 | E12: =Jan!I12+'Feb UPDATED'!I12+Mar!I12 -> 1666337.9 | F12: =Jan!J12+'Feb UPDATED'!J12+Mar!J12 -> 1186845.3 | G12: =E12-F12 -> 479492.69
B13: 5 | C13: First Metro Consumer Fund on MSCI Phils. IMI, Inc. | D13: =Mar!F13 -> 525337648 | E13: =Jan!I13+'Feb UPDATED'!I13+Mar!I13 -> 2007744.5 | F13: =Jan!J13+'Feb UPDATED'!J13+Mar!J13 -> 4867715.4 | G13: =E13-F13 -> -2859970.9
B14: 6 | C14: First Metro Save and Learn Equity Fund, Inc. | D14: =Mar!F14 -> 4239535922 | E14: =Jan!I14+'Feb UPDATED'!I14+Mar!I14 -> 86323936 | F14: =Jan!J14+'Feb UPDATED'!J14+Mar!J14 -> 88721730 | G14: =E14-F14 -> -2397794
B15: 7 | C15: First Metro Save and Learn Phil. Index Fund, Inc. | D15: =Mar!F15 -> 101535937 | E15: =Jan!I15+'Feb UPDATED'!I15+Mar!I15 -> 5445974.7 | F15: =Jan!J15+'Feb UPDATED'!J15+Mar!J15 -> 4807202.9 | G15: =E15-F15 -> 638771.8
B16: 8 | C16: MBG Equity Investment Fund, Inc. | D16: =Mar!F16 -> 1.2062748e+08 | E16: =Jan!I16+'Feb UPDATED'!I16+Mar!I16 -> 241.49 | F16: =Jan!J16+'Feb UPDATED'!J16+Mar!J16 -> 764224.93 | G16: =E16-F16 -> -763983.44
B17: 9 | C17: PAMI Equity Index Fund, Inc. | D17: =Mar!F17 -> 1266684572 | E17: =Jan!I17+'Feb UPDATED'!I17+Mar!I17 -> 0 | F17: =Jan!J17+'Feb UPDATED'!J17+Mar!J17 -> 49670539 | G17: =E17-F17 -> -49670539
B18: 10 | C18: Philam Strategic Growth Fund, Inc. | D18: =Mar!F18 -> 3707895226 | E18: =Jan!I18+'Feb UPDATED'!I18+Mar!I18 -> 10283369 | F18: =Jan!J18+'Feb UPDATED'!J18+Mar!J18 -> 87402788 | G18: =E18-F18 -> -77119420
B19: 11 | C19: Philequity Dividend Yield Fund, Inc. | D19: =Mar!F19 -> 2257298871 | E19: =Jan!I19+'Feb UPDATED'!I19+Mar!I19 -> 1.3546812e+08 | F19: =Jan!J19+'Feb UPDATED'!J19+Mar!J19 -> 11417041 | G19: =E19-F19 -> 1.2405108e+08
B20: 12 | C20: Philequity Fund, Inc. | D20: =Mar!F20 -> 9802902571 | E20: =Jan!I20+'Feb UPDATED'!I20+Mar!I20 -> 63619218 | F20: =Jan!J20+'Feb UPDATED'!J20+Mar!J20 -> 1.5533761e+08 | G20: =E20-F20 -> -91718394
... B27: 19 | C27: United Fund, Inc. | D27: =Mar!F27 -> 592013847 | E27: =Jan!I27+'Feb UPDATED'!I27+Mar!I27 -> 3954705.6 | F27: =Jan!J27+'Feb UPDATED'!J27+Mar!J27 -> 4141404.2 | G27: =E27-F27 -> -186698.59
A28: Primarily invested in Peso Securities (units)
B29: 20 | C29: COL Equity Index Unitized Mutual Fund, Inc. | D29: =Mar!F29 -> 186792848 | E29: =Jan!I29+'Feb UPDATED'!I29+Mar!I29 -> 82815041 | F29: =Jan!J29+'Feb UPDATED'!J29+Mar!J29 -> 3860031.8 | G29: =E29-F29 -> 78955009
B30: 21 | C30: Philequity Alpha One Fund, Inc. | D30: =Mar!F30 -> 343949326 | E30: =Jan!I30+'Feb UPDATED'!I30+Mar!I30 -> 8119700.5 | F30: =Jan!J30+'Feb UPDATED'!J30+Mar!J30 -> 12841597 | G30: =E30-F30 -> -4721897
B31: 22 | C31: Philippine Stock Index Fund Corp. | D31: =Mar!F31 -> 4.8879028e+08 | E31: =Jan!I31+'Feb UPDATED'!I31+Mar!I31 -> 97621384 | F31: =Jan!J31+'Feb UPDATED'!J31+Mar!J31 -> 87258762 | G31: =E31-F31 -> 10362622
A32: Exchange Traded Fund
B33: 23 | C33: First Metro Phil. Equity Exchange Traded Fund, Inc. | D33: =Mar!F33 -> 2161549204 | E33: =Jan!I33+'Feb UPDATED'!I33+Mar!I33 -> 24256591 | F33: =Jan!J33+'Feb UPDATED'!J33+Mar!J33 -> 76900589 | G33: =E33-F33 -> -52643998
A34: Sub total - Peso Currency | D34: =SUM(D9:D33) -> 68096725981 | E34: =SUM(E9:E33) -> 2385752875 | F34: =SUM(F9:F33) -> 2613602379 | G34: =SUM(G9:G33) -> -2.278495e+08
A35: Primarily invested in foreign currency securities (shares)
B36: 24 | C36: ATRAM AsiaPlus Equity Fund, Inc. | D36: =Mar!F36 -> 34451210 | E36: =Jan!I36+'Feb UPDATED'!I36+Mar!I36 -> 78879.62 | F36: =Jan!J36+'Feb UPDATED'!J36+Mar!J36 -> 19382.09 | G36: =E36-F36 -> 59497.53
B37: 25 | C37: Sun Life Prosperity World Voyager Fund, Inc. | D37: =Mar!F37 -> 1769788333 | E37: =Jan!I37+'Feb UPDATED'!I37+Mar!I37 -> 18475062 | F37: =Jan!J37+'Feb UPDATED'!J37+Mar!J37 -> 77759569 | G37: =E37-F37 -> -59284507
A38: Sub total - US Currency | D38: =SUM(D36:D37) -> 1804239543 | E38: =SUM(E36:E37) -> 18553942 | F38: =SUM(F36:F37) -> 77778952 | G38: =SUM(G36:G37) -> -59225009
A39: Sub total - stock funds | D39: =D34+D38 -> 69900965524 | E39: =E34+E38 -> 2404306817 | F39: =F34+F38 -> 2691381331 | G39: =G34+G38 -> -2.8707451e+08
A40: Balanced Funds
A41: Primarily invested in Peso Securities (shares)
B42: 26 | C42: ATRAM Dynamic Allocation Fund, Inc. | D42: =Mar!F42 -> 116368890 | E42: =Jan!I42+'Feb UPDATED'!I42+Mar!I42 -> 1090496.1 | F42: =Jan!J42+'Feb UPDATED'!J42+Mar!J42 -> 739241 | G42: =E42-F42 -> 351255.06
B43: 27 | C43: ATRAM Philippine Balanced Fund, Inc. | D43: =Mar!F43 -> 5.812871e+08 | E43: =Jan!I43+'Feb UPDATED'!I43+Mar!I43 -> 3123622.1 | F43: =Jan!J43+'Feb UPDATED'!J43+Mar!J43 -> 16165567 | G43: =E43-F43 -> -13041945
B44: 28 | C44: First Metro Save and Learn Balanced Fund, Inc. | D44: =Mar!F44 -> 1056169633 | E44: =Jan!I44+'Feb UPDATED'!I44+Mar!I44 -> 6487314.5 | F44: =Jan!J44+'Feb UPDATED'!J44+Mar!J44 -> 14463100 | G44: =E44-F44 -> -7975785.5
B45: 29 | C45: First Metro Save and Learn F.O.C.C.U.S. Dynamic Fund, Inc. | D45: =Mar!F45 -> 270264638 | E45: =Jan!I45+'Feb UPDATED'!I45+Mar!I45 -> 9671594.3 | F45: =Jan!J45+'Feb UPDATED'!J45+Mar!J45 -> 42536435 | G45: =E45-F45 -> -32864841
B46: 30 | C46: NCM Mutual Fund of the Phils., Inc. | D46: =Mar!F46 -> 344616852 | E46: =Jan!I46+'Feb UPDATED'!I46+Mar!I46 -> 0 | F46: =Jan!J46+'Feb UPDATED'!J46+Mar!J46 -> 1508185 | G46: =E46-F46 -> -1508185
B47: 31 | C47: PAMI Horizon Fund, Inc. | D47: =Mar!F47 -> 5.4365285e+08 | E47: =Jan!I47+'Feb UPDATED'!I47+Mar!I47 -> 1928994.3 | F47: =Jan!J47+'Feb UPDATED'!J47+Mar!J47 -> 12123095 | G47: =E47-F47 -> -10194101
B48: 32 | C48: Philam Fund, Inc. | D48: =Mar!F48 -> 2040940824 | E48: =Jan!I48+'Feb UPDATED'!I48+Mar!I48 -> 6642233.2 | F48: =Jan!J48+'Feb UPDATED'!J48+Mar!J48 -> 48668489 | G48: =E48-F48 -> -42026256
B49: 33 | C49: Solidaritas Fund, Inc. | D49: =Mar!F49 -> 1.3671178e+08 | E49: =Jan!I49+'Feb UPDATED'!I49+Mar!I49 -> 211296.33 | F49: =Jan!J49+'Feb UPDATED'!J49+Mar!J49 -> 1632502.1 | G49: =E49-F49 -> -1421205.8
B50: 34 | C50: Sun Life Prosperity Balanced Fund, Inc. | D50: =Mar!F50 -> 7177072486 | E50: =Jan!I50+'Feb UPDATED'!I50+Mar!I50 -> 25898108 | F50: =Jan!J50+'Feb UPDATED'!J50+Mar!J50 -> 1.6652221e+08 | G50: =E50-F50 -> -1.406241e+08
B51: 35 | C51: Sun Life Prosperity Dynamic Fund, Inc. | D51: =Mar!F51 -> 1158094632 | E51: =Jan!I51+'Feb UPDATED'!I51+Mar!I51 -> 0 | F51: =Jan!J51+'Feb UPDATED'!J51+Mar!J51 -> 15774240 | G51: =E51-F51 -> -15774240
A52: Primarily invested in Peso Securities (units)
B53: 36 | C53: Sun Life Prosperity Achiever Fund 2028, Inc. | D53: =Mar!F53 -> 76824272 | E53: =Jan!I53+'Feb UPDATED'!I53+Mar!I53 -> 1637171.2 | F53: =Jan!J53+'Feb UPDATED'!J53+Mar!J53 -> 331541.55 | G53: =E53-F53 -> 1305629.6
B54: 37 | C54: Sun Life Prosperity Achiever Fund 2038, Inc. | D54: =Mar!F54 -> 55942811 | E54: =Jan!I54+'Feb UPDATED'!I54+Mar!I54 -> 685741 | F54: =Jan!J54+'Feb UPDATED'!J54+Mar!J54 -> 321665.19 | G54: =E54-F54 -> 364075.81
B55: 38 | C55: Sun Life Prosperity Achiever Fund 2048, Inc. | D55: =Mar!F55 -> 46883173 | E55: =Jan!I55+'Feb UPDATED'!I55+Mar!I55 -> 181950 | F55: =Jan!J55+'Feb UPDATED'!J55+Mar!J55 -> 91381.96 | G55: =E55-F55 -> 90568.04
A56: Sub total - Peso Currency | D56: =SUM(D42:D55) -> 13604829942 | E56: =SUM(E42:E55) -> 57558521 | F56: =SUM(F42:F55) -> 3.2087765e+08 | G56: =SUM(G42:G55) -> -2.6331913e+08
A57: Primarily invested in foreign currency securities (shares)
B58: 39 | C58: Cocolife Dollar Fund Builder, Inc. | D58: =Mar!F58 -> 70212097 | E58: =Jan!I58+'Feb UPDATED'!I58+Mar!I58 -> 0 | F58: =Jan!J58+'Feb UPDATED'!J58+Mar!J58 -> 447875.75 | G58: =E58-F58 -> -447875.75
B59: 40 | C59: PAMI Asia Balanced Fund, Inc. | D59: =Mar!F59 -> 3.2167691e+08 | E59: =Jan!I59+'Feb UPDATED'!I59+Mar!I59 -> 5631.4684 | F59: =Jan!J59+'Feb UPDATED'!J59+Mar!J59 -> 9739240.4 | G59: =E59-F59 -> -9733609
B60: 41 | C60: Sun Life Prosperity Dollar Advantage Fund, Inc. | D60: =Mar!F60 -> 1489278458 | E60: =Jan!I60+'Feb UPDATED'!I60+Mar!I60 -> 2766963.3 | F60: =Jan!J60+'Feb UPDATED'!J60+Mar!J60 -> 44017287 | G60: =E60-F60 -> -41250324
B61: 42 | C61: Sun Life Prosperity Dollar Wellspring Fund, Inc. | D61: =Mar!F61 -> 261845277 | E61: =Jan!I61+'Feb UPDATED'!I61+Mar!I61 -> 645309.06 | F61: =Jan!J61+'Feb UPDATED'!J61+Mar!J61 -> 30957204 | G61: =E61-F61 -> -30311895
A62: Sub total - US Currency | D62: =SUM(D58:D61) -> 2143012739 | E62: =SUM(E58:E61) -> 3417903.8 | F62: =SUM(F58:F61) -> 85161608 | G62: =SUM(G58:G61) -> -81743704
A63: Sub total - balanced funds | D63: =D56+D62 -> 15747842682 | E63: =E56+E62 -> 60976425 | F63: =F56+F62 -> 4.0603926e+08 | G63: =G56+G62 -> -3.4506283e+08
A64: Bond Funds
A65: Primarily invested in Peso Securities (shares)
B66: 43 | C66: ALFM Peso Bond Fund, Inc. | D66: =Mar!F66 -> 38767945220 | E66: =Jan!I66+'Feb UPDATED'!I66+Mar!I66 -> 8.3784126e+08 | F66: =Jan!J66+'Feb UPDATED'!J66+Mar!J66 -> 2157279967 | G66: =E66-F66 -> -1319438706
B67: 44 | C67: ATRAM Corporate Bond Fund, Inc. | D67: =Mar!F67 -> 4.7736016e+08 | E67: =Jan!I67+'Feb UPDATED'!I67+Mar!I67 -> 32574306 | F67: =Jan!J67+'Feb UPDATED'!J67+Mar!J67 -> 22388002 | G67: =E67-F67 -> 10186303
B68: 45 | C68: Cocolife Fixed Income Fund, Inc. | D68: =Mar!F68 -> 984102901 | E68: =Jan!I68+'Feb UPDATED'!I68+Mar!I68 -> 21474257 | F68: =Jan!J68+'Feb UPDATED'!J68+Mar!J68 -> 42667489 | G68: =E68-F68 -> -21193233
B69: 46 | C69: Ekklesia Mutual Fund, Inc. | D69: =Mar!F69 -> 1.95751e+08 | E69: =Jan!I69+'Feb UPDATED'!I69+Mar!I69 -> 3098037.8 | F69: =Jan!J69+'Feb UPDATED'!J69+Mar!J69 -> 4172275.1 | G69: =E69-F69 -> -1074237.3
B70: 47 | C70: First Metro Save and Learn Fixed Income Fund, Inc. | D70: =Mar!F70 -> 1351958344 | E70: =Jan!I70+'Feb UPDATED'!I70+Mar!I70 -> 69708595 | F70: =Jan!J70+'Feb UPDATED'!J70+Mar!J70 -> 16254704 | G70: =E70-F70 -> 53453891
B71: 48 | C71: Philam Managed Income Fund, Inc. | D71: =Mar!F71 -> 7.2562342e+08 | E71: =Jan!I71+'Feb UPDATED'!I71+Mar!I71 -> 6438783.8 | F71: =Jan!J71+'Feb UPDATED'!J71+Mar!J71 -> 104157657 | G71: =E71-F71 -> -97718873
B72: 49 | C72: Philam Bond Fund, Inc. | D72: =Mar!F72 -> 1689250788 | E72: =Jan!I72+'Feb UPDATED'!I72+Mar!I72 -> 12138516 | F72: =Jan!J72+'Feb UPDATED'!J72+Mar!J72 -> 38299535 | G72: =E72-F72 -> -26161019
B73: 50 | C73: Philequity Peso Bond Fund, Inc. | D73: =Mar!F73 -> 307672604 | E73: =Jan!I73+'Feb UPDATED'!I73+Mar!I73 -> 15334937 | F73: =Jan!J73+'Feb UPDATED'!J73+Mar!J73 -> 16594169 | G73: =E73-F73 -> -1259231.7
B74: 51 | C74: Soldivo Bond Fund, Inc. | D74: =Mar!F74 -> 1337144081 | E74: =Jan!I74+'Feb UPDATED'!I74+Mar!I74 -> 1.0303834e+08 | F74: =Jan!J74+'Feb UPDATED'!J74+Mar!J74 -> 2996959 | G74: =E74-F74 -> 1.0004138e+08
B75: 52 | C75: Sun Life Prosperity Bond Fund, Inc. | D75: =Mar!F75 -> 4900458919 | E75: =Jan!I75+'Feb UPDATED'!I75+Mar!I75 -> 565047786 | F75: =Jan!J75+'Feb UPDATED'!J75+Mar!J75 -> 219267428 | G75: =E75-F75 -> 345780358
B76: 53 | C76: Sun Life Prosperity GS Fund, Inc. | D76: =Mar!F76 -> 139365179 | E76: =Jan!I76+'Feb UPDATED'!I76+Mar!I76 -> 1488132.4 | F76: =Jan!J76+'Feb UPDATED'!J76+Mar!J76 -> 2245623.7 | G76: =E76-F76 -> -757491.27
A77: Sub total - Peso Currency | D77: =SUM(D66:D76) -> 50876632615 | E77: =SUM(E66:E76) -> 1668182947 | F77: =SUM(F66:F76) -> 2626323809 | G77: =SUM(G66:G76) -> -9.5814086e+08
A78: Primarily invested in foreign currency securities (shares)
B79: 54 | C79: ALFM Dollar Bond Fund, Inc. | D79: =Mar!F79 -> 13373773161 | E79: =Jan!I79+'Feb UPDATED'!I79+Mar!I79 -> 221143714 | F79: =Jan!J79+'Feb UPDATED'!J79+Mar!J79 -> 4.2865875e+08 | G79: =E79-F79 -> -2.0751504e+08
B80: 55 | C80: ATRAM Total Return Dollar Bond Fund, Inc. | D80: =Mar!F80 -> 2.5379297e+08 | E80: =Jan!I80+'Feb UPDATED'!I80+Mar!I80 -> 1198438.1 | F80: =Jan!J80+'Feb UPDATED'!J80+Mar!J80 -> 4110826.6 | G80: =E80-F80 -> -2912388.5
B81: 56 | C81: First Metro Save and Learn Dollar Bond Fund, Inc. | D81: =Mar!F81 -> 429679508 | E81: =Jan!I81+'Feb UPDATED'!I81+Mar!I81 -> 7722912.5 | F81: =Jan!J81+'Feb UPDATED'!J81+Mar!J81 -> 5609456 | G81: =E81-F81 -> 2113456.5
B82: 57 | C82: PAMI Global Bond Fund Phils., Inc. | D82: =Mar!F82 -> 49000893 | E82: =Jan!I82+'Feb UPDATED'!I82+Mar!I82 -> 0 | F82: =Jan!J82+'Feb UPDATED'!J82+Mar!J82 -> 0 | G82: =E82-F82 -> 0
B83: 58 | C83: Philam Dollar Bond Fund, Inc. | D83: =Mar!F83 -> 1944508226 | E83: =Jan!I83+'Feb UPDATED'!I83+Mar!I83 -> 280843.09 | F83: =Jan!J83+'Feb UPDATED'!J83+Mar!J83 -> 50642898 | G83: =E83-F83 -> -50362055
B84: 59 | C84: Philequity Dollar Income Fund, Inc. | D84: =Mar!F84 -> 228667414 | E84: =Jan!I84+'Feb UPDATED'!I84+Mar!I84 -> 419293 | F84: =Jan!J84+'Feb UPDATED'!J84+Mar!J84 -> 427057 | G84: =E84-F84 -> -7764
B85: 60 | C85: Sun Life Prosperity Dollar Abundance Fund, Inc. | D85: =Mar!F85 -> 527873803 | E85: =Jan!I85+'Feb UPDATED'!I85+Mar!I85 -> 96117321 | F85: =Jan!J85+'Feb UPDATED'!J85+Mar!J85 -> 10158359 | G85: =E85-F85 -> 85958962
A86: Sub total - US Currency | D86: =SUM(D79:D85) -> 16807295980 | E86: =SUM(E79:E85) -> 3.2688252e+08 | F86: =SUM(F79:F85) -> 4.9960735e+08 | G86: =SUM(G79:G85) -> -172724824
B87: 61 | C87: ALFM Euro Bond Fund, Inc. | D87: =Mar!F87 -> 9.2309535e+08 | E87: =Jan!I87+'Feb UPDATED'!I87+Mar!I87 -> 18284661 | F87: =Jan!J87+'Feb UPDATED'!J87+Mar!J87 -> 8631913.5 | G87: =E87-F87 -> 9652747.9
A88: Sub total - Euro Currency | D88: =SUM(D87) -> 9.2309535e+08 | E88: =SUM(E87) -> 18284661 | F88: =SUM(F87) -> 8631913.5 | G88: =SUM(G87) -> 9652747.9
A89: Sub total - bond funds | D89: =D77+D86+D88 -> 68607023945 | E89: =E77+E86+E88 -> 2013350130 | F89: =F77+F86+F88 -> 3134563068 | G89: =G77+G86+G88 -> -1121212938
A90: Money Market Funds
A91: Primarily invested in Peso Securities (shares)
B92: 62 | C92: ALFM Money Market Fund, Inc. | D92: =Mar!F92 -> 36738105513 | E92: =Jan!I92+'Feb UPDATED'!I92+Mar!I92 -> 7711525429 | F92: =Jan!J92+'Feb UPDATED'!J92+Mar!J92 -> 7275236743 | G92: =E92-F92 -> 4.3628869e+08
B93: 63 | C93: First Metro Save and Learn Money Market Fund, Inc. | D93: =Mar!F93 -> 2563537369 | E93: =Jan!I93+'Feb UPDATED'!I93+Mar!I93 -> 2.4823679e+08 | F93: =Jan!J93+'Feb UPDATED'!J93+Mar!J93 -> 5.3028422e+08 | G93: =E93-F93 -> -2.8204743e+08
B94: 64 | C94: Sun Life Prosperity Peso Starter Fund, Inc. | D94: =Mar!F94 -> 39600841388 | E94: =Jan!I94+'Feb UPDATED'!I94+Mar!I94 -> 6585586404 | F94: =Jan!J94+'Feb UPDATED'!J94+Mar!J94 -> 19510089226 | G94: =E94-F94 -> -12924502822
A95: Primarily invested in Peso Securities (units)
B96: 65 | C96: ALFM Money Market Fund, Inc. | D96: =Mar!F96 -> 4906812744 | E96: =Jan!I96+'Feb UPDATED'!I96+Mar!I96 -> 5166042319 | F96: =Jan!J96+'Feb UPDATED'!J96+Mar!J96 -> 3819778545 | G96: =E96-F96 -> 1346263774
A97: Sub total - Peso Currency | D97: =SUM(D92:D96) -> 83809297014 | E97: =SUM(E92:E96) -> 19711390941 | F97: =SUM(F92:F96) -> 31135388736 | G97: =SUM(G92:G96) -> -11423997795
A98: Primarily invested in foreign currency securities (shares)
B99: 66 | C99: Sun Life Prosperity Dollar Starter Fund, Inc. | D99: =Mar!F99 -> 4018021821 | E99: =Jan!I99+'Feb UPDATED'!I99+Mar!I99 -> 2143612081 | F99: =Jan!J99+'Feb UPDATED'!J99+Mar!J99 -> 4677688708 | G99: =E99-F99 -> -2534076627
A100: Sub total - US Currency | D100: =SUM(D99) -> 4018021821 | E100: =SUM(E99) -> 2143612081 | F100: =SUM(F99) -> 4677688708 | G100: =SUM(G99) -> -2534076627
A101: Sub total - money market funds | D101: =D97+D100 -> 87827318835 | E101: =E97+E100 -> 21855003022 | F101: =F97+F100 -> 35813077444 | G101: =G97+G100 -> -13958074422
A102: Feeder Fund
A103: Primarily invested in Peso securities (units)
B104: 67 | C104: ALFM Global Multi-Asset Income Fund Inc. | D104: =Mar!F104 -> 9084381006 | E104: =Jan!I104+'Feb UPDATED'!I104+Mar!I104 -> 3.8211503e+08 | F104: =Jan!J104+'Feb UPDATED'!J104+Mar!J104 -> 4.1725174e+08 | G104: =E104-F104 -> -35136709
B105: 68 | C105: Sun Life Prosperity World Equity Index Feeder Fund, Inc. | D105: =Mar!F105 -> 3310295075 | E105: =Jan!I105+'Feb UPDATED'!I105+Mar!I105 -> 65307884 | F105: =Jan!J105+'Feb UPDATED'!J105+Mar!J105 -> 1.2879797e+08 | G105: =E105-F105 -> -63490082
A106: Sub total - Peso Currency | D106: =SUM(D104:D105) -> 12394676081 | E106: =SUM(E104:E105) -> 447422912 | F106: =SUM(F104:F105) -> 5.460497e+08 | G106: =SUM(G104:G105) -> -98626791
A107: Primarily invested in foreign currency securities (units)
...

Sheet Apr
A1: PHILIPPINE INVESTMENT FUNDS ASSOCIATION, INC.
A2: MUTUAL FUNDS STATISTICAL REPORT
A3: Month of April 2023
A4: (Amounts in Peso)
I5: F O R - T H E - M O N T H | L5: Y E A R - T O - D A T E
A6: Fund Category | C6: Fund Name | D6: ASSETS | E6: LIABILITIES | F6: NET ASSETS | G6: EQUITY INV. | H6: NO. OF A/C | I6: SALES | J6: REDEMPTIONS | K6: NET SALES | L6: TOTAL SALES | M6: TOTAL REDEMPTIONS | N6: TOTAL NET SALES
A7: Stock Funds
A8: Primarily invested in Peso Securities (shares)
B9: 1 | C9: ALFM Growth Fund, Inc. | D9: 4.667551e+09 | E9: 11980470 | F9: =D9-E9 -> 4655570510 | G9: 4.1886425e+09 | H9: 7172 | I9: 7189190.9 | J9: 20503747 | K9: =I9-J9 -> -13314556 | L9: =I9+Mar!L9 -> 26383297 | M9: =J9+Mar!M9 -> 1.7187858e+08 | N9: =L9-M9 -> -1.4549528e+08
B10: 2 | C10: ATRAM Alpha Opportunity Fund, Inc. | D10: 774351672 | E10: 3180125 | F10: =D10-E10 -> 771171547 | G10: 731386659 | H10: 4222 | I10: 3101557 | J10: 2532451 | K10: =I10-J10 -> 569106 | L10: =I10+Mar!L10 -> 18811476 | M10: =J10+Mar!M10 -> 38929164 | N10: =L10-M10 -> -20117688
B11: 3 | C11: ATRAM Phil. Equity Opportunity Fund, Inc. | D11: 1528840217 | E11: 92591666 | F11: =D11-E11 -> 1436248551 | G11: 1320522430 | H11: 2841 | I11: 11561939 | J11: 112504436 | K11: =I11-J11 -> -100942497 | L11: =I11+Mar!L11 -> 3.981013e+08 | M11: =J11+Mar!M11 -> 2.7595791e+08 | N11: =L11-M11 -> 122143388
B12: 4 | C12: Climbs Share Capital Equity Investment Fund Corp. | D12: 3.4791205e+08 | E12: 10358152 | F12: =D12-E12 -> 3.375539e+08 | G12: 2.2799623e+08 | H12: 1764 | I12: 356196.5 | J12: 90033.22 | K12: =I12-J12 -> 266163.28 | L12: =I12+Mar!L12 -> 2022534.4 | M12: =J12+Mar!M12 -> 1276878.5 | N12: =L12-M12 -> 745655.97
B13: 5 | C13: First Metro Consumer Fund, Inc. | D13: 527205896 | E13: 4272347 | F13: =D13-E13 -> 522933549 | G13: 404537326 | H13: 1402 | I13: 324817 | J13: 623219 | K13: =I13-J13 -> -298402 | L13: =I13+Mar!L13 -> 2332561.5 | M13: =J13+Mar!M13 -> 5490934.4 | N13: =L13-M13 -> -3158372.9
B14: 6 | C14: First Metro Save and Learn Equity Fund, Inc. | D14: 4411079875 | E14: 74465389 | F14: =D14-E14 -> 4336614486 | G14: 3698284832 | H14: 16086 | I14: 19127887 | J14: 12992516 | K14: =I14-J14 -> 6135371 | L14: =I14+Mar!L14 -> 1.0545182e+08 | M14: =J14+Mar!M14 -> 1.0171425e+08 | N14: =L14-M14 -> 3737577
B15: 7 | C15: First Metro Save and Learn Phil. Index Fund, Inc. | D15: 104697431 | E15: 799966 | F15: =D15-E15 -> 103897465 | G15: 101962097 | H15: 546 | I15: 662770 | J15: 320731 | K15: =I15-J15 -> 342039 | L15: =I15+Mar!L15 -> 6108744.7 | M15: =J15+Mar!M15 -> 5127933.9 | N15: =L15-M15 -> 980810.8
B16: 8 | C16: MBG Equity Investment Fund, Inc. | D16: 131712890 | E16: 3997860 | F16: =D16-E16 -> 127715030 | G16: 112676941 | H16: 50 | I16: 0 | J16: 1621658 | K16: =I16-J16 -> -1621658 | L16: =I16+Mar!L16 -> 241.49 | M16: =J16+Mar!M16 -> 2385882.9 | N16: =L16-M16 -> -2385641.4
B17: 9 | C17: PAMI Equity Index Fund, Inc. | D17: 1.3619197e+09 | E17: 74392111 | F17: =D17-E17 -> 1287527639 | G17: 1.306339e+09 | H17: 12146 | I17: 0 | J17: 6486076 | K17: =I17-J17 -> -6486076 | L17: =I17+Mar!L17 -> 0 | M17: =J17+Mar!M17 -> 56156615 | N17: =L17-M17 -> -56156615
B18: 10 | C18: Philam Strategic Growth Fund, Inc. | D18: 3.9284951e+09 | E18: 1.6284258e+08 | F18: =D18-E18 -> 3765652473 | G18: 3.3630699e+09 | H18: 12093 | I18: 2872849.1 | J18: 16902753 | K18: =I18-J18 -> -14029904 | L18: =I18+Mar!L18 -> 13156218 | M18: =J18+Mar!M18 -> 1.0430554e+08 | N18: =L18-M18 -> -91149324
B19: 11 | C19: Philequity Dividend Yield Fund, Inc. | D19: 2250008121 | E19: 5450875 | F19: =D19-E19 -> 2244557246 | G19: 1952954572 | H19: 5522 | I19: 1521685 | J19: 2874317 | K19: =I19-J19 -> -1352632 | L19: =I19+Mar!L19 -> 1.369898e+08 | M19: =J19+Mar!M19 -> 14291358 | N19: =L19-M19 -> 1.2269845e+08
B20: 12 | C20: Philequity Fund, Inc. | D20: 10026638780 | E20: 48501629 | F20: =D20-E20 -> 9978137151 | G20: 9069995771 | H20: 35719 | I20: 7969619 | J20: 38388163 | K20: =I20-J20 -> -30418544 | L20: =I20+Mar!L20 -> 71588837 | M20: =J20+Mar!M20 -> 1.9372577e+08 | N20: =L20-M20 -> -1.2213694e+08
... B27: 19 | C27: United Fund, Inc. | D27: 602158905 | E27: 1634154 | F27: =D27-E27 -> 600524751 | G27: 519188141 | H27: 1299 | I27: 226182 | J27: 424100 | K27: =I27-J27 -> -197918 | L27: =I27+Mar!L27 -> 4180887.6 | M27: =J27+Mar!M27 -> 4565504.2 | N27: =L27-M27 -> -384616.59
A28: Primarily invested in Peso Securities (units)
B29: 20 | C29: COL Equity Index Unitized Mutual Fund, Inc. | D29: 196433580 | E29: 907906 | F29: =D29-E29 -> 195525674 | G29: 190585636 | H29: 1831 | I29: 5141519 | J29: 607224 | K29: =I29-J29 -> 4534295 | L29: =I29+Mar!L29 -> 87956560 | M29: =J29+Mar!M29 -> 4467255.8 | N29: =L29-M29 -> 83489304
B30: 21 | C30: Philequity Alpha One Fund, Inc. | D30: 350754219 | E30: 5543884 | F30: =D30-E30 -> 345210335 | G30: 302350718 | H30: 1403 | I30: 2887511 | J30: 2537938 | K30: =I30-J30 -> 349573 | L30: =I30+Mar!L30 -> 11007211 | M30: =J30+Mar!M30 -> 15379535 | N30: =L30-M30 -> -4372324
B31: 22 | C31: Philippine Stock Index Fund Corp. | D31: 5.0876378e+08 | E31: 1899177.5 | F31: =D31-E31 -> 5.068646e+08 | G31: 5.0244325e+08 | H31: 370876 | I31: 20438722 | J31: 13223196 | K31: =I31-J31 -> 7215525.4 | L31: =I31+Mar!L31 -> 1.1806011e+08 | M31: =J31+Mar!M31 -> 1.0048196e+08 | N31: =L31-M31 -> 17578147
A32: Exchange Traded Fund
B33: 23 | C33: First Metro Phil. Equity Exchange Traded Fund, Inc. | D33: 2212522760 | E33: 5746902 | F33: =D33-E33 -> 2206775858 | G33: 2183005778 | H33: 3262 | I33: 2027560 | J33: 4091292 | K33: =I33-J33 -> -2063732 | L33: =I33+Mar!L33 -> 26284151 | M33: =J33+Mar!M33 -> 80991881 | N33: =L33-M33 -> -54707730
A34: Sub total - Peso Currency | D34: =SUM(D9:D33) -> 69821583845 | E34: =SUM(E9:E33) -> 6.8537759e+08 | F34: =SUM(F9:F33) -> 69136206251 | G34: =SUM(G9:G33) -> 65190195279 | H34: =SUM(H9:H33) -> 655135 | I34: =SUM(I9:I33) -> 1.7136161e+08 | J34: =SUM(J9:J33) -> 4.2413855e+08 | K34: =SUM(K9:K33) -> -2.5277693e+08 | ... N34: =SUM(N9:N33) -> -4.8062644e+08
A35: Primarily invested in foreign currency securities (shares)
B36: 24 | C36: ATRAM AsiaPlus Equity Fund, Inc. | D36: =55.38*632270.24 -> 35015126 | E36: =55.38*13124.47 -> 726833.15 | F36: =D36-E36 -> 34288293 | G36: =55.38*561556.6 -> 31099005 | H36: 54 | I36: =55.38*189.86 -> 10514.447 | J36: =55.38*919.93 -> 50945.723 | K36: =I36-J36 -> -40431.277 | L36: =I36+Mar!L36 -> 89394.067 | M36: =J36+Mar!M36 -> 70327.813 | N36: =L36-M36 -> 19066.253
B37: 25 | C37: Sun Life Prosperity World Voyager Fund, Inc. | D37: 1831047393 | E37: 8458856 | F37: =D37-E37 -> 1822588537 | G37: 0 | H37: 2881 | I37: 1608433 | J37: 4852919 | K37: =I37-J37 -> -3244486 | L37: =I37+Mar!L37 -> 20083495 | M37: =J37+Mar!M37 -> 82612488 | N37: =L37-M37 -> -62528993
A38: Sub total - US Currency | D38: =SUM(D36:D37) -> 1866062519 | E38: =SUM(E36:E37) -> 9185689.1 | F38: =SUM(F36:F37) -> 1856876830 | G38: =SUM(G36:G37) -> 31099005 | H38: =SUM(H36:H37) -> 2935 | I38: =SUM(I36:I37) -> 1618947.4 | J38: =SUM(J36:J37) -> 4903864.7 | K38: =SUM(K36:K37) -> -3284917.3 | ... N38: =SUM(N36:N37) -> -62509927
A39: Sub total - stock funds | D39: =D34+D38 -> 71687646364 | E39: =E34+E38 -> 6.9456328e+08 | F39: =F34+F38 -> 70993083080 | G39: =G34+G38 -> 65221294283 | H39: =H34+H38 -> 658070 | I39: =I34+I38 -> 1.7298056e+08 | J39: =J34+J38 -> 4.2904241e+08 | K39: =K34+K38 -> -2.5606185e+08 | ... N39: =N34+N38 -> -5.4313637e+08
A40: Balanced Funds
A41: Primarily invested in Peso Securities (shares)
B42: 26 | C42: ATRAM Dynamic Allocation Fund, Inc. | D42: 128087667 | E42: 9040364 | F42: =D42-E42 -> 119047303 | G42: 34591450 | H42: 724 | I42: 214713 | J42: 111893 | K42: =I42-J42 -> 102820 | L42: =I42+Mar!L42 -> 1305209.1 | M42: =J42+Mar!M42 -> 851134 | N42: =L42-M42 -> 454075.06
B43: 27 | C43: ATRAM Philippine Balanced Fund, Inc. | D43: 604211941 | E43: 12563354 | F43: =D43-E43 -> 591648587 | G43: 266804912 | H43: 2415 | I43: 417818 | J43: 1591707 | K43: =I43-J43 -> -1173889 | L43: =I43+Mar!L43 -> 3541440.1 | M43: =J43+Mar!M43 -> 17757274 | N43: =L43-M43 -> -14215834
B44: 28 | C44: First Metro Save and Learn Balanced Fund, Inc. | D44: 1078420636 | E44: 16022947 | F44: =D44-E44 -> 1062397689 | G44: 509526700 | H44: 4635 | I44: 671902 | J44: 7277210 | K44: =I44-J44 -> -6605308 | L44: =I44+Mar!L44 -> 7159216.5 | M44: =J44+Mar!M44 -> 21740310 | N44: =L44-M44 -> -14581094
B45: 29 | C45: First Metro Save and Learn F.O.C.C.U.S. Dynamic Fund, Inc. | D45: 290596193 | E45: 4956355 | F45: =D45-E45 -> 285639838 | G45: 133315522 | H45: 245 | I45: 13086295 | J45: 10084 | K45: =I45-J45 -> 13076211 | L45: =I45+Mar!L45 -> 22757889 | M45: =J45+Mar!M45 -> 42546519 | N45: =L45-M45 -> -19788630
B46: 30 | C46: NCM Mutual Fund of the Phils., Inc. | D46: 352168980 | E46: 3988742 | F46: =D46-E46 -> 348180238 | G46: 157797583 | H46: 54 | I46: 0 | K46: =I46-J46 -> 0 | L46: =I46+Mar!L46 -> 0 | M46: =J46+Mar!M46 -> 1508185 | N46: =L46-M46 -> -1508185
B47: 31 | C47: PAMI Horizon Fund, Inc. | D47: 5.6016077e+08 | E47: 18515127 | F47: =D47-E47 -> 5.4164564e+08 | G47: 2.7946804e+08 | H47: 10056 | I47: 114470.59 | J47: 8539447.4 | K47: =I47-J47 -> -8424976.8 | L47: =I47+Mar!L47 -> 2043464.9 | M47: =J47+Mar!M47 -> 20662543 | N47: =L47-M47 -> -18619078
B48: 32 | C48: Philam Fund, Inc. | D48: 2.1245928e+09 | E48: 64291188 | F48: =D48-E48 -> 2060301587 | G48: 1.0394057e+09 | H48: 8107 | I48: 1249811.8 | J48: 9094962 | K48: =I48-J48 -> -7845150.2 | L48: =I48+Mar!L48 -> 7892045 | M48: =J48+Mar!M48 -> 57763451 | N48: =L48-M48 -> -49871406
B49: 33 | C49: Solidaritas Fund, Inc. | D49: 1.3851964e+08 | E49: 169852.83 | F49: =D49-E49 -> 1.3834979e+08 | G49: 76575224 | H49: 198 | I49: 4998.34 | J49: 105465.41 | K49: =I49-J49 -> -100467.07 | L49: =I49+Mar!L49 -> 216294.67 | M49: =J49+Mar!M49 -> 1737967.6 | N49: =L49-M49 -> -1521672.9
B50: 34 | C50: Sun Life Prosperity Balanced Fund, Inc. | D50: 7398265146 | E50: 160060307 | F50: =D50-E50 -> 7238204839 | G50: 3532450839 | H50: 53760 | I50: 7373278 | J50: 26322514 | K50: =I50-J50 -> -18949236 | L50: =I50+Mar!L50 -> 33271386 | M50: =J50+Mar!M50 -> 1.9284472e+08 | N50: =L50-M50 -> -1.5957333e+08
B51: 35 | C51: Sun Life Prosperity Dynamic Fund, Inc. | D51: 1182599992 | E51: 12902762 | F51: =D51-E51 -> 1169697230 | G51: 626817425 | H51: 4998 | I51: 0 | J51: 3201908 | K51: =I51-J51 -> -3201908 | L51: =I51+Mar!L51 -> 0 | M51: =J51+Mar!M51 -> 18976148 | N51: =L51-M51 -> -18976148
A52: Primarily invested in Peso Securities (units)
B53: 36 | C53: Sun Life Prosperity Achiever Fund 2028, Inc. | D53: 78296086 | E53: 288718 | F53: =D53-E53 -> 78007368 | G53: 23177051 | H53: 1080 | I53: 487882 | J53: 39850 | K53: =I53-J53 -> 448032 | L53: =I53+Mar!L53 -> 2125053.2 | M53: =J53+Mar!M53 -> 371391.55 | N53: =L53-M53 -> 1753661.6
B54: 37 | C54: Sun Life Prosperity Achiever Fund 2038, Inc. | D54: 57106410 | E54: 296009 | F54: =D54-E54 -> 56810401 | G54: 44835485 | H54: 422 | I54: 139506 | J54: 289101 | K54: =I54-J54 -> -149595 | L54: =I54+Mar!L54 -> 825247 | M54: =J54+Mar!M54 -> 610766.19 | N54: =L54-M54 -> 214480.81
B55: 38 | C55: Sun Life Prosperity Achiever Fund 2048, Inc. | D55: 48011871 | E55: 219875 | F55: =D55-E55 -> 47791996 | G55: 40362550 | H55: 196 | I55: 48000 | J55: 11422 | K55: =I55-J55 -> 36578 | L55: =I55+Mar!L55 -> 229950 | M55: =J55+Mar!M55 -> 102803.96 | N55: =L55-M55 -> 127146.04
A56: Sub total - Peso Currency | D56: =SUM(D42:D55) -> 14041038106 | E56: =SUM(E42:E55) -> 3.033156e+08 | F56: =SUM(F42:F55) -> 13737722505 | G56: =SUM(G42:G55) -> 6765128464 | H56: =SUM(H42:H55) -> 86890 | I56: =SUM(I42:I55) -> 23808675 | J56: =SUM(J42:J55) -> 56595564 | K56: =SUM(K42:K55) -> -32786889 | ... N56: =SUM(N42:N55) -> -2.9610602e+08
A57: Primarily invested in foreign currency securities (shares)
B58: 39 | C58: Cocolife Dollar Fund Builder, Inc. | D58: 72088549 | E58: 424241 | F58: =D58-E58 -> 71664308 | G58: 0 | H58: 51 | I58: 0 | J58: 0 | K58: =I58-J58 -> 0 | L58: =I58+Mar!L58 -> 0 | M58: =J58+Mar!M58 -> 447875.75 | N58: =L58-M58 -> -447875.75
B59: 40 | C59: PAMI Asia Balanced Fund, Inc. | D59: 3.4505844e+08 | E59: 24104628 | F59: =D59-E59 -> 3.2095382e+08 | G59: 1.7029174e+08 | H59: 256 | I59: 0 | J59: 1115977.3 | K59: =I59-J59 -> -1115977.3 | L59: =I59+Mar!L59 -> 5631.4684 | M59: =J59+Mar!M59 -> 10855218 | N59: =L59-M59 -> -10849586
B60: 41 | C60: Sun Life Prosperity Dollar Advantage Fund, Inc. | D60: 1531707348 | E60: 4911434 | F60: =D60-E60 -> 1526795914 | G60: 0 | H60: 4142 | I60: 614718 | J60: 5651635 | K60: =I60-J60 -> -5036917 | L60: =I60+Mar!L60 -> 3381681.3 | M60: =J60+Mar!M60 -> 49668922 | N60: =L60-M60 -> -46287241
B61: 42 | C61: Sun Life Prosperity Dollar Wellspring Fund, Inc. | D61: 268377307 | E61: 1365981 | F61: =D61-E61 -> 267011326 | G61: 0 | H61: 717 | I61: 27690 | J61: 1651089 | K61: =I61-J61 -> -1623399 | L61: =I61+Mar!L61 -> 672999.06 | M61: =J61+Mar!M61 -> 32608293 | N61: =L61-M61 -> -31935294
A62: Sub total - US Currency | D62: =SUM(D58:D61) -> 2217231648 | E62: =SUM(E58:E61) -> 30806284 | F62: =SUM(F58:F61) -> 2186425364 | G62: =SUM(G58:G61) -> 1.7029174e+08 | H62: =SUM(H58:H61) -> 5166 | I62: =SUM(I58:I61) -> 642408 | J62: =SUM(J58:J61) -> 8418701.3 | K62: =SUM(K58:K61) -> -7776293.3 | ... N62: =SUM(N58:N61) -> -89519997
A63: Sub total - balanced funds | D63: =D56+D62 -> 16258269754 | E63: =E56+E62 -> 3.3412189e+08 | F63: =F56+F62 -> 15924147869 | G63: =G56+G62 -> 6935420204 | H63: =H56+H62 -> 92056 | I63: =I56+I62 -> 24451083 | J63: =J56+J62 -> 65014265 | K63: =K56+K62 -> -40563182 | ... N63: =N56+N62 -> -3.8562602e+08
A64: Bond Funds
A65: Primarily invested in Peso Securities (shares)
B66: 43 | C66: ALFM Peso Bond Fund, Inc. | D66: 38916311427 | E66: 2.5239928e+08 | F66: =D66-E66 -> 38663912145 | G66: 924912800 | H66: 24570 | I66: 2.0620251e+08 | J66: 4.3991376e+08 | K66: =I66-J66 -> -2.3371124e+08 | L66: =I66+Mar!L66 -> 1044043776 | M66: =J66+Mar!M66 -> 2597193726 | N66: =L66-M66 -> -1553149950
B67: 44 | C67: ATRAM Corporate Bond Fund, Inc. | D67: 492618091 | E67: 438110 | F67: =D67-E67 -> 492179981 | G67: 0 | H67: 1086 | I67: 16216029 | J67: 3220291 | K67: =I67-J67 -> 12995738 | L67: =I67+Mar!L67 -> 48790335 | M67: =J67+Mar!M67 -> 25608293 | N67: =L67-M67 -> 23182041
B68: 45 | C68: Cocolife Fixed Income Fund, Inc. | D68: 994297419 | E68: 23319755 | F68: =D68-E68 -> 970977664 | G68: 0 | H68: 1957 | I68: 2227964 | J68: 18195536 | K68: =I68-J68 -> -15967572 | L68: =I68+Mar!L68 -> 23702221 | M68: =J68+Mar!M68 -> 60863025 | N68: =L68-M68 -> -37160805
B69: 46 | C69: Ekklesia Mutual Fund, Inc. | D69: 1.9752355e+08 | E69: 170346.78 | F69: =D69-E69 -> 197353206 | G69: 4950000 | H69: 195 | I69: 766010.08 | J69: 85323.54 | K69: =I69-J69 -> 680686.54 | L69: =I69+Mar!L69 -> 3864047.9 | M69: =J69+Mar!M69 -> 4257598.6 | N69: =L69-M69 -> -393550.79
B70: 47 | C70: First Metro Save and Learn Fixed Income Fund, Inc. | D70: 1354602922 | E70: 2558332 | F70: =D70-E70 -> 1352044590 | G70: 0 | H70: 1824 | I70: 16661151 | J70: 18833897 | K70: =I70-J70 -> -2172746 | L70: =I70+Mar!L70 -> 86369746 | M70: =J70+Mar!M70 -> 35088601 | N70: =L70-M70 -> 51281145
B71: 48 | C71: Philam Managed Income Fund, Inc. | D71: 7.6453719e+08 | E71: 36846490 | F71: =D71-E71 -> 7.276907e+08 | G71: 0 | H71: 501 | I71: 1076458.6 | J71: 1025711.7 | K71: =I71-J71 -> 50746.9 | L71: =I71+Mar!L71 -> 7515242.5 | M71: =J71+Mar!M71 -> 1.0518337e+08 | N71: =L71-M71 -> -97668126
B72: 49 | C72: Philam Bond Fund, Inc. | D72: 1.7134647e+09 | E72: 24526578 | F72: =D72-E72 -> 1688938169 | G72: 0 | H72: 4982 | I72: 1084225.3 | J72: 6723733.8 | K72: =I72-J72 -> -5639508.5 | L72: =I72+Mar!L72 -> 13222741 | M72: =J72+Mar!M72 -> 45023269 | N72: =L72-M72 -> -31800527
B73: 50 | C73: Philequity Peso Bond Fund, Inc. | D73: 306464993 | E73: 610267 | F73: =D73-E73 -> 305854726 | G73: 0 | H73: 4148 | I73: 1640857 | J73: 3827179 | K73: =I73-J73 -> -2186322 | L73: =I73+Mar!L73 -> 16975794 | M73: =J73+Mar!M73 -> 20421348 | N73: =L73-M73 -> -3445553.7
B74: 51 | C74: Soldivo Bond Fund, Inc. | D74: 1342684201 | E74: 707129 | F74: =D74-E74 -> 1341977072 | G74: 0 | H74: 818 | I74: 1063954 | J74: 1076884 | K74: =I74-J74 -> -12930 | L74: =I74+Mar!L74 -> 1.0410229e+08 | M74: =J74+Mar!M74 -> 4073843 | N74: =L74-M74 -> 1.0002845e+08
B75: 52 | C75: Sun Life Prosperity Bond Fund, Inc. | D75: 5143975560 | E75: 169085279 | F75: =D75-E75 -> 4974890281 | G75: 0 | H75: 16952 | I75: 88063243 | J75: 27737250 | K75: =I75-J75 -> 60325993 | L75: =I75+Mar!L75 -> 653111029 | M75: =J75+Mar!M75 -> 247004678 | N75: =L75-M75 -> 406106351
B76: 53 | C76: Sun Life Prosperity GS Fund, Inc. | D76: 143129992 | E76: 5293272 | F76: =D76-E76 -> 137836720 | G76: 0 | H76: 2670 | I76: 623100 | J76: 2456752 | K76: =I76-J76 -> -1833652 | L76: =I76+Mar!L76 -> 2111232.4 | M76: =J76+Mar!M76 -> 4702375.7 | N76: =L76-M76 -> -2591143.3
A77: Sub total - Peso Currency | D77: =SUM(D66:D76) -> 51369610098 | E77: =SUM(E66:E76) -> 5.1595484e+08 | F77: =SUM(F66:F76) -> 50853655258 | G77: =SUM(G66:G76) -> 929862800 | H77: =SUM(H66:H76) -> 59703 | I77: =SUM(I66:I76) -> 3.3562551e+08 | J77: =SUM(J66:J76) -> 5.2309632e+08 | K77: =SUM(K66:K76) -> -1.8747081e+08 | ... N77: =SUM(N66:N76) -> -1145611672
A78: Primarily invested in foreign currency securities (shares)
B79: 54 | C79: ALFM Dollar Bond Fund, Inc. | D79: 1.375275e+10 | E79: 1.7024445e+08 | F79: =D79-E79 -> 13582505697 | G79: 0 | H79: 8511 | I79: 41876697 | J79: 1.3887275e+08 | K79: =I79-J79 -> -96996049 | L79: =I79+Mar!L79 -> 2.6302041e+08 | M79: =J79+Mar!M79 -> 5.675315e+08 | N79: =L79-M79 -> -3.0451108e+08
B80: 55 | C80: ATRAM Total Return Dollar Bond Fund, Inc. | D80: =55.38*4771386.37 -> 2.6423938e+08 | E80: =55.38*18676.66 -> 1034313.4 | F80: =D80-E80 -> 2.6320506e+08 | G80: 0 | H80: 165 | I80: =55.38*199.33 -> 11038.895 | J80: =55.38*15013.24 -> 831433.23 | K80: =I80-J80 -> -820394.34 | L80: =I80+Mar!L80 -> 1209477 | M80: =J80+Mar!M80 -> 4942259.8 | N80: =L80-M80 -> -3732782.8
B81: 56 | C81: First Metro Save and Learn Dollar Bond Fund, Inc. | D81: 443523711 | E81: 3125435 | F81: =D81-E81 -> 440398276 | G81: 0 | H81: 157 | I81: 1517173 | J81: 1364872 | K81: =I81-J81 -> 152301 | L81: =I81+Mar!L81 -> 9240085.5 | M81: =J81+Mar!M81 -> 6974328 | N81: =L81-M81 -> 2265757.5
B82: 57 | C82: PAMI Global Bond Fund, Inc. | D82: 64374634 | E82: 14070226 | F82: =D82-E82 -> 50304408 | G82: 0 | H82: 27 | I82: 0 | J82: 0 | K82: =I82-J82 -> 0 | L82: =I82+Mar!L82 -> 0 | M82: =J82+Mar!M82 -> 0 | N82: =L82-M82 -> 0
B83: 58 | C83: Philam Dollar Bond Fund, Inc. | D83: 2.0534461e+09 | E83: 52860842 | F83: =D83-E83 -> 2000585255 | G83: 0 | H83: 1882 | I83: 431091.77 | J83: 5372130.3 | K83: =I83-J83 -> -4941038.5 | L83: =I83+Mar!L83 -> 711934.85 | M83: =J83+Mar!M83 -> 56015028 | N83: =L83-M83 -> -55303093
B84: 59 | C84: Philequity Dollar Income Fund, Inc. | D84: 242719402 | E84: 1229043 | F84: =D84-E84 -> 241490359 | G84: 0 | H84: 122 | I84: 149526 | J84: 0 | K84: =I84-J84 -> 149526 | L84: =I84+Mar!L84 -> 568819 | M84: =J84+Mar!M84 -> 427057 | N84: =L84-M84 -> 141762
B85: 60 | C85: Sun Life Prosperity Dollar Abundance Fund, Inc. | D85: 532742307 | E85: 3861690 | F85: =D85-E85 -> 528880617 | G85: 0 | H85: 2535 | I85: 0 | J85: 15507049 | K85: =I85-J85 -> -15507049 | L85: =I85+Mar!L85 -> 96117321 | M85: =J85+Mar!M85 -> 25665408 | N85: =L85-M85 -> 70451913
A86: Sub total - US Currency | D86: =SUM(D79:D85) -> 17353795674 | E86: =SUM(E79:E85) -> 2.46426e+08 | F86: =SUM(F79:F85) -> 17107369676 | G86: =SUM(G79:G85) -> 0 | H86: =SUM(H79:H85) -> 13399 | I86: =SUM(I79:I85) -> 43985527 | J86: =SUM(J79:J85) -> 161948231 | K86: =SUM(K79:K85) -> -117962704 | ... N86: =SUM(N79:N85) -> -290687528
B87: 61 | C87: ALFM Euro Bond Fund, Inc. | D87: 9.5307674e+08 | E87: 7726474.1 | F87: =D87-E87 -> 9.4535027e+08 | G87: 0 | H87: 647 | I87: 2963291.8 | J87: 7416122.3 | K87: =I87-J87 -> -4452830.6 | L87: =I87+Mar!L87 -> 21247953 | M87: =J87+Mar!M87 -> 16048036 | N87: =L87-M87 -> 5199917.3
A88: Sub total - Euro Currency | D88: =SUM(D87) -> 9.5307674e+08 | E88: =SUM(E87) -> 7726474.1 | F88: =SUM(F87) -> 9.4535027e+08 | G88: =SUM(G87) -> 0 | H88: =SUM(H87) -> 647 | I88: =SUM(I87) -> 2963291.8 | J88: =SUM(J87) -> 7416122.3 | K88: =SUM(K87) -> -4452830.6 | ... N88: =SUM(N87) -> 5199917.3
A89: Sub total - bond funds | D89: =D77+D86+D88 -> 69676482515 | E89: =E77+E86+E88 -> 7.7010731e+08 | F89: =F77+F86+F88 -> 68906375202 | G89: =G77+G86+G88 -> 929862800 | H89: =H77+H86+H88 -> 73749 | I89: =I77+I86+I88 -> 3.8257433e+08 | J89: =J77+J86+J88 -> 6.9246067e+08 | K89: =K77+K86+K88 -> -3.0988634e+08 | ... N89: =N77+N86+N88 -> -1431099283
A90: Money Market Funds
A91: Primarily invested in Peso Securities (shares)
B92: 62 | C92: ALFM Money Market Fund, Inc. | D92: 3.5788591e+10 | E92: 5.110711e+08 | F92: =D92-E92 -> 35277519509 | G92: 0 | H92: 29046 | I92: 1471263532 | J92: 1.5686596e+09 | K92: =I92-J92 -> -97396088 | L92: =I92+Mar!L92 -> 9182788961 | M92: =J92+Mar!M92 -> 8843896363 | N92: =L92-M92 -> 3.388926e+08
B93: 63 | C93: First Metro Save and Learn Money Market Fund, Inc. | D93: 2611319806 | E93: 5354100 | F93: =D93-E93 -> 2605965706 | G93: 0 | H93: 777 | I93: 93127984 | J93: 57086520 | K93: =I93-J93 -> 36041464 | L93: =I93+Mar!L93 -> 3.4136477e+08 | M93: =J93+Mar!M93 -> 5.8737074e+08 | N93: =L93-M93 -> -2.4600597e+08
B94: 64 | C94: Sun Life Prosperity Peso Starter Fund, Inc. | D94: 38096782723 | E94: 159169312 | F94: =D94-E94 -> 37937613411 | G94: 0 | H94: 66904 | I94: 2029174298 | J94: 3781700540 | K94: =I94-J94 -> -1752526242 | L94: =I94+Mar!L94 -> 8614760702 | M94: =J94+Mar!M94 -> 23291789766 | N94: =L94-M94 -> -14677029064
A95: Primarily invested in Peso Securities (units)
B96: 65 | C96: ALFM Money Market Fund, Inc. | D96: 5.9468476e+09 | E96: 4.9560806e+08 | F96: =D96-E96 -> 5451239588 | G96: 0 | H96: 5691 | I96: 9.1154219e+08 | J96: 3.8845934e+08 | K96: =I96-J96 -> 5.2308285e+08 | L96: =I96+Mar!L96 -> 6077584506 | M96: =J96+Mar!M96 -> 4208237883 | N96: =L96-M96 -> 1869346622
A97: Sub total - Peso Currency | D97: =SUM(D92:D94)+D96 -> 82443540786 | E97: =SUM(E92:E94)+E96 -> 1171202571 | F97: =SUM(F92:F94)+F96 -> 81272338214 | G97: =SUM(G92:G94)+G96 -> 0 | H97: =SUM(H92:H94)+H96 -> 102418 | I97: =SUM(I92:I94)+I96 -> 4505108000 | J97: =SUM(J92:J94)+J96 -> 5795906018 | K97: =SUM(K92:K94)+K96 -> -1290798018 | ... N97: =SUM(N92:N94)+N96 -> -12714795813
A98: Primarily invested in foreign currency securities (shares)
B99: 66 | C99: Sun Life Prosperity Dollar Starter Fund, Inc. | D99: 3987818761 | E99: 15450960 | F99: =D99-E99 -> 3972367801 | G99: 0 | H99: 3513 | I99: 610251762 | J99: 738478065 | K99: =I99-J99 -> -128226303 | L99: =I99+Mar!L99 -> 2753863843 | M99: =J99+Mar!M99 -> 5416166773 | N99: =L99-M99 -> -2662302930
A100: Sub total - US Currency | D100: =SUM(D99) -> 3987818761 | E100: =SUM(E99) -> 15450960 | F100: =SUM(F99) -> 3972367801 | G100: =SUM(G99) -> 0 | H100: =SUM(H99) -> 3513 | I100: =SUM(I99) -> 610251762 | J100: =SUM(J99) -> 738478065 | K100: =SUM(K99) -> -128226303 | ... N100: =SUM(N99) -> -2662302930
A101: Sub total - money market funds | D101: =D97+D100 -> 86431359547 | E101: =E97+E100 -> 1186653531 | F101: =F97+F100 -> 85244706015 | G101: =G97+G100 -> 0 | H101: =H97+H100 -> 105931 | I101: =I97+I100 -> 5115359762 | J101: =J97+J100 -> 6534384083 | K101: =K97+K100 -> -1419024321 | ... N101: =N97+N100 -> -15377098743
A102: Feeder Fund
A103: Primarily invested in Peso securities (units)
B104: 67 | C104: ALFM Global Multi-Asset Income Fund Inc. | D104: 9.3346773e+09 | E104: 43262674 | F104: =D104-E104 -> 9291414593 | G104: 0 | H104: 76524 | I104: 51151662 | J104: 45764492 | K104: =I104-J104 -> 5387169.9 | L104: =I104+Mar!L104 -> 4.3326669e+08 | M104: =J104+Mar!M104 -> 4.6301623e+08 | N104: =L104-M104 -> -29749539
B105: 68 | C105: Sun Life Prosperity World Equity Index Feeder Fund, Inc. | D105: 3320603522 | E105: 39449370 | F105: =D105-E105 -> 3281154152 | G105: 0 | H105: 6082 | I105: 10906391 | J105: 140432363 | K105: =I105-J105 -> -129525972 | L105: =I105+Mar!L105 -> 76214275 | M105: =J105+Mar!M105 -> 2.6923033e+08 | N105: =L105-M105 -> -1.9301605e+08
A106: Sub total - Peso Currency | D106: =D104+D105 -> 12655280789 | E106: =E104+E105 -> 82712044 | F106: =F104+F105 -> 12572568745 | G106: =G104+G105 -> 0 | H106: =H104+H105 -> 82606 | I106: =I104+I105 -> 62058053 | J106: =J104+J105 -> 1.8619686e+08 | K106: =K104+K105 -> -1.241388e+08 | ... N106: =N104+N105 -> -222765593
...

Sheet May
A1: PHILIPPINE INVESTMENT FUNDS ASSOCIATION, INC.
A2: MUTUAL FUNDS STATISTICAL REPORT
A3: Month of May 2023
A4: (Amounts in Peso)
I5: F O R - T H E - M O N T H | L5: Y E A R - T O - D A T E
A6: Fund Category | C6: Fund Name | D6: ASSETS | E6: LIABILITIES | F6: NET ASSETS | G6: EQUITY INV. | H6: NO. OF A/C | I6: SALES | J6: REDEMPTIONS | K6: NET SALES | L6: TOTAL SALES | M6: TOTAL REDEMPTIONS | N6: TOTAL NET SALES
A7: Stock Funds
A8: Primarily invested in Peso Securities (shares)
B9: 1 | C9: ALFM Growth Fund, Inc. | D9: 4580283054 | E9: 41708631 | F9: =D9-E9 -> 4538574423 | G9: 4088428812 | H9: 7113 | I9: 21300859 | J9: 59179975 | K9: =I9-J9 -> -37879116 | L9: =I9+Apr!L9 -> 47684156 | M9: =J9+Apr!M9 -> 2.3105855e+08 | N9: =L9-M9 -> -1.833744e+08
B10: 2 | C10: ATRAM Alpha Opportunity Fund, Inc. | D10: 807006136 | E10: 36975838 | F10: =D10-E10 -> 770030298 | G10: 727559256 | H10: 4210 | I10: 10786118 | J10: 5902468 | K10: =I10-J10 -> 4883650 | L10: =I10+Apr!L10 -> 29597594 | M10: =J10+Apr!M10 -> 44831632 | N10: =L10-M10 -> -15234038
B11: 3 | C11: ATRAM Phil. Equity Opportunity Fund, Inc. | D11: 1338790122 | E11: 17473630 | F11: =D11-E11 -> 1321316492 | G11: 1262531747 | H11: 2822 | I11: 5539370 | J11: 102641009 | K11: =I11-J11 -> -97101639 | L11: =I11+Apr!L11 -> 4.0364067e+08 | M11: =J11+Apr!M11 -> 3.7859892e+08 | N11: =L11-M11 -> 25041749
B12: 4 | C12: Climbs Share Capital Equity Investment Fund Corp. | D12: 345494042 | E12: 7536978 | F12: =D12-E12 -> 337957064 | G12: 231995040 | H12: 1775 | I12: 559688 | J12: 64773 | K12: =I12-J12 -> 494915 | L12: =I12+Apr!L12 -> 2582222.5 | M12: =J12+Apr!M12 -> 1341651.5 | N12: =L12-M12 -> 1240571
B13: 5 | C13: First Metro Consumer Fund, Inc. | D13: 514887101 | E13: 8495304 | F13: =D13-E13 -> 506391797 | G13: 444226187 | H13: 1393 | I13: 509137 | J13: 1535932 | K13: =I13-J13 -> -1026795 | L13: =I13+Apr!L13 -> 2841698.5 | M13: =J13+Apr!M13 -> 7026866.4 | N13: =L13-M13 -> -4185167.9
B14: 6 | C14: First Metro Save and Learn Equity Fund, Inc. | D14: 4107114137 | E14: 42256803 | F14: =D14-E14 -> 4064857334 | G14: 3764677328 | H14: 15997 | I14: 13906297 | J14: 191260478 | K14: =I14-J14 -> -177354181 | L14: =I14+Apr!L14 -> 1.1935812e+08 | M14: =J14+Apr!M14 -> 2.9297472e+08 | N14: =L14-M14 -> -173616604
B15: 7 | C15: First Metro Save and Learn Phil. Index Fund, Inc. | D15: 102335589 | E15: 790199 | F15: =D15-E15 -> 101545390 | G15: 99688379 | H15: 541 | I15: 741530 | J15: 944418 | K15: =I15-J15 -> -202888 | L15: =I15+Apr!L15 -> 6850274.7 | M15: =J15+Apr!M15 -> 6072351.9 | N15: =L15-M15 -> 777922.8
B16: 8 | C16: MBG Equity Investment Fund, Inc. | D16: 132203274 | E16: 2397846 | F16: =D16-E16 -> 129805428 | G16: 118915632 | H16: 50 | I16: 0 | J16: 75475 | K16: =I16-J16 -> -75475 | L16: =I16+Apr!L16 -> 241.49 | M16: =J16+Apr!M16 -> 2461357.9 | N16: =L16-M16 -> -2461116.4
B17: 9 | C17: PAMI Equity Index Fund, Inc. | D17: 1330130478 | E17: 74573444 | F17: =D17-E17 -> 1255557034 | G17: 1272397363 | H17: 12086 | I17: 0 | J17: 5781563 | K17: =I17-J17 -> -5781563 | L17: =I17+Apr!L17 -> 0 | M17: =J17+Apr!M17 -> 61938178 | N17: =L17-M17 -> -61938178
B18: 10 | C18: Philam Strategic Growth Fund, Inc. | D18: 3872439462 | E18: 202508627 | F18: =D18-E18 -> 3669930835 | G18: 3297074710 | H18: 12041 | I18: 1977642 | J18: 33389100 | K18: =I18-J18 -> -31411458 | L18: =I18+Apr!L18 -> 15133860 | M18: =J18+Apr!M18 -> 1.3769464e+08 | N18: =L18-M18 -> -1.2256078e+08
B19: 11 | C19: Philequity Dividend Yield Fund, Inc. | D19: 2.2017712e+09 | E19: 11092900 | F19: =D19-E19 -> 2190678272 | G19: =VLOOKUP(C19,'[1]May 2023'!$A:$E,5,FALSE) -> #REF! | H19: 5438 | I19: 1797727.2 | J19: 7003587.1 | K19: =I19-J19 -> -5205859.9 | L19: =I19+Apr!L19 -> 1.3878753e+08 | M19: =J19+Apr!M19 -> 21294945 | N19: =L19-M19 -> 117492586
B20: 12 | C20: Philequity Fund, Inc. | D20: 9.8166714e+09 | E20: 83043570 | F20: =D20-E20 -> 9733627855 | G20: =VLOOKUP(C20,'[1]May 2023'!$A:$E,5,FALSE) -> #REF! | H20: 35498 | I20: 16169798 | J20: 67042576 | K20: =I20-J20 -> -50872778 | L20: =I20+Apr!L20 -> 87758635 | M20: =J20+Apr!M20 -> 2.6076835e+08 | N20: =L20-M20 -> -1.7300972e+08
B21: 13 | C21: Philequity MSCI Phil. Index Fund, Inc. | D21: 3.2865136e+08 | E21: 19138827 | F21: =D21-E21 -> 3.0951253e+08 | G21: =VLOOKUP(C21,'[1]May 2023'!$A:$E,5,FALSE) -> #REF! | H21: 998 | I21: 211920.79 | J21: 536416.84 | K21: =I21-J21 -> -324496.05 | L21: =I21+Apr!L21 -> 1624149.1 | M21: =J21+Apr!M21 -> 4097591.6 | N21: =L21-M21 -> -2473442.6
B22: 14 | C22: Philequity PSE Index Fund, Inc. | D22: 3.8580665e+09 | E22: 13561922 | F22: =D22-E22 -> 3844504596 | G22: =VLOOKUP(C22,'[1]May 2023'!$A:$E,5,FALSE) -> #REF! | H22: 26552 | I22: 8896361.5 | J22: 14227740 | K22: =I22-J22 -> -5331378.1 | L22: =I22+Apr!L22 -> 2.6753906e+08 | M22: =J22+Apr!M22 -> 1.999281e+08 | N22: =L22-M22 -> 67610955
B23: 15 | C23: Philippine Stock Index Fund Corp. | D23: 8683492437 | E23: 12709656 | F23: =D23-E23 -> 8670782781 | G23: 8621744003 | H23: 14009 | I23: 1084781 | J23: 68954130 | K23: =I23-J23 -> -67869349 | L23: =I23+Apr!L23 -> 9007613 | M23: =J23+Apr!M23 -> 4.7099363e+08 | N23: =L23-M23 -> -4.6198601e+08
B24: 16 | C24: Soldivo Strategic Growth Fund, Inc. | D24: 3266404923 | E24: 20535171 | F24: =D24-E24 -> 3245869752 | G24: 3079277001 | H24: 4432 | I24: 52238108 | J24: 3095006 | K24: =I24-J24 -> 49143102 | L24: =I24+Apr!L24 -> 2.0354128e+08 | M24: =J24+Apr!M24 -> 15875726 | N24: =L24-M24 -> 1.8766556e+08
B25: 17 | C25: Sun Life Prosperity Philippine Equity Fund, Inc. | D25: 7060451708 | E25: 119829389 | F25: =D25-E25 -> 6940622319 | G25: 6783849788 | H25: 66621 | I25: 77429144 | J25: 116325853 | K25: =I25-J25 -> -38896709 | L25: =I25+Apr!L25 -> 1.8910185e+08 | M25: =J25+Apr!M25 -> 4.7641023e+08 | N25: =L25-M25 -> -2.8730838e+08
B26: 18 | C26: Sun Life Prosperity Phil. Stock Index Fund, Inc. | D26: 11945694172 | E26: 100045704 | F26: =D26-E26 -> 11845648468 | G26: 11794114479 | H26: 57340 | I26: 73810926 | J26: 173117339 | K26: =I26-J26 -> -99306413 | L26: =I26+Apr!L26 -> 1071536026 | M26: =J26+Apr!M26 -> 1069565183 | N26: =L26-M26 -> 1970842.2
B27: 19 | C27: United Fund, Inc. | D27: 591099456 | E27: 2837752 | F27: =D27-E27 -> 588261704 | G27: 513442594 | H27: 1290 | I27: 317554 | J27: 1653648 | K27: =I27-J27 -> -1336094 | L27: =I27+Apr!L27 -> 4498441.6 | M27: =J27+Apr!M27 -> 6219152.2 | N27: =L27-M27 -> -1720710.6
A28: Primarily invested in Peso Securities (units)
B29: 20 | C29: COL Equity Index Unitized Mutual Fund, Inc. | D29: 197733142 | E29: 1637615 | F29: =D29-E29 -> 196095527 | G29: 190411528 | H29: 1973 | I29: 5567706 | J29: 1011621 | K29: =I29-J29 -> 4556085 | L29: =I29+Apr!L29 -> 93524266 | M29: =J29+Apr!M29 -> 5478876.8 | N29: =L29-M29 -> 88045389
B30: 21 | C30: Philequity Alpha One Fund, Inc. | D30: 3.3427097e+08 | E30: 6658410.8 | F30: =D30-E30 -> 3.2761256e+08 | G30: 3.0089513e+08 | H30: 1393 | I30: 1677415.5 | J30: 4637868.5 | K30: =I30-J30 -> -2960453 | L30: =I30+Apr!L30 -> 12684627 | M30: =J30+Apr!M30 -> 20017404 | N30: =L30-M30 -> -7332777
B31: 22 | C31: Philippine Stock Index Fund Corp. | D31: 501758357 | E31: 2296560 | F31: =D31-E31 -> 499461797 | G31: 495648024 | H31: 504922 | I31: 17776509 | J31: 14758957 | K31: =I31-J31 -> 3017552 | L31: =I31+Apr!L31 -> 1.3583661e+08 | M31: =J31+Apr!M31 -> 1.1524092e+08 | N31: =L31-M31 -> 20595699
A32: Exchange Traded Fund
B33: 23 | C33: First Metro Phil. Equity Exchange Traded Fund, Inc. | D33: 2143737388 | E33: 1645707 | F33: =D33-E33 -> 2142091681 | G33: 2121367148 | H33: 3254 | I33: 0 | J33: 22934110 | K33: =I33-J33 -> -22934110 | L33: =I33+Apr!L33 -> 26284151 | M33: =J33+Apr!M33 -> 103925991 | N33: =L33-M33 -> -77641840
A34: Sub total - Peso Currency | D34: =SUM(D9:D33) -> 68060486421 | E34: =SUM(E9:E33) -> 8.2975048e+08 | F34: =SUM(F9:F33) -> 67230735937 | G34: =SUM(G9:G33) -> #REF! | H34: =SUM(H9:H33) -> 781748 | I34: =SUM(I9:I33) -> 3.1229859e+08 | J34: =SUM(J9:J33) -> 896074043 | K34: =SUM(K9:K33) -> -5.8377545e+08 | ... N34: =SUM(N9:N33) -> -1064401890
A35: Primarily invested in foreign currency securities (shares)
B36: 24 | C36: ATRAM AsiaPlus Equity Fund, Inc. | D36: 34293712 | E36: 1181708.8 | F36: =D36-E36 -> 33112004 | G36: 0 | H36: 54 | I36: 58657.1 | J36: 258449.47 | K36: =I36-J36 -> -199792.37 | L36: =I36+Apr!L36 -> 148051.17 | M36: =J36+Apr!M36 -> 328777.28 | N36: =L36-M36 -> -180726.11
B37: 25 | C37: Sun Life Prosperity World Voyager Fund, Inc. | D37: 1933831702 | E37: 58437981 | F37: =D37-E37 -> 1875393721 | G37: 0 | H37: 2886 | I37: 6687779 | J37: 7259235 | K37: =I37-J37 -> -571456 | L37: =I37+Apr!L37 -> 26771274 | M37: =J37+Apr!M37 -> 89871723 | N37: =L37-M37 -> -63100449
A38: Sub total - US Currency | D38: =SUM(D36:D37) -> 1968125414 | E38: =SUM(E36:E37) -> 59619690 | F38: =SUM(F36:F37) -> 1908505725 | G38: =SUM(G36:G37) -> 0 | H38: =SUM(H36:H37) -> 2940 | I38: =SUM(I36:I37) -> 6746436.1 | J38: =SUM(J36:J37) -> 7517684.5 | K38: =SUM(K36:K37) -> -771248.37 | ... N38: =SUM(N36:N37) -> -63281175
A39: Sub total - stock funds | D39: =D34+D38 -> 70028611835 | E39: =E34+E38 -> 8.8937017e+08 | F39: =F34+F38 -> 69139241662 | G39: =G34+G38 -> #REF! | H39: =H34+H38 -> 784688 | I39: =I34+I38 -> 3.1904503e+08 | J39: =J34+J38 -> 9.0359173e+08 | K39: =K34+K38 -> -5.845467e+08 | ... N39: =N34+N38 -> -1127683066
A40: Balanced Funds
A41: Primarily invested in Peso Securities (shares)
B42: 26 | C42: ATRAM Dynamic Allocation Fund, Inc. | D42: 136647808 | E42: 21415098 | F42: =D42-E42 -> 115232710 | G42: 28457159 | H42: 723 | I42: 221981 | J42: 446662 | K42: =I42-J42 -> -224681 | L42: =I42+Apr!L42 -> 1527190.1 | M42: =J42+Apr!M42 -> 1297796 | N42: =L42-M42 -> 229394.06
B43: 27 | C43: ATRAM Philippine Balanced Fund, Inc. | D43: 690790882 | E43: 116806029 | F43: =D43-E43 -> 573984853 | G43: 220018253 | H43: 2404 | I43: 1022695 | J43: 7505061 | K43: =I43-J43 -> -6482366 | L43: =I43+Apr!L43 -> 4564135.1 | M43: =J43+Apr!M43 -> 25262335 | N43: =L43-M43 -> -20698200
B44: 28 | C44: First Metro Save and Learn Balanced Fund, Inc. | D44: 1058040975 | E44: 10934047 | F44: =D44-E44 -> 1047106928 | G44: 536752090 | H44: 4610 | I44: 1221623 | J44: 4671927 | K44: =I44-J44 -> -3450304 | L44: =I44+Apr!L44 -> 8380839.5 | M44: =J44+Apr!M44 -> 26412237 | N44: =L44-M44 -> -18031398
B45: 29 | C45: First Metro Save and Learn F.O.C.C.U.S. Dynamic Fund, Inc. | D45: 286034684 | E45: 2236080 | F45: =D45-E45 -> 283798604 | G45: 173091479 | H45: 245 | I45: 8518810 | J45: 1237200 | K45: =I45-J45 -> 7281610 | L45: =I45+Apr!L45 -> 31276699 | M45: =J45+Apr!M45 -> 43783719 | N45: =L45-M45 -> -12507020
B46: 30 | C46: NCM Mutual Fund of the Phils., Inc. | D46: 350295727 | E46: 4211386 | F46: =D46-E46 -> 346084341 | G46: 155516563 | H46: 54 | I46: 0 | J46: 0 | K46: =I46-J46 -> 0 | L46: =I46+Apr!L46 -> 0 | M46: =J46+Apr!M46 -> 1508185 | N46: =L46-M46 -> -1508185
B47: 31 | C47: PAMI Horizon Fund, Inc. | D47: 553955165 | E47: 18266913 | F47: =D47-E47 -> 535688252 | G47: 269756246 | H47: 10034 | I47: 202241 | J47: 4585190 | K47: =I47-J47 -> -4382949 | L47: =I47+Apr!L47 -> 2245705.9 | M47: =J47+Apr!M47 -> 25247733 | N47: =L47-M47 -> -23002027
B48: 32 | C48: Philam Fund, Inc. | D48: 2100875342 | E48: 52643497 | F48: =D48-E48 -> 2048231845 | G48: 988913624 | H48: 8090 | I48: 2337885 | J48: 9771921 | K48: =I48-J48 -> -7434036 | L48: =I48+Apr!L48 -> 10229930 | M48: =J48+Apr!M48 -> 67535372 | N48: =L48-M48 -> -57305442
B49: 33 | C49: Solidaritas Fund, Inc. | D49: 134015840 | E49: 554613 | F49: =D49-E49 -> 133461227 | G49: 74873921 | H49: 199 | I49: 19998 | J49: 3713275 | K49: =I49-J49 -> -3693277 | L49: =I49+Apr!L49 -> 236292.67 | M49: =J49+Apr!M49 -> 5451242.5 | N49: =L49-M49 -> -5214949.9
B50: 34 | C50: Sun Life Prosperity Balanced Fund, Inc. | D50: 7458714123 | E50: 301328292 | F50: =D50-E50 -> 7157385831 | G50: 3375029819 | H50: 53783 | I50: 14328996 | J50: 62936026 | K50: =I50-J50 -> -48607030 | L50: =I50+Apr!L50 -> 47600382 | M50: =J50+Apr!M50 -> 2.5578075e+08 | N50: =L50-M50 -> -2.0818036e+08
B51: 35 | C51: Sun Life Prosperity Dynamic Fund, Inc. | D51: 1137193258 | E51: 6142717 | F51: =D51-E51 -> 1131050541 | G51: 585477393 | H51: 4998 | I51: 0 | J51: 32957690 | K51: =I51-J51 -> -32957690 | L51: =I51+Apr!L51 -> 0 | M51: =J51+Apr!M51 -> 51933838 | N51: =L51-M51 -> -51933838
A52: Primarily invested in Peso Securities (units)
B53: 36 | C53: Sun Life Prosperity Achiever Fund 2028, Inc. | D53: 78268370 | E53: 445603 | F53: =D53-E53 -> 77822767 | G53: 22666877 | H53: 1090 | I53: 387279 | J53: 579057 | K53: =I53-J53 -> -191778 | L53: =I53+Apr!L53 -> 2512332.2 | M53: =J53+Apr!M53 -> 950448.55 | N53: =L53-M53 -> 1561883.6
B54: 37 | C54: Sun Life Prosperity Achiever Fund 2038, Inc. | D54: 55428473 | E54: 267004 | F54: =D54-E54 -> 55161469 | G54: 43205949 | H54: 425 | I54: 92950 | J54: 1211823 | K54: =I54-J54 -> -1118873 | L54: =I54+Apr!L54 -> 918197 | M54: =J54+Apr!M54 -> 1822589.2 | N54: =L54-M54 -> -904392.19
B55: 38 | C55: Sun Life Prosperity Achiever Fund 2048, Inc. | D55: 47475569 | E55: 196913 | F55: =D55-E55 -> 47278656 | G55: 39423663 | H55: 199 | I55: 77017 | J55: 1030 | K55: =I55-J55 -> 75987 | L55: =I55+Apr!L55 -> 306967 | M55: =J55+Apr!M55 -> 103833.96 | N55: =L55-M55 -> 203133.04
A56: Sub total - Peso Currency | D56: =SUM(D42:D55) -> 14087736216 | E56: =SUM(E42:E55) -> 535448192 | F56: =SUM(F42:F55) -> 13552288024 | G56: =SUM(G42:G55) -> 6513183036 | H56: =SUM(H42:H55) -> 86854 | I56: =SUM(I42:I55) -> 28431475 | J56: =SUM(J42:J55) -> 129616862 | K56: =SUM(K42:K55) -> -101185387 | ... N56: =SUM(N42:N55) -> -3.9729141e+08
A57: Primarily invested in foreign currency securities (shares)
B58: 39 | C58: Cocolife Dollar Fund Builder, Inc. | D58: 72938472 | E58: 401259 | F58: =D58-E58 -> 72537213 | G58: 0 | H58: 51 | I58: 0 | J58: 0 | K58: =I58-J58 -> 0 | L58: =I58+Apr!L58 -> 0 | M58: =J58+Apr!M58 -> 447875.75 | N58: =L58-M58 -> -447875.75
B59: 40 | C59: PAMI Asia Balanced Fund, Inc. | D59: 340970285 | E59: 26836143 | F59: =D59-E59 -> 314134142 | G59: 166508689 | H59: 256 | I59: 0 | J59: 2242046 | K59: =I59-J59 -> -2242046 | L59: =I59+Apr!L59 -> 5631.4684 | M59: =J59+Apr!M59 -> 13097264 | N59: =L59-M59 -> -13091632
B60: 41 | C60: Sun Life Prosperity Dollar Advantage Fund, Inc. | D60: 1566699002 | E60: 27132749 | F60: =D60-E60 -> 1539566253 | G60: 0 | H60: 4144 | I60: 7548543 | J60: 19456611 | K60: =I60-J60 -> -11908068 | L60: =I60+Apr!L60 -> 10930224 | M60: =J60+Apr!M60 -> 69125533 | N60: =L60-M60 -> -58195309
B61: 42 | C61: Sun Life Prosperity Dollar Wellspring Fund, Inc. | D61: 274709690 | E61: 3010721 | F61: =D61-E61 -> 271698969 | G61: 0 | H61: 731 | I61: 4606579 | J61: 1209537 | K61: =I61-J61 -> 3397042 | L61: =I61+Apr!L61 -> 5279578.1 | M61: =J61+Apr!M61 -> 33817830 | N61: =L61-M61 -> -28538252
A62: Sub total - US Currency | D62: =SUM(D58:D61) -> 2255317449 | E62: =SUM(E58:E61) -> 57380872 | F62: =SUM(F58:F61) -> 2197936577 | G62: =SUM(G58:G61) -> 166508689 | H62: =SUM(H58:H61) -> 5182 | I62: =SUM(I58:I61) -> 12155122 | J62: =SUM(J58:J61) -> 22908194 | K62: =SUM(K58:K61) -> -10753072 | ... N62: =SUM(N58:N61) -> -1.0027307e+08
A63: Sub total - balanced funds | D63: =D56+D62 -> 16343053665 | E63: =E56+E62 -> 592829064 | F63: =F56+F62 -> 15750224601 | G63: =G56+G62 -> 6679691725 | H63: =H56+H62 -> 92036 | I63: =I56+I62 -> 40586597 | J63: =J56+J62 -> 152525056 | K63: =K56+K62 -> -111938459 | ... N63: =N56+N62 -> -4.9756447e+08
A64: Bond Funds
A65: Primarily invested in Peso Securities (shares)
B66: 43 | C66: ALFM Peso Bond Fund, Inc. | D66: 38749691626 | E66: 249919505 | F66: =D66-E66 -> 38499772121 | G66: 919953080 | H66: 24428 | I66: 187763900 | J66: 480238531 | K66: =I66-J66 -> -292474631 | L66: =I66+Apr!L66 -> 1231807676 | M66: =J66+Apr!M66 -> 3077432257 | N66: =L66-M66 -> -1845624581
B67: 44 | C67: ATRAM Corporate Bond Fund, Inc. | D67: 495546274 | E67: 4507434 | F67: =D67-E67 -> 491038840 | G67: 0 | H67: 1079 | I67: 4367927 | J67: 6469374 | K67: =I67-J67 -> -2101447 | L67: =I67+Apr!L67 -> 53158262 | M67: =J67+Apr!M67 -> 32077667 | N67: =L67-M67 -> 21080594
B68: 45 | C68: Cocolife Fixed Income Fund, Inc. | D68: 987630600 | E68: 22942691 | F68: =D68-E68 -> 964687909 | G68: 0 | H68: 1940 | I68: 1518412 | J68: 13689750 | K68: =I68-J68 -> -12171338 | L68: =I68+Apr!L68 -> 25220633 | M68: =J68+Apr!M68 -> 74552775 | N68: =L68-M68 -> -49332143
B69: 46 | C69: Ekklesia Mutual Fund, Inc. | D69: 200436104 | E69: 180312 | F69: =D69-E69 -> 200255792 | G69: 4900000 | H69: 206 | I69: 1257961 | J69: 94464 | K69: =I69-J69 -> 1163497 | L69: =I69+Apr!L69 -> 5122008.8 | M69: =J69+Apr!M69 -> 4352062.6 | N69: =L69-M69 -> 769946.21
B70: 47 | C70: First Metro Save and Learn Fixed Income Fund, Inc. | D70: 1526311889 | E70: 13343154 | F70: =D70-E70 -> 1512968735 | G70: 0 | H70: 1851 | I70: 169646484 | J70: 13870528 | K70: =I70-J70 -> 155775956 | L70: =I70+Apr!L70 -> 2.5601623e+08 | M70: =J70+Apr!M70 -> 48959129 | N70: =L70-M70 -> 2.070571e+08
B71: 48 | C71: Philam Managed Income Fund, Inc. | D71: 765465051 | E71: 36929591 | F71: =D71-E71 -> 728535460 | G71: 0 | H71: 493 | I71: 3623141 | J71: 6828177 | K71: =I71-J71 -> -3205036 | L71: =I71+Apr!L71 -> 11138383 | M71: =J71+Apr!M71 -> 1.1201155e+08 | N71: =L71-M71 -> -1.0087316e+08
B72: 49 | C72: Philam Bond Fund, Inc. | D72: 1731227669 | E72: 24225049 | F72: =D72-E72 -> 1707002620 | G72: 0 | H72: 4976 | I72: 5465061 | J72: 4431973 | K72: =I72-J72 -> 1033088 | L72: =I72+Apr!L72 -> 18687802 | M72: =J72+Apr!M72 -> 49455242 | N72: =L72-M72 -> -30767439
B73: 50 | C73: Philequity Peso Bond Fund, Inc. | D73: 3.1016011e+08 | E73: 976487.63 | F73: =D73-E73 -> 3.0918362e+08 | G73: 0 | H73: 4127 | I73: 1916075.4 | J73: 1037039.7 | K73: =I73-J73 -> 879035.67 | L73: =I73+Apr!L73 -> 18891869 | M73: =J73+Apr!M73 -> 21458387 | N73: =L73-M73 -> -2566518.1
B74: 51 | C74: Soldivo Bond Fund, Inc. | D74: 1373856353 | E74: 2950946 | F74: =D74-E74 -> 1370905407 | G74: 0 | H74: 816 | I74: 27161687 | J74: 290604 | K74: =I74-J74 -> 26871083 | L74: =I74+Apr!L74 -> 1.3126398e+08 | M74: =J74+Apr!M74 -> 4364447 | N74: =L74-M74 -> 1.2689953e+08
B75: 52 | C75: Sun Life Prosperity Bond Fund, Inc. | D75: 5866508589 | E75: 386186307 | F75: =D75-E75 -> 5480322282 | G75: 0 | H75: 17126 | I75: 513453037 | J75: 70970507 | K75: =I75-J75 -> 442482530 | L75: =I75+Apr!L75 -> 1166564066 | M75: =J75+Apr!M75 -> 317975185 | N75: =L75-M75 -> 848588881
B76: 53 | C76: Sun Life Prosperity GS Fund, Inc. | D76: 149031728 | E76: 8631772 | F76: =D76-E76 -> 140399956 | G76: 0 | H76: 2685 | I76: 1190411 | J76: 308010 | K76: =I76-J76 -> 882401 | L76: =I76+Apr!L76 -> 3301643.4 | M76: =J76+Apr!M76 -> 5010385.7 | N76: =L76-M76 -> -1708742.3
A77: Sub total - Peso Currency | D77: =SUM(D66:D76) -> 52155865989 | E77: =SUM(E66:E76) -> 7.5079325e+08 | F77: =SUM(F66:F76) -> 51405072740 | G77: =SUM(G66:G76) -> 924853080 | H77: =SUM(H66:H76) -> 59727 | I77: =SUM(I66:I76) -> 9.173641e+08 | J77: =SUM(J66:J76) -> 5.9822896e+08 | K77: =SUM(K66:K76) -> 3.1913514e+08 | ... N77: =SUM(N66:N76) -> -8.2647653e+08
A78: Primarily invested in foreign currency securities (shares)
B79: 54 | C79: ALFM Dollar Bond Fund, Inc. | D79: 13803537305 | E79: 125725878 | F79: =D79-E79 -> 13677811427 | G79: 0 | H79: 8441 | I79: 42629736 | J79: 166616944 | K79: =I79-J79 -> -123987208 | L79: =I79+Apr!L79 -> 3.0565015e+08 | M79: =J79+Apr!M79 -> 7.3414844e+08 | N79: =L79-M79 -> -4.2849829e+08
B80: 55 | C80: ATRAM Total Return Dollar Bond Fund, Inc. | D80: 267353504 | E80: 2374869 | F80: =D80-E80 -> 264978635 | G80: 0 | H80: 162 | I80: 125205 | J80: 903151 | K80: =I80-J80 -> -777946 | L80: =I80+Apr!L80 -> 1334682 | M80: =J80+Apr!M80 -> 5845410.8 | N80: =L80-M80 -> -4510728.8
B81: 56 | C81: First Metro Save and Learn Dollar Bond Fund, Inc. | D81: 467054008 | E81: 16067236 | F81: =D81-E81 -> 450986772 | G81: 0 | H81: 163 | I81: 4960352 | J81: 268703 | K81: =I81-J81 -> 4691649 | L81: =I81+Apr!L81 -> 14200437 | M81: =J81+Apr!M81 -> 7243031 | N81: =L81-M81 -> 6957406.5
B82: 57 | C82: PAMI Global Bond Fund, Inc. | D82: 65196234 | E82: 14434758 | F82: =D82-E82 -> 50761476 | G82: 0 | H82: 27 | I82: 0 | J82: 0 | K82: =I82-J82 -> 0 | L82: =I82+Apr!L82 -> 0 | M82: =J82+Apr!M82 -> 0 | N82: =L82-M82 -> 0
B83: 58 | C83: Philam Dollar Bond Fund, Inc. | D83: 2034415722 | E83: 23767207 | F83: =D83-E83 -> 2010648515 | G83: 0 | H83: 1871 | I83: 166766 | J83: 11444690 | K83: =I83-J83 -> -11277924 | L83: =I83+Apr!L83 -> 878700.85 | M83: =J83+Apr!M83 -> 67459718 | N83: =L83-M83 -> -66581017
B84: 59 | C84: Philequity Dollar Income Fund, Inc. | D84: 2.3535213e+08 | E84: 1427612.9 | F84: =D84-E84 -> 2.3392452e+08 | G84: 0 | H84: 120 | I84: 572730 | J84: 2945111.3 | K84: =I84-J84 -> -2372381.3 | L84: =I84+Apr!L84 -> 1141549 | M84: =J84+Apr!M84 -> 3372168.3 | N84: =L84-M84 -> -2230619.3
B85: 60 | C85: Sun Life Prosperity Dollar Abundance Fund, Inc. | D85: 557649169 | E85: 19521180 | F85: =D85-E85 -> 538127989 | G85: 0 | H85: 2552 | I85: 10576226 | J85: 2006947 | K85: =I85-J85 -> 8569279 | L85: =I85+Apr!L85 -> 1.0669355e+08 | M85: =J85+Apr!M85 -> 27672355 | N85: =L85-M85 -> 79021192
A86: Sub total - US Currency | D86: =SUM(D79:D85) -> 17430558074 | E86: =SUM(E79:E85) -> 2.0331874e+08 | F86: =SUM(F79:F85) -> 17227239333 | G86: =SUM(G79:G85) -> 0 | H86: =SUM(H79:H85) -> 13336 | I86: =SUM(I79:I85) -> 59031015 | J86: =SUM(J79:J85) -> 1.8418555e+08 | K86: =SUM(K79:K85) -> -1.2515453e+08 | ... N86: =SUM(N79:N85) -> -4.1584206e+08
B87: 61 | C87: ALFM Euro Bond Fund, Inc. | D87: 938896613 | E87: 7506388 | F87: =D87-E87 -> 931390225 | G87: 0 | H87: 638 | I87: 7786935 | J87: 7662775 | K87: =I87-J87 -> 124160 | L87: =I87+Apr!L87 -> 29034888 | M87: =J87+Apr!M87 -> 23710811 | N87: =L87-M87 -> 5324077.3
A88: Sub total - Euro Currency | D88: =SUM(D87) -> 938896613 | E88: =SUM(E87) -> 7506388 | F88: =SUM(F87) -> 931390225 | G88: =SUM(G87) -> 0 | H88: =SUM(H87) -> 638 | I88: =SUM(I87) -> 7786935 | J88: =SUM(J87) -> 7662775 | K88: =SUM(K87) -> 124160 | ... N88: =SUM(N87) -> 5324077.3
A89: Sub total - bond funds | D89: =D77+D86+D88 -> 70525320676 | E89: =E77+E86+E88 -> 9.6161838e+08 | F89: =F77+F86+F88 -> 69563702299 | G89: =G77+G86+G88 -> 924853080 | H89: =H77+H86+H88 -> 73701 | I89: =I77+I86+I88 -> 9.8418205e+08 | J89: =J77+J86+J88 -> 790077279 | K89: =K77+K86+K88 -> 1.9410477e+08 | ... N89: =N77+N86+N88 -> -1236994515
A90: Money Market Funds
A91: Primarily invested in Peso Securities (shares)
B92: 62 | C92: ALFM Money Market Fund, Inc. | D92: 33441296471 | E92: 15144091 | F92: =D92-E92 -> 33426152380 | G92: 0 | H92: 28479 | I92: 330976 | J92: 1921285065 | K92: =I92-J92 -> -1920954089 | L92: =I92+Apr!L92 -> 9183119937 | M92: =J92+Apr!M92 -> 10765181428 | N92: =L92-M92 -> -1582061491
B93: 63 | C93: First Metro Save and Learn Money Market Fund, Inc. | D93: 2361688888 | E93: 34154044 | F93: =D93-E93 -> 2327534844 | G93: 0 | H93: 772 | I93: 42761934 | J93: 327297837 | K93: =I93-J93 -> -284535903 | L93: =I93+Apr!L93 -> 3.8412671e+08 | M93: =J93+Apr!M93 -> 9.1466858e+08 | N93: =L93-M93 -> -5.3054187e+08
B94: 64 | C94: Sun Life Prosperity Peso Starter Fund, Inc. | D94: 35319350802 | E94: 473892456 | F94: =D94-E94 -> 34845458346 | G94: 0 | H94: 67226 | I94: 2524774314 | J94: 5717726950 | K94: =I94-J94 -> -3192952636 | L94: =I94+Apr!L94 -> 11139535016 | M94: =J94+Apr!M94 -> 29009516716 | N94: =L94-M94 -> -17869981700
A95: Primarily invested in Peso Securities (units)
B96: 65 | C96: ALFM Money Market Fund, Inc. | D96: 6191545429 | E96: 67252779 | F96: =D96-E96 -> 6124292650 | G96: 0 | H96: 6219 | I96: 1271785514 | J96: 618916505 | K96: =I96-J96 -> 652869009 | L96: =I96+Apr!L96 -> 7349370020 | M96: =J96+Apr!M96 -> 4827154388 | N96: =L96-M96 -> 2522215631
A97: Sub total - Peso Currency | D97: =SUM(D92:D94)+D96 -> 77313881590 | E97: =SUM(E92:E94)+E96 -> 590443370 | F97: =SUM(F92:F94)+F96 -> 76723438220 | G97: =SUM(G92:G94)+G96 -> 0 | H97: =SUM(H92:H94)+H96 -> 102696 | I97: =SUM(I92:I94)+I96 -> 3839652738 | J97: =SUM(J92:J94)+J96 -> 8585226357 | K97: =SUM(K92:K94)+K96 -> -4745573619 | ... N97: =SUM(N92:N94)+N96 -> -17460369432
A98: Primarily invested in foreign currency securities (shares)
B99: 66 | C99: Sun Life Prosperity Dollar Starter Fund, Inc. | D99: 3727835903 | E99: 33826491 | F99: =D99-E99 -> 3694009412 | G99: 0 | H99: 3530 | I99: 385946849 | J99: 725749473 | K99: =I99-J99 -> -339802624 | L99: =I99+Apr!L99 -> 3139810692 | M99: =J99+Apr!M99 -> 6141916246 | N99: =L99-M99 -> -3002105554
A100: Sub total - US Currency | D100: =SUM(D99) -> 3727835903 | E100: =SUM(E99) -> 33826491 | F100: =SUM(F99) -> 3694009412 | G100: =SUM(G99) -> 0 | H100: =SUM(H99) -> 3530 | I100: =SUM(I99) -> 385946849 | J100: =SUM(J99) -> 725749473 | K100: =SUM(K99) -> -339802624 | ... N100: =SUM(N99) -> -3002105554
...

Sheet June
A1: PHILIPPINE INVESTMENT FUNDS ASSOCIATION, INC.
A2: MUTUAL FUNDS STATISTICAL REPORT
A3: Month of June 2023
A4: (Amounts in Peso)
I5: F O R - T H E - M O N T H | L5: Y E A R - T O - D A T E
A6: Fund Category | C6: Fund Name | D6: ASSETS | E6: LIABILITIES | F6: NET ASSETS | G6: EQUITY INV. | H6: NO. OF A/C | I6: SALES | J6: REDEMPTIONS | K6: NET SALES | L6: TOTAL SALES | M6: TOTAL REDEMPTIONS | N6: TOTAL NET SALES
A7: Stock Funds
A8: Primarily invested in Peso Securities (shares)
B9: 1 | C9: ALFM Growth Fund, Inc. | D9: 4519704326 | E9: 12940968 | F9: =D9-E9 -> 4506763358 | G9: 4063335527 | H9: 7065 | I9: 6314992 | J9: 30883033 | K9: =I9-J9 -> -24568041 | L9: =I9+May!L9 -> 53999148 | M9: =J9+May!M9 -> 2.6194159e+08 | N9: =L9-M9 -> -2.0794244e+08
B10: 2 | C10: ATRAM Alpha Opportunity Fund, Inc. | D10: 7.6409491e+08 | E10: -201219.8 | F10: =D10-E10 -> 7.6429613e+08 | G10: 7.0907016e+08 | H10: 4205 | I10: 3858863.2 | J10: 7787882.2 | K10: =I10-J10 -> -3929019 | L10: =I10+May!L10 -> 33456458 | M10: =J10+May!M10 -> 52619514 | N10: =L10-M10 -> -19163057
B11: 3 | C11: ATRAM Phil. Equity Opportunity Fund, Inc. | D11: 1.3119665e+09 | E11: -1975918.3 | F11: =D11-E11 -> 1313942373 | G11: 1.2413264e+09 | H11: 2798 | I11: 6791913.1 | J11: 14430972 | K11: =I11-J11 -> -7639059.2 | L11: =I11+May!L11 -> 4.1043258e+08 | M11: =J11+May!M11 -> 393029889 | N11: =L11-M11 -> 17402690
B12: 4 | C12: Climbs Share Capital Equity Investment Fund Corp. | D12: 3.4659653e+08 | E12: 8106943.4 | F12: =D12-E12 -> 3.3848959e+08 | G12: 2.3833073e+08 | H12: 1775 | I12: 537755 | J12: 99811.43 | K12: =I12-J12 -> 437943.57 | L12: =I12+May!L12 -> 3119977.5 | M12: =J12+May!M12 -> 1441462.9 | N12: =L12-M12 -> 1678514.5
B13: 5 | C13: First Metro Consumer Fund, Inc. | D13: 503601000 | E13: 4468748 | F13: =D13-E13 -> 499132252 | G13: 433741357 | H13: 1382 | I13: 913160 | J13: 6723954 | K13: =I13-J13 -> -5810794 | L13: =I13+May!L13 -> 3754858.5 | M13: =J13+May!M13 -> 13750820 | N13: =L13-M13 -> -9995961.9
B14: 6 | C14: First Metro Save and Learn Equity Fund, Inc. | D14: 4087023035 | E14: 40116705 | F14: =D14-E14 -> 4046906330 | G14: 3721398214 | H14: 15925 | I14: 21575801 | J14: 47303083 | K14: =I14-J14 -> -25727282 | L14: =I14+May!L14 -> 1.4093392e+08 | M14: =J14+May!M14 -> 3.4027781e+08 | N14: =L14-M14 -> -199343886
B15: 7 | C15: First Metro Save and Learn Phil. Index Fund, Inc. | D15: 100659177 | E15: 2778419 | F15: =D15-E15 -> 97880758 | G15: 96428653 | H15: 534 | I15: 521480 | J15: 3761220 | K15: =I15-J15 -> -3239740 | L15: =I15+May!L15 -> 7371754.7 | M15: =J15+May!M15 -> 9833571.9 | N15: =L15-M15 -> -2461817.2
B16: 8 | C16: MBG Equity Investment Fund, Inc. | D16: 129602761 | E16: 2513877 | F16: =D16-E16 -> 127088884 | G16: 111912846 | H16: 50 | I16: 100000 | J16: 0 | K16: =I16-J16 -> 100000 | L16: =I16+May!L16 -> 100241.49 | M16: =J16+May!M16 -> 2461357.9 | N16: =L16-M16 -> -2361116.4
B17: 9 | C17: PAMI Equity Index Fund, Inc. | D17: 1324812525 | E17: 83001665 | F17: =D17-E17 -> 1241810860 | G17: 1262973553 | H17: 12046 | I17: 0 | J17: 10641597 | K17: =I17-J17 -> -10641597 | L17: =I17+May!L17 -> 0 | M17: =J17+May!M17 -> 72579775 | N17: =L17-M17 -> -72579775
B18: 10 | C18: Philam Strategic Growth Fund, Inc. | D18: 3779463650 | E18: 161752088 | F18: =D18-E18 -> 3617711562 | G18: 3273592686 | H18: 11984 | I18: 1519230 | J18: 43164563 | K18: =I18-J18 -> -41645333 | L18: =I18+May!L18 -> 16653090 | M18: =J18+May!M18 -> 1.808592e+08 | N18: =L18-M18 -> -1.6420611e+08
B19: 11 | C19: Philequity Dividend Yield Fund, Inc. | D19: 2.2317517e+09 | E19: 6314038.7 | F19: =D19-E19 -> 2225437656 | G19: 1.9692092e+09 | H19: 5390 | I19: 3432722.3 | J19: 5976136 | K19: =I19-J19 -> -2543413.7 | L19: =I19+May!L19 -> 1.4222025e+08 | M19: =J19+May!M19 -> 27271081 | N19: =L19-M19 -> 1.1494917e+08
B20: 12 | C20: Philequity Fund, Inc. | D20: 9.7414605e+09 | E20: 55820411 | F20: =D20-E20 -> 9685640050 | G20: 8.842122e+09 | H20: 35340 | I20: 12248419 | J20: 1.0153578e+08 | K20: =I20-J20 -> -89287356 | L20: =I20+May!L20 -> 1.0000705e+08 | M20: =J20+May!M20 -> 3.6230413e+08 | N20: =L20-M20 -> -262297072
... B27: 19 | C27: United Fund, Inc. | D27: 5.9244157e+08 | E27: 7069290.9 | F27: =D27-E27 -> 585372283 | G27: 5.2332429e+08 | H27: 1279 | I27: 330567.29 | J27: 891252.2 | K27: =I27-J27 -> -560684.91 | L27: =I27+May!L27 -> 4829008.9 | M27: =J27+May!M27 -> 7110404.4 | N27: =L27-M27 -> -2281395.5
A28: Primarily invested in Peso Securities (units)
B29: 20 | C29: COL Equity Index Unitized Mutual Fund, Inc. | D29: 2.0168422e+08 | E29: 1071110.2 | F29: =D29-E29 -> 2.006131e+08 | G29: 1.9483351e+08 | H29: 2086 | I29: 4536245.4 | J29: 635459.4 | K29: =I29-J29 -> 3900786 | L29: =I29+May!L29 -> 98060512 | M29: =J29+May!M29 -> 6114336.2 | N29: =L29-M29 -> 91946175
B30: 21 | C30: Philequity Alpha One Fund, Inc. | D30: 3.3233187e+08 | E30: 1287431.5 | F30: =D30-E30 -> 3.3104444e+08 | G30: 3.0225003e+08 | H30: 1378 | I30: 1060898.6 | J30: 187876.83 | K30: =I30-J30 -> 873021.8 | L30: =I30+May!L30 -> 13745526 | M30: =J30+May!M30 -> 20205281 | N30: =L30-M30 -> -6459755.2
B31: 22 | C31: Philippine Stock Index Fund Corp. | D31: 526148519 | E31: 2200743 | F31: =D31-E31 -> 523947776 | G31: 513065465 | H31: 530211 | I31: 34982496 | J31: 9895950 | K31: =I31-J31 -> 25086546 | L31: =I31+May!L31 -> 1.7081911e+08 | M31: =J31+May!M31 -> 1.2513687e+08 | N31: =L31-M31 -> 45682245
A32: Exchange Traded Fund
B33: 23 | C33: First Metro Phil. Equity Exchange Traded Fund, Inc. | D33: 2147148552 | E33: 1768565 | F33: =D33-E33 -> 2145379987 | G33: 2140200348 | H33: 3289 | I33: 6069276 | J33: 0 | K33: =I33-J33 -> 6069276 | L33: =I33+May!L33 -> 32353427 | M33: =J33+May!M33 -> 103925991 | N33: =L33-M33 -> -71572564
A34: Sub total - Peso Currency | D34: =SUM(D9:D33) -> 67576902248 | E34: =SUM(E9:E33) -> 6.0723449e+08 | F34: =SUM(F9:F33) -> 66969667754 | G34: =SUM(G9:G33) -> 63817560688 | H34: =SUM(H9:H33) -> 814805 | I34: =SUM(I9:I33) -> 269482312 | J34: =SUM(J9:J33) -> 5.0357778e+08 | K34: =SUM(K9:K33) -> -2.3409547e+08 | ... N34: =SUM(N9:N33) -> -1298497361
A35: Primarily invested in foreign currency securities (shares)
B36: 24 | C36: ATRAM AsiaPlus Equity Fund, Inc. | D36: 34344004 | E36: -724229.52 | F36: =D36-E36 -> 35068234 | G36: 572690.03 | H36: 54 | I36: 795.33 | J36: 0 | K36: =I36-J36 -> 795.33 | L36: =I36+May!L36 -> 148846.5 | M36: =J36+May!M36 -> 328777.28 | N36: =L36-M36 -> -179930.78
B37: 25 | C37: Sun Life Prosperity World Voyager Fund, Inc. | D37: 1901135258 | E37: 8817940 | F37: =D37-E37 -> 1892317318 | G37: 0 | H37: 2892 | I37: 2646948 | J37: 6694801 | K37: =I37-J37 -> -4047853 | L37: =I37+May!L37 -> 29418222 | M37: =J37+May!M37 -> 96566524 | N37: =L37-M37 -> -67148302
A38: Sub total - US Currency | D38: =SUM(D36:D37) -> 1935479262 | E38: =SUM(E36:E37) -> 8093710.5 | F38: =SUM(F36:F37) -> 1927385552 | G38: =SUM(G36:G37) -> 572690.03 | H38: =SUM(H36:H37) -> 2946 | I38: =SUM(I36:I37) -> 2647743.3 | J38: =SUM(J36:J37) -> 6694801 | K38: =SUM(K36:K37) -> -4047057.7 | ... N38: =SUM(N36:N37) -> -67328233
A39: Sub total - stock funds | D39: =D34+D38 -> 69512381510 | E39: =E34+E38 -> 6.153282e+08 | F39: =F34+F38 -> 68897053306 | G39: =G34+G38 -> 63818133378 | H39: =H34+H38 -> 817751 | I39: =I34+I38 -> 2.7213006e+08 | J39: =J34+J38 -> 5.1027258e+08 | K39: =K34+K38 -> -2.3814253e+08 | ... N39: =N34+N38 -> -1365825594
A40: Balanced Funds
A41: Primarily invested in Peso Securities (shares)
B42: 26 | C42: ATRAM Dynamic Allocation Fund, Inc. | D42: 1.1527189e+08 | E42: -1817653.2 | F42: =D42-E42 -> 1.1708954e+08 | G42: 32362067 | H42: 720 | I42: 193997.32 | J42: 491583.26 | K42: =I42-J42 -> -297585.94 | L42: =I42+May!L42 -> 1721187.4 | M42: =J42+May!M42 -> 1789379.3 | N42: =L42-M42 -> -68191.88
B43: 27 | C43: ATRAM Philippine Balanced Fund, Inc. | D43: 5.6578439e+08 | E43: -16578410 | F43: =D43-E43 -> 5.823628e+08 | G43: 2.4386081e+08 | H43: 2398 | I43: 790681.9 | J43: 19915744 | K43: =I43-J43 -> -19125062 | L43: =I43+May!L43 -> 5354817 | M43: =J43+May!M43 -> 45178079 | N43: =L43-M43 -> -39823262
B44: 28 | C44: First Metro Save and Learn Balanced Fund, Inc. | D44: 1026318888 | E44: 6844517 | F44: =D44-E44 -> 1019474371 | G44: 534069472 | H44: 4580 | I44: 992502 | J44: 26518372 | K44: =I44-J44 -> -25525870 | L44: =I44+May!L44 -> 9373341.6 | M44: =J44+May!M44 -> 52930609 | N44: =L44-M44 -> -43557268
B45: 29 | C45: First Metro Save and Learn F.O.C.C.U.S. Dynamic Fund, Inc. | D45: 288079128 | E45: 1162830 | F45: =D45-E45 -> 286916298 | G45: 174229870 | H45: 245 | I45: 564730 | J45: 849404 | K45: =I45-J45 -> -284674 | L45: =I45+May!L45 -> 31841429 | M45: =J45+May!M45 -> 44633123 | N45: =L45-M45 -> -12791694
B46: 30 | C46: NCM Mutual Fund of the Phils., Inc. | D46: 3.4919166e+08 | E46: 4140409.2 | F46: =D46-E46 -> 3.4505125e+08 | G46: 1.5519828e+08 | H46: 53 | I46: 0 | J46: 68876 | K46: =I46-J46 -> -68876 | L46: =I46+May!L46 -> 0 | M46: =J46+May!M46 -> 1577061 | N46: =L46-M46 -> -1577061
B47: 31 | C47: PAMI Horizon Fund, Inc. | D47: 548304260 | E47: 18127716 | F47: =D47-E47 -> 530176544 | G47: 268894091 | H47: 10011 | I47: 145412 | J47: 2117238 | K47: =I47-J47 -> -1971826 | L47: =I47+May!L47 -> 2391117.9 | M47: =J47+May!M47 -> 27364971 | N47: =L47-M47 -> -24973853
B48: 32 | C48: Philam Fund, Inc. | D48: 2053335360 | E48: 51696547 | F48: =D48-E48 -> 2001638813 | G48: 981740942 | H48: 8057 | I48: 2635740 | J48: 34774652 | K48: =I48-J48 -> -32138912 | L48: =I48+May!L48 -> 12865670 | M48: =J48+May!M48 -> 1.0231002e+08 | N48: =L48-M48 -> -89444354
B49: 33 | C49: Solidaritas Fund, Inc. | D49: 132712707 | E49: 165716 | F49: =D49-E49 -> 132546991 | G49: 74621057 | H49: 197 | I49: 9999 | J49: 728704 | K49: =I49-J49 -> -718705 | L49: =I49+May!L49 -> 246291.67 | M49: =J49+May!M49 -> 6179946.5 | N49: =L49-M49 -> -5933654.9
B50: 34 | C50: Sun Life Prosperity Balanced Fund, Inc. | D50: 7112742697 | E50: 31000609 | F50: =D50-E50 -> 7081742088 | G50: 3464224318 | H50: 53801 | I50: 7646054 | J50: 47260177 | K50: =I50-J50 -> -39614123 | L50: =I50+May!L50 -> 55246436 | M50: =J50+May!M50 -> 3.0304092e+08 | N50: =L50-M50 -> -2.4779449e+08
B51: 35 | C51: Sun Life Prosperity Dynamic Fund, Inc. | D51: 1125956184 | E51: 8387122 | F51: =D51-E51 -> 1117569062 | G51: 594542418 | H51: 4998 | I51: 0 | J51: 3082253 | K51: =I51-J51 -> -3082253 | L51: =I51+May!L51 -> 0 | M51: =J51+May!M51 -> 55016091 | N51: =L51-M51 -> -55016091
A52: Primarily invested in Peso Securities (units)
B53: 36 | C53: Sun Life Prosperity Achiever Fund 2028, Inc. | D53: 77372100 | E53: 1076491 | F53: =D53-E53 -> 76295609 | G53: 22639198 | H53: 1101 | I53: 315597 | J53: 1077571 | K53: =I53-J53 -> -761974 | L53: =I53+May!L53 -> 2827929.2 | M53: =J53+May!M53 -> 2028019.6 | N53: =L53-M53 -> 799909.65
B54: 37 | C54: Sun Life Prosperity Achiever Fund 2038, Inc. | D54: 55154691 | E54: 278634 | F54: =D54-E54 -> 54876057 | G54: 43175901 | H54: 431 | I54: 94117 | J54: 39831 | K54: =I54-J54 -> 54286 | L54: =I54+May!L54 -> 1012314 | M54: =J54+May!M54 -> 1862420.2 | N54: =L54-M54 -> -850106.19
B55: 38 | C55: Sun Life Prosperity Achiever Fund 2048, Inc. | D55: 47292064 | E55: 235941 | F55: =D55-E55 -> 47056123 | G55: 39416520 | H55: 199 | I55: 30500 | J55: 22148 | K55: =I55-J55 -> 8352 | L55: =I55+May!L55 -> 337467 | M55: =J55+May!M55 -> 125981.96 | N55: =L55-M55 -> 211485.04
A56: Sub total - Peso Currency | D56: =SUM(D42:D55) -> 13497516015 | E56: =SUM(E42:E55) -> 1.0472047e+08 | F56: =SUM(F42:F55) -> 13392795546 | G56: =SUM(G42:G55) -> 6628974942 | H56: =SUM(H42:H55) -> 86791 | I56: =SUM(I42:I55) -> 13419330 | J56: =SUM(J42:J55) -> 1.3694655e+08 | K56: =SUM(K42:K55) -> -1.2352722e+08 | ... N56: =SUM(N42:N55) -> -520818628
A57: Primarily invested in foreign currency securities (shares)
B58: 39 | C58: Cocolife Dollar Fund Builder, Inc. | D58: 71683468 | E58: 416874.26 | F58: =D58-E58 -> 71266594 | G58: 0 | H58: 51 | I58: 0 | J58: 0 | K58: =I58-J58 -> 0 | L58: =I58+May!L58 -> 0 | M58: =J58+May!M58 -> 447875.75 | N58: =L58-M58 -> -447875.75
B59: 40 | C59: PAMI Asia Balanced Fund, Inc. | D59: 337795624 | E59: 25342162 | F59: =D59-E59 -> 3.1245346e+08 | G59: 168249073 | H59: 255 | I59: 0 | J59: 306135 | K59: =I59-J59 -> -306135 | L59: =I59+May!L59 -> 5631.4684 | M59: =J59+May!M59 -> 13403399 | N59: =L59-M59 -> -13397767
B60: 41 | C60: Sun Life Prosperity Dollar Advantage Fund, Inc. | D60: 1540567705 | E60: 8794967 | F60: =D60-E60 -> 1531772738 | G60: 0 | H60: 4148 | I60: 1270589 | J60: 10735417 | K60: =I60-J60 -> -9464828 | L60: =I60+May!L60 -> 12200813 | M60: =J60+May!M60 -> 79860950 | N60: =L60-M60 -> -67660137
B61: 42 | C61: Sun Life Prosperity Dollar Wellspring Fund, Inc. | D61: 262064512 | E61: 697125 | F61: =D61-E61 -> 261367387 | G61: 0 | H61: 732 | I61: 3296559 | J61: 11636098 | K61: =I61-J61 -> -8339539 | L61: =I61+May!L61 -> 8576137.1 | M61: =J61+May!M61 -> 45453928 | N61: =L61-M61 -> -36877791
A62: Sub total - US Currency | D62: =SUM(D58:D61) -> 2212111309 | E62: =SUM(E58:E61) -> 35251128 | F62: =SUM(F58:F61) -> 2176860181 | G62: =SUM(G58:G61) -> 168249073 | H62: =SUM(H58:H61) -> 5186 | I62: =SUM(I58:I61) -> 4567148 | J62: =SUM(J58:J61) -> 22677650 | K62: =SUM(K58:K61) -> -18110502 | ... N62: =SUM(N58:N61) -> -1.1838357e+08
A63: Sub total - balanced funds | D63: =D56+D62 -> 15709627324 | E63: =E56+E62 -> 1.399716e+08 | F63: =F56+F62 -> 15569655727 | G63: =G56+G62 -> 6797224015 | H63: =H56+H62 -> 91977 | I63: =I56+I62 -> 17986478 | J63: =J56+J62 -> 1.596242e+08 | K63: =K56+K62 -> -1.4163772e+08 | ... N63: =N56+N62 -> -6.392022e+08
A64: Bond Funds
A65: Primarily invested in Peso Securities (shares)
B66: 43 | C66: ALFM Peso Bond Fund, Inc. | D66: 38504982510 | E66: 224261960 | F66: =D66-E66 -> 38280720550 | G66: 929406112 | H66: 24332 | I66: 177287307 | J66: 435266736 | K66: =I66-J66 -> -257979429 | L66: =I66+May!L66 -> 1409094983 | M66: =J66+May!M66 -> 3512698993 | N66: =L66-M66 -> -2103604010
B67: 44 | C67: ATRAM Corporate Bond Fund, Inc. | D67: 4.7428397e+08 | E67: -5158686.3 | F67: =D67-E67 -> 4.7944266e+08 | G67: 0 | H67: 1073 | I67: 2482180.3 | J67: 25380528 | K67: =I67-J67 -> -22898347 | L67: =I67+May!L67 -> 55640442 | M67: =J67+May!M67 -> 57458195 | N67: =L67-M67 -> -1817753
B68: 45 | C68: Cocolife Fixed Income Fund, Inc. | D68: 9.5798691e+08 | E68: 18492655 | F68: =D68-E68 -> 9.3949425e+08 | G68: 0 | H68: 1917 | I68: 3124787.5 | J68: 24804469 | K68: =I68-J68 -> -21679682 | L68: =I68+May!L68 -> 28345420 | M68: =J68+May!M68 -> 99357245 | N68: =L68-M68 -> -71011824
B69: 46 | C69: Ekklesia Mutual Fund, Inc. | D69: 198490228 | E69: 173602 | F69: =D69-E69 -> 198316626 | G69: 4870000 | H69: 212 | I69: 289175 | J69: 695123 | K69: =I69-J69 -> -405948 | L69: =I69+May!L69 -> 5411183.8 | M69: =J69+May!M69 -> 5047185.6 | N69: =L69-M69 -> 363998.21
B70: 47 | C70: First Metro Save and Learn Fixed Income Fund, Inc. | D70: 1503587800 | E70: 2727191 | F70: =D70-E70 -> 1500860609 | G70: 0 | H70: 1850 | I70: 13142256 | J70: 14451213 | K70: =I70-J70 -> -1308957 | L70: =I70+May!L70 -> 2.6915849e+08 | M70: =J70+May!M70 -> 63410342 | N70: =L70-M70 -> 2.0574814e+08
B71: 48 | C71: Philam Managed Income Fund, Inc. | D71: 761796807 | E71: 38072448 | F71: =D71-E71 -> 723724359 | G71: 0 | H71: 490 | I71: 1082276 | J71: 5070748 | K71: =I71-J71 -> -3988472 | L71: =I71+May!L71 -> 12220659 | M71: =J71+May!M71 -> 1.1708229e+08 | N71: =L71-M71 -> -1.0486163e+08
B72: 49 | C72: Philam Bond Fund, Inc. | D72: 1700920116 | E72: 24900757 | F72: =D72-E72 -> 1676019359 | G72: 0 | H72: 4975 | I72: 5334812 | J72: 14235452 | K72: =I72-J72 -> -8900640 | L72: =I72+May!L72 -> 24022614 | M72: =J72+May!M72 -> 63690694 | N72: =L72-M72 -> -39668079
B73: 50 | C73: Philequity Peso Bond Fund, Inc. | D73: 3.0798214e+08 | E73: 694687.97 | F73: =D73-E73 -> 3.0728745e+08 | G73: 0 | H73: 4126 | I73: 816347.31 | J73: 1018332.9 | K73: =I73-J73 -> -201985.61 | L73: =I73+May!L73 -> 19708217 | M73: =J73+May!M73 -> 22476720 | N73: =L73-M73 -> -2768503.7
B74: 51 | C74: Soldivo Bond Fund, Inc. | D74: 1.3730355e+09 | E74: -698862.49 | F74: =D74-E74 -> 1373734333 | G74: 0 | H74: 809 | I74: 52805.59 | J74: 104156.91 | K74: =I74-J74 -> -51351.32 | L74: =I74+May!L74 -> 131316782 | M74: =J74+May!M74 -> 4468603.9 | N74: =L74-M74 -> 1.2684818e+08
B75: 52 | C75: Sun Life Prosperity Bond Fund, Inc. | D75: 5541069292 | E75: 9233465 | F75: =D75-E75 -> 5531835827 | G75: 0 | H75: 17278 | I75: 145063588 | J75: 35908642 | K75: =I75-J75 -> 109154946 | L75: =I75+May!L75 -> 1311627654 | M75: =J75+May!M75 -> 353883827 | N75: =L75-M75 -> 957743827
B76: 53 | C76: Sun Life Prosperity GS Fund, Inc. | D76: 138924622 | E76: 399541 | F76: =D76-E76 -> 138525081 | G76: 0 | H76: 2695 | I76: 3904010 | J76: 4111917 | K76: =I76-J76 -> -207907 | L76: =I76+May!L76 -> 7205653.4 | M76: =J76+May!M76 -> 9122302.7 | N76: =L76-M76 -> -1916649.3
A77: Sub total - Peso Currency | D77: =SUM(D66:D76) -> 51463059863 | E77: =SUM(E66:E76) -> 3.1309876e+08 | F77: =SUM(F66:F76) -> 51149961105 | G77: =SUM(G66:G76) -> 934276112 | H77: =SUM(H66:H76) -> 59757 | I77: =SUM(I66:I76) -> 3.5257954e+08 | J77: =SUM(J66:J76) -> 5.6104732e+08 | K77: =SUM(K66:K76) -> -2.0846777e+08 | ... N77: =SUM(N66:N76) -> -1034944306
A78: Primarily invested in foreign currency securities (shares)
B79: 54 | C79: ALFM Dollar Bond Fund, Inc. | D79: 13483206111 | E79: 1.2109612e+08 | F79: =D79-E79 -> 13362109987 | G79: 0 | H79: 8374 | I79: 29722064 | J79: 131122672 | K79: =I79-J79 -> -101400608 | L79: =I79+May!L79 -> 3.3537221e+08 | M79: =J79+May!M79 -> 8.6527111e+08 | N79: =L79-M79 -> -5.298989e+08
B80: 55 | C80: ATRAM Total Return Dollar Bond Fund, Inc. | D80: 2.6195251e+08 | E80: -1186074.7 | F80: =D80-E80 -> 2.6313858e+08 | G80: 0 | H80: 160 | I80: 0 | J80: 12246.73 | K80: =I80-J80 -> -12246.73 | L80: =I80+May!L80 -> 1334682 | M80: =J80+May!M80 -> 5857657.6 | N80: =L80-M80 -> -4522975.6
B81: 56 | C81: First Metro Save and Learn Dollar Bond Fund, Inc. | D81: 447547347 | E81: 3167954 | F81: =D81-E81 -> 444379393 | G81: 0 | H81: 167 | I81: 1770731 | J81: 323284 | K81: =I81-J81 -> 1447447 | L81: =I81+May!L81 -> 15971168 | M81: =J81+May!M81 -> 7566315 | N81: =L81-M81 -> 8404853.5
B82: 57 | C82: PAMI Global Bond Fund, Inc. | D82: 63739041 | E82: 14355185 | F82: =D82-E82 -> 49383856 | G82: 0 | H82: 27 | I82: 0 | J82: 0 | K82: =I82-J82 -> 0 | L82: =I82+May!L82 -> 0 | M82: =J82+May!M82 -> 0 | N82: =L82-M82 -> 0
B83: 58 | C83: Philam Dollar Bond Fund, Inc. | D83: 1991807402 | E83: 23000881 | F83: =D83-E83 -> 1968806521 | G83: 0 | H83: 1865 | I83: 250829 | J83: 12098388 | K83: =I83-J83 -> -11847559 | L83: =I83+May!L83 -> 1129529.9 | M83: =J83+May!M83 -> 79558106 | N83: =L83-M83 -> -78428576
B84: 59 | C84: Philequity Dollar Income Fund, Inc. | D84: 2.3122614e+08 | E84: 1233751.1 | F84: =D84-E84 -> 2.2999239e+08 | G84: 0 | H84: 118 | I84: 149040 | J84: 607823.21 | K84: =I84-J84 -> -458783.21 | L84: =I84+May!L84 -> 1290589 | M84: =J84+May!M84 -> 3979991.5 | N84: =L84-M84 -> -2689402.5
B85: 60 | C85: Sun Life Prosperity Dollar Abundance Fund, Inc. | D85: 529499820 | E85: 3466208 | F85: =D85-E85 -> 526033612 | G85: 0 | H85: 2555 | I85: 2155839 | J85: 2409524 | K85: =I85-J85 -> -253685 | L85: =I85+May!L85 -> 1.0884939e+08 | M85: =J85+May!M85 -> 30081879 | N85: =L85-M85 -> 78767507
A86: Sub total - US Currency | D86: =SUM(D79:D85) -> 17008978366 | E86: =SUM(E79:E85) -> 1.6513403e+08 | F86: =SUM(F79:F85) -> 16843844337 | G86: =SUM(G79:G85) -> 0 | H86: =SUM(H79:H85) -> 13266 | I86: =SUM(I79:I85) -> 34048503 | J86: =SUM(J79:J85) -> 1.4657394e+08 | K86: =SUM(K79:K85) -> -1.1252543e+08 | ... N86: =SUM(N79:N85) -> -5.2836749e+08
B87: 61 | C87: ALFM Euro Bond Fund, Inc. | D87: 938432451 | E87: 7459457 | F87: =D87-E87 -> 930972994 | G87: 0 | H87: 634 | I87: 4261174 | J87: 5306522 | K87: =I87-J87 -> -1045348 | L87: =I87+May!L87 -> 33296062 | M87: =J87+May!M87 -> 29017333 | N87: =L87-M87 -> 4278729.3
A88: Sub total - Euro Currency | D88: =SUM(D87) -> 938432451 | E88: =SUM(E87) -> 7459457 | F88: =SUM(F87) -> 930972994 | G88: =SUM(G87) -> 0 | H88: =SUM(H87) -> 634 | I88: =SUM(I87) -> 4261174 | J88: =SUM(J87) -> 5306522 | K88: =SUM(K87) -> -1045348 | ... N88: =SUM(N87) -> 4278729.3
A89: Sub total - bond funds | D89: =D77+D86+D88 -> 69410470680 | E89: =E77+E86+E88 -> 4.8569224e+08 | F89: =F77+F86+F88 -> 68924778436 | G89: =G77+G86+G88 -> 934276112 | H89: =H77+H86+H88 -> 73657 | I89: =I77+I86+I88 -> 3.9088922e+08 | J89: =J77+J86+J88 -> 7.1292778e+08 | K89: =K77+K86+K88 -> -3.2203856e+08 | ... N89: =N77+N86+N88 -> -1559033071
A90: Money Market Funds
A91: Primarily invested in Peso Securities (shares)
B92: 62 | C92: ALFM Money Market Fund, Inc. | D92: 32673646292 | E92: 515245636 | F92: =D92-E92 -> 32158400656 | G92: 0 | H92: 28038 | I92: 342917 | J92: 1322124768 | K92: =I92-J92 -> -1321781851 | L92: =I92+May!L92 -> 9183462854 | M92: =J92+May!M92 -> 12087306196 | N92: =L92-M92 -> -2903843342
B93: 63 | C93: First Metro Save and Learn Money Market Fund, Inc. | D93: 2259155326 | E93: 16267706 | F93: =D93-E93 -> 2242887620 | G93: 0 | H93: 789 | I93: 51236970 | J93: 141760704 | K93: =I93-J93 -> -90523734 | L93: =I93+May!L93 -> 4.3536368e+08 | M93: =J93+May!M93 -> 1056429283 | N93: =L93-M93 -> -6.2106561e+08
B94: 64 | C94: Sun Life Prosperity Peso Starter Fund, Inc. | D94: 33047350010 | E94: 110368042 | F94: =D94-E94 -> 32936981968 | G94: 0 | H94: 67472 | I94: 1378505927 | J94: 3364912824 | K94: =I94-J94 -> -1986406897 | L94: =I94+May!L94 -> 12518040943 | M94: =J94+May!M94 -> 32374429540 | N94: =L94-M94 -> -19856388597
A95: Primarily invested in Peso Securities (units)
B96: 65 | C96: ALFM Money Market Fund, Inc. | D96: 6678643874 | E96: 214846156 | F96: =D96-E96 -> 6463797718 | G96: 0 | H96: 6502 | I96: 1022888880 | J96: 700585421 | K96: =I96-J96 -> 322303459 | L96: =I96+May!L96 -> 8372258900 | M96: =J96+May!M96 -> 5527739809 | N96: =L96-M96 -> 2844519090
A97: Sub total - Peso Currency | D97: =SUM(D92:D94)+D96 -> 74658795502 | E97: =SUM(E92:E94)+E96 -> 856727540 | F97: =SUM(F92:F94)+F96 -> 73802067962 | G97: =SUM(G92:G94)+G96 -> 0 | H97: =SUM(H92:H94)+H96 -> 102801 | I97: =SUM(I92:I94)+I96 -> 2452974694 | J97: =SUM(J92:J94)+J96 -> 5529383717 | K97: =SUM(K92:K94)+K96 -> -3076409023 | ... N97: =SUM(N92:N94)+N96 -> -20536778455
A98: Primarily invested in foreign currency securities (shares)
B99: 66 | C99: Sun Life Prosperity Dollar Starter Fund, Inc. | D99: 3346907573 | E99: 12582125 | F99: =D99-E99 -> 3334325448 | G99: 0 | H99: 3542 | I99: 462595657 | J99: 763951274 | K99: =I99-J99 -> -301355617 | L99: =I99+May!L99 -> 3602406349 | M99: =J99+May!M99 -> 6905867520 | N99: =L99-M99 -> -3303461171
A100: Sub total - US Currency | D100: =SUM(D99) -> 3346907573 | E100: =SUM(E99) -> 12582125 | F100: =SUM(F99) -> 3334325448 | G100: =SUM(G99) -> 0 | H100: =SUM(H99) -> 3542 | I100: =SUM(I99) -> 462595657 | J100: =SUM(J99) -> 763951274 | K100: =SUM(K99) -> -301355617 | ... N100: =SUM(N99) -> -3303461171
A101: Sub total - money market funds | D101: =D97+D100 -> 78005703075 | E101: =E97+E100 -> 869309665 | F101: =F97+F100 -> 77136393410 | G101: =G97+G100 -> 0 | H101: =H97+H100 -> 106343 | I101: =I97+I100 -> 2915570351 | J101: =J97+J100 -> 6293334991 | K101: =K97+K100 -> -3377764640 | ... N101: =N97+N100 -> -23840239626
A102: Feeder Fund
A103: Primarily invested in Peso securities (units)
B104: 67 | C104: ALFM Global Multi-Asset Income Fund, Inc. | D104: 9159268240 | E104: 93546557 | F104: =D104-E104 -> 9065721683 | G104: 0 | H104: 62388 | I104: 45168502 | J104: 114070308 | K104: =I104-J104 -> -68901806 | L104: =I104+May!L104 -> 5.5282581e+08 | M104: =J104+May!M104 -> 6.8124209e+08 | N104: =L104-M104 -> -1.2841628e+08
B105: 68 | C105: Sun Life Prosperity World Equity Index Feeder Fund, Inc. | D105: 3334245963 | E105: 21183555 | F105: =D105-E105 -> 3313062408 | G105: 0 | H105: 6185 | I105: 62150570 | J105: 75512865 | K105: =I105-J105 -> -13362295 | L105: =I105+May!L105 -> 1.7426858e+08 | M105: =J105+May!M105 -> 4.6877002e+08 | N105: =L105-M105 -> -2.9450144e+08
A106: Sub total - Peso Currency | D106: =D104+D105 -> 12493514203 | E106: =E104+E105 -> 114730112 | F106: =F104+F105 -> 12378784091 | G106: =G104+G105 -> 0 | H106: =H104+H105 -> 68573 | I106: =I104+I105 -> 107319072 | J106: =J104+J105 -> 189583173 | K106: =K104+K105 -> -82264101 | ... N106: =N104+N105 -> -422917720
...

Sheet Q2
A1: PHILIPPINE INVESTMENT FUNDS ASSOCIATION, INC.
A2: MUTUAL FUNDS STATISTICAL REPORT
A3: As of the Second Quarter of 2023
A4: (Amounts in Peso)
A6: Fund Category | C6: Fund Name | D6: NET ASSETS | E6: TOTAL SALES | F6: TOTAL REDEMPTIONS | G6: NET SALES
A7: Stock Funds
A8: Primarily invested in Peso Securities (shares)
B9: 1 | C9: ALFM Growth Fund, Inc. | D9: =June!F9 -> 4506763358 | E9: =Apr!I9+May!I9+June!I9 -> 34805042 | F9: =Apr!J9+May!J9+June!J9 -> 1.1056676e+08 | G9: =E9-F9 -> -75761713
B10: 2 | C10: ATRAM Alpha Opportunity Fund, Inc. | D10: =June!F10 -> 7.6429613e+08 | E10: =Apr!I10+May!I10+June!I10 -> 17746538 | F10: =Apr!J10+May!J10+June!J10 -> 16222801 | G10: =E10-F10 -> 1523737
B11: 3 | C11: ATRAM Phil. Equity Opportunity Fund, Inc. | D11: =June!F11 -> 1313942373 | E11: =Apr!I11+May!I11+June!I11 -> 23893222 | F11: =Apr!J11+May!J11+June!J11 -> 2.2957642e+08 | G11: =E11-F11 -> -2.056832e+08
B12: 4 | C12: Climbs Share Capital Equity Investment Fund Corp. | D12: =June!F12 -> 3.3848959e+08 | E12: =Apr!I12+May!I12+June!I12 -> 1453639.5 | F12: =Apr!J12+May!J12+June!J12 -> 254617.65 | G12: =E12-F12 -> 1199021.9
B13: 5 | C13: First Metro Consumer Fund on MSCI Phils. IMI, Inc. | D13: =June!F13 -> 499132252 | E13: =Apr!I13+May!I13+June!I13 -> 1747114 | F13: =Apr!J13+May!J13+June!J13 -> 8883105 | G13: =E13-F13 -> -7135991
B14: 6 | C14: First Metro Save and Learn Equity Fund, Inc. | D14: =June!F14 -> 4046906330 | E14: =Apr!I14+May!I14+June!I14 -> 54609985 | F14: =Apr!J14+May!J14+June!J14 -> 251556077 | G14: =E14-F14 -> -196946092
B15: 7 | C15: First Metro Save and Learn Phil. Index Fund, Inc. | D15: =June!F15 -> 97880758 | E15: =Apr!I15+May!I15+June!I15 -> 1925780 | F15: =Apr!J15+May!J15+June!J15 -> 5026369 | G15: =E15-F15 -> -3100589
B16: 8 | C16: MBG Equity Investment Fund, Inc. | D16: =June!F16 -> 127088884 | E16: =Apr!I16+May!I16+June!I16 -> 100000 | F16: =Apr!J16+May!J16+June!J16 -> 1697133 | G16: =E16-F16 -> -1597133
B17: 9 | C17: PAMI Equity Index Fund, Inc. | D17: =June!F17 -> 1241810860 | E17: =Apr!I17+May!I17+June!I17 -> 0 | F17: =Apr!J17+May!J17+June!J17 -> 22909236 | G17: =E17-F17 -> -22909236
B18: 10 | C18: Philam Strategic Growth Fund, Inc. | D18: =June!F18 -> 3617711562 | E18: =Apr!I18+May!I18+June!I18 -> 6369721.1 | F18: =Apr!J18+May!J18+June!J18 -> 93456416 | G18: =E18-F18 -> -87086695
B19: 11 | C19: Philequity Dividend Yield Fund, Inc. | D19: =June!F19 -> 2225437656 | E19: =Apr!I19+May!I19+June!I19 -> 6752134.5 | F19: =Apr!J19+May!J19+June!J19 -> 15854040 | G19: =E19-F19 -> -9101905.6
B20: 12 | C20: Philequity Fund, Inc. | D20: =June!F20 -> 9685640050 | E20: =Apr!I20+May!I20+June!I20 -> 36387836 | F20: =Apr!J20+May!J20+June!J20 -> 2.0696651e+08 | G20: =E20-F20 -> -1.7057868e+08
... B27: 19 | C27: United Fund, Inc. | D27: =June!F27 -> 585372283 | E27: =Apr!I27+May!I27+June!I27 -> 874303.29 | F27: =Apr!J27+May!J27+June!J27 -> 2969000.2 | G27: =E27-F27 -> -2094696.9
A28: Primarily invested in Peso Securities (units)
B29: 20 | C29: COL Equity Index Unitized Mutual Fund, Inc. | D29: =June!F29 -> 2.006131e+08 | E29: =Apr!I29+May!I29+June!I29 -> 15245470 | F29: =Apr!J29+May!J29+June!J29 -> 2254304.4 | G29: =E29-F29 -> 12991166
B30: 21 | C30: Philequity Alpha One Fund, Inc. | D30: =June!F30 -> 3.3104444e+08 | E30: =Apr!I30+May!I30+June!I30 -> 5625825.1 | F30: =Apr!J30+May!J30+June!J30 -> 7363683.3 | G30: =E30-F30 -> -1737858.2
B31: 22 | C31: Philippine Stock Index Fund Corp. | D31: =June!F31 -> 523947776 | E31: =Apr!I31+May!I31+June!I31 -> 73197727 | F31: =Apr!J31+May!J31+June!J31 -> 37878103 | G31: =E31-F31 -> 35319623
A32: Exchange Traded Fund
B33: 23 | C33: First Metro Phil. Equity Exchange Traded Fund, Inc. | D33: =June!F33 -> 2145379987 | E33: =Apr!I33+May!I33+June!I33 -> 8096836 | F33: =Apr!J33+May!J33+June!J33 -> 27025402 | G33: =E33-F33 -> -18928566
A34: Sub total - Peso Currency | D34: =SUM(D9:D33) -> 66969667754 | E34: =SUM(E9:E33) -> 7.5314252e+08 | F34: =SUM(F9:F33) -> 1823790372 | G34: =SUM(G9:G33) -> -1070647856
A35: Primarily invested in foreign currency securities (shares)
B36: 24 | C36: ATRAM AsiaPlus Equity Fund, Inc. | D36: =June!F36 -> 35068234 | E36: =Apr!I36+May!I36+June!I36 -> 69966.877 | F36: =Apr!J36+May!J36+June!J36 -> 309395.19 | G36: =E36-F36 -> -239428.31
B37: 25 | C37: Sun Life Prosperity World Voyager Fund, Inc. | D37: =June!F37 -> 1892317318 | E37: =Apr!I37+May!I37+June!I37 -> 10943160 | F37: =Apr!J37+May!J37+June!J37 -> 18806955 | G37: =E37-F37 -> -7863795
A38: Sub total - US Currency | D38: =SUM(D36:D37) -> 1927385552 | E38: =SUM(E36:E37) -> 11013127 | F38: =SUM(F36:F37) -> 19116350 | G38: =SUM(G36:G37) -> -8103223.3
A39: Sub total - stock funds | D39: =D34+D38 -> 68897053306 | E39: =E34+E38 -> 7.6415564e+08 | F39: =F34+F38 -> 1842906722 | G39: =G34+G38 -> -1078751080
A40: Balanced Funds
A41: Primarily invested in Peso Securities (shares)
B42: 26 | C42: ATRAM Dynamic Allocation Fund, Inc. | D42: =June!F42 -> 1.1708954e+08 | E42: =Apr!I42+May!I42+June!I42 -> 630691.32 | F42: =Apr!J42+May!J42+June!J42 -> 1050138.3 | G42: =E42-F42 -> -419446.94
B43: 27 | C43: ATRAM Philippine Balanced Fund, Inc. | D43: =June!F43 -> 5.823628e+08 | E43: =Apr!I43+May!I43+June!I43 -> 2231194.9 | F43: =Apr!J43+May!J43+June!J43 -> 29012512 | G43: =E43-F43 -> -26781317
B44: 28 | C44: First Metro Save and Learn Balanced Fund, Inc. | D44: =June!F44 -> 1019474371 | E44: =Apr!I44+May!I44+June!I44 -> 2886027 | F44: =Apr!J44+May!J44+June!J44 -> 38467509 | G44: =E44-F44 -> -35581482
B45: 29 | C45: First Metro Save and Learn F.O.C.C.U.S. Dynamic Fund, Inc. | D45: =June!F45 -> 286916298 | E45: =Apr!I45+May!I45+June!I45 -> 22169835 | F45: =Apr!J45+May!J45+June!J45 -> 2096688 | G45: =E45-F45 -> 20073147
B46: 30 | C46: NCM Mutual Fund of the Phils., Inc. | D46: =June!F46 -> 3.4505125e+08 | E46: =Apr!I46+May!I46+June!I46 -> 0 | F46: =Apr!J46+May!J46+June!J46 -> 68876 | G46: =E46-F46 -> -68876
B47: 31 | C47: PAMI Horizon Fund, Inc. | D47: =June!F47 -> 530176544 | E47: =Apr!I47+May!I47+June!I47 -> 462123.59 | F47: =Apr!J47+May!J47+June!J47 -> 15241875 | G47: =E47-F47 -> -14779752
B48: 32 | C48: Philam Fund, Inc. | D48: =June!F48 -> 2001638813 | E48: =Apr!I48+May!I48+June!I48 -> 6223436.8 | F48: =Apr!J48+May!J48+June!J48 -> 53641535 | G48: =E48-F48 -> -47418098
B49: 33 | C49: Solidaritas Fund, Inc. | D49: =June!F49 -> 132546991 | E49: =Apr!I49+May!I49+June!I49 -> 34995.34 | F49: =Apr!J49+May!J49+June!J49 -> 4547444.4 | G49: =E49-F49 -> -4512449.1
B50: 34 | C50: Sun Life Prosperity Balanced Fund, Inc. | D50: =June!F50 -> 7081742088 | E50: =Apr!I50+May!I50+June!I50 -> 29348328 | F50: =Apr!J50+May!J50+June!J50 -> 136518717 | G50: =E50-F50 -> -107170389
B51: 35 | C51: Sun Life Prosperity Dynamic Fund, Inc. | D51: =June!F51 -> 1117569062 | E51: =Apr!I51+May!I51+June!I51 -> 0 | F51: =Apr!J51+May!J51+June!J51 -> 39241851 | G51: =E51-F51 -> -39241851
A52: Primarily invested in Peso Securities (units)
B53: 36 | C53: Sun Life Prosperity Achiever Fund 2028, Inc. | D53: =June!F53 -> 76295609 | E53: =Apr!I53+May!I53+June!I53 -> 1190758 | F53: =Apr!J53+May!J53+June!J53 -> 1696478 | G53: =E53-F53 -> -505720
B54: 37 | C54: Sun Life Prosperity Achiever Fund 2038, Inc. | D54: =June!F54 -> 54876057 | E54: =Apr!I54+May!I54+June!I54 -> 326573 | F54: =Apr!J54+May!J54+June!J54 -> 1540755 | G54: =E54-F54 -> -1214182
B55: 38 | C55: Sun Life Prosperity Achiever Fund 2048, Inc. | D55: =June!F55 -> 47056123 | E55: =Apr!I55+May!I55+June!I55 -> 155517 | F55: =Apr!J55+May!J55+June!J55 -> 34600 | G55: =E55-F55 -> 120917
A56: Sub total - Peso Currency | D56: =SUM(D42:D55) -> 13392795546 | E56: =SUM(E42:E55) -> 65659480 | F56: =SUM(F42:F55) -> 3.2315898e+08 | G56: =SUM(G42:G55) -> -2.574995e+08
A57: Primarily invested in foreign currency securities (shares)
B58: 39 | C58: Cocolife Dollar Fund Builder, Inc. | D58: =June!F58 -> 71266594 | E58: =Apr!I58+May!I58+June!I58 -> 0 | F58: =Apr!J58+May!J58+June!J58 -> 0 | G58: =E58-F58 -> 0
B59: 40 | C59: PAMI Asia Balanced Fund, Inc. | D59: =June!F59 -> 3.1245346e+08 | E59: =Apr!I59+May!I59+June!I59 -> 0 | F59: =Apr!J59+May!J59+June!J59 -> 3664158.3 | G59: =E59-F59 -> -3664158.3
B60: 41 | C60: Sun Life Prosperity Dollar Advantage Fund, Inc. | D60: =June!F60 -> 1531772738 | E60: =Apr!I60+May!I60+June!I60 -> 9433850 | F60: =Apr!J60+May!J60+June!J60 -> 35843663 | G60: =E60-F60 -> -26409813
B61: 42 | C61: Sun Life Prosperity Dollar Wellspring Fund, Inc. | D61: =June!F61 -> 261367387 | E61: =Apr!I61+May!I61+June!I61 -> 7930828 | F61: =Apr!J61+May!J61+June!J61 -> 14496724 | G61: =E61-F61 -> -6565896
A62: Sub total - US Currency | D62: =SUM(D58:D61) -> 2176860181 | E62: =SUM(E58:E61) -> 17364678 | F62: =SUM(F58:F61) -> 54004545 | G62: =SUM(G58:G61) -> -36639867
A63: Sub total - balanced funds | D63: =D56+D62 -> 15569655727 | E63: =E56+E62 -> 83024158 | F63: =F56+F62 -> 3.7716352e+08 | G63: =G56+G62 -> -2.9413937e+08
A64: Bond Funds
A65: Primarily invested in Peso Securities (shares)
B66: 43 | C66: ALFM Peso Bond Fund, Inc. | D66: =June!F66 -> 38280720550 | E66: =Apr!I66+May!I66+June!I66 -> 5.7125372e+08 | F66: =Apr!J66+May!J66+June!J66 -> 1355419026 | G66: =E66-F66 -> -7.841653e+08
B67: 44 | C67: ATRAM Corporate Bond Fund, Inc. | D67: =June!F67 -> 4.7944266e+08 | E67: =Apr!I67+May!I67+June!I67 -> 23066136 | F67: =Apr!J67+May!J67+June!J67 -> 35070193 | G67: =E67-F67 -> -12004056
B68: 45 | C68: Cocolife Fixed Income Fund, Inc. | D68: =June!F68 -> 9.3949425e+08 | E68: =Apr!I68+May!I68+June!I68 -> 6871163.5 | F68: =Apr!J68+May!J68+June!J68 -> 56689755 | G68: =E68-F68 -> -49818592
B69: 46 | C69: Ekklesia Mutual Fund, Inc. | D69: =June!F69 -> 198316626 | E69: =Apr!I69+May!I69+June!I69 -> 2313146.1 | F69: =Apr!J69+May!J69+June!J69 -> 874910.54 | G69: =E69-F69 -> 1438235.5
B70: 47 | C70: First Metro Save and Learn Fixed Income Fund, Inc. | D70: =June!F70 -> 1500860609 | E70: =Apr!I70+May!I70+June!I70 -> 199449891 | F70: =Apr!J70+May!J70+June!J70 -> 47155638 | G70: =E70-F70 -> 152294253
B71: 48 | C71: Philam Managed Income Fund, Inc. | D71: =June!F71 -> 723724359 | E71: =Apr!I71+May!I71+June!I71 -> 5781875.6 | F71: =Apr!J71+May!J71+June!J71 -> 12924637 | G71: =E71-F71 -> -7142761.1
B72: 49 | C72: Philam Bond Fund, Inc. | D72: =June!F72 -> 1676019359 | E72: =Apr!I72+May!I72+June!I72 -> 11884098 | F72: =Apr!J72+May!J72+June!J72 -> 25391159 | G72: =E72-F72 -> -13507061
B73: 50 | C73: Philequity Peso Bond Fund, Inc. | D73: =June!F73 -> 3.0728745e+08 | E73: =Apr!I73+May!I73+June!I73 -> 4373279.7 | F73: =Apr!J73+May!J73+June!J73 -> 5882551.6 | G73: =E73-F73 -> -1509271.9
B74: 51 | C74: Soldivo Bond Fund, Inc. | D74: =June!F74 -> 1373734333 | E74: =Apr!I74+May!I74+June!I74 -> 28278447 | F74: =Apr!J74+May!J74+June!J74 -> 1471644.9 | G74: =E74-F74 -> 26806802
