Workbook

Sheet Jan
A1: PHILIPPINE INVESTMENT FUNDS ASSOCIATION, INC.
A2: MUTUAL FUNDS STATISTICAL REPORT
A3: Month of January 2024
A4: (Amounts in Peso)
I5: F O R - T H E - M O N T H | L5: Y E A R - T O - D A T E
A6: Fund Category | C6: Fund Name | D6: ASSETS | E6: LIABILITIES | F6: NET ASSETS | G6: EQUITY INV. | H6: NO. OF A/C | I6: SALES | J6: REDEMPTIONS | K6: NET SALES | L6: TOTAL SALES | M6: TOTAL REDEMPTIONS | N6: TOTAL NET SALES
A7: Stock Funds
A8: Primarily invested in Peso Securities (shares)
B9: 1 | C9: ALFM Growth Fund, Inc. | D9: 15852448 | E9: 493145 | F9: =D9-E9 -> 15359303 | G9: 4170172547 | H9: 6647 | I9: 5246522 | J9: 59052402 | K9: =I9-J9 -> -53805880 | L9: =I9 -> 5246522 | M9: =J9 -> 59052402 | N9: =L9-M9 -> -53805880
B10: =1+B9 -> 2 | C10: ATRAM Alpha Opportunity Fund, Inc. | D10: 7.7679695e+08 | E10: 4549367 | F10: =D10-E10 -> 772247588 | G10: 7.2461709e+08 | H10: 4097 | I10: 2767579.5 | J10: 18155947 | K10: =I10-J10 -> -15388367 | L10: =I10 -> 2767579.5 | M10: =J10 -> 18155947 | N10: =L10-M10 -> -15388367
B11: =1+B10 -> 3 | C11: ATRAM Phil. Equity Opportunity Fund, Inc. | D11: 1.3863369e+09 | E11: 20532353 | F11: =D11-E11 -> 1365804545 | G11: 1.2929364e+09 | H11: 2694 | I11: 18300741 | J11: 10969605 | K11: =I11-J11 -> 7331135.8 | L11: =I11 -> 18300741 | M11: =J11 -> 10969605 | N11: =L11-M11 -> 7331135.8
B12: =1+B11 -> 4 | C12: Climbs Share Capital Equity Investment Fund Corp. | D12: 3.5333195e+08 | E12: 4843605.6 | F12: =D12-E12 -> 3.4848835e+08 | G12: 2.1089339e+08 | H12: 1773 | I12: 527670.76 | J12: 7339206.8 | K12: =I12-J12 -> -6811536 | L12: =I12 -> 527670.76 | M12: =J12 -> 7339206.8 | N12: =L12-M12 -> -6811536
B13: =1+B12 -> 5 | C13: First Metro Consumer Fund, Inc. | D13: 470095998 | E13: 10696373 | F13: =D13-E13 -> 459399625 | G13: 383056795 | H13: 1322 | I13: 1482636 | J13: 4852537 | K13: =I13-J13 -> -3369901 | L13: =I13 -> 1482636 | M13: =J13 -> 4852537 | N13: =L13-M13 -> -3369901
B14: =1+B13 -> 6 | C14: First Metro Save and Learn Equity Fund, Inc. | D14: 4387782585 | E14: 149266345 | F14: =D14-E14 -> 4238516240 | G14: 4039857719 | H14: 15399 | I14: 4098336 | J14: 214609288 | K14: =I14-J14 -> -210510952 | L14: =I14 -> 4098336 | M14: =J14 -> 214609288 | N14: =L14-M14 -> -210510952
B15: =1+B14 -> 7 | C15: First Metro Save and Learn Phil. Index Fund, Inc. | D15: 101862188 | E15: 439965 | F15: =D15-E15 -> 101422223 | G15: 99758532 | H15: 512 | I15: 263908 | J15: 2310554 | K15: =I15-J15 -> -2046646 | L15: =I15 -> 263908 | M15: =J15 -> 2310554 | N15: =L15-M15 -> -2046646
B16: =1+B15 -> 8 | C16: MBG Equity Investment Fund, Inc. | D16: 126198350 | E16: 887102 | F16: =D16-E16 -> 125311248 | G16: 119327669 | H16: 49 | I16: 0 | J16: 1946420 | K16: =I16-J16 -> -1946420 | L16: =I16 -> 0 | M16: =J16 -> 1946420 | N16: =L16-M16 -> -1946420
B17: =1+B16 -> 9 | C17: PAMI Equity Index Fund, Inc. | D17: 1226771013 | E17: 39110074 | F17: =D17-E17 -> 1187660939 | G17: 1206090296 | H17: 11637 | I17: 0 | J17: 23899895 | K17: =I17-J17 -> -23899895 | L17: =I17 -> 0 | M17: =J17 -> 23899895 | N17: =L17-M17 -> -23899895
B18: =1+B17 -> 10 | C18: Philam Strategic Growth Fund, Inc. | D18: 3567912442 | E18: 37673568 | F18: =D18-E18 -> 3530238874 | G18: 3377488242 | H18: 11557 | I18: 5622689 | J18: 26906601 | K18: =I18-J18 -> -21283912 | L18: =I18 -> 5622689 | M18: =J18 -> 26906601 | N18: =L18-M18 -> -21283912
B19: =1+B18 -> 11 | C19: Philequity Dividend Yield Fund, Inc. | D19: 2.2366069e+09 | E19: 3269549.4 | F19: =D19-E19 -> 2233337400 | G19: 2.1104744e+09 | H19: 5014 | I19: 1455818.5 | J19: 5231460.5 | K19: =I19-J19 -> -3775642 | L19: =I19 -> 1455818.5 | M19: =J19 -> 5231460.5 | N19: =L19-M19 -> -3775642
B20: =1+B19 -> 12 | C20: Philequity Fund, Inc. | D20: 9.5676448e+09 | E20: 45360648 | F20: =D20-E20 -> 9522284162 | G20: 8.9689223e+09 | H20: 34177 | I20: 11795600 | J20: 63364290 | K20: =I20-J20 -> -51568690 | L20: =I20 -> 11795600 | M20: =J20 -> 63364290 | N20: =L20-M20 -> -51568690
B21: =1+B20 -> 13 | C21: Philequity MSCI Phil. Index Fund, Inc. | D21: 3.2164396e+08 | E21: 1024021.8 | F21: =D21-E21 -> 3.2061994e+08 | G21: 3.1891805e+08 | H21: 950 | I21: 670425.85 | J21: 504660.13 | K21: =I21-J21 -> 165765.72 | L21: =I21 -> 670425.85 | M21: =J21 -> 504660.13 | N21: =L21-M21 -> 165765.72
... B27: =1+B26 -> 19 | C27: United Fund, Inc. | D27: 6.0499976e+08 | E27: 2313657.1 | F27: =D27-E27 -> 6.0268611e+08 | G27: 5.2266307e+08 | H27: 1246 | I27: 69775.75 | J27: 1178611.1 | K27: =I27-J27 -> -1108835.3 | L27: =I27 -> 69775.75 | M27: =J27 -> 1178611.1 | N27: =L27-M27 -> -1108835.3
A28: Primarily invested in Peso Securities (units)
B29: =1+B27 -> 20 | C29: COL Equity Index Unitized Mutual Fund, Inc. | D29: 2.358269e+08 | E29: 5529640.7 | F29: =D29-E29 -> 230297255 | G29: 2.2761921e+08 | H29: 2971 | I29: 6397829.8 | J29: 11528172 | K29: =I29-J29 -> -5130341.8 | L29: =I29 -> 6397829.8 | M29: =J29 -> 11528172 | N29: =L29-M29 -> -5130341.8
B30: =1+B29 -> 21 | C30: COL Strategic Growth Equity Unitized Mutual Fund, Inc. | D30: 1.3320932e+08 | E30: 643619.95 | F30: =D30-E30 -> 1.325657e+08 | G30: 66740681 | H30: 1928 | I30: 28375881 | J30: 6871653.6 | K30: =I30-J30 -> 21504227 | L30: =I30 -> 28375881 | M30: =J30 -> 6871653.6 | N30: =L30-M30 -> 21504227
B31: =1+B30 -> 22 | C31: Philequity Alpha One Fund, Inc. | D31: 3.1721867e+08 | E31: 5821552.2 | F31: =D31-E31 -> 3.1139712e+08 | G31: 292544795 | H31: 1284 | I31: 808356.87 | J31: 5488814.9 | K31: =I31-J31 -> -4680458 | L31: =I31 -> 808356.87 | M31: =J31 -> 5488814.9 | N31: =L31-M31 -> -4680458
B32: =1+B31 -> 23 | C32: Philippine Stock Index Fund Corp. | D32: 622283336 | E32: 1895742 | F32: =D32-E32 -> 620387594 | G32: 615642340 | H32: 580880 | I32: 12415949 | J32: 26551720 | K32: =I32-J32 -> -14135771 | L32: =I32 -> 12415949 | M32: =J32 -> 26551720 | N32: =L32-M32 -> -14135771
A33: Exchange Traded Fund
B34: =1+B32 -> 24 | C34: First Metro Phil. Equity Exchange Traded Fund, Inc. | D34: 2202380827 | E34: 1752195 | F34: =D34-E34 -> 2200628632 | G34: 2197606516 | H34: 3266 | I34: 6181440 | J34: 8442016 | K34: =I34-J34 -> -2260576 | L34: =I34 -> 6181440 | M34: =J34 -> 8442016 | N34: =L34-M34 -> -2260576
A35: Sub total - Peso Currency | D35: =SUM(D9:D34) -> 62080064976 | E35: =SUM(E9:E34) -> 5.1109707e+08 | F35: =SUM(F9:F34) -> 61568967908 | G35: =SUM(G9:G34) -> 63733764266 | H35: =SUM(H9:H34) -> 863311 | I35: =SUM(I9:I34) -> 2.064859e+08 | J35: =SUM(J9:J34) -> 1166313041 | K35: =SUM(K9:K34) -> -9.5982714e+08 | ... N35: =SUM(N9:N34) -> -9.5982714e+08
A36: Primarily invested in foreign currency securities (shares)
B37: =1+B34 -> 25 | C37: ATRAM AsiaPlus Equity Fund, Inc. | D37: 24541947 | E37: 60919.38 | F37: =D37-E37 -> 24481027 | G37: 22780589 | H37: 52 | I37: 92758.65 | J37: 11209.42 | K37: =I37-J37 -> 81549.23 | L37: =I37 -> 92758.65 | M37: =J37 -> 11209.42 | N37: =L37-M37 -> 81549.23
B38: =1+B37 -> 26 | C38: Sun Life Prosperity World Voyager Fund, Inc. | D38: 1992280284 | E38: 13992408 | F38: =D38-E38 -> 1978287876 | G38: 0 | H38: 2948 | I38: 17601442 | J38: 71992871 | K38: =I38-J38 -> -54391429 | L38: =I38 -> 17601442 | M38: =J38 -> 71992871 | N38: =L38-M38 -> -54391429
A39: Sub total - US Currency | D39: =SUM(D37:D38) -> 2016822231 | E39: =SUM(E37:E38) -> 14053327 | F39: =SUM(F37:F38) -> 2002768903 | G39: =SUM(G37:G38) -> 22780589 | H39: =SUM(H37:H38) -> 3000 | I39: =SUM(I37:I38) -> 17694201 | J39: =SUM(J37:J38) -> 72004080 | K39: =SUM(K37:K38) -> -54309880 | ... N39: =SUM(N37:N38) -> -54309880
A40: Sub total - stock funds | D40: =D35+D39 -> 64096887206 | E40: =E35+E39 -> 525150395 | F40: =F35+F39 -> 63571736811 | G40: =G35+G39 -> 63756544855 | H40: =H35+H39 -> 866311 | I40: =I35+I39 -> 2.241801e+08 | J40: =J35+J39 -> 1238317121 | K40: =K35+K39 -> -1014137018 | ... N40: =N35+N39 -> -1014137018
A41: Balanced Funds
A42: Primarily invested in Peso Securities (shares)
B43: =1+B38 -> 27 | C43: ATRAM Philippine Balanced Fund, Inc. | D43: 5.0901746e+08 | E43: 20310423 | F43: =D43-E43 -> 4.8870704e+08 | G43: 2.9181271e+08 | H43: 2360 | I43: 694300.78 | J43: 5482668.2 | K43: =I43-J43 -> -4788367.4 | L43: =I43 -> 694300.78 | M43: =J43 -> 5482668.2 | N43: =L43-M43 -> -4788367.4
B44: =1+B43 -> 28 | C44: ATRAM Unicapital Diversified Growth Fund, Inc. | D44: 1.2134157e+08 | E44: 95295.18 | F44: =D44-E44 -> 1.2124627e+08 | G44: 49650782 | H44: 705 | I44: 407405.34 | J44: 592892.9 | K44: =I44-J44 -> -185487.56 | L44: =I44 -> 407405.34 | M44: =J44 -> 592892.9 | N44: =L44-M44 -> -185487.56
B45: =1+B44 -> 29 | C45: First Metro Save and Learn Balanced Fund, Inc. | D45: 994292212 | E45: 40094161 | F45: =D45-E45 -> 954198051 | G45: 578347588 | H45: 4415 | I45: 1459383 | J45: 10707460 | K45: =I45-J45 -> -9248077 | L45: =I45 -> 1459383 | M45: =J45 -> 10707460 | N45: =L45-M45 -> -9248077
B46: =1+B45 -> 30 | C46: First Metro Save and Learn F.O.C.C.U.S. Dynamic Fund, Inc. | D46: 287292107 | E46: 4025774 | F46: =D46-E46 -> 283266333 | G46: 222416328 | H46: 231 | I46: 194078 | J46: 1468633 | K46: =I46-J46 -> -1274555 | L46: =I46 -> 194078 | M46: =J46 -> 1468633 | N46: =L46-M46 -> -1274555
B47: =1+B46 -> 31 | C47: NCM Mutual Fund of the Phils., Inc. | D47: 3.244564e+08 | E47: 1313113.3 | F47: =D47-E47 -> 3.2314329e+08 | G47: 1.6112885e+08 | H47: 48 | I47: 0 | J47: 66119 | K47: =I47-J47 -> -66119 | L47: =I47 -> 0 | M47: =J47 -> 66119 | N47: =L47-M47 -> -66119
B48: =1+B47 -> 32 | C48: PAMI Horizon Fund, Inc. | D48: 525568035 | E48: 17606323 | F48: =D48-E48 -> 507961712 | G48: 256917360 | H48: 9884 | I48: 190706 | J48: 1677070 | K48: =I48-J48 -> -1486364 | L48: =I48 -> 190706 | M48: =J48 -> 1677070 | N48: =L48-M48 -> -1486364
B49: =1+B48 -> 33 | C49: Philam Fund, Inc. | D49: 2013809081 | E49: 25217055 | F49: =D49-E49 -> 1988592026 | G49: 982580501 | H49: 7815 | I49: 4023159 | J49: 14677340 | K49: =I49-J49 -> -10654181 | L49: =I49 -> 4023159 | M49: =J49 -> 14677340 | N49: =L49-M49 -> -10654181
B50: =1+B49 -> 34 | C50: Solidaritas Fund, Inc. | D50: 124822493 | E50: 5172745 | F50: =D50-E50 -> 119649748 | G50: 60573243 | H50: 179 | I50: 0 | J50: 1575976 | K50: =I50-J50 -> -1575976 | L50: =I50 -> 0 | M50: =J50 -> 1575976 | N50: =L50-M50 -> -1575976
B51: =1+B50 -> 35 | C51: Sun Life Prosperity Balanced Fund, Inc. | D51: 6780952988 | E51: 46611972 | F51: =D51-E51 -> 6734341016 | G51: 3624141057 | H51: 54148 | I51: 7931244 | J51: 107215215 | K51: =I51-J51 -> -99283971 | L51: =I51 -> 7931244 | M51: =J51 -> 107215215 | N51: =L51-M51 -> -99283971
B52: =1+B51 -> 36 | C52: Sun Life Prosperity Dynamic Fund, Inc. | D52: 638234077 | E52: 23877438 | F52: =D52-E52 -> 614356639 | G52: 338620746 | H52: 4999 | I52: 0 | J52: 24689448 | K52: =I52-J52 -> -24689448 | L52: =I52 -> 0 | M52: =J52 -> 24689448 | N52: =L52-M52 -> -24689448
A53: Primarily invested in Peso Securities (units)
B54: =1+B52 -> 37 | C54: Sun Life Prosperity Achiever Fund 2028, Inc. | D54: 79220053 | E54: 341725 | F54: =D54-E54 -> 78878328 | G54: 20057466 | H54: 1162 | I54: 289923 | J54: 195287 | K54: =I54-J54 -> 94636 | L54: =I54 -> 289923 | M54: =J54 -> 195287 | N54: =L54-M54 -> 94636
B55: =1+B54 -> 38 | C55: Sun Life Prosperity Achiever Fund 2038, Inc. | D55: 56888354 | E55: 297157 | F55: =D55-E55 -> 56591197 | G55: 44280489 | H55: 461 | I55: 157453 | J55: 15088 | K55: =I55-J55 -> 142365 | L55: =I55 -> 157453 | M55: =J55 -> 15088 | N55: =L55-M55 -> 142365
B56: =1+B55 -> 39 | C56: Sun Life Prosperity Achiever Fund 2048, Inc. | D56: 48313680 | E56: 277227 | F56: =D56-E56 -> 48036453 | G56: 40397976 | H56: 212 | I56: 38600 | J56: 17469 | K56: =I56-J56 -> 21131 | L56: =I56 -> 38600 | M56: =J56 -> 17469 | N56: =L56-M56 -> 21131
A57: Sub total - Peso Currency | D57: =SUM(D43:D56) -> 12504208507 | E57: =SUM(E43:E56) -> 1.8524041e+08 | F57: =SUM(F43:F56) -> 12318968099 | G57: =SUM(G43:G56) -> 6670925100 | H57: =SUM(H42:H56) -> 86619 | I57: =SUM(I43:I56) -> 15386252 | J57: =SUM(J43:J56) -> 1.6838067e+08 | K57: =SUM(K43:K56) -> -152994414 | L57: =SUM(L43:L56) -> 15386252 | M57: =SUM(M43:M56) -> 1.6838067e+08 | N57: =SUM(N43:N56) -> -152994414
A58: Primarily invested in foreign currency securities (shares)
B59: =1+B56 -> 40 | C59: Cocolife Dollar Fund Builder, Inc. | D59: 72558452 | E59: 488674.01 | F59: =D59-E59 -> 72069778 | G59: 0 | H59: 50 | I59: 84501.37 | J59: 0 | K59: =I59-J59 -> 84501.37 | L59: =I59 -> 84501.37 | M59: =J59 -> 0 | N59: =L59-M59 -> 84501.37
B60: =1+B59 -> 41 | C60: PAMI Asia Balanced Fund, Inc. | D60: 331808184 | E60: 33593243 | F60: =D60-E60 -> 298214941 | G60: 164158556 | H60: 238 | I60: 0 | J60: 1945062 | K60: =I60-J60 -> -1945062 | L60: =I60 -> 0 | M60: =J60 -> 1945062 | N60: =L60-M60 -> -1945062
B61: =1+B60 -> 42 | C61: Sun Life Prosperity Dollar Advantage Fund, Inc. | D61: 1526765001 | E61: 94277318 | F61: =D61-E61 -> 1432487683 | G61: 0 | H61: 4167 | I61: 339628 | J61: 98169488 | K61: =I61-J61 -> -97829860 | L61: =I61 -> 339628 | M61: =J61 -> 98169488 | N61: =L61-M61 -> -97829860
B62: =1+B61 -> 43 | C62: Sun Life Prosperity Dollar Wellspring Fund, Inc. | D62: 254882372 | E62: 1538635 | F62: =D62-E62 -> 253343737 | G62: 0 | H62: 741 | I62: 229264 | J62: 3132758 | K62: =I62-J62 -> -2903494 | L62: =I62 -> 229264 | M62: =J62 -> 3132758 | N62: =L62-M62 -> -2903494
A63: Sub total - US Currency | D63: =SUM(D59:D62) -> 2186014009 | E63: =SUM(E59:E62) -> 129897870 | F63: =SUM(F59:F62) -> 2056116139 | G63: =SUM(G59:G62) -> 164158556 | H63: =SUM(H59:H62) -> 5196 | I63: =SUM(I59:I62) -> 653393.37 | J63: =SUM(J59:J62) -> 103247308 | K63: =SUM(K59:K62) -> -1.0259391e+08 | ... N63: =SUM(N59:N62) -> -1.0259391e+08
A64: Sub total - balanced funds | D64: =D57+D63 -> 14690222517 | E64: =E57+E63 -> 3.1513828e+08 | F64: =F57+F63 -> 14375084238 | G64: =G57+G63 -> 6835083656 | H64: =H57+H63 -> 91815 | I64: =I57+I63 -> 16039645 | J64: =J57+J63 -> 2.7162797e+08 | K64: =K57+K63 -> -2.5558833e+08 | ... N64: =N57+N63 -> -2.5558833e+08
A65: Bond Funds
A66: Primarily invested in Peso Securities (shares)
B67: =1+B62 -> 44 | C67: ALFM Peso Bond Fund, Inc. | D67: 36640932761 | E67: 209103763 | F67: =D67-E67 -> 36431828998 | G67: 0 | H67: 23540 | I67: 169734849 | J67: 447651902 | K67: =I67-J67 -> -277917053 | L67: =I67 -> 169734849 | M67: =J67 -> 447651902 | N67: =L67-M67 -> -277917053
B68: =1+B67 -> 45 | C68: ATRAM Corporate Bond Fund, Inc. | D68: 4.2965529e+08 | E68: 17381028 | F68: =D68-E68 -> 4.1227426e+08 | G68: 0 | H68: 1031 | I68: 3425405.5 | J68: 24128174 | K68: =I68-J68 -> -20702769 | L68: =I68 -> 3425405.5 | M68: =J68 -> 24128174 | N68: =L68-M68 -> -20702769
B69: =1+B68 -> 46 | C69: Cocolife Fixed Income Fund, Inc. | D69: 9.0669886e+08 | E69: 12128007 | F69: =D69-E69 -> 8.9457086e+08 | G69: 0 | H69: 1860 | I69: 6826049.4 | J69: 20213096 | K69: =I69-J69 -> -13387047 | L69: =I69 -> 6826049.4 | M69: =J69 -> 20213096 | N69: =L69-M69 -> -13387047
B70: =1+B69 -> 47 | C70: Ekklesia Mutual Fund, Inc. | D70: 196224412 | E70: 185650 | F70: =D70-E70 -> 196038762 | G70: 0 | H70: 165 | I70: 0 | J70: 819842 | K70: =I70-J70 -> -819842 | L70: =I70 -> 0 | M70: =J70 -> 819842 | N70: =L70-M70 -> -819842
B71: =1+B70 -> 48 | C71: First Metro Save and Learn Fixed Income Fund, Inc. | D71: 1298675981 | E71: 16403147 | F71: =D71-E71 -> 1282272834 | G71: 0 | H71: 1791 | I71: 26051669 | J71: 17240233 | K71: =I71-J71 -> 8811436 | L71: =I71 -> 26051669 | M71: =J71 -> 17240233 | N71: =L71-M71 -> 8811436
B72: =1+B71 -> 49 | C72: Philam Bond Fund, Inc. | D72: 1613819515 | E72: 32089860 | F72: =D72-E72 -> 1581729655 | G72: 0 | H72: 4834 | I72: 4735286 | J72: 23247798 | K72: =I72-J72 -> -18512512 | L72: =I72 -> 4735286 | M72: =J72 -> 23247798 | N72: =L72-M72 -> -18512512
B73: =1+B72 -> 50 | C73: Philam Managed Income Fund, Inc. | D73: 598810513 | E73: 18365263 | F73: =D73-E73 -> 580445250 | G73: 0 | H73: 455 | I73: 1384160 | J73: 3634642 | K73: =I73-J73 -> -2250482 | L73: =I73 -> 1384160 | M73: =J73 -> 3634642 | N73: =L73-M73 -> -2250482
B74: =1+B73 -> 51 | C74: Philequity Peso Bond Fund, Inc. | D74: 3.2731008e+08 | E74: 1153129.9 | F74: =D74-E74 -> 3.2615695e+08 | G74: 0 | H74: 4045 | I74: 714738.84 | J74: 988374.12 | K74: =I74-J74 -> -273635.28 | L74: =I74 -> 714738.84 | M74: =J74 -> 988374.12 | N74: =L74-M74 -> -273635.28
B75: =1+B74 -> 52 | C75: Soldivo Bond Fund, Inc. | D75: 1.6333781e+09 | E75: 91717840 | F75: =D75-E75 -> 1541660290 | G75: 0 | H75: 791 | I75: 28126650 | J75: 4255790.9 | K75: =I75-J75 -> 23870860 | L75: =I75 -> 28126650 | M75: =J75 -> 4255790.9 | N75: =L75-M75 -> 23870860
B76: =1+B75 -> 53 | C76: Sun Life Prosperity Bond Fund, Inc. | D76: 5892780060 | E76: 14079226 | F76: =D76-E76 -> 5878700834 | G76: 0 | H76: 18215 | I76: 113015677 | J76: 165912834 | K76: =I76-J76 -> -52897157 | L76: =I76 -> 113015677 | M76: =J76 -> 165912834 | N76: =L76-M76 -> -52897157
B77: =1+B76 -> 54 | C77: Sun Life Prosperity GS Fund, Inc. | D77: 125685863 | E77: 1307828 | F77: =D77-E77 -> 124378035 | G77: 0 | H77: 2765 | I77: 706115 | J77: 1442571 | K77: =I77-J77 -> -736456 | L77: =I77 -> 706115 | M77: =J77 -> 1442571 | N77: =L77-M77 -> -736456
A78: Corporate Debt Vehicle (units)
B79: =1+B77 -> 55 | C79: ATRAM Unitized Corporate Debt Vehicle, Inc. | D79: 7.1181613e+08 | E79: 201070 | F79: =D79-E79 -> 7.1161506e+08 | G79: 0 | H79: 13 | I79: 0 | J79: 0 | K79: =I79-J79 -> 0 | L79: =I79 -> 0 | M79: =J79 -> 0 | N79: =L79-M79 -> 0
A80: Sub total - Peso Currency | D80: =SUM(D67:D79) -> 50375787599 | E80: =SUM(E67:E79) -> 4.1411581e+08 | F80: =SUM(F67:F79) -> 49961671787 | G80: =SUM(G67:G79) -> 0 | H80: =SUM(H67:H79) -> 59505 | I80: =SUM(I67:I79) -> 3.547206e+08 | J80: =SUM(J67:J79) -> 7.0953526e+08 | K80: =SUM(K67:K79) -> -354814657 | ... N80: =SUM(N67:N79) -> -354814657
A81: Primarily invested in foreign currency securities (shares)
B82: =1+B79 -> 56 | C82: ALFM Dollar Bond Fund, Inc. | D82: 12983691988 | E82: 177754428 | F82: =D82-E82 -> 12805937560 | G82: 0 | H82: 7878 | I82: 26018270 | J82: 126508071 | K82: =I82-J82 -> -100489801 | L82: =I82 -> 26018270 | M82: =J82 -> 126508071 | N82: =L82-M82 -> -100489801
B83: =1+B82 -> 57 | C83: ATRAM Total Return Dollar Bond Fund, Inc. | D83: 2.6077588e+08 | E83: 995094.51 | F83: =D83-E83 -> 2.5978079e+08 | G83: 0 | H83: 144 | I83: 24748.06 | J83: 118353.08 | K83: =I83-J83 -> -93605.02 | L83: =I83 -> 24748.06 | M83: =J83 -> 118353.08 | N83: =L83-M83 -> -93605.02
B84: =1+B83 -> 58 | C84: First Metro Save and Learn Dollar Bond Fund, Inc. | D84: 443363860 | E84: 1260859 | F84: =D84-E84 -> 442103001 | G84: 0 | H84: 156 | I84: 1227442 | J84: 1402735 | K84: =I84-J84 -> -175293 | L84: =I84 -> 1227442 | M84: =J84 -> 1402735 | N84: =L84-M84 -> -175293
B85: =1+B84 -> 59 | C85: PAMI Global Bond Fund, Inc. | D85: 66626706 | E85: 15826873 | F85: =D85-E85 -> 50799833 | G85: 0 | H85: 27 | I85: 0 | J85: 0 | K85: =I85-J85 -> 0 | L85: =I85 -> 0 | M85: =J85 -> 0 | N85: =L85-M85 -> 0
B86: =1+B85 -> 60 | C86: Philam Dollar Bond Fund, Inc. | D86: 1914798195 | E86: 24777134 | F86: =D86-E86 -> 1890021061 | G86: 0 | H86: 1783 | I86: 111002 | J86: 31895211 | K86: =I86-J86 -> -31784209 | L86: =I86 -> 111002 | M86: =J86 -> 31895211 | N86: =L86-M86 -> -31784209
B87: =1+B86 -> 61 | C87: Philequity Dollar Income Fund, Inc. | D87: 2.358069e+08 | E87: 1402410.9 | F87: =D87-E87 -> 234404490 | G87: 0 | H87: 117 | I87: 157570 | J87: 0 | K87: =I87-J87 -> 157570 | L87: =I87 -> 157570 | M87: =J87 -> 0 | N87: =L87-M87 -> 157570
B88: =1+B87 -> 62 | C88: Sun Life Prosperity Dollar Abundance Fund, Inc. | D88: 626249388 | E88: 30385958 | F88: =D88-E88 -> 595863430 | G88: 0 | H88: 2588 | I88: 11932127 | J88: 3191370 | K88: =I88-J88 -> 8740757 | L88: =I88 -> 11932127 | M88: =J88 -> 3191370 | N88: =L88-M88 -> 8740757
A89: Sub total - US Currency | D89: =SUM(D82:D88) -> 16531312920 | E89: =SUM(E82:E88) -> 2.5240276e+08 | F89: =SUM(F82:F88) -> 16278910163 | G89: =SUM(G82:G88) -> 0 | H89: =SUM(H82:H88) -> 12693 | I89: =SUM(I82:I88) -> 39471159 | J89: =SUM(J82:J88) -> 1.6311574e+08 | K89: =SUM(K82:K88) -> -123644581 | ... N89: =SUM(N82:N88) -> -123644581
B90: =1+B88 -> 63 | C90: ALFM Euro Bond Fund, Inc. | D90: 965426833 | E90: 30032920 | F90: =D90-E90 -> 935393913 | G90: 0 | H90: 608 | I90: 429974 | J90: 2529855 | K90: =I90-J90 -> -2099881 | L90: =I90 -> 429974 | M90: =J90 -> 2529855 | N90: =L90-M90 -> -2099881
A91: Sub total - Euro Currency | D91: =SUM(D90) -> 965426833 | E91: =SUM(E90) -> 30032920 | F91: =SUM(F90) -> 935393913 | G91: =SUM(G90) -> 0 | H91: =SUM(H90) -> 608 | I91: =SUM(I90) -> 429974 | J91: =SUM(J90) -> 2529855 | K91: =SUM(K90) -> -2099881 | ... N91: =SUM(N90) -> -2099881
A92: Sub total - bond funds | D92: =D80+D89+D91 -> 67872527352 | E92: =E80+E89+E91 -> 6.9655149e+08 | F92: =F80+F89+F91 -> 67175975863 | G92: =G80+G89+G91 -> 0 | H92: =H80+H89+H91 -> 72806 | I92: =I80+I89+I91 -> 3.9462173e+08 | J92: =J80+J89+J91 -> 8.7518085e+08 | K92: =K80+K89+K91 -> -480559119 | ... N92: =N80+N89+N91 -> -480559119
A93: Money Market Funds
A94: Primarily invested in Peso Securities (shares)
B95: =1+B90 -> 64 | C95: ALFM Money Market Fund, Inc. | D95: 26355145809 | E95: 21987814 | F95: =D95-E95 -> 26333157995 | G95: 0 | H95: 25414 | I95: 349668 | J95: 674395468 | K95: =I95-J95 -> -674045800 | L95: =I95 -> 349668 | M95: =J95 -> 674395468 | N95: =L95-M95 -> -674045800
B96: =1+B95 -> 65 | C96: First Metro Save and Learn Money Market Fund, Inc. | D96: 3138695311 | E96: 208831153 | F96: =D96-E96 -> 2929864158 | G96: 0 | H96: 974 | I96: 310205086 | J96: 629801548 | K96: =I96-J96 -> -319596462 | L96: =I96 -> 310205086 | M96: =J96 -> 629801548 | N96: =L96-M96 -> -319596462
B97: =1+B96 -> 66 | C97: Sun Life Prosperity Peso Starter Fund, Inc. | D97: 19763580934 | E97: 482457319 | F97: =D97-E97 -> 19281123615 | G97: 0 | H97: 70150 | I97: 399493061 | J97: 1927759182 | K97: =I97-J97 -> -1528266121 | L97: =I97 -> 399493061 | M97: =J97 -> 1927759182 | N97: =L97-M97 -> -1528266121
A98: Primarily invested in Peso Securities (units)
B99: =1+B97 -> 67 | C99: ALFM Money Market Fund, Inc. | D99: 8428259211 | E99: 7287929 | F99: =D99-E99 -> 8420971282 | G99: 0 | H99: 9218 | I99: 1011006495 | J99: 803000391 | K99: =I99-J99 -> 208006104 | L99: =I99 -> 1011006495 | M99: =J99 -> 803000391 | N99: =L99-M99 -> 208006104
A100: Sub total - Peso Currency | D100: =SUM(D95:D97)+D99 -> 57685681265 | E100: =SUM(E95:E97)+E99 -> 720564215 | F100: =SUM(F95:F97)+F99 -> 56965117050 | G100: =SUM(G95:G97)+G99 -> 0 | H100: =SUM(H95:H97)+H99 -> 105756 | I100: =SUM(I95:I97)+I99 -> 1721054310 | J100: =SUM(J95:J97)+J99 -> 4034956589 | K100: =SUM(K95:K97)+K99 -> -2313902279 | ... N100: =SUM(N95:N97)+N99 -> -2313902279
A101: Primarily invested in foreign currency securities (shares)
B102: =1+B99 -> 68 | C102: Sun Life Prosperity Dollar Starter Fund, Inc. | D102: 2334625756 | E102: 22854473 | F102: =D102-E102 -> 2311771283 | G102: 0 | H102: 3635 | I102: 34289270 | J102: 122269167 | K102: =I102-J102 -> -87979897 | L102: =I102 -> 34289270 | M102: =J102 -> 122269167 | N102: =L102-M102 -> -87979897
A103: Sub total - US Currency | D103: =SUM(D102) -> 2334625756 | E103: =SUM(E102) -> 22854473 | F103: =SUM(F102) -> 2311771283 | G103: =SUM(G102) -> 0 | H103: =SUM(H102) -> 3635 | I103: =SUM(I102) -> 34289270 | J103: =SUM(J102) -> 122269167 | K103: =SUM(K102) -> -87979897 | ... N103: =SUM(N102) -> -87979897
A104: Sub total - money market funds | D104: =D100+D103 -> 60020307021 | E104: =E100+E103 -> 743418688 | F104: =F100+F103 -> 59276888333 | G104: =G100+G103 -> 0 | H104: =H100+H103 -> 109391 | I104: =I100+I103 -> 1755343580 | J104: =J100+J103 -> 4157225756 | K104: =K100+K103 -> -2401882176 | ... N104: =N100+N103 -> -2401882176
A105: Feeder Fund
...

Sheet Jan UPDATED
A1: PHILIPPINE INVESTMENT FUNDS ASSOCIATION, INC.
A2: MUTUAL FUNDS STATISTICAL REPORT
A3: Month of January 2024
A4: (Amounts in Peso)
I5: F O R - T H E - M O N T H | L5: Y E A R - T O - D A T E
A6: Fund Category | C6: Fund Name | D6: ASSETS | E6: LIABILITIES | F6: NET ASSETS | G6: EQUITY INV. | H6: NO. OF A/C | I6: SALES | J6: REDEMPTIONS | K6: NET SALES | L6: TOTAL SALES | M6: TOTAL REDEMPTIONS | N6: TOTAL NET SALES
A7: Stock Funds
A8: Primarily invested in Peso Securities (shares)
B9: 1 | C9: ALFM Growth Fund, Inc. | D9: 4.3886259e+09 | E9: 25251041 | F9: =D9-E9 -> 4363374893 | G9: 4170172547 | H9: 6647 | I9: 5246522 | J9: 59052402 | K9: =I9-J9 -> -53805880 | L9: =I9 -> 5246522 | M9: =J9 -> 59052402 | N9: =L9-M9 -> -53805880
B10: =1+B9 -> 2 | C10: ATRAM Alpha Opportunity Fund, Inc. | D10: 7.7679695e+08 | E10: 4549367 | F10: =D10-E10 -> 772247588 | G10: 7.2461709e+08 | H10: 4097 | I10: 2767579.5 | J10: 18155947 | K10: =I10-J10 -> -15388367 | L10: =I10 -> 2767579.5 | M10: =J10 -> 18155947 | N10: =L10-M10 -> -15388367
B11: =1+B10 -> 3 | C11: ATRAM Phil. Equity Opportunity Fund, Inc. | D11: 1.3863369e+09 | E11: 20532353 | F11: =D11-E11 -> 1365804545 | G11: 1.2929364e+09 | H11: 2694 | I11: 18300741 | J11: 10969605 | K11: =I11-J11 -> 7331135.8 | L11: =I11 -> 18300741 | M11: =J11 -> 10969605 | N11: =L11-M11 -> 7331135.8
B12: =1+B11 -> 4 | C12: Climbs Share Capital Equity Investment Fund Corp. | D12: 3.5333195e+08 | E12: 4843605.6 | F12: =D12-E12 -> 3.4848835e+08 | G12: 2.1089339e+08 | H12: 1773 | I12: 527670.76 | J12: 7339206.8 | K12: =I12-J12 -> -6811536 | L12: =I12 -> 527670.76 | M12: =J12 -> 7339206.8 | N12: =L12-M12 -> -6811536
B13: =1+B12 -> 5 | C13: First Metro Consumer Fund, Inc. | D13: 470095998 | E13: 10696373 | F13: =D13-E13 -> 459399625 | G13: 383056795 | H13: 1322 | I13: 1482636 | J13: 4852537 | K13: =I13-J13 -> -3369901 | L13: =I13 -> 1482636 | M13: =J13 -> 4852537 | N13: =L13-M13 -> -3369901
B14: =1+B13 -> 6 | C14: First Metro Save and Learn Equity Fund, Inc. | D14: 4387782585 | E14: 149266345 | F14: =D14-E14 -> 4238516240 | G14: 4039857719 | H14: 15399 | I14: 4098336 | J14: 214609288 | K14: =I14-J14 -> -210510952 | L14: =I14 -> 4098336 | M14: =J14 -> 214609288 | N14: =L14-M14 -> -210510952
B15: =1+B14 -> 7 | C15: First Metro Save and Learn Phil. Index Fund, Inc. | D15: 101862188 | E15: 439965 | F15: =D15-E15 -> 101422223 | G15: 99758532 | H15: 512 | I15: 263908 | J15: 2310554 | K15: =I15-J15 -> -2046646 | L15: =I15 -> 263908 | M15: =J15 -> 2310554 | N15: =L15-M15 -> -2046646
B16: =1+B15 -> 8 | C16: MBG Equity Investment Fund, Inc. | D16: 126198350 | E16: 887102 | F16: =D16-E16 -> 125311248 | G16: 119327669 | H16: 49 | I16: 0 | J16: 1946420 | K16: =I16-J16 -> -1946420 | L16: =I16 -> 0 | M16: =J16 -> 1946420 | N16: =L16-M16 -> -1946420
B17: =1+B16 -> 9 | C17: PAMI Equity Index Fund, Inc. | D17: 1226771013 | E17: 39110074 | F17: =D17-E17 -> 1187660939 | G17: 1206090296 | H17: 11637 | I17: 0 | J17: 23899895 | K17: =I17-J17 -> -23899895 | L17: =I17 -> 0 | M17: =J17 -> 23899895 | N17: =L17-M17 -> -23899895
B18: =1+B17 -> 10 | C18: Philam Strategic Growth Fund, Inc. | D18: 3567912442 | E18: 37673568 | F18: =D18-E18 -> 3530238874 | G18: 3377488242 | H18: 11557 | I18: 5622689 | J18: 26906601 | K18: =I18-J18 -> -21283912 | L18: =I18 -> 5622689 | M18: =J18 -> 26906601 | N18: =L18-M18 -> -21283912
B19: =1+B18 -> 11 | C19: Philequity Dividend Yield Fund, Inc. | D19: 2.2366069e+09 | E19: 3269549.4 | F19: =D19-E19 -> 2233337400 | G19: 2.1104744e+09 | H19: 5014 | I19: 1455818.5 | J19: 5231460.5 | K19: =I19-J19 -> -3775642 | L19: =I19 -> 1455818.5 | M19: =J19 -> 5231460.5 | N19: =L19-M19 -> -3775642
B20: =1+B19 -> 12 | C20: Philequity Fund, Inc. | D20: 9.5676448e+09 | E20: 45360648 | F20: =D20-E20 -> 9522284162 | G20: 8.9689223e+09 | H20: 34177 | I20: 11795600 | J20: 63364290 | K20: =I20-J20 -> -51568690 | L20: =I20 -> 11795600 | M20: =J20 -> 63364290 | N20: =L20-M20 -> -51568690
B21: =1+B20 -> 13 | C21: Philequity MSCI Phil. Index Fund, Inc. | D21: 3.2164396e+08 | E21: 1024021.8 | F21: =D21-E21 -> 3.2061994e+08 | G21: 3.1891805e+08 | H21: 950 | I21: 670425.85 | J21: 504660.13 | K21: =I21-J21 -> 165765.72 | L21: =I21 -> 670425.85 | M21: =J21 -> 504660.13 | N21: =L21-M21 -> 165765.72
... B27: =1+B26 -> 19 | C27: United Fund, Inc. | D27: 6.0499976e+08 | E27: 2313657.1 | F27: =D27-E27 -> 6.0268611e+08 | G27: 5.2266307e+08 | H27: 1246 | I27: 69775.75 | J27: 1178611.1 | K27: =I27-J27 -> -1108835.3 | L27: =I27 -> 69775.75 | M27: =J27 -> 1178611.1 | N27: =L27-M27 -> -1108835.3
A28: Primarily invested in Peso Securities (units)
B29: =1+B27 -> 20 | C29: COL Equity Index Unitized Mutual Fund, Inc. | D29: 2.358269e+08 | E29: 5529640.7 | F29: =D29-E29 -> 230297255 | G29: 2.2761921e+08 | H29: 2971 | I29: 6397829.8 | J29: 11528172 | K29: =I29-J29 -> -5130341.8 | L29: =I29 -> 6397829.8 | M29: =J29 -> 11528172 | N29: =L29-M29 -> -5130341.8
B30: =1+B29 -> 21 | C30: COL Strategic Growth Equity Unitized Mutual Fund, Inc. | D30: 1.3320932e+08 | E30: 643619.95 | F30: =D30-E30 -> 1.325657e+08 | G30: 66740681 | H30: 1928 | I30: 28375881 | J30: 6871653.6 | K30: =I30-J30 -> 21504227 | L30: =I30 -> 28375881 | M30: =J30 -> 6871653.6 | N30: =L30-M30 -> 21504227
B31: =1+B30 -> 22 | C31: Philequity Alpha One Fund, Inc. | D31: 3.1721867e+08 | E31: 5821552.2 | F31: =D31-E31 -> 3.1139712e+08 | G31: 292544795 | H31: 1284 | I31: 808356.87 | J31: 5488814.9 | K31: =I31-J31 -> -4680458 | L31: =I31 -> 808356.87 | M31: =J31 -> 5488814.9 | N31: =L31-M31 -> -4680458
B32: =1+B31 -> 23 | C32: Philippine Stock Index Fund Corp. | D32: 622283336 | E32: 1895742 | F32: =D32-E32 -> 620387594 | G32: 615642340 | H32: 580880 | I32: 12415949 | J32: 26551720 | K32: =I32-J32 -> -14135771 | L32: =I32 -> 12415949 | M32: =J32 -> 26551720 | N32: =L32-M32 -> -14135771
A33: Exchange Traded Fund
B34: =1+B32 -> 24 | C34: First Metro Phil. Equity Exchange Traded Fund, Inc. | D34: 2202380827 | E34: 1752195 | F34: =D34-E34 -> 2200628632 | G34: 2197606516 | H34: 3266 | I34: 6181440 | J34: 8442016 | K34: =I34-J34 -> -2260576 | L34: =I34 -> 6181440 | M34: =J34 -> 8442016 | N34: =L34-M34 -> -2260576
A35: Sub total - Peso Currency | D35: =SUM(D9:D34) -> 66452838461 | E35: =SUM(E9:E34) -> 535854964 | F35: =SUM(F9:F34) -> 65916983497 | G35: =SUM(G9:G34) -> 63733764266 | H35: =SUM(H9:H34) -> 863311 | I35: =SUM(I9:I34) -> 2.064859e+08 | J35: =SUM(J9:J34) -> 1166313041 | K35: =SUM(K9:K34) -> -9.5982714e+08 | ... N35: =SUM(N9:N34) -> -9.5982714e+08
A36: Primarily invested in foreign currency securities (shares)
B37: =1+B34 -> 25 | C37: ATRAM AsiaPlus Equity Fund, Inc. | D37: 24541947 | E37: 60919.38 | F37: =D37-E37 -> 24481027 | G37: 22780589 | H37: 52 | I37: 92758.65 | J37: 11209.42 | K37: =I37-J37 -> 81549.23 | L37: =I37 -> 92758.65 | M37: =J37 -> 11209.42 | N37: =L37-M37 -> 81549.23
B38: =1+B37 -> 26 | C38: Sun Life Prosperity World Voyager Fund, Inc. | D38: 1992280284 | E38: 13992408 | F38: =D38-E38 -> 1978287876 | G38: 0 | H38: 2948 | I38: 17601442 | J38: 71992871 | K38: =I38-J38 -> -54391429 | L38: =I38 -> 17601442 | M38: =J38 -> 71992871 | N38: =L38-M38 -> -54391429
A39: Sub total - US Currency | D39: =SUM(D37:D38) -> 2016822231 | E39: =SUM(E37:E38) -> 14053327 | F39: =SUM(F37:F38) -> 2002768903 | G39: =SUM(G37:G38) -> 22780589 | H39: =SUM(H37:H38) -> 3000 | I39: =SUM(I37:I38) -> 17694201 | J39: =SUM(J37:J38) -> 72004080 | K39: =SUM(K37:K38) -> -54309880 | ... N39: =SUM(N37:N38) -> -54309880
A40: Sub total - stock funds | D40: =D35+D39 -> 68469660692 | E40: =E35+E39 -> 5.4990829e+08 | F40: =F35+F39 -> 67919752401 | G40: =G35+G39 -> 63756544855 | H40: =H35+H39 -> 866311 | I40: =I35+I39 -> 2.241801e+08 | J40: =J35+J39 -> 1238317121 | K40: =K35+K39 -> -1014137018 | ... N40: =N35+N39 -> -1014137018
A41: Balanced Funds
A42: Primarily invested in Peso Securities (shares)
B43: =1+B38 -> 27 | C43: ATRAM Philippine Balanced Fund, Inc. | D43: 5.0901746e+08 | E43: 20310423 | F43: =D43-E43 -> 4.8870704e+08 | G43: 2.9181271e+08 | H43: 2360 | I43: 694300.78 | J43: 5482668.2 | K43: =I43-J43 -> -4788367.4 | L43: =I43 -> 694300.78 | M43: =J43 -> 5482668.2 | N43: =L43-M43 -> -4788367.4
B44: =1+B43 -> 28 | C44: ATRAM Unicapital Diversified Growth Fund, Inc. | D44: 1.2134157e+08 | E44: 95295.18 | F44: =D44-E44 -> 1.2124627e+08 | G44: 49650782 | H44: 705 | I44: 407405.34 | J44: 592892.9 | K44: =I44-J44 -> -185487.56 | L44: =I44 -> 407405.34 | M44: =J44 -> 592892.9 | N44: =L44-M44 -> -185487.56
B45: =1+B44 -> 29 | C45: First Metro Save and Learn Balanced Fund, Inc. | D45: 994292212 | E45: 40094161 | F45: =D45-E45 -> 954198051 | G45: 578347588 | H45: 4415 | I45: 1459383 | J45: 10707460 | K45: =I45-J45 -> -9248077 | L45: =I45 -> 1459383 | M45: =J45 -> 10707460 | N45: =L45-M45 -> -9248077
B46: =1+B45 -> 30 | C46: First Metro Save and Learn F.O.C.C.U.S. Dynamic Fund, Inc. | D46: 287292107 | E46: 4025774 | F46: =D46-E46 -> 283266333 | G46: 222416328 | H46: 231 | I46: 194078 | J46: 1468633 | K46: =I46-J46 -> -1274555 | L46: =I46 -> 194078 | M46: =J46 -> 1468633 | N46: =L46-M46 -> -1274555
B47: =1+B46 -> 31 | C47: NCM Mutual Fund of the Phils., Inc. | D47: 3.244564e+08 | E47: 1313113.3 | F47: =D47-E47 -> 3.2314329e+08 | G47: 1.6112885e+08 | H47: 48 | I47: 0 | J47: 66119 | K47: =I47-J47 -> -66119 | L47: =I47 -> 0 | M47: =J47 -> 66119 | N47: =L47-M47 -> -66119
B48: =1+B47 -> 32 | C48: PAMI Horizon Fund, Inc. | D48: 525568035 | E48: 17606323 | F48: =D48-E48 -> 507961712 | G48: 256917360 | H48: 9884 | I48: 190706 | J48: 1677070 | K48: =I48-J48 -> -1486364 | L48: =I48 -> 190706 | M48: =J48 -> 1677070 | N48: =L48-M48 -> -1486364
B49: =1+B48 -> 33 | C49: Philam Fund, Inc. | D49: 2013809081 | E49: 25217055 | F49: =D49-E49 -> 1988592026 | G49: 982580501 | H49: 7815 | I49: 4023159 | J49: 14677340 | K49: =I49-J49 -> -10654181 | L49: =I49 -> 4023159 | M49: =J49 -> 14677340 | N49: =L49-M49 -> -10654181
B50: =1+B49 -> 34 | C50: Solidaritas Fund, Inc. | D50: 124822493 | E50: 5172745 | F50: =D50-E50 -> 119649748 | G50: 60573243 | H50: 179 | I50: 0 | J50: 1575976 | K50: =I50-J50 -> -1575976 | L50: =I50 -> 0 | M50: =J50 -> 1575976 | N50: =L50-M50 -> -1575976
B51: =1+B50 -> 35 | C51: Sun Life Prosperity Balanced Fund, Inc. | D51: 6780952988 | E51: 46611972 | F51: =D51-E51 -> 6734341016 | G51: 3624141057 | H51: 54148 | I51: 7931244 | J51: 107215215 | K51: =I51-J51 -> -99283971 | L51: =I51 -> 7931244 | M51: =J51 -> 107215215 | N51: =L51-M51 -> -99283971
B52: =1+B51 -> 36 | C52: Sun Life Prosperity Dynamic Fund, Inc. | D52: 638234077 | E52: 23877438 | F52: =D52-E52 -> 614356639 | G52: 338620746 | H52: 4999 | I52: 0 | J52: 24689448 | K52: =I52-J52 -> -24689448 | L52: =I52 -> 0 | M52: =J52 -> 24689448 | N52: =L52-M52 -> -24689448
A53: Primarily invested in Peso Securities (units)
B54: =1+B52 -> 37 | C54: Sun Life Prosperity Achiever Fund 2028, Inc. | D54: 79220053 | E54: 341725 | F54: =D54-E54 -> 78878328 | G54: 20057466 | H54: 1162 | I54: 289923 | J54: 195287 | K54: =I54-J54 -> 94636 | L54: =I54 -> 289923 | M54: =J54 -> 195287 | N54: =L54-M54 -> 94636
B55: =1+B54 -> 38 | C55: Sun Life Prosperity Achiever Fund 2038, Inc. | D55: 56888354 | E55: 297157 | F55: =D55-E55 -> 56591197 | G55: 44280489 | H55: 461 | I55: 157453 | J55: 15088 | K55: =I55-J55 -> 142365 | L55: =I55 -> 157453 | M55: =J55 -> 15088 | N55: =L55-M55 -> 142365
B56: =1+B55 -> 39 | C56: Sun Life Prosperity Achiever Fund 2048, Inc. | D56: 48313680 | E56: 277227 | F56: =D56-E56 -> 48036453 | G56: 40397976 | H56: 212 | I56: 38600 | J56: 17469 | K56: =I56-J56 -> 21131 | L56: =I56 -> 38600 | M56: =J56 -> 17469 | N56: =L56-M56 -> 21131
A57: Sub total - Peso Currency | D57: =SUM(D43:D56) -> 12504208507 | E57: =SUM(E43:E56) -> 1.8524041e+08 | F57: =SUM(F43:F56) -> 12318968099 | G57: =SUM(G43:G56) -> 6670925100 | H57: =SUM(H42:H56) -> 86619 | I57: =SUM(I43:I56) -> 15386252 | J57: =SUM(J43:J56) -> 1.6838067e+08 | K57: =SUM(K43:K56) -> -152994414 | L57: =SUM(L43:L56) -> 15386252 | M57: =SUM(M43:M56) -> 1.6838067e+08 | N57: =SUM(N43:N56) -> -152994414
A58: Primarily invested in foreign currency securities (shares)
B59: =1+B56 -> 40 | C59: Cocolife Dollar Fund Builder, Inc. | D59: 72558452 | E59: 488674.01 | F59: =D59-E59 -> 72069778 | G59: 0 | H59: 50 | I59: 84501.37 | J59: 0 | K59: =I59-J59 -> 84501.37 | L59: =I59 -> 84501.37 | M59: =J59 -> 0 | N59: =L59-M59 -> 84501.37
B60: =1+B59 -> 41 | C60: PAMI Asia Balanced Fund, Inc. | D60: 331808184 | E60: 33593243 | F60: =D60-E60 -> 298214941 | G60: 1.60548e+08 | H60: 238 | I60: 0 | J60: 1945062 | K60: =I60-J60 -> -1945062 | L60: =I60 -> 0 | M60: =J60 -> 1945062 | N60: =L60-M60 -> -1945062
B61: =1+B60 -> 42 | C61: Sun Life Prosperity Dollar Advantage Fund, Inc. | D61: 1526765001 | E61: 94277318 | F61: =D61-E61 -> 1432487683 | G61: 0 | H61: 4167 | I61: 339628 | J61: 98169488 | K61: =I61-J61 -> -97829860 | L61: =I61 -> 339628 | M61: =J61 -> 98169488 | N61: =L61-M61 -> -97829860
B62: =1+B61 -> 43 | C62: Sun Life Prosperity Dollar Wellspring Fund, Inc. | D62: 254882372 | E62: 1538635 | F62: =D62-E62 -> 253343737 | G62: 0 | H62: 741 | I62: 229264 | J62: 3132758 | K62: =I62-J62 -> -2903494 | L62: =I62 -> 229264 | M62: =J62 -> 3132758 | N62: =L62-M62 -> -2903494
A63: Sub total - US Currency | D63: =SUM(D59:D62) -> 2186014009 | E63: =SUM(E59:E62) -> 129897870 | F63: =SUM(F59:F62) -> 2056116139 | G63: =SUM(G59:G62) -> 1.60548e+08 | H63: =SUM(H59:H62) -> 5196 | I63: =SUM(I59:I62) -> 653393.37 | J63: =SUM(J59:J62) -> 103247308 | K63: =SUM(K59:K62) -> -1.0259391e+08 | ... N63: =SUM(N59:N62) -> -1.0259391e+08
A64: Sub total - balanced funds | D64: =D57+D63 -> 14690222517 | E64: =E57+E63 -> 3.1513828e+08 | F64: =F57+F63 -> 14375084238 | G64: =G57+G63 -> 6831473096 | H64: =H57+H63 -> 91815 | I64: =I57+I63 -> 16039645 | J64: =J57+J63 -> 2.7162797e+08 | K64: =K57+K63 -> -2.5558833e+08 | ... N64: =N57+N63 -> -2.5558833e+08
A65: Bond Funds
A66: Primarily invested in Peso Securities (shares)
B67: =1+B62 -> 44 | C67: ALFM Peso Bond Fund, Inc. | D67: 36640932761 | E67: 209103763 | F67: =D67-E67 -> 36431828998 | G67: 0 | H67: 23540 | I67: 169734849 | J67: 447651902 | K67: =I67-J67 -> -277917053 | L67: =I67 -> 169734849 | M67: =J67 -> 447651902 | N67: =L67-M67 -> -277917053
B68: =1+B67 -> 45 | C68: ATRAM Corporate Bond Fund, Inc. | D68: 4.2965529e+08 | E68: 17381028 | F68: =D68-E68 -> 4.1227426e+08 | G68: 0 | H68: 1031 | I68: 3425405.5 | J68: 24128174 | K68: =I68-J68 -> -20702769 | L68: =I68 -> 3425405.5 | M68: =J68 -> 24128174 | N68: =L68-M68 -> -20702769
B69: =1+B68 -> 46 | C69: Cocolife Fixed Income Fund, Inc. | D69: 9.0669886e+08 | E69: 12128007 | F69: =D69-E69 -> 8.9457086e+08 | G69: 0 | H69: 1860 | I69: 6826049.4 | J69: 20213096 | K69: =I69-J69 -> -13387047 | L69: =I69 -> 6826049.4 | M69: =J69 -> 20213096 | N69: =L69-M69 -> -13387047
B70: =1+B69 -> 47 | C70: Ekklesia Mutual Fund, Inc. | D70: 196224412 | E70: 185650 | F70: =D70-E70 -> 196038762 | G70: 0 | H70: 165 | I70: 0 | J70: 819842 | K70: =I70-J70 -> -819842 | L70: =I70 -> 0 | M70: =J70 -> 819842 | N70: =L70-M70 -> -819842
B71: =1+B70 -> 48 | C71: First Metro Save and Learn Fixed Income Fund, Inc. | D71: 1298675981 | E71: 16403147 | F71: =D71-E71 -> 1282272834 | G71: 0 | H71: 1791 | I71: 26051669 | J71: 17240233 | K71: =I71-J71 -> 8811436 | L71: =I71 -> 26051669 | M71: =J71 -> 17240233 | N71: =L71-M71 -> 8811436
B72: =1+B71 -> 49 | C72: Philam Bond Fund, Inc. | D72: 1613819515 | E72: 32089860 | F72: =D72-E72 -> 1581729655 | G72: 0 | H72: 4834 | I72: 4735286 | J72: 23247798 | K72: =I72-J72 -> -18512512 | L72: =I72 -> 4735286 | M72: =J72 -> 23247798 | N72: =L72-M72 -> -18512512
B73: =1+B72 -> 50 | C73: Philam Managed Income Fund, Inc. | D73: 598810513 | E73: 18365263 | F73: =D73-E73 -> 580445250 | G73: 0 | H73: 455 | I73: 1384160 | J73: 3634642 | K73: =I73-J73 -> -2250482 | L73: =I73 -> 1384160 | M73: =J73 -> 3634642 | N73: =L73-M73 -> -2250482
B74: =1+B73 -> 51 | C74: Philequity Peso Bond Fund, Inc. | D74: 3.2731008e+08 | E74: 1153129.9 | F74: =D74-E74 -> 3.2615695e+08 | G74: 0 | H74: 4045 | I74: 714738.84 | J74: 988374.12 | K74: =I74-J74 -> -273635.28 | L74: =I74 -> 714738.84 | M74: =J74 -> 988374.12 | N74: =L74-M74 -> -273635.28
B75: =1+B74 -> 52 | C75: Soldivo Bond Fund, Inc. | D75: 1.6333781e+09 | E75: 91717840 | F75: =D75-E75 -> 1541660290 | G75: 0 | H75: 791 | I75: 28126650 | J75: 4255790.9 | K75: =I75-J75 -> 23870860 | L75: =I75 -> 28126650 | M75: =J75 -> 4255790.9 | N75: =L75-M75 -> 23870860
B76: =1+B75 -> 53 | C76: Sun Life Prosperity Bond Fund, Inc. | D76: 5892780060 | E76: 14079226 | F76: =D76-E76 -> 5878700834 | G76: 0 | H76: 18215 | I76: 113015677 | J76: 165912834 | K76: =I76-J76 -> -52897157 | L76: =I76 -> 113015677 | M76: =J76 -> 165912834 | N76: =L76-M76 -> -52897157
B77: =1+B76 -> 54 | C77: Sun Life Prosperity GS Fund, Inc. | D77: 125685863 | E77: 1307828 | F77: =D77-E77 -> 124378035 | G77: 0 | H77: 2765 | I77: 706115 | J77: 1442571 | K77: =I77-J77 -> -736456 | L77: =I77 -> 706115 | M77: =J77 -> 1442571 | N77: =L77-M77 -> -736456
A78: Corporate Debt Vehicle (units)
B79: =1+B77 -> 55 | C79: ATRAM Unitized Corporate Debt Vehicle, Inc. | D79: 7.1181613e+08 | E79: 201070 | F79: =D79-E79 -> 7.1161506e+08 | G79: 0 | H79: 13 | I79: 0 | J79: 0 | K79: =I79-J79 -> 0 | L79: =I79 -> 0 | M79: =J79 -> 0 | N79: =L79-M79 -> 0
A80: Sub total - Peso Currency | D80: =SUM(D67:D79) -> 50375787599 | E80: =SUM(E67:E79) -> 4.1411581e+08 | F80: =SUM(F67:F79) -> 49961671787 | G80: =SUM(G67:G79) -> 0 | H80: =SUM(H67:H79) -> 59505 | I80: =SUM(I67:I79) -> 3.547206e+08 | J80: =SUM(J67:J79) -> 7.0953526e+08 | K80: =SUM(K67:K79) -> -354814657 | ... N80: =SUM(N67:N79) -> -354814657
A81: Primarily invested in foreign currency securities (shares)
B82: =1+B79 -> 56 | C82: ALFM Dollar Bond Fund, Inc. | D82: 12983691988 | E82: 177754428 | F82: =D82-E82 -> 12805937560 | G82: 0 | H82: 7878 | I82: 26018270 | J82: 126508071 | K82: =I82-J82 -> -100489801 | L82: =I82 -> 26018270 | M82: =J82 -> 126508071 | N82: =L82-M82 -> -100489801
B83: =1+B82 -> 57 | C83: ATRAM Total Return Dollar Bond Fund, Inc. | D83: 2.6077588e+08 | E83: 995094.51 | F83: =D83-E83 -> 2.5978079e+08 | G83: 0 | H83: 144 | I83: 24748.06 | J83: 118353.08 | K83: =I83-J83 -> -93605.02 | L83: =I83 -> 24748.06 | M83: =J83 -> 118353.08 | N83: =L83-M83 -> -93605.02
B84: =1+B83 -> 58 | C84: First Metro Save and Learn Dollar Bond Fund, Inc. | D84: 443363860 | E84: 1260859 | F84: =D84-E84 -> 442103001 | G84: 0 | H84: 156 | I84: 1227442 | J84: 1402735 | K84: =I84-J84 -> -175293 | L84: =I84 -> 1227442 | M84: =J84 -> 1402735 | N84: =L84-M84 -> -175293
B85: =1+B84 -> 59 | C85: PAMI Global Bond Fund, Inc. | D85: 66626706 | E85: 15826873 | F85: =D85-E85 -> 50799833 | G85: 0 | H85: 27 | I85: 0 | J85: 0 | K85: =I85-J85 -> 0 | L85: =I85 -> 0 | M85: =J85 -> 0 | N85: =L85-M85 -> 0
B86: =1+B85 -> 60 | C86: Philam Dollar Bond Fund, Inc. | D86: 1914798195 | E86: 24777134 | F86: =D86-E86 -> 1890021061 | G86: 0 | H86: 1783 | I86: 111002 | J86: 31895211 | K86: =I86-J86 -> -31784209 | L86: =I86 -> 111002 | M86: =J86 -> 31895211 | N86: =L86-M86 -> -31784209
B87: =1+B86 -> 61 | C87: Philequity Dollar Income Fund, Inc. | D87: 2.358069e+08 | E87: 1402410.9 | F87: =D87-E87 -> 234404490 | G87: 0 | H87: 117 | I87: 157570 | J87: 0 | K87: =I87-J87 -> 157570 | L87: =I87 -> 157570 | M87: =J87 -> 0 | N87: =L87-M87 -> 157570
B88: =1+B87 -> 62 | C88: Sun Life Prosperity Dollar Abundance Fund, Inc. | D88: 626249388 | E88: 30385958 | F88: =D88-E88 -> 595863430 | G88: 0 | H88: 2588 | I88: 11932127 | J88: 3191370 | K88: =I88-J88 -> 8740757 | L88: =I88 -> 11932127 | M88: =J88 -> 3191370 | N88: =L88-M88 -> 8740757
A89: Sub total - US Currency | D89: =SUM(D82:D88) -> 16531312920 | E89: =SUM(E82:E88) -> 2.5240276e+08 | F89: =SUM(F82:F88) -> 16278910163 | G89: =SUM(G82:G88) -> 0 | H89: =SUM(H82:H88) -> 12693 | I89: =SUM(I82:I88) -> 39471159 | J89: =SUM(J82:J88) -> 1.6311574e+08 | K89: =SUM(K82:K88) -> -123644581 | ... N89: =SUM(N82:N88) -> -123644581
B90: =1+B88 -> 63 | C90: ALFM Euro Bond Fund, Inc. | D90: 965426833 | E90: 30032920 | F90: =D90-E90 -> 935393913 | G90: 0 | H90: 608 | I90: 429974 | J90: 2529855 | K90: =I90-J90 -> -2099881 | L90: =I90 -> 429974 | M90: =J90 -> 2529855 | N90: =L90-M90 -> -2099881
A91: Sub total - Euro Currency | D91: =SUM(D90) -> 965426833 | E91: =SUM(E90) -> 30032920 | F91: =SUM(F90) -> 935393913 | G91: =SUM(G90) -> 0 | H91: =SUM(H90) -> 608 | I91: =SUM(I90) -> 429974 | J91: =SUM(J90) -> 2529855 | K91: =SUM(K90) -> -2099881 | ... N91: =SUM(N90) -> -2099881
A92: Sub total - bond funds | D92: =D80+D89+D91 -> 67872527352 | E92: =E80+E89+E91 -> 6.9655149e+08 | F92: =F80+F89+F91 -> 67175975863 | G92: =G80+G89+G91 -> 0 | H92: =H80+H89+H91 -> 72806 | I92: =I80+I89+I91 -> 3.9462173e+08 | J92: =J80+J89+J91 -> 8.7518085e+08 | K92: =K80+K89+K91 -> -480559119 | ... N92: =N80+N89+N91 -> -480559119
A93: Money Market Funds
A94: Primarily invested in Peso Securities (shares)
B95: =1+B90 -> 64 | C95: ALFM Money Market Fund, Inc. | D95: 26355145809 | E95: 21987814 | F95: =D95-E95 -> 26333157995 | G95: 0 | H95: 25414 | I95: 349668 | J95: 674395468 | K95: =I95-J95 -> -674045800 | L95: =I95 -> 349668 | M95: =J95 -> 674395468 | N95: =L95-M95 -> -674045800
B96: =1+B95 -> 65 | C96: First Metro Save and Learn Money Market Fund, Inc. | D96: 3138695311 | E96: 208831153 | F96: =D96-E96 -> 2929864158 | G96: 0 | H96: 974 | I96: 310205086 | J96: 629801548 | K96: =I96-J96 -> -319596462 | L96: =I96 -> 310205086 | M96: =J96 -> 629801548 | N96: =L96-M96 -> -319596462
B97: =1+B96 -> 66 | C97: Sun Life Prosperity Peso Starter Fund, Inc. | D97: 19763580934 | E97: 482457319 | F97: =D97-E97 -> 19281123615 | G97: 0 | H97: 70150 | I97: 399493061 | J97: 1927759182 | K97: =I97-J97 -> -1528266121 | L97: =I97 -> 399493061 | M97: =J97 -> 1927759182 | N97: =L97-M97 -> -1528266121
A98: Primarily invested in Peso Securities (units)
B99: =1+B97 -> 67 | C99: ALFM Money Market Fund, Inc. | D99: 8428259211 | E99: 7287929 | F99: =D99-E99 -> 8420971282 | G99: 0 | H99: 9218 | I99: 1011006495 | J99: 803000391 | K99: =I99-J99 -> 208006104 | L99: =I99 -> 1011006495 | M99: =J99 -> 803000391 | N99: =L99-M99 -> 208006104
A100: Sub total - Peso Currency | D100: =SUM(D95:D97)+D99 -> 57685681265 | E100: =SUM(E95:E97)+E99 -> 720564215 | F100: =SUM(F95:F97)+F99 -> 56965117050 | G100: =SUM(G95:G97)+G99 -> 0 | H100: =SUM(H95:H97)+H99 -> 105756 | I100: =SUM(I95:I97)+I99 -> 1721054310 | J100: =SUM(J95:J97)+J99 -> 4034956589 | K100: =SUM(K95:K97)+K99 -> -2313902279 | ... N100: =SUM(N95:N97)+N99 -> -2313902279
A101: Primarily invested in foreign currency securities (shares)
B102: =1+B99 -> 68 | C102: Sun Life Prosperity Dollar Starter Fund, Inc. | D102: 2334625756 | E102: 22854473 | F102: =D102-E102 -> 2311771283 | G102: 0 | H102: 3635 | I102: 34289270 | J102: 122269167 | K102: =I102-J102 -> -87979897 | L102: =I102 -> 34289270 | M102: =J102 -> 122269167 | N102: =L102-M102 -> -87979897
A103: Sub total - US Currency | D103: =SUM(D102) -> 2334625756 | E103: =SUM(E102) -> 22854473 | F103: =SUM(F102) -> 2311771283 | G103: =SUM(G102) -> 0 | H103: =SUM(H102) -> 3635 | I103: =SUM(I102) -> 34289270 | J103: =SUM(J102) -> 122269167 | K103: =SUM(K102) -> -87979897 | ... N103: =SUM(N102) -> -87979897
A104: Sub total - money market funds | D104: =D100+D103 -> 60020307021 | E104: =E100+E103 -> 743418688 | F104: =F100+F103 -> 59276888333 | G104: =G100+G103 -> 0 | H104: =H100+H103 -> 109391 | I104: =I100+I103 -> 1755343580 | J104: =J100+J103 -> 4157225756 | K104: =K100+K103 -> -2401882176 | ... N104: =N100+N103 -> -2401882176
A105: Feeder Fund
...

Sheet Feb
A1: PHILIPPINE INVESTMENT FUNDS ASSOCIATION, INC.
A2: MUTUAL FUNDS STATISTICAL REPORT
A3: Month of February 2024
A4: (Amounts in Peso)
I5: F O R - T H E - M O N T H | L5: Y E A R - T O - D A T E
A6: Fund Category | C6: Fund Name | D6: ASSETS | E6: LIABILITIES | F6: NET ASSETS | G6: EQUITY INV. | H6: NO. OF A/C | I6: SALES | J6: REDEMPTIONS | K6: NET SALES | L6: TOTAL SALES | M6: TOTAL REDEMPTIONS | N6: TOTAL NET SALES
A7: Stock Funds
A8: Primarily invested in Peso Securities (shares)
B9: 1 | C9: ALFM Growth Fund, Inc. | D9: 4537893336 | E9: 25764830 | F9: =D9-E9 -> 4512128506 | G9: 4318682817 | H9: 6542 | I9: 2563558 | J9: 56906144 | K9: =I9-J9 -> -54342586 | L9: =I9+'Jan UPDATED'!L9 -> 7810080 | M9: =J9+'Jan UPDATED'!M9 -> 115958546 | N9: =L9-M9 -> -108148466
B10: =1+B9 -> 2 | C10: ATRAM Alpha Opportunity Fund, Inc. | D10: 7.7947833e+08 | E10: 7522486.7 | F10: =D10-E10 -> 7.7195584e+08 | G10: 7.3126179e+08 | H10: 4075 | I10: 1872432.5 | J10: 13189805 | K10: =I10-J10 -> -11317372 | L10: =I10+Jan!L10 -> 4640012 | M10: =J10+Jan!M10 -> 31345751 | N10: =L10-M10 -> -26705739
B11: =1+B10 -> 3 | C11: ATRAM Phil. Equity Opportunity Fund, Inc. | D11: 1.4188661e+09 | E11: 7983030.2 | F11: =D11-E11 -> 1410883056 | G11: 1.3258309e+09 | H11: 2676 | I11: 5755161.2 | J11: 36631886 | K11: =I11-J11 -> -30876725 | L11: =I11+Jan!L11 -> 24055902 | M11: =J11+Jan!M11 -> 47601492 | N11: =L11-M11 -> -23545590
B12: =1+B11 -> 4 | C12: Climbs Share Capital Equity Investment Fund Corp. | D12: 4.0184556e+08 | E12: 12279326 | F12: =D12-E12 -> 389566232 | G12: 2.2312001e+08 | H12: 1783 | I12: 42693995 | J12: 965467.03 | K12: =I12-J12 -> 41728528 | L12: =I12+Jan!L12 -> 43221666 | M12: =J12+Jan!M12 -> 8304673.8 | N12: =L12-M12 -> 34916992
B13: =1+B12 -> 5 | C13: First Metro Consumer Fund, Inc. | D13: 481665173 | E13: 11752609 | F13: =D13-E13 -> 469912564 | G13: 450628587 | H13: 1311 | I13: 31492395 | J13: 32197132 | K13: =I13-J13 -> -704737 | L13: =I13+Jan!L13 -> 32975031 | M13: =J13+Jan!M13 -> 37049669 | N13: =L13-M13 -> -4074638
B14: =1+B13 -> 6 | C14: First Metro Save and Learn Equity Fund, Inc. | D14: 4110224484 | E14: 41164477 | F14: =D14-E14 -> 4069060007 | G14: 3965059614 | H14: 15300 | I14: 267007353 | J14: 602967795 | K14: =I14-J14 -> -335960442 | L14: =I14+Jan!L14 -> 271105689 | M14: =J14+Jan!M14 -> 817577083 | N14: =L14-M14 -> -546471394
B15: =1+B14 -> 7 | C15: First Metro Save and Learn Phil. Index Fund, Inc. | D15: 105470622 | E15: 451506 | F15: =D15-E15 -> 105019116 | G15: 104245833 | H15: 509 | I15: 351501 | J15: 1075524 | K15: =I15-J15 -> -724023 | L15: =I15+Jan!L15 -> 615409 | M15: =J15+Jan!M15 -> 3386078 | N15: =L15-M15 -> -2770669
B16: =1+B15 -> 8 | C16: MBG Equity Investment Fund, Inc. | D16: 123800115 | E16: 1007085 | F16: =D16-E16 -> 122793030 | G16: 112054432 | H16: 49 | I16: 0 | J16: 0 | K16: =I16-J16 -> 0 | L16: =I16+Jan!L16 -> 0 | M16: =J16+Jan!M16 -> 1946420 | N16: =L16-M16 -> -1946420
B17: =1+B16 -> 9 | C17: PAMI Equity Index Fund, Inc. | D17: 1260431593 | E17: 38562522 | F17: =D17-E17 -> 1221869071 | G17: 1239720234 | H17: 11580 | I17: 0 | J17: 17923616 | K17: =I17-J17 -> -17923616 | L17: =I17+Jan!L17 -> 0 | M17: =J17+Jan!M17 -> 41823511 | N17: =L17-M17 -> -41823511
B18: =1+B17 -> 10 | C18: Philam Strategic Growth Fund, Inc. | D18: 3713496352 | E18: 46037315 | F18: =D18-E18 -> 3667459037 | G18: 3507936237 | H18: 11487 | I18: 7278270 | J18: 37850465 | K18: =I18-J18 -> -30572195 | L18: =I18+Jan!L18 -> 12900959 | M18: =J18+Jan!M18 -> 64757066 | N18: =L18-M18 -> -51856107
B19: =1+B18 -> 11 | C19: Philequity Dividend Yield Fund, Inc. | D19: 2.3143928e+09 | E19: 2939147.1 | F19: =D19-E19 -> 2311453640 | G19: 2.1900991e+09 | H19: 4976 | I19: 1347007.7 | J19: 4123676.2 | K19: =I19-J19 -> -2776668.4 | L19: =I19+Jan!L19 -> 2802826.2 | M19: =J19+Jan!M19 -> 9355136.6 | N19: =L19-M19 -> -6552310.4
B20: =1+B19 -> 12 | C20: Philequity Fund, Inc. | D20: 9.9420787e+09 | E20: 36569566 | F20: =D20-E20 -> 9905509178 | G20: 9.236565e+09 | H20: 33975 | I20: 8033646.3 | J20: 42419727 | K20: =I20-J20 -> -34386080 | L20: =I20+Jan!L20 -> 19829246 | M20: =J20+Jan!M20 -> 1.0578402e+08 | N20: =L20-M20 -> -85954771
B21: =1+B20 -> 13 | C21: Philequity MSCI Phil. Index Fund, Inc. | D21: 3.3645196e+08 | E21: 783171.4 | F21: =D21-E21 -> 3.3566879e+08 | G21: 3.3332276e+08 | H21: 938 | I21: 181299 | J21: 1399624.1 | K21: =I21-J21 -> -1218325.1 | L21: =I21+Jan!L21 -> 851724.85 | M21: =J21+Jan!M21 -> 1904284.2 | N21: =L21-M21 -> -1052559.4
... B27: =1+B26 -> 19 | C27: United Fund, Inc. | D27: 6.2069875e+08 | E27: 5402879.9 | F27: =D27-E27 -> 6.1529587e+08 | G27: 5.194373e+08 | H27: 1241 | I27: 784953.5 | J27: 3063940.6 | K27: =I27-J27 -> -2278987.1 | L27: =I27+Jan!L27 -> 854729.25 | M27: =J27+Jan!M27 -> 4242551.7 | N27: =L27-M27 -> -3387822.5
A28: Primarily invested in Peso Securities (units)
B29: =1+B27 -> 20 | C29: COL Equity Index Unitized Mutual Fund, Inc. | D29: 2.3785871e+08 | E29: 4970811.2 | F29: =D29-E29 -> 2.328879e+08 | G29: 2.3067381e+08 | H29: 3136 | I29: 6418630.1 | J29: 13847818 | K29: =I29-J29 -> -7429188.3 | L29: =I29+Jan!L29 -> 12816460 | M29: =J29+Jan!M29 -> 25375990 | N29: =L29-M29 -> -12559530
B30: =1+B29 -> 21 | C30: COL Strategic Growth Equity Unitized Mutual Fund, Inc. | D30: 2.4338453e+08 | E30: 5688384.3 | F30: =D30-E30 -> 2.3769615e+08 | G30: 1.3959825e+08 | H30: 2322 | I30: 1.0400048e+08 | J30: 1319415.5 | K30: =I30-J30 -> 1.0268107e+08 | L30: =I30+Jan!L30 -> 1.3237636e+08 | M30: =J30+Jan!M30 -> 8191069 | N30: =L30-M30 -> 1.2418529e+08
B31: =1+B30 -> 22 | C31: Philequity Alpha One Fund, Inc. | D31: 3.1588606e+08 | E31: 3404000.6 | F31: =D31-E31 -> 312482057 | G31: 2.8684164e+08 | H31: 1250 | I31: 693735.02 | J31: 9527958 | K31: =I31-J31 -> -8834223 | L31: =I31+Jan!L31 -> 1502091.9 | M31: =J31+Jan!M31 -> 15016773 | N31: =L31-M31 -> -13514681
B32: =1+B31 -> 23 | C32: Philippine Stock Index Fund Corp. | D32: 639917212 | E32: 3883445 | F32: =D32-E32 -> 636033767 | G32: 632086498 | H32: 627401 | I32: 18963149 | J32: 30219075 | K32: =I32-J32 -> -11255926 | L32: =I32+Jan!L32 -> 31379098 | M32: =J32+Jan!M32 -> 56770795 | N32: =L32-M32 -> -25391697
A33: Exchange Traded Fund
B34: =1+B32 -> 24 | C34: First Metro Phil. Equity Exchange Traded Fund, Inc. | D34: 2259839759 | E34: 1757382 | F34: =D34-E34 -> 2258082377 | G34: 2256006861 | H34: 3223 | I34: 2154855 | J34: 41653113 | K34: =I34-J34 -> -39498258 | L34: =I34+Jan!L34 -> 8336295 | M34: =J34+Jan!M34 -> 50095129 | N34: =L34-M34 -> -41758834
A35: Sub total - Peso Currency | D35: =SUM(D9:D34) -> 68183803326 | E35: =SUM(E9:E34) -> 3.870149e+08 | F35: =SUM(F9:F34) -> 67796788424 | G35: =SUM(G9:G34) -> 65572794434 | H35: =SUM(H9:H34) -> 909066 | I35: =SUM(I9:I34) -> 591596146 | J35: =SUM(J9:J34) -> 1536649575 | K35: =SUM(K9:K34) -> -9.4505343e+08 | ... N35: =SUM(N9:N34) -> -1904880567
A36: Primarily invested in foreign currency securities (shares)
B37: =1+B34 -> 25 | C37: ATRAM AsiaPlus Equity Fund, Inc. | D37: 25686145 | E37: 60860.67 | F37: =D37-E37 -> 25625285 | G37: 23847897 | H37: 52 | I37: 179724.23 | J37: 0 | K37: =I37-J37 -> 179724.23 | L37: =I37+Jan!L37 -> 272482.88 | M37: =J37+Jan!M37 -> 11209.42 | N37: =L37-M37 -> 261273.46
B38: =1+B37 -> 26 | C38: Sun Life Prosperity World Voyager Fund, Inc. | D38: 2078110359 | E38: 33126415 | F38: =D38-E38 -> 2044983944 | G38: 0 | H38: 2963 | I38: 17576578 | J38: 11364242 | K38: =I38-J38 -> 6212336 | L38: =I38+Jan!L38 -> 35178020 | M38: =J38+Jan!M38 -> 83357113 | N38: =L38-M38 -> -48179093
A39: Sub total - US Currency | D39: =SUM(D37:D38) -> 2103796504 | E39: =SUM(E37:E38) -> 33187276 | F39: =SUM(F37:F38) -> 2070609229 | G39: =SUM(G37:G38) -> 23847897 | H39: =SUM(H37:H38) -> 3015 | I39: =SUM(I37:I38) -> 17756302 | J39: =SUM(J37:J38) -> 11364242 | K39: =SUM(K37:K38) -> 6392060.2 | ... N39: =SUM(N37:N38) -> -47917820
A40: Sub total - stock funds | D40: =D35+D39 -> 70287599830 | E40: =E35+E39 -> 4.2020218e+08 | F40: =F35+F39 -> 69867397653 | G40: =G35+G39 -> 65596642331 | H40: =H35+H39 -> 912081 | I40: =I35+I39 -> 6.0935245e+08 | J40: =J35+J39 -> 1548013817 | K40: =K35+K39 -> -9.3866137e+08 | ... N40: =N35+N39 -> -1952798386
A41: Balanced Funds
A42: Primarily invested in Peso Securities (shares)
B43: =1+B38 -> 27 | C43: ATRAM Philippine Balanced Fund, Inc. | D43: 5.2701244e+08 | E43: 48138802 | F43: =D43-E43 -> 4.7887363e+08 | G43: 300042871 | H43: 2354 | I43: 915834.42 | J43: 12695508 | K43: =I43-J43 -> -11779673 | L43: =I43+Jan!L43 -> 1610135.2 | M43: =J43+Jan!M43 -> 18178176 | N43: =L43-M43 -> -16568041
B44: =1+B43 -> 28 | C44: ATRAM Unicapital Diversified Growth Fund, Inc. | D44: 1.2291743e+08 | E44: 4061715.2 | F44: =D44-E44 -> 1.1885572e+08 | G44: 49683979 | H44: 706 | I44: 375966.52 | J44: 2339667 | K44: =I44-J44 -> -1963700.5 | L44: =I44+Jan!L44 -> 783371.86 | M44: =J44+Jan!M44 -> 2932559.9 | N44: =L44-M44 -> -2149188
B45: =1+B44 -> 29 | C45: First Metro Save and Learn Balanced Fund, Inc. | D45: 877618660 | E45: 5813840 | F45: =D45-E45 -> 871804820 | G45: 561372118 | H45: 4386 | I45: 895961 | J45: 107049944 | K45: =I45-J45 -> -106153983 | L45: =I45+Jan!L45 -> 2355344 | M45: =J45+Jan!M45 -> 117757404 | N45: =L45-M45 -> -115402060
B46: =1+B45 -> 30 | C46: First Metro Save and Learn F.O.C.C.U.S. Dynamic Fund, Inc. | D46: 299045145 | E46: 3598513 | F46: =D46-E46 -> 295446632 | G46: 271645605 | H46: 225 | I46: 80295085 | J46: 82726158 | K46: =I46-J46 -> -2431073 | L46: =I46+Jan!L46 -> 80489163 | M46: =J46+Jan!M46 -> 84194791 | N46: =L46-M46 -> -3705628
B47: =1+B46 -> 31 | C47: NCM Mutual Fund of the Phils., Inc. | D47: 3.3186644e+08 | E47: 1475229.4 | F47: =D47-E47 -> 330391214 | G47: 1.681715e+08 | H47: 48 | I47: 0 | J47: 0 | K47: =I47-J47 -> 0 | L47: =I47+Jan!L47 -> 0 | M47: =J47+Jan!M47 -> 66119 | N47: =L47-M47 -> -66119
B48: =1+B47 -> 32 | C48: PAMI Horizon Fund, Inc. | D48: 530295263 | E48: 17810638 | F48: =D48-E48 -> 512484625 | G48: 261713576 | H48: 9863 | I48: 168326 | J48: 8325618 | K48: =I48-J48 -> -8157292 | L48: =I48+Jan!L48 -> 359032 | M48: =J48+Jan!M48 -> 10002688 | N48: =L48-M48 -> -9643656
B49: =1+B48 -> 33 | C49: Philam Fund, Inc. | D49: 2040930075 | E49: 25286000 | F49: =D49-E49 -> 2015644075 | G49: 1015716016 | H49: 7755 | I49: 2560122 | J49: 23596072 | K49: =I49-J49 -> -21035950 | L49: =I49+Jan!L49 -> 6583281 | M49: =J49+Jan!M49 -> 38273412 | N49: =L49-M49 -> -31690131
B50: =1+B49 -> 34 | C50: Solidaritas Fund, Inc. | D50: 122576839 | E50: 154480 | F50: =D50-E50 -> 122422359 | G50: 62045714 | H50: 174 | I50: 0 | J50: 282352 | K50: =I50-J50 -> -282352 | L50: =I50+Jan!L50 -> 0 | M50: =J50+Jan!M50 -> 1858328 | N50: =L50-M50 -> -1858328
B51: =1+B50 -> 35 | C51: Sun Life Prosperity Balanced Fund, Inc. | D51: 6881233358 | E51: 31421461 | F51: =D51-E51 -> 6849811897 | G51: 4043192747 | H51: 54205 | I51: 6642130 | J51: 64137165 | K51: =I51-J51 -> -57495035 | L51: =I51+Jan!L51 -> 14573374 | M51: =J51+Jan!M51 -> 171352380 | N51: =L51-M51 -> -156779006
B52: =1+B51 -> 36 | C52: Sun Life Prosperity Dynamic Fund, Inc. | D52: 607549660 | E52: 5120570 | F52: =D52-E52 -> 602429090 | G52: 370847144 | H52: 4999 | I52: 0 | J52: 27348629 | K52: =I52-J52 -> -27348629 | L52: =I52+Jan!L52 -> 0 | M52: =J52+Jan!M52 -> 52038077 | N52: =L52-M52 -> -52038077
A53: Primarily invested in Peso Securities (units)
B54: =1+B52 -> 37 | C54: Sun Life Prosperity Achiever Fund 2028, Inc. | D54: 80120605 | E54: 404740 | F54: =D54-E54 -> 79715865 | G54: 20388360 | H54: 1168 | I54: 275542 | J54: 212974 | K54: =I54-J54 -> 62568 | L54: =I54+Jan!L54 -> 565465 | M54: =J54+Jan!M54 -> 408261 | N54: =L54-M54 -> 157204
B55: =1+B54 -> 38 | C55: Sun Life Prosperity Achiever Fund 2038, Inc. | D55: 58758614 | E55: 355383 | F55: =D55-E55 -> 58403231 | G55: 46089174 | H55: 464 | I55: 90564 | J55: 34877 | K55: =I55-J55 -> 55687 | L55: =I55+Jan!L55 -> 248017 | M55: =J55+Jan!M55 -> 49965 | N55: =L55-M55 -> 198052
B56: =1+B55 -> 39 | C56: Sun Life Prosperity Achiever Fund 2048, Inc. | D56: 49951699 | E56: 324932 | F56: =D56-E56 -> 49626767 | G56: 42251582 | H56: 214 | I56: 73500 | J56: 67836 | K56: =I56-J56 -> 5664 | L56: =I56+Jan!L56 -> 112100 | M56: =J56+Jan!M56 -> 85305 | N56: =L56-M56 -> 26795
A57: Sub total - Peso Currency | D57: =SUM(D43:D56) -> 12529876231 | E57: =SUM(E43:E56) -> 1.439663e+08 | F57: =SUM(F43:F56) -> 12385909927 | G57: =SUM(G43:G56) -> 7213160386 | H57: =SUM(H42:H56) -> 86561 | I57: =SUM(I43:I56) -> 92293031 | J57: =SUM(J43:J56) -> 3.288168e+08 | K57: =SUM(K43:K56) -> -2.3652377e+08 | L57: =SUM(L43:L56) -> 1.0767928e+08 | M57: =SUM(M43:M56) -> 4.9719747e+08 | N57: =SUM(N43:N56) -> -3.8951818e+08
A58: Primarily invested in foreign currency securities (shares)
B59: =1+B56 -> 40 | C59: Cocolife Dollar Fund Builder, Inc. | D59: 71917450 | E59: 641501.64 | F59: =D59-E59 -> 71275948 | G59: 0 | H59: 50 | I59: 0 | J59: 79493.21 | K59: =I59-J59 -> -79493.21 | L59: =I59+Jan!L59 -> 84501.37 | M59: =J59+Jan!M59 -> 79493.21 | N59: =L59-M59 -> 5008.16
B60: =1+B59 -> 41 | C60: PAMI Asia Balanced Fund, Inc. | D60: 334478392 | E60: 33337721 | F60: =D60-E60 -> 301140671 | G60: 166540164 | H60: 236 | I60: 0 | J60: 4508975 | K60: =I60-J60 -> -4508975 | L60: =I60+Jan!L60 -> 0 | M60: =J60+Jan!M60 -> 6454037 | N60: =L60-M60 -> -6454037
B61: =1+B60 -> 42 | C61: Sun Life Prosperity Dollar Advantage Fund, Inc. | D61: 1436681490 | E61: 40336126 | F61: =D61-E61 -> 1396345364 | G61: 0 | H61: 4173 | I61: 3022251 | J61: 63486071 | K61: =I61-J61 -> -60463820 | L61: =I61+Jan!L61 -> 3361879 | M61: =J61+Jan!M61 -> 161655559 | N61: =L61-M61 -> -158293680
B62: =1+B61 -> 43 | C62: Sun Life Prosperity Dollar Wellspring Fund, Inc. | D62: 260919199 | E62: 4969081 | F62: =D62-E62 -> 255950118 | G62: 0 | H62: 745 | I62: 3392721 | J62: 1512016 | K62: =I62-J62 -> 1880705 | L62: =I62+Jan!L62 -> 3621985 | M62: =J62+Jan!M62 -> 4644774 | N62: =L62-M62 -> -1022789
A63: Sub total - US Currency | D63: =SUM(D59:D62) -> 2103996531 | E63: =SUM(E59:E62) -> 79284430 | F63: =SUM(F59:F62) -> 2024712101 | G63: =SUM(G59:G62) -> 166540164 | H63: =SUM(H59:H62) -> 5204 | I63: =SUM(I59:I62) -> 6414972 | J63: =SUM(J59:J62) -> 69586555 | K63: =SUM(K59:K62) -> -63171583 | ... N63: =SUM(N59:N62) -> -1.657655e+08
A64: Sub total - balanced funds | D64: =D57+D63 -> 14633872761 | E64: =E57+E63 -> 2.2325073e+08 | F64: =F57+F63 -> 14410622028 | G64: =G57+G63 -> 7379700550 | H64: =H57+H63 -> 91765 | I64: =I57+I63 -> 98708003 | J64: =J57+J63 -> 398403355 | K64: =K57+K63 -> -2.9969535e+08 | ... N64: =N57+N63 -> -5.5528368e+08
A65: Bond Funds
A66: Primarily invested in Peso Securities (shares)
B67: =1+B62 -> 44 | C67: ALFM Peso Bond Fund, Inc. | D67: 36488661443 | E67: 277954545 | F67: =D67-E67 -> 36210706898 | G67: 0 | H67: 23469 | I67: 174595573 | J67: 459016062 | K67: =I67-J67 -> -284420489 | L67: =I67+Jan!L67 -> 344330422 | M67: =J67+Jan!M67 -> 906667964 | N67: =L67-M67 -> -562337542
B68: =1+B67 -> 45 | C68: ATRAM Corporate Bond Fund, Inc. | D68: 3.8116333e+08 | E68: 13538305 | F68: =D68-E68 -> 3.6762503e+08 | G68: 0 | H68: 1013 | I68: 745822.22 | J68: 46310675 | K68: =I68-J68 -> -45564853 | L68: =I68+Jan!L68 -> 4171227.7 | M68: =J68+Jan!M68 -> 70438850 | N68: =L68-M68 -> -66267622
B69: =1+B68 -> 46 | C69: Cocolife Fixed Income Fund, Inc. | D69: 8.9746261e+08 | E69: 21628850 | F69: =D69-E69 -> 8.7583376e+08 | G69: 0 | H69: 1857 | I69: 3242661.6 | J69: 22001342 | K69: =I69-J69 -> -18758680 | L69: =I69+Jan!L69 -> 10068711 | M69: =J69+Jan!M69 -> 42214438 | N69: =L69-M69 -> -32145727
B70: =1+B69 -> 47 | C70: Ekklesia Mutual Fund, Inc. | D70: 194744538 | E70: 186357 | F70: =D70-E70 -> 194558181 | G70: 0 | H70: 161 | I70: 0 | J70: 1144639 | K70: =I70-J70 -> -1144639 | L70: =I70+Jan!L70 -> 0 | M70: =J70+Jan!M70 -> 1964481 | N70: =L70-M70 -> -1964481
B71: =1+B70 -> 48 | C71: First Metro Save and Learn Fixed Income Fund, Inc. | D71: 1177208679 | E71: 5022371 | F71: =D71-E71 -> 1172186308 | G71: 0 | H71: 1781 | I71: 110640749 | J71: 219652395 | K71: =I71-J71 -> -109011646 | L71: =I71+Jan!L71 -> 136692418 | M71: =J71+Jan!M71 -> 236892628 | N71: =L71-M71 -> -100200210
B72: =1+B71 -> 49 | C72: Philam Bond Fund, Inc. | D72: 1598442972 | E72: 31322413 | F72: =D72-E72 -> 1567120559 | G72: 0 | H72: 4817 | I72: 2844491 | J72: 14286171 | K72: =I72-J72 -> -11441680 | L72: =I72+Jan!L72 -> 7579777 | M72: =J72+Jan!M72 -> 37533969 | N72: =L72-M72 -> -29954192
B73: =1+B72 -> 50 | C73: Philam Managed Income Fund, Inc. | D73: 592833748 | E73: 13065185 | F73: =D73-E73 -> 579768563 | G73: 0 | H73: 453 | I73: 1121253 | J73: 3592856 | K73: =I73-J73 -> -2471603 | L73: =I73+Jan!L73 -> 2505413 | M73: =J73+Jan!M73 -> 7227498 | N73: =L73-M73 -> -4722085
B74: =1+B73 -> 51 | C74: Philequity Peso Bond Fund, Inc. | D74: 3.2675024e+08 | E74: 1036280.2 | F74: =D74-E74 -> 3.2571396e+08 | G74: 0 | H74: 4037 | I74: 484073.75 | J74: 1377087.7 | K74: =I74-J74 -> -893013.91 | L74: =I74+Jan!L74 -> 1198812.6 | M74: =J74+Jan!M74 -> 2365461.8 | N74: =L74-M74 -> -1166649.2
B75: =1+B74 -> 52 | C75: Soldivo Bond Fund, Inc. | D75: 1.5708289e+09 | E75: 226484.59 | F75: =D75-E75 -> 1570602420 | G75: 0 | H75: 789 | I75: 25175200 | J75: 299950.26 | K75: =I75-J75 -> 24875250 | L75: =I75+Jan!L75 -> 53301850 | M75: =J75+Jan!M75 -> 4555741.1 | N75: =L75-M75 -> 48746109
B76: =1+B75 -> 53 | C76: Sun Life Prosperity Bond Fund, Inc. | D76: 5909551094 | E76: 13888568 | F76: =D76-E76 -> 5895662526 | G76: 0 | H76: 18308 | I76: 95501412 | J76: 79048994 | K76: =I76-J76 -> 16452418 | L76: =I76+Jan!L76 -> 208517089 | M76: =J76+Jan!M76 -> 244961828 | N76: =L76-M76 -> -36444739
B77: =1+B76 -> 54 | C77: Sun Life Prosperity GS Fund, Inc. | D77: 124238659 | E77: 520307 | F77: =D77-E77 -> 123718352 | G77: 0 | H77: 2773 | I77: 348360 | J77: 923906 | K77: =I77-J77 -> -575546 | L77: =I77+Jan!L77 -> 1054475 | M77: =J77+Jan!M77 -> 2366477 | N77: =L77-M77 -> -1312002
A78: Corporate Debt Vehicle (units)
B79: =1+B77 -> 55 | C79: ATRAM Unitized Corporate Debt Vehicle, Inc. | D79: 703215007 | E79: 201070 | F79: =D79-E79 -> 703013937 | G79: 0 | H79: 13 | I79: 0 | J79: 0 | K79: =I79-J79 -> 0 | L79: =I79+Jan!L79 -> 0 | M79: =J79+Jan!M79 -> 0 | N79: =L79-M79 -> 0
A80: Sub total - Peso Currency | D80: =SUM(D67:D79) -> 49965101222 | E80: =SUM(E67:E79) -> 3.7859074e+08 | F80: =SUM(F67:F79) -> 49586510486 | G80: =SUM(G67:G79) -> 0 | H80: =SUM(H67:H79) -> 59471 | I80: =SUM(I67:I79) -> 4.146996e+08 | J80: =SUM(J67:J79) -> 8.4765408e+08 | K80: =SUM(K67:K79) -> -4.3295448e+08 | ... N80: =SUM(N67:N79) -> -7.8776914e+08
A81: Primarily invested in foreign currency securities (shares)
B82: =1+B79 -> 56 | C82: ALFM Dollar Bond Fund, Inc. | D82: 12889882564 | E82: 107164073 | F82: =D82-E82 -> 12782718491 | G82: 0 | H82: 7830 | I82: 32475538 | J82: 61070581 | K82: =I82-J82 -> -28595043 | L82: =I82+Jan!L82 -> 58493808 | M82: =J82+Jan!M82 -> 187578652 | N82: =L82-M82 -> -129084844
B83: =1+B82 -> 57 | C83: ATRAM Total Return Dollar Bond Fund, Inc. | D83: 3.3504444e+08 | E83: 85324031 | F83: =D83-E83 -> 2.4972041e+08 | G83: 0 | H83: 139 | I83: 28069.65 | J83: 6752417.6 | K83: =I83-J83 -> -6724348 | L83: =I83+Jan!L83 -> 52817.71 | M83: =J83+Jan!M83 -> 6870770.7 | N83: =L83-M83 -> -6817953
B84: =1+B83 -> 58 | C84: First Metro Save and Learn Dollar Bond Fund, Inc. | D84: 441747299 | E84: 1003989 | F84: =D84-E84 -> 440743310 | G84: 0 | H84: 154 | I84: 2098125 | J84: 1315720 | K84: =I84-J84 -> 782405 | L84: =I84+Jan!L84 -> 3325567 | M84: =J84+Jan!M84 -> 2718455 | N84: =L84-M84 -> 607112
B85: =1+B84 -> 59 | C85: PAMI Global Bond Fund, Inc. | D85: 66237413 | E85: 15972138 | F85: =D85-E85 -> 50265275 | G85: 0 | H85: 27 | I85: 0 | J85: 0 | K85: =I85-J85 -> 0 | L85: =I85+Jan!L85 -> 0 | M85: =J85+Jan!M85 -> 0 | N85: =L85-M85 -> 0
B86: =1+B85 -> 60 | C86: Philam Dollar Bond Fund, Inc. | D86: 1858086797 | E86: 23837554 | F86: =D86-E86 -> 1834249243 | G86: 0 | H86: 1768 | I86: 50074 | J86: 41068055 | K86: =I86-J86 -> -41017981 | L86: =I86+Jan!L86 -> 161076 | M86: =J86+Jan!M86 -> 72963266 | N86: =L86-M86 -> -72802190
B87: =1+B86 -> 61 | C87: Philequity Dollar Income Fund, Inc. | D87: 2.3577048e+08 | E87: 1149123.3 | F87: =D87-E87 -> 2.3462135e+08 | G87: 0 | H87: 117 | I87: 151740 | J87: 0 | K87: =I87-J87 -> 151740 | L87: =I87+Jan!L87 -> 309310 | M87: =J87+Jan!M87 -> 0 | N87: =L87-M87 -> 309310
B88: =1+B87 -> 62 | C88: Sun Life Prosperity Dollar Abundance Fund, Inc. | D88: 622890662 | E88: 25405466 | F88: =D88-E88 -> 597485196 | G88: 0 | H88: 2603 | I88: 13037043 | J88: 3906128 | K88: =I88-J88 -> 9130915 | L88: =I88+Jan!L88 -> 24969170 | M88: =J88+Jan!M88 -> 7097498 | N88: =L88-M88 -> 17871672
A89: Sub total - US Currency | D89: =SUM(D82:D88) -> 16449659652 | E89: =SUM(E82:E88) -> 2.5985637e+08 | F89: =SUM(F82:F88) -> 16189803278 | G89: =SUM(G82:G88) -> 0 | H89: =SUM(H82:H88) -> 12638 | I89: =SUM(I82:I88) -> 47840590 | J89: =SUM(J82:J88) -> 1.141129e+08 | K89: =SUM(K82:K88) -> -66272312 | ... N89: =SUM(N82:N88) -> -189916893
B90: =1+B88 -> 63 | C90: ALFM Euro Bond Fund, Inc. | D90: 934959731 | E90: 7554725 | F90: =D90-E90 -> 927405006 | G90: 0 | H90: 605 | I90: 771221 | J90: 9326128 | K90: =I90-J90 -> -8554907 | L90: =I90+Jan!L90 -> 1201195 | M90: =J90+Jan!M90 -> 11855983 | N90: =L90-M90 -> -10654788
A91: Sub total - Euro Currency | D91: =SUM(D90) -> 934959731 | E91: =SUM(E90) -> 7554725 | F91: =SUM(F90) -> 927405006 | G91: =SUM(G90) -> 0 | H91: =SUM(H90) -> 605 | I91: =SUM(I90) -> 771221 | J91: =SUM(J90) -> 9326128 | K91: =SUM(K90) -> -8554907 | ... N91: =SUM(N90) -> -10654788
A92: Sub total - bond funds | D92: =D80+D89+D91 -> 67349720605 | E92: =E80+E89+E91 -> 6.4600184e+08 | F92: =F80+F89+F91 -> 66703718770 | G92: =G80+G89+G91 -> 0 | H92: =H80+H89+H91 -> 72714 | I92: =I80+I89+I91 -> 4.6331141e+08 | J92: =J80+J89+J91 -> 9.7109311e+08 | K92: =K80+K89+K91 -> -5.077817e+08 | ... N92: =N80+N89+N91 -> -9.8834082e+08
A93: Money Market Funds
A94: Primarily invested in Peso Securities (shares)
B95: 64 | C95: AIB Money Market Mutual Fund, Inc. * | D95: 1.7193041e+08 | E95: 223051.08 | F95: =D95-E95 -> 1.7170735e+08 | G95: 0 | H95: 36 | I95: 10544175 | J95: 0 | K95: =I95-J95 -> 10544175 | L95: =I95 -> 10544175 | M95: =J95 -> 0 | N95: =L95-M95 -> 10544175
B96: 65 | C96: ALFM Money Market Fund, Inc. | D96: 25782769078 | E96: 19361515 | F96: =D96-E96 -> 25763407563 | G96: 0 | H96: 25090 | I96: 349688 | J96: 642002091 | K96: =I96-J96 -> -641652403 | L96: =I96+Jan!L95 -> 699356 | M96: =J96+Jan!M95 -> 1316397559 | N96: =L96-M96 -> -1315698203
B97: =1+B96 -> 66 | C97: First Metro Save and Learn Money Market Fund, Inc. | D97: 3715455906 | E97: 22484107 | F97: =D97-E97 -> 3692971799 | G97: 0 | H97: 1014 | I97: 803863052 | J97: 50468832 | K97: =I97-J97 -> 753394220 | L97: =I97+Jan!L96 -> 1114068138 | M97: =J97+Jan!M96 -> 680270380 | N97: =L97-M97 -> 433797758
B98: =1+B97 -> 67 | C98: Sun Life Prosperity Peso Starter Fund, Inc. | D98: 18475495897 | E98: 118474880 | F98: =D98-E98 -> 18357021017 | G98: 0 | H98: 70354 | I98: 305731886 | J98: 1275856276 | K98: =I98-J98 -> -970124390 | L98: =I98+Jan!L97 -> 705224947 | M98: =J98+Jan!M97 -> 3203615458 | N98: =L98-M98 -> -2498390511
A99: Primarily invested in Peso Securities (units) | L99: =I99+Jan!L98 -> 0 | M99: =J99+Jan!M98 -> 0
B100: =1+B98 -> 68 | C100: ALFM Money Market Fund, Inc. | D100: 8693810949 | E100: 7157783 | F100: =D100-E100 -> 8686653166 | G100: 0 | H100: 15313 | I100: 1085526410 | J100: 847848531 | K100: =I100-J100 -> 237677879 | L100: =I100+Jan!L99 -> 2096532905 | M100: =J100+Jan!M99 -> 1650848922 | N100: =L100-M100 -> 445683983
A101: Sub total - Peso Currency | D101: =SUM(D95:D98)+D100 -> 56839462236 | E101: =SUM(E95:E98)+E100 -> 1.6770134e+08 | F101: =SUM(F95:F98)+F100 -> 56671760900 | G101: =SUM(G95:G98)+G100 -> 0 | H101: =SUM(H95:H98)+H100 -> 111807 | I101: =SUM(I95:I98)+I100 -> 2206015211 | J101: =SUM(J95:J98)+J100 -> 2816175730 | K101: =SUM(K95:K98)+K100 -> -610160519 | ... N101: =SUM(N95:N98)+N100 -> -2924062798
A102: Primarily invested in foreign currency securities (shares)
B103: =1+B100 -> 69 | C103: Sun Life Prosperity Dollar Starter Fund, Inc. | D103: 2388598544 | E103: 8134301 | F103: =D103-E103 -> 2380464243 | G103: 0 | H103: 3649 | I103: 209287424 | J103: 145329781 | K103: =I103-J103 -> 63957643 | L103: =I103+Jan!L102 -> 243576694 | M103: =J103+Jan!M102 -> 267598948 | N103: =L103-M103 -> -24022254
A104: Sub total - US Currency | D104: =SUM(D103) -> 2388598544 | E104: =SUM(E103) -> 8134301 | F104: =SUM(F103) -> 2380464243 | G104: =SUM(G103) -> 0 | H104: =SUM(H103) -> 3649 | I104: =SUM(I103) -> 209287424 | J104: =SUM(J103) -> 145329781 | K104: =SUM(K103) -> 63957643 | ... N104: =SUM(N103) -> -24022254
A105: Sub total - money market funds | D105: =D101+D104 -> 59228060780 | E105: =E101+E104 -> 1.7583564e+08 | F105: =F101+F104 -> 59052225143 | G105: =G101+G104 -> 0 | H105: =H101+H104 -> 115456 | I105: =I101+I104 -> 2415302635 | J105: =J101+J104 -> 2961505511 | K105: =K101+K104 -> -546202876 | ... N105: =N101+N104 -> -2948085052
...

Sheet Mar
A1: PHILIPPINE INVESTMENT FUNDS ASSOCIATION, INC.
A2: MUTUAL FUNDS STATISTICAL REPORT
A3: Month of March 2024
A4: (Amounts in Peso)
I5: F O R - T H E - M O N T H | L5: Y E A R - T O - D A T E
A6: Fund Category | C6: Fund Name | D6: ASSETS | E6: LIABILITIES | F6: NET ASSETS | G6: EQUITY INV. | H6: NO. OF A/C | I6: SALES | J6: REDEMPTIONS | K6: NET SALES | L6: TOTAL SALES | M6: TOTAL REDEMPTIONS | N6: TOTAL NET SALES
A7: Stock Funds
A8: Primarily invested in Peso Securities (shares)
B9: 1 | C9: ALFM Growth Fund, Inc. | D9: 4483880182 | E9: 24760270 | F9: =D9-E9 -> 4459119912 | G9: 4279876512 | H9: 6452 | I9: 4311324 | J9: 63633150 | K9: =I9-J9 -> -59321826 | L9: =I9+Feb!L9 -> 12121404 | M9: =J9+Feb!M9 -> 179591696 | N9: =L9-M9 -> -167470292
B10: =1+B9 -> 2 | C10: ATRAM Alpha Opportunity Fund, Inc. | D10: 8.0051861e+08 | E10: 257503.58 | F10: =D10-E10 -> 800261106 | G10: 7.5358229e+08 | H10: 4050 | I10: 1804163.6 | J10: 8684311.5 | K10: =I10-J10 -> -6880147.9 | L10: =I10+Feb!L10 -> 6444175.6 | M10: =J10+Feb!M10 -> 40030063 | N10: =L10-M10 -> -33585887
B11: =1+B10 -> 3 | C11: ATRAM Phil. Equity Opportunity Fund, Inc. | D11: 1.3586972e+09 | E11: 1237636 | F11: =D11-E11 -> 1357459559 | G11: 1.2486355e+09 | H11: 2711 | I11: 8349734.5 | J11: 58456640 | K11: =I11-J11 -> -50106905 | L11: =I11+Feb!L11 -> 32405637 | M11: =J11+Feb!M11 -> 1.0605813e+08 | N11: =L11-M11 -> -73652495
B12: =1+B11 -> 4 | C12: Climbs Share Capital Equity Investment Fund Corp. | D12: 4.0394648e+08 | E12: 7201648.5 | F12: =D12-E12 -> 3.9674483e+08 | G12: 2.3503542e+08 | H12: 1770 | I12: 8509497.4 | J12: 688828.72 | K12: =I12-J12 -> 7820668.7 | L12: =I12+Feb!L12 -> 51731163 | M12: =J12+Feb!M12 -> 8993502.6 | N12: =L12-M12 -> 42737661
B13: =1+B12 -> 5 | C13: First Metro Consumer Fund, Inc. | D13: 474934315 | E13: 1372196 | F13: =D13-E13 -> 473562119 | G13: 408743942 | H13: 1297 | I13: 235156 | J13: 1160298 | K13: =I13-J13 -> -925142 | L13: =I13+Feb!L13 -> 33210187 | M13: =J13+Feb!M13 -> 38209967 | N13: =L13-M13 -> -4999780
B14: =1+B13 -> 6 | C14: First Metro Save and Learn Equity Fund, Inc. | D14: 4107170056 | E14: 107166362 | F14: =D14-E14 -> 4000003694 | G14: 3953133772 | H14: 15221 | I14: 10570282 | J14: 75380451 | K14: =I14-J14 -> -64810169 | L14: =I14+Feb!L14 -> 281675971 | M14: =J14+Feb!M14 -> 892957534 | N14: =L14-M14 -> -611281563
B15: =1+B14 -> 7 | C15: First Metro Save and Learn Phil. Index Fund, Inc. | D15: 104824830 | E15: 368554 | F15: =D15-E15 -> 104456276 | G15: 102257134 | H15: 507 | I15: 312196 | J15: 962960 | K15: =I15-J15 -> -650764 | L15: =I15+Feb!L15 -> 927605 | M15: =J15+Feb!M15 -> 4349038 | N15: =L15-M15 -> -3421433
B16: =1+B15 -> 8 | C16: MBG Equity Investment Fund, Inc. | D16: 136476488 | E16: 818611 | F16: =D16-E16 -> 135657877 | G16: 120686665 | H16: 48 | I16: 20000000 | J16: 5282425 | K16: =I16-J16 -> 14717575 | L16: =I16+Feb!L16 -> 20000000 | M16: =J16+Feb!M16 -> 7228845 | N16: =L16-M16 -> 12771155
B17: =1+B16 -> 9 | C17: PAMI Equity Index Fund, Inc. | D17: 1255565234 | E17: 45895664 | F17: =D17-E17 -> 1209669570 | G17: 1231270634 | H17: 11530 | I17: 0 | J17: 7267094 | K17: =I17-J17 -> -7267094 | L17: =I17+Feb!L17 -> 0 | M17: =J17+Feb!M17 -> 49090605 | N17: =L17-M17 -> -49090605
B18: =1+B17 -> 10 | C18: Philam Strategic Growth Fund, Inc. | D18: 3660635386 | E18: 34638252 | F18: =D18-E18 -> 3625997134 | G18: 3479893417 | H18: 11434 | I18: 7092987 | J18: 45919508 | K18: =I18-J18 -> -38826521 | L18: =I18+Feb!L18 -> 19993946 | M18: =J18+Feb!M18 -> 110676574 | N18: =L18-M18 -> -90682628
B19: =1+B18 -> 11 | C19: Philequity Dividend Yield Fund, Inc. | D19: 2.3688486e+09 | E19: 6250197.9 | F19: =D19-E19 -> 2362598414 | G19: 2.1862566e+09 | H19: 4930 | I19: 4169868.2 | J19: 3629097.8 | K19: =I19-J19 -> 540770.4 | L19: =I19+Feb!L19 -> 6972694.4 | M19: =J19+Feb!M19 -> 12984234 | N19: =L19-M19 -> -6011540
B20: =1+B19 -> 12 | C20: Philequity Fund, Inc. | D20: 9.9454505e+09 | E20: 44508162 | F20: =D20-E20 -> 9900942311 | G20: 9.1746985e+09 | H20: 33793 | I20: 8475106.3 | J20: 48156529 | K20: =I20-J20 -> -39681422 | L20: =I20+Feb!L20 -> 28304353 | M20: =J20+Feb!M20 -> 1.5394055e+08 | N20: =L20-M20 -> -125636193
B21: =1+B20 -> 13 | C21: Philequity MSCI Phil. Index Fund, Inc. | D21: 3.3202565e+08 | E21: 769105.37 | F21: =D21-E21 -> 3.3125655e+08 | G21: 3.2467583e+08 | H21: 933 | I21: 218923.87 | J21: 3955790.4 | K21: =I21-J21 -> -3736866.5 | L21: =I21+Feb!L21 -> 1070648.7 | M21: =J21+Feb!M21 -> 5860074.7 | N21: =L21-M21 -> -4789425.9
... B27: =1+B26 -> 19 | C27: United Fund, Inc. | D27: 6.2017586e+08 | E27: 4592568.1 | F27: =D27-E27 -> 6.155833e+08 | G27: 5.3441245e+08 | H27: 1237 | I27: 1788635.6 | J27: 495371.89 | K27: =I27-J27 -> 1293263.7 | L27: =I27+Feb!L27 -> 2643364.8 | M27: =J27+Feb!M27 -> 4737923.6 | N27: =L27-M27 -> -2094558.8
A28: Primarily invested in Peso Securities (units)
B29: =1+B27 -> 20 | C29: COL Equity Index Unitized Mutual Fund, Inc. | D29: 2.3225626e+08 | E29: 1808934.6 | F29: =D29-E29 -> 2.3044733e+08 | G29: 2.2771641e+08 | H29: 3298 | I29: 5136368.2 | J29: 7889440.5 | K29: =I29-J29 -> -2753072.3 | L29: =I29+Feb!L29 -> 17952828 | M29: =J29+Feb!M29 -> 33265430 | N29: =L29-M29 -> -15312602
B30: =1+B29 -> 21 | C30: COL Strategic Growth Equity Unitized Mutual Fund, Inc. | D30: 2.5495943e+08 | E30: 1548984.6 | F30: =D30-E30 -> 2.5341044e+08 | G30: 1.4247344e+08 | H30: 2756 | I30: 19567449 | J30: 6717379.6 | K30: =I30-J30 -> 12850070 | L30: =I30+Feb!L30 -> 151943812 | M30: =J30+Feb!M30 -> 14908449 | N30: =L30-M30 -> 1.3703536e+08
B31: =1+B30 -> 22 | C31: Philequity Alpha One Fund, Inc. | D31: 3.1407579e+08 | E31: 2116146.9 | F31: =D31-E31 -> 3.1195964e+08 | G31: 2.7664281e+08 | H31: 1235 | I31: 433154.2 | J31: 1373893.6 | K31: =I31-J31 -> -940739.35 | L31: =I31+Feb!L31 -> 1935246.1 | M31: =J31+Feb!M31 -> 16390666 | N31: =L31-M31 -> -14455420
B32: =1+B31 -> 23 | C32: Philippine Stock Index Fund Corp. | D32: 634834115 | E32: 9852473 | F32: =D32-E32 -> 624981642 | G32: 618773532 | H32: 652918 | I32: 19301863 | J32: 31460608 | K32: =I32-J32 -> -12158745 | L32: =I32+Feb!L32 -> 50680961 | M32: =J32+Feb!M32 -> 88231403 | N32: =L32-M32 -> -37550442
A33: Exchange Traded Fund
B34: =1+B32 -> 24 | C34: First Metro Phil. Equity Exchange Traded Fund, Inc. | D34: 2237964469 | E34: 1890662 | F34: =D34-E34 -> 2236073807 | G34: 2211932497 | H34: 3209 | I34: 0 | J34: 27517230 | K34: =I34-J34 -> -27517230 | L34: =I34+Feb!L34 -> 8336295 | M34: =J34+Feb!M34 -> 77612359 | N34: =L34-M34 -> -69276064
A35: Sub total - Peso Currency | D35: =SUM(D9:D34) -> 67863075101 | E35: =SUM(E9:E34) -> 4.4184464e+08 | F35: =SUM(F9:F34) -> 67421230465 | G35: =SUM(G9:G34) -> 65138272502 | H35: =SUM(H9:H34) -> 934721 | I35: =SUM(I9:I34) -> 2.593522e+08 | J35: =SUM(J9:J34) -> 8.8743059e+08 | K35: =SUM(K9:K34) -> -628078395 | ... N35: =SUM(N9:N34) -> -2532958962
A36: Primarily invested in foreign currency securities (shares)
B37: =1+B34 -> 25 | C37: ATRAM AsiaPlus Equity Fund, Inc. | D37: 26205148 | E37: 60742.01 | F37: =D37-E37 -> 26144406 | G37: 24858777 | H37: 51 | I37: 33714.19 | J37: 21556.23 | K37: =I37-J37 -> 12157.96 | L37: =I37+Feb!L37 -> 306197.07 | M37: =J37+Feb!M37 -> 32765.65 | N37: =L37-M37 -> 273431.42
B38: =1+B37 -> 26 | C38: Sun Life Prosperity World Voyager Fund, Inc. | D38: 2111913039 | E38: 9289520 | F38: =D38-E38 -> 2102623519 | G38: 0 | H38: 2972 | I38: 10927273 | J38: 15841522 | K38: =I38-J38 -> -4914249 | L38: =I38+Feb!L38 -> 46105293 | M38: =J38+Feb!M38 -> 99198635 | N38: =L38-M38 -> -53093342
A39: Sub total - US Currency | D39: =SUM(D37:D38) -> 2138118187 | E39: =SUM(E37:E38) -> 9350262 | F39: =SUM(F37:F38) -> 2128767925 | G39: =SUM(G37:G38) -> 24858777 | H39: =SUM(H37:H38) -> 3023 | I39: =SUM(I37:I38) -> 10960987 | J39: =SUM(J37:J38) -> 15863078 | K39: =SUM(K37:K38) -> -4902091 | ... N39: =SUM(N37:N38) -> -52819911
A40: Sub total - stock funds | D40: =D35+D39 -> 70001193288 | E40: =E35+E39 -> 4.511949e+08 | F40: =F35+F39 -> 69549998390 | G40: =G35+G39 -> 65163131278 | H40: =H35+H39 -> 937744 | I40: =I35+I39 -> 2.7031319e+08 | J40: =J35+J39 -> 9.0329367e+08 | K40: =K35+K39 -> -6.3298049e+08 | ... N40: =N35+N39 -> -2585778872
A41: Balanced Funds
A42: Primarily invested in Peso Securities (shares)
B43: =1+B38 -> 27 | C43: ATRAM Philippine Balanced Fund, Inc. | D43: 4.641075e+08 | E43: 311279.24 | F43: =D43-E43 -> 4.6379622e+08 | G43: 2.7540604e+08 | H43: 2345 | I43: 576961.65 | J43: 5889286.7 | K43: =I43-J43 -> -5312325 | L43: =I43+Feb!L43 -> 2187096.9 | M43: =J43+Feb!M43 -> 24067463 | N43: =L43-M43 -> -21880366
B44: =1+B43 -> 28 | C44: ATRAM Unicapital Diversified Growth Fund, Inc. | D44: 1.1814101e+08 | E44: 13122.93 | F44: =D44-E44 -> 1.1812789e+08 | G44: 45273972 | H44: 697 | I44: 227512.69 | J44: 409061.65 | K44: =I44-J44 -> -181548.96 | L44: =I44+Feb!L44 -> 1010884.6 | M44: =J44+Feb!M44 -> 3341621.5 | N44: =L44-M44 -> -2330737
B45: =1+B44 -> 29 | C45: First Metro Save and Learn Balanced Fund, Inc. | D45: 839590805 | E45: 13763593 | F45: =D45-E45 -> 825827212 | G45: 532334445 | H45: 4350 | I45: 5797527 | J45: 51213538 | K45: =I45-J45 -> -45416011 | L45: =I45+Feb!L45 -> 8152871 | M45: =J45+Feb!M45 -> 168970942 | N45: =L45-M45 -> -160818071
B46: =1+B45 -> 30 | C46: First Metro Save and Learn F.O.C.C.U.S. Dynamic Fund, Inc. | D46: 315253466 | E46: 11789047 | F46: =D46-E46 -> 303464419 | G46: 277993113 | H46: 224 | I46: 7406721 | J46: 6420864 | K46: =I46-J46 -> 985857 | L46: =I46+Feb!L46 -> 87895884 | M46: =J46+Feb!M46 -> 90615655 | N46: =L46-M46 -> -2719771
B47: =1+B46 -> 31 | C47: NCM Mutual Fund of the Phils., Inc. | D47: 3.3270112e+08 | E47: 1554769.5 | F47: =D47-E47 -> 3.3114635e+08 | G47: 1.6774952e+08 | H47: 48 | I47: 0 | J47: 0 | K47: =I47-J47 -> 0 | L47: =I47+Feb!L47 -> 0 | M47: =J47+Feb!M47 -> 66119 | N47: =L47-M47 -> -66119
B48: =1+B47 -> 32 | C48: PAMI Horizon Fund, Inc. | D48: 526471179 | E48: 14620229 | F48: =D48-E48 -> 511850950 | G48: 257930300 | H48: 9845 | I48: 481722 | J48: 4057766 | K48: =I48-J48 -> -3576044 | L48: =I48+Feb!L48 -> 840754 | M48: =J48+Feb!M48 -> 14060454 | N48: =L48-M48 -> -13219700
B49: =1+B48 -> 33 | C49: Philam Fund, Inc. | D49: 2008867592 | E49: 18648328 | F49: =D49-E49 -> 1990219264 | G49: 987888654 | H49: 7691 | I49: 1405485 | J49: 30517471 | K49: =I49-J49 -> -29111986 | L49: =I49+Feb!L49 -> 7988766 | M49: =J49+Feb!M49 -> 68790883 | N49: =L49-M49 -> -60802117
B50: =1+B49 -> 34 | C50: Solidaritas Fund, Inc. | D50: 122870442 | E50: 161003 | F50: =D50-E50 -> 122709439 | G50: 60958220 | H50: 174 | I50: 0 | J50: 0 | K50: =I50-J50 -> 0 | L50: =I50+Feb!L50 -> 0 | M50: =J50+Feb!M50 -> 1858328 | N50: =L50-M50 -> -1858328
B51: =1+B50 -> 35 | C51: Sun Life Prosperity Balanced Fund, Inc. | D51: 6853654401 | E51: 38459788 | F51: =D51-E51 -> 6815194613 | G51: 4043192747 | H51: 54225 | I51: 24805188 | J51: 91940941 | K51: =I51-J51 -> -67135753 | L51: =I51+Feb!L51 -> 39378562 | M51: =J51+Feb!M51 -> 263293321 | N51: =L51-M51 -> -223914759
B52: =1+B51 -> 36 | C52: Sun Life Prosperity Dynamic Fund, Inc. | D52: 588295152 | E52: 2289820 | F52: =D52-E52 -> 586005332 | G52: 370847144 | H52: 5000 | I52: 0 | J52: 19212668 | K52: =I52-J52 -> -19212668 | L52: =I52+Feb!L52 -> 0 | M52: =J52+Feb!M52 -> 71250745 | N52: =L52-M52 -> -71250745
A53: Primarily invested in Peso Securities (units)
B54: =1+B52 -> 37 | C54: Sun Life Prosperity Achiever Fund 2028, Inc. | D54: 80170006 | E54: 306227 | F54: =D54-E54 -> 79863779 | G54: 20388360 | H54: 1171 | I54: 215789 | J54: 281422 | K54: =I54-J54 -> -65633 | L54: =I54+Feb!L54 -> 781254 | M54: =J54+Feb!M54 -> 689683 | N54: =L54-M54 -> 91571
B55: =1+B54 -> 38 | C55: Sun Life Prosperity Achiever Fund 2038, Inc. | D55: 58842027 | E55: 288526 | F55: =D55-E55 -> 58553501 | G55: 46089174 | H55: 467 | I55: 193006 | J55: 174527 | K55: =I55-J55 -> 18479 | L55: =I55+Feb!L55 -> 441023 | M55: =J55+Feb!M55 -> 224492 | N55: =L55-M55 -> 216531
B56: =1+B55 -> 39 | C56: Sun Life Prosperity Achiever Fund 2048, Inc. | D56: 49757025 | E56: 295304 | F56: =D56-E56 -> 49461721 | G56: 42251582 | H56: 217 | I56: 58223 | J56: 297627 | K56: =I56-J56 -> -239404 | L56: =I56+Feb!L56 -> 170323 | M56: =J56+Feb!M56 -> 382932 | N56: =L56-M56 -> -212609
A57: Sub total - Peso Currency | D57: =SUM(D43:D56) -> 12358721723 | E57: =SUM(E43:E56) -> 1.0250104e+08 | F57: =SUM(F43:F56) -> 12256220687 | G57: =SUM(G43:G56) -> 7128303275 | H57: =SUM(H42:H56) -> 86454 | I57: =SUM(I43:I56) -> 41168135 | J57: =SUM(J43:J56) -> 2.1041517e+08 | K57: =SUM(K43:K56) -> -169247037 | L57: =SUM(L43:L56) -> 1.4884742e+08 | M57: =SUM(M43:M56) -> 7.0761264e+08 | N57: =SUM(N43:N56) -> -5.5876522e+08
A58: Primarily invested in foreign currency securities (shares)
B59: =1+B56 -> 40 | C59: Cocolife Dollar Fund Builder, Inc. | D59: 72215306 | E59: 502761.42 | F59: =D59-E59 -> 71712544 | G59: 0 | H59: 50 | I59: 0 | J59: 0 | K59: =I59-J59 -> 0 | L59: =I59+Feb!L59 -> 84501.37 | M59: =J59+Feb!M59 -> 79493.21 | N59: =L59-M59 -> 5008.16
B60: =1+B59 -> 41 | C60: PAMI Asia Balanced Fund, Inc. | D60: 330482041 | E60: 31289778 | F60: =D60-E60 -> 299192263 | G60: 165843152 | H60: 235 | I60: 22403 | J60: 2737798 | K60: =I60-J60 -> -2715395 | L60: =I60+Feb!L60 -> 22403 | M60: =J60+Feb!M60 -> 9191835 | N60: =L60-M60 -> -9169432
B61: =1+B60 -> 42 | C61: Sun Life Prosperity Dollar Advantage Fund, Inc. | D61: 1428913522 | E61: 6682325 | F61: =D61-E61 -> 1422231197 | G61: 0 | H61: 4178 | I61: 4011681 | J61: 12033602 | K61: =I61-J61 -> -8021921 | L61: =I61+Feb!L61 -> 7373560 | M61: =J61+Feb!M61 -> 173689161 | N61: =L61-M61 -> -166315601
B62: =1+B61 -> 43 | C62: Sun Life Prosperity Dollar Wellspring Fund, Inc. | D62: 257724284 | E62: 706962 | F62: =D62-E62 -> 257017322 | G62: 0 | H62: 748 | I62: 583548 | J62: 4013493 | K62: =I62-J62 -> -3429945 | L62: =I62+Feb!L62 -> 4205533 | M62: =J62+Feb!M62 -> 8658267 | N62: =L62-M62 -> -4452734
A63: Sub total - US Currency | D63: =SUM(D59:D62) -> 2089335153 | E63: =SUM(E59:E62) -> 39181826 | F63: =SUM(F59:F62) -> 2050153326 | G63: =SUM(G59:G62) -> 165843152 | H63: =SUM(H59:H62) -> 5211 | I63: =SUM(I59:I62) -> 4617632 | J63: =SUM(J59:J62) -> 18784893 | K63: =SUM(K59:K62) -> -14167261 | ... N63: =SUM(N59:N62) -> -1.7993276e+08
A64: Sub total - balanced funds | D64: =D57+D63 -> 14448056876 | E64: =E57+E63 -> 1.4168286e+08 | F64: =F57+F63 -> 14306374013 | G64: =G57+G63 -> 7294146427 | H64: =H57+H63 -> 91665 | I64: =I57+I63 -> 45785767 | J64: =J57+J63 -> 2.2920007e+08 | K64: =K57+K63 -> -183414298 | ... N64: =N57+N63 -> -7.3869798e+08
A65: Bond Funds
A66: Primarily invested in Peso Securities (shares)
B67: =1+B62 -> 44 | C67: ALFM Peso Bond Fund, Inc. | D67: 36317013232 | E67: 213599815 | F67: =D67-E67 -> 36103413417 | G67: 0 | H67: 23440 | I67: 147595454 | J67: 361527860 | K67: =I67-J67 -> -213932406 | L67: =I67+Feb!L67 -> 491925876 | M67: =J67+Feb!M67 -> 1268195824 | N67: =L67-M67 -> -776269948
B68: =1+B67 -> 45 | C68: ATRAM Corporate Bond Fund, Inc. | D68: 3.739165e+08 | E68: 23676149 | F68: =D68-E68 -> 3.5024035e+08 | G68: 0 | H68: 999 | I68: 9365349.9 | J68: 27106533 | K68: =I68-J68 -> -17741183 | L68: =I68+Feb!L68 -> 13536578 | M68: =J68+Feb!M68 -> 97545382 | N68: =L68-M68 -> -84008805
B69: =1+B68 -> 46 | C69: Cocolife Fixed Income Fund, Inc. | D69: 9.0003173e+08 | E69: 13542925 | F69: =D69-E69 -> 8.864888e+08 | G69: 0 | H69: 1847 | I69: 9484268.4 | J69: 3753027.6 | K69: =I69-J69 -> 5731240.8 | L69: =I69+Feb!L69 -> 19552979 | M69: =J69+Feb!M69 -> 45967466 | N69: =L69-M69 -> -26414486
B70: =1+B69 -> 47 | C70: Ekklesia Mutual Fund, Inc. | D70: 187667942 | E70: 184705 | F70: =D70-E70 -> 187483237 | G70: 0 | H70: 157 | I70: 0 | J70: 7882193 | K70: =I70-J70 -> -7882193 | L70: =I70+Feb!L70 -> 0 | M70: =J70+Feb!M70 -> 9846674 | N70: =L70-M70 -> -9846674
B71: =1+B70 -> 48 | C71: First Metro Save and Learn Fixed Income Fund, Inc. | D71: 1283680158 | E71: 115419083 | F71: =D71-E71 -> 1168261075 | G71: 0 | H71: 1776 | I71: 3399461 | J71: 9751447 | K71: =I71-J71 -> -6351986 | L71: =I71+Feb!L71 -> 140091879 | M71: =J71+Feb!M71 -> 246644075 | N71: =L71-M71 -> -106552196
B72: =1+B71 -> 49 | C72: Philam Bond Fund, Inc. | D72: 1593490961 | E72: 25579364 | F72: =D72-E72 -> 1567911597 | G72: 0 | H72: 4802 | I72: 1354211 | J72: 9726676 | K72: =I72-J72 -> -8372465 | L72: =I72+Feb!L72 -> 8933988 | M72: =J72+Feb!M72 -> 47260645 | N72: =L72-M72 -> -38326657
B73: =1+B72 -> 50 | C73: Philam Managed Income Fund, Inc. | D73: 592247301 | E73: 9881211 | F73: =D73-E73 -> 582366090 | G73: 0 | H73: 445 | I73: 1470626 | J73: 4424320 | K73: =I73-J73 -> -2953694 | L73: =I73+Feb!L73 -> 3976039 | M73: =J73+Feb!M73 -> 11651818 | N73: =L73-M73 -> -7675779
B74: =1+B73 -> 51 | C74: Philequity Peso Bond Fund, Inc. | D74: 3.2779266e+08 | E74: 1331242.4 | F74: =D74-E74 -> 3.2646142e+08 | G74: 0 | H74: 4025 | I74: 610711 | J74: 881784.94 | K74: =I74-J74 -> -271073.94 | L74: =I74+Feb!L74 -> 1809523.6 | M74: =J74+Feb!M74 -> 3247246.7 | N74: =L74-M74 -> -1437723.1
B75: =1+B74 -> 52 | C75: Soldivo Bond Fund, Inc. | D75: 1.7843209e+09 | E75: 1.6149272e+08 | F75: =D75-E75 -> 1622828168 | G75: 0 | H75: 781 | I75: 50067537 | J75: 123858.65 | K75: =I75-J75 -> 49943678 | L75: =I75+Feb!L75 -> 103369387 | M75: =J75+Feb!M75 -> 4679599.8 | N75: =L75-M75 -> 98689787
B76: =1+B75 -> 53 | C76: Sun Life Prosperity Bond Fund, Inc. | D76: 5975776897 | E76: 30979828 | F76: =D76-E76 -> 5944797069 | G76: 0 | H76: 18407 | I76: 108832188 | J76: 84429162 | K76: =I76-J76 -> 24403026 | L76: =I76+Feb!L76 -> 317349277 | M76: =J76+Feb!M76 -> 329390990 | N76: =L76-M76 -> -12041713
B77: =1+B76 -> 54 | C77: Sun Life Prosperity GS Fund, Inc. | D77: 124367553 | E77: 471537 | F77: =D77-E77 -> 123896016 | G77: 0 | H77: 2781 | I77: 486927 | J77: 813194 | K77: =I77-J77 -> -326267 | L77: =I77+Feb!L77 -> 1541402 | M77: =J77+Feb!M77 -> 3179671 | N77: =L77-M77 -> -1638269
A78: Corporate Debt Vehicle (units)
B79: =1+B77 -> 55 | C79: ATRAM Unitized Corporate Debt Vehicle, Inc. | D79: 7.0742871e+08 | E79: 201070 | F79: =D79-E79 -> 7.0722764e+08 | G79: 0 | H79: 13 | I79: 0 | J79: 0 | K79: =I79-J79 -> 0 | L79: =I79+Feb!L79 -> 0 | M79: =J79+Feb!M79 -> 0 | N79: =L79-M79 -> 0
A80: Sub total - Peso Currency | D80: =SUM(D67:D79) -> 50167734536 | E80: =SUM(E67:E79) -> 596359654 | F80: =SUM(F67:F79) -> 49571374882 | G80: =SUM(G67:G79) -> 0 | H80: =SUM(H67:H79) -> 59473 | I80: =SUM(I67:I79) -> 332666733 | J80: =SUM(J67:J79) -> 5.1042006e+08 | K80: =SUM(K67:K79) -> -1.7775332e+08 | ... N80: =SUM(N67:N79) -> -9.6552246e+08
A81: Primarily invested in foreign currency securities (shares)
B82: =1+B79 -> 56 | C82: ALFM Dollar Bond Fund, Inc. | D82: 12798764943 | E82: 104955346 | F82: =D82-E82 -> 12693809597 | G82: 0 | H82: 7787 | I82: 18578808 | J82: 164294745 | K82: =I82-J82 -> -145715937 | L82: =I82+Feb!L82 -> 77072616 | M82: =J82+Feb!M82 -> 351873397 | N82: =L82-M82 -> -274800781
B83: =1+B82 -> 57 | C83: ATRAM Total Return Dollar Bond Fund, Inc. | D83: 2.1799079e+08 | E83: 1284406.3 | F83: =D83-E83 -> 2.1670638e+08 | G83: 0 | H83: 129 | I83: 0 | J83: 34666945 | K83: =I83-J83 -> -34666945 | L83: =I83+Feb!L83 -> 52817.71 | M83: =J83+Feb!M83 -> 41537716 | N83: =L83-M83 -> -41484898
B84: =1+B83 -> 58 | C84: First Metro Save and Learn Dollar Bond Fund, Inc. | D84: 443908991 | E84: 1022349 | F84: =D84-E84 -> 442886642 | G84: 0 | H84: 154 | I84: 668715 | J84: 1205744 | K84: =I84-J84 -> -537029 | L84: =I84+Feb!L84 -> 3994282 | M84: =J84+Feb!M84 -> 3924199 | N84: =L84-M84 -> 70083
B85: =1+B84 -> 59 | C85: PAMI Global Bond Fund, Inc. | D85: 65250460 | E85: 15727767 | F85: =D85-E85 -> 49522693 | G85: 0 | H85: 27 | I85: 0 | J85: 0 | K85: =I85-J85 -> 0 | L85: =I85+Feb!L85 -> 0 | M85: =J85+Feb!M85 -> 0 | N85: =L85-M85 -> 0
B86: =1+B85 -> 60 | C86: Philam Dollar Bond Fund, Inc. | D86: 1853406437 | E86: 10936335 | F86: =D86-E86 -> 1842470102 | G86: 0 | H86: 1762 | I86: 38974 | J86: 6682995 | K86: =I86-J86 -> -6644021 | L86: =I86+Feb!L86 -> 200050 | M86: =J86+Feb!M86 -> 79646261 | N86: =L86-M86 -> -79446211
B87: =1+B86 -> 61 | C87: Philequity Dollar Income Fund, Inc. | D87: 2.2923401e+08 | E87: 1382087 | F87: =D87-E87 -> 2.2785192e+08 | G87: 0 | H87: 113 | I87: 151848 | J87: 7723341.9 | K87: =I87-J87 -> -7571493.9 | L87: =I87+Feb!L87 -> 461158 | M87: =J87+Feb!M87 -> 7723341.9 | N87: =L87-M87 -> -7262183.9
B88: =1+B87 -> 62 | C88: Sun Life Prosperity Dollar Abundance Fund, Inc. | D88: 606889678 | E88: 3309036 | F88: =D88-E88 -> 603580642 | G88: 0 | H88: 2609 | I88: 3444551 | J88: 2407039 | K88: =I88-J88 -> 1037512 | L88: =I88+Feb!L88 -> 28413721 | M88: =J88+Feb!M88 -> 9504537 | N88: =L88-M88 -> 18909184
A89: Sub total - US Currency | D89: =SUM(D82:D88) -> 16215445308 | E89: =SUM(E82:E88) -> 1.3861733e+08 | F89: =SUM(F82:F88) -> 16076827982 | G89: =SUM(G82:G88) -> 0 | H89: =SUM(H82:H88) -> 12581 | I89: =SUM(I82:I88) -> 22882896 | J89: =SUM(J82:J88) -> 216980810 | K89: =SUM(K82:K88) -> -194097914 | ... N89: =SUM(N82:N88) -> -384014807
B90: =1+B88 -> 63 | C90: ALFM Euro Bond Fund, Inc. | D90: 936012633 | E90: 7023168 | F90: =D90-E90 -> 928989465 | G90: 0 | H90: 602 | I90: 994509 | J90: 1672187 | K90: =I90-J90 -> -677678 | L90: =I90+Feb!L90 -> 2195704 | M90: =J90+Feb!M90 -> 13528170 | N90: =L90-M90 -> -11332466
A91: Sub total - Euro Currency | D91: =SUM(D90) -> 936012633 | E91: =SUM(E90) -> 7023168 | F91: =SUM(F90) -> 928989465 | G91: =SUM(G90) -> 0 | H91: =SUM(H90) -> 602 | I91: =SUM(I90) -> 994509 | J91: =SUM(J90) -> 1672187 | K91: =SUM(K90) -> -677678 | ... N91: =SUM(N90) -> -11332466
A92: Sub total - bond funds | D92: =D80+D89+D91 -> 67319192477 | E92: =E80+E89+E91 -> 7.4200015e+08 | F92: =F80+F89+F91 -> 66577192329 | G92: =G80+G89+G91 -> 0 | H92: =H80+H89+H91 -> 72656 | I92: =I80+I89+I91 -> 356544138 | J92: =J80+J89+J91 -> 7.2907305e+08 | K92: =K80+K89+K91 -> -3.7252892e+08 | ... N92: =N80+N89+N91 -> -1360869736
A93: Money Market Funds
A94: Primarily invested in Peso Securities (shares)
B95: 64 | C95: AIB Money Market Mutual Fund, Inc. | D95: 1.7289832e+08 | E95: 273328.09 | F95: =D95-E95 -> 1.7262499e+08 | G95: 0 | H95: 46 | I95: 401800 | J95: 0 | K95: =I95-J95 -> 401800 | L95: =I95+Feb!L95 -> 10945975 | M95: =J95+Feb!M95 -> 0 | N95: =L95-M95 -> 10945975
B96: 65 | C96: ALFM Money Market Fund, Inc. | D96: 25356077569 | E96: 18539720 | F96: =D96-E96 -> 25337537849 | G96: 0 | H96: 24850 | I96: 328181 | J96: 513631827 | K96: =I96-J96 -> -513303646 | L96: =I96+Feb!L96 -> 1027537 | M96: =J96+Feb!M96 -> 1830029386 | N96: =L96-M96 -> -1829001849
B97: =1+B96 -> 66 | C97: First Metro Save and Learn Money Market Fund, Inc. | D97: 3602058301 | E97: 8559303 | F97: =D97-E97 -> 3593498998 | G97: 0 | H97: 1083 | I97: 291116044 | J97: 402278219 | K97: =I97-J97 -> -111162175 | L97: =I97+Feb!L97 -> 1405184182 | M97: =J97+Feb!M97 -> 1082548599 | N97: =L97-M97 -> 322635583
B98: =1+B97 -> 67 | C98: Sun Life Prosperity Peso Starter Fund, Inc. | D98: 18106128498 | E98: 81252797 | F98: =D98-E98 -> 18024875701 | G98: 0 | H98: 70501 | I98: 344356754 | J98: 724960773 | K98: =I98-J98 -> -380604019 | L98: =I98+Feb!L98 -> 1049581701 | M98: =J98+Feb!M98 -> 3928576231 | N98: =L98-M98 -> -2878994530
A99: Primarily invested in Peso Securities (units)
B100: =1+B98 -> 68 | C100: ALFM Money Market Fund, Inc. | D100: 8977753747 | E100: 7473607 | F100: =D100-E100 -> 8970280140 | G100: 0 | H100: 16233 | I100: 1150325985 | J100: 898976634 | K100: =I100-J100 -> 251349351 | L100: =I100+Feb!L100 -> 3246858890 | M100: =J100+Feb!M100 -> 2549825556 | N100: =L100-M100 -> 697033334
A101: Sub total - Peso Currency | D101: =SUM(D95:D98)+D100 -> 56214916437 | E101: =SUM(E95:E98)+E100 -> 1.1609876e+08 | F101: =SUM(F95:F98)+F100 -> 56098817682 | G101: =SUM(G95:G98)+G100 -> 0 | H101: =SUM(H95:H98)+H100 -> 112713 | I101: =SUM(I95:I98)+I100 -> 1786528764 | J101: =SUM(J95:J98)+J100 -> 2539847453 | K101: =SUM(K95:K98)+K100 -> -753318689 | ... N101: =SUM(N95:N98)+N100 -> -3677381487
A102: Primarily invested in foreign currency securities (shares)
B103: =1+B100 -> 69 | C103: Sun Life Prosperity Dollar Starter Fund, Inc. | D103: 2332435271 | E103: 10853237 | F103: =D103-E103 -> 2321582034 | G103: 0 | H103: 3665 | I103: 48688922 | J103: 117483668 | K103: =I103-J103 -> -68794746 | L103: =I103+Feb!L103 -> 292265616 | M103: =J103+Feb!M103 -> 385082616 | N103: =L103-M103 -> -92817000
A104: Sub total - US Currency | D104: =SUM(D103) -> 2332435271 | E104: =SUM(E103) -> 10853237 | F104: =SUM(F103) -> 2321582034 | G104: =SUM(G103) -> 0 | H104: =SUM(H103) -> 3665 | I104: =SUM(I103) -> 48688922 | J104: =SUM(J103) -> 117483668 | K104: =SUM(K103) -> -68794746 | ... N104: =SUM(N103) -> -92817000
A105: Sub total - money market funds | D105: =D101+D104 -> 58547351708 | E105: =E101+E104 -> 1.2695199e+08 | F105: =F101+F104 -> 58420399716 | G105: =G101+G104 -> 0 | H105: =H101+H104 -> 116378 | I105: =I101+I104 -> 1835217686 | J105: =J101+J104 -> 2657331121 | K105: =K101+K104 -> -822113435 | ... N105: =N101+N104 -> -3770198487
...

Sheet Q1
A1: PHILIPPINE INVESTMENT FUNDS ASSOCIATION, INC.
A2: MUTUAL FUNDS STATISTICAL REPORT
A3: As of the First Quarter of 2024
A4: (Amounts in Philippine Peso)
A6: Fund Category | C6: Fund Name | D6: NET ASSETS | E6: TOTAL SALES | F6: TOTAL REDEMPTIONS | G6: NET SALES
A7: Stock Funds
A8: Primarily invested in Peso Securities (shares)
B9: 1 | C9: ALFM Growth Fund, Inc. | D9: =Mar!F9 -> 4459119912 | E9: ='Jan UPDATED'!I9+Feb!I9+Mar!I9 -> 12121404 | F9: ='Jan UPDATED'!J9+Feb!J9+Mar!J9 -> 179591696 | G9: =E9-F9 -> -167470292
B10: =1+B9 -> 2 | C10: ATRAM Alpha Opportunity Fund, Inc. | D10: =Mar!F10 -> 800261106 | E10: ='Jan UPDATED'!I10+Feb!I10+Mar!I10 -> 6444175.6 | F10: ='Jan UPDATED'!J10+Feb!J10+Mar!J10 -> 40030063 | G10: =E10-F10 -> -33585887
B11: =1+B10 -> 3 | C11: ATRAM Phil. Equity Opportunity Fund, Inc. | D11: =Mar!F11 -> 1357459559 | E11: ='Jan UPDATED'!I11+Feb!I11+Mar!I11 -> 32405637 | F11: ='Jan UPDATED'!J11+Feb!J11+Mar!J11 -> 1.0605813e+08 | G11: =E11-F11 -> -73652495
B12: =1+B11 -> 4 | C12: Climbs Share Capital Equity Investment Fund Corp. | D12: =Mar!F12 -> 3.9674483e+08 | E12: ='Jan UPDATED'!I12+Feb!I12+Mar!I12 -> 51731163 | F12: ='Jan UPDATED'!J12+Feb!J12+Mar!J12 -> 8993502.6 | G12: =E12-F12 -> 42737661
B13: =1+B12 -> 5 | C13: First Metro Consumer Fund, Inc. | D13: =Mar!F13 -> 473562119 | E13: ='Jan UPDATED'!I13+Feb!I13+Mar!I13 -> 33210187 | F13: ='Jan UPDATED'!J13+Feb!J13+Mar!J13 -> 38209967 | G13: =E13-F13 -> -4999780
B14: =1+B13 -> 6 | C14: First Metro Save and Learn Equity Fund, Inc. | D14: =Mar!F14 -> 4000003694 | E14: ='Jan UPDATED'!I14+Feb!I14+Mar!I14 -> 281675971 | F14: ='Jan UPDATED'!J14+Feb!J14+Mar!J14 -> 892957534 | G14: =E14-F14 -> -611281563
B15: =1+B14 -> 7 | C15: First Metro Save and Learn Phil. Index Fund, Inc. | D15: =Mar!F15 -> 104456276 | E15: ='Jan UPDATED'!I15+Feb!I15+Mar!I15 -> 927605 | F15: ='Jan UPDATED'!J15+Feb!J15+Mar!J15 -> 4349038 | G15: =E15-F15 -> -3421433
B16: =1+B15 -> 8 | C16: MBG Equity Investment Fund, Inc. | D16: =Mar!F16 -> 135657877 | E16: ='Jan UPDATED'!I16+Feb!I16+Mar!I16 -> 20000000 | F16: ='Jan UPDATED'!J16+Feb!J16+Mar!J16 -> 7228845 | G16: =E16-F16 -> 12771155
B17: =1+B16 -> 9 | C17: PAMI Equity Index Fund, Inc. | D17: =Mar!F17 -> 1209669570 | E17: ='Jan UPDATED'!I17+Feb!I17+Mar!I17 -> 0 | F17: ='Jan UPDATED'!J17+Feb!J17+Mar!J17 -> 49090605 | G17: =E17-F17 -> -49090605
B18: =1+B17 -> 10 | C18: Philam Strategic Growth Fund, Inc. | D18: =Mar!F18 -> 3625997134 | E18: ='Jan UPDATED'!I18+Feb!I18+Mar!I18 -> 19993946 | F18: ='Jan UPDATED'!J18+Feb!J18+Mar!J18 -> 110676574 | G18: =E18-F18 -> -90682628
B19: =1+B18 -> 11 | C19: Philequity Dividend Yield Fund, Inc. | D19: =Mar!F19 -> 2362598414 | E19: ='Jan UPDATED'!I19+Feb!I19+Mar!I19 -> 6972694.4 | F19: ='Jan UPDATED'!J19+Feb!J19+Mar!J19 -> 12984234 | G19: =E19-F19 -> -6011540
B20: =1+B19 -> 12 | C20: Philequity Fund, Inc. | D20: =Mar!F20 -> 9900942311 | E20: ='Jan UPDATED'!I20+Feb!I20+Mar!I20 -> 28304353 | F20: ='Jan UPDATED'!J20+Feb!J20+Mar!J20 -> 1.5394055e+08 | G20: =E20-F20 -> -125636193
B21: =1+B20 -> 13 | C21: Philequity MSCI Phils. Index Fund, Inc. | D21: =Mar!F21 -> 3.3125655e+08 | E21: ='Jan UPDATED'!I21+Feb!I21+Mar!I21 -> 1070648.7 | F21: ='Jan UPDATED'!J21+Feb!J21+Mar!J21 -> 5860074.7 | G21: =E21-F21 -> -4789425.9
... B27: =1+B26 -> 19 | C27: United Fund, Inc. | D27: =Mar!F27 -> 6.155833e+08 | E27: ='Jan UPDATED'!I27+Feb!I27+Mar!I27 -> 2643364.8 | F27: ='Jan UPDATED'!J27+Feb!J27+Mar!J27 -> 4737923.6 | G27: =E27-F27 -> -2094558.8
A28: Primarily invested in Peso Securities (units) | D28: =Mar!F28 | E28: ='Jan UPDATED'!I28+Feb!I28+Mar!I28 -> 0 | F28: ='Jan UPDATED'!J28+Feb!J28+Mar!J28 -> 0
B29: =1+B27 -> 20 | C29: COL Equity Index Unitized Mutual Fund, Inc. | D29: =Mar!F29 -> 2.3044733e+08 | E29: ='Jan UPDATED'!I29+Feb!I29+Mar!I29 -> 17952828 | F29: ='Jan UPDATED'!J29+Feb!J29+Mar!J29 -> 33265430 | G29: =E29-F29 -> -15312602
B30: =1+B29 -> 21 | C30: COL Strategic Growth Equity Unitized Mutual Fund, Inc. | D30: =Mar!F30 -> 2.5341044e+08 | E30: ='Jan UPDATED'!I30+Feb!I30+Mar!I30 -> 151943812 | F30: ='Jan UPDATED'!J30+Feb!J30+Mar!J30 -> 14908449 | G30: =E30-F30 -> 1.3703536e+08
B31: =1+B30 -> 22 | C31: Philequity Alpha One Fund, Inc. | D31: =Mar!F31 -> 3.1195964e+08 | E31: ='Jan UPDATED'!I31+Feb!I31+Mar!I31 -> 1935246.1 | F31: ='Jan UPDATED'!J31+Feb!J31+Mar!J31 -> 16390666 | G31: =E31-F31 -> -14455420
B32: =1+B31 -> 23 | C32: Philippine Stock Index Fund Corp. | D32: =Mar!F32 -> 624981642 | E32: ='Jan UPDATED'!I32+Feb!I32+Mar!I32 -> 50680961 | F32: ='Jan UPDATED'!J32+Feb!J32+Mar!J32 -> 88231403 | G32: =E32-F32 -> -37550442
A33: Exchange Traded Fund | D33: =Mar!F33 | E33: ='Jan UPDATED'!I33+Feb!I33+Mar!I33 -> 0 | F33: ='Jan UPDATED'!J33+Feb!J33+Mar!J33 -> 0
B34: =1+B32 -> 24 | C34: First Metro Phil. Equity Exchange Traded Fund, Inc. | D34: =Mar!F34 -> 2236073807 | E34: ='Jan UPDATED'!I34+Feb!I34+Mar!I34 -> 8336295 | F34: ='Jan UPDATED'!J34+Feb!J34+Mar!J34 -> 77612359 | G34: =E34-F34 -> -69276064
A35: Sub total - Peso Currency | D35: =SUM(D9:D34) -> 67421230465 | E35: =SUM(E9:E34) -> 1057434248 | F35: =SUM(F9:F34) -> 3590393209 | G35: =SUM(G9:G34) -> -2532958962
A36: Primarily invested in foreign currency securities (shares)
B37: =1+B34 -> 25 | C37: ATRAM AsiaPlus Equity Fund, Inc. | D37: =Mar!F37 -> 26144406 | E37: ='Jan UPDATED'!I37+Feb!I37+Mar!I37 -> 306197.07 | F37: ='Jan UPDATED'!J37+Feb!J37+Mar!J37 -> 32765.65 | G37: =E37-F37 -> 273431.42
B38: =1+B37 -> 26 | C38: Sun Life Prosperity World Voyager Fund, Inc. | D38: =Mar!F38 -> 2102623519 | E38: ='Jan UPDATED'!I38+Feb!I38+Mar!I38 -> 46105293 | F38: ='Jan UPDATED'!J38+Feb!J38+Mar!J38 -> 99198635 | G38: =E38-F38 -> -53093342
A39: Sub total - US Currency | D39: =SUM(D37:D38) -> 2128767925 | E39: =SUM(E37:E38) -> 46411490 | F39: =SUM(F37:F38) -> 99231401 | G39: =SUM(G37:G38) -> -52819911
A40: Sub total - stock funds | D40: =D35+D39 -> 69549998390 | E40: =E35+E39 -> 1103845738 | F40: =F35+F39 -> 3689624610 | G40: =G35+G39 -> -2585778872
A41: Balanced Funds
A42: Primarily invested in Peso Securities (shares)
B43: =B38+1 -> 27 | C43: ATRAM Philippine Balanced Fund, Inc. | D43: =Mar!F43 -> 4.6379622e+08 | E43: ='Jan UPDATED'!I43+Feb!I43+Mar!I43 -> 2187096.9 | F43: ='Jan UPDATED'!J43+Feb!J43+Mar!J43 -> 24067463 | G43: =E43-F43 -> -21880366
B44: =B43+1 -> 28 | C44: ATRAM Unicapital Diversified Growth Fund, Inc. | D44: =Mar!F44 -> 1.1812789e+08 | E44: ='Jan UPDATED'!I44+Feb!I44+Mar!I44 -> 1010884.6 | F44: ='Jan UPDATED'!J44+Feb!J44+Mar!J44 -> 3341621.5 | G44: =E44-F44 -> -2330737
B45: =B44+1 -> 29 | C45: First Metro Save and Learn Balanced Fund, Inc. | D45: =Mar!F45 -> 825827212 | E45: ='Jan UPDATED'!I45+Feb!I45+Mar!I45 -> 8152871 | F45: ='Jan UPDATED'!J45+Feb!J45+Mar!J45 -> 168970942 | G45: =E45-F45 -> -160818071
B46: =B45+1 -> 30 | C46: First Metro Save and Learn F.O.C.C.U.S. Dynamic Fund, Inc. | D46: =Mar!F46 -> 303464419 | E46: ='Jan UPDATED'!I46+Feb!I46+Mar!I46 -> 87895884 | F46: ='Jan UPDATED'!J46+Feb!J46+Mar!J46 -> 90615655 | G46: =E46-F46 -> -2719771
B47: =B46+1 -> 31 | C47: NCM Mutual Fund of the Phils., Inc. | D47: =Mar!F47 -> 3.3114635e+08 | E47: ='Jan UPDATED'!I47+Feb!I47+Mar!I47 -> 0 | F47: ='Jan UPDATED'!J47+Feb!J47+Mar!J47 -> 66119 | G47: =E47-F47 -> -66119
B48: =B47+1 -> 32 | C48: PAMI Horizon Fund, Inc. | D48: =Mar!F48 -> 511850950 | E48: ='Jan UPDATED'!I48+Feb!I48+Mar!I48 -> 840754 | F48: ='Jan UPDATED'!J48+Feb!J48+Mar!J48 -> 14060454 | G48: =E48-F48 -> -13219700
B49: =B48+1 -> 33 | C49: Philam Fund, Inc. | D49: =Mar!F49 -> 1990219264 | E49: ='Jan UPDATED'!I49+Feb!I49+Mar!I49 -> 7988766 | F49: ='Jan UPDATED'!J49+Feb!J49+Mar!J49 -> 68790883 | G49: =E49-F49 -> -60802117
B50: =B49+1 -> 34 | C50: Solidaritas Fund, Inc. | D50: =Mar!F50 -> 122709439 | E50: ='Jan UPDATED'!I50+Feb!I50+Mar!I50 -> 0 | F50: ='Jan UPDATED'!J50+Feb!J50+Mar!J50 -> 1858328 | G50: =E50-F50 -> -1858328
B51: =B50+1 -> 35 | C51: Sun Life Prosperity Balanced Fund, Inc. | D51: =Mar!F51 -> 6815194613 | E51: ='Jan UPDATED'!I51+Feb!I51+Mar!I51 -> 39378562 | F51: ='Jan UPDATED'!J51+Feb!J51+Mar!J51 -> 263293321 | G51: =E51-F51 -> -223914759
B52: =B51+1 -> 36 | C52: Sun Life Prosperity Dynamic Fund, Inc. | D52: =Mar!F52 -> 586005332 | E52: ='Jan UPDATED'!I52+Feb!I52+Mar!I52 -> 0 | F52: ='Jan UPDATED'!J52+Feb!J52+Mar!J52 -> 71250745 | G52: =E52-F52 -> -71250745
A53: Primarily invested in Peso Securities (units)
B54: =1+B52 -> 37 | C54: Sun Life Prosperity Achiever Fund 2028, Inc. | D54: =Mar!F54 -> 79863779 | E54: ='Jan UPDATED'!I54+Feb!I54+Mar!I54 -> 781254 | F54: ='Jan UPDATED'!J54+Feb!J54+Mar!J54 -> 689683 | G54: =E54-F54 -> 91571
B55: =1+B54 -> 38 | C55: Sun Life Prosperity Achiever Fund 2038, Inc. | D55: =Mar!F55 -> 58553501 | E55: ='Jan UPDATED'!I55+Feb!I55+Mar!I55 -> 441023 | F55: ='Jan UPDATED'!J55+Feb!J55+Mar!J55 -> 224492 | G55: =E55-F55 -> 216531
B56: =1+B55 -> 39 | C56: Sun Life Prosperity Achiever Fund 2048, Inc. | D56: =Mar!F56 -> 49461721 | E56: ='Jan UPDATED'!I56+Feb!I56+Mar!I56 -> 170323 | F56: ='Jan UPDATED'!J56+Feb!J56+Mar!J56 -> 382932 | G56: =E56-F56 -> -212609
A57: Sub total - Peso Currency | D57: =SUM(D43:D56) -> 12256220687 | E57: =SUM(E43:E56) -> 1.4884742e+08 | F57: =SUM(F43:F56) -> 7.0761264e+08 | G57: =SUM(G43:G56) -> -5.5876522e+08
A58: Primarily invested in foreign currency securities (shares)
B59: =1+B56 -> 40 | C59: Cocolife Dollar Fund Builder, Inc. | D59: =Mar!F59 -> 71712544 | E59: ='Jan UPDATED'!I59+Feb!I59+Mar!I59 -> 84501.37 | F59: ='Jan UPDATED'!J59+Feb!J59+Mar!J59 -> 79493.21 | G59: =E59-F59 -> 5008.16
B60: =1+B59 -> 41 | C60: PAMI Asia Balanced Fund, Inc. | D60: =Mar!F60 -> 299192263 | E60: ='Jan UPDATED'!I60+Feb!I60+Mar!I60 -> 22403 | F60: ='Jan UPDATED'!J60+Feb!J60+Mar!J60 -> 9191835 | G60: =E60-F60 -> -9169432
B61: =1+B60 -> 42 | C61: Sun Life Prosperity Dollar Advantage Fund, Inc. | D61: =Mar!F61 -> 1422231197 | E61: ='Jan UPDATED'!I61+Feb!I61+Mar!I61 -> 7373560 | F61: ='Jan UPDATED'!J61+Feb!J61+Mar!J61 -> 173689161 | G61: =E61-F61 -> -166315601
B62: =1+B61 -> 43 | C62: Sun Life Prosperity Dollar Wellspring Fund, Inc. | D62: =Mar!F62 -> 257017322 | E62: ='Jan UPDATED'!I62+Feb!I62+Mar!I62 -> 4205533 | F62: ='Jan UPDATED'!J62+Feb!J62+Mar!J62 -> 8658267 | G62: =E62-F62 -> -4452734
A63: Sub total - US Currency | D63: =SUM(D59:D62) -> 2050153326 | E63: =SUM(E59:E62) -> 11685997 | F63: =SUM(F59:F62) -> 1.9161876e+08 | G63: =SUM(G59:G62) -> -1.7993276e+08
A64: Sub total - balanced funds | D64: =D57+D63 -> 14306374013 | E64: =E57+E63 -> 1.6053342e+08 | F64: =F57+F63 -> 8.9923139e+08 | G64: =G57+G63 -> -7.3869798e+08
A65: Bond Funds
A66: Primarily invested in Peso Securities (shares)
B67: =1+B62 -> 44 | C67: ALFM Peso Bond Fund, Inc. | D67: =Mar!F67 -> 36103413417 | E67: ='Jan UPDATED'!I67+Feb!I67+Mar!I67 -> 491925876 | F67: ='Jan UPDATED'!J67+Feb!J67+Mar!J67 -> 1268195824 | G67: =E67-F67 -> -776269948
B68: =1+B67 -> 45 | C68: ATRAM Corporate Bond Fund, Inc. | D68: =Mar!F68 -> 3.5024035e+08 | E68: ='Jan UPDATED'!I68+Feb!I68+Mar!I68 -> 13536578 | F68: ='Jan UPDATED'!J68+Feb!J68+Mar!J68 -> 97545382 | G68: =E68-F68 -> -84008805
B69: =1+B68 -> 46 | C69: Cocolife Fixed Income Fund, Inc. | D69: =Mar!F69 -> 8.864888e+08 | E69: ='Jan UPDATED'!I69+Feb!I69+Mar!I69 -> 19552979 | F69: ='Jan UPDATED'!J69+Feb!J69+Mar!J69 -> 45967466 | G69: =E69-F69 -> -26414486
B70: =1+B69 -> 47 | C70: Ekklesia Mutual Fund, Inc. | D70: =Mar!F70 -> 187483237 | E70: ='Jan UPDATED'!I70+Feb!I70+Mar!I70 -> 0 | F70: ='Jan UPDATED'!J70+Feb!J70+Mar!J70 -> 9846674 | G70: =E70-F70 -> -9846674
B71: =1+B70 -> 48 | C71: First Metro Save and Learn Fixed Income Fund, Inc. | D71: =Mar!F71 -> 1168261075 | E71: ='Jan UPDATED'!I71+Feb!I71+Mar!I71 -> 140091879 | F71: ='Jan UPDATED'!J71+Feb!J71+Mar!J71 -> 246644075 | G71: =E71-F71 -> -106552196
B72: =1+B71 -> 49 | C72: Philam Bond Fund, Inc. | D72: =Mar!F72 -> 1567911597 | E72: ='Jan UPDATED'!I72+Feb!I72+Mar!I72 -> 8933988 | F72: ='Jan UPDATED'!J72+Feb!J72+Mar!J72 -> 47260645 | G72: =E72-F72 -> -38326657
B73: =1+B72 -> 50 | C73: Philam Managed Income Fund, Inc. | D73: =Mar!F73 -> 582366090 | E73: ='Jan UPDATED'!I73+Feb!I73+Mar!I73 -> 3976039 | F73: ='Jan UPDATED'!J73+Feb!J73+Mar!J73 -> 11651818 | G73: =E73-F73 -> -7675779
B74: =1+B73 -> 51 | C74: Philequity Peso Bond Fund, Inc. | D74: =Mar!F74 -> 3.2646142e+08 | E74: ='Jan UPDATED'!I74+Feb!I74+Mar!I74 -> 1809523.6 | F74: ='Jan UPDATED'!J74+Feb!J74+Mar!J74 -> 3247246.7 | G74: =E74-F74 -> -1437723.1
B75: =1+B74 -> 52 | C75: Soldivo Bond Fund, Inc. | D75: =Mar!F75 -> 1622828168 | E75: ='Jan UPDATED'!I75+Feb!I75+Mar!I75 -> 103369387 | F75: ='Jan UPDATED'!J75+Feb!J75+Mar!J75 -> 4679599.8 | G75: =E75-F75 -> 98689787
B76: =1+B75 -> 53 | C76: Sun Life Prosperity Bond Fund, Inc. | D76: =Mar!F76 -> 5944797069 | E76: ='Jan UPDATED'!I76+Feb!I76+Mar!I76 -> 317349277 | F76: ='Jan UPDATED'!J76+Feb!J76+Mar!J76 -> 329390990 | G76: =E76-F76 -> -12041713
B77: =1+B76 -> 54 | C77: Sun Life Prosperity GS Fund, Inc. | D77: =Mar!F77 -> 123896016 | E77: ='Jan UPDATED'!I77+Feb!I77+Mar!I77 -> 1541402 | F77: ='Jan UPDATED'!J77+Feb!J77+Mar!J77 -> 3179671 | G77: =E77-F77 -> -1638269
A78: Corporat e Debt Vehicle (units) | D78: =Mar!F78
B79: =1+B77 -> 55 | C79: ATRAM Unitized Corporate Debt Vehicle, Inc. | D79: =Mar!F79 -> 7.0722764e+08 | E79: ='Jan UPDATED'!I79+Feb!I79+Mar!I79 -> 0 | F79: ='Jan UPDATED'!J79+Feb!J79+Mar!J79 -> 0 | G79: =E79-F79 -> 0
A80: Sub total - Peso Currency | D80: =SUM(D67:D79) -> 49571374882 | E80: =SUM(E67:E79) -> 1102086929 | F80: =SUM(F67:F79) -> 2067609392 | G80: =SUM(G67:G79) -> -9.6552246e+08
A81: Primarily invested in foreign currency securities (shares)
B82: =1+B79 -> 56 | C82: ALFM Dollar Bond Fund, Inc. | D82: =Mar!F82 -> 12693809597 | E82: ='Jan UPDATED'!I82+Feb!I82+Mar!I82 -> 77072616 | F82: ='Jan UPDATED'!J82+Feb!J82+Mar!J82 -> 351873397 | G82: =E82-F82 -> -274800781
B83: =1+B82 -> 57 | C83: ATRAM Total Return Dollar Bond Fund, Inc. | D83: =Mar!F83 -> 2.1670638e+08 | E83: ='Jan UPDATED'!I83+Feb!I83+Mar!I83 -> 52817.71 | F83: ='Jan UPDATED'!J83+Feb!J83+Mar!J83 -> 41537716 | G83: =E83-F83 -> -41484898
B84: =1+B83 -> 58 | C84: First Metro Save and Learn Dollar Bond Fund, Inc. | D84: =Mar!F84 -> 442886642 | E84: ='Jan UPDATED'!I84+Feb!I84+Mar!I84 -> 3994282 | F84: ='Jan UPDATED'!J84+Feb!J84+Mar!J84 -> 3924199 | G84: =E84-F84 -> 70083
B85: =1+B84 -> 59 | C85: PAMI Global Bond Fund Phils., Inc. | D85: =Mar!F85 -> 49522693 | E85: ='Jan UPDATED'!I85+Feb!I85+Mar!I85 -> 0 | F85: ='Jan UPDATED'!J85+Feb!J85+Mar!J85 -> 0 | G85: =E85-F85 -> 0
B86: =1+B85 -> 60 | C86: Philam Dollar Bond Fund, Inc. | D86: =Mar!F86 -> 1842470102 | E86: ='Jan UPDATED'!I86+Feb!I86+Mar!I86 -> 200050 | F86: ='Jan UPDATED'!J86+Feb!J86+Mar!J86 -> 79646261 | G86: =E86-F86 -> -79446211
B87: =1+B86 -> 61 | C87: Philequity Dollar Income Fund, Inc. | D87: =Mar!F87 -> 2.2785192e+08 | E87: ='Jan UPDATED'!I87+Feb!I87+Mar!I87 -> 461158 | F87: ='Jan UPDATED'!J87+Feb!J87+Mar!J87 -> 7723341.9 | G87: =E87-F87 -> -7262183.9
B88: =1+B87 -> 62 | C88: Sun Life Prosperity Dollar Abundance Fund, Inc. | D88: =Mar!F88 -> 603580642 | E88: ='Jan UPDATED'!I88+Feb!I88+Mar!I88 -> 28413721 | F88: ='Jan UPDATED'!J88+Feb!J88+Mar!J88 -> 9504537 | G88: =E88-F88 -> 18909184
A89: Sub total - US Currency | D89: =SUM(D82:D88) -> 16076827982 | E89: =SUM(E82:E88) -> 1.1019464e+08 | F89: =SUM(F82:F88) -> 4.9420945e+08 | G89: =SUM(G82:G88) -> -384014807
B90: =1+B88 -> 63 | C90: ALFM Euro Bond Fund, Inc. | D90: =Mar!F90 -> 928989465 | E90: ='Jan UPDATED'!I90+Feb!I90+Mar!I90 -> 2195704 | F90: ='Jan UPDATED'!J90+Feb!J90+Mar!J90 -> 13528170 | G90: =E90-F90 -> -11332466
A91: Sub total - Euro Currency | D91: =SUM(D90) -> 928989465 | E91: =SUM(E90) -> 2195704 | F91: =SUM(F90) -> 13528170 | G91: =SUM(G90) -> -11332466
A92: Sub total - bond funds | D92: =D80+D89+D91 -> 66577192329 | E92: =E80+E89+E91 -> 1214477277 | F92: =F80+F89+F91 -> 2575347013 | G92: =G80+G89+G91 -> -1360869736
A93: Money Market Funds
A94: Primarily invested in Peso Securities (shares)
B95: =B90+1 -> 64 | C95: AIB Money Market Mutual Fund, Inc. * | D95: =Mar!F95 -> 1.7262499e+08 | E95: =Feb!I95+Mar!I95 -> 10945975 | F95: =Feb!J95+Mar!J95 -> 0 | G95: =E95-F95 -> 10945975
B96: =1+B95 -> 65 | C96: ALFM Money Market Fund, Inc. | D96: =Mar!F96 -> 25337537849 | E96: ='Jan UPDATED'!I95+Feb!I96+Mar!I96 -> 1027537 | F96: ='Jan UPDATED'!J95+Feb!J96+Mar!J96 -> 1830029386 | G96: =E96-F96 -> -1829001849
B97: =1+B96 -> 66 | C97: First Metro Save and Learn Money Market Fund, Inc. | D97: =Mar!F97 -> 3593498998 | E97: ='Jan UPDATED'!I96+Feb!I97+Mar!I97 -> 1405184182 | F97: ='Jan UPDATED'!J96+Feb!J97+Mar!J97 -> 1082548599 | G97: =E97-F97 -> 322635583
B98: =1+B97 -> 67 | C98: Sun Life Prosperity Peso Starter Fund, Inc. | D98: =Mar!F98 -> 18024875701 | E98: ='Jan UPDATED'!I97+Feb!I98+Mar!I98 -> 1049581701 | F98: ='Jan UPDATED'!J97+Feb!J98+Mar!J98 -> 3928576231 | G98: =E98-F98 -> -2878994530
A99: Primarily invested in Peso Securities (units) | D99: =Mar!F99 | E99: ='Jan UPDATED'!I98+Feb!I99+Mar!I99 -> 0 | F99: ='Jan UPDATED'!J98+Feb!J99+Mar!J99 -> 0
B100: =1+B98 -> 68 | C100: ALFM Money Market Fund, Inc. | D100: =Mar!F100 -> 8970280140 | E100: ='Jan UPDATED'!I99+Feb!I100+Mar!I100 -> 3246858890 | F100: ='Jan UPDATED'!J99+Feb!J100+Mar!J100 -> 2549825556 | G100: =E100-F100 -> 697033334
A101: Sub total - Peso Currency | D101: =SUM(D95:D100) -> 56098817682 | E101: =SUM(E95:E100) -> 5713598285 | F101: =SUM(F95:F100) -> 9390979772 | G101: =SUM(G95:G100) -> -3677381487
A102: Primarily invested in foreign currency securities (shares)
B103: =1+B100 -> 69 | C103: Sun Life Prosperity Dollar Starter Fund, Inc. | D103: =Mar!F103 -> 2321582034 | E103: ='Jan UPDATED'!I102+Feb!I103+Mar!I103 -> 292265616 | F103: ='Jan UPDATED'!J102+Feb!J103+Mar!J103 -> 385082616 | G103: =E103-F103 -> -92817000
A104: Sub total - US Currency | D104: =SUM(D103) -> 2321582034 | E104: =SUM(E103) -> 292265616 | F104: =SUM(F103) -> 385082616 | G104: =SUM(G103) -> -92817000
A105: Sub total - money market funds | D105: =D101+D104 -> 58420399716 | E105: =E101+E104 -> 6005863901 | F105: =F101+F104 -> 9776062388 | G105: =G101+G104 -> -3770198487
A106: Feeder Fund
...

Sheet Apr
A1: PHILIPPINE INVESTMENT FUNDS ASSOCIATION, INC.
A2: MUTUAL FUNDS STATISTICAL REPORT
A3: Month of April 2024
A4: (Amounts in Peso)
I5: F O R - T H E - M O N T H | L5: Y E A R - T O - D A T E
A6: Fund Category | C6: Fund Name | D6: ASSETS | E6: LIABILITIES | F6: NET ASSETS | G6: EQUITY INV. | H6: NO. OF A/C | I6: SALES | J6: REDEMPTIONS | K6: NET SALES | L6: TOTAL SALES | M6: TOTAL REDEMPTIONS | N6: TOTAL NET SALES
A7: Stock Funds
A8: Primarily invested in Peso Securities (shares)
B9: 1 | C9: ALFM Growth Fund, Inc. | D9: 4324706938 | E9: 12765826 | F9: =D9-E9 -> 4311941112 | G9: 4143331275 | H9: 6398 | I9: 4855576 | J9: 31743228 | K9: =I9-J9 -> -26887652 | L9: =I9+Mar!L9 -> 16976980 | M9: =J9+Mar!M9 -> 211334924 | N9: =L9-M9 -> -194357944
B10: =1+B9 -> 2 | C10: ATRAM Alpha Opportunity Fund, Inc. | D10: 7.8367735e+08 | E10: 210890.79 | F10: =D10-E10 -> 7.8346645e+08 | G10: 7.218737e+08 | H10: 4026 | I10: 3611881.2 | J10: 10167385 | K10: =I10-J10 -> -6555503.4 | L10: =I10+Mar!L10 -> 10056057 | M10: =J10+Mar!M10 -> 50197448 | N10: =L10-M10 -> -40141391
B11: =1+B10 -> 3 | C11: ATRAM Phil. Equity Opportunity Fund, Inc. | D11: 1.3066175e+09 | E11: 946676.02 | F11: =D11-E11 -> 1305670840 | G11: 1.2290593e+09 | H11: 2642 | I11: 6216093.7 | J11: 24945078 | K11: =I11-J11 -> -18728984 | L11: =I11+Mar!L11 -> 38621730 | M11: =J11+Mar!M11 -> 1.3100321e+08 | N11: =L11-M11 -> -92381479
B12: =1+B11 -> 4 | C12: Climbs Share Capital Equity Investment Fund Corp. | D12: 4.1801023e+08 | E12: 6948729.3 | F12: =D12-E12 -> 4.110615e+08 | G12: 3.1772831e+08 | H12: 1760 | I12: 15652857 | J12: 281371.09 | K12: =I12-J12 -> 15371486 | L12: =I12+Mar!L12 -> 67384020 | M12: =J12+Mar!M12 -> 9274873.7 | N12: =L12-M12 -> 58109147
B13: =1+B12 -> 5 | C13: First Metro Consumer Fund, Inc. | D13: 457811351 | E13: 4280116 | F13: =D13-E13 -> 453531235 | G13: 306615119 | H13: 1287 | I13: 31139718 | J13: 35560063 | K13: =I13-J13 -> -4420345 | L13: =I13+Mar!L13 -> 64349905 | M13: =J13+Mar!M13 -> 73770030 | N13: =L13-M13 -> -9420125
B14: =1+B13 -> 6 | C14: First Metro Save and Learn Equity Fund, Inc. | D14: 3832512626 | E14: 78179127 | F14: =D14-E14 -> 3754333499 | G14: 3110046771 | H14: 15133 | I14: 274892935 | J14: 371014043 | K14: =I14-J14 -> -96121108 | L14: =I14+Mar!L14 -> 556568906 | M14: =J14+Mar!M14 -> 1263971577 | N14: =L14-M14 -> -707402671
B15: =1+B14 -> 7 | C15: First Metro Save and Learn Phil. Index Fund, Inc. | D15: 101873353 | E15: 401213 | F15: =D15-E15 -> 101472140 | G15: 99243234 | H15: 506 | I15: 510069 | J15: 493714 | K15: =I15-J15 -> 16355 | L15: =I15+Mar!L15 -> 1437674 | M15: =J15+Mar!M15 -> 4842752 | N15: =L15-M15 -> -3405078
B16: =1+B15 -> 8 | C16: MBG Equity Investment Fund, Inc. | D16: 136784852 | E16: 1540683 | F16: =D16-E16 -> 135244169 | G16: 117944390 | H16: 47 | I16: 3000000 | J16: 313773 | K16: =I16-J16 -> 2686227 | L16: =I16+Mar!L16 -> 23000000 | M16: =J16+Mar!M16 -> 7542618 | N16: =L16-M16 -> 15457382
B17: =1+B16 -> 9 | C17: PAMI Equity Index Fund, Inc. | D17: 1195857998 | E17: 27005919 | F17: =D17-E17 -> 1168852079 | G17: 1178726225 | H17: 11490 | I17: 0 | J17: 7726419 | K17: =I17-J17 -> -7726419 | L17: =I17+Mar!L17 -> 0 | M17: =J17+Mar!M17 -> 56817024 | N17: =L17-M17 -> -56817024
B18: =1+B17 -> 10 | C18: Philam Strategic Growth Fund, Inc. | D18: 3528769287 | E18: 31061967 | F18: =D18-E18 -> 3497707320 | G18: 3374100919 | H18: 11384 | I18: 7501654 | J18: 34851344 | K18: =I18-J18 -> -27349690 | L18: =I18+Mar!L18 -> 27495600 | M18: =J18+Mar!M18 -> 145527918 | N18: =L18-M18 -> -118032318
B19: =1+B18 -> 11 | C19: Philequity Dividend Yield Fund, Inc. | D19: 2.3636668e+09 | E19: 6495743.1 | F19: =D19-E19 -> 2357171034 | G19: 2.1320997e+09 | H19: 4897 | I19: 4854076 | J19: 7765123.8 | K19: =I19-J19 -> -2911047.7 | L19: =I19+Mar!L19 -> 11826770 | M19: =J19+Mar!M19 -> 20749358 | N19: =L19-M19 -> -8922587.8
B20: =1+B19 -> 12 | C20: Philequity Fund, Inc. | D20: 9.6400033e+09 | E20: 39896435 | F20: =D20-E20 -> 9600106884 | G20: 8.7087155e+09 | H20: 33629 | I20: 11819125 | J20: 43435134 | K20: =I20-J20 -> -31616009 | L20: =I20+Mar!L20 -> 40123478 | M20: =J20+Mar!M20 -> 1.9737568e+08 | N20: =L20-M20 -> -1.572522e+08
B21: =1+B20 -> 13 | C21: Philequity MSCI Phil. Index Fund, Inc. | D21: 3.2150242e+08 | E21: 748479.42 | F21: =D21-E21 -> 3.2075394e+08 | G21: 3.1420374e+08 | H21: 932 | I21: 356181.63 | J21: 69213.24 | K21: =I21-J21 -> 286968.39 | L21: =I21+Mar!L21 -> 1426830.4 | M21: =J21+Mar!M21 -> 5929287.9 | N21: =L21-M21 -> -4502457.5
... B27: =1+B26 -> 19 | C27: United Fund, Inc. | D27: 6.2556624e+08 | E27: 20960020 | F27: =D27-E27 -> 604606217 | G27: 5.3967495e+08 | H27: 1233 | I27: 7450782.6 | J27: 1390154.2 | K27: =I27-J27 -> 6060628.4 | L27: =I27+Mar!L27 -> 10094147 | M27: =J27+Mar!M27 -> 6128077.8 | N27: =L27-M27 -> 3966069.6
A28: Primarily invested in Peso Securities (units)
B29: =1+B27 -> 20 | C29: COL Equity Index Unitized Mutual Fund, Inc. | D29: 2.2770206e+08 | E29: 922248.71 | F29: =D29-E29 -> 2.2677981e+08 | G29: 2.2362517e+08 | H29: 3470 | I29: 5963945.1 | J29: 3151445.6 | K29: =I29-J29 -> 2812499.6 | L29: =I29+Mar!L29 -> 23916773 | M29: =J29+Mar!M29 -> 36416876 | N29: =L29-M29 -> -12500103
B30: =1+B29 -> 21 | C30: COL Strategic Growth Equity Unitized Mutual Fund, Inc. | D30: 2.6000024e+08 | E30: 604612.73 | F30: =D30-E30 -> 2.5939562e+08 | G30: 149131269 | H30: 3137 | I30: 13248793 | J30: 2791651.4 | K30: =I30-J30 -> 10457141 | L30: =I30+Mar!L30 -> 1.651926e+08 | M30: =J30+Mar!M30 -> 17700100 | N30: =L30-M30 -> 1.474925e+08
B31: =1+B30 -> 22 | C31: Philequity Alpha One Fund, Inc. | D31: 3.0235854e+08 | E31: 1581879.3 | F31: =D31-E31 -> 3.0077666e+08 | G31: 274822933 | H31: 1219 | I31: 498335.29 | J31: 4336046.9 | K31: =I31-J31 -> -3837711.6 | L31: =I31+Mar!L31 -> 2433581.4 | M31: =J31+Mar!M31 -> 20726713 | N31: =L31-M31 -> -18293132
B32: =1+B31 -> 23 | C32: Philippine Stock Index Fund Corp. | D32: 624420763 | E32: 5502308 | F32: =D32-E32 -> 618918455 | G32: 612947226 | H32: 646399 | I32: 28103494 | J32: 17118746 | K32: =I32-J32 -> 10984748 | L32: =I32+Mar!L32 -> 78784455 | M32: =J32+Mar!M32 -> 105350149 | N32: =L32-M32 -> -26565694
A33: Exchange Traded Fund
B34: =1+B32 -> 24 | C34: First Metro Phil. Equity Exchange Traded Fund, Inc. | D34: 2141987007 | E34: 1932857 | F34: =D34-E34 -> 2140054150 | G34: 2127887775 | H34: 3225 | I34: 6199623 | J34: 41981604 | K34: =I34-J34 -> -35781981 | L34: =I34+Mar!L34 -> 14535918 | M34: =J34+Mar!M34 -> 119593963 | N34: =L34-M34 -> -105058045
A35: Sub total - Peso Currency | D35: =SUM(D9:D34) -> 65421075432 | E35: =SUM(E9:E34) -> 4.0083047e+08 | F35: =SUM(F9:F34) -> 65020244959 | G35: =SUM(G9:G34) -> 61811389174 | H35: =SUM(H9:H34) -> 928043 | I35: =SUM(I9:I34) -> 6.2795297e+08 | J35: =SUM(J9:J34) -> 1156456765 | K35: =SUM(K9:K34) -> -528503795 | ... N35: =SUM(N9:N34) -> -3061462757
A36: Primarily invested in foreign currency securities (shares)
B37: =1+B34 -> 25 | C37: ATRAM AsiaPlus Equity Fund, Inc. | D37: 26983952 | E37: 62379.64 | F37: =D37-E37 -> 26921572 | G37: 0 | H37: 51 | I37: 46170.46 | J37: 7354.58 | K37: =I37-J37 -> 38815.88 | L37: =I37+Mar!L37 -> 352367.53 | M37: =J37+Mar!M37 -> 40120.23 | N37: =L37-M37 -> 312247.3
B38: =1+B37 -> 26 | C38: Sun Life Prosperity World Voyager Fund, Inc. | D38: 1868204040 | E38: 41500208 | F38: =D38-E38 -> 1826703832 | G38: 0 | H38: 2982 | I38: 14579177 | J38: 298337949 | K38: =I38-J38 -> -283758772 | L38: =I38+Mar!L38 -> 60684470 | M38: =J38+Mar!M38 -> 397536584 | N38: =L38-M38 -> -336852114
A39: Sub total - US Currency | D39: =SUM(D37:D38) -> 1895187992 | E39: =SUM(E37:E38) -> 41562588 | F39: =SUM(F37:F38) -> 1853625404 | G39: =SUM(G37:G38) -> 0 | H39: =SUM(H37:H38) -> 3033 | I39: =SUM(I37:I38) -> 14625347 | J39: =SUM(J37:J38) -> 2.983453e+08 | K39: =SUM(K37:K38) -> -2.8371996e+08 | ... N39: =SUM(N37:N38) -> -3.3653987e+08
A40: Sub total - stock funds | D40: =D35+D39 -> 67316263424 | E40: =E35+E39 -> 4.4239306e+08 | F40: =F35+F39 -> 66873870363 | G40: =G35+G39 -> 61811389174 | H40: =H35+H39 -> 931076 | I40: =I35+I39 -> 6.4257832e+08 | J40: =J35+J39 -> 1454802069 | K40: =K35+K39 -> -8.1222375e+08 | ... N40: =N35+N39 -> -3398002623
A41: Balanced Funds
A42: Primarily invested in Peso Securities (shares)
B43: =1+B38 -> 27 | C43: ATRAM Philippine Balanced Fund, Inc. | D43: 4.4481235e+08 | E43: 69146.33 | F43: =D43-E43 -> 4.4474321e+08 | G43: 2.3403218e+08 | H43: 2332 | I43: 492069.9 | J43: 3461082.6 | K43: =I43-J43 -> -2969012.7 | L43: =I43+Mar!L43 -> 2679166.8 | M43: =J43+Mar!M43 -> 27528545 | N43: =L43-M43 -> -24849378
B44: =1+B43 -> 28 | C44: ATRAM Unicapital Diversified Growth Fund, Inc. | D44: 1.2150824e+08 | E44: 5873675.2 | F44: =D44-E44 -> 1.1563456e+08 | G44: 34232023 | H44: 698 | I44: 155535.2 | J44: 327702.35 | K44: =I44-J44 -> -172167.15 | L44: =I44+Mar!L44 -> 1166419.8 | M44: =J44+Mar!M44 -> 3669323.9 | N44: =L44-M44 -> -2502904.1
B45: =1+B44 -> 29 | C45: First Metro Save and Learn Balanced Fund, Inc. | D45: 810734671 | E45: 12426091 | F45: =D45-E45 -> 798308580 | G45: 384981968 | H45: 4320 | I45: 672857 | J45: 5911411 | K45: =I45-J45 -> -5238554 | L45: =I45+Mar!L45 -> 8825728 | M45: =J45+Mar!M45 -> 174882353 | N45: =L45-M45 -> -166056625
B46: =1+B45 -> 30 | C46: First Metro Save and Learn F.O.C.C.U.S. Dynamic Fund, Inc. | D46: 310998143 | E46: 7968237 | F46: =D46-E46 -> 303029906 | G46: 200917302 | H46: 233 | I46: 87901502 | J46: 88255262 | K46: =I46-J46 -> -353760 | L46: =I46+Mar!L46 -> 175797386 | M46: =J46+Mar!M46 -> 178870917 | N46: =L46-M46 -> -3073531
B47: =1+B46 -> 31 | C47: NCM Mutual Fund of the Phils., Inc. | D47: 3.2755056e+08 | E47: 1275094.8 | F47: =D47-E47 -> 3.2627547e+08 | G47: 1.6371018e+08 | H47: 48 | I47: 0 | J47: 0 | K47: =I47-J47 -> 0 | L47: =I47+Mar!L47 -> 0 | M47: =J47+Mar!M47 -> 66119 | N47: =L47-M47 -> -66119
B48: =1+B47 -> 32 | C48: PAMI Horizon Fund, Inc. | D48: 508472123 | E48: 14716344 | F48: =D48-E48 -> 493755779 | G48: 250803148 | H48: 9829 | I48: 1970006 | J48: 5661863 | K48: =I48-J48 -> -3691857 | L48: =I48+Mar!L48 -> 2810760 | M48: =J48+Mar!M48 -> 19722317 | N48: =L48-M48 -> -16911557
B49: =1+B48 -> 33 | C49: Philam Fund, Inc. | D49: 1953166938 | E49: 19538985 | F49: =D49-E49 -> 1933627953 | G49: 962357381 | H49: 7712 | I49: 3973535 | J49: 11499349 | K49: =I49-J49 -> -7525814 | L49: =I49+Mar!L49 -> 11962301 | M49: =J49+Mar!M49 -> 80290232 | N49: =L49-M49 -> -68327931
B50: =1+B49 -> 34 | C50: Solidaritas Fund, Inc. | D50: 120571070 | E50: 152036 | F50: =D50-E50 -> 120419034 | G50: 57722922 | H50: 173 | I50: 0 | J50: 32600 | K50: =I50-J50 -> -32600 | L50: =I50+Mar!L50 -> 0 | M50: =J50+Mar!M50 -> 1890928 | N50: =L50-M50 -> -1890928
B51: =1+B50 -> 35 | C51: Sun Life Prosperity Balanced Fund, Inc. | D51: 6608764371 | E51: 37381558 | F51: =D51-E51 -> 6571382813 | G51: 3500273678 | H51: 54246 | I51: 7878470 | J51: 66964171 | K51: =I51-J51 -> -59085701 | L51: =I51+Mar!L51 -> 47257032 | M51: =J51+Mar!M51 -> 330257492 | N51: =L51-M51 -> -283000460
B52: =1+B51 -> 36 | C52: Sun Life Prosperity Dynamic Fund, Inc. | D52: 561801916 | E52: 4683660 | F52: =D52-E52 -> 557118256 | G52: 303561970 | H52: 5000 | I52: 0 | J52: 9026230 | K52: =I52-J52 -> -9026230 | L52: =I52+Mar!L52 -> 0 | M52: =J52+Mar!M52 -> 80276975 | N52: =L52-M52 -> -80276975
A53: Primarily invested in Peso Securities (units)
B54: =1+B52 -> 37 | C54: Sun Life Prosperity Achiever Fund 2028, Inc. | D54: 98388781 | E54: 521816 | F54: =D54-E54 -> 97866965 | G54: 25304359 | H54: 1173 | I54: 19872237 | J54: 465480 | K54: =I54-J54 -> 19406757 | L54: =I54+Mar!L54 -> 20653491 | M54: =J54+Mar!M54 -> 1155163 | N54: =L54-M54 -> 19498328
B55: =1+B54 -> 38 | C55: Sun Life Prosperity Achiever Fund 2038, Inc. | D55: 57000067 | E55: 353182 | F55: =D55-E55 -> 56646885 | G55: 44399705 | H55: 467 | I55: 83000 | J55: 28949 | K55: =I55-J55 -> 54051 | L55: =I55+Mar!L55 -> 524023 | M55: =J55+Mar!M55 -> 253441 | N55: =L55-M55 -> 270582
B56: =1+B55 -> 39 | C56: Sun Life Prosperity Achiever Fund 2048, Inc. | D56: 48199767 | E56: 340441 | F56: =D56-E56 -> 47859326 | G56: 39828294 | H56: 218 | I56: 36500 | J56: 0 | K56: =I56-J56 -> 36500 | L56: =I56+Mar!L56 -> 206823 | M56: =J56+Mar!M56 -> 382932 | N56: =L56-M56 -> -176109
A57: Sub total - Peso Currency | D57: =SUM(D43:D56) -> 11971969000 | E57: =SUM(E43:E56) -> 1.0530027e+08 | F57: =SUM(F43:F56) -> 11866668734 | G57: =SUM(G43:G56) -> 6202125110 | H57: =SUM(H43:H56) -> 86449 | I57: =SUM(I43:I56) -> 1.2303571e+08 | J57: =SUM(J43:J56) -> 191634100 | K57: =SUM(K43:K56) -> -68598388 | ... N57: =SUM(N43:N56) -> -6.2736361e+08
A58: Primarily invested in foreign currency securities (shares)
B59: =1+B56 -> 40 | C59: Cocolife Dollar Fund Builder, Inc. | D59: 1257662.7 | E59: 6476.49 | F59: =D59-E59 -> 1251186.2 | G59: 0 | H59: 49 | I59: 0 | J59: 0 | K59: =I59-J59 -> 0 | L59: =I59+Mar!L59 -> 84501.37 | M59: =J59+Mar!M59 -> 79493.21 | N59: =L59-M59 -> 5008.16
B60: =1+B59 -> 41 | C60: PAMI Asia Balanced Fund, Inc. | D60: 334125507 | E60: 32126344 | F60: =D60-E60 -> 301999163 | G60: 168817389 | H60: 233 | I60: 5743 | J60: 347368 | K60: =I60-J60 -> -341625 | L60: =I60+Mar!L60 -> 28146 | M60: =J60+Mar!M60 -> 9539203 | N60: =L60-M60 -> -9511057
B61: =1+B60 -> 42 | C61: Sun Life Prosperity Dollar Advantage Fund, Inc. | D61: 1468248413 | E61: 34876252 | F61: =D61-E61 -> 1433372161 | G61: 0 | H61: 4183 | I61: 20077720 | J61: 14831308 | K61: =I61-J61 -> 5246412 | L61: =I61+Mar!L61 -> 27451280 | M61: =J61+Mar!M61 -> 188520469 | N61: =L61-M61 -> -161069189
B62: =1+B61 -> 43 | C62: Sun Life Prosperity Dollar Wellspring Fund, Inc. | D62: 258374847 | E62: 4282038 | F62: =D62-E62 -> 254092809 | G62: 0 | H62: 748 | I62: 98192 | J62: 4235723 | K62: =I62-J62 -> -4137531 | L62: =I62+Mar!L62 -> 4303725 | M62: =J62+Mar!M62 -> 12893990 | N62: =L62-M62 -> -8590265
A63: Sub total - US Currency | D63: =SUM(D59:D62) -> 2062006430 | E63: =SUM(E59:E62) -> 71291110 | F63: =SUM(F59:F62) -> 1990715319 | G63: =SUM(G59:G62) -> 168817389 | H63: =SUM(H59:H62) -> 5213 | I63: =SUM(I59:I62) -> 20181655 | J63: =SUM(J59:J62) -> 19414399 | K63: =SUM(K59:K62) -> 767256 | ... N63: =SUM(N59:N62) -> -1.791655e+08
A64: Sub total - balanced funds | D64: =D57+D63 -> 14033975430 | E64: =E57+E63 -> 1.7659138e+08 | F64: =F57+F63 -> 13857384053 | G64: =G57+G63 -> 6370942499 | H64: =H57+H63 -> 91662 | I64: =I57+I63 -> 1.4321737e+08 | J64: =J57+J63 -> 211048499 | K64: =K57+K63 -> -67831132 | ... N64: =N57+N63 -> -8.0652911e+08
A65: Bond Funds
A66: Primarily invested in Peso Securities (shares)
B67: =1+B62 -> 44 | C67: ALFM Peso Bond Fund, Inc. | D67: 35776547641 | E67: 176385963 | F67: =D67-E67 -> 35600161678 | G67: 256250000 | H67: 23313 | I67: 114927235 | J67: 552491694 | K67: =I67-J67 -> -437564459 | L67: =I67+Mar!L67 -> 606853111 | M67: =J67+Mar!M67 -> 1820687518 | N67: =L67-M67 -> -1213834407
B68: =1+B67 -> 45 | C68: ATRAM Corporate Bond Fund, Inc. | D68: 3.4560364e+08 | E68: 118251.48 | F68: =D68-E68 -> 3.4548539e+08 | G68: 0 | H68: 992 | I68: 236101.5 | J68: 6118778.2 | K68: =I68-J68 -> -5882676.7 | L68: =I68+Mar!L68 -> 13772679 | M68: =J68+Mar!M68 -> 1.0366416e+08 | N68: =L68-M68 -> -89891482
B69: =1+B68 -> 46 | C69: Cocolife Fixed Income Fund, Inc. | D69: 8.9046057e+08 | E69: 8918136.5 | F69: =D69-E69 -> 8.8154243e+08 | G69: 0 | H69: 1847 | I69: 478131.5 | J69: 1947911.2 | K69: =I69-J69 -> -1469779.7 | L69: =I69+Mar!L69 -> 20031111 | M69: =J69+Mar!M69 -> 47915377 | N69: =L69-M69 -> -27884266
B70: =1+B69 -> 47 | C70: Ekklesia Mutual Fund, Inc. | D70: 184325722 | E70: 175250 | F70: =D70-E70 -> 184150472 | G70: 0 | H70: 156 | I70: 0 | J70: 4997 | K70: =I70-J70 -> -4997 | L70: =I70+Mar!L70 -> 0 | M70: =J70+Mar!M70 -> 9851671 | N70: =L70-M70 -> -9851671
B71: =1+B70 -> 48 | C71: First Metro Save and Learn Fixed Income Fund, Inc. | D71: 1161024533 | E71: 23880618 | F71: =D71-E71 -> 1137143915 | G71: 0 | H71: 1773 | I71: 3513024 | J71: 20455631 | K71: =I71-J71 -> -16942607 | L71: =I71+Mar!L71 -> 143604903 | M71: =J71+Mar!M71 -> 267099706 | N71: =L71-M71 -> -123494803
B72: =1+B71 -> 49 | C72: Philam Bond Fund, Inc. | D72: 1531672179 | E72: 35055568 | F72: =D72-E72 -> 1496616611 | G72: 0 | H72: 4786 | I72: 2777108 | J72: 45131638 | K72: =I72-J72 -> -42354530 | L72: =I72+Mar!L72 -> 11711096 | M72: =J72+Mar!M72 -> 92392283 | N72: =L72-M72 -> -80681187
B73: =1+B72 -> 50 | C73: Philam Managed Income Fund, Inc. | D73: 588009195 | E73: 9994538 | F73: =D73-E73 -> 578014657 | G73: 0 | H73: 442 | I73: 1961720 | J73: 4642866 | K73: =I73-J73 -> -2681146 | L73: =I73+Mar!L73 -> 5937759 | M73: =J73+Mar!M73 -> 16294684 | N73: =L73-M73 -> -10356925
B74: =1+B73 -> 51 | C74: Philequity Peso Bond Fund, Inc. | D74: 3.2019804e+08 | E74: 1393709.8 | F74: =D74-E74 -> 3.1880433e+08 | G74: 0 | H74: 4011 | I74: 583682.96 | J74: 5035999.5 | K74: =I74-J74 -> -4452316.5 | L74: =I74+Mar!L74 -> 2393206.5 | M74: =J74+Mar!M74 -> 8283246.2 | N74: =L74-M74 -> -5890039.6
B75: =1+B74 -> 52 | C75: Soldivo Bond Fund, Inc. | D75: 1.9583033e+09 | E75: 3.2239062e+08 | F75: =D75-E75 -> 1635912718 | G75: 0 | H75: 781 | I75: 31730561 | J75: 13081275 | K75: =I75-J75 -> 18649287 | L75: =I75+Mar!L75 -> 1.3509995e+08 | M75: =J75+Mar!M75 -> 17760874 | N75: =L75-M75 -> 1.1733907e+08
B76: =1+B75 -> 53 | C76: Sun Life Prosperity Bond Fund, Inc. | D76: 5828610784 | E76: 10642960 | F76: =D76-E76 -> 5817967824 | G76: 0 | H76: 18456 | I76: 91127025 | J76: 140345128 | K76: =I76-J76 -> -49218103 | L76: =I76+Mar!L76 -> 408476302 | M76: =J76+Mar!M76 -> 469736118 | N76: =L76-M76 -> -61259816
B77: =1+B76 -> 54 | C77: Sun Life Prosperity GS Fund, Inc. | D77: 145629590 | E77: 587612 | F77: =D77-E77 -> 145041978 | G77: 0 | H77: 2791 | I77: 25290772 | J77: 2549136 | K77: =I77-J77 -> 22741636 | L77: =I77+Mar!L77 -> 26832174 | M77: =J77+Mar!M77 -> 5728807 | N77: =L77-M77 -> 21103367
A78: Corporate Debt Vehicle (units)
B79: =1+B77 -> 55 | C79: ATRAM Unitized Corporate Debt Vehicle, Inc. | D79: 7.1206188e+08 | E79: 201070 | F79: =D79-E79 -> 7.1186081e+08 | G79: 0 | H79: 13 | I79: 0 | J79: 0 | K79: =I79-J79 -> 0 | L79: =I79+Mar!L79 -> 0 | M79: =J79+Mar!M79 -> 0 | N79: =L79-M79 -> 0
A80: Sub total - Peso Currency | D80: =SUM(D67:D79) -> 49442447115 | E80: =SUM(E67:E79) -> 5.897443e+08 | F80: =SUM(F67:F79) -> 48852702816 | G80: =SUM(G67:G79) -> 256250000 | H80: =SUM(H67:H79) -> 59361 | I80: =SUM(I67:I79) -> 2.7262536e+08 | J80: =SUM(J67:J79) -> 7.9180505e+08 | K80: =SUM(K67:K79) -> -5.1917969e+08 | ... N80: =SUM(N67:N79) -> -1484702155
A81: Primarily invested in foreign currency securities (shares)
B82: =1+B79 -> 56 | C82: ALFM Dollar Bond Fund, Inc. | D82: 13049069405 | E82: 96372043 | F82: =D82-E82 -> 12952697362 | G82: 0 | H82: 7731 | I82: 23533848 | J82: 85290956 | K82: =I82-J82 -> -61757108 | L82: =I82+Mar!L82 -> 100606464 | M82: =J82+Mar!M82 -> 437164353 | N82: =L82-M82 -> -336557889
B83: =1+B82 -> 57 | C83: ATRAM Total Return Dollar Bond Fund, Inc. | D83: 2.1872435e+08 | E83: 1021348.7 | F83: =D83-E83 -> 2.17703e+08 | G83: 0 | H83: 128 | I83: 202114.37 | J83: 820752.85 | K83: =I83-J83 -> -618638.48 | L83: =I83+Mar!L83 -> 254932.08 | M83: =J83+Mar!M83 -> 42358469 | N83: =L83-M83 -> -42103537
B84: =1+B83 -> 58 | C84: First Metro Save and Learn Dollar Bond Fund, Inc. | D84: 449219257 | E84: 1011336 | F84: =D84-E84 -> 448207921 | G84: 0 | H84: 154 | I84: 393547 | J84: 839062 | K84: =I84-J84 -> -445515 | L84: =I84+Mar!L84 -> 4387829 | M84: =J84+Mar!M84 -> 4763261 | N84: =L84-M84 -> -375432
B85: =1+B84 -> 59 | C85: PAMI Global Bond Fund, Inc. | D85: 65762858 | E85: 16242760 | F85: =D85-E85 -> 49520098 | G85: 0 | H85: 27 | I85: 0 | J85: 0 | K85: =I85-J85 -> 0 | L85: =I85+Mar!L85 -> 0 | M85: =J85+Mar!M85 -> 0 | N85: =L85-M85 -> 0
B86: =1+B85 -> 60 | C86: Philam Dollar Bond Fund, Inc. | D86: 1847483264 | E86: 11448198 | F86: =D86-E86 -> 1836035066 | G86: 0 | H86: 1750 | I86: 11436 | J86: 11956647 | K86: =I86-J86 -> -11945211 | L86: =I86+Mar!L86 -> 211486 | M86: =J86+Mar!M86 -> 91602908 | N86: =L86-M86 -> -91391422
B87: =1+B86 -> 61 | C87: Philequity Dollar Income Fund, Inc. | D87: 2.3512721e+08 | E87: 1431495.8 | F87: =D87-E87 -> 2.3369571e+08 | G87: 0 | H87: 113 | I87: 155952 | J87: 0 | K87: =I87-J87 -> 155952 | L87: =I87+Mar!L87 -> 617110 | M87: =J87+Mar!M87 -> 7723341.9 | N87: =L87-M87 -> -7106231.9
B88: =1+B87 -> 62 | C88: Sun Life Prosperity Dollar Abundance Fund, Inc. | D88: 615137115 | E88: 15085543 | F88: =D88-E88 -> 600051572 | G88: 0 | H88: 2612 | I88: 1604044 | J88: 2502440 | K88: =I88-J88 -> -898396 | L88: =I88+Mar!L88 -> 30017765 | M88: =J88+Mar!M88 -> 12006977 | N88: =L88-M88 -> 18010788
A89: Sub total - US Currency | D89: =SUM(D82:D88) -> 16480523458 | E89: =SUM(E82:E88) -> 1.4261272e+08 | F89: =SUM(F82:F88) -> 16337910733 | G89: =SUM(G82:G88) -> 0 | H89: =SUM(H82:H88) -> 12515 | I89: =SUM(I82:I88) -> 25900941 | J89: =SUM(J82:J88) -> 1.0140986e+08 | K89: =SUM(K82:K88) -> -75508916 | ... N89: =SUM(N82:N88) -> -4.5952372e+08
B90: =1+B88 -> 63 | C90: ALFM Euro Bond Fund, Inc. | D90: 943682960 | E90: 6549489 | F90: =D90-E90 -> 937133471 | G90: 0 | H90: 602 | I90: 3893510 | J90: 8333883 | K90: =I90-J90 -> -4440373 | L90: =I90+Mar!L90 -> 6089214 | M90: =J90+Mar!M90 -> 21862053 | N90: =L90-M90 -> -15772839
A91: Sub total - Euro Currency | D91: =SUM(D90) -> 943682960 | E91: =SUM(E90) -> 6549489 | F91: =SUM(F90) -> 937133471 | G91: =SUM(G90) -> 0 | H91: =SUM(H90) -> 602 | I91: =SUM(I90) -> 3893510 | J91: =SUM(J90) -> 8333883 | K91: =SUM(K90) -> -4440373 | ... N91: =SUM(N90) -> -15772839
A92: Sub total - bond funds | D92: =D80+D89+D91 -> 66866653533 | E92: =E80+E89+E91 -> 7.3890651e+08 | F92: =F80+F89+F91 -> 66127747020 | G92: =G80+G89+G91 -> 256250000 | H92: =H80+H89+H91 -> 72478 | I92: =I80+I89+I91 -> 3.0241981e+08 | J92: =J80+J89+J91 -> 9.0154879e+08 | K92: =K80+K89+K91 -> -5.9912898e+08 | ... N92: =N80+N89+N91 -> -1959998718
A93: Money Market Funds
A94: Primarily invested in Peso Securities (shares)
B95: 64 | C95: AIB Money Market Mutual Fund, Inc. | D95: 1.7687377e+08 | E95: 297770.15 | F95: =D95-E95 -> 1.76576e+08 | G95: 0 | H95: 56 | I95: 3486400 | J95: 0 | K95: =I95-J95 -> 3486400 | L95: =I95+Mar!L95 -> 14432375 | M95: =J95+Mar!M95 -> 0 | N95: =L95-M95 -> 14432375
B96: 65 | C96: ALFM Money Market Fund, Inc. | D96: 24872022721 | E96: 18036793 | F96: =D96-E96 -> 24853985928 | G96: 0 | H96: 24584 | I96: 344396 | J96: 529408667 | K96: =I96-J96 -> -529064271 | L96: =I96+Mar!L96 -> 1371933 | M96: =J96+Mar!M96 -> 2359438053 | N96: =L96-M96 -> -2358066120
B97: =1+B96 -> 66 | C97: First Metro Save and Learn Money Market Fund, Inc. | D97: 3694945220 | E97: 8578445 | F97: =D97-E97 -> 3686366775 | G97: 0 | H97: 1129 | I97: 562781520 | J97: 481584181 | K97: =I97-J97 -> 81197339 | L97: =I97+Mar!L97 -> 1967965702 | M97: =J97+Mar!M97 -> 1564132780 | N97: =L97-M97 -> 403832922
B98: =1+B97 -> 67 | C98: Sun Life Prosperity Peso Starter Fund, Inc. | D98: 17768430892 | E98: 83755347 | F98: =D98-E98 -> 17684675545 | G98: 0 | H98: 70699 | I98: 743633479 | J98: 1129613246 | K98: =I98-J98 -> -385979767 | L98: =I98+Mar!L98 -> 1793215180 | M98: =J98+Mar!M98 -> 5058189477 | N98: =L98-M98 -> -3264974297
A99: Primarily invested in Peso Securities (units)
B100: =1+B98 -> 68 | C100: ALFM Money Market Fund, Inc. | D100: 9466870028 | E100: 7440874 | F100: =D100-E100 -> 9459429154 | G100: 0 | H100: 17200 | I100: 1223919807 | J100: 753016320 | K100: =I100-J100 -> 470903487 | L100: =I100+Mar!L100 -> 4470778697 | M100: =J100+Mar!M100 -> 3302841876 | N100: =L100-M100 -> 1167936821
A101: Sub total - Peso Currency | D101: =SUM(D95:D98)+D100 -> 55979142632 | E101: =SUM(E95:E98)+E100 -> 1.1810923e+08 | F101: =SUM(F95:F98)+F100 -> 55861033403 | G101: =SUM(G95:G98)+G100 -> 0 | H101: =SUM(H95:H98)+H100 -> 113668 | I101: =SUM(I95:I98)+I100 -> 2534165602 | J101: =SUM(J95:J98)+J100 -> 2893622414 | K101: =SUM(K95:K98)+K100 -> -359456812 | ... N101: =SUM(N95:N98)+N100 -> -4036838299
A102: Primarily invested in foreign currency securities (shares)
B103: =1+B100 -> 69 | C103: Sun Life Prosperity Dollar Starter Fund, Inc. | D103: 2491155593 | E103: 9125971 | F103: =D103-E103 -> 2482029622 | G103: 0 | H103: 3679 | I103: 318294325 | J103: 228779799 | K103: =I103-J103 -> 89514526 | L103: =I103+Mar!L103 -> 610559941 | M103: =J103+Mar!M103 -> 613862415 | N103: =L103-M103 -> -3302474
A104: Sub total - US Currency | D104: =SUM(D103) -> 2491155593 | E104: =SUM(E103) -> 9125971 | F104: =SUM(F103) -> 2482029622 | G104: =SUM(G103) -> 0 | H104: =SUM(H103) -> 3679 | I104: =SUM(I103) -> 318294325 | J104: =SUM(J103) -> 228779799 | K104: =SUM(K103) -> 89514526 | ... N104: =SUM(N103) -> -3302474
A105: Sub total - money market funds | D105: =D101+D104 -> 58470298225 | E105: =E101+E104 -> 1.272352e+08 | F105: =F101+F104 -> 58343063025 | G105: =G101+G104 -> 0 | H105: =H101+H104 -> 117347 | I105: =I101+I104 -> 2852459927 | J105: =J101+J104 -> 3122402213 | K105: =K101+K104 -> -269942286 | ... N105: =N101+N104 -> -4040140773
...

Sheet May
A1: PHILIPPINE INVESTMENT FUNDS ASSOCIATION, INC.
A2: MUTUAL FUNDS STATISTICAL REPORT
A3: Month of May 2024
A4: (Amounts in Peso)
I5: F O R - T H E - M O N T H | L5: Y E A R - T O - D A T E
A6: Fund Category | C6: Fund Name | D6: ASSETS | E6: LIABILITIES | F6: NET ASSETS | G6: EQUITY INV. | H6: NO. OF A/C | I6: SALES | J6: REDEMPTIONS | K6: NET SALES | L6: TOTAL SALES | M6: TOTAL REDEMPTIONS | N6: TOTAL NET SALES
A7: Stock Funds
A8: Primarily invested in Peso Securities (shares)
B9: 1 | C9: ALFM Growth Fund, Inc. | D9: 4114788301 | E9: 16837865 | F9: =D9-E9 -> 4097950436 | G9: 3918040331 | H9: 6365 | I9: 4301884 | J9: 43398326 | K9: =I9-J9 -> -39096442 | L9: =I9+Apr!L9 -> 21278864 | M9: =J9+Apr!M9 -> 254733250 | N9: =L9-M9 -> -233454386
B10: =1+B9 -> 2 | C10: ATRAM Alpha Opportunity Fund, Inc. | D10: 7.8519195e+08 | E10: 1029848.4 | F10: =D10-E10 -> 7.841621e+08 | G10: 7.3942494e+08 | H10: 4000 | I10: 12157264 | J10: 63510391 | K10: =I10-J10 -> -51353127 | L10: =I10+Apr!L10 -> 22213321 | M10: =J10+Apr!M10 -> 1.1370784e+08 | N10: =L10-M10 -> -91494517
B11: =1+B10 -> 3 | C11: ATRAM Phil. Equity Opportunity Fund, Inc. | D11: 1.2470821e+09 | E11: 1.0661299e+08 | F11: =D11-E11 -> 1140469153 | G11: 1.0686439e+09 | H11: 2626 | I11: 3593981.3 | J11: 1.1190924e+08 | K11: =I11-J11 -> -1.0831526e+08 | L11: =I11+Apr!L11 -> 42215712 | M11: =J11+Apr!M11 -> 2.4291245e+08 | N11: =L11-M11 -> -2.0069674e+08
B12: =1+B11 -> 4 | C12: Climbs Share Capital Equity Investment Fund Corp. | D12: 4.2719516e+08 | E12: 14459284 | F12: =D12-E12 -> 4.1273587e+08 | G12: 3.2724066e+08 | H12: 1764 | I12: 1758548 | J12: 174565.04 | K12: =I12-J12 -> 1583983 | L12: =I12+Apr!L12 -> 69142568 | M12: =J12+Apr!M12 -> 9449438.7 | N12: =L12-M12 -> 59693130
B13: =1+B12 -> 5 | C13: First Metro Consumer Fund, Inc. | D13: 470998960 | E13: 3001073 | F13: =D13-E13 -> 467997887 | G13: 427372598 | H13: 1271 | I13: 281811 | J13: 1625028 | K13: =I13-J13 -> -1343217 | L13: =I13+Apr!L13 -> 64631716 | M13: =J13+Apr!M13 -> 75395058 | N13: =L13-M13 -> -10763342
B14: =1+B13 -> 6 | C14: First Metro Save and Learn Equity Fund, Inc. | D14: 3679149560 | E14: 95646435 | F14: =D14-E14 -> 3583503125 | G14: 3371420641 | H14: 15063 | I14: 9872816 | J14: 44146222 | K14: =I14-J14 -> -34273406 | L14: =I14+Apr!L14 -> 566441722 | M14: =J14+Apr!M14 -> 1308117799 | N14: =L14-M14 -> -741676077
B15: =1+B14 -> 7 | C15: First Metro Save and Learn Phil. Index Fund, Inc. | D15: 118989573 | E15: 5978976 | F15: =D15-E15 -> 113010597 | G15: 100570166 | H15: 506 | I15: 15926426 | J15: 254849 | K15: =I15-J15 -> 15671577 | L15: =I15+Apr!L15 -> 17364100 | M15: =J15+Apr!M15 -> 5097601 | N15: =L15-M15 -> 12266499
B16: =1+B15 -> 8 | C16: MBG Equity Investment Fund, Inc. | D16: 134979483 | E16: 1718998 | F16: =D16-E16 -> 133260485 | G16: 123915955 | H16: 47 | I16: 0 | J16: 0 | K16: =I16-J16 -> 0 | L16: =I16+Apr!L16 -> 23000000 | M16: =J16+Apr!M16 -> 7542618 | N16: =L16-M16 -> 15457382
B17: =1+B16 -> 9 | C17: PAMI Equity Index Fund, Inc. | D17: 1145258534 | E17: 29853423 | F17: =D17-E17 -> 1115405111 | G17: 1127104795 | H17: 11440 | I17: 0 | J17: 9483523 | K17: =I17-J17 -> -9483523 | L17: =I17+Apr!L17 -> 0 | M17: =J17+Apr!M17 -> 66300547 | N17: =L17-M17 -> -66300547
B18: =1+B17 -> 10 | C18: Philam Strategic Growth Fund, Inc. | D18: 3372360836 | E18: 28863147 | F18: =D18-E18 -> 3343497689 | G18: 3208019197 | H18: 11347 | I18: 6598010 | J18: 15263035 | K18: =I18-J18 -> -8665025 | L18: =I18+Apr!L18 -> 34093610 | M18: =J18+Apr!M18 -> 160790953 | N18: =L18-M18 -> -126697343
B19: =1+B18 -> 11 | C19: Philequity Dividend Yield Fund, Inc. | D19: 2.3892951e+09 | E19: 8145658.1 | F19: =D19-E19 -> 2381149456 | G19: 2.1891663e+09 | H19: 4873 | I19: 2771733.6 | J19: 8062768.3 | K19: =I19-J19 -> -5291034.8 | L19: =I19+Apr!L19 -> 14598504 | M19: =J19+Apr!M19 -> 28812126 | N19: =L19-M19 -> -14213623
B20: =1+B19 -> 12 | C20: Philequity Fund, Inc. | D20: 9.2512941e+09 | E20: 49281085 | F20: =D20-E20 -> 9202013043 | G20: 8.4155578e+09 | H20: 33438 | I20: 8118872.5 | J20: 49146025 | K20: =I20-J20 -> -41027152 | L20: =I20+Apr!L20 -> 48242351 | M20: =J20+Apr!M20 -> 2.465217e+08 | N20: =L20-M20 -> -1.9827935e+08
B21: =1+B20 -> 13 | C21: Philequity MSCI Phil. Index Fund, Inc. | D21: 3.0666187e+08 | E21: 964165.84 | F21: =D21-E21 -> 3.0569771e+08 | G21: 2.9927956e+08 | H21: 918 | I21: 673929.16 | J21: 176216.28 | K21: =I21-J21 -> 497712.88 | L21: =I21+Apr!L21 -> 2100759.5 | M21: =J21+Apr!M21 -> 6105504.2 | N21: =L21-M21 -> -4004744.7
... B27: =1+B26 -> 19 | C27: United Fund, Inc. | D27: 6.0377667e+08 | E27: 16176386 | F27: =D27-E27 -> 5.8760029e+08 | G27: 5.3372861e+08 | H27: 1230 | I27: 384084.82 | J27: 552820.07 | K27: =I27-J27 -> -168735.25 | L27: =I27+Apr!L27 -> 10478232 | M27: =J27+Apr!M27 -> 6680897.9 | N27: =L27-M27 -> 3797334.3
A28: Primarily invested in Peso Securities (units)
B29: =1+B27 -> 20 | C29: COL Equity Index Unitized Mutual Fund, Inc. | D29: 2.2485669e+08 | E29: 1411560 | F29: =D29-E29 -> 2.2344513e+08 | G29: 2.1843907e+08 | H29: 3594 | I29: 6595133.9 | J29: 1493387.5 | K29: =I29-J29 -> 5101746.3 | L29: =I29+Apr!L29 -> 30511907 | M29: =J29+Apr!M29 -> 37910264 | N29: =L29-M29 -> -7398356.4
B30: =1+B29 -> 21 | C30: COL Strategic Growth Equity Unitized Mutual Fund, Inc. | D30: 2.7490098e+08 | E30: 6138558 | F30: =D30-E30 -> 2.6876242e+08 | G30: 175221460 | H30: 3368 | I30: 14491781 | J30: 4210310.9 | K30: =I30-J30 -> 10281470 | L30: =I30+Apr!L30 -> 1.7968439e+08 | M30: =J30+Apr!M30 -> 21910411 | N30: =L30-M30 -> 1.5777397e+08
B31: =1+B30 -> 22 | C31: Philequity Alpha One Fund, Inc. | D31: 2.9549599e+08 | E31: 3292576.6 | F31: =D31-E31 -> 2.9220341e+08 | G31: 2.6612999e+08 | H31: 1201 | I31: 210603.36 | J31: 2243687.3 | K31: =I31-J31 -> -2033083.9 | L31: =I31+Apr!L31 -> 2644184.7 | M31: =J31+Apr!M31 -> 22970401 | N31: =L31-M31 -> -20326216
B32: =1+B31 -> 23 | C32: Philippine Stock Index Fund Corp. | D32: 609387098 | E32: 6781623 | F32: =D32-E32 -> 602605475 | G32: 597059392 | H32: 655066 | I32: 19542511 | J32: 13060471 | K32: =I32-J32 -> 6482040 | L32: =I32+Apr!L32 -> 98326966 | M32: =J32+Apr!M32 -> 118410620 | N32: =L32-M32 -> -20083654
A33: Exchange Traded Fund
B34: =1+B32 -> 24 | C34: First Metro Phil. Equity Exchange Traded Fund, Inc. | D34: 1981619812 | E34: 2023313 | F34: =D34-E34 -> 1979596499 | G34: 1960685178 | H34: 3242 | I34: 0 | J34: 84244427 | K34: =I34-J34 -> -84244427 | L34: =I34+Apr!L34 -> 14535918 | M34: =J34+Apr!M34 -> 203838390 | N34: =L34-M34 -> -189302472
A35: Sub total - Peso Currency | D35: =SUM(D9:D34) -> 62485996471 | E35: =SUM(E9:E34) -> 5.8605246e+08 | F35: =SUM(F9:F34) -> 61899944013 | G35: =SUM(G9:G34) -> 59476959768 | H35: =SUM(H9:H34) -> 936364 | I35: =SUM(I9:I34) -> 209184762 | J35: =SUM(J9:J34) -> 1130093881 | K35: =SUM(K9:K34) -> -9.2090912e+08 | ... N35: =SUM(N9:N34) -> -3982371875
A36: Primarily invested in foreign currency securities (shares)
B37: =1+B34 -> 25 | C37: ATRAM AsiaPlus Equity Fund, Inc. | D37: 27817915 | E37: 63193.14 | F37: =D37-E37 -> 27754722 | G37: 0 | H37: 50 | I37: 35069.72 | J37: 41280.56 | K37: =I37-J37 -> -6210.84 | L37: =I37+Apr!L37 -> 387437.25 | M37: =J37+Apr!M37 -> 81400.79 | N37: =L37-M37 -> 306036.46
B38: =1+B37 -> 26 | C38: Sun Life Prosperity World Voyager Fund, Inc. | D38: 1917208482 | E38: 57050271 | F38: =D38-E38 -> 1860158211 | G38: 0 | H38: 2998 | I38: 13945134 | J38: 50383339 | K38: =I38-J38 -> -36438205 | L38: =I38+Apr!L38 -> 74629604 | M38: =J38+Apr!M38 -> 447919923 | N38: =L38-M38 -> -373290319
A39: Sub total - US Currency | D39: =SUM(D37:D38) -> 1945026397 | E39: =SUM(E37:E38) -> 57113464 | F39: =SUM(F37:F38) -> 1887912933 | G39: =SUM(G37:G38) -> 0 | H39: =SUM(H37:H38) -> 3048 | I39: =SUM(I37:I38) -> 13980204 | J39: =SUM(J37:J38) -> 50424620 | K39: =SUM(K37:K38) -> -36444416 | ... N39: =SUM(N37:N38) -> -3.7298428e+08
A40: Sub total - stock funds | D40: =D35+D39 -> 64431022868 | E40: =E35+E39 -> 6.4316592e+08 | F40: =F35+F39 -> 63787856946 | G40: =G35+G39 -> 59476959768 | H40: =H35+H39 -> 939412 | I40: =I35+I39 -> 2.2316497e+08 | J40: =J35+J39 -> 1180518500 | K40: =K35+K39 -> -9.5735353e+08 | ... N40: =N35+N39 -> -4355356158
A41: Balanced Funds
A42: Primarily invested in Peso Securities (shares)
B43: =1+B38 -> 27 | C43: ATRAM Philippine Balanced Fund, Inc. | D43: 4.2968468e+08 | E43: 85972.1 | F43: =D43-E43 -> 4.2959871e+08 | G43: 2.3113906e+08 | H43: 2320 | I43: 426316.56 | J43: 3619093 | K43: =I43-J43 -> -3192776.5 | L43: =I43+Apr!L43 -> 3105483.3 | M43: =J43+Apr!M43 -> 31147638 | N43: =L43-M43 -> -28042155
B44: =1+B43 -> 28 | C44: ATRAM Unicapital Diversified Growth Fund, Inc. | D44: 1.1245545e+08 | E44: 43837.98 | F44: =D44-E44 -> 1.1241162e+08 | G44: 32708230 | H44: 694 | I44: 116044.44 | J44: 3611140.2 | K44: =I44-J44 -> -3495095.8 | L44: =I44+Apr!L44 -> 1282464.2 | M44: =J44+Apr!M44 -> 7280464.1 | N44: =L44-M44 -> -5997999.9
B45: =1+B44 -> 29 | C45: First Metro Save and Learn Balanced Fund, Inc. | D45: 790243747 | E45: 15515262 | F45: =D45-E45 -> 774728485 | G45: 450616886 | H45: 4294 | I45: 983683 | J45: 7661747 | K45: =I45-J45 -> -6678064 | L45: =I45+Apr!L45 -> 9809411 | M45: =J45+Apr!M45 -> 182544100 | N45: =L45-M45 -> -172734689
B46: =1+B45 -> 30 | C46: First Metro Save and Learn F.O.C.C.U.S. Dynamic Fund, Inc. | D46: 297494662 | E46: 762060 | F46: =D46-E46 -> 296732602 | G46: 272476183 | H46: 241 | I46: 6199892 | J46: 7926601 | K46: =I46-J46 -> -1726709 | L46: =I46+Apr!L46 -> 181997278 | M46: =J46+Apr!M46 -> 186797518 | N46: =L46-M46 -> -4800240
B47: =1+B46 -> 31 | C47: NCM Mutual Fund of the Phils., Inc. | D47: 3.2225255e+08 | E47: 1381737.6 | F47: =D47-E47 -> 3.2087081e+08 | G47: 1.57311e+08 | H47: 48 | I47: 0 | J47: 0 | K47: =I47-J47 -> 0 | L47: =I47+Apr!L47 -> 0 | M47: =J47+Apr!M47 -> 66119 | N47: =L47-M47 -> -66119
B48: =1+B47 -> 32 | C48: PAMI Horizon Fund, Inc. | D48: 489742681 | E48: 14932478 | F48: =D48-E48 -> 474810203 | G48: 234352926 | H48: 9813 | I48: 107856 | J48: 11277010 | K48: =I48-J48 -> -11169154 | L48: =I48+Apr!L48 -> 2918616 | M48: =J48+Apr!M48 -> 30999327 | N48: =L48-M48 -> -28080711
B49: =1+B48 -> 33 | C49: Philam Fund, Inc. | D49: 1910899929 | E49: 18492933 | F49: =D49-E49 -> 1892406996 | G49: 909516858 | H49: 7653 | I49: 636226 | J49: 9511047 | K49: =I49-J49 -> -8874821 | L49: =I49+Apr!L49 -> 12598527 | M49: =J49+Apr!M49 -> 89801279 | N49: =L49-M49 -> -77202752
B50: =1+B49 -> 34 | C50: Solidaritas Fund, Inc. | D50: 118790066 | E50: 744126 | F50: =D50-E50 -> 118045940 | G50: 57367650 | H50: 171 | I50: 0 | J50: 15305 | K50: =I50-J50 -> -15305 | L50: =I50+Apr!L50 -> 0 | M50: =J50+Apr!M50 -> 1906233 | N50: =L50-M50 -> -1906233
B51: =1+B50 -> 35 | C51: Sun Life Prosperity Balanced Fund, Inc. | D51: 6517444512 | E51: 133417900 | F51: =D51-E51 -> 6384026612 | G51: 3289572767 | H51: 54274 | I51: 9086128 | J51: 80896303 | K51: =I51-J51 -> -71810175 | L51: =I51+Apr!L51 -> 56343160 | M51: =J51+Apr!M51 -> 411153795 | N51: =L51-M51 -> -354810635
B52: =1+B51 -> 36 | C52: Sun Life Prosperity Dynamic Fund, Inc. | D52: 563285703 | E52: 25241303 | F52: =D52-E52 -> 538044400 | G52: 300817444 | H52: 5000 | I52: 0 | J52: 10417716 | K52: =I52-J52 -> -10417716 | L52: =I52+Apr!L52 -> 0 | M52: =J52+Apr!M52 -> 90694691 | N52: =L52-M52 -> -90694691
A53: Primarily invested in Peso Securities (units)
B54: =1+B52 -> 37 | C54: Sun Life Prosperity Achiever Fund 2028, Inc. | D54: 97063750 | E54: 821227 | F54: =D54-E54 -> 96242523 | G54: 24294409 | H54: 1182 | I54: 214943 | J54: 1610047 | K54: =I54-J54 -> -1395104 | L54: =I54+Apr!L54 -> 20868434 | M54: =J54+Apr!M54 -> 2765210 | N54: =L54-M54 -> 18103224
B55: =1+B54 -> 38 | C55: Sun Life Prosperity Achiever Fund 2038, Inc. | D55: 55840817 | E55: 232134 | F55: =D55-E55 -> 55608683 | G55: 42651699 | H55: 469 | I55: 418812 | J55: 52032 | K55: =I55-J55 -> 366780 | L55: =I55+Apr!L55 -> 942835 | M55: =J55+Apr!M55 -> 305473 | N55: =L55-M55 -> 637362
B56: =1+B55 -> 39 | C56: Sun Life Prosperity Achiever Fund 2048, Inc. | D56: 46806443 | E56: 221440 | F56: =D56-E56 -> 46585003 | G56: 38267090 | H56: 219 | I56: 89131 | J56: 66496 | K56: =I56-J56 -> 22635 | L56: =I56+Apr!L56 -> 295954 | M56: =J56+Apr!M56 -> 449428 | N56: =L56-M56 -> -153474
A57: Sub total - Peso Currency | D57: =SUM(D43:D56) -> 11752004992 | E57: =SUM(E43:E56) -> 2.1189241e+08 | F57: =SUM(F43:F56) -> 11540112581 | G57: =SUM(G43:G56) -> 6041092194 | H57: =SUM(H43:H56) -> 86378 | I57: =SUM(I43:I56) -> 18279032 | J57: =SUM(J43:J56) -> 1.3666454e+08 | K57: =SUM(K43:K56) -> -1.1838551e+08 | ... N57: =SUM(N43:N56) -> -7.4574911e+08
A58: Primarily invested in foreign currency securities (shares)
B59: =1+B56 -> 40 | C59: Cocolife Dollar Fund Builder, Inc. | D59: 73929323 | E59: 386506.53 | F59: =D59-E59 -> 73542816 | G59: 0 | H59: 49 | I59: 0 | J59: 134572.41 | K59: =I59-J59 -> -134572.41 | L59: =I59+Apr!L59 -> 84501.37 | M59: =J59+Apr!M59 -> 214065.62 | N59: =L59-M59 -> -129564.25
B60: =1+B59 -> 41 | C60: PAMI Asia Balanced Fund, Inc. | D60: 335120787 | E60: 18070996 | F60: =D60-E60 -> 317049791 | G60: 174015865 | H60: 232 | I60: 0 | J60: 6225060 | K60: =I60-J60 -> -6225060 | L60: =I60+Apr!L60 -> 28146 | M60: =J60+Apr!M60 -> 15764263 | N60: =L60-M60 -> -15736117
B61: =1+B60 -> 42 | C61: Sun Life Prosperity Dollar Advantage Fund, Inc. | D61: 1480951634 | E61: 30697772 | F61: =D61-E61 -> 1450253862 | G61: 0 | H61: 4196 | I61: 7747950 | J61: 36622095 | K61: =I61-J61 -> -28874145 | L61: =I61+Apr!L61 -> 35199230 | M61: =J61+Apr!M61 -> 225142564 | N61: =L61-M61 -> -189943334
B62: =1+B61 -> 43 | C62: Sun Life Prosperity Dollar Wellspring Fund, Inc. | D62: 249785986 | E62: 3241022 | F62: =D62-E62 -> 246544964 | G62: 0 | H62: 748 | I62: 0 | J62: 14207167 | K62: =I62-J62 -> -14207167 | L62: =I62+Apr!L62 -> 4303725 | M62: =J62+Apr!M62 -> 27101157 | N62: =L62-M62 -> -22797432
A63: Sub total - US Currency | D63: =SUM(D59:D62) -> 2139787730 | E63: =SUM(E59:E62) -> 52396297 | F63: =SUM(F59:F62) -> 2087391433 | G63: =SUM(G59:G62) -> 174015865 | H63: =SUM(H59:H62) -> 5225 | I63: =SUM(I59:I62) -> 7747950 | J63: =SUM(J59:J62) -> 57188894 | K63: =SUM(K59:K62) -> -49440944 | ... N63: =SUM(N59:N62) -> -2.2860645e+08
A64: Sub total - balanced funds | D64: =D57+D63 -> 13891792722 | E64: =E57+E63 -> 2.6428871e+08 | F64: =F57+F63 -> 13627504015 | G64: =G57+G63 -> 6215108059 | H64: =H57+H63 -> 91603 | I64: =I57+I63 -> 26026982 | J64: =J57+J63 -> 1.9385343e+08 | K64: =K57+K63 -> -1.6782645e+08 | ... N64: =N57+N63 -> -9.7435556e+08
A65: Bond Funds
A66: Primarily invested in Peso Securities (shares)
B67: =1+B62 -> 44 | C67: ALFM Peso Bond Fund, Inc. | D67: 35739892690 | E67: 237125583 | F67: =D67-E67 -> 35502767107 | G67: 255250000 | H67: 23392 | I67: 140135821 | J67: 371224663 | K67: =I67-J67 -> -231088842 | L67: =I67+Apr!L67 -> 746988932 | M67: =J67+Apr!M67 -> 2191912181 | N67: =L67-M67 -> -1444923249
B68: =1+B67 -> 45 | C68: ATRAM Corporate Bond Fund, Inc. | D68: 3.4334711e+08 | E68: 2217474.7 | F68: =D68-E68 -> 3.4112964e+08 | G68: 0 | H68: 990 | I68: 278345.05 | J68: 5743071.7 | K68: =I68-J68 -> -5464726.7 | L68: =I68+Apr!L68 -> 14051024 | M68: =J68+Apr!M68 -> 1.0940723e+08 | N68: =L68-M68 -> -95356208
B69: =1+B68 -> 46 | C69: Cocolife Fixed Income Fund, Inc. | D69: 9.0167354e+08 | E69: 9074321.4 | F69: =D69-E69 -> 8.9259921e+08 | G69: 0 | H69: 1840 | I69: 14186950 | J69: 6444268.7 | K69: =I69-J69 -> 7742680.8 | L69: =I69+Apr!L69 -> 34218060 | M69: =J69+Apr!M69 -> 54359645 | N69: =L69-M69 -> -20141585
B70: =1+B69 -> 47 | C70: Ekklesia Mutual Fund, Inc. | D70: 186197851 | E70: 175805 | F70: =D70-E70 -> 186022046 | G70: 0 | H70: 155 | I70: 0 | J70: 15064 | K70: =I70-J70 -> -15064 | L70: =I70+Apr!L70 -> 0 | M70: =J70+Apr!M70 -> 9866735 | N70: =L70-M70 -> -9866735
B71: =1+B70 -> 48 | C71: First Metro Save and Learn Fixed Income Fund, Inc. | D71: 1149447069 | E71: 7544345 | F71: =D71-E71 -> 1141902724 | G71: 0 | H71: 1766 | I71: 5541657 | J71: 8430134 | K71: =I71-J71 -> -2888477 | L71: =I71+Apr!L71 -> 149146560 | M71: =J71+Apr!M71 -> 275529840 | N71: =L71-M71 -> -126383280
B72: =1+B71 -> 49 | C72: Philam Bond Fund, Inc. | D72: 1550267902 | E72: 33362867 | F72: =D72-E72 -> 1516905035 | G72: 0 | H72: 4773 | I72: 3418117 | J72: 3608905 | K72: =I72-J72 -> -190788 | L72: =I72+Apr!L72 -> 15129213 | M72: =J72+Apr!M72 -> 96001188 | N72: =L72-M72 -> -80871975
B73: =1+B72 -> 50 | C73: Philam Managed Income Fund, Inc. | D73: 597530564 | E73: 13739293 | F73: =D73-E73 -> 583791271 | G73: 0 | H73: 440 | I73: 7039859 | J73: 5542579 | K73: =I73-J73 -> 1497280 | L73: =I73+Apr!L73 -> 12977618 | M73: =J73+Apr!M73 -> 21837263 | N73: =L73-M73 -> -8859645
B74: =1+B73 -> 51 | C74: Philequity Peso Bond Fund, Inc. | D74: 3.2060153e+08 | E74: 1274174.9 | F74: =D74-E74 -> 3.1932736e+08 | G74: 0 | H74: 3998 | I74: 825303.58 | J74: 2362761.7 | K74: =I74-J74 -> -1537458.1 | L74: =I74+Apr!L74 -> 3218510.1 | M74: =J74+Apr!M74 -> 10646008 | N74: =L74-M74 -> -7427497.7
B75: =1+B74 -> 52 | C75: Soldivo Bond Fund, Inc. | D75: 1.6911707e+09 | E75: 343404.74 | F75: =D75-E75 -> 1690827339 | G75: 0 | H75: 773 | I75: 50194357 | J75: 571855.68 | K75: =I75-J75 -> 49622502 | L75: =I75+Apr!L75 -> 1.8529431e+08 | M75: =J75+Apr!M75 -> 18332730 | N75: =L75-M75 -> 1.6696158e+08
B76: =1+B75 -> 53 | C76: Sun Life Prosperity Bond Fund, Inc. | D76: 5883918277 | E76: 10066717 | F76: =D76-E76 -> 5873851560 | G76: 0 | H76: 18517 | I76: 73849424 | J76: 79472628 | K76: =I76-J76 -> -5623204 | L76: =I76+Apr!L76 -> 482325726 | M76: =J76+Apr!M76 -> 549208746 | N76: =L76-M76 -> -66883020
B77: =1+B76 -> 54 | C77: Sun Life Prosperity GS Fund, Inc. | D77: 144832461 | E77: 449304 | F77: =D77-E77 -> 144383157 | G77: 0 | H77: 2792 | I77: 426059 | J77: 2556078 | K77: =I77-J77 -> -2130019 | L77: =I77+Apr!L77 -> 27258233 | M77: =J77+Apr!M77 -> 8284885 | N77: =L77-M77 -> 18973348
A78: Corporate Debt Vehicle (units)
B79: =1+B77 -> 55 | C79: ATRAM Unitized Corporate Debt Vehicle, Inc. | D79: 7.0312446e+08 | E79: 201070 | F79: =D79-E79 -> 7.0292339e+08 | G79: 0 | H79: 13 | I79: 0 | J79: 0 | K79: =I79-J79 -> 0 | L79: =I79+Apr!L79 -> 0 | M79: =J79+Apr!M79 -> 0 | N79: =L79-M79 -> 0
A80: Sub total - Peso Currency | D80: =SUM(D67:D79) -> 49212004201 | E80: =SUM(E67:E79) -> 3.1557436e+08 | F80: =SUM(F67:F79) -> 48896429841 | G80: =SUM(G67:G79) -> 255250000 | H80: =SUM(H67:H79) -> 59449 | I80: =SUM(I67:I79) -> 2.9589589e+08 | J80: =SUM(J67:J79) -> 4.8597201e+08 | K80: =SUM(K67:K79) -> -1.9007612e+08 | ... N80: =SUM(N67:N79) -> -1674778271
A81: Primarily invested in foreign currency securities (shares)
B82: =1+B79 -> 56 | C82: ALFM Dollar Bond Fund, Inc. | D82: 13039767130 | E82: 102813564 | F82: =D82-E82 -> 12936953566 | G82: 0 | H82: 7671 | I82: 15319345 | J82: 245730125 | K82: =I82-J82 -> -230410780 | L82: =I82+Apr!L82 -> 115925809 | M82: =J82+Apr!M82 -> 682894478 | N82: =L82-M82 -> -566968669
B83: =1+B82 -> 57 | C83: ATRAM Total Return Dollar Bond Fund, Inc. | D83: 2.2346676e+08 | E83: 19339.21 | F83: =D83-E83 -> 2.2344742e+08 | G83: 0 | H83: 125 | I83: 106472.4 | J83: 292783.45 | K83: =I83-J83 -> -186311.05 | L83: =I83+Apr!L83 -> 361404.48 | M83: =J83+Apr!M83 -> 42651252 | N83: =L83-M83 -> -42289848
B84: =1+B83 -> 58 | C84: First Metro Save and Learn Dollar Bond Fund, Inc. | D84: 384442590 | E84: 1027773 | F84: =D84-E84 -> 383414817 | G84: 0 | H84: 153 | I84: 705351 | J84: 71336822 | K84: =I84-J84 -> -70631471 | L84: =I84+Apr!L84 -> 5093180 | M84: =J84+Apr!M84 -> 76100083 | N84: =L84-M84 -> -71006903
B85: =1+B84 -> 59 | C85: PAMI Global Bond Fund, Inc. | D85: 69789619 | E85: 16129620 | F85: =D85-E85 -> 53659999 | G85: 0 | H85: 27 | I85: 0 | J85: 0 | K85: =I85-J85 -> 0 | L85: =I85+Apr!L85 -> 0 | M85: =J85+Apr!M85 -> 0 | N85: =L85-M85 -> 0
B86: =1+B85 -> 60 | C86: Philam Dollar Bond Fund, Inc. | D86: 1878514010 | E86: 16171724 | F86: =D86-E86 -> 1862342286 | G86: 0 | H86: 1736 | I86: 17377 | J86: 17754060 | K86: =I86-J86 -> -17736683 | L86: =I86+Apr!L86 -> 228863 | M86: =J86+Apr!M86 -> 109356968 | N86: =L86-M86 -> -109128105
B87: =1+B86 -> 61 | C87: Philequity Dollar Income Fund, Inc. | D87: 2.3932902e+08 | E87: 1622083.5 | F87: =D87-E87 -> 2.3770694e+08 | G87: 0 | H87: 113 | I87: 266396.03 | J87: 0 | K87: =I87-J87 -> 266396.03 | L87: =I87+Apr!L87 -> 883506.03 | M87: =J87+Apr!M87 -> 7723341.9 | N87: =L87-M87 -> -6839835.9
B88: =1+B87 -> 62 | C88: Sun Life Prosperity Dollar Abundance Fund, Inc. | D88: 621122383 | E88: 23065362 | F88: =D88-E88 -> 598057021 | G88: 0 | H88: 2619 | I88: 1228073 | J88: 18625287 | K88: =I88-J88 -> -17397214 | L88: =I88+Apr!L88 -> 31245838 | M88: =J88+Apr!M88 -> 30632264 | N88: =L88-M88 -> 613574
A89: Sub total - US Currency | D89: =SUM(D82:D88) -> 16456431513 | E89: =SUM(E82:E88) -> 1.6084947e+08 | F89: =SUM(F82:F88) -> 16295582048 | G89: =SUM(G82:G88) -> 0 | H89: =SUM(H82:H88) -> 12444 | I89: =SUM(I82:I88) -> 17643014 | J89: =SUM(J82:J88) -> 3.5373908e+08 | K89: =SUM(K82:K88) -> -336096063 | ... N89: =SUM(N82:N88) -> -7.9561979e+08
B90: =1+B88 -> 63 | C90: ALFM Euro Bond Fund, Inc. | D90: 974792393 | E90: 6997798 | F90: =D90-E90 -> 967794595 | G90: 0 | H90: 600 | I90: 7309748 | J90: 2169156 | K90: =I90-J90 -> 5140592 | L90: =I90+Apr!L90 -> 13398962 | M90: =J90+Apr!M90 -> 24031209 | N90: =L90-M90 -> -10632247
A91: Sub total - Euro Currency | D91: =SUM(D90) -> 974792393 | E91: =SUM(E90) -> 6997798 | F91: =SUM(F90) -> 967794595 | G91: =SUM(G90) -> 0 | H91: =SUM(H90) -> 600 | I91: =SUM(I90) -> 7309748 | J91: =SUM(J90) -> 2169156 | K91: =SUM(K90) -> 5140592 | ... N91: =SUM(N90) -> -10632247
A92: Sub total - bond funds | D92: =D80+D89+D91 -> 66643228108 | E92: =E80+E89+E91 -> 4.8342162e+08 | F92: =F80+F89+F91 -> 66159806484 | G92: =G80+G89+G91 -> 255250000 | H92: =H80+H89+H91 -> 72493 | I92: =I80+I89+I91 -> 320848655 | J92: =J80+J89+J91 -> 8.4188024e+08 | K92: =K80+K89+K91 -> -5.2103159e+08 | ... N92: =N80+N89+N91 -> -2481030305
A93: Money Market Funds
A94: Primarily invested in Peso Securities (shares)
B95: 64 | C95: AIB Money Market Mutual Fund, Inc. | D95: 1.7875446e+08 | E95: 311388.6 | F95: =D95-E95 -> 178443072 | G95: 0 | H95: 67 | I95: 1472431.5 | J95: 119000 | K95: =I95-J95 -> 1353431.5 | L95: =I95+Apr!L95 -> 15904807 | M95: =J95+Apr!M95 -> 119000 | N95: =L95-M95 -> 15785807
B96: 65 | C96: ALFM Money Market Fund, Inc. | D96: 24401096620 | E96: 15431687 | F96: =D96-E96 -> 24385664933 | G96: 0 | H96: 24273 | I96: 329530 | J96: 575713455 | K96: =I96-J96 -> -575383925 | L96: =I96+Apr!L96 -> 1701463 | M96: =J96+Apr!M96 -> 2935151508 | N96: =L96-M96 -> -2933450045
B97: =1+B96 -> 66 | C97: First Metro Save and Learn Money Market Fund, Inc. | D97: 3219789371 | E97: 8616960 | F97: =D97-E97 -> 3211172411 | G97: 0 | H97: 1183 | I97: 409356678 | J97: 895660577 | K97: =I97-J97 -> -486303899 | L97: =I97+Apr!L97 -> 2377322380 | M97: =J97+Apr!M97 -> 2459793357 | N97: =L97-M97 -> -82470977
B98: =1+B97 -> 67 | C98: Sun Life Prosperity Peso Starter Fund, Inc. | D98: 16746852915 | E98: 91203030 | F98: =D98-E98 -> 16655649885 | G98: 0 | H98: 70850 | I98: 392131009 | J98: 1471023471 | K98: =I98-J98 -> -1078892462 | L98: =I98+Apr!L98 -> 2185346189 | M98: =J98+Apr!M98 -> 6529212948 | N98: =L98-M98 -> -4343866759
A99: Primarily invested in Peso Securities (units)
B100: =1+B98 -> 68 | C100: ALFM Money Market Fund, Inc. | D100: 9929841158 | E100: 7483609 | F100: =D100-E100 -> 9922357549 | G100: 0 | H100: 18773 | I100: 1162209232 | J100: 741943957 | K100: =I100-J100 -> 420265275 | L100: =I100+Apr!L100 -> 5632987929 | M100: =J100+Apr!M100 -> 4044785833 | N100: =L100-M100 -> 1588202096
A101: Sub total - Peso Currency | D101: =SUM(D95:D98)+D100 -> 54476334525 | E101: =SUM(E95:E98)+E100 -> 1.2304667e+08 | F101: =SUM(F95:F98)+F100 -> 54353287850 | G101: =SUM(G95:G98)+G100 -> 0 | H101: =SUM(H95:H98)+H100 -> 115146 | I101: =SUM(I95:I98)+I100 -> 1965498881 | J101: =SUM(J95:J98)+J100 -> 3684460460 | K101: =SUM(K95:K98)+K100 -> -1718961580 | ... N101: =SUM(N95:N98)+N100 -> -5755799878
A102: Primarily invested in foreign currency securities (shares)
B103: =1+B100 -> 69 | C103: Sun Life Prosperity Dollar Starter Fund, Inc. | D103: 2396830834 | E103: 9440486 | F103: =D103-E103 -> 2387390348 | G103: 0 | H103: 3687 | I103: 16395572 | J103: 151828249 | K103: =I103-J103 -> -135432677 | L103: =I103+Apr!L103 -> 626955513 | M103: =J103+Apr!M103 -> 765690664 | N103: =L103-M103 -> -138735151
A104: Sub total - US Currency | D104: =SUM(D103) -> 2396830834 | E104: =SUM(E103) -> 9440486 | F104: =SUM(F103) -> 2387390348 | G104: =SUM(G103) -> 0 | H104: =SUM(H103) -> 3687 | I104: =SUM(I103) -> 16395572 | J104: =SUM(J103) -> 151828249 | K104: =SUM(K103) -> -135432677 | ... N104: =SUM(N103) -> -138735151
A105: Sub total - money market funds | D105: =D101+D104 -> 56873165359 | E105: =E101+E104 -> 1.3248716e+08 | F105: =F101+F104 -> 56740678198 | G105: =G101+G104 -> 0 | H105: =H101+H104 -> 118833 | I105: =I101+I104 -> 1981894453 | J105: =J101+J104 -> 3836288709 | K105: =K101+K104 -> -1854394257 | ... N105: =N101+N104 -> -5894535029
...

Sheet May UPDATED
A1: PHILIPPINE INVESTMENT FUNDS ASSOCIATION, INC.
A2: MUTUAL FUNDS STATISTICAL REPORT
A3: Month of May 2024
A4: (Amounts in Peso)
I5: F O R - T H E - M O N T H | L5: Y E A R - T O - D A T E
A6: Fund Category | C6: Fund Name | D6: ASSETS | E6: LIABILITIES | F6: NET ASSETS | G6: EQUITY INV. | H6: NO. OF A/C | I6: SALES | J6: REDEMPTIONS | K6: NET SALES | L6: TOTAL SALES | M6: TOTAL REDEMPTIONS | N6: TOTAL NET SALES
A7: Stock Funds
A8: Primarily invested in Peso Securities (shares)
B9: 1 | C9: ALFM Growth Fund, Inc. | D9: 4114788301 | E9: 16837865 | F9: =D9-E9 -> 4097950436 | G9: 3918040331 | H9: 6365 | I9: 4301884 | J9: 43398326 | K9: =I9-J9 -> -39096442 | L9: =I9+Apr!L9 -> 21278864 | M9: =J9+Apr!M9 -> 254733250 | N9: =L9-M9 -> -233454386
B10: =1+B9 -> 2 | C10: ATRAM Alpha Opportunity Fund, Inc. | D10: 7.8519195e+08 | E10: 2765724.9 | F10: =D10-E10 -> 7.8242622e+08 | G10: 7.3942494e+08 | H10: 4000 | I10: 12157264 | J10: 63510391 | K10: =I10-J10 -> -51353127 | L10: =I10+Apr!L10 -> 22213321 | M10: =J10+Apr!M10 -> 1.1370784e+08 | N10: =L10-M10 -> -91494517
B11: =1+B10 -> 3 | C11: ATRAM Phil. Equity Opportunity Fund, Inc. | D11: 1.2470821e+09 | E11: 1.0964911e+08 | F11: =D11-E11 -> 1137433028 | G11: 1.0686439e+09 | H11: 2626 | I11: 3593981.3 | J11: 1.1190924e+08 | K11: =I11-J11 -> -1.0831526e+08 | L11: =I11+Apr!L11 -> 42215712 | M11: =J11+Apr!M11 -> 2.4291245e+08 | N11: =L11-M11 -> -2.0069674e+08
B12: =1+B11 -> 4 | C12: Climbs Share Capital Equity Investment Fund Corp. | D12: 4.2719516e+08 | E12: 14459284 | F12: =D12-E12 -> 4.1273587e+08 | G12: 3.2724066e+08 | H12: 1764 | I12: 1758548 | J12: 174565.04 | K12: =I12-J12 -> 1583983 | L12: =I12+Apr!L12 -> 69142568 | M12: =J12+Apr!M12 -> 9449438.7 | N12: =L12-M12 -> 59693130
B13: =1+B12 -> 5 | C13: First Metro Consumer Fund, Inc. | D13: 470998960 | E13: 3001073 | F13: =D13-E13 -> 467997887 | G13: 427372598 | H13: 1271 | I13: 281811 | J13: 1625028 | K13: =I13-J13 -> -1343217 | L13: =I13+Apr!L13 -> 64631716 | M13: =J13+Apr!M13 -> 75395058 | N13: =L13-M13 -> -10763342
B14: =1+B13 -> 6 | C14: First Metro Save and Learn Equity Fund, Inc. | D14: 3679149560 | E14: 95646435 | F14: =D14-E14 -> 3583503125 | G14: 3371420641 | H14: 15063 | I14: 9872816 | J14: 44146222 | K14: =I14-J14 -> -34273406 | L14: =I14+Apr!L14 -> 566441722 | M14: =J14+Apr!M14 -> 1308117799 | N14: =L14-M14 -> -741676077
B15: =1+B14 -> 7 | C15: First Metro Save and Learn Phil. Index Fund, Inc. | D15: 118989573 | E15: 5978976 | F15: =D15-E15 -> 113010597 | G15: 100570166 | H15: 506 | I15: 15926426 | J15: 254849 | K15: =I15-J15 -> 15671577 | L15: =I15+Apr!L15 -> 17364100 | M15: =J15+Apr!M15 -> 5097601 | N15: =L15-M15 -> 12266499
B16: =1+B15 -> 8 | C16: MBG Equity Investment Fund, Inc. | D16: 134979483 | E16: 1718998 | F16: =D16-E16 -> 133260485 | G16: 123915955 | H16: 47 | I16: 0 | J16: 0 | K16: =I16-J16 -> 0 | L16: =I16+Apr!L16 -> 23000000 | M16: =J16+Apr!M16 -> 7542618 | N16: =L16-M16 -> 15457382
B17: =1+B16 -> 9 | C17: PAMI Equity Index Fund, Inc. | D17: 1145258534 | E17: 29853423 | F17: =D17-E17 -> 1115405111 | G17: 1127104795 | H17: 11440 | I17: 0 | J17: 9483523 | K17: =I17-J17 -> -9483523 | L17: =I17+Apr!L17 -> 0 | M17: =J17+Apr!M17 -> 66300547 | N17: =L17-M17 -> -66300547
B18: =1+B17 -> 10 | C18: Philam Strategic Growth Fund, Inc. | D18: 3372360836 | E18: 28863147 | F18: =D18-E18 -> 3343497689 | G18: 3208019197 | H18: 11347 | I18: 6598010 | J18: 15263035 | K18: =I18-J18 -> -8665025 | L18: =I18+Apr!L18 -> 34093610 | M18: =J18+Apr!M18 -> 160790953 | N18: =L18-M18 -> -126697343
B19: =1+B18 -> 11 | C19: Philequity Dividend Yield Fund, Inc. | D19: 2.3892951e+09 | E19: 8145658.1 | F19: =D19-E19 -> 2381149456 | G19: 2.1891663e+09 | H19: 4873 | I19: 2771733.6 | J19: 8062768.3 | K19: =I19-J19 -> -5291034.8 | L19: =I19+Apr!L19 -> 14598504 | M19: =J19+Apr!M19 -> 28812126 | N19: =L19-M19 -> -14213623
B20: =1+B19 -> 12 | C20: Philequity Fund, Inc. | D20: 9.2512941e+09 | E20: 49281085 | F20: =D20-E20 -> 9202013043 | G20: 8.4155578e+09 | H20: 33438 | I20: 8118872.5 | J20: 49146025 | K20: =I20-J20 -> -41027152 | L20: =I20+Apr!L20 -> 48242351 | M20: =J20+Apr!M20 -> 2.465217e+08 | N20: =L20-M20 -> -1.9827935e+08
B21: =1+B20 -> 13 | C21: Philequity MSCI Phil. Index Fund, Inc. | D21: 3.0666187e+08 | E21: 964165.84 | F21: =D21-E21 -> 3.0569771e+08 | G21: 2.9927956e+08 | H21: 918 | I21: 673929.16 | J21: 176216.28 | K21: =I21-J21 -> 497712.88 | L21: =I21+Apr!L21 -> 2100759.5 | M21: =J21+Apr!M21 -> 6105504.2 | N21: =L21-M21 -> -4004744.7
... B27: =1+B26 -> 19 | C27: United Fund, Inc. | D27: 6.0377667e+08 | E27: 16176386 | F27: =D27-E27 -> 5.8760029e+08 | G27: 5.3372861e+08 | H27: 1230 | I27: 384084.82 | J27: 552820.07 | K27: =I27-J27 -> -168735.25 | L27: =I27+Apr!L27 -> 10478232 | M27: =J27+Apr!M27 -> 6680897.9 | N27: =L27-M27 -> 3797334.3
A28: Primarily invested in Peso Securities (units)
B29: =1+B27 -> 20 | C29: COL Equity Index Unitized Mutual Fund, Inc. | D29: 2.2485669e+08 | E29: 1411560 | F29: =D29-E29 -> 2.2344513e+08 | G29: 2.1843907e+08 | H29: 3594 | I29: 6595133.9 | J29: 1493387.5 | K29: =I29-J29 -> 5101746.3 | L29: =I29+Apr!L29 -> 30511907 | M29: =J29+Apr!M29 -> 37910264 | N29: =L29-M29 -> -7398356.4
B30: =1+B29 -> 21 | C30: COL Strategic Growth Equity Unitized Mutual Fund, Inc. | D30: 2.7490098e+08 | E30: 6138558 | F30: =D30-E30 -> 2.6876242e+08 | G30: 175221460 | H30: 3368 | I30: 14491781 | J30: 4210310.9 | K30: =I30-J30 -> 10281470 | L30: =I30+Apr!L30 -> 1.7968439e+08 | M30: =J30+Apr!M30 -> 21910411 | N30: =L30-M30 -> 1.5777397e+08
B31: =1+B30 -> 22 | C31: Philequity Alpha One Fund, Inc. | D31: 2.9549599e+08 | E31: 3292576.6 | F31: =D31-E31 -> 2.9220341e+08 | G31: 2.6612999e+08 | H31: 1201 | I31: 210603.36 | J31: 2243687.3 | K31: =I31-J31 -> -2033083.9 | L31: =I31+Apr!L31 -> 2644184.7 | M31: =J31+Apr!M31 -> 22970401 | N31: =L31-M31 -> -20326216
B32: =1+B31 -> 23 | C32: Philippine Stock Index Fund Corp. | D32: 609387098 | E32: 6781623 | F32: =D32-E32 -> 602605475 | G32: 597059392 | H32: 655066 | I32: 19542511 | J32: 13060471 | K32: =I32-J32 -> 6482040 | L32: =I32+Apr!L32 -> 98326966 | M32: =J32+Apr!M32 -> 118410620 | N32: =L32-M32 -> -20083654
A33: Exchange Traded Fund
B34: =1+B32 -> 24 | C34: First Metro Phil. Equity Exchange Traded Fund, Inc. | D34: 1981619812 | E34: 2023313 | F34: =D34-E34 -> 1979596499 | G34: 1960685178 | H34: 3242 | I34: 0 | J34: 84244427 | K34: =I34-J34 -> -84244427 | L34: =I34+Apr!L34 -> 14535918 | M34: =J34+Apr!M34 -> 203838390 | N34: =L34-M34 -> -189302472
A35: Sub total - Peso Currency | D35: =SUM(D9:D34) -> 62485996471 | E35: =SUM(E9:E34) -> 5.9875444e+08 | F35: =SUM(F9:F34) -> 61887242026 | G35: =SUM(G9:G34) -> 59476959768 | H35: =SUM(H9:H34) -> 936364 | I35: =SUM(I9:I34) -> 209184762 | J35: =SUM(J9:J34) -> 1130093881 | K35: =SUM(K9:K34) -> -9.2090912e+08 | ... N35: =SUM(N9:N34) -> -3982371875
A36: Primarily invested in foreign currency securities (shares)
B37: =1+B34 -> 25 | C37: ATRAM AsiaPlus Equity Fund, Inc. | D37: 27817915 | E37: 249639.35 | F37: =D37-E37 -> 27568276 | G37: 0 | H37: 50 | I37: 35069.72 | J37: 41280.56 | K37: =I37-J37 -> -6210.84 | L37: =I37+Apr!L37 -> 387437.25 | M37: =J37+Apr!M37 -> 81400.79 | N37: =L37-M37 -> 306036.46
B38: =1+B37 -> 26 | C38: Sun Life Prosperity World Voyager Fund, Inc. | D38: 1917208482 | E38: 57050271 | F38: =D38-E38 -> 1860158211 | G38: 0 | H38: 2998 | I38: 13945134 | J38: 50383339 | K38: =I38-J38 -> -36438205 | L38: =I38+Apr!L38 -> 74629604 | M38: =J38+Apr!M38 -> 447919923 | N38: =L38-M38 -> -373290319
A39: Sub total - US Currency | D39: =SUM(D37:D38) -> 1945026397 | E39: =SUM(E37:E38) -> 57299910 | F39: =SUM(F37:F38) -> 1887726487 | G39: =SUM(G37:G38) -> 0 | H39: =SUM(H37:H38) -> 3048 | I39: =SUM(I37:I38) -> 13980204 | J39: =SUM(J37:J38) -> 50424620 | K39: =SUM(K37:K38) -> -36444416 | ... N39: =SUM(N37:N38) -> -3.7298428e+08
A40: Sub total - stock funds | D40: =D35+D39 -> 64431022868 | E40: =E35+E39 -> 6.5605436e+08 | F40: =F35+F39 -> 63774968513 | G40: =G35+G39 -> 59476959768 | H40: =H35+H39 -> 939412 | I40: =I35+I39 -> 2.2316497e+08 | J40: =J35+J39 -> 1180518500 | K40: =K35+K39 -> -9.5735353e+08 | ... N40: =N35+N39 -> -4355356158
A41: Balanced Funds
A42: Primarily invested in Peso Securities (shares)
B43: =1+B38 -> 27 | C43: ATRAM Philippine Balanced Fund, Inc. | D43: 4.2968468e+08 | E43: 1177078.3 | F43: =D43-E43 -> 4.285076e+08 | G43: 2.3113906e+08 | H43: 2320 | I43: 426316.56 | J43: 3619093 | K43: =I43-J43 -> -3192776.5 | L43: =I43+Apr!L43 -> 3105483.3 | M43: =J43+Apr!M43 -> 31147638 | N43: =L43-M43 -> -28042155
B44: =1+B43 -> 28 | C44: ATRAM Unicapital Diversified Growth Fund, Inc. | D44: 1.1245545e+08 | E44: 329787.42 | F44: =D44-E44 -> 1.1212567e+08 | G44: 32708230 | H44: 694 | I44: 116044.44 | J44: 3611140.2 | K44: =I44-J44 -> -3495095.8 | L44: =I44+Apr!L44 -> 1282464.2 | M44: =J44+Apr!M44 -> 7280464.1 | N44: =L44-M44 -> -5997999.9
B45: =1+B44 -> 29 | C45: First Metro Save and Learn Balanced Fund, Inc. | D45: 790243747 | E45: 15515262 | F45: =D45-E45 -> 774728485 | G45: 450616886 | H45: 4294 | I45: 983683 | J45: 7661747 | K45: =I45-J45 -> -6678064 | L45: =I45+Apr!L45 -> 9809411 | M45: =J45+Apr!M45 -> 182544100 | N45: =L45-M45 -> -172734689
B46: =1+B45 -> 30 | C46: First Metro Save and Learn F.O.C.C.U.S. Dynamic Fund, Inc. | D46: 297494662 | E46: 762060 | F46: =D46-E46 -> 296732602 | G46: 272476183 | H46: 241 | I46: 6199892 | J46: 7926601 | K46: =I46-J46 -> -1726709 | L46: =I46+Apr!L46 -> 181997278 | M46: =J46+Apr!M46 -> 186797518 | N46: =L46-M46 -> -4800240
B47: =1+B46 -> 31 | C47: NCM Mutual Fund of the Phils., Inc. | D47: 3.2225255e+08 | E47: 1381737.6 | F47: =D47-E47 -> 3.2087081e+08 | G47: 1.57311e+08 | H47: 48 | I47: 0 | J47: 0 | K47: =I47-J47 -> 0 | L47: =I47+Apr!L47 -> 0 | M47: =J47+Apr!M47 -> 66119 | N47: =L47-M47 -> -66119
B48: =1+B47 -> 32 | C48: PAMI Horizon Fund, Inc. | D48: 489742681 | E48: 14932478 | F48: =D48-E48 -> 474810203 | G48: 234352926 | H48: 9813 | I48: 107856 | J48: 11277010 | K48: =I48-J48 -> -11169154 | L48: =I48+Apr!L48 -> 2918616 | M48: =J48+Apr!M48 -> 30999327 | N48: =L48-M48 -> -28080711
B49: =1+B48 -> 33 | C49: Philam Fund, Inc. | D49: 1910899929 | E49: 18492933 | F49: =D49-E49 -> 1892406996 | G49: 909516858 | H49: 7653 | I49: 636226 | J49: 9511047 | K49: =I49-J49 -> -8874821 | L49: =I49+Apr!L49 -> 12598527 | M49: =J49+Apr!M49 -> 89801279 | N49: =L49-M49 -> -77202752
B50: =1+B49 -> 34 | C50: Solidaritas Fund, Inc. | D50: 118790066 | E50: 744126 | F50: =D50-E50 -> 118045940 | G50: 57367650 | H50: 171 | I50: 0 | J50: 15305 | K50: =I50-J50 -> -15305 | L50: =I50+Apr!L50 -> 0 | M50: =J50+Apr!M50 -> 1906233 | N50: =L50-M50 -> -1906233
B51: =1+B50 -> 35 | C51: Sun Life Prosperity Balanced Fund, Inc. | D51: 6517444512 | E51: 133417900 | F51: =D51-E51 -> 6384026612 | G51: 3289572767 | H51: 54274 | I51: 9086128 | J51: 80896303 | K51: =I51-J51 -> -71810175 | L51: =I51+Apr!L51 -> 56343160 | M51: =J51+Apr!M51 -> 411153795 | N51: =L51-M51 -> -354810635
B52: =1+B51 -> 36 | C52: Sun Life Prosperity Dynamic Fund, Inc. | D52: 563285703 | E52: 25241303 | F52: =D52-E52 -> 538044400 | G52: 300817444 | H52: 5000 | I52: 0 | J52: 10417716 | K52: =I52-J52 -> -10417716 | L52: =I52+Apr!L52 -> 0 | M52: =J52+Apr!M52 -> 90694691 | N52: =L52-M52 -> -90694691
A53: Primarily invested in Peso Securities (units)
B54: =1+B52 -> 37 | C54: Sun Life Prosperity Achiever Fund 2028, Inc. | D54: 97063750 | E54: 821227 | F54: =D54-E54 -> 96242523 | G54: 24294409 | H54: 1182 | I54: 214943 | J54: 1610047 | K54: =I54-J54 -> -1395104 | L54: =I54+Apr!L54 -> 20868434 | M54: =J54+Apr!M54 -> 2765210 | N54: =L54-M54 -> 18103224
B55: =1+B54 -> 38 | C55: Sun Life Prosperity Achiever Fund 2038, Inc. | D55: 55840817 | E55: 232134 | F55: =D55-E55 -> 55608683 | G55: 42651699 | H55: 469 | I55: 418812 | J55: 52032 | K55: =I55-J55 -> 366780 | L55: =I55+Apr!L55 -> 942835 | M55: =J55+Apr!M55 -> 305473 | N55: =L55-M55 -> 637362
B56: =1+B55 -> 39 | C56: Sun Life Prosperity Achiever Fund 2048, Inc. | D56: 46806443 | E56: 221440 | F56: =D56-E56 -> 46585003 | G56: 38267090 | H56: 219 | I56: 89131 | J56: 66496 | K56: =I56-J56 -> 22635 | L56: =I56+Apr!L56 -> 295954 | M56: =J56+Apr!M56 -> 449428 | N56: =L56-M56 -> -153474
A57: Sub total - Peso Currency | D57: =SUM(D43:D56) -> 11752004992 | E57: =SUM(E43:E56) -> 2.1326947e+08 | F57: =SUM(F43:F56) -> 11538735526 | G57: =SUM(G43:G56) -> 6041092194 | H57: =SUM(H43:H56) -> 86378 | I57: =SUM(I43:I56) -> 18279032 | J57: =SUM(J43:J56) -> 1.3666454e+08 | K57: =SUM(K43:K56) -> -1.1838551e+08 | ... N57: =SUM(N43:N56) -> -7.4574911e+08
A58: Primarily invested in foreign currency securities (shares)
B59: =1+B56 -> 40 | C59: Cocolife Dollar Fund Builder, Inc. | D59: 73929323 | E59: 386506.53 | F59: =D59-E59 -> 73542816 | G59: 0 | H59: 49 | I59: 0 | J59: 134572.41 | K59: =I59-J59 -> -134572.41 | L59: =I59+Apr!L59 -> 84501.37 | M59: =J59+Apr!M59 -> 214065.62 | N59: =L59-M59 -> -129564.25
B60: =1+B59 -> 41 | C60: PAMI Asia Balanced Fund, Inc. | D60: 335120787 | E60: 18070996 | F60: =D60-E60 -> 317049791 | G60: 174015865 | H60: 232 | I60: 0 | J60: 6225060 | K60: =I60-J60 -> -6225060 | L60: =I60+Apr!L60 -> 28146 | M60: =J60+Apr!M60 -> 15764263 | N60: =L60-M60 -> -15736117
B61: =1+B60 -> 42 | C61: Sun Life Prosperity Dollar Advantage Fund, Inc. | D61: 1480951634 | E61: 30697772 | F61: =D61-E61 -> 1450253862 | G61: 0 | H61: 4196 | I61: 7747950 | J61: 36622095 | K61: =I61-J61 -> -28874145 | L61: =I61+Apr!L61 -> 35199230 | M61: =J61+Apr!M61 -> 225142564 | N61: =L61-M61 -> -189943334
B62: =1+B61 -> 43 | C62: Sun Life Prosperity Dollar Wellspring Fund, Inc. | D62: 249785986 | E62: 3241022 | F62: =D62-E62 -> 246544964 | G62: 0 | H62: 748 | I62: 0 | J62: 14207167 | K62: =I62-J62 -> -14207167 | L62: =I62+Apr!L62 -> 4303725 | M62: =J62+Apr!M62 -> 27101157 | N62: =L62-M62 -> -22797432
A63: Sub total - US Currency | D63: =SUM(D59:D62) -> 2139787730 | E63: =SUM(E59:E62) -> 52396297 | F63: =SUM(F59:F62) -> 2087391433 | G63: =SUM(G59:G62) -> 174015865 | H63: =SUM(H59:H62) -> 5225 | I63: =SUM(I59:I62) -> 7747950 | J63: =SUM(J59:J62) -> 57188894 | K63: =SUM(K59:K62) -> -49440944 | ... N63: =SUM(N59:N62) -> -2.2860645e+08
A64: Sub total - balanced funds | D64: =D57+D63 -> 13891792722 | E64: =E57+E63 -> 2.6566576e+08 | F64: =F57+F63 -> 13626126959 | G64: =G57+G63 -> 6215108059 | H64: =H57+H63 -> 91603 | I64: =I57+I63 -> 26026982 | J64: =J57+J63 -> 1.9385343e+08 | K64: =K57+K63 -> -1.6782645e+08 | ... N64: =N57+N63 -> -9.7435556e+08
A65: Bond Funds
A66: Primarily invested in Peso Securities (shares)
B67: =1+B62 -> 44 | C67: ALFM Peso Bond Fund, Inc. | D67: 35739892690 | E67: 237125583 | F67: =D67-E67 -> 35502767107 | G67: 255250000 | H67: 23392 | I67: 140135821 | J67: 371224663 | K67: =I67-J67 -> -231088842 | L67: =I67+Apr!L67 -> 746988932 | M67: =J67+Apr!M67 -> 2191912181 | N67: =L67-M67 -> -1444923249
B68: =1+B67 -> 45 | C68: ATRAM Corporate Bond Fund, Inc. | D68: 3.4334711e+08 | E68: 2753110.6 | F68: =D68-E68 -> 3.40594e+08 | G68: 0 | H68: 990 | I68: 278345.05 | J68: 5743071.7 | K68: =I68-J68 -> -5464726.7 | L68: =I68+Apr!L68 -> 14051024 | M68: =J68+Apr!M68 -> 1.0940723e+08 | N68: =L68-M68 -> -95356208
B69: =1+B68 -> 46 | C69: Cocolife Fixed Income Fund, Inc. | D69: 9.0167354e+08 | E69: 9074321.4 | F69: =D69-E69 -> 8.9259921e+08 | G69: 0 | H69: 1840 | I69: 14186950 | J69: 6444268.7 | K69: =I69-J69 -> 7742680.8 | L69: =I69+Apr!L69 -> 34218060 | M69: =J69+Apr!M69 -> 54359645 | N69: =L69-M69 -> -20141585
B70: =1+B69 -> 47 | C70: Ekklesia Mutual Fund, Inc. | D70: 186197851 | E70: 175805 | F70: =D70-E70 -> 186022046 | G70: 0 | H70: 155 | I70: 0 | J70: 15064 | K70: =I70-J70 -> -15064 | L70: =I70+Apr!L70 -> 0 | M70: =J70+Apr!M70 -> 9866735 | N70: =L70-M70 -> -9866735
B71: =1+B70 -> 48 | C71: First Metro Save and Learn Fixed Income Fund, Inc. | D71: 1149447069 | E71: 7544345 | F71: =D71-E71 -> 1141902724 | G71: 0 | H71: 1766 | I71: 5541657 | J71: 8430134 | K71: =I71-J71 -> -2888477 | L71: =I71+Apr!L71 -> 149146560 | M71: =J71+Apr!M71 -> 275529840 | N71: =L71-M71 -> -126383280
B72: =1+B71 -> 49 | C72: Philam Bond Fund, Inc. | D72: 1550267902 | E72: 33362867 | F72: =D72-E72 -> 1516905035 | G72: 0 | H72: 4773 | I72: 3418117 | J72: 3608905 | K72: =I72-J72 -> -190788 | L72: =I72+Apr!L72 -> 15129213 | M72: =J72+Apr!M72 -> 96001188 | N72: =L72-M72 -> -80871975
B73: =1+B72 -> 50 | C73: Philam Managed Income Fund, Inc. | D73: 597530564 | E73: 13739293 | F73: =D73-E73 -> 583791271 | G73: 0 | H73: 440 | I73: 7039859 | J73: 5542579 | K73: =I73-J73 -> 1497280 | L73: =I73+Apr!L73 -> 12977618 | M73: =J73+Apr!M73 -> 21837263 | N73: =L73-M73 -> -8859645
B74: =1+B73 -> 51 | C74: Philequity Peso Bond Fund, Inc. | D74: 3.2060153e+08 | E74: 1274174.9 | F74: =D74-E74 -> 3.1932736e+08 | G74: 0 | H74: 3998 | I74: 825303.58 | J74: 2362761.7 | K74: =I74-J74 -> -1537458.1 | L74: =I74+Apr!L74 -> 3218510.1 | M74: =J74+Apr!M74 -> 10646008 | N74: =L74-M74 -> -7427497.7
B75: =1+B74 -> 52 | C75: Soldivo Bond Fund, Inc. | D75: 1.6911707e+09 | E75: 2948032.8 | F75: =D75-E75 -> 1688222710 | G75: 0 | H75: 773 | I75: 50194357 | J75: 571855.68 | K75: =I75-J75 -> 49622502 | L75: =I75+Apr!L75 -> 1.8529431e+08 | M75: =J75+Apr!M75 -> 18332730 | N75: =L75-M75 -> 1.6696158e+08
B76: =1+B75 -> 53 | C76: Sun Life Prosperity Bond Fund, Inc. | D76: 5883918277 | E76: 10066717 | F76: =D76-E76 -> 5873851560 | G76: 0 | H76: 18517 | I76: 73849424 | J76: 79472628 | K76: =I76-J76 -> -5623204 | L76: =I76+Apr!L76 -> 482325726 | M76: =J76+Apr!M76 -> 549208746 | N76: =L76-M76 -> -66883020
B77: =1+B76 -> 54 | C77: Sun Life Prosperity GS Fund, Inc. | D77: 144832461 | E77: 449304 | F77: =D77-E77 -> 144383157 | G77: 0 | H77: 2792 | I77: 426059 | J77: 2556078 | K77: =I77-J77 -> -2130019 | L77: =I77+Apr!L77 -> 27258233 | M77: =J77+Apr!M77 -> 8284885 | N77: =L77-M77 -> 18973348
A78: Corporate Debt Vehicle (units)
B79: =1+B77 -> 55 | C79: ATRAM Unitized Corporate Debt Vehicle, Inc. | D79: 7.0312446e+08 | E79: 1809103.1 | F79: =D79-E79 -> 7.0131536e+08 | G79: 0 | H79: 13 | I79: 0 | J79: 0 | K79: =I79-J79 -> 0 | L79: =I79+Apr!L79 -> 0 | M79: =J79+Apr!M79 -> 0 | N79: =L79-M79 -> 0
A80: Sub total - Peso Currency | D80: =SUM(D67:D79) -> 49212004201 | E80: =SUM(E67:E79) -> 3.2032266e+08 | F80: =SUM(F67:F79) -> 48891681544 | G80: =SUM(G67:G79) -> 255250000 | H80: =SUM(H67:H79) -> 59449 | I80: =SUM(I67:I79) -> 2.9589589e+08 | J80: =SUM(J67:J79) -> 4.8597201e+08 | K80: =SUM(K67:K79) -> -1.9007612e+08 | ... N80: =SUM(N67:N79) -> -1674778271
A81: Primarily invested in foreign currency securities (shares)
B82: =1+B79 -> 56 | C82: ALFM Dollar Bond Fund, Inc. | D82: 13039767130 | E82: 102813564 | F82: =D82-E82 -> 12936953566 | G82: 0 | H82: 7671 | I82: 15319345 | J82: 245730125 | K82: =I82-J82 -> -230410780 | L82: =I82+Apr!L82 -> 115925809 | M82: =J82+Apr!M82 -> 682894478 | N82: =L82-M82 -> -566968669
B83: =1+B82 -> 57 | C83: ATRAM Total Return Dollar Bond Fund, Inc. | D83: 2.2346676e+08 | E83: 2453460.6 | F83: =D83-E83 -> 2.210133e+08 | G83: 0 | H83: 125 | I83: 106472.4 | J83: 292783.45 | K83: =I83-J83 -> -186311.05 | L83: =I83+Apr!L83 -> 361404.48 | M83: =J83+Apr!M83 -> 42651252 | N83: =L83-M83 -> -42289848
B84: =1+B83 -> 58 | C84: First Metro Save and Learn Dollar Bond Fund, Inc. | D84: 384442590 | E84: 1027773 | F84: =D84-E84 -> 383414817 | G84: 0 | H84: 153 | I84: 705351 | J84: 71336822 | K84: =I84-J84 -> -70631471 | L84: =I84+Apr!L84 -> 5093180 | M84: =J84+Apr!M84 -> 76100083 | N84: =L84-M84 -> -71006903
B85: =1+B84 -> 59 | C85: PAMI Global Bond Fund, Inc. | D85: 69789619 | E85: 16129620 | F85: =D85-E85 -> 53659999 | G85: 0 | H85: 27 | I85: 0 | J85: 0 | K85: =I85-J85 -> 0 | L85: =I85+Apr!L85 -> 0 | M85: =J85+Apr!M85 -> 0 | N85: =L85-M85 -> 0
B86: =1+B85 -> 60 | C86: Philam Dollar Bond Fund, Inc. | D86: 1878514010 | E86: 16171724 | F86: =D86-E86 -> 1862342286 | G86: 0 | H86: 1736 | I86: 17377 | J86: 17754060 | K86: =I86-J86 -> -17736683 | L86: =I86+Apr!L86 -> 228863 | M86: =J86+Apr!M86 -> 109356968 | N86: =L86-M86 -> -109128105
B87: =1+B86 -> 61 | C87: Philequity Dollar Income Fund, Inc. | D87: 2.3932902e+08 | E87: 1622083.5 | F87: =D87-E87 -> 2.3770694e+08 | G87: 0 | H87: 113 | I87: 266396.03 | J87: 0 | K87: =I87-J87 -> 266396.03 | L87: =I87+Apr!L87 -> 883506.03 | M87: =J87+Apr!M87 -> 7723341.9 | N87: =L87-M87 -> -6839835.9
B88: =1+B87 -> 62 | C88: Sun Life Prosperity Dollar Abundance Fund, Inc. | D88: 621122383 | E88: 23065362 | F88: =D88-E88 -> 598057021 | G88: 0 | H88: 2619 | I88: 1228073 | J88: 18625287 | K88: =I88-J88 -> -17397214 | L88: =I88+Apr!L88 -> 31245838 | M88: =J88+Apr!M88 -> 30632264 | N88: =L88-M88 -> 613574
A89: Sub total - US Currency | D89: =SUM(D82:D88) -> 16456431513 | E89: =SUM(E82:E88) -> 1.6328359e+08 | F89: =SUM(F82:F88) -> 16293147926 | G89: =SUM(G82:G88) -> 0 | H89: =SUM(H82:H88) -> 12444 | I89: =SUM(I82:I88) -> 17643014 | J89: =SUM(J82:J88) -> 3.5373908e+08 | K89: =SUM(K82:K88) -> -336096063 | ... N89: =SUM(N82:N88) -> -7.9561979e+08
B90: =1+B88 -> 63 | C90: ALFM Euro Bond Fund, Inc. | D90: 974792393 | E90: 6997798 | F90: =D90-E90 -> 967794595 | G90: 0 | H90: 600 | I90: 7309748 | J90: 2169156 | K90: =I90-J90 -> 5140592 | L90: =I90+Apr!L90 -> 13398962 | M90: =J90+Apr!M90 -> 24031209 | N90: =L90-M90 -> -10632247
A91: Sub total - Euro Currency | D91: =SUM(D90) -> 974792393 | E91: =SUM(E90) -> 6997798 | F91: =SUM(F90) -> 967794595 | G91: =SUM(G90) -> 0 | H91: =SUM(H90) -> 600 | I91: =SUM(I90) -> 7309748 | J91: =SUM(J90) -> 2169156 | K91: =SUM(K90) -> 5140592 | ... N91: =SUM(N90) -> -10632247
A92: Sub total - bond funds | D92: =D80+D89+D91 -> 66643228108 | E92: =E80+E89+E91 -> 490604042 | F92: =F80+F89+F91 -> 66152624066 | G92: =G80+G89+G91 -> 255250000 | H92: =H80+H89+H91 -> 72493 | I92: =I80+I89+I91 -> 320848655 | J92: =J80+J89+J91 -> 8.4188024e+08 | K92: =K80+K89+K91 -> -5.2103159e+08 | ... N92: =N80+N89+N91 -> -2481030305
A93: Money Market Funds
A94: Primarily invested in Peso Securities (shares)
B95: 64 | C95: AIB Money Market Mutual Fund, Inc. | D95: 1.7875446e+08 | E95: 311388.6 | F95: =D95-E95 -> 178443072 | G95: 0 | H95: 67 | I95: 1472431.5 | J95: 119000 | K95: =I95-J95 -> 1353431.5 | L95: =I95+Apr!L95 -> 15904807 | M95: =J95+Apr!M95 -> 119000 | N95: =L95-M95 -> 15785807
B96: 65 | C96: ALFM Money Market Fund, Inc. | D96: 24401096620 | E96: 15431687 | F96: =D96-E96 -> 24385664933 | G96: 0 | H96: 24273 | I96: 329530 | J96: 575713455 | K96: =I96-J96 -> -575383925 | L96: =I96+Apr!L96 -> 1701463 | M96: =J96+Apr!M96 -> 2935151508 | N96: =L96-M96 -> -2933450045
B97: =1+B96 -> 66 | C97: First Metro Save and Learn Money Market Fund, Inc. | D97: 3219789371 | E97: 8616960 | F97: =D97-E97 -> 3211172411 | G97: 0 | H97: 1183 | I97: 409356678 | J97: 895660577 | K97: =I97-J97 -> -486303899 | L97: =I97+Apr!L97 -> 2377322380 | M97: =J97+Apr!M97 -> 2459793357 | N97: =L97-M97 -> -82470977
B98: =1+B97 -> 67 | C98: Sun Life Prosperity Peso Starter Fund, Inc. | D98: 16746852915 | E98: 91203030 | F98: =D98-E98 -> 16655649885 | G98: 0 | H98: 70850 | I98: 392131009 | J98: 1471023471 | K98: =I98-J98 -> -1078892462 | L98: =I98+Apr!L98 -> 2185346189 | M98: =J98+Apr!M98 -> 6529212948 | N98: =L98-M98 -> -4343866759
A99: Primarily invested in Peso Securities (units)
B100: =1+B98 -> 68 | C100: ALFM Money Market Fund, Inc. | D100: 9929841158 | E100: 7483609 | F100: =D100-E100 -> 9922357549 | G100: 0 | H100: 18773 | I100: 1162209232 | J100: 741943957 | K100: =I100-J100 -> 420265275 | L100: =I100+Apr!L100 -> 5632987929 | M100: =J100+Apr!M100 -> 4044785833 | N100: =L100-M100 -> 1588202096
A101: Sub total - Peso Currency | D101: =SUM(D95:D98)+D100 -> 54476334525 | E101: =SUM(E95:E98)+E100 -> 1.2304667e+08 | F101: =SUM(F95:F98)+F100 -> 54353287850 | G101: =SUM(G95:G98)+G100 -> 0 | H101: =SUM(H95:H98)+H100 -> 115146 | I101: =SUM(I95:I98)+I100 -> 1965498881 | J101: =SUM(J95:J98)+J100 -> 3684460460 | K101: =SUM(K95:K98)+K100 -> -1718961580 | ... N101: =SUM(N95:N98)+N100 -> -5755799878
A102: Primarily invested in foreign currency securities (shares)
B103: =1+B100 -> 69 | C103: Sun Life Prosperity Dollar Starter Fund, Inc. | D103: 2396830834 | E103: 9440486 | F103: =D103-E103 -> 2387390348 | G103: 0 | H103: 3687 | I103: 16395572 | J103: 151828249 | K103: =I103-J103 -> -135432677 | L103: =I103+Apr!L103 -> 626955513 | M103: =J103+Apr!M103 -> 765690664 | N103: =L103-M103 -> -138735151
A104: Sub total - US Currency | D104: =SUM(D103) -> 2396830834 | E104: =SUM(E103) -> 9440486 | F104: =SUM(F103) -> 2387390348 | G104: =SUM(G103) -> 0 | H104: =SUM(H103) -> 3687 | I104: =SUM(I103) -> 16395572 | J104: =SUM(J103) -> 151828249 | K104: =SUM(K103) -> -135432677 | ... N104: =SUM(N103) -> -138735151
A105: Sub total - money market funds | D105: =D101+D104 -> 56873165359 | E105: =E101+E104 -> 1.3248716e+08 | F105: =F101+F104 -> 56740678198 | G105: =G101+G104 -> 0 | H105: =H101+H104 -> 118833 | I105: =I101+I104 -> 1981894453 | J105: =J101+J104 -> 3836288709 | K105: =K101+K104 -> -1854394257 | ... N105: =N101+N104 -> -5894535029
...

Sheet June
A1: PHILIPPINE INVESTMENT FUNDS ASSOCIATION, INC.
A2: MUTUAL FUNDS STATISTICAL REPORT
A3: Month of June 2024
A4: (Amounts in Peso)
I5: F O R - T H E - M O N T H | L5: Y E A R - T O - D A T E
A6: Fund Category | C6: Fund Name | D6: ASSETS | E6: LIABILITIES | F6: NET ASSETS | G6: EQUITY INV. | H6: NO. OF A/C | I6: SALES | J6: REDEMPTIONS | K6: NET SALES | L6: TOTAL SALES | M6: TOTAL REDEMPTIONS | N6: TOTAL NET SALES
A7: Stock Funds
A8: Primarily invested in Peso Securities (shares)
B9: 1 | C9: ALFM Growth Fund, Inc. | D9: 4105110463 | E9: 14082940 | F9: =D9-E9 -> 4091027523 | G9: 3925863877 | H9: 6323 | I9: 3824159 | J9: 44338227 | K9: =I9-J9 -> -40514068 | L9: =I9+May!L9 -> 25103023 | M9: =J9+May!M9 -> 299071477 | N9: =L9-M9 -> -273968454
B10: =1+B9 -> 2 | C10: ATRAM Alpha Opportunity Fund, Inc. | D10: 7.490149e+08 | E10: 1889032.1 | F10: =D10-E10 -> 7.4712587e+08 | G10: 7.1593864e+08 | H10: 3987 | I10: 2635480.3 | J10: 8809048.8 | K10: =I10-J10 -> -6173568.5 | L10: =I10+May!L10 -> 24848801 | M10: =J10+May!M10 -> 1.2251689e+08 | N10: =L10-M10 -> -97668086
B11: =1+B10 -> 3 | C11: ATRAM Phil. Equity Opportunity Fund, Inc. | D11: 1.1559206e+09 | E11: 8323925.7 | F11: =D11-E11 -> 1147596703 | G11: 1.0782413e+09 | H11: 2614 | I11: 7405305.4 | J11: 4743019.6 | K11: =I11-J11 -> 2662285.8 | L11: =I11+May!L11 -> 49621017 | M11: =J11+May!M11 -> 2.4765547e+08 | N11: =L11-M11 -> -198034452
B12: =1+B11 -> 4 | C12: Climbs Share Capital Equity Investment Fund Corp. | D12: 4.3003354e+08 | E12: 8361514.9 | F12: =D12-E12 -> 4.2167203e+08 | G12: 3.2961991e+08 | H12: 1764 | I12: 4631001 | J12: 138254.16 | K12: =I12-J12 -> 4492746.8 | L12: =I12+May!L12 -> 73773569 | M12: =J12+May!M12 -> 9587692.8 | N12: =L12-M12 -> 64185876
B13: =1+B12 -> 5 | C13: First Metro Consumer Fund, Inc. | D13: 438303596 | E13: 1126378 | F13: =D13-E13 -> 437177218 | G13: 355666226 | H13: 1254 | I13: 277926 | J13: 9690331 | K13: =I13-J13 -> -9412405 | L13: =I13+May!L13 -> 64909642 | M13: =J13+May!M13 -> 85085389 | N13: =L13-M13 -> -20175747
B14: =1+B13 -> 6 | C14: First Metro Save and Learn Equity Fund, Inc. | D14: 3633781124 | E14: 123516155 | F14: =D14-E14 -> 3510264969 | G14: 3178029560 | H14: 15014 | I14: 13700437 | J14: 53072660 | K14: =I14-J14 -> -39372223 | L14: =I14+May!L14 -> 580142159 | M14: =J14+May!M14 -> 1361190459 | N14: =L14-M14 -> -781048300
B15: =1+B14 -> 7 | C15: First Metro Save and Learn Phil. Index Fund, Inc. | D15: 135482008 | E15: 5027098 | F15: =D15-E15 -> 130454910 | G15: 127872065 | H15: 504 | I15: 23255743 | J15: 4911406 | K15: =I15-J15 -> 18344337 | L15: =I15+May!L15 -> 40619843 | M15: =J15+May!M15 -> 10009007 | N15: =L15-M15 -> 30610836
B16: =1+B15 -> 8 | C16: MBG Equity Investment Fund, Inc. | D16: 131461026 | E16: 1200456 | F16: =D16-E16 -> 130260570 | G16: 122597863 | H16: 47 | I16: 0 | J16: 0 | K16: =I16-J16 -> 0 | L16: =I16+May!L16 -> 23000000 | M16: =J16+May!M16 -> 7542618 | N16: =L16-M16 -> 15457382
B17: =1+B16 -> 9 | C17: PAMI Equity Index Fund, Inc. | D17: 1133741611 | E17: 25765925 | F17: =D17-E17 -> 1107975686 | G17: 1118980481 | H17: 11401 | I17: 2999985 | J17: 7781648 | K17: =I17-J17 -> -4781663 | L17: =I17+May!L17 -> 2999985 | M17: =J17+May!M17 -> 74082195 | N17: =L17-M17 -> -71082210
B18: =1+B17 -> 10 | C18: Philam Strategic Growth Fund, Inc. | D18: 3382632440 | E18: 24477175 | F18: =D18-E18 -> 3358155265 | G18: 3232104019 | H18: 11293 | I18: 6092296 | J18: 18997070 | K18: =I18-J18 -> -12904774 | L18: =I18+May!L18 -> 40185906 | M18: =J18+May!M18 -> 179788023 | N18: =L18-M18 -> -139602117
B19: =1+B18 -> 11 | C19: Philequity Dividend Yield Fund, Inc. | D19: 2.3695419e+09 | E19: 12947753 | F19: =D19-E19 -> 2356594115 | G19: 2.1962063e+09 | H19: 4841 | I19: 1514489.8 | J19: 29900901 | K19: =I19-J19 -> -28386411 | L19: =I19+May!L19 -> 16112994 | M19: =J19+May!M19 -> 58713027 | N19: =L19-M19 -> -42600034
B20: =1+B19 -> 12 | C20: Philequity Fund, Inc. | D20: 9.2593483e+09 | E20: 68499177 | F20: =D20-E20 -> 9190849078 | G20: 8.4272828e+09 | H20: 33293 | I20: 8374875.4 | J20: 24309101 | K20: =I20-J20 -> -15934225 | L20: =I20+May!L20 -> 56617226 | M20: =J20+May!M20 -> 2.7083081e+08 | N20: =L20-M20 -> -2.1421358e+08
B21: =1+B20 -> 13 | C21: Philequity MSCI Phil. Index Fund, Inc. | D21: 3.0974676e+08 | E21: 896751.87 | F21: =D21-E21 -> 3.0885e+08 | G21: 2.9935259e+08 | H21: 912 | I21: 478040.17 | J21: 204657.41 | K21: =I21-J21 -> 273382.76 | L21: =I21+May!L21 -> 2578799.7 | M21: =J21+May!M21 -> 6310161.6 | N21: =L21-M21 -> -3731361.9
... B27: =1+B26 -> 19 | C27: United Fund, Inc. | D27: 5.9964703e+08 | E27: 16741550 | F27: =D27-E27 -> 5.8290548e+08 | G27: 536690739 | H27: 1224 | I27: 245598.19 | J27: 3060296.5 | K27: =I27-J27 -> -2814698.3 | L27: =I27+May!L27 -> 10723830 | M27: =J27+May!M27 -> 9741194.4 | N27: =L27-M27 -> 982636.03
A28: Primarily invested in Peso Securities (units)
B29: =1+B27 -> 20 | C29: COL Equity Index Unitized Mutual Fund, Inc. | D29: 2.3394264e+08 | E29: 423103.46 | F29: =D29-E29 -> 2.3351954e+08 | G29: 2.2981576e+08 | H29: 3669 | I29: 11807954 | J29: 1342731.8 | K29: =I29-J29 -> 10465222 | L29: =I29+May!L29 -> 42319861 | M29: =J29+May!M29 -> 39252995 | N29: =L29-M29 -> 3066866
B30: =1+B29 -> 21 | C30: COL Strategic Growth Equity Unitized Mutual Fund, Inc. | D30: 2.7385455e+08 | E30: 647490.35 | F30: =D30-E30 -> 2.7320706e+08 | G30: 1.7004181e+08 | H30: 3569 | I30: 13604619 | J30: 10105004 | K30: =I30-J30 -> 3499614.9 | L30: =I30+May!L30 -> 193289005 | M30: =J30+May!M30 -> 32015415 | N30: =L30-M30 -> 1.6127359e+08
B31: =1+B30 -> 22 | C31: Philequity Alpha One Fund, Inc. | D31: 2.9288385e+08 | E31: 1451919.6 | F31: =D31-E31 -> 2.9143193e+08 | G31: 2.6148931e+08 | H31: 1192 | I31: 381680.95 | J31: 3248061.2 | K31: =I31-J31 -> -2866380.2 | L31: =I31+May!L31 -> 3025865.7 | M31: =J31+May!M31 -> 26218462 | N31: =L31-M31 -> -23192596
B32: =1+B31 -> 23 | C32: Philippine Stock Index Fund Corp. | D32: 616853488 | E32: 2657940 | F32: =D32-E32 -> 614195548 | G32: 607847516 | H32: 656921 | I32: 20190629 | J32: 7390898 | K32: =I32-J32 -> 12799731 | L32: =I32+May!L32 -> 118517595 | M32: =J32+May!M32 -> 125801518 | N32: =L32-M32 -> -7283923
A33: Exchange Traded Fund
B34: =1+B32 -> 24 | C34: First Metro Phil. Equity Exchange Traded Fund, Inc. | D34: 1902517121 | E34: 1511371 | F34: =D34-E34 -> 1901005750 | G34: 1894031053 | H34: 3261 | I34: 0 | J34: 74868504 | K34: =I34-J34 -> -74868504 | L34: =I34+May!L34 -> 14535918 | M34: =J34+May!M34 -> 278706894 | N34: =L34-M34 -> -264170976
A35: Sub total - Peso Currency | D35: =SUM(D9:D34) -> 61798698996 | E35: =SUM(E9:E34) -> 4.3432057e+08 | F35: =SUM(F9:F34) -> 61364378428 | G35: =SUM(G9:G34) -> 58863667520 | H35: =SUM(H9:H34) -> 937904 | I35: =SUM(I9:I34) -> 2.0572867e+08 | J35: =SUM(J9:J34) -> 7.2329423e+08 | K35: =SUM(K9:K34) -> -5.1756555e+08 | ... N35: =SUM(N9:N34) -> -4499937428
A36: Primarily invested in foreign currency securities (shares)
B37: =1+B34 -> 25 | C37: ATRAM AsiaPlus Equity Fund, Inc. | D37: 28522322 | E37: 287193.69 | F37: =D37-E37 -> 28235128 | G37: 0 | H37: 50 | I37: 0 | J37: 0 | K37: =I37-J37 -> 0 | L37: =I37+May!L37 -> 387437.25 | M37: =J37+May!M37 -> 81400.79 | N37: =L37-M37 -> 306036.46
B38: =1+B37 -> 26 | C38: Sun Life Prosperity World Voyager Fund, Inc. | D38: 1964045104 | E38: 45412936 | F38: =D38-E38 -> 1918632168 | G38: 0 | H38: 3022 | I38: 12660835 | J38: 27768881 | K38: =I38-J38 -> -15108046 | L38: =I38+May!L38 -> 87290439 | M38: =J38+May!M38 -> 475688804 | N38: =L38-M38 -> -388398365
A39: Sub total - US Currency | D39: =SUM(D37:D38) -> 1992567426 | E39: =SUM(E37:E38) -> 45700130 | F39: =SUM(F37:F38) -> 1946867296 | G39: =SUM(G37:G38) -> 0 | H39: =SUM(H37:H38) -> 3072 | I39: =SUM(I37:I38) -> 12660835 | J39: =SUM(J37:J38) -> 27768881 | K39: =SUM(K37:K38) -> -15108046 | ... N39: =SUM(N37:N38) -> -3.8809233e+08
A40: Sub total - stock funds | D40: =D35+D39 -> 63791266422 | E40: =E35+E39 -> 4.800207e+08 | F40: =F35+F39 -> 63311245724 | G40: =G35+G39 -> 58863667520 | H40: =H35+H39 -> 940976 | I40: =I35+I39 -> 2.1838951e+08 | J40: =J35+J39 -> 7.5106311e+08 | K40: =K35+K39 -> -5.326736e+08 | ... N40: =N35+N39 -> -4888029756
A41: Balanced Funds
A42: Primarily invested in Peso Securities (shares)
B43: =1+B38 -> 27 | C43: ATRAM Philippine Balanced Fund, Inc. | D43: 4.3127768e+08 | E43: 1093807.8 | F43: =D43-E43 -> 4.3018388e+08 | G43: 2.1527592e+08 | H43: 2319 | I43: 219385.24 | J43: 1308121.9 | K43: =I43-J43 -> -1088736.6 | L43: =I43+May!L43 -> 3324868.5 | M43: =J43+May!M43 -> 32455760 | N43: =L43-M43 -> -29130892
B44: =1+B43 -> 28 | C44: ATRAM Unicapital Diversified Growth Fund, Inc. | D44: 1.1415714e+08 | E44: 276188.56 | F44: =D44-E44 -> 1.1388095e+08 | G44: 28013822 | H44: 699 | I44: 224460.09 | J44: 118722.25 | K44: =I44-J44 -> 105737.84 | L44: =I44+May!L44 -> 1506924.3 | M44: =J44+May!M44 -> 7399186.3 | N44: =L44-M44 -> -5892262.1
B45: =1+B44 -> 29 | C45: First Metro Save and Learn Balanced Fund, Inc. | D45: 777352709 | E45: 15914529 | F45: =D45-E45 -> 761438180 | G45: 420457079 | H45: 4274 | I45: 895344 | J45: 9838514 | K45: =I45-J45 -> -8943170 | L45: =I45+May!L45 -> 10704755 | M45: =J45+May!M45 -> 192382614 | N45: =L45-M45 -> -181677859
B46: =1+B45 -> 30 | C46: First Metro Save and Learn F.O.C.C.U.S. Dynamic Fund, Inc. | D46: 306790633 | E46: 682248 | F46: =D46-E46 -> 306108385 | G46: 215071034 | H46: 256 | I46: 10290349 | J46: 1396900 | K46: =I46-J46 -> 8893449 | L46: =I46+May!L46 -> 192287627 | M46: =J46+May!M46 -> 188194418 | N46: =L46-M46 -> 4093209
B47: =1+B46 -> 31 | C47: NCM Mutual Fund of the Phils., Inc. | D47: 3.2294638e+08 | E47: 1486083.9 | F47: =D47-E47 -> 3.214603e+08 | G47: 1.576746e+08 | H47: 48 | I47: 0 | J47: 0 | K47: =I47-J47 -> 0 | L47: =I47+May!L47 -> 0 | M47: =J47+May!M47 -> 66119 | N47: =L47-M47 -> -66119
B48: =1+B47 -> 32 | C48: PAMI Horizon Fund, Inc. | D48: 485842650 | E48: 14349718 | F48: =D48-E48 -> 471492932 | G48: 235070559 | H48: 9801 | I48: 166351 | J48: 6719224 | K48: =I48-J48 -> -6552873 | L48: =I48+May!L48 -> 3084967 | M48: =J48+May!M48 -> 37718551 | N48: =L48-M48 -> -34633584
