Workbook

Sheet Jan
A1: PHILIPPINE INVESTMENT FUNDS ASSOCIATION, INC.
A2: MUTUAL FUNDS STATISTICAL REPORT
A3: Month of January 2025
A4: (Amounts in Peso)
I5: F O R - T H E - M O N T H | L5: Y E A R - T O - D A T E
A6: Fund Category | C6: Fund Name | D6: ASSETS | E6: LIABILITIES | F6: NET ASSETS | G6: EQUITY INV. | H6: NO. OF A/C | I6: SALES | J6: REDEMPTIONS | K6: NET SALES | L6: TOTAL SALES | M6: TOTAL REDEMPTIONS | N6: TOTAL NET SALES
A7: Stock Funds
A8: Primarily invested in Peso Securities (shares)
B9: 1 | C9: ALFM Growth Fund, Inc. | D9: 3579826711 | E9: 60047130 | F9: =D9-E9 -> 3519779581 | G9: 3475227040 | H9: 5846 | I9: 11499302 | J9: 30214575 | K9: =I9-J9 -> -18715273 | L9: =I9 -> 11499302 | M9: =J9 -> 30214575 | N9: =L9-M9 -> -18715273
B10: =1+B9 -> 2 | C10: ATRAM Alpha Opportunity Fund, Inc. | D10: 9.3805794e+08 | E10: 58592991 | F10: =D10-E10 -> 8.7946495e+08 | G10: 5.9089101e+08 | H10: 4061 | I10: 13170545 | J10: 6220592.8 | K10: =I10-J10 -> 6949951.9 | L10: =I10 -> 13170545 | M10: =J10 -> 6220592.8 | N10: =L10-M10 -> 6949951.9
B11: =1+B10 -> 3 | C11: ATRAM Phil. Equity Opportunity Fund, Inc. | D11: 1.0065305e+09 | E11: 17071102 | F11: =D11-E11 -> 9.8945944e+08 | G11: 8.7106506e+08 | H11: 2503 | I11: 5383935.7 | J11: 8624066.5 | K11: =I11-J11 -> -3240130.8 | L11: =I11 -> 5383935.7 | M11: =J11 -> 8624066.5 | N11: =L11-M11 -> -3240130.8
B12: =1+B11 -> 4 | C12: Climbs Share Capital Equity Investment Fund Corp. | D12: 4.2124987e+08 | E12: 19479963 | F12: =D12-E12 -> 4.0176991e+08 | G12: 3.3617052e+08 | H12: 1740 | I12: 20489233 | J12: 276473.35 | K12: =I12-J12 -> 20212760 | L12: =I12 -> 20489233 | M12: =J12 -> 276473.35 | N12: =L12-M12 -> 20212760
B13: =1+B12 -> 5 | C13: First Metro Consumer Fund, Inc. | D13: 341431433 | E13: 884460 | F13: =D13-E13 -> 340546973 | G13: 248281283 | H13: 1161 | I13: 256022 | J13: 6969374 | K13: =I13-J13 -> -6713352 | L13: =I13 -> 256022 | M13: =J13 -> 6969374 | N13: =L13-M13 -> -6713352
B14: =1+B13 -> 6 | C14: First Metro Save and Learn Equity Fund, Inc. | D14: 2952083625 | E14: 17366215 | F14: =D14-E14 -> 2934717410 | G14: 2419813390 | H14: 14472 | I14: 7725106 | J14: 57441139 | K14: =I14-J14 -> -49716033 | L14: =I14 -> 7725106 | M14: =J14 -> 57441139 | N14: =L14-M14 -> -49716033
B15: =1+B14 -> 7 | C15: First Metro Save and Learn Phil. Index Fund, Inc. | D15: 78267694 | E15: 705356 | F15: =D15-E15 -> 77562338 | G15: 76061457 | H15: 482 | I15: 291880 | J15: 693859 | K15: =I15-J15 -> -401979 | L15: =I15 -> 291880 | M15: =J15 -> 693859 | N15: =L15-M15 -> -401979
B16: =1+B15 -> 8 | C16: MBG Equity Investment Fund, Inc. | D16: 119035466 | E16: 1095263 | F16: =D16-E16 -> 117940203 | G16: 106213102 | H16: 43 | I16: 0 | J16: 0 | K16: =I16-J16 -> 0 | L16: =I16 -> 0 | M16: =J16 -> 0 | N16: =L16-M16 -> 0
B17: =1+B16 -> 9 | C17: PAMI Equity Index Fund, Inc. | D17: 1006525465 | E17: 65887982 | F17: =D17-E17 -> 940637483 | G17: 950993002 | H17: 11023 | I17: 0 | J17: 11500602 | K17: =I17-J17 -> -11500602 | L17: =I17 -> 0 | M17: =J17 -> 11500602 | N17: =L17-M17 -> -11500602
B18: =1+B17 -> 10 | C18: Philam Strategic Growth Fund, Inc. | D18: 2989820457 | E18: 54632474 | F18: =D18-E18 -> 2935187983 | G18: 2890363132 | H18: 10798 | I18: 7570471 | J18: 10535783 | K18: =I18-J18 -> -2965312 | L18: =I18 -> 7570471 | M18: =J18 -> 10535783 | N18: =L18-M18 -> -2965312
B19: =1+B18 -> 11 | C19: Philequity Dividend Yield Fund, Inc. | D19: 2.4243623e+09 | E19: 16065153 | F19: =D19-E19 -> 2408297162 | G19: 2.1769677e+09 | H19: 4996 | I19: 5960467.9 | J19: 4335582.7 | K19: =I19-J19 -> 1624885.2 | L19: =I19 -> 5960467.9 | M19: =J19 -> 4335582.7 | N19: =L19-M19 -> 1624885.2
B20: =1+B19 -> 12 | C20: Philequity Fund, Inc. | D20: 8.3221859e+09 | E20: 40501500 | F20: =D20-E20 -> 8281684398 | G20: 7.5329936e+09 | H20: 31941 | I20: 9043925.1 | J20: 33846096 | K20: =I20-J20 -> -24802171 | L20: =I20 -> 9043925.1 | M20: =J20 -> 33846096 | N20: =L20-M20 -> -24802171
B21: =1+B20 -> 13 | C21: Philequity MSCI Phil. Index Fund, Inc. | D21: 2.8477119e+08 | E21: 530690.7 | F21: =D21-E21 -> 2.842405e+08 | G21: 2.7753402e+08 | H21: 889 | I21: 426331.18 | J21: 230967.34 | K21: =I21-J21 -> 195363.84 | L21: =I21 -> 426331.18 | M21: =J21 -> 230967.34 | N21: =L21-M21 -> 195363.84
... B27: =1+B26 -> 19 | C27: United Fund, Inc. | D27: 4.7107537e+08 | E27: 9249195.2 | F27: =D27-E27 -> 4.6182618e+08 | G27: 4.4986876e+08 | H27: 1199 | I27: 383693.8 | J27: 156012.72 | K27: =I27-J27 -> 227681.08 | L27: =I27 -> 383693.8 | M27: =J27 -> 156012.72 | N27: =L27-M27 -> 227681.08
A28: Primarily invested in Peso Securities (units)
B29: =1+B27 -> 20 | C29: COL Equity Index Unitized Mutual Fund, Inc. | D29: 2.1880443e+08 | E29: 1072328.6 | F29: =D29-E29 -> 2.177321e+08 | G29: 2.0383569e+08 | H29: 4535 | I29: 14204655 | J29: 1702977.7 | K29: =I29-J29 -> 12501677 | L29: =I29 -> 14204655 | M29: =J29 -> 1702977.7 | N29: =L29-M29 -> 12501677
B30: =1+B29 -> 21 | C30: COL Strategic Growth Equity Unitized Mutual Fund, Inc. | D30: 3.74349e+08 | E30: 1332236.2 | F30: =D30-E30 -> 3.7301676e+08 | G30: 259592968 | H30: 5777 | I30: 17585486 | J30: 9255197.5 | K30: =I30-J30 -> 8330288.1 | L30: =I30 -> 17585486 | M30: =J30 -> 9255197.5 | N30: =L30-M30 -> 8330288.1
B31: =1+B30 -> 22 | C31: Philequity Alpha One Fund, Inc. | D31: 2.6160626e+08 | E31: 3299887.8 | F31: =D31-E31 -> 2.5830637e+08 | G31: 2.5752204e+08 | H31: 1145 | I31: 392667.96 | J31: 361446.73 | K31: =I31-J31 -> 31221.23 | L31: =I31 -> 392667.96 | M31: =J31 -> 361446.73 | N31: =L31-M31 -> 31221.23
B32: =1+B31 -> 23 | C32: Philippine Stock Index Fund Corp. | D32: 680494522 | E32: 36647664 | F32: =D32-E32 -> 643846858 | G32: 641628933 | H32: 753266 | I32: 65027228 | J32: 45283184 | K32: =I32-J32 -> 19744044 | L32: =I32 -> 65027228 | M32: =J32 -> 45283184 | N32: =L32-M32 -> 19744044
A33: Exchange Traded Fund
B34: =1+B32 -> 24 | C34: First Metro Phil. Equity Exchange Traded Fund, Inc. | D34: 1261499223 | E34: 1633140 | F34: =D34-E34 -> 1259866083 | G34: 1253247378 | H34: 3234 | I34: 13123499 | J34: 0 | K34: =I34-J34 -> 13123499 | L34: =I34 -> 13123499 | M34: =J34 -> 0 | N34: =L34-M34 -> 13123499
A35: Sub total - Peso Currency | D35: =SUM(D9:D34) -> 54154634125 | E35: =SUM(E9:E34) -> 1293236119 | F35: =SUM(F9:F34) -> 52861398006 | G35: =SUM(G9:G34) -> 49955877099 | H35: =SUM(H9:H34) -> 1032356 | I35: =SUM(I9:I34) -> 3.2058945e+08 | J35: =SUM(J9:J34) -> 4.8905661e+08 | K35: =SUM(K9:K34) -> -168467158 | ... N35: =SUM(N9:N34) -> -168467158
A36: Primarily invested in foreign currency securities (shares)
B37: =1+B34 -> 25 | C37: ATRAM AsiaPlus Equity Fund, Inc. | D37: 28047684 | E37: 257491.79 | F37: =D37-E37 -> 27790192 | G37: 0 | H37: 50 | I37: 46669.82 | J37: 98660.78 | K37: =I37-J37 -> -51990.96 | L37: =I37 -> 46669.82 | M37: =J37 -> 98660.78 | N37: =L37-M37 -> -51990.96
B38: =1+B37 -> 26 | C38: Sun Life Prosperity World Voyager Fund, Inc. | D38: 2117078191 | E38: 10072922 | F38: =D38-E38 -> 2107005269 | G38: 0 | H38: 3168 | I38: 24947275 | J38: 12017256 | K38: =I38-J38 -> 12930019 | L38: =I38 -> 24947275 | M38: =J38 -> 12017256 | N38: =L38-M38 -> 12930019
A39: Sub total - US Currency | D39: =SUM(D37:D38) -> 2145125875 | E39: =SUM(E37:E38) -> 10330414 | F39: =SUM(F37:F38) -> 2134795461 | G39: =SUM(G37:G38) -> 0 | H39: =SUM(H37:H38) -> 3218 | I39: =SUM(I37:I38) -> 24993945 | J39: =SUM(J37:J38) -> 12115917 | K39: =SUM(K37:K38) -> 12878028 | ... N39: =SUM(N37:N38) -> 12878028
A40: Sub total - stock funds | D40: =D35+D39 -> 56299759999 | E40: =E35+E39 -> 1303566533 | F40: =F35+F39 -> 54996193467 | G40: =G35+G39 -> 49955877099 | H40: =H35+H39 -> 1035574 | I40: =I35+I39 -> 345583399 | J40: =J35+J39 -> 501172529 | K40: =K35+K39 -> -155589130 | ... N40: =N35+N39 -> -155589130
A41: Balanced Funds
A42: Primarily invested in Peso Securities (shares)
B43: =1+B38 -> 27 | C43: ATRAM Philippine Balanced Fund, Inc. | D43: 4.3817323e+08 | E43: 43482111 | F43: =D43-E43 -> 3.9469112e+08 | G43: 2.0987916e+08 | H43: 2318 | I43: 470306.26 | J43: 6607205.7 | K43: =I43-J43 -> -6136899.4 | L43: =I43 -> 470306.26 | M43: =J43 -> 6607205.7 | N43: =L43-M43 -> -6136899.4
B44: =1+B43 -> 28 | C44: ATRAM Unicapital Diversified Growth Fund, Inc. | D44: 1.1731335e+08 | E44: 5835578.6 | F44: =D44-E44 -> 1.1147777e+08 | G44: 29499292 | H44: 801 | I44: 368040.7 | J44: 464959.65 | K44: =I44-J44 -> -96918.95 | L44: =I44 -> 368040.7 | M44: =J44 -> 464959.65 | N44: =L44-M44 -> -96918.95
B45: =1+B44 -> 29 | C45: First Metro Save and Learn Balanced Fund, Inc. | D45: 637012595 | E45: 2723392 | F45: =D45-E45 -> 634289203 | G45: 267879202 | H45: 4116 | I45: 1150101 | J45: 4973213 | K45: =I45-J45 -> -3823112 | L45: =I45 -> 1150101 | M45: =J45 -> 4973213 | N45: =L45-M45 -> -3823112
B46: =1+B45 -> 30 | C46: First Metro Save and Learn F.O.C.C.U.S. Dynamic Fund, Inc. | D46: 463347016 | E46: 1235900 | F46: =D46-E46 -> 462111116 | G46: 305893587 | H46: 368 | I46: 4615774 | J46: 564961 | K46: =I46-J46 -> 4050813 | L46: =I46 -> 4615774 | M46: =J46 -> 564961 | N46: =L46-M46 -> 4050813
B47: =1+B46 -> 31 | C47: NCM Mutual Fund of the Phils., Inc. | D47: 3.0680384e+08 | E47: 824442.17 | F47: =D47-E47 -> 3.0597939e+08 | G47: 1.4249879e+08 | H47: 47 | I47: 0 | J47: 0 | K47: =I47-J47 -> 0 | L47: =I47 -> 0 | M47: =J47 -> 0 | N47: =L47-M47 -> 0
B48: =1+B47 -> 32 | C48: PAMI Horizon Fund, Inc. | D48: 443669422 | E48: 16570398 | F48: =D48-E48 -> 427099024 | G48: 201157413 | H48: 9653 | I48: 27138 | J48: 2622975 | K48: =I48-J48 -> -2595837 | L48: =I48 -> 27138 | M48: =J48 -> 2622975 | N48: =L48-M48 -> -2595837
B49: =1+B48 -> 33 | C49: Philam Fund, Inc. | D49: 1792582158 | E49: 13747014 | F49: =D49-E49 -> 1778835144 | G49: 814823016 | H49: 7388 | I49: 397729 | J49: 9521415 | K49: =I49-J49 -> -9123686 | L49: =I49 -> 397729 | M49: =J49 -> 9521415 | N49: =L49-M49 -> -9123686
B50: =1+B49 -> 34 | C50: Solidaritas Fund, Inc. | D50: 114957923 | E50: 160175 | F50: =D50-E50 -> 114797748 | G50: 53662770 | H50: 159 | I50: 0 | J50: 1646755 | K50: =I50-J50 -> -1646755 | L50: =I50 -> 0 | M50: =J50 -> 1646755 | N50: =L50-M50 -> -1646755
B51: =1+B50 -> 35 | C51: Sun Life Prosperity Balanced Fund, Inc. | D51: 5685550239 | E51: 34283644 | F51: =D51-E51 -> 5651266595 | G51: 2731516807 | H51: 54647 | I51: 7700398 | J51: 47270640 | K51: =I51-J51 -> -39570242 | L51: =I51 -> 7700398 | M51: =J51 -> 47270640 | N51: =L51-M51 -> -39570242
B52: =1+B51 -> 36 | C52: Sun Life Prosperity Dynamic Fund, Inc. | D52: 460821311 | E52: 4243177 | F52: =D52-E52 -> 456578134 | G52: 238776665 | H52: 5000 | I52: 0 | J52: 12246728 | K52: =I52-J52 -> -12246728 | L52: =I52 -> 0 | M52: =J52 -> 12246728 | N52: =L52-M52 -> -12246728
A53: Primarily invested in Peso Securities (units)
B54: =1+B52 -> 37 | C54: Sun Life Prosperity Achiever Fund 2028, Inc. | D54: 75783898 | E54: 1106906 | F54: =D54-E54 -> 74676992 | G54: 14575887 | H54: 1249 | I54: 237195 | J54: 567479 | K54: =I54-J54 -> -330284 | L54: =I54 -> 237195 | M54: =J54 -> 567479 | N54: =L54-M54 -> -330284
B55: =1+B54 -> 38 | C55: Sun Life Prosperity Achiever Fund 2038, Inc. | D55: 52954393 | E55: 360300 | F55: =D55-E55 -> 52594093 | G55: 36535344 | H55: 508 | I55: 85140 | J55: 68305 | K55: =I55-J55 -> 16835 | L55: =I55 -> 85140 | M55: =J55 -> 68305 | N55: =L55-M55 -> 16835
B56: =1+B55 -> 39 | C56: Sun Life Prosperity Achiever Fund 2048, Inc. | D56: 44102372 | E56: 192270 | F56: =D56-E56 -> 43910102 | G56: 35628046 | H56: 244 | I56: 49019 | J56: 2122 | K56: =I56-J56 -> 46897 | L56: =I56 -> 49019 | M56: =J56 -> 2122 | N56: =L56-M56 -> 46897
A57: Sub total - Peso Currency | D57: =SUM(D43:D56) -> 10633071749 | E57: =SUM(E43:E56) -> 1.2476531e+08 | F57: =SUM(F43:F56) -> 10508306441 | G57: =SUM(G43:G56) -> 5082325983 | H57: =SUM(H43:H56) -> 86498 | I57: =SUM(I42:I56) -> 15100841 | J57: =SUM(J43:J56) -> 86556758 | K57: =SUM(K43:K56) -> -71455917 | L57: =SUM(L43:L56) -> 15100841 | M57: =SUM(M43:M56) -> 86556758 | N57: =SUM(N43:N56) -> -71455917
A58: Primarily invested in foreign currency securities (shares)
B59: =1+B56 -> 40 | C59: Cocolife Dollar Fund Builder, Inc. | D59: 65050318 | E59: 395958.08 | F59: =D59-E59 -> 64654360 | G59: 0 | H59: 49 | I59: 0 | J59: 0 | K59: =I59-J59 -> 0 | L59: =I59 -> 0 | M59: =J59 -> 0 | N59: =L59-M59 -> 0
B60: =1+B59 -> 41 | C60: PAMI Asia Balanced Fund, Inc. | D60: 328307174 | E60: 18475394 | F60: =D60-E60 -> 309831780 | G60: 169999375 | H60: 213 | I60: 0 | J60: 633322 | K60: =I60-J60 -> -633322 | L60: =I60 -> 0 | M60: =J60 -> 633322 | N60: =L60-M60 -> -633322
B61: =1+B60 -> 42 | C61: Sun Life Prosperity Dollar Advantage Fund, Inc. | D61: 1720155866 | E61: 15209833 | F61: =D61-E61 -> 1704946033 | G61: 0 | H61: 4278 | I61: 3180729 | J61: 26440762 | K61: =I61-J61 -> -23260033 | L61: =I61 -> 3180729 | M61: =J61 -> 26440762 | N61: =L61-M61 -> -23260033
B62: =1+B61 -> 43 | C62: Sun Life Prosperity Dollar Wellspring Fund, Inc. | D62: 249049349 | E62: 552098 | F62: =D62-E62 -> 248497251 | G62: 0 | H62: 768 | I62: 198386 | J62: 898979 | K62: =I62-J62 -> -700593 | L62: =I62 -> 198386 | M62: =J62 -> 898979 | N62: =L62-M62 -> -700593
A63: Sub total - US Currency | D63: =SUM(D59:D62) -> 2362562707 | E63: =SUM(E59:E62) -> 34633283 | F63: =SUM(F59:F62) -> 2327929424 | G63: =SUM(G59:G62) -> 169999375 | H63: =SUM(H59:H62) -> 5308 | I63: =SUM(I59:I62) -> 3379115 | J63: =SUM(J59:J62) -> 27973063 | K63: =SUM(K59:K62) -> -24593948 | ... N63: =SUM(N59:N62) -> -24593948
A64: Sub total - balanced funds | D64: =D57+D63 -> 12995634456 | E64: =E57+E63 -> 1.5939859e+08 | F64: =F57+F63 -> 12836235865 | G64: =G57+G63 -> 5252325358 | H64: =H57+H63 -> 91806 | I64: =I57+I63 -> 18479956 | J64: =J57+J63 -> 1.1452982e+08 | K64: =K57+K63 -> -96049865 | ... N64: =N57+N63 -> -96049865
A65: Bond Funds
A66: Primarily invested in Peso Securities (shares)
B67: =1+B62 -> 44 | C67: ALFM Peso Bond Fund, Inc. | D67: 35053787744 | E67: 331397081 | F67: =D67-E67 -> 34722390663 | G67: 253250000 | H67: 23990 | I67: 156178508 | J67: 353003090 | K67: =I67-J67 -> -196824582 | L67: =I67 -> 156178508 | M67: =J67 -> 353003090 | N67: =L67-M67 -> -196824582
B68: =1+B67 -> 45 | C68: ATRAM Corporate Bond Fund, Inc. | D68: 2.6584845e+08 | E68: 1052902.4 | F68: =D68-E68 -> 2.6479555e+08 | G68: 0 | H68: 934 | I68: 721716.86 | J68: 11532961 | K68: =I68-J68 -> -10811244 | L68: =I68 -> 721716.86 | M68: =J68 -> 11532961 | N68: =L68-M68 -> -10811244
B69: =1+B68 -> 46 | C69: Cocolife Fixed Income Fund, Inc. | D69: 9.5999586e+08 | E69: 12629934 | F69: =D69-E69 -> 9.4736593e+08 | G69: 0 | H69: 1818 | I69: 10588123 | J69: 4766314.2 | K69: =I69-J69 -> 5821808.8 | L69: =I69 -> 10588123 | M69: =J69 -> 4766314.2 | N69: =L69-M69 -> 5821808.8
B70: =1+B69 -> 47 | C70: Ekklesia Mutual Fund, Inc. | D70: 187624073 | E70: 185826 | F70: =D70-E70 -> 187438247 | G70: 0 | H70: 137 | I70: 4998 | J70: 17151 | K70: =I70-J70 -> -12153 | L70: =I70 -> 4998 | M70: =J70 -> 17151 | N70: =L70-M70 -> -12153
B71: =1+B70 -> 48 | C71: First Metro Save and Learn Fixed Income Fund, Inc. | D71: 1187001679 | E71: 4904650 | F71: =D71-E71 -> 1182097029 | G71: 0 | H71: 1763 | I71: 1063226 | J71: 8458302 | K71: =I71-J71 -> -7395076 | L71: =I71 -> 1063226 | M71: =J71 -> 8458302 | N71: =L71-M71 -> -7395076
B72: =1+B71 -> 49 | C72: Philam Bond Fund, Inc. | D72: 1427535341 | E72: 34111709 | F72: =D72-E72 -> 1393423632 | G72: 0 | H72: 4591 | I72: 1170222 | J72: 9134352 | K72: =I72-J72 -> -7964130 | L72: =I72 -> 1170222 | M72: =J72 -> 9134352 | N72: =L72-M72 -> -7964130
B73: =1+B72 -> 50 | C73: Philam Managed Income Fund, Inc. | D73: 619986948 | E73: 10539208 | F73: =D73-E73 -> 609447740 | G73: 0 | H73: 410 | I73: 0 | J73: 9560035 | K73: =I73-J73 -> -9560035 | L73: =I73 -> 0 | M73: =J73 -> 9560035 | N73: =L73-M73 -> -9560035
B74: =1+B73 -> 51 | C74: Philequity Peso Bond Fund, Inc. | D74: 3.2896731e+08 | E74: 1389672.7 | F74: =D74-E74 -> 3.2757764e+08 | G74: 0 | H74: 3935 | I74: 1685606.5 | J74: 795006.81 | K74: =I74-J74 -> 890599.67 | L74: =I74 -> 1685606.5 | M74: =J74 -> 795006.81 | N74: =L74-M74 -> 890599.67
B75: =1+B74 -> 52 | C75: Soldivo Bond Fund, Inc. | D75: 1.8060207e+09 | E75: 3421894.2 | F75: =D75-E75 -> 1802598804 | G75: 0 | H75: 787 | I75: 25044.77 | J75: 166614.99 | K75: =I75-J75 -> -141570.22 | L75: =I75 -> 25044.77 | M75: =J75 -> 166614.99 | N75: =L75-M75 -> -141570.22
B76: =1+B75 -> 53 | C76: Sun Life Prosperity Bond Fund, Inc. | D76: 6405868990 | E76: 17355548 | F76: =D76-E76 -> 6388513442 | G76: 0 | H76: 19263 | I76: 46900420 | J76: 201213170 | K76: =I76-J76 -> -154312750 | L76: =I76 -> 46900420 | M76: =J76 -> 201213170 | N76: =L76-M76 -> -154312750
B77: =1+B76 -> 54 | C77: Sun Life Prosperity GS Fund, Inc. | D77: 150697006 | E77: 329185 | F77: =D77-E77 -> 150367821 | G77: 0 | H77: 2887 | I77: 866363 | J77: 986873 | K77: =I77-J77 -> -120510 | L77: =I77 -> 866363 | M77: =J77 -> 986873 | N77: =L77-M77 -> -120510
A78: Corporate Debt Vehicle (units)
B79: =1+B77 -> 55 | C79: ATRAM Unitized Corporate Debt Vehicle, Inc. | D79: 7.1268237e+08 | E79: 1733115.9 | F79: =D79-E79 -> 7.1094926e+08 | G79: 0 | H79: 13 | I79: 0 | J79: 0 | K79: =I79-J79 -> 0 | L79: =I79 -> 0 | M79: =J79 -> 0 | N79: =L79-M79 -> 0
A80: Sub total - Peso Currency | D80: =SUM(D67:D79) -> 49106016474 | E80: =SUM(E67:E79) -> 4.1905073e+08 | F80: =SUM(F67:F79) -> 48686965748 | G80: =SUM(G67:G79) -> 253250000 | H80: =SUM(H67:H79) -> 60528 | I80: =SUM(I67:I79) -> 2.1920423e+08 | J80: =SUM(J67:J79) -> 5.9963387e+08 | K80: =SUM(K67:K79) -> -3.8042964e+08 | ... N80: =SUM(N67:N79) -> -3.8042964e+08
A81: Primarily invested in foreign currency securities (shares)
B82: =1+B79 -> 56 | C82: ALFM Dollar Bond Fund, Inc. | D82: 11589239636 | E82: 191892303 | F82: =D82-E82 -> 11397347333 | G82: 0 | H82: 7319 | I82: 28500139 | J82: 103531034 | K82: =I82-J82 -> -75030895 | L82: =I82 -> 28500139 | M82: =J82 -> 103531034 | N82: =L82-M82 -> -75030895
B83: =1+B82 -> 57 | C83: ATRAM Total Return Dollar Bond Fund, Inc. | D83: 97848202 | E83: 2449802 | F83: =D83-E83 -> 95398400 | G83: 0 | H83: 79 | I83: 0 | J83: 1120366.4 | K83: =I83-J83 -> -1120366.4 | L83: =I83 -> 0 | M83: =J83 -> 1120366.4 | N83: =L83-M83 -> -1120366.4
B84: =1+B83 -> 58 | C84: First Metro Save and Learn Dollar Bond Fund, Inc. | D84: 321191933 | E84: 802460 | F84: =D84-E84 -> 320389473 | G84: 0 | H84: 161 | I84: 129302 | J84: 598649 | K84: =I84-J84 -> -469347 | L84: =I84 -> 129302 | M84: =J84 -> 598649 | N84: =L84-M84 -> -469347
B85: =1+B84 -> 59 | C85: PAMI Global Bond Fund, Inc. | D85: 68508607 | E85: 16600989 | F85: =D85-E85 -> 51907618 | G85: 0 | H85: 24 | I85: 0 | J85: 0 | K85: =I85-J85 -> 0 | L85: =I85 -> 0 | M85: =J85 -> 0 | N85: =L85-M85 -> 0
B86: =1+B85 -> 60 | C86: Philam Dollar Bond Fund, Inc. | D86: 1736320491 | E86: 66968148 | F86: =D86-E86 -> 1669352343 | G86: 0 | H86: 1609 | I86: 40447 | J86: 26933682 | K86: =I86-J86 -> -26893235 | L86: =I86 -> 40447 | M86: =J86 -> 26933682 | N86: =L86-M86 -> -26893235
B87: =1+B86 -> 61 | C87: Philequity Dollar Income Fund, Inc. | D87: 2.2881235e+08 | E87: 1268775.4 | F87: =D87-E87 -> 2.2754357e+08 | G87: 0 | H87: 96 | I87: 23346 | J87: 0 | K87: =I87-J87 -> 23346 | L87: =I87 -> 23346 | M87: =J87 -> 0 | N87: =L87-M87 -> 23346
B88: =1+B87 -> 62 | C88: Sun Life Prosperity Dollar Abundance Fund, Inc. | D88: 521593651 | E88: 29814791 | F88: =D88-E88 -> 491778860 | G88: 0 | H88: 2645 | I88: 3078247 | J88: 4609226 | K88: =I88-J88 -> -1530979 | L88: =I88 -> 3078247 | M88: =J88 -> 4609226 | N88: =L88-M88 -> -1530979
A89: Sub total - US Currency | D89: =SUM(D82:D88) -> 14563514870 | E89: =SUM(E82:E88) -> 3.0979727e+08 | F89: =SUM(F82:F88) -> 14253717602 | G89: =SUM(G82:G88) -> 0 | H89: =SUM(H82:H88) -> 11933 | I89: =SUM(I82:I88) -> 31771481 | J89: =SUM(J82:J88) -> 1.3679296e+08 | K89: =SUM(K82:K88) -> -1.0502148e+08 | ... N89: =SUM(N82:N88) -> -1.0502148e+08
B90: =1+B88 -> 63 | C90: ALFM Euro Bond Fund, Inc. | D90: 706703532 | E90: 5296146 | F90: =D90-E90 -> 701407386 | G90: 0 | H90: 578 | I90: 8267224 | J90: 7140867 | K90: =I90-J90 -> 1126357 | L90: =I90 -> 8267224 | M90: =J90 -> 7140867 | N90: =L90-M90 -> 1126357
A91: Sub total - Euro Currency | D91: =SUM(D90) -> 706703532 | E91: =SUM(E90) -> 5296146 | F91: =SUM(F90) -> 701407386 | G91: =SUM(G90) -> 0 | H91: =SUM(H90) -> 578 | I91: =SUM(I90) -> 8267224 | J91: =SUM(J90) -> 7140867 | K91: =SUM(K90) -> 1126357 | ... N91: =SUM(N90) -> 1126357
A92: Sub total - bond funds | D92: =D80+D89+D91 -> 64376234876 | E92: =E80+E89+E91 -> 7.3414414e+08 | F92: =F80+F89+F91 -> 63642090736 | G92: =G80+G89+G91 -> 253250000 | H92: =H80+H89+H91 -> 73039 | I92: =I80+I89+I91 -> 2.5924293e+08 | J92: =J80+J89+J91 -> 7.4356769e+08 | K92: =K80+K89+K91 -> -484324761 | ... N92: =N80+N89+N91 -> -484324761
A93: Money Market Funds
A94: Primarily invested in Peso Securities (shares)
B95: 64 | C95: AIB Money Market Mutual Fund, Inc. | D95: 1.7067427e+08 | E95: 269196.13 | F95: =D95-E95 -> 1.7040507e+08 | G95: 0 | H95: 64 | I95: 65000 | J95: 0 | K95: =I95-J95 -> 65000 | L95: =I95 -> 65000 | M95: =J95 -> 0 | N95: =L95-M95 -> 65000
B96: 65 | C96: ALFM Money Market Fund, Inc. | D96: 21659038091 | E96: 11413232 | F96: =D96-E96 -> 21647624859 | G96: 0 | H96: 22362 | I96: 351578 | J96: 473588088 | K96: =I96-J96 -> -473236510 | L96: =I96 -> 351578 | M96: =J96 -> 473588088 | N96: =L96-M96 -> -473236510
B97: =1+B96 -> 66 | C97: First Metro Save and Learn Money Market Fund, Inc. | D97: 2590112535 | E97: 26062103 | F97: =D97-E97 -> 2564050432 | G97: 0 | H97: 1238 | I97: 129380774 | J97: 325822967 | K97: =I97-J97 -> -196442193 | L97: =I97 -> 129380774 | M97: =J97 -> 325822967 | N97: =L97-M97 -> -196442193
B98: =1+B97 -> 67 | C98: Sun Life Prosperity Peso Starter Fund, Inc. | D98: 12603746215 | E98: 75268802 | F98: =D98-E98 -> 12528477413 | G98: 0 | H98: 73121 | I98: 790280592 | J98: 690776248 | K98: =I98-J98 -> 99504344 | L98: =I98 -> 790280592 | M98: =J98 -> 690776248 | N98: =L98-M98 -> 99504344
A99: Primarily invested in Peso Securities (units)
B100: =1+B98 -> 68 | C100: ALFM Money Market Fund, Inc. | D100: 11305590452 | E100: 6852077 | F100: =D100-E100 -> 11298738375 | G100: 0 | H100: 26014 | I100: 723602096 | J100: 864345032 | K100: =I100-J100 -> -140742936 | L100: =I100 -> 723602096 | M100: =J100 -> 864345032 | N100: =L100-M100 -> -140742936
A101: Sub total - Peso Currency | D101: =SUM(D95:D98)+D100 -> 48329161559 | E101: =SUM(E95:E98)+E100 -> 1.1986541e+08 | F101: =SUM(F95:F98)+F100 -> 48209296149 | G101: =SUM(G95:G98)+G100 -> 0 | H101: =SUM(H95:H98)+H100 -> 122799 | I101: =SUM(I95:I98)+I100 -> 1643680040 | J101: =SUM(J95:J98)+J100 -> 2354532335 | K101: =SUM(K95:K98)+K100 -> -710852295 | ... N101: =SUM(N95:N98)+N100 -> -710852295
A102: Primarily invested in foreign currency securities (shares)
B103: =1+B100 -> 69 | C103: Sun Life Prosperity Dollar Starter Fund, Inc. | D103: 2242281457 | E103: 10196842 | F103: =D103-E103 -> 2232084615 | G103: 0 | H103: 3805 | I103: 144142036 | J103: 269508814 | K103: =I103-J103 -> -125366778 | L103: =I103 -> 144142036 | M103: =J103 -> 269508814 | N103: =L103-M103 -> -125366778
A104: Sub total - US Currency | D104: =SUM(D103) -> 2242281457 | E104: =SUM(E103) -> 10196842 | F104: =SUM(F103) -> 2232084615 | G104: =SUM(G103) -> 0 | H104: =SUM(H103) -> 3805 | I104: =SUM(I103) -> 144142036 | J104: =SUM(J103) -> 269508814 | K104: =SUM(K103) -> -125366778 | ... N104: =SUM(N103) -> -125366778
A105: Sub total - money market funds | D105: =D101+D104 -> 50571443016 | E105: =E101+E104 -> 1.3006225e+08 | F105: =F101+F104 -> 50441380764 | G105: =G101+G104 -> 0 | H105: =H101+H104 -> 126604 | I105: =I101+I104 -> 1787822076 | J105: =J101+J104 -> 2624041149 | K105: =K101+K104 -> -836219073 | ... N105: =N101+N104 -> -836219073
...

Sheet Feb
A1: PHILIPPINE INVESTMENT FUNDS ASSOCIATION, INC.
A2: MUTUAL FUNDS STATISTICAL REPORT
A3: Month of February 2025
A4: (Amounts in Peso)
I5: F O R - T H E - M O N T H | L5: Y E A R - T O - D A T E
A6: Fund Category | C6: Fund Name | D6: ASSETS | E6: LIABILITIES | F6: NET ASSETS | G6: EQUITY INV. | H6: NO. OF A/C | I6: SALES | J6: REDEMPTIONS | K6: NET SALES | L6: TOTAL SALES | M6: TOTAL REDEMPTIONS | N6: TOTAL NET SALES
A7: Stock Funds
A8: Primarily invested in Peso Securities (shares)
B9: 1 | C9: ALFM Growth Fund, Inc. | D9: 3614590099 | E9: 9804439 | F9: =D9-E9 -> 3604785660 | G9: 3550553739 | H9: 5820 | I9: 8526054 | J9: 24540198 | K9: =I9-J9 -> -16014144 | L9: =I9+Jan!L9 -> 20025356 | M9: =J9+Jan!M9 -> 54754773 | N9: =L9-M9 -> -34729417
B10: =1+B9 -> 2 | C10: ATRAM Alpha Opportunity Fund, Inc. | D10: 9.7563577e+08 | E10: 58807440 | F10: =D10-E10 -> 9.1682833e+08 | G10: 846930515 | H10: 4101 | I10: 29130413 | J10: 17776753 | K10: =I10-J10 -> 11353659 | L10: =I10+Jan!L10 -> 42300957 | M10: =J10+Jan!M10 -> 23997346 | N10: =L10-M10 -> 18303611
B11: =1+B10 -> 3 | C11: ATRAM Phil. Equity Opportunity Fund, Inc. | D11: 1.0590887e+09 | E11: 41496227 | F11: =D11-E11 -> 1017592443 | G11: 9.6020108e+08 | H11: 2491 | I11: 7391344.5 | J11: 4318041.7 | K11: =I11-J11 -> 3073302.8 | L11: =I11+Jan!L11 -> 12775280 | M11: =J11+Jan!M11 -> 12942108 | N11: =L11-M11 -> -166828.01
B12: =1+B11 -> 4 | C12: Climbs Share Capital Equity Investment Fund Corp. | D12: 4.2146263e+08 | E12: 16453509 | F12: =D12-E12 -> 4.0500912e+08 | G12: 3.6255925e+08 | H12: 1709 | I12: 593070 | J12: 699624.3 | K12: =I12-J12 -> -106554.3 | L12: =I12+Jan!L12 -> 21082303 | M12: =J12+Jan!M12 -> 976097.65 | N12: =L12-M12 -> 20106206
B13: =1+B12 -> 5 | C13: First Metro Consumer Fund, Inc. | D13: 350949757 | E13: 747413 | F13: =D13-E13 -> 350202344 | G13: 254813507 | H13: 1155 | I13: 306037 | J13: 545372 | K13: =I13-J13 -> -239335 | L13: =I13+Jan!L13 -> 562059 | M13: =J13+Jan!M13 -> 7514746 | N13: =L13-M13 -> -6952687
B14: =1+B13 -> 6 | C14: First Metro Save and Learn Equity Fund, Inc. | D14: 2999143112 | E14: 8918826 | F14: =D14-E14 -> 2990224286 | G14: 2442258472 | H14: 14421 | I14: 28260213 | J14: 41238048 | K14: =I14-J14 -> -12977835 | L14: =I14+Jan!L14 -> 35985319 | M14: =J14+Jan!M14 -> 98679187 | N14: =L14-M14 -> -62693868
B15: =1+B14 -> 7 | C15: First Metro Save and Learn Phil. Index Fund, Inc. | D15: 85088943 | E15: 353406 | F15: =D15-E15 -> 84735537 | G15: 77831015 | H15: 477 | I15: 5473707 | J15: 179157 | K15: =I15-J15 -> 5294550 | L15: =I15+Jan!L15 -> 5765587 | M15: =J15+Jan!M15 -> 873016 | N15: =L15-M15 -> 4892571
B16: =1+B15 -> 8 | C16: MBG Equity Investment Fund, Inc. | D16: 117859044 | E16: 1412322 | F16: =D16-E16 -> 116446722 | G16: 108671198 | H16: 43 | I16: 0 | J16: 0 | K16: =I16-J16 -> 0 | L16: =I16+Jan!L16 -> 0 | M16: =J16+Jan!M16 -> 0 | N16: =L16-M16 -> 0
B17: =1+B16 -> 9 | C17: PAMI Equity Index Fund, Inc. | D17: 984401545 | E17: 24592054 | F17: =D17-E17 -> 959809491 | G17: 970682329 | H17: 10897 | I17: 0 | J17: 2577792 | K17: =I17-J17 -> -2577792 | L17: =I17+Jan!L17 -> 0 | M17: =J17+Jan!M17 -> 14078394 | N17: =L17-M17 -> -14078394
B18: =1+B17 -> 10 | C18: Philam Strategic Growth Fund, Inc. | D18: 3023222400 | E18: 44931046 | F18: =D18-E18 -> 2978291354 | G18: 2959270074 | H18: 10760 | I18: 5943949 | J18: 44233057 | K18: =I18-J18 -> -38289108 | L18: =I18+Jan!L18 -> 13514420 | M18: =J18+Jan!M18 -> 54768840 | N18: =L18-M18 -> -41254420
B19: =1+B18 -> 11 | C19: Philequity Dividend Yield Fund, Inc. | D19: 2.482421e+09 | E19: 3733841.7 | F19: =D19-E19 -> 2478687115 | G19: 2.2618273e+09 | H19: 4987 | I19: 10296707 | J19: 2915154.5 | K19: =I19-J19 -> 7381552.7 | L19: =I19+Jan!L19 -> 16257175 | M19: =J19+Jan!M19 -> 7250737.2 | N19: =L19-M19 -> 9006437.8
B20: =1+B19 -> 12 | C20: Philequity Fund, Inc. | D20: 8.7195517e+09 | E20: 1.5736146e+08 | F20: =D20-E20 -> 8562190284 | G20: 8.0222041e+09 | H20: 31851 | I20: 7707527.2 | J20: 17618680 | K20: =I20-J20 -> -9911152.9 | L20: =I20+Jan!L20 -> 16751452 | M20: =J20+Jan!M20 -> 51464776 | N20: =L20-M20 -> -34713324
B21: =1+B20 -> 13 | C21: Philequity MSCI Phil. Index Fund, Inc. | D21: 2.9667971e+08 | E21: 2988299.6 | F21: =D21-E21 -> 2.9369141e+08 | G21: 2.8591525e+08 | H21: 890 | I21: 384397.33 | J21: 53008.27 | K21: =I21-J21 -> 331389.06 | L21: =I21+Jan!L21 -> 810728.51 | M21: =J21+Jan!M21 -> 283975.61 | N21: =L21-M21 -> 526752.9
... B27: =1+B26 -> 19 | C27: United Fund, Inc. | D27: 4.8489152e+08 | E27: 12147024 | F27: =D27-E27 -> 4.727445e+08 | G27: 4.6132164e+08 | H27: 1201 | I27: 488658.88 | J27: 77704.41 | K27: =I27-J27 -> 410954.47 | L27: =I27+Jan!L27 -> 872352.68 | M27: =J27+Jan!M27 -> 233717.13 | N27: =L27-M27 -> 638635.55
A28: Primarily invested in Peso Securities (units)
B29: =1+B27 -> 20 | C29: COL Equity Index Unitized Mutual Fund, Inc. | D29: 2.2057332e+08 | E29: 679642.68 | F29: =D29-E29 -> 2.1989368e+08 | G29: 2.1035685e+08 | H29: 4611 | I29: 7128940.7 | J29: 10780180 | K29: =I29-J29 -> -3651239.4 | L29: =I29+Jan!L29 -> 21333596 | M29: =J29+Jan!M29 -> 12483158 | N29: =L29-M29 -> 8850437.8
B30: =1+B29 -> 21 | C30: COL Strategic Growth Equity Unitized Mutual Fund, Inc. | D30: 3.9513504e+08 | E30: 2678228.1 | F30: =D30-E30 -> 3.9245681e+08 | G30: 314883869 | H30: 6017 | I30: 18418420 | J30: 3195589 | K30: =I30-J30 -> 15222831 | L30: =I30+Jan!L30 -> 36003905 | M30: =J30+Jan!M30 -> 12450786 | N30: =L30-M30 -> 23553119
B31: =1+B30 -> 22 | C31: Philequity Alpha One Fund, Inc. | D31: 2.5394841e+08 | E31: 833338.16 | F31: =D31-E31 -> 2.5311507e+08 | G31: 2.5099544e+08 | H31: 1142 | I31: 2348070.8 | J31: 12035552 | K31: =I31-J31 -> -9687481.2 | L31: =I31+Jan!L31 -> 2740738.8 | M31: =J31+Jan!M31 -> 12396999 | N31: =L31-M31 -> -9656260
B32: =1+B31 -> 23 | C32: Philippine Stock Index Fund Corp. | D32: 673460777 | E32: 8406067 | F32: =D32-E32 -> 665054710 | G32: 664103983 | H32: 755020 | I32: 40951090 | J32: 34020108 | K32: =I32-J32 -> 6930982 | L32: =I32+Jan!L32 -> 105978318 | M32: =J32+Jan!M32 -> 79303292 | N32: =L32-M32 -> 26675026
A33: Exchange Traded Fund
B34: =1+B32 -> 24 | C34: First Metro Phil. Equity Exchange Traded Fund, Inc. | D34: 1317597331 | E34: 1941343 | F34: =D34-E34 -> 1315655988 | G34: 1314949404 | H34: 3278 | I34: 27108889 | J34: 0 | K34: =I34-J34 -> 27108889 | L34: =I34+Jan!L34 -> 40232388 | M34: =J34+Jan!M34 -> 0 | N34: =L34-M34 -> 40232388
A35: Sub total - Peso Currency | D35: =SUM(D9:D34) -> 54802113405 | E35: =SUM(E9:E34) -> 6.7922424e+08 | F35: =SUM(F9:F34) -> 54122889167 | G35: =SUM(G9:G34) -> 51981591359 | H35: =SUM(H9:H34) -> 1034017 | I35: =SUM(I9:I34) -> 327765508 | J35: =SUM(J9:J34) -> 4.9561963e+08 | K35: =SUM(K9:K34) -> -1.6785412e+08 | ... N35: =SUM(N9:N34) -> -3.3632128e+08
A36: Primarily invested in foreign currency securities (shares)
B37: =1+B34 -> 25 | C37: ATRAM AsiaPlus Equity Fund, Inc. | D37: 27883687 | E37: 237825.32 | F37: =D37-E37 -> 27645862 | G37: 0 | H37: 50 | I37: 57972.38 | J37: 25942.32 | K37: =I37-J37 -> 32030.06 | L37: =I37+Jan!L37 -> 104642.2 | M37: =J37+Jan!M37 -> 124603.1 | N37: =L37-M37 -> -19960.9
B38: =1+B37 -> 26 | C38: Sun Life Prosperity World Voyager Fund, Inc. | D38: 2051182309 | E38: 24649862 | F38: =D38-E38 -> 2026532447 | G38: 0 | H38: 3192 | I38: 46285415 | J38: 69993528 | K38: =I38-J38 -> -23708113 | L38: =I38+Jan!L38 -> 71232690 | M38: =J38+Jan!M38 -> 82010784 | N38: =L38-M38 -> -10778094
A39: Sub total - US Currency | D39: =SUM(D37:D38) -> 2079065996 | E39: =SUM(E37:E38) -> 24887687 | F39: =SUM(F37:F38) -> 2054178309 | G39: =SUM(G37:G38) -> 0 | H39: =SUM(H37:H38) -> 3242 | I39: =SUM(I37:I38) -> 46343387 | J39: =SUM(J37:J38) -> 70019470 | K39: =SUM(K37:K38) -> -23676083 | ... N39: =SUM(N37:N38) -> -10798055
A40: Sub total - stock funds | D40: =D35+D39 -> 56881179401 | E40: =E35+E39 -> 7.0411193e+08 | F40: =F35+F39 -> 56177067476 | G40: =G35+G39 -> 51981591359 | H40: =H35+H39 -> 1037259 | I40: =I35+I39 -> 3.741089e+08 | J40: =J35+J39 -> 5.656391e+08 | K40: =K35+K39 -> -1.915302e+08 | ... N40: =N35+N39 -> -3.4711933e+08
A41: Balanced Funds
A42: Primarily invested in Peso Securities (shares)
B43: =1+B38 -> 27 | C43: ATRAM Philippine Balanced Fund, Inc. | D43: 4.1445908e+08 | E43: 22106061 | F43: =D43-E43 -> 3.9235302e+08 | G43: 2.081194e+08 | H43: 2316 | I43: 437016.77 | J43: 10198627 | K43: =I43-J43 -> -9761610.1 | L43: =I43+Jan!L43 -> 907323.03 | M43: =J43+Jan!M43 -> 16805833 | N43: =L43-M43 -> -15898510
B44: =1+B43 -> 28 | C44: ATRAM Unicapital Diversified Growth Fund, Inc. | D44: 1.1474133e+08 | E44: 2717663.1 | F44: =D44-E44 -> 1.1202367e+08 | G44: 29379221 | H44: 811 | I44: 290811.7 | J44: 407410.94 | K44: =I44-J44 -> -116599.24 | L44: =I44+Jan!L44 -> 658852.4 | M44: =J44+Jan!M44 -> 872370.59 | N44: =L44-M44 -> -213518.19
B45: =1+B44 -> 29 | C45: First Metro Save and Learn Balanced Fund, Inc. | D45: 640273113 | E45: 2636848 | F45: =D45-E45 -> 637636265 | G45: 270617654 | H45: 4096 | I45: 647209 | J45: 5537711 | K45: =I45-J45 -> -4890502 | L45: =I45+Jan!L45 -> 1797310 | M45: =J45+Jan!M45 -> 10510924 | N45: =L45-M45 -> -8713614
B46: =1+B45 -> 30 | C46: First Metro Save and Learn F.O.C.C.U.S. Dynamic Fund, Inc. | D46: 439985781 | E46: 1070074 | F46: =D46-E46 -> 438915707 | G46: 305145322 | H46: 365 | I46: 862427 | J46: 32178451 | K46: =I46-J46 -> -31316024 | L46: =I46+Jan!L46 -> 5478201 | M46: =J46+Jan!M46 -> 32743412 | N46: =L46-M46 -> -27265211
B47: =1+B46 -> 31 | C47: NCM Mutual Fund of the Phils., Inc. | D47: 3.1081158e+08 | E47: 1024750.7 | F47: =D47-E47 -> 3.0978683e+08 | G47: 1.4801722e+08 | H47: 46 | I47: 122503445 | J47: 122717300 | K47: =I47-J47 -> -213855 | L47: =I47+Jan!L47 -> 122503445 | M47: =J47+Jan!M47 -> 122717300 | N47: =L47-M47 -> -213855
B48: =1+B47 -> 32 | C48: PAMI Horizon Fund, Inc. | D48: 445982559 | E48: 14201661 | F48: =D48-E48 -> 431780898 | G48: 207080114 | H48: 9638 | I48: 33038 | J48: 1971975 | K48: =I48-J48 -> -1938937 | L48: =I48+Jan!L48 -> 60176 | M48: =J48+Jan!M48 -> 4594950 | N48: =L48-M48 -> -4534774
B49: =1+B48 -> 33 | C49: Philam Fund, Inc. | D49: 1810914268 | E49: 19470841 | F49: =D49-E49 -> 1791443427 | G49: 845716072 | H49: 7346 | I49: 451884 | J49: 16125413 | K49: =I49-J49 -> -15673529 | L49: =I49+Jan!L49 -> 849613 | M49: =J49+Jan!M49 -> 25646828 | N49: =L49-M49 -> -24797215
B50: =1+B49 -> 34 | C50: Solidaritas Fund, Inc. | D50: 117783321 | E50: 912809 | F50: =D50-E50 -> 116870512 | G50: 57094895 | H50: 158 | I50: 0 | J50: 25801 | K50: =I50-J50 -> -25801 | L50: =I50+Jan!L50 -> 0 | M50: =J50+Jan!M50 -> 1672556 | N50: =L50-M50 -> -1672556
B51: =1+B50 -> 35 | C51: Sun Life Prosperity Balanced Fund, Inc. | D51: 5773731260 | E51: 64716407 | F51: =D51-E51 -> 5709014853 | G51: 2886035977 | H51: 54663 | I51: 4829646 | J51: 46156030 | K51: =I51-J51 -> -41326384 | L51: =I51+Jan!L51 -> 12530044 | M51: =J51+Jan!M51 -> 93426670 | N51: =L51-M51 -> -80896626
B52: =1+B51 -> 36 | C52: Sun Life Prosperity Dynamic Fund, Inc. | D52: 463682813 | E52: 6939679 | F52: =D52-E52 -> 456743134 | G52: 245959562 | H52: 5000 | I52: 0 | J52: 8784024 | K52: =I52-J52 -> -8784024 | L52: =I52+Jan!L52 -> 0 | M52: =J52+Jan!M52 -> 21030752 | N52: =L52-M52 -> -21030752
A53: Primarily invested in Peso Securities (units) | L53: =I53+Jan!L53 -> 0 | M53: =J53+Jan!M53 -> 0
B54: =1+B52 -> 37 | C54: Sun Life Prosperity Achiever Fund 2028, Inc. | D54: 75393922 | E54: 294678 | F54: =D54-E54 -> 75099244 | G54: 14912081 | H54: 1254 | I54: 207829 | J54: 339230 | K54: =I54-J54 -> -131401 | L54: =I54+Jan!L54 -> 445024 | M54: =J54+Jan!M54 -> 906709 | N54: =L54-M54 -> -461685
B55: =1+B54 -> 38 | C55: Sun Life Prosperity Achiever Fund 2038, Inc. | D55: 53738844 | E55: 250696 | F55: =D55-E55 -> 53488148 | G55: 37509380 | H55: 510 | I55: 63503 | J55: 118325 | K55: =I55-J55 -> -54822 | L55: =I55+Jan!L55 -> 148643 | M55: =J55+Jan!M55 -> 186630 | N55: =L55-M55 -> -37987
B56: =1+B55 -> 39 | C56: Sun Life Prosperity Achiever Fund 2048, Inc. | D56: 45205220 | E56: 278147 | F56: =D56-E56 -> 44927073 | G56: 36584727 | H56: 246 | I56: 118342 | J56: 42308 | K56: =I56-J56 -> 76034 | L56: =I56+Jan!L56 -> 167361 | M56: =J56+Jan!M56 -> 44430 | N56: =L56-M56 -> 122931
A57: Sub total - Peso Currency | D57: =SUM(D43:D56) -> 10706703093 | E57: =SUM(E42:E56) -> 1.3662031e+08 | F57: =SUM(F43:F56) -> 10570082778 | G57: =SUM(G43:G56) -> 5292171631 | H57: =SUM(H43:H56) -> 86449 | I57: =SUM(I42:I56) -> 1.3044515e+08 | J57: =SUM(J43:J56) -> 2.4460261e+08 | K57: =SUM(K43:K56) -> -1.1415745e+08 | L57: =SUM(L43:L56) -> 1.4554599e+08 | M57: =SUM(M43:M56) -> 3.3115936e+08 | N57: =SUM(N43:N56) -> -1.8561337e+08
A58: Primarily invested in foreign currency securities (shares)
B59: =1+B56 -> 40 | C59: Cocolife Dollar Fund Builder, Inc. | D59: 64807691 | E59: 584745.61 | F59: =D59-E59 -> 64222946 | G59: 0 | H59: 48 | I59: 0 | J59: 150381.61 | K59: =I59-J59 -> -150381.61 | L59: =I59+Jan!L59 -> 0 | M59: =J59+Jan!M59 -> 150381.61 | N59: =L59-M59 -> -150381.61
B60: =1+B59 -> 41 | C60: PAMI Asia Balanced Fund, Inc. | D60: 329171745 | E60: 21066096 | F60: =D60-E60 -> 308105649 | G60: 171152633 | H60: 212 | I60: 0 | J60: 3236193 | K60: =I60-J60 -> -3236193 | L60: =I60+Jan!L60 -> 0 | M60: =J60+Jan!M60 -> 3869515 | N60: =L60-M60 -> -3869515
B61: =1+B60 -> 42 | C61: Sun Life Prosperity Dollar Advantage Fund, Inc. | D61: 1763209520 | E61: 104537726 | F61: =D61-E61 -> 1658671794 | G61: 0 | H61: 4281 | I61: 1363591 | J61: 23289927 | K61: =I61-J61 -> -21926336 | L61: =I61+Jan!L61 -> 4544320 | M61: =J61+Jan!M61 -> 49730689 | N61: =L61-M61 -> -45186369
B62: =1+B61 -> 43 | C62: Sun Life Prosperity Dollar Wellspring Fund, Inc. | D62: 271043915 | E62: 23913055 | F62: =D62-E62 -> 247130860 | G62: 0 | H62: 772 | I62: 242431 | J62: 763337 | K62: =I62-J62 -> -520906 | L62: =I62+Jan!L62 -> 440817 | M62: =J62+Jan!M62 -> 1662316 | N62: =L62-M62 -> -1221499
A63: Sub total - US Currency | D63: =SUM(D59:D62) -> 2428232871 | E63: =SUM(E59:E62) -> 1.5010162e+08 | F63: =SUM(F59:F62) -> 2278131249 | G63: =SUM(G59:G62) -> 171152633 | H63: =SUM(H59:H62) -> 5313 | I63: =SUM(I59:I62) -> 1606022 | J63: =SUM(J59:J62) -> 27439839 | K63: =SUM(K59:K62) -> -25833817 | ... N63: =SUM(N59:N62) -> -50427765
A64: Sub total - balanced funds | D64: =D57+D63 -> 13134935964 | E64: =E57+E63 -> 2.8672194e+08 | F64: =F57+F63 -> 12848214027 | G64: =G57+G63 -> 5463324264 | H64: =H57+H63 -> 91762 | I64: =I57+I63 -> 1.3205117e+08 | J64: =J57+J63 -> 2.7204244e+08 | K64: =K57+K63 -> -139991271 | ... N64: =N57+N63 -> -2.3604114e+08
A65: Bond Funds
A66: Primarily invested in Peso Securities (shares)
B67: =1+B62 -> 44 | C67: ALFM Peso Bond Fund, Inc. | D67: 35037904695 | E67: 315706287 | F67: =D67-E67 -> 34722198408 | G67: 258500000 | H67: 24063 | I67: 277660495 | J67: 398623904 | K67: =I67-J67 -> -120963409 | L67: =I67+Jan!L67 -> 433839003 | M67: =J67+Jan!M67 -> 751626994 | N67: =L67-M67 -> -317787991
B68: =1+B67 -> 45 | C68: ATRAM Corporate Bond Fund, Inc. | D68: 2.6414262e+08 | E68: 2311253.8 | F68: =D68-E68 -> 2.6183137e+08 | G68: 0 | H68: 935 | I68: 996640.2 | J68: 4601362.2 | K68: =I68-J68 -> -3604722 | L68: =I68+Jan!L68 -> 1718357.1 | M68: =J68+Jan!M68 -> 16134323 | N68: =L68-M68 -> -14415966
B69: =1+B68 -> 46 | C69: Cocolife Fixed Income Fund, Inc. | D69: 9.5310111e+08 | E69: 11281985 | F69: =D69-E69 -> 9.4181913e+08 | G69: 0 | H69: 1807 | I69: 3566164 | J69: 12622293 | K69: =I69-J69 -> -9056129.2 | L69: =I69+Jan!L69 -> 14154287 | M69: =J69+Jan!M69 -> 17388607 | N69: =L69-M69 -> -3234320.3
B70: =1+B69 -> 47 | C70: Ekklesia Mutual Fund, Inc. | D70: 188106650 | E70: 163293 | F70: =D70-E70 -> 187943357 | G70: 0 | H70: 136 | I70: 0 | J70: 41820 | K70: =I70-J70 -> -41820 | L70: =I70+Jan!L70 -> 4998 | M70: =J70+Jan!M70 -> 58971 | N70: =L70-M70 -> -53973
B71: =1+B70 -> 48 | C71: First Metro Save and Learn Fixed Income Fund, Inc. | D71: 1175363584 | E71: 5086812 | F71: =D71-E71 -> 1170276772 | G71: 0 | H71: 1748 | I71: 454771 | J71: 15902205 | K71: =I71-J71 -> -15447434 | L71: =I71+Jan!L71 -> 1517997 | M71: =J71+Jan!M71 -> 24360507 | N71: =L71-M71 -> -22842510
B72: =1+B71 -> 49 | C72: Philam Bond Fund, Inc. | D72: 1482187773 | E72: 84688617 | F72: =D72-E72 -> 1397499156 | G72: 0 | H72: 4576 | I72: 1808827 | J72: 7851388 | K72: =I72-J72 -> -6042561 | L72: =I72+Jan!L72 -> 2979049 | M72: =J72+Jan!M72 -> 16985740 | N72: =L72-M72 -> -14006691
B73: =1+B72 -> 50 | C73: Philam Managed Income Fund, Inc. | D73: 613823181 | E73: 9928777 | F73: =D73-E73 -> 603894404 | G73: 0 | H73: 407 | I73: 0 | J73: 7638558 | K73: =I73-J73 -> -7638558 | L73: =I73+Jan!L73 -> 0 | M73: =J73+Jan!M73 -> 17198593 | N73: =L73-M73 -> -17198593
B74: =1+B73 -> 51 | C74: Philequity Peso Bond Fund, Inc. | D74: 3.3293396e+08 | E74: 1250900.2 | F74: =D74-E74 -> 3.3168306e+08 | G74: 0 | H74: 3934 | I74: 4002331.8 | J74: 1307090.7 | K74: =I74-J74 -> 2695241.2 | L74: =I74+Jan!L74 -> 5687938.3 | M74: =J74+Jan!M74 -> 2102097.5 | N74: =L74-M74 -> 3585840.8
B75: =1+B74 -> 52 | C75: Soldivo Bond Fund, Inc. | D75: 1.8336967e+09 | E75: 2940167 | F75: =D75-E75 -> 1830756551 | G75: 0 | H75: 785 | I75: 27568416 | J75: 5067089 | K75: =I75-J75 -> 22501327 | L75: =I75+Jan!L75 -> 27593461 | M75: =J75+Jan!M75 -> 5233703.9 | N75: =L75-M75 -> 22359757
B76: =1+B75 -> 53 | C76: Sun Life Prosperity Bond Fund, Inc. | D76: 6415546996 | E76: 10679833 | F76: =D76-E76 -> 6404867163 | G76: 0 | H76: 19323 | I76: 62370438 | J76: 67861406 | K76: =I76-J76 -> -5490968 | L76: =I76+Jan!L76 -> 109270858 | M76: =J76+Jan!M76 -> 269074576 | N76: =L76-M76 -> -159803718
B77: =1+B76 -> 54 | C77: Sun Life Prosperity GS Fund, Inc. | D77: 144938304 | E77: 348916 | F77: =D77-E77 -> 144589388 | G77: 0 | H77: 2894 | I77: 508077 | J77: 6727882 | K77: =I77-J77 -> -6219805 | L77: =I77+Jan!L77 -> 1374440 | M77: =J77+Jan!M77 -> 7714755 | N77: =L77-M77 -> -6340315
A78: Corporate Debt Vehicle (units)
B79: =1+B77 -> 55 | C79: ATRAM Unitized Corporate Debt Vehicle, Inc. | D79: 7.1736866e+08 | E79: 14579745 | F79: =D79-E79 -> 7.0278891e+08 | G79: 0 | H79: 13 | I79: 0 | J79: 0 | K79: =I79-J79 -> 0 | L79: =I79+Jan!L79 -> 0 | M79: =J79+Jan!M79 -> 0 | N79: =L79-M79 -> 0
A80: Sub total - Peso Currency | D80: =SUM(D67:D79) -> 49159114254 | E80: =SUM(E67:E79) -> 4.5896659e+08 | F80: =SUM(F67:F79) -> 48700147668 | G80: =SUM(G67:G79) -> 258500000 | H80: =SUM(H67:H79) -> 60621 | I80: =SUM(I67:I79) -> 378936160 | J80: =SUM(J67:J79) -> 5.28245e+08 | K80: =SUM(K67:K79) -> -1.4930884e+08 | ... N80: =SUM(N67:N79) -> -5.2973848e+08
A81: Primarily invested in foreign currency securities (shares)
B82: =1+B79 -> 56 | C82: ALFM Dollar Bond Fund, Inc. | D82: 11812201246 | E82: 81715012 | F82: =D82-E82 -> 11730486234 | G82: 0 | H82: 7269 | I82: 30781004 | J82: 92473213 | K82: =I82-J82 -> -61692209 | L82: =I82+Jan!L82 -> 59281143 | M82: =J82+Jan!M82 -> 196004247 | N82: =L82-M82 -> -136723104
B83: =1+B82 -> 57 | C83: ATRAM Total Return Dollar Bond Fund, Inc. | D83: 97580899 | E83: 2082738.5 | F83: =D83-E83 -> 95498161 | G83: 0 | H83: 76 | I83: 0 | J83: 441366.31 | K83: =I83-J83 -> -441366.31 | L83: =I83+Jan!L83 -> 0 | M83: =J83+Jan!M83 -> 1561732.7 | N83: =L83-M83 -> -1561732.7
B84: =1+B83 -> 58 | C84: First Metro Save and Learn Dollar Bond Fund, Inc. | D84: 323067986 | E84: 914294 | F84: =D84-E84 -> 322153692 | G84: 0 | H84: 161 | I84: 7 | J84: 203889 | K84: =I84-J84 -> -203882 | L84: =I84+Jan!L84 -> 129309 | M84: =J84+Jan!M84 -> 802538 | N84: =L84-M84 -> -673229
B85: =1+B84 -> 59 | C85: PAMI Global Bond Fund, Inc. | D85: 68117345 | E85: 16424378 | F85: =D85-E85 -> 51692967 | G85: 0 | H85: 24 | I85: 0 | J85: 0 | K85: =I85-J85 -> 0 | L85: =I85+Jan!L85 -> 0 | M85: =J85+Jan!M85 -> 0 | N85: =L85-M85 -> 0
B86: =1+B85 -> 60 | C86: Philam Dollar Bond Fund, Inc. | D86: 1683467585 | E86: 8291591 | F86: =D86-E86 -> 1675175994 | G86: 0 | H86: 1597 | I86: 17225 | J86: 11931695 | K86: =I86-J86 -> -11914470 | L86: =I86+Jan!L86 -> 57672 | M86: =J86+Jan!M86 -> 38865377 | N86: =L86-M86 -> -38807705
B87: =1+B86 -> 61 | C87: Philequity Dollar Income Fund, Inc. | D87: 2.2866852e+08 | E87: 1223742.6 | F87: =D87-E87 -> 2.2744478e+08 | G87: 0 | H87: 96 | I87: 173985 | J87: 0 | K87: =I87-J87 -> 173985 | L87: =I87+Jan!L87 -> 197331 | M87: =J87+Jan!M87 -> 0 | N87: =L87-M87 -> 197331
B88: =1+B87 -> 62 | C88: Sun Life Prosperity Dollar Abundance Fund, Inc. | D88: 495728438 | E88: 13547663 | F88: =D88-E88 -> 482180775 | G88: 0 | H88: 2645 | I88: 11599 | J88: 16687295 | K88: =I88-J88 -> -16675696 | L88: =I88+Jan!L88 -> 3089846 | M88: =J88+Jan!M88 -> 21296521 | N88: =L88-M88 -> -18206675
A89: Sub total - US Currency | D89: =SUM(D82:D88) -> 14708832024 | E89: =SUM(E82:E88) -> 1.2419942e+08 | F89: =SUM(F82:F88) -> 14584632605 | G89: =SUM(G82:G88) -> 0 | H89: =SUM(H82:H88) -> 11868 | I89: =SUM(I82:I88) -> 30983820 | J89: =SUM(J82:J88) -> 1.2173746e+08 | K89: =SUM(K82:K88) -> -90753638 | ... N89: =SUM(N82:N88) -> -1.9577511e+08
B90: =1+B88 -> 63 | C90: ALFM Euro Bond Fund, Inc. | D90: 709815512 | E90: 5491486 | F90: =D90-E90 -> 704324026 | G90: 0 | H90: 576 | I90: 6965811 | J90: 4483137 | K90: =I90-J90 -> 2482674 | L90: =I90+Jan!L90 -> 15233035 | M90: =J90+Jan!M90 -> 11624004 | N90: =L90-M90 -> 3609031
A91: Sub total - Euro Currency | D91: =SUM(D90) -> 709815512 | E91: =SUM(E90) -> 5491486 | F91: =SUM(F90) -> 704324026 | G91: =SUM(G90) -> 0 | H91: =SUM(H90) -> 576 | I91: =SUM(I90) -> 6965811 | J91: =SUM(J90) -> 4483137 | K91: =SUM(K90) -> 2482674 | ... N91: =SUM(N90) -> 3609031
A92: Sub total - bond funds | D92: =D80+D89+D91 -> 64577761790 | E92: =E80+E89+E91 -> 5.8865749e+08 | F92: =F80+F89+F91 -> 63989104299 | G92: =G80+G89+G91 -> 258500000 | H92: =H80+H89+H91 -> 73065 | I92: =I80+I89+I91 -> 416885791 | J92: =J80+J89+J91 -> 6.5446559e+08 | K92: =K80+K89+K91 -> -2.375798e+08 | ... N92: =N80+N89+N91 -> -7.2190456e+08
A93: Money Market Funds
A94: Primarily invested in Peso Securities (shares)
B95: 64 | C95: AIB Money Market Mutual Fund, Inc. | D95: 1.7182881e+08 | E95: 270682.9 | F95: =D95-E95 -> 1.7155813e+08 | G95: 0 | H95: 69 | I95: 726000 | J95: 0 | K95: =I95-J95 -> 726000 | L95: =I95+Jan!L95 -> 791000 | M95: =J95+Jan!M95 -> 0 | N95: =L95-M95 -> 791000
B96: 65 | C96: ALFM Money Market Fund, Inc. | D96: 21373117843 | E96: 10337146 | F96: =D96-E96 -> 21362780697 | G96: 0 | H96: 22168 | I96: 353990 | J96: 354381193 | K96: =I96-J96 -> -354027203 | L96: =I96+Jan!L96 -> 705568 | M96: =J96+Jan!M96 -> 827969281 | N96: =L96-M96 -> -827263713
B97: =1+B96 -> 66 | C97: First Metro Save and Learn Money Market Fund, Inc. | D97: 2556977968 | E97: 6929410 | F97: =D97-E97 -> 2550048558 | G97: 0 | H97: 1217 | I97: 45315353 | J97: 66896008 | K97: =I97-J97 -> -21580655 | L97: =I97+Jan!L97 -> 174696127 | M97: =J97+Jan!M97 -> 392718975 | N97: =L97-M97 -> -218022848
B98: =1+B97 -> 67 | C98: Sun Life Prosperity Peso Starter Fund, Inc. | D98: 12472363539 | E98: 72278629 | F98: =D98-E98 -> 12400084910 | G98: 0 | H98: 73291 | I98: 170467860 | J98: 334151491 | K98: =I98-J98 -> -163683631 | L98: =I98+Jan!L98 -> 960748452 | M98: =J98+Jan!M98 -> 1024927739 | N98: =L98-M98 -> -64179287
A99: Primarily invested in Peso Securities (units)
B100: =1+B98 -> 68 | C100: ALFM Money Market Fund, Inc. | D100: 11561509374 | E100: 5969773 | F100: =D100-E100 -> 11555539601 | G100: 0 | H100: 26474 | I100: 756886453 | J100: 536113649 | K100: =I100-J100 -> 220772804 | L100: =I100+Jan!L100 -> 1480488549 | M100: =J100+Jan!M100 -> 1400458681 | N100: =L100-M100 -> 80029868
A101: Sub total - Peso Currency | D101: =SUM(D95:D98)+D100 -> 48135797535 | E101: =SUM(E95:E98)+E100 -> 95785641 | F101: =SUM(F95:F98)+F100 -> 48040011895 | G101: =SUM(G95:G98)+G100 -> 0 | H101: =SUM(H95:H98)+H100 -> 123219 | I101: =SUM(I95:I98)+I100 -> 973749656 | J101: =SUM(J95:J98)+J100 -> 1291542341 | K101: =SUM(K95:K98)+K100 -> -317792685 | ... N101: =SUM(N95:N98)+N100 -> -1028644980
A102: Primarily invested in foreign currency securities (shares)
B103: =1+B100 -> 69 | C103: Sun Life Prosperity Dollar Starter Fund, Inc. | D103: 2383931932 | E103: 4788671 | F103: =D103-E103 -> 2379143261 | G103: 0 | H103: 3821 | I103: 215251222 | J103: 59621792 | K103: =I103-J103 -> 155629430 | L103: =I103+Jan!L103 -> 359393258 | M103: =J103+Jan!M103 -> 329130606 | N103: =L103-M103 -> 30262652
A104: Sub total - US Currency | D104: =SUM(D103) -> 2383931932 | E104: =SUM(E103) -> 4788671 | F104: =SUM(F103) -> 2379143261 | G104: =SUM(G103) -> 0 | H104: =SUM(H103) -> 3821 | I104: =SUM(I103) -> 215251222 | J104: =SUM(J103) -> 59621792 | K104: =SUM(K103) -> 155629430 | ... N104: =SUM(N103) -> 30262652
A105: Sub total - money market funds | D105: =D101+D104 -> 50519729467 | E105: =E101+E104 -> 1.0057431e+08 | F105: =F101+F104 -> 50419155156 | G105: =G101+G104 -> 0 | H105: =H101+H104 -> 127040 | I105: =I101+I104 -> 1189000878 | J105: =J101+J104 -> 1351164133 | K105: =K101+K104 -> -162163255 | ... N105: =N101+N104 -> -998382328
...

Sheet Feb UPDATED
A1: PHILIPPINE INVESTMENT FUNDS ASSOCIATION, INC.
A2: MUTUAL FUNDS STATISTICAL REPORT
A3: Month of February 2025
A4: (Amounts in Peso)
I5: F O R - T H E - M O N T H | L5: Y E A R - T O - D A T E
A6: Fund Category | C6: Fund Name | D6: ASSETS | E6: LIABILITIES | F6: NET ASSETS | G6: EQUITY INV. | H6: NO. OF A/C | I6: SALES | J6: REDEMPTIONS | K6: NET SALES | L6: TOTAL SALES | M6: TOTAL REDEMPTIONS | N6: TOTAL NET SALES
A7: Stock Funds
A8: Primarily invested in Peso Securities (shares)
B9: 1 | C9: ALFM Growth Fund, Inc. | D9: 3614590099 | E9: 9804439 | F9: =D9-E9 -> 3604785660 | G9: 3550553739 | H9: 5820 | I9: 8526054 | J9: 24540198 | K9: =I9-J9 -> -16014144 | L9: =I9+Jan!L9 -> 20025356 | M9: =J9+Jan!M9 -> 54754773 | N9: =L9-M9 -> -34729417
B10: =1+B9 -> 2 | C10: ATRAM Alpha Opportunity Fund, Inc. | D10: 9.7563577e+08 | E10: 58807440 | F10: =D10-E10 -> 9.1682833e+08 | G10: 846930515 | H10: 4101 | I10: 29130413 | J10: 17776753 | K10: =I10-J10 -> 11353659 | L10: =I10+Jan!L10 -> 42300957 | M10: =J10+Jan!M10 -> 23997346 | N10: =L10-M10 -> 18303611
B11: =1+B10 -> 3 | C11: ATRAM Phil. Equity Opportunity Fund, Inc. | D11: 1.0590887e+09 | E11: 41496227 | F11: =D11-E11 -> 1017592443 | G11: 9.6020108e+08 | H11: 2491 | I11: 7391344.5 | J11: 4318041.7 | K11: =I11-J11 -> 3073302.8 | L11: =I11+Jan!L11 -> 12775280 | M11: =J11+Jan!M11 -> 12942108 | N11: =L11-M11 -> -166828.01
B12: =1+B11 -> 4 | C12: Climbs Share Capital Equity Investment Fund Corp. | D12: 4.2146263e+08 | E12: 16453509 | F12: =D12-E12 -> 4.0500912e+08 | G12: 3.6255925e+08 | H12: 1709 | I12: 593070 | J12: 699624.3 | K12: =I12-J12 -> -106554.3 | L12: =I12+Jan!L12 -> 21082303 | M12: =J12+Jan!M12 -> 976097.65 | N12: =L12-M12 -> 20106206
B13: =1+B12 -> 5 | C13: First Metro Consumer Fund, Inc. | D13: 350949757 | E13: 747413 | F13: =D13-E13 -> 350202344 | G13: 254813507 | H13: 1155 | I13: 306037 | J13: 545372 | K13: =I13-J13 -> -239335 | L13: =I13+Jan!L13 -> 562059 | M13: =J13+Jan!M13 -> 7514746 | N13: =L13-M13 -> -6952687
B14: =1+B13 -> 6 | C14: First Metro Save and Learn Equity Fund, Inc. | D14: 2999143112 | E14: 8918826 | F14: =D14-E14 -> 2990224286 | G14: 2442258472 | H14: 14421 | I14: 28260213 | J14: 41238048 | K14: =I14-J14 -> -12977835 | L14: =I14+Jan!L14 -> 35985319 | M14: =J14+Jan!M14 -> 98679187 | N14: =L14-M14 -> -62693868
B15: =1+B14 -> 7 | C15: First Metro Save and Learn Phil. Index Fund, Inc. | D15: 85088943 | E15: 353406 | F15: =D15-E15 -> 84735537 | G15: 77831015 | H15: 477 | I15: 5473707 | J15: 179157 | K15: =I15-J15 -> 5294550 | L15: =I15+Jan!L15 -> 5765587 | M15: =J15+Jan!M15 -> 873016 | N15: =L15-M15 -> 4892571
B16: =1+B15 -> 8 | C16: MBG Equity Investment Fund, Inc. | D16: 117859044 | E16: 1412322 | F16: =D16-E16 -> 116446722 | G16: 108671198 | H16: 43 | I16: 0 | J16: 0 | K16: =I16-J16 -> 0 | L16: =I16+Jan!L16 -> 0 | M16: =J16+Jan!M16 -> 0 | N16: =L16-M16 -> 0
B17: =1+B16 -> 9 | C17: PAMI Equity Index Fund, Inc. | D17: 984401545 | E17: 24592054 | F17: =D17-E17 -> 959809491 | G17: 970682329 | H17: 10897 | I17: 0 | J17: 2577792 | K17: =I17-J17 -> -2577792 | L17: =I17+Jan!L17 -> 0 | M17: =J17+Jan!M17 -> 14078394 | N17: =L17-M17 -> -14078394
B18: =1+B17 -> 10 | C18: Philam Strategic Growth Fund, Inc. | D18: 3023222400 | E18: 44931046 | F18: =D18-E18 -> 2978291354 | G18: 2959270074 | H18: 10760 | I18: 5943949 | J18: 44233057 | K18: =I18-J18 -> -38289108 | L18: =I18+Jan!L18 -> 13514420 | M18: =J18+Jan!M18 -> 54768840 | N18: =L18-M18 -> -41254420
B19: =1+B18 -> 11 | C19: Philequity Dividend Yield Fund, Inc. | D19: 2.482421e+09 | E19: 3733841.7 | F19: =D19-E19 -> 2478687115 | G19: 2.2618273e+09 | H19: 4987 | I19: 10296707 | J19: 2915154.5 | K19: =I19-J19 -> 7381552.7 | L19: =I19+Jan!L19 -> 16257175 | M19: =J19+Jan!M19 -> 7250737.2 | N19: =L19-M19 -> 9006437.8
B20: =1+B19 -> 12 | C20: Philequity Fund, Inc. | D20: 8.7195517e+09 | E20: 1.5736146e+08 | F20: =D20-E20 -> 8562190284 | G20: 8.0222041e+09 | H20: 31851 | I20: 7707527.2 | J20: 17618680 | K20: =I20-J20 -> -9911152.9 | L20: =I20+Jan!L20 -> 16751452 | M20: =J20+Jan!M20 -> 51464776 | N20: =L20-M20 -> -34713324
B21: =1+B20 -> 13 | C21: Philequity MSCI Phil. Index Fund, Inc. | D21: 2.9667971e+08 | E21: 2988299.6 | F21: =D21-E21 -> 2.9369141e+08 | G21: 2.8591525e+08 | H21: 890 | I21: 384397.33 | J21: 53008.27 | K21: =I21-J21 -> 331389.06 | L21: =I21+Jan!L21 -> 810728.51 | M21: =J21+Jan!M21 -> 283975.61 | N21: =L21-M21 -> 526752.9
... B27: =1+B26 -> 19 | C27: United Fund, Inc. | D27: 4.8489152e+08 | E27: 12147024 | F27: =D27-E27 -> 4.727445e+08 | G27: 4.6132164e+08 | H27: 1201 | I27: 488658.88 | J27: 77704.41 | K27: =I27-J27 -> 410954.47 | L27: =I27+Jan!L27 -> 872352.68 | M27: =J27+Jan!M27 -> 233717.13 | N27: =L27-M27 -> 638635.55
A28: Primarily invested in Peso Securities (units)
B29: =1+B27 -> 20 | C29: COL Equity Index Unitized Mutual Fund, Inc. | D29: 2.2057332e+08 | E29: 679642.68 | F29: =D29-E29 -> 2.1989368e+08 | G29: 2.1035685e+08 | H29: 4611 | I29: 7128940.7 | J29: 10780180 | K29: =I29-J29 -> -3651239.4 | L29: =I29+Jan!L29 -> 21333596 | M29: =J29+Jan!M29 -> 12483158 | N29: =L29-M29 -> 8850437.8
B30: =1+B29 -> 21 | C30: COL Strategic Growth Equity Unitized Mutual Fund, Inc. | D30: 3.9513504e+08 | E30: 2678228.1 | F30: =D30-E30 -> 3.9245681e+08 | G30: 314883869 | H30: 6017 | I30: 18418420 | J30: 3195589 | K30: =I30-J30 -> 15222831 | L30: =I30+Jan!L30 -> 36003905 | M30: =J30+Jan!M30 -> 12450786 | N30: =L30-M30 -> 23553119
B31: =1+B30 -> 22 | C31: Philequity Alpha One Fund, Inc. | D31: 2.5394841e+08 | E31: 833338.16 | F31: =D31-E31 -> 2.5311507e+08 | G31: 2.5099544e+08 | H31: 1142 | I31: 2348070.8 | J31: 12035552 | K31: =I31-J31 -> -9687481.2 | L31: =I31+Jan!L31 -> 2740738.8 | M31: =J31+Jan!M31 -> 12396999 | N31: =L31-M31 -> -9656260
B32: =1+B31 -> 23 | C32: Philippine Stock Index Fund Corp. | D32: 673460777 | E32: 8406067 | F32: =D32-E32 -> 665054710 | G32: 664103983 | H32: 755020 | I32: 40951090 | J32: 34020108 | K32: =I32-J32 -> 6930982 | L32: =I32+Jan!L32 -> 105978318 | M32: =J32+Jan!M32 -> 79303292 | N32: =L32-M32 -> 26675026
A33: Exchange Traded Fund
B34: =1+B32 -> 24 | C34: First Metro Phil. Equity Exchange Traded Fund, Inc. | D34: 1317597331 | E34: 1941343 | F34: =D34-E34 -> 1315655988 | G34: 1314949404 | H34: 3278 | I34: 27108889 | J34: 0 | K34: =I34-J34 -> 27108889 | L34: =I34+Jan!L34 -> 40232388 | M34: =J34+Jan!M34 -> 0 | N34: =L34-M34 -> 40232388
A35: Sub total - Peso Currency | D35: =SUM(D9:D34) -> 54802113405 | E35: =SUM(E9:E34) -> 6.7922424e+08 | F35: =SUM(F9:F34) -> 54122889167 | G35: =SUM(G9:G34) -> 51981591359 | H35: =SUM(H9:H34) -> 1034017 | I35: =SUM(I9:I34) -> 327765508 | J35: =SUM(J9:J34) -> 4.9561963e+08 | K35: =SUM(K9:K34) -> -1.6785412e+08 | ... N35: =SUM(N9:N34) -> -3.3632128e+08
A36: Primarily invested in foreign currency securities (shares)
B37: =1+B34 -> 25 | C37: ATRAM AsiaPlus Equity Fund, Inc. | D37: 27883687 | E37: 237825.32 | F37: =D37-E37 -> 27645862 | G37: 0 | H37: 50 | I37: 57972.38 | J37: 25942.32 | K37: =I37-J37 -> 32030.06 | L37: =I37+Jan!L37 -> 104642.2 | M37: =J37+Jan!M37 -> 124603.1 | N37: =L37-M37 -> -19960.9
B38: =1+B37 -> 26 | C38: Sun Life Prosperity World Voyager Fund, Inc. | D38: 2051182309 | E38: 24649862 | F38: =D38-E38 -> 2026532447 | G38: 0 | H38: 3192 | I38: 46285415 | J38: 69993528 | K38: =I38-J38 -> -23708113 | L38: =I38+Jan!L38 -> 71232690 | M38: =J38+Jan!M38 -> 82010784 | N38: =L38-M38 -> -10778094
A39: Sub total - US Currency | D39: =SUM(D37:D38) -> 2079065996 | E39: =SUM(E37:E38) -> 24887687 | F39: =SUM(F37:F38) -> 2054178309 | G39: =SUM(G37:G38) -> 0 | H39: =SUM(H37:H38) -> 3242 | I39: =SUM(I37:I38) -> 46343387 | J39: =SUM(J37:J38) -> 70019470 | K39: =SUM(K37:K38) -> -23676083 | ... N39: =SUM(N37:N38) -> -10798055
A40: Sub total - stock funds | D40: =D35+D39 -> 56881179401 | E40: =E35+E39 -> 7.0411193e+08 | F40: =F35+F39 -> 56177067476 | G40: =G35+G39 -> 51981591359 | H40: =H35+H39 -> 1037259 | I40: =I35+I39 -> 3.741089e+08 | J40: =J35+J39 -> 5.656391e+08 | K40: =K35+K39 -> -1.915302e+08 | ... N40: =N35+N39 -> -3.4711933e+08
A41: Balanced Funds
A42: Primarily invested in Peso Securities (shares)
B43: =1+B38 -> 27 | C43: ATRAM Philippine Balanced Fund, Inc. | D43: 4.1445908e+08 | E43: 22106061 | F43: =D43-E43 -> 3.9235302e+08 | G43: 2.081194e+08 | H43: 2316 | I43: 437016.77 | J43: 10198627 | K43: =I43-J43 -> -9761610.1 | L43: =I43+Jan!L43 -> 907323.03 | M43: =J43+Jan!M43 -> 16805833 | N43: =L43-M43 -> -15898510
B44: =1+B43 -> 28 | C44: ATRAM Unicapital Diversified Growth Fund, Inc. | D44: 1.1474133e+08 | E44: 2717663.1 | F44: =D44-E44 -> 1.1202367e+08 | G44: 29379221 | H44: 811 | I44: 290811.7 | J44: 407410.94 | K44: =I44-J44 -> -116599.24 | L44: =I44+Jan!L44 -> 658852.4 | M44: =J44+Jan!M44 -> 872370.59 | N44: =L44-M44 -> -213518.19
B45: =1+B44 -> 29 | C45: First Metro Save and Learn Balanced Fund, Inc. | D45: 640273113 | E45: 2636848 | F45: =D45-E45 -> 637636265 | G45: 270617654 | H45: 4096 | I45: 647209 | J45: 5537711 | K45: =I45-J45 -> -4890502 | L45: =I45+Jan!L45 -> 1797310 | M45: =J45+Jan!M45 -> 10510924 | N45: =L45-M45 -> -8713614
B46: =1+B45 -> 30 | C46: First Metro Save and Learn F.O.C.C.U.S. Dynamic Fund, Inc. | D46: 439985781 | E46: 1070074 | F46: =D46-E46 -> 438915707 | G46: 305145322 | H46: 365 | I46: 862427 | J46: 32178451 | K46: =I46-J46 -> -31316024 | L46: =I46+Jan!L46 -> 5478201 | M46: =J46+Jan!M46 -> 32743412 | N46: =L46-M46 -> -27265211
B47: =1+B46 -> 31 | C47: NCM Mutual Fund of the Phils., Inc. | D47: 3.1081158e+08 | E47: 1024750.7 | F47: =D47-E47 -> 3.0978683e+08 | G47: 1.4801722e+08 | H47: 46 | I47: 2.3662765e+08 | J47: 2.3704074e+08 | K47: =I47-J47 -> -413082.32 | L47: =I47+Jan!L47 -> 2.3662765e+08 | M47: =J47+Jan!M47 -> 2.3704074e+08 | N47: =L47-M47 -> -413082.32
B48: =1+B47 -> 32 | C48: PAMI Horizon Fund, Inc. | D48: 445982559 | E48: 14201661 | F48: =D48-E48 -> 431780898 | G48: 207080114 | H48: 9638 | I48: 33038 | J48: 1971975 | K48: =I48-J48 -> -1938937 | L48: =I48+Jan!L48 -> 60176 | M48: =J48+Jan!M48 -> 4594950 | N48: =L48-M48 -> -4534774
B49: =1+B48 -> 33 | C49: Philam Fund, Inc. | D49: 1810914268 | E49: 19470841 | F49: =D49-E49 -> 1791443427 | G49: 845716072 | H49: 7346 | I49: 451884 | J49: 16125413 | K49: =I49-J49 -> -15673529 | L49: =I49+Jan!L49 -> 849613 | M49: =J49+Jan!M49 -> 25646828 | N49: =L49-M49 -> -24797215
B50: =1+B49 -> 34 | C50: Solidaritas Fund, Inc. | D50: 117783321 | E50: 912809 | F50: =D50-E50 -> 116870512 | G50: 57094895 | H50: 158 | I50: 0 | J50: 25801 | K50: =I50-J50 -> -25801 | L50: =I50+Jan!L50 -> 0 | M50: =J50+Jan!M50 -> 1672556 | N50: =L50-M50 -> -1672556
B51: =1+B50 -> 35 | C51: Sun Life Prosperity Balanced Fund, Inc. | D51: 5773731260 | E51: 64716407 | F51: =D51-E51 -> 5709014853 | G51: 2886035977 | H51: 54663 | I51: 4829646 | J51: 46156030 | K51: =I51-J51 -> -41326384 | L51: =I51+Jan!L51 -> 12530044 | M51: =J51+Jan!M51 -> 93426670 | N51: =L51-M51 -> -80896626
B52: =1+B51 -> 36 | C52: Sun Life Prosperity Dynamic Fund, Inc. | D52: 463682813 | E52: 6939679 | F52: =D52-E52 -> 456743134 | G52: 245959562 | H52: 5000 | I52: 0 | J52: 8784024 | K52: =I52-J52 -> -8784024 | L52: =I52+Jan!L52 -> 0 | M52: =J52+Jan!M52 -> 21030752 | N52: =L52-M52 -> -21030752
A53: Primarily invested in Peso Securities (units) | L53: =I53+Jan!L53 -> 0 | M53: =J53+Jan!M53 -> 0
B54: =1+B52 -> 37 | C54: Sun Life Prosperity Achiever Fund 2028, Inc. | D54: 75393922 | E54: 294678 | F54: =D54-E54 -> 75099244 | G54: 14912081 | H54: 1254 | I54: 207829 | J54: 339230 | K54: =I54-J54 -> -131401 | L54: =I54+Jan!L54 -> 445024 | M54: =J54+Jan!M54 -> 906709 | N54: =L54-M54 -> -461685
B55: =1+B54 -> 38 | C55: Sun Life Prosperity Achiever Fund 2038, Inc. | D55: 53738844 | E55: 250696 | F55: =D55-E55 -> 53488148 | G55: 37509380 | H55: 510 | I55: 63503 | J55: 118325 | K55: =I55-J55 -> -54822 | L55: =I55+Jan!L55 -> 148643 | M55: =J55+Jan!M55 -> 186630 | N55: =L55-M55 -> -37987
B56: =1+B55 -> 39 | C56: Sun Life Prosperity Achiever Fund 2048, Inc. | D56: 45205220 | E56: 278147 | F56: =D56-E56 -> 44927073 | G56: 36584727 | H56: 246 | I56: 118342 | J56: 42308 | K56: =I56-J56 -> 76034 | L56: =I56+Jan!L56 -> 167361 | M56: =J56+Jan!M56 -> 44430 | N56: =L56-M56 -> 122931
A57: Sub total - Peso Currency | D57: =SUM(D43:D56) -> 10706703093 | E57: =SUM(E42:E56) -> 1.3662031e+08 | F57: =SUM(F43:F56) -> 10570082778 | G57: =SUM(G43:G56) -> 5292171631 | H57: =SUM(H43:H56) -> 86449 | I57: =SUM(I42:I56) -> 2.4456936e+08 | J57: =SUM(J43:J56) -> 3.5892604e+08 | K57: =SUM(K43:K56) -> -1.1435668e+08 | L57: =SUM(L43:L56) -> 2.596702e+08 | M57: =SUM(M43:M56) -> 4.454828e+08 | N57: =SUM(N43:N56) -> -1.858126e+08
A58: Primarily invested in foreign currency securities (shares)
B59: =1+B56 -> 40 | C59: Cocolife Dollar Fund Builder, Inc. | D59: 64807691 | E59: 584745.61 | F59: =D59-E59 -> 64222946 | G59: 0 | H59: 48 | I59: 0 | J59: 150381.61 | K59: =I59-J59 -> -150381.61 | L59: =I59+Jan!L59 -> 0 | M59: =J59+Jan!M59 -> 150381.61 | N59: =L59-M59 -> -150381.61
B60: =1+B59 -> 41 | C60: PAMI Asia Balanced Fund, Inc. | D60: 329171745 | E60: 21066096 | F60: =D60-E60 -> 308105649 | G60: 171152633 | H60: 212 | I60: 0 | J60: 3236193 | K60: =I60-J60 -> -3236193 | L60: =I60+Jan!L60 -> 0 | M60: =J60+Jan!M60 -> 3869515 | N60: =L60-M60 -> -3869515
B61: =1+B60 -> 42 | C61: Sun Life Prosperity Dollar Advantage Fund, Inc. | D61: 1763209520 | E61: 104537726 | F61: =D61-E61 -> 1658671794 | G61: 0 | H61: 4281 | I61: 1363591 | J61: 23289927 | K61: =I61-J61 -> -21926336 | L61: =I61+Jan!L61 -> 4544320 | M61: =J61+Jan!M61 -> 49730689 | N61: =L61-M61 -> -45186369
B62: =1+B61 -> 43 | C62: Sun Life Prosperity Dollar Wellspring Fund, Inc. | D62: 271043915 | E62: 23913055 | F62: =D62-E62 -> 247130860 | G62: 0 | H62: 772 | I62: 242431 | J62: 763337 | K62: =I62-J62 -> -520906 | L62: =I62+Jan!L62 -> 440817 | M62: =J62+Jan!M62 -> 1662316 | N62: =L62-M62 -> -1221499
A63: Sub total - US Currency | D63: =SUM(D59:D62) -> 2428232871 | E63: =SUM(E59:E62) -> 1.5010162e+08 | F63: =SUM(F59:F62) -> 2278131249 | G63: =SUM(G59:G62) -> 171152633 | H63: =SUM(H59:H62) -> 5313 | I63: =SUM(I59:I62) -> 1606022 | J63: =SUM(J59:J62) -> 27439839 | K63: =SUM(K59:K62) -> -25833817 | ... N63: =SUM(N59:N62) -> -50427765
A64: Sub total - balanced funds | D64: =D57+D63 -> 13134935964 | E64: =E57+E63 -> 2.8672194e+08 | F64: =F57+F63 -> 12848214027 | G64: =G57+G63 -> 5463324264 | H64: =H57+H63 -> 91762 | I64: =I57+I63 -> 2.4617538e+08 | J64: =J57+J63 -> 3.8636588e+08 | K64: =K57+K63 -> -1.401905e+08 | ... N64: =N57+N63 -> -2.3624036e+08
A65: Bond Funds
A66: Primarily invested in Peso Securities (shares)
B67: =1+B62 -> 44 | C67: ALFM Peso Bond Fund, Inc. | D67: 35037904695 | E67: 315706287 | F67: =D67-E67 -> 34722198408 | G67: 258500000 | H67: 24063 | I67: 277660495 | J67: 398623904 | K67: =I67-J67 -> -120963409 | L67: =I67+Jan!L67 -> 433839003 | M67: =J67+Jan!M67 -> 751626994 | N67: =L67-M67 -> -317787991
B68: =1+B67 -> 45 | C68: ATRAM Corporate Bond Fund, Inc. | D68: 2.6414262e+08 | E68: 2311253.8 | F68: =D68-E68 -> 2.6183137e+08 | G68: 0 | H68: 935 | I68: 996640.2 | J68: 4601362.2 | K68: =I68-J68 -> -3604722 | L68: =I68+Jan!L68 -> 1718357.1 | M68: =J68+Jan!M68 -> 16134323 | N68: =L68-M68 -> -14415966
B69: =1+B68 -> 46 | C69: Cocolife Fixed Income Fund, Inc. | D69: 9.5310111e+08 | E69: 11281985 | F69: =D69-E69 -> 9.4181913e+08 | G69: 0 | H69: 1807 | I69: 3566164 | J69: 12622293 | K69: =I69-J69 -> -9056129.2 | L69: =I69+Jan!L69 -> 14154287 | M69: =J69+Jan!M69 -> 17388607 | N69: =L69-M69 -> -3234320.3
B70: =1+B69 -> 47 | C70: Ekklesia Mutual Fund, Inc. | D70: 188106650 | E70: 163293 | F70: =D70-E70 -> 187943357 | G70: 0 | H70: 136 | I70: 0 | J70: 41820 | K70: =I70-J70 -> -41820 | L70: =I70+Jan!L70 -> 4998 | M70: =J70+Jan!M70 -> 58971 | N70: =L70-M70 -> -53973
B71: =1+B70 -> 48 | C71: First Metro Save and Learn Fixed Income Fund, Inc. | D71: 1175363584 | E71: 5086812 | F71: =D71-E71 -> 1170276772 | G71: 0 | H71: 1748 | I71: 454771 | J71: 15902205 | K71: =I71-J71 -> -15447434 | L71: =I71+Jan!L71 -> 1517997 | M71: =J71+Jan!M71 -> 24360507 | N71: =L71-M71 -> -22842510
B72: =1+B71 -> 49 | C72: Philam Bond Fund, Inc. | D72: 1482187773 | E72: 84688617 | F72: =D72-E72 -> 1397499156 | G72: 0 | H72: 4576 | I72: 1808827 | J72: 7851388 | K72: =I72-J72 -> -6042561 | L72: =I72+Jan!L72 -> 2979049 | M72: =J72+Jan!M72 -> 16985740 | N72: =L72-M72 -> -14006691
B73: =1+B72 -> 50 | C73: Philam Managed Income Fund, Inc. | D73: 613823181 | E73: 9928777 | F73: =D73-E73 -> 603894404 | G73: 0 | H73: 407 | I73: 0 | J73: 7638558 | K73: =I73-J73 -> -7638558 | L73: =I73+Jan!L73 -> 0 | M73: =J73+Jan!M73 -> 17198593 | N73: =L73-M73 -> -17198593
B74: =1+B73 -> 51 | C74: Philequity Peso Bond Fund, Inc. | D74: 3.3293396e+08 | E74: 1250900.2 | F74: =D74-E74 -> 3.3168306e+08 | G74: 0 | H74: 3934 | I74: 4002331.8 | J74: 1307090.7 | K74: =I74-J74 -> 2695241.2 | L74: =I74+Jan!L74 -> 5687938.3 | M74: =J74+Jan!M74 -> 2102097.5 | N74: =L74-M74 -> 3585840.8
B75: =1+B74 -> 52 | C75: Soldivo Bond Fund, Inc. | D75: 1.8336967e+09 | E75: 2940167 | F75: =D75-E75 -> 1830756551 | G75: 0 | H75: 785 | I75: 27568416 | J75: 5067089 | K75: =I75-J75 -> 22501327 | L75: =I75+Jan!L75 -> 27593461 | M75: =J75+Jan!M75 -> 5233703.9 | N75: =L75-M75 -> 22359757
B76: =1+B75 -> 53 | C76: Sun Life Prosperity Bond Fund, Inc. | D76: 6415546996 | E76: 10679833 | F76: =D76-E76 -> 6404867163 | G76: 0 | H76: 19323 | I76: 62370438 | J76: 67861406 | K76: =I76-J76 -> -5490968 | L76: =I76+Jan!L76 -> 109270858 | M76: =J76+Jan!M76 -> 269074576 | N76: =L76-M76 -> -159803718
B77: =1+B76 -> 54 | C77: Sun Life Prosperity GS Fund, Inc. | D77: 144938304 | E77: 348916 | F77: =D77-E77 -> 144589388 | G77: 0 | H77: 2894 | I77: 508077 | J77: 6727882 | K77: =I77-J77 -> -6219805 | L77: =I77+Jan!L77 -> 1374440 | M77: =J77+Jan!M77 -> 7714755 | N77: =L77-M77 -> -6340315
A78: Corporate Debt Vehicle (units)
B79: =1+B77 -> 55 | C79: ATRAM Unitized Corporate Debt Vehicle, Inc. | D79: 7.1736866e+08 | E79: 14579745 | F79: =D79-E79 -> 7.0278891e+08 | G79: 0 | H79: 13 | I79: 0 | J79: 0 | K79: =I79-J79 -> 0 | L79: =I79+Jan!L79 -> 0 | M79: =J79+Jan!M79 -> 0 | N79: =L79-M79 -> 0
A80: Sub total - Peso Currency | D80: =SUM(D67:D79) -> 49159114254 | E80: =SUM(E67:E79) -> 4.5896659e+08 | F80: =SUM(F67:F79) -> 48700147668 | G80: =SUM(G67:G79) -> 258500000 | H80: =SUM(H67:H79) -> 60621 | I80: =SUM(I67:I79) -> 378936160 | J80: =SUM(J67:J79) -> 5.28245e+08 | K80: =SUM(K67:K79) -> -1.4930884e+08 | ... N80: =SUM(N67:N79) -> -5.2973848e+08
A81: Primarily invested in foreign currency securities (shares)
B82: =1+B79 -> 56 | C82: ALFM Dollar Bond Fund, Inc. | D82: 11812201246 | E82: 81715012 | F82: =D82-E82 -> 11730486234 | G82: 0 | H82: 7269 | I82: 30781004 | J82: 92473213 | K82: =I82-J82 -> -61692209 | L82: =I82+Jan!L82 -> 59281143 | M82: =J82+Jan!M82 -> 196004247 | N82: =L82-M82 -> -136723104
B83: =1+B82 -> 57 | C83: ATRAM Total Return Dollar Bond Fund, Inc. | D83: 97580899 | E83: 2082738.5 | F83: =D83-E83 -> 95498161 | G83: 0 | H83: 76 | I83: 0 | J83: 441366.31 | K83: =I83-J83 -> -441366.31 | L83: =I83+Jan!L83 -> 0 | M83: =J83+Jan!M83 -> 1561732.7 | N83: =L83-M83 -> -1561732.7
B84: =1+B83 -> 58 | C84: First Metro Save and Learn Dollar Bond Fund, Inc. | D84: 323067986 | E84: 914294 | F84: =D84-E84 -> 322153692 | G84: 0 | H84: 161 | I84: 7 | J84: 203889 | K84: =I84-J84 -> -203882 | L84: =I84+Jan!L84 -> 129309 | M84: =J84+Jan!M84 -> 802538 | N84: =L84-M84 -> -673229
B85: =1+B84 -> 59 | C85: PAMI Global Bond Fund, Inc. | D85: 68117345 | E85: 16424378 | F85: =D85-E85 -> 51692967 | G85: 0 | H85: 24 | I85: 0 | J85: 0 | K85: =I85-J85 -> 0 | L85: =I85+Jan!L85 -> 0 | M85: =J85+Jan!M85 -> 0 | N85: =L85-M85 -> 0
B86: =1+B85 -> 60 | C86: Philam Dollar Bond Fund, Inc. | D86: 1683467585 | E86: 8291591 | F86: =D86-E86 -> 1675175994 | G86: 0 | H86: 1597 | I86: 17225 | J86: 11931695 | K86: =I86-J86 -> -11914470 | L86: =I86+Jan!L86 -> 57672 | M86: =J86+Jan!M86 -> 38865377 | N86: =L86-M86 -> -38807705
B87: =1+B86 -> 61 | C87: Philequity Dollar Income Fund, Inc. | D87: 2.2866852e+08 | E87: 1223742.6 | F87: =D87-E87 -> 2.2744478e+08 | G87: 0 | H87: 96 | I87: 173985 | J87: 0 | K87: =I87-J87 -> 173985 | L87: =I87+Jan!L87 -> 197331 | M87: =J87+Jan!M87 -> 0 | N87: =L87-M87 -> 197331
B88: =1+B87 -> 62 | C88: Sun Life Prosperity Dollar Abundance Fund, Inc. | D88: 495728438 | E88: 13547663 | F88: =D88-E88 -> 482180775 | G88: 0 | H88: 2645 | I88: 11599 | J88: 16687295 | K88: =I88-J88 -> -16675696 | L88: =I88+Jan!L88 -> 3089846 | M88: =J88+Jan!M88 -> 21296521 | N88: =L88-M88 -> -18206675
A89: Sub total - US Currency | D89: =SUM(D82:D88) -> 14708832024 | E89: =SUM(E82:E88) -> 1.2419942e+08 | F89: =SUM(F82:F88) -> 14584632605 | G89: =SUM(G82:G88) -> 0 | H89: =SUM(H82:H88) -> 11868 | I89: =SUM(I82:I88) -> 30983820 | J89: =SUM(J82:J88) -> 1.2173746e+08 | K89: =SUM(K82:K88) -> -90753638 | ... N89: =SUM(N82:N88) -> -1.9577511e+08
B90: =1+B88 -> 63 | C90: ALFM Euro Bond Fund, Inc. | D90: 709815512 | E90: 5491486 | F90: =D90-E90 -> 704324026 | G90: 0 | H90: 576 | I90: 6965811 | J90: 4483137 | K90: =I90-J90 -> 2482674 | L90: =I90+Jan!L90 -> 15233035 | M90: =J90+Jan!M90 -> 11624004 | N90: =L90-M90 -> 3609031
A91: Sub total - Euro Currency | D91: =SUM(D90) -> 709815512 | E91: =SUM(E90) -> 5491486 | F91: =SUM(F90) -> 704324026 | G91: =SUM(G90) -> 0 | H91: =SUM(H90) -> 576 | I91: =SUM(I90) -> 6965811 | J91: =SUM(J90) -> 4483137 | K91: =SUM(K90) -> 2482674 | ... N91: =SUM(N90) -> 3609031
A92: Sub total - bond funds | D92: =D80+D89+D91 -> 64577761790 | E92: =E80+E89+E91 -> 5.8865749e+08 | F92: =F80+F89+F91 -> 63989104299 | G92: =G80+G89+G91 -> 258500000 | H92: =H80+H89+H91 -> 73065 | I92: =I80+I89+I91 -> 416885791 | J92: =J80+J89+J91 -> 6.5446559e+08 | K92: =K80+K89+K91 -> -2.375798e+08 | ... N92: =N80+N89+N91 -> -7.2190456e+08
A93: Money Market Funds
A94: Primarily invested in Peso Securities (shares)
B95: 64 | C95: AIB Money Market Mutual Fund, Inc. | D95: 1.7182881e+08 | E95: 270682.9 | F95: =D95-E95 -> 1.7155813e+08 | G95: 0 | H95: 69 | I95: 726000 | J95: 0 | K95: =I95-J95 -> 726000 | L95: =I95+Jan!L95 -> 791000 | M95: =J95+Jan!M95 -> 0 | N95: =L95-M95 -> 791000
B96: 65 | C96: ALFM Money Market Fund, Inc. | D96: 21373117843 | E96: 10337146 | F96: =D96-E96 -> 21362780697 | G96: 0 | H96: 22168 | I96: 353990 | J96: 354381193 | K96: =I96-J96 -> -354027203 | L96: =I96+Jan!L96 -> 705568 | M96: =J96+Jan!M96 -> 827969281 | N96: =L96-M96 -> -827263713
B97: =1+B96 -> 66 | C97: First Metro Save and Learn Money Market Fund, Inc. | D97: 2556977968 | E97: 6929410 | F97: =D97-E97 -> 2550048558 | G97: 0 | H97: 1217 | I97: 45315353 | J97: 66896008 | K97: =I97-J97 -> -21580655 | L97: =I97+Jan!L97 -> 174696127 | M97: =J97+Jan!M97 -> 392718975 | N97: =L97-M97 -> -218022848
B98: =1+B97 -> 67 | C98: Sun Life Prosperity Peso Starter Fund, Inc. | D98: 12472363539 | E98: 72278629 | F98: =D98-E98 -> 12400084910 | G98: 0 | H98: 73291 | I98: 170467860 | J98: 334151491 | K98: =I98-J98 -> -163683631 | L98: =I98+Jan!L98 -> 960748452 | M98: =J98+Jan!M98 -> 1024927739 | N98: =L98-M98 -> -64179287
A99: Primarily invested in Peso Securities (units)
B100: =1+B98 -> 68 | C100: ALFM Money Market Fund, Inc. | D100: 11561509374 | E100: 5969773 | F100: =D100-E100 -> 11555539601 | G100: 0 | H100: 26474 | I100: 756886453 | J100: 536113649 | K100: =I100-J100 -> 220772804 | L100: =I100+Jan!L100 -> 1480488549 | M100: =J100+Jan!M100 -> 1400458681 | N100: =L100-M100 -> 80029868
A101: Sub total - Peso Currency | D101: =SUM(D95:D98)+D100 -> 48135797535 | E101: =SUM(E95:E98)+E100 -> 95785641 | F101: =SUM(F95:F98)+F100 -> 48040011895 | G101: =SUM(G95:G98)+G100 -> 0 | H101: =SUM(H95:H98)+H100 -> 123219 | I101: =SUM(I95:I98)+I100 -> 973749656 | J101: =SUM(J95:J98)+J100 -> 1291542341 | K101: =SUM(K95:K98)+K100 -> -317792685 | ... N101: =SUM(N95:N98)+N100 -> -1028644980
A102: Primarily invested in foreign currency securities (shares)
B103: =1+B100 -> 69 | C103: Sun Life Prosperity Dollar Starter Fund, Inc. | D103: 2383931932 | E103: 4788671 | F103: =D103-E103 -> 2379143261 | G103: 0 | H103: 3821 | I103: 215251222 | J103: 59621792 | K103: =I103-J103 -> 155629430 | L103: =I103+Jan!L103 -> 359393258 | M103: =J103+Jan!M103 -> 329130606 | N103: =L103-M103 -> 30262652
A104: Sub total - US Currency | D104: =SUM(D103) -> 2383931932 | E104: =SUM(E103) -> 4788671 | F104: =SUM(F103) -> 2379143261 | G104: =SUM(G103) -> 0 | H104: =SUM(H103) -> 3821 | I104: =SUM(I103) -> 215251222 | J104: =SUM(J103) -> 59621792 | K104: =SUM(K103) -> 155629430 | ... N104: =SUM(N103) -> 30262652
A105: Sub total - money market funds | D105: =D101+D104 -> 50519729467 | E105: =E101+E104 -> 1.0057431e+08 | F105: =F101+F104 -> 50419155156 | G105: =G101+G104 -> 0 | H105: =H101+H104 -> 127040 | I105: =I101+I104 -> 1189000878 | J105: =J101+J104 -> 1351164133 | K105: =K101+K104 -> -162163255 | ... N105: =N101+N104 -> -998382328
...

Sheet Mar
A1: PHILIPPINE INVESTMENT FUNDS ASSOCIATION, INC.
A2: MUTUAL FUNDS STATISTICAL REPORT
A3: Month of March 2025
A4: (Amounts in Peso)
I5: F O R - T H E - M O N T H | L5: Y E A R - T O - D A T E
A6: Fund Category | C6: Fund Name | D6: ASSETS | E6: LIABILITIES | F6: NET ASSETS | G6: EQUITY INV. | H6: NO. OF A/C | I6: SALES | J6: REDEMPTIONS | K6: NET SALES | L6: TOTAL SALES | M6: TOTAL REDEMPTIONS | N6: TOTAL NET SALES
A7: Stock Funds
A8: Primarily invested in Peso Securities (shares)
B9: 1 | C9: ALFM Growth Fund, Inc. | D9: 3727680401 | E9: 16586059 | F9: =D9-E9 -> 3711094342 | G9: 3610766587 | H9: 5787 | I9: 3895709 | J9: 38893467 | K9: =I9-J9 -> -34997758 | L9: =I9+Feb!L9 -> 23921065 | M9: =J9+Feb!M9 -> 93648240 | N9: =L9-M9 -> -69727175
B10: =1+B9 -> 2 | C10: ATRAM Alpha Opportunity Fund, Inc. | D10: 9.9423617e+08 | E10: 5881151.8 | F10: =D10-E10 -> 9.8835502e+08 | G10: 9.0877886e+08 | H10: 4153 | I10: 19453917 | J10: 13827556 | K10: =I10-J10 -> 5626361.1 | L10: =I10+Feb!L10 -> 61754874 | M10: =J10+Feb!M10 -> 37824902 | N10: =L10-M10 -> 23929972
B11: =1+B10 -> 3 | C11: ATRAM Phil. Equity Opportunity Fund, Inc. | D11: 1.0518217e+09 | E11: 5938330.4 | F11: =D11-E11 -> 1045883409 | G11: 9.6679502e+08 | H11: 2475 | I11: 3871055.5 | J11: 16375873 | K11: =I11-J11 -> -12504818 | L11: =I11+Feb!L11 -> 16646336 | M11: =J11+Feb!M11 -> 29317981 | N11: =L11-M11 -> -12671646
B12: =1+B11 -> 4 | C12: Climbs Share Capital Equity Investment Fund Corp. | D12: 4.3695162e+08 | E12: 11777166 | F12: =D12-E12 -> 4.2517445e+08 | G12: 3.7292096e+08 | H12: 1714 | I12: 19950320 | J12: 744807.26 | K12: =I12-J12 -> 19205513 | L12: =I12+Feb!L12 -> 41032623 | M12: =J12+Feb!M12 -> 1720904.9 | N12: =L12-M12 -> 39311718
B13: =1+B12 -> 5 | C13: First Metro Consumer Fund, Inc. | D13: 344433276 | E13: 863871 | F13: =D13-E13 -> 343569405 | G13: 292407742 | H13: 1147 | I13: 232895 | J13: 1582188 | K13: =I13-J13 -> -1349293 | L13: =I13+Feb!L13 -> 794954 | M13: =J13+Feb!M13 -> 9096934 | N13: =L13-M13 -> -8301980
B14: =1+B13 -> 6 | C14: First Metro Save and Learn Equity Fund, Inc. | D14: 3089753006 | E14: 76002487 | F14: =D14-E14 -> 3013750519 | G14: 2727444004 | H14: 14342 | I14: 4949273 | J14: 23436077 | K14: =I14-J14 -> -18486804 | L14: =I14+Feb!L14 -> 40934592 | M14: =J14+Feb!M14 -> 122115264 | N14: =L14-M14 -> -81180672
B15: =1+B14 -> 7 | C15: First Metro Save and Learn Phil. Index Fund, Inc. | D15: 89427281 | E15: 351878 | F15: =D15-E15 -> 89075403 | G15: 83341085 | H15: 477 | I15: 1471042 | J15: 207686 | K15: =I15-J15 -> 1263356 | L15: =I15+Feb!L15 -> 7236629 | M15: =J15+Feb!M15 -> 1080702 | N15: =L15-M15 -> 6155927
B16: =1+B15 -> 8 | C16: MBG Equity Investment Fund, Inc. | D16: 115693364 | E16: 1384500 | F16: =D16-E16 -> 114308864 | G16: 110977560 | H16: 42 | I16: 0 | J16: 4270929 | K16: =I16-J16 -> -4270929 | L16: =I16+Feb!L16 -> 0 | M16: =J16+Feb!M16 -> 4270929 | N16: =L16-M16 -> -4270929
B17: =1+B16 -> 9 | C17: PAMI Equity Index Fund, Inc. | D17: 1019368785 | E17: 26321603 | F17: =D17-E17 -> 993047182 | G17: 1000248093 | H17: 10954 | I17: 0 | J17: 6430162 | K17: =I17-J17 -> -6430162 | L17: =I17+Feb!L17 -> 0 | M17: =J17+Feb!M17 -> 20508556 | N17: =L17-M17 -> -20508556
B18: =1+B17 -> 10 | C18: Philam Strategic Growth Fund, Inc. | D18: 3094232781 | E18: 22477588 | F18: =D18-E18 -> 3071755193 | G18: 3004745015 | H18: 10693 | I18: 6119251 | J18: 29665773 | K18: =I18-J18 -> -23546522 | L18: =I18+Feb!L18 -> 19633671 | M18: =J18+Feb!M18 -> 84434613 | N18: =L18-M18 -> -64800942
B19: =1+B18 -> 11 | C19: Philequity Dividend Yield Fund, Inc. | D19: 2.5359326e+09 | E19: 6843692.3 | F19: =D19-E19 -> 2529088882 | G19: 2.2821337e+09 | H19: 4988 | I19: 31989924 | J19: 38421353 | K19: =I19-J19 -> -6431428.4 | L19: =I19+Feb!L19 -> 48247099 | M19: =J19+Feb!M19 -> 45672090 | N19: =L19-M19 -> 2575009.4
B20: =1+B19 -> 12 | C20: Philequity Fund, Inc. | D20: 8.8235385e+09 | E20: 36790936 | F20: =D20-E20 -> 8786747587 | G20: 8.2239539e+09 | H20: 31681 | I20: 74305031 | J20: 1.267538e+08 | K20: =I20-J20 -> -52448769 | L20: =I20+Feb!L20 -> 91056483 | M20: =J20+Feb!M20 -> 1.7821858e+08 | N20: =L20-M20 -> -87162094
B21: =1+B20 -> 13 | C21: Philequity MSCI Phil. Index Fund, Inc. | D21: 3.0726806e+08 | E21: 487370.37 | F21: =D21-E21 -> 3.0678069e+08 | G21: 3.0049202e+08 | H21: 880 | I21: 275121.22 | J21: 266085.37 | K21: =I21-J21 -> 9035.85 | L21: =I21+Feb!L21 -> 1085849.7 | M21: =J21+Feb!M21 -> 550060.98 | N21: =L21-M21 -> 535788.75
... B27: =1+B26 -> 19 | C27: United Fund, Inc. | D27: 5.3042687e+08 | E27: 13536163 | F27: =D27-E27 -> 516890704 | G27: 4.6848837e+08 | H27: 1194 | I27: 206949.78 | J27: 2849276.1 | K27: =I27-J27 -> -2642326.3 | L27: =I27+Feb!L27 -> 1079302.5 | M27: =J27+Feb!M27 -> 3082993.2 | N27: =L27-M27 -> -2003690.8
A28: Primarily invested in Peso Securities (units) | L28: =I28+Feb!L28 -> 0 | M28: =J28+Feb!M28 -> 0
B29: =1+B27 -> 20 | C29: COL Equity Index Unitized Mutual Fund, Inc. | D29: 2.4543406e+08 | E29: 864167.18 | F29: =D29-E29 -> 2.445699e+08 | G29: 2.3410723e+08 | H29: 4662 | I29: 18132360 | J29: 2549403.9 | K29: =I29-J29 -> 15582956 | L29: =I29+Feb!L29 -> 39465956 | M29: =J29+Feb!M29 -> 15032562 | N29: =L29-M29 -> 24433394
B30: =1+B29 -> 21 | C30: COL Strategic Growth Equity Unitized Mutual Fund, Inc. | D30: 3.9447779e+08 | E30: 1349185 | F30: =D30-E30 -> 3.931286e+08 | G30: 326519805 | H30: 6215 | I30: 7932697.3 | J30: 16842612 | K30: =I30-J30 -> -8909914.5 | L30: =I30+Feb!L30 -> 43936603 | M30: =J30+Feb!M30 -> 29293398 | N30: =L30-M30 -> 14643204
B31: =1+B30 -> 22 | C31: Philequity Alpha One Fund, Inc. | D31: 2.6046398e+08 | E31: 2099576.2 | F31: =D31-E31 -> 2.583644e+08 | G31: 254967084 | H31: 1136 | I31: 219446.22 | J31: 217179.09 | K31: =I31-J31 -> 2267.13 | L31: =I31+Feb!L31 -> 2960185 | M31: =J31+Feb!M31 -> 12614178 | N31: =L31-M31 -> -9653992.9
B32: =1+B31 -> 23 | C32: Philippine Stock Index Fund Corp. | D32: 705683012 | E32: 8613527 | F32: =D32-E32 -> 697069485 | G32: 688515295 | H32: 760660 | I32: 12965953 | J32: 8335050 | K32: =I32-J32 -> 4630903 | L32: =I32+Feb!L32 -> 118944271 | M32: =J32+Feb!M32 -> 87638342 | N32: =L32-M32 -> 31305929
A33: Exchange Traded Fund | L33: =I33+Feb!L33 -> 0 | M33: =J33+Feb!M33 -> 0
B34: =1+B32 -> 24 | C34: First Metro Phil. Equity Exchange Traded Fund, Inc. | D34: 1371676029 | E34: 1307345 | F34: =D34-E34 -> 1370368684 | G34: 1355032660 | H34: 3288 | I34: 0 | J34: 0 | K34: =I34-J34 -> 0 | L34: =I34+Feb!L34 -> 40232388 | M34: =J34+Feb!M34 -> 0 | N34: =L34-M34 -> 40232388
A35: Sub total - Peso Currency | D35: =SUM(D9:D34) -> 56029683910 | E35: =SUM(E9:E34) -> 3.7989204e+08 | F35: =SUM(F9:F34) -> 55649791867 | G35: =SUM(G9:G34) -> 53445377699 | H35: =SUM(H9:H34) -> 1039385 | I35: =SUM(I9:I34) -> 2.7130564e+08 | J35: =SUM(J9:J34) -> 7.1958525e+08 | K35: =SUM(K9:K34) -> -4.4827961e+08 | ... N35: =SUM(N9:N34) -> -7.8460089e+08
A36: Primarily invested in foreign currency securities (shares)
B37: =1+B34 -> 25 | C37: ATRAM AsiaPlus Equity Fund, Inc. | D37: 27486376 | E37: 260731.71 | F37: =D37-E37 -> 27225644 | G37: 0 | H37: 50 | I37: 0 | J37: 28531.77 | K37: =I37-J37 -> -28531.77 | L37: =I37+Feb!L37 -> 104642.2 | M37: =J37+Feb!M37 -> 153134.87 | N37: =L37-M37 -> -48492.67
B38: =1+B37 -> 26 | C38: Sun Life Prosperity World Voyager Fund, Inc. | D38: 1756788232 | E38: 32256146 | F38: =D38-E38 -> 1724532086 | G38: 0 | H38: 3216 | I38: 16360241 | J38: 215287917 | K38: =I38-J38 -> -198927676 | L38: =I38+Feb!L38 -> 87592931 | M38: =J38+Feb!M38 -> 297298701 | N38: =L38-M38 -> -209705770
A39: Sub total - US Currency | D39: =SUM(D37:D38) -> 1784274608 | E39: =SUM(E37:E38) -> 32516878 | F39: =SUM(F37:F38) -> 1751757730 | G39: =SUM(G37:G38) -> 0 | H39: =SUM(H37:H38) -> 3266 | I39: =SUM(I37:I38) -> 16360241 | J39: =SUM(J37:J38) -> 2.1531645e+08 | K39: =SUM(K37:K38) -> -1.9895621e+08 | ... N39: =SUM(N37:N38) -> -2.0975426e+08
A40: Sub total - stock funds | D40: =D35+D39 -> 57813958518 | E40: =E35+E39 -> 4.1240892e+08 | F40: =F35+F39 -> 57401549597 | G40: =G35+G39 -> 53445377699 | H40: =H35+H39 -> 1042651 | I40: =I35+I39 -> 2.8766588e+08 | J40: =J35+J39 -> 9.349017e+08 | K40: =K35+K39 -> -6.4723582e+08 | ... N40: =N35+N39 -> -9.9435515e+08
A41: Balanced Funds
A42: Primarily invested in Peso Securities (shares)
B43: =1+B38 -> 27 | C43: ATRAM Philippine Balanced Fund, Inc. | D43: 4.5410321e+08 | E43: 54254241 | F43: =D43-E43 -> 3.9984897e+08 | G43: 210736819 | H43: 2316 | I43: 716009.53 | J43: 1378680.6 | K43: =I43-J43 -> -662671.11 | L43: =I43+Feb!L43 -> 1623332.6 | M43: =J43+Feb!M43 -> 18184513 | N43: =L43-M43 -> -16561181
B44: =1+B43 -> 28 | C44: ATRAM Unicapital Diversified Growth Fund, Inc. | D44: 1.161206e+08 | E44: 4693809.3 | F44: =D44-E44 -> 1.1142679e+08 | G44: 25667204 | H44: 811 | I44: 284574.8 | J44: 507627.26 | K44: =I44-J44 -> -223052.46 | L44: =I44+Feb!L44 -> 943427.2 | M44: =J44+Feb!M44 -> 1379997.9 | N44: =L44-M44 -> -436570.65
B45: =1+B44 -> 29 | C45: First Metro Save and Learn Balanced Fund, Inc. | D45: 652137686 | E45: 12621540 | F45: =D45-E45 -> 639516146 | G45: 291800977 | H45: 4073 | I45: 565535 | J45: 5023185 | K45: =I45-J45 -> -4457650 | L45: =I45+Feb!L45 -> 2362845 | M45: =J45+Feb!M45 -> 15534109 | N45: =L45-M45 -> -13171264
B46: =1+B45 -> 30 | C46: First Metro Save and Learn F.O.C.C.U.S. Dynamic Fund, Inc. | D46: 355367464 | E46: 4478580 | F46: =D46-E46 -> 350888884 | G46: 246454009 | H46: 366 | I46: 1596875 | J46: 98630792 | K46: =I46-J46 -> -97033917 | L46: =I46+Feb!L46 -> 7075076 | M46: =J46+Feb!M46 -> 131374204 | N46: =L46-M46 -> -124299128
B47: =1+B46 -> 31 | C47: NCM Mutual Fund of the Phils., Inc. | D47: 3.1386964e+08 | E47: 1014514.4 | F47: =D47-E47 -> 3.1285512e+08 | G47: 1.5092638e+08 | H47: 46 | I47: 0 | J47: 984000 | K47: =I47-J47 -> -984000 | L47: =I47+Feb!L47 -> 122503445 | M47: =J47+Feb!M47 -> 123701300 | N47: =L47-M47 -> -1197855
B48: =1+B47 -> 32 | C48: PAMI Horizon Fund, Inc. | D48: 441465506 | E48: 14171677 | F48: =D48-E48 -> 427293829 | G48: 213307123 | H48: 9611 | I48: 58303 | J48: 13444723 | K48: =I48-J48 -> -13386420 | L48: =I48+Feb!L48 -> 118479 | M48: =J48+Feb!M48 -> 18039673 | N48: =L48-M48 -> -17921194
B49: =1+B48 -> 33 | C49: Philam Fund, Inc. | D49: 1818549891 | E49: 21662067 | F49: =D49-E49 -> 1796887824 | G49: 880548703 | H49: 7201 | I49: 438438 | J49: 29365728 | K49: =I49-J49 -> -28927290 | L49: =I49+Feb!L49 -> 1288051 | M49: =J49+Feb!M49 -> 55012556 | N49: =L49-M49 -> -53724505
B50: =1+B49 -> 34 | C50: Solidaritas Fund, Inc. | D50: 119583839 | E50: 311579 | F50: =D50-E50 -> 119272260 | G50: 56561225 | H50: 158 | I50: 0 | J50: 0 | K50: =I50-J50 -> 0 | L50: =I50+Feb!L50 -> 0 | M50: =J50+Feb!M50 -> 1672556 | N50: =L50-M50 -> -1672556
B51: =1+B50 -> 35 | C51: Sun Life Prosperity Balanced Fund, Inc. | D51: 5778277025 | E51: 46002830 | F51: =D51-E51 -> 5732274195 | G51: 2880626160 | H51: 54678 | I51: 5014510 | J51: 82540554 | K51: =I51-J51 -> -77526044 | L51: =I51+Feb!L51 -> 17544554 | M51: =J51+Feb!M51 -> 175967224 | N51: =L51-M51 -> -158422670
B52: =1+B51 -> 36 | C52: Sun Life Prosperity Dynamic Fund, Inc. | D52: 463480315 | E52: 2768491 | F52: =D52-E52 -> 460711824 | G52: 246053794 | H52: 5000 | I52: 0 | J52: 3471330 | K52: =I52-J52 -> -3471330 | L52: =I52+Feb!L52 -> 0 | M52: =J52+Feb!M52 -> 24502082 | N52: =L52-M52 -> -24502082
A53: Primarily invested in Peso Securities (units)
B54: =1+B52 -> 37 | C54: Sun Life Prosperity Achiever Fund 2028, Inc. | D54: 76160330 | E54: 377997 | F54: =D54-E54 -> 75782333 | G54: 15367322 | H54: 1258 | I54: 183009 | J54: 306104 | K54: =I54-J54 -> -123095 | L54: =I54+Feb!L54 -> 628033 | M54: =J54+Feb!M54 -> 1212813 | N54: =L54-M54 -> -584780
B55: =1+B54 -> 38 | C55: Sun Life Prosperity Achiever Fund 2038, Inc. | D55: 55431053 | E55: 313246 | F55: =D55-E55 -> 55117807 | G55: 38564326 | H55: 511 | I55: 156298 | J55: 0 | K55: =I55-J55 -> 156298 | L55: =I55+Feb!L55 -> 304941 | M55: =J55+Feb!M55 -> 186630 | N55: =L55-M55 -> 118311
B56: =1+B55 -> 39 | C56: Sun Life Prosperity Achiever Fund 2048, Inc. | D56: 46519580 | E56: 298330 | F56: =D56-E56 -> 46221250 | G56: 37563583 | H56: 247 | I56: 38024 | J56: 57797 | K56: =I56-J56 -> -19773 | L56: =I56+Feb!L56 -> 205385 | M56: =J56+Feb!M56 -> 102227 | N56: =L56-M56 -> 103158
A57: Sub total - Peso Currency | D57: =SUM(D43:D56) -> 10691066132 | E57: =SUM(E42:E56) -> 1.629689e+08 | F57: =SUM(F43:F56) -> 10528097230 | G57: =SUM(G43:G56) -> 5294177625 | H57: =SUM(H43:H56) -> 86276 | I57: =SUM(I42:I56) -> 9051576.3 | J57: =SUM(J43:J56) -> 2.3571052e+08 | K57: =SUM(K43:K56) -> -2.2665894e+08 | L57: =SUM(L43:L56) -> 1.5459757e+08 | M57: =SUM(M43:M56) -> 5.6686989e+08 | N57: =SUM(N43:N56) -> -4.1227232e+08
A58: Primarily invested in foreign currency securities (shares)
B59: =1+B56 -> 40 | C59: Cocolife Dollar Fund Builder, Inc. | D59: 62422169 | E59: 474661.64 | F59: =D59-E59 -> 61947507 | G59: 0 | H59: 48 | I59: 0 | J59: 57425.68 | K59: =I59-J59 -> -57425.68 | L59: =I59+Feb!L59 -> 0 | M59: =J59+Feb!M59 -> 207807.29 | N59: =L59-M59 -> -207807.29
B60: =1+B59 -> 41 | C60: PAMI Asia Balanced Fund, Inc. | D60: 302450503 | E60: 18783003 | F60: =D60-E60 -> 283667500 | G60: 155708323 | H60: 210 | I60: 0 | J60: 17230182 | K60: =I60-J60 -> -17230182 | L60: =I60+Feb!L60 -> 0 | M60: =J60+Feb!M60 -> 21099697 | N60: =L60-M60 -> -21099697
B61: =1+B60 -> 42 | C61: Sun Life Prosperity Dollar Advantage Fund, Inc. | D61: 1587489506 | E61: 9128957 | F61: =D61-E61 -> 1578360549 | G61: 0 | H61: 4289 | I61: 16008526 | J61: 31673105 | K61: =I61-J61 -> -15664579 | L61: =I61+Feb!L61 -> 20552846 | M61: =J61+Feb!M61 -> 81403794 | N61: =L61-M61 -> -60850948
B62: =1+B61 -> 43 | C62: Sun Life Prosperity Dollar Wellspring Fund, Inc. | D62: 241905243 | E62: 657951 | F62: =D62-E62 -> 241247292 | G62: 0 | H62: 772 | I62: 4468816 | J62: 3643411 | K62: =I62-J62 -> 825405 | L62: =I62+Feb!L62 -> 4909633 | M62: =J62+Feb!M62 -> 5305727 | N62: =L62-M62 -> -396094
A63: Sub total - US Currency | D63: =SUM(D59:D62) -> 2194267421 | E63: =SUM(E59:E62) -> 29044573 | F63: =SUM(F59:F62) -> 2165222848 | G63: =SUM(G59:G62) -> 155708323 | H63: =SUM(H59:H62) -> 5319 | I63: =SUM(I59:I62) -> 20477342 | J63: =SUM(J59:J62) -> 52604124 | K63: =SUM(K59:K62) -> -32126782 | ... N63: =SUM(N59:N62) -> -82554546
A64: Sub total - balanced funds | D64: =D57+D63 -> 12885333553 | E64: =E57+E63 -> 1.9201347e+08 | F64: =F57+F63 -> 12693320078 | G64: =G57+G63 -> 5449885948 | H64: =H57+H63 -> 91595 | I64: =I57+I63 -> 29528918 | J64: =J57+J63 -> 2.8831464e+08 | K64: =K57+K63 -> -2.5878573e+08 | ... N64: =N57+N63 -> -4.9482686e+08
A65: Bond Funds
A66: Primarily invested in Peso Securities (shares)
B67: =1+B62 -> 44 | C67: ALFM Peso Bond Fund, Inc. | D67: 35011943452 | E67: 315721106 | F67: =D67-E67 -> 34696222346 | G67: 260000000 | H67: 24134 | I67: 182690214 | J67: 315697456 | K67: =I67-J67 -> -133007242 | L67: =I67+Feb!L67 -> 616529217 | M67: =J67+Feb!M67 -> 1067324450 | N67: =L67-M67 -> -450795233
B68: =1+B67 -> 45 | C68: ATRAM Corporate Bond Fund, Inc. | D68: 2.5925238e+08 | E68: 1530231.9 | F68: =D68-E68 -> 2.5772214e+08 | G68: 0 | H68: 928 | I68: 531794.82 | J68: 5285058.4 | K68: =I68-J68 -> -4753263.6 | L68: =I68+Feb!L68 -> 2250151.9 | M68: =J68+Feb!M68 -> 21419382 | N68: =L68-M68 -> -19169230
B69: =1+B68 -> 46 | C69: Cocolife Fixed Income Fund, Inc. | D69: 9.4259474e+08 | E69: 10505661 | F69: =D69-E69 -> 9.3208908e+08 | G69: 0 | H69: 1807 | I69: 1054031.6 | J69: 14062342 | K69: =I69-J69 -> -13008310 | L69: =I69+Feb!L69 -> 15208319 | M69: =J69+Feb!M69 -> 31450950 | N69: =L69-M69 -> -16242631
B70: =1+B69 -> 47 | C70: Ekklesia Mutual Fund, Inc. | D70: 188355784 | E70: 181220 | F70: =D70-E70 -> 188174564 | G70: 0 | H70: 134 | I70: 0 | J70: 367690 | K70: =I70-J70 -> -367690 | L70: =I70+Feb!L70 -> 4998 | M70: =J70+Feb!M70 -> 426661 | N70: =L70-M70 -> -421663
B71: =1+B70 -> 48 | C71: First Metro Save and Learn Fixed Income Fund, Inc. | D71: 1157782211 | E71: 14755902 | F71: =D71-E71 -> 1143026309 | G71: 0 | H71: 1727 | I71: 482410 | J71: 29552121 | K71: =I71-J71 -> -29069711 | L71: =I71+Feb!L71 -> 2000407 | M71: =J71+Feb!M71 -> 53912628 | N71: =L71-M71 -> -51912221
B72: =1+B71 -> 49 | C72: Philam Bond Fund, Inc. | D72: 1403284308 | E72: 31710405 | F72: =D72-E72 -> 1371573903 | G72: 0 | H72: 4548 | I72: 2673894 | J72: 28185079 | K72: =I72-J72 -> -25511185 | L72: =I72+Feb!L72 -> 5652943 | M72: =J72+Feb!M72 -> 45170819 | N72: =L72-M72 -> -39517876
B73: =1+B72 -> 50 | C73: Philam Managed Income Fund, Inc. | D73: 613334190 | E73: 9891727 | F73: =D73-E73 -> 603442463 | G73: 0 | H73: 399 | I73: 0 | J73: 3208515 | K73: =I73-J73 -> -3208515 | L73: =I73+Feb!L73 -> 0 | M73: =J73+Feb!M73 -> 20407108 | N73: =L73-M73 -> -20407108
B74: =1+B73 -> 51 | C74: Philequity Peso Bond Fund, Inc. | D74: 3.3492437e+08 | E74: 1322888.7 | F74: =D74-E74 -> 333601483 | G74: 0 | H74: 3948 | I74: 2584215.3 | J74: 1683005.7 | K74: =I74-J74 -> 901209.59 | L74: =I74+Feb!L74 -> 8272153.6 | M74: =J74+Feb!M74 -> 3785103.2 | N74: =L74-M74 -> 4487050.4
B75: =1+B74 -> 52 | C75: Soldivo Bond Fund, Inc. | D75: 1.8864493e+09 | E75: 3434138.3 | F75: =D75-E75 -> 1883015190 | G75: 0 | H75: 781 | I75: 50119148 | J75: 331463.09 | K75: =I75-J75 -> 49787685 | L75: =I75+Feb!L75 -> 77712609 | M75: =J75+Feb!M75 -> 5565167 | N75: =L75-M75 -> 72147442
B76: =1+B75 -> 53 | C76: Sun Life Prosperity Bond Fund, Inc. | D76: 6457659157 | E76: 25379690 | F76: =D76-E76 -> 6432279467 | G76: 0 | H76: 19389 | I76: 70643479 | J76: 63731558 | K76: =I76-J76 -> 6911921 | L76: =I76+Feb!L76 -> 179914337 | M76: =J76+Feb!M76 -> 332806134 | N76: =L76-M76 -> -152891797
B77: =1+B76 -> 54 | C77: Sun Life Prosperity GS Fund, Inc. | D77: 145871845 | E77: 429561 | F77: =D77-E77 -> 145442284 | G77: 0 | H77: 2904 | I77: 991818 | J77: 560261 | K77: =I77-J77 -> 431557 | L77: =I77+Feb!L77 -> 2366258 | M77: =J77+Feb!M77 -> 8275016 | N77: =L77-M77 -> -5908758
A78: Corporate Debt Vehicle (units)
B79: =1+B77 -> 55 | C79: ATRAM Unitized Corporate Debt Vehicle, Inc. | D79: 7.0947451e+08 | E79: 2353242.3 | F79: =D79-E79 -> 7.0712127e+08 | G79: 0 | H79: 13 | I79: 0 | J79: 0 | K79: =I79-J79 -> 0 | L79: =I79+Feb!L79 -> 0 | M79: =J79+Feb!M79 -> 0 | N79: =L79-M79 -> 0
A80: Sub total - Peso Currency | D80: =SUM(D67:D79) -> 49110926276 | E80: =SUM(E67:E79) -> 4.1721577e+08 | F80: =SUM(F67:F79) -> 48693710503 | G80: =SUM(G67:G79) -> 260000000 | H80: =SUM(H67:H79) -> 60712 | I80: =SUM(I67:I79) -> 3.1177101e+08 | J80: =SUM(J67:J79) -> 4.6266455e+08 | K80: =SUM(K67:K79) -> -1.5089354e+08 | ... N80: =SUM(N67:N79) -> -680632024
A81: Primarily invested in foreign currency securities (shares)
B82: =1+B79 -> 56 | C82: ALFM Dollar Bond Fund, Inc. | D82: 11888326265 | E82: 363840025 | F82: =D82-E82 -> 11524486240 | G82: 0 | H82: 7227 | I82: 24760602 | J82: 106568499 | K82: =I82-J82 -> -81807897 | L82: =I82+Feb!L82 -> 84041745 | M82: =J82+Feb!M82 -> 302572746 | N82: =L82-M82 -> -218531001
B83: =1+B82 -> 57 | C83: ATRAM Total Return Dollar Bond Fund, Inc. | D83: 1.3732471e+08 | E83: 24998404 | F83: =D83-E83 -> 1.1232631e+08 | G83: 0 | H83: 72 | I83: 18590524 | J83: 1121789.7 | K83: =I83-J83 -> 17468734 | L83: =I83+Feb!L83 -> 18590524 | M83: =J83+Feb!M83 -> 2683522.4 | N83: =L83-M83 -> 15907002
B84: =1+B83 -> 58 | C84: First Metro Save and Learn Dollar Bond Fund, Inc. | D84: 347939037 | E84: 30527926 | F84: =D84-E84 -> 317411111 | G84: 0 | H84: 160 | I84: 57289 | J84: 1489691 | K84: =I84-J84 -> -1432402 | L84: =I84+Feb!L84 -> 186598 | M84: =J84+Feb!M84 -> 2292229 | N84: =L84-M84 -> -2105631
B85: =1+B84 -> 59 | C85: PAMI Global Bond Fund, Inc. | D85: 67431124 | E85: 16227836 | F85: =D85-E85 -> 51203288 | G85: 0 | H85: 24 | I85: 0 | J85: 0 | K85: =I85-J85 -> 0 | L85: =I85+Feb!L85 -> 0 | M85: =J85+Feb!M85 -> 0 | N85: =L85-M85 -> 0
B86: =1+B85 -> 60 | C86: Philam Dollar Bond Fund, Inc. | D86: 1643599522 | E86: 10902682 | F86: =D86-E86 -> 1632696840 | G86: 0 | H86: 1579 | I86: 101948 | J86: 23885287 | K86: =I86-J86 -> -23783339 | L86: =I86+Feb!L86 -> 159620 | M86: =J86+Feb!M86 -> 62750664 | N86: =L86-M86 -> -62591044
B87: =1+B86 -> 61 | C87: Philequity Dollar Income Fund, Inc. | D87: 2.2673422e+08 | E87: 1310923.3 | F87: =D87-E87 -> 225423299 | G87: 0 | H87: 96 | I87: 200235 | J87: 0 | K87: =I87-J87 -> 200235 | L87: =I87+Feb!L87 -> 397566 | M87: =J87+Feb!M87 -> 0 | N87: =L87-M87 -> 397566
B88: =1+B87 -> 62 | C88: Sun Life Prosperity Dollar Abundance Fund, Inc. | D88: 497456656 | E88: 27491398 | F88: =D88-E88 -> 469965258 | G88: 0 | H88: 2648 | I88: 114420 | J88: 6249374 | K88: =I88-J88 -> -6134954 | L88: =I88+Feb!L88 -> 3204266 | M88: =J88+Feb!M88 -> 27545895 | N88: =L88-M88 -> -24341629
A89: Sub total - US Currency | D89: =SUM(D82:D88) -> 14808811540 | E89: =SUM(E82:E88) -> 4.7529919e+08 | F89: =SUM(F82:F88) -> 14333512345 | G89: =SUM(G82:G88) -> 0 | H89: =SUM(H82:H88) -> 11806 | I89: =SUM(I82:I88) -> 43825018 | J89: =SUM(J82:J88) -> 1.3931464e+08 | K89: =SUM(K82:K88) -> -95489623 | ... N89: =SUM(N82:N88) -> -2.9126474e+08
B90: =1+B88 -> 63 | C90: ALFM Euro Bond Fund, Inc. | D90: 716100749 | E90: 4813605 | F90: =D90-E90 -> 711287144 | G90: 0 | H90: 572 | I90: 3194049 | J90: 12332908 | K90: =I90-J90 -> -9138859 | L90: =I90+Feb!L90 -> 18427084 | M90: =J90+Feb!M90 -> 23956912 | N90: =L90-M90 -> -5529828
A91: Sub total - Euro Currency | D91: =SUM(D90) -> 716100749 | E91: =SUM(E90) -> 4813605 | F91: =SUM(F90) -> 711287144 | G91: =SUM(G90) -> 0 | H91: =SUM(H90) -> 572 | I91: =SUM(I90) -> 3194049 | J91: =SUM(J90) -> 12332908 | K91: =SUM(K90) -> -9138859 | ... N91: =SUM(N90) -> -5529828
A92: Sub total - bond funds | D92: =D80+D89+D91 -> 64635838565 | E92: =E80+E89+E91 -> 8.9732857e+08 | F92: =F80+F89+F91 -> 63738509992 | G92: =G80+G89+G91 -> 260000000 | H92: =H80+H89+H91 -> 73090 | I92: =I80+I89+I91 -> 3.5879007e+08 | J92: =J80+J89+J91 -> 6.143121e+08 | K92: =K80+K89+K91 -> -255522026 | ... N92: =N80+N89+N91 -> -9.7742659e+08
A93: Money Market Funds
A94: Primarily invested in Peso Securities (shares)
B95: 64 | C95: AIB Money Market Mutual Fund, Inc. | D95: 1.7239219e+08 | E95: 291417.38 | F95: =D95-E95 -> 1.7210077e+08 | G95: 0 | H95: 73 | I95: 131000 | J95: 80394.93 | K95: =I95-J95 -> 50605.07 | L95: =I95+Feb!L95 -> 922000 | M95: =J95+Feb!M95 -> 80394.93 | N95: =L95-M95 -> 841605.07
B96: 65 | C96: ALFM Money Market Fund, Inc. | D96: 21722533721 | E96: 564324251 | F96: =D96-E96 -> 21158209470 | G96: 0 | H96: 21966 | I96: 321013 | J96: 282272705 | K96: =I96-J96 -> -281951692 | L96: =I96+Feb!L96 -> 1026581 | M96: =J96+Feb!M96 -> 1110241986 | N96: =L96-M96 -> -1109215405
B97: =1+B96 -> 66 | C97: First Metro Save and Learn Money Market Fund, Inc. | D97: 2569051527 | E97: 25930703 | F97: =D97-E97 -> 2543120824 | G97: 0 | H97: 1179 | I97: 68989395 | J97: 86975012 | K97: =I97-J97 -> -17985617 | L97: =I97+Feb!L97 -> 243685522 | M97: =J97+Feb!M97 -> 479693987 | N97: =L97-M97 -> -236008465
B98: =1+B97 -> 67 | C98: Sun Life Prosperity Peso Starter Fund, Inc. | D98: 13067107895 | E98: 639453089 | F98: =D98-E98 -> 12427654806 | G98: 0 | H98: 73474 | I98: 609974547 | J98: 621449569 | K98: =I98-J98 -> -11475022 | L98: =I98+Feb!L98 -> 1570722999 | M98: =J98+Feb!M98 -> 1646377308 | N98: =L98-M98 -> -75654309
A99: Primarily invested in Peso Securities (units)
B100: =1+B98 -> 68 | C100: ALFM Money Market Fund, Inc. | D100: 11881390234 | E100: 307498510 | F100: =D100-E100 -> 11573891724 | G100: 0 | H100: 27113 | I100: 835811931 | J100: 859984068 | K100: =I100-J100 -> -24172137 | L100: =I100+Feb!L100 -> 2316300480 | M100: =J100+Feb!M100 -> 2260442749 | N100: =L100-M100 -> 55857731
A101: Sub total - Peso Currency | D101: =SUM(D95:D98)+D100 -> 49412475564 | E101: =SUM(E95:E98)+E100 -> 1537497970 | F101: =SUM(F95:F98)+F100 -> 47874977594 | G101: =SUM(G95:G98)+G100 -> 0 | H101: =SUM(H95:H98)+H100 -> 123805 | I101: =SUM(I95:I98)+I100 -> 1515227886 | J101: =SUM(J95:J98)+J100 -> 1850761749 | K101: =SUM(K95:K98)+K100 -> -3.3553386e+08 | ... N101: =SUM(N95:N98)+N100 -> -1364178843
A102: Primarily invested in foreign currency securities (shares)
B103: =1+B100 -> 69 | C103: Sun Life Prosperity Dollar Starter Fund, Inc. | D103: 2533421448 | E103: 22147457 | F103: =D103-E103 -> 2511273991 | G103: 0 | H103: 3848 | I103: 309927025 | J103: 152225465 | K103: =I103-J103 -> 157701560 | L103: =I103+Feb!L103 -> 669320283 | M103: =J103+Feb!M103 -> 481356071 | N103: =L103-M103 -> 187964212
A104: Sub total - US Currency | D104: =SUM(D103) -> 2533421448 | E104: =SUM(E103) -> 22147457 | F104: =SUM(F103) -> 2511273991 | G104: =SUM(G103) -> 0 | H104: =SUM(H103) -> 3848 | I104: =SUM(I103) -> 309927025 | J104: =SUM(J103) -> 152225465 | K104: =SUM(K103) -> 157701560 | ... N104: =SUM(N103) -> 187964212
A105: Sub total - money market funds | D105: =D101+D104 -> 51945897012 | E105: =E101+E104 -> 1559645427 | F105: =F101+F104 -> 50386251585 | G105: =G101+G104 -> 0 | H105: =H101+H104 -> 127653 | I105: =I101+I104 -> 1825154911 | J105: =J101+J104 -> 2002987214 | K105: =K101+K104 -> -1.778323e+08 | ... N105: =N101+N104 -> -1176214631
...

Sheet Mar UPDATED
A1: PHILIPPINE INVESTMENT FUNDS ASSOCIATION, INC.
A2: MUTUAL FUNDS STATISTICAL REPORT
A3: Month of March 2025
A4: (Amounts in Peso)
I5: F O R - T H E - M O N T H | L5: Y E A R - T O - D A T E
A6: Fund Category | C6: Fund Name | D6: ASSETS | E6: LIABILITIES | F6: NET ASSETS | G6: EQUITY INV. | H6: NO. OF A/C | I6: SALES | J6: REDEMPTIONS | K6: NET SALES | L6: TOTAL SALES | M6: TOTAL REDEMPTIONS | N6: TOTAL NET SALES
A7: Stock Funds
A8: Primarily invested in Peso Securities (shares)
B9: 1 | C9: ALFM Growth Fund, Inc. | D9: 3727680401 | E9: 16586059 | F9: =D9-E9 -> 3711094342 | G9: 3610766587 | H9: 5787 | I9: 3895709 | J9: 38893467 | K9: =I9-J9 -> -34997758 | L9: =I9+Feb!L9 -> 23921065 | M9: =J9+Feb!M9 -> 93648240 | N9: =L9-M9 -> -69727175
B10: =1+B9 -> 2 | C10: ATRAM Alpha Opportunity Fund, Inc. | D10: 9.9423617e+08 | E10: 5881151.8 | F10: =D10-E10 -> 9.8835502e+08 | G10: 9.0877886e+08 | H10: 4153 | I10: 19453917 | J10: 13827556 | K10: =I10-J10 -> 5626361.1 | L10: =I10+Feb!L10 -> 61754874 | M10: =J10+Feb!M10 -> 37824902 | N10: =L10-M10 -> 23929972
B11: =1+B10 -> 3 | C11: ATRAM Phil. Equity Opportunity Fund, Inc. | D11: 1.0518217e+09 | E11: 5938330.4 | F11: =D11-E11 -> 1045883409 | G11: 9.6679502e+08 | H11: 2475 | I11: 3871055.5 | J11: 16375873 | K11: =I11-J11 -> -12504818 | L11: =I11+Feb!L11 -> 16646336 | M11: =J11+Feb!M11 -> 29317981 | N11: =L11-M11 -> -12671646
B12: =1+B11 -> 4 | C12: Climbs Share Capital Equity Investment Fund Corp. | D12: 4.3695162e+08 | E12: 11777166 | F12: =D12-E12 -> 4.2517445e+08 | G12: 3.7292096e+08 | H12: 1714 | I12: 19950320 | J12: 744807.26 | K12: =I12-J12 -> 19205513 | L12: =I12+Feb!L12 -> 41032623 | M12: =J12+Feb!M12 -> 1720904.9 | N12: =L12-M12 -> 39311718
B13: =1+B12 -> 5 | C13: First Metro Consumer Fund, Inc. | D13: 344433276 | E13: 863871 | F13: =D13-E13 -> 343569405 | G13: 292407742 | H13: 1147 | I13: 232895 | J13: 1582188 | K13: =I13-J13 -> -1349293 | L13: =I13+Feb!L13 -> 794954 | M13: =J13+Feb!M13 -> 9096934 | N13: =L13-M13 -> -8301980
B14: =1+B13 -> 6 | C14: First Metro Save and Learn Equity Fund, Inc. | D14: 3089753006 | E14: 76002487 | F14: =D14-E14 -> 3013750519 | G14: 2727444004 | H14: 14342 | I14: 4949273 | J14: 23436077 | K14: =I14-J14 -> -18486804 | L14: =I14+Feb!L14 -> 40934592 | M14: =J14+Feb!M14 -> 122115264 | N14: =L14-M14 -> -81180672
B15: =1+B14 -> 7 | C15: First Metro Save and Learn Phil. Index Fund, Inc. | D15: 89427281 | E15: 351878 | F15: =D15-E15 -> 89075403 | G15: 83341085 | H15: 477 | I15: 1471042 | J15: 207686 | K15: =I15-J15 -> 1263356 | L15: =I15+Feb!L15 -> 7236629 | M15: =J15+Feb!M15 -> 1080702 | N15: =L15-M15 -> 6155927
B16: =1+B15 -> 8 | C16: MBG Equity Investment Fund, Inc. | D16: 115693364 | E16: 1384500 | F16: =D16-E16 -> 114308864 | G16: 110977560 | H16: 42 | I16: 0 | J16: 4270929 | K16: =I16-J16 -> -4270929 | L16: =I16+Feb!L16 -> 0 | M16: =J16+Feb!M16 -> 4270929 | N16: =L16-M16 -> -4270929
B17: =1+B16 -> 9 | C17: PAMI Equity Index Fund, Inc. | D17: 1019368785 | E17: 26321603 | F17: =D17-E17 -> 993047182 | G17: 1000248093 | H17: 10954 | I17: 0 | J17: 6430162 | K17: =I17-J17 -> -6430162 | L17: =I17+Feb!L17 -> 0 | M17: =J17+Feb!M17 -> 20508556 | N17: =L17-M17 -> -20508556
B18: =1+B17 -> 10 | C18: Philam Strategic Growth Fund, Inc. | D18: 3094232781 | E18: 22477588 | F18: =D18-E18 -> 3071755193 | G18: 3004745015 | H18: 10693 | I18: 6119251 | J18: 29665773 | K18: =I18-J18 -> -23546522 | L18: =I18+Feb!L18 -> 19633671 | M18: =J18+Feb!M18 -> 84434613 | N18: =L18-M18 -> -64800942
B19: =1+B18 -> 11 | C19: Philequity Dividend Yield Fund, Inc. | D19: 2.5359326e+09 | E19: 6843692.3 | F19: =D19-E19 -> 2529088882 | G19: 2.2821337e+09 | H19: 4988 | I19: 31989924 | J19: 38421353 | K19: =I19-J19 -> -6431428.4 | L19: =I19+Feb!L19 -> 48247099 | M19: =J19+Feb!M19 -> 45672090 | N19: =L19-M19 -> 2575009.4
B20: =1+B19 -> 12 | C20: Philequity Fund, Inc. | D20: 8.8235385e+09 | E20: 36790936 | F20: =D20-E20 -> 8786747587 | G20: 8.2239539e+09 | H20: 31681 | I20: 74305031 | J20: 1.267538e+08 | K20: =I20-J20 -> -52448769 | L20: =I20+Feb!L20 -> 91056483 | M20: =J20+Feb!M20 -> 1.7821858e+08 | N20: =L20-M20 -> -87162094
B21: =1+B20 -> 13 | C21: Philequity MSCI Phil. Index Fund, Inc. | D21: 3.0726806e+08 | E21: 487370.37 | F21: =D21-E21 -> 3.0678069e+08 | G21: 3.0049202e+08 | H21: 880 | I21: 275121.22 | J21: 266085.37 | K21: =I21-J21 -> 9035.85 | L21: =I21+Feb!L21 -> 1085849.7 | M21: =J21+Feb!M21 -> 550060.98 | N21: =L21-M21 -> 535788.75
... B27: =1+B26 -> 19 | C27: United Fund, Inc. | D27: 5.3042687e+08 | E27: 13536163 | F27: =D27-E27 -> 516890704 | G27: 4.6848837e+08 | H27: 1194 | I27: 206949.78 | J27: 2849276.1 | K27: =I27-J27 -> -2642326.3 | L27: =I27+Feb!L27 -> 1079302.5 | M27: =J27+Feb!M27 -> 3082993.2 | N27: =L27-M27 -> -2003690.8
A28: Primarily invested in Peso Securities (units) | L28: =I28+Feb!L28 -> 0 | M28: =J28+Feb!M28 -> 0
B29: =1+B27 -> 20 | C29: COL Equity Index Unitized Mutual Fund, Inc. | D29: 2.4543406e+08 | E29: 864167.18 | F29: =D29-E29 -> 2.445699e+08 | G29: 2.3410723e+08 | H29: 4662 | I29: 18132360 | J29: 2549403.9 | K29: =I29-J29 -> 15582956 | L29: =I29+Feb!L29 -> 39465956 | M29: =J29+Feb!M29 -> 15032562 | N29: =L29-M29 -> 24433394
B30: =1+B29 -> 21 | C30: COL Strategic Growth Equity Unitized Mutual Fund, Inc. | D30: 3.9447779e+08 | E30: 1349185 | F30: =D30-E30 -> 3.931286e+08 | G30: 326519805 | H30: 6215 | I30: 7932697.3 | J30: 16842612 | K30: =I30-J30 -> -8909914.5 | L30: =I30+Feb!L30 -> 43936603 | M30: =J30+Feb!M30 -> 29293398 | N30: =L30-M30 -> 14643204
B31: =1+B30 -> 22 | C31: Philequity Alpha One Fund, Inc. | D31: 2.6046398e+08 | E31: 2099576.2 | F31: =D31-E31 -> 2.583644e+08 | G31: 254967084 | H31: 1136 | I31: 219446.22 | J31: 217179.09 | K31: =I31-J31 -> 2267.13 | L31: =I31+Feb!L31 -> 2960185 | M31: =J31+Feb!M31 -> 12614178 | N31: =L31-M31 -> -9653992.9
B32: =1+B31 -> 23 | C32: Philippine Stock Index Fund Corp. | D32: 705683012 | E32: 8613527 | F32: =D32-E32 -> 697069485 | G32: 688515295 | H32: 760660 | I32: 12965953 | J32: 8335050 | K32: =I32-J32 -> 4630903 | L32: =I32+Feb!L32 -> 118944271 | M32: =J32+Feb!M32 -> 87638342 | N32: =L32-M32 -> 31305929
A33: Exchange Traded Fund | L33: =I33+Feb!L33 -> 0 | M33: =J33+Feb!M33 -> 0
B34: =1+B32 -> 24 | C34: First Metro Phil. Equity Exchange Traded Fund, Inc. | D34: 1371676029 | E34: 1307345 | F34: =D34-E34 -> 1370368684 | G34: 1355032660 | H34: 3288 | I34: 0 | J34: 0 | K34: =I34-J34 -> 0 | L34: =I34+Feb!L34 -> 40232388 | M34: =J34+Feb!M34 -> 0 | N34: =L34-M34 -> 40232388
A35: Sub total - Peso Currency | D35: =SUM(D9:D34) -> 56029683910 | E35: =SUM(E9:E34) -> 3.7989204e+08 | F35: =SUM(F9:F34) -> 55649791867 | G35: =SUM(G9:G34) -> 53445377699 | H35: =SUM(H9:H34) -> 1039385 | I35: =SUM(I9:I34) -> 2.7130564e+08 | J35: =SUM(J9:J34) -> 7.1958525e+08 | K35: =SUM(K9:K34) -> -4.4827961e+08 | ... N35: =SUM(N9:N34) -> -7.8460089e+08
A36: Primarily invested in foreign currency securities (shares)
B37: =1+B34 -> 25 | C37: ATRAM AsiaPlus Equity Fund, Inc. | D37: 27486376 | E37: 260731.71 | F37: =D37-E37 -> 27225644 | G37: 0 | H37: 50 | I37: 0 | J37: 28531.77 | K37: =I37-J37 -> -28531.77 | L37: =I37+Feb!L37 -> 104642.2 | M37: =J37+Feb!M37 -> 153134.87 | N37: =L37-M37 -> -48492.67
B38: =1+B37 -> 26 | C38: Sun Life Prosperity World Voyager Fund, Inc. | D38: 1756788232 | E38: 32256146 | F38: =D38-E38 -> 1724532086 | G38: 0 | H38: 3216 | I38: 16360241 | J38: 215287917 | K38: =I38-J38 -> -198927676 | L38: =I38+Feb!L38 -> 87592931 | M38: =J38+Feb!M38 -> 297298701 | N38: =L38-M38 -> -209705770
A39: Sub total - US Currency | D39: =SUM(D37:D38) -> 1784274608 | E39: =SUM(E37:E38) -> 32516878 | F39: =SUM(F37:F38) -> 1751757730 | G39: =SUM(G37:G38) -> 0 | H39: =SUM(H37:H38) -> 3266 | I39: =SUM(I37:I38) -> 16360241 | J39: =SUM(J37:J38) -> 2.1531645e+08 | K39: =SUM(K37:K38) -> -1.9895621e+08 | ... N39: =SUM(N37:N38) -> -2.0975426e+08
A40: Sub total - stock funds | D40: =D35+D39 -> 57813958518 | E40: =E35+E39 -> 4.1240892e+08 | F40: =F35+F39 -> 57401549597 | G40: =G35+G39 -> 53445377699 | H40: =H35+H39 -> 1042651 | I40: =I35+I39 -> 2.8766588e+08 | J40: =J35+J39 -> 9.349017e+08 | K40: =K35+K39 -> -6.4723582e+08 | ... N40: =N35+N39 -> -9.9435515e+08
A41: Balanced Funds
A42: Primarily invested in Peso Securities (shares)
B43: =1+B38 -> 27 | C43: ATRAM Philippine Balanced Fund, Inc. | D43: 4.5410321e+08 | E43: 54254241 | F43: =D43-E43 -> 3.9984897e+08 | G43: 210736819 | H43: 2316 | I43: 716009.53 | J43: 1378680.6 | K43: =I43-J43 -> -662671.11 | L43: =I43+Feb!L43 -> 1623332.6 | M43: =J43+Feb!M43 -> 18184513 | N43: =L43-M43 -> -16561181
B44: =1+B43 -> 28 | C44: ATRAM Unicapital Diversified Growth Fund, Inc. | D44: 1.161206e+08 | E44: 4693809.3 | F44: =D44-E44 -> 1.1142679e+08 | G44: 25667204 | H44: 811 | I44: 284574.8 | J44: 507627.26 | K44: =I44-J44 -> -223052.46 | L44: =I44+Feb!L44 -> 943427.2 | M44: =J44+Feb!M44 -> 1379997.9 | N44: =L44-M44 -> -436570.65
B45: =1+B44 -> 29 | C45: First Metro Save and Learn Balanced Fund, Inc. | D45: 652137686 | E45: 12621540 | F45: =D45-E45 -> 639516146 | G45: 291800977 | H45: 4073 | I45: 565535 | J45: 5023185 | K45: =I45-J45 -> -4457650 | L45: =I45+Feb!L45 -> 2362845 | M45: =J45+Feb!M45 -> 15534109 | N45: =L45-M45 -> -13171264
B46: =1+B45 -> 30 | C46: First Metro Save and Learn F.O.C.C.U.S. Dynamic Fund, Inc. | D46: 355367464 | E46: 4478580 | F46: =D46-E46 -> 350888884 | G46: 246454009 | H46: 366 | I46: 1596875 | J46: 98630792 | K46: =I46-J46 -> -97033917 | L46: =I46+Feb!L46 -> 7075076 | M46: =J46+Feb!M46 -> 131374204 | N46: =L46-M46 -> -124299128
B47: =1+B46 -> 31 | C47: NCM Mutual Fund of the Phils., Inc. | D47: 3.1386964e+08 | E47: 1014514.4 | F47: =D47-E47 -> 3.1285512e+08 | G47: 1.5092638e+08 | H47: 46 | I47: 0 | J47: 1929722.4 | K47: =I47-J47 -> -1929722.4 | L47: =I47+'Feb UPDATED'!L47 -> 2.3662765e+08 | M47: =J47+'Feb UPDATED'!M47 -> 2.3897046e+08 | N47: =L47-M47 -> -2342804.7
B48: =1+B47 -> 32 | C48: PAMI Horizon Fund, Inc. | D48: 441465506 | E48: 14171677 | F48: =D48-E48 -> 427293829 | G48: 213307123 | H48: 9611 | I48: 58303 | J48: 13444723 | K48: =I48-J48 -> -13386420 | L48: =I48+Feb!L48 -> 118479 | M48: =J48+Feb!M48 -> 18039673 | N48: =L48-M48 -> -17921194
B49: =1+B48 -> 33 | C49: Philam Fund, Inc. | D49: 1818549891 | E49: 21662067 | F49: =D49-E49 -> 1796887824 | G49: 880548703 | H49: 7201 | I49: 438438 | J49: 29365728 | K49: =I49-J49 -> -28927290 | L49: =I49+Feb!L49 -> 1288051 | M49: =J49+Feb!M49 -> 55012556 | N49: =L49-M49 -> -53724505
B50: =1+B49 -> 34 | C50: Solidaritas Fund, Inc. | D50: 119583839 | E50: 311579 | F50: =D50-E50 -> 119272260 | G50: 56561225 | H50: 158 | I50: 0 | J50: 0 | K50: =I50-J50 -> 0 | L50: =I50+Feb!L50 -> 0 | M50: =J50+Feb!M50 -> 1672556 | N50: =L50-M50 -> -1672556
B51: =1+B50 -> 35 | C51: Sun Life Prosperity Balanced Fund, Inc. | D51: 5778277025 | E51: 46002830 | F51: =D51-E51 -> 5732274195 | G51: 2880626160 | H51: 54678 | I51: 5014510 | J51: 82540554 | K51: =I51-J51 -> -77526044 | L51: =I51+Feb!L51 -> 17544554 | M51: =J51+Feb!M51 -> 175967224 | N51: =L51-M51 -> -158422670
B52: =1+B51 -> 36 | C52: Sun Life Prosperity Dynamic Fund, Inc. | D52: 463480315 | E52: 2768491 | F52: =D52-E52 -> 460711824 | G52: 246053794 | H52: 5000 | I52: 0 | J52: 3471330 | K52: =I52-J52 -> -3471330 | L52: =I52+Feb!L52 -> 0 | M52: =J52+Feb!M52 -> 24502082 | N52: =L52-M52 -> -24502082
A53: Primarily invested in Peso Securities (units)
B54: =1+B52 -> 37 | C54: Sun Life Prosperity Achiever Fund 2028, Inc. | D54: 76160330 | E54: 377997 | F54: =D54-E54 -> 75782333 | G54: 15367322 | H54: 1258 | I54: 183009 | J54: 306104 | K54: =I54-J54 -> -123095 | L54: =I54+Feb!L54 -> 628033 | M54: =J54+Feb!M54 -> 1212813 | N54: =L54-M54 -> -584780
B55: =1+B54 -> 38 | C55: Sun Life Prosperity Achiever Fund 2038, Inc. | D55: 55431053 | E55: 313246 | F55: =D55-E55 -> 55117807 | G55: 38564326 | H55: 511 | I55: 156298 | J55: 0 | K55: =I55-J55 -> 156298 | L55: =I55+Feb!L55 -> 304941 | M55: =J55+Feb!M55 -> 186630 | N55: =L55-M55 -> 118311
B56: =1+B55 -> 39 | C56: Sun Life Prosperity Achiever Fund 2048, Inc. | D56: 46519580 | E56: 298330 | F56: =D56-E56 -> 46221250 | G56: 37563583 | H56: 247 | I56: 38024 | J56: 57797 | K56: =I56-J56 -> -19773 | L56: =I56+Feb!L56 -> 205385 | M56: =J56+Feb!M56 -> 102227 | N56: =L56-M56 -> 103158
A57: Sub total - Peso Currency | D57: =SUM(D43:D56) -> 10691066132 | E57: =SUM(E42:E56) -> 1.629689e+08 | F57: =SUM(F43:F56) -> 10528097230 | G57: =SUM(G43:G56) -> 5294177625 | H57: =SUM(H43:H56) -> 86276 | I57: =SUM(I42:I56) -> 9051576.3 | J57: =SUM(J43:J56) -> 2.3665624e+08 | K57: =SUM(K43:K56) -> -227604667 | L57: =SUM(L43:L56) -> 2.6872178e+08 | M57: =SUM(M43:M56) -> 6.8213904e+08 | N57: =SUM(N43:N56) -> -413417266
A58: Primarily invested in foreign currency securities (shares)
B59: =1+B56 -> 40 | C59: Cocolife Dollar Fund Builder, Inc. | D59: 62422169 | E59: 474661.64 | F59: =D59-E59 -> 61947507 | G59: 0 | H59: 48 | I59: 0 | J59: 57425.68 | K59: =I59-J59 -> -57425.68 | L59: =I59+Feb!L59 -> 0 | M59: =J59+Feb!M59 -> 207807.29 | N59: =L59-M59 -> -207807.29
B60: =1+B59 -> 41 | C60: PAMI Asia Balanced Fund, Inc. | D60: 302450503 | E60: 18783003 | F60: =D60-E60 -> 283667500 | G60: 155708323 | H60: 210 | I60: 0 | J60: 17230182 | K60: =I60-J60 -> -17230182 | L60: =I60+Feb!L60 -> 0 | M60: =J60+Feb!M60 -> 21099697 | N60: =L60-M60 -> -21099697
B61: =1+B60 -> 42 | C61: Sun Life Prosperity Dollar Advantage Fund, Inc. | D61: 1587489506 | E61: 9128957 | F61: =D61-E61 -> 1578360549 | G61: 0 | H61: 4289 | I61: 16008526 | J61: 31673105 | K61: =I61-J61 -> -15664579 | L61: =I61+Feb!L61 -> 20552846 | M61: =J61+Feb!M61 -> 81403794 | N61: =L61-M61 -> -60850948
B62: =1+B61 -> 43 | C62: Sun Life Prosperity Dollar Wellspring Fund, Inc. | D62: 241905243 | E62: 657951 | F62: =D62-E62 -> 241247292 | G62: 0 | H62: 772 | I62: 4468816 | J62: 3643411 | K62: =I62-J62 -> 825405 | L62: =I62+Feb!L62 -> 4909633 | M62: =J62+Feb!M62 -> 5305727 | N62: =L62-M62 -> -396094
A63: Sub total - US Currency | D63: =SUM(D59:D62) -> 2194267421 | E63: =SUM(E59:E62) -> 29044573 | F63: =SUM(F59:F62) -> 2165222848 | G63: =SUM(G59:G62) -> 155708323 | H63: =SUM(H59:H62) -> 5319 | I63: =SUM(I59:I62) -> 20477342 | J63: =SUM(J59:J62) -> 52604124 | K63: =SUM(K59:K62) -> -32126782 | ... N63: =SUM(N59:N62) -> -82554546
A64: Sub total - balanced funds | D64: =D57+D63 -> 12885333553 | E64: =E57+E63 -> 1.9201347e+08 | F64: =F57+F63 -> 12693320078 | G64: =G57+G63 -> 5449885948 | H64: =H57+H63 -> 91595 | I64: =I57+I63 -> 29528918 | J64: =J57+J63 -> 289260367 | K64: =K57+K63 -> -2.5973145e+08 | ... N64: =N57+N63 -> -4.9597181e+08
A65: Bond Funds
A66: Primarily invested in Peso Securities (shares)
B67: =1+B62 -> 44 | C67: ALFM Peso Bond Fund, Inc. | D67: 35011943452 | E67: 315721106 | F67: =D67-E67 -> 34696222346 | G67: 260000000 | H67: 24134 | I67: 182690214 | J67: 315697456 | K67: =I67-J67 -> -133007242 | L67: =I67+Feb!L67 -> 616529217 | M67: =J67+Feb!M67 -> 1067324450 | N67: =L67-M67 -> -450795233
B68: =1+B67 -> 45 | C68: ATRAM Corporate Bond Fund, Inc. | D68: 2.5925238e+08 | E68: 1530231.9 | F68: =D68-E68 -> 2.5772214e+08 | G68: 0 | H68: 928 | I68: 531794.82 | J68: 5285058.4 | K68: =I68-J68 -> -4753263.6 | L68: =I68+Feb!L68 -> 2250151.9 | M68: =J68+Feb!M68 -> 21419382 | N68: =L68-M68 -> -19169230
B69: =1+B68 -> 46 | C69: Cocolife Fixed Income Fund, Inc. | D69: 9.4259474e+08 | E69: 10505661 | F69: =D69-E69 -> 9.3208908e+08 | G69: 0 | H69: 1807 | I69: 1054031.6 | J69: 14062342 | K69: =I69-J69 -> -13008310 | L69: =I69+Feb!L69 -> 15208319 | M69: =J69+Feb!M69 -> 31450950 | N69: =L69-M69 -> -16242631
B70: =1+B69 -> 47 | C70: Ekklesia Mutual Fund, Inc. | D70: 188355784 | E70: 181220 | F70: =D70-E70 -> 188174564 | G70: 0 | H70: 134 | I70: 0 | J70: 367690 | K70: =I70-J70 -> -367690 | L70: =I70+Feb!L70 -> 4998 | M70: =J70+Feb!M70 -> 426661 | N70: =L70-M70 -> -421663
B71: =1+B70 -> 48 | C71: First Metro Save and Learn Fixed Income Fund, Inc. | D71: 1157782211 | E71: 14755902 | F71: =D71-E71 -> 1143026309 | G71: 0 | H71: 1727 | I71: 482410 | J71: 29552121 | K71: =I71-J71 -> -29069711 | L71: =I71+Feb!L71 -> 2000407 | M71: =J71+Feb!M71 -> 53912628 | N71: =L71-M71 -> -51912221
B72: =1+B71 -> 49 | C72: Philam Bond Fund, Inc. | D72: 1403284308 | E72: 31710405 | F72: =D72-E72 -> 1371573903 | G72: 0 | H72: 4548 | I72: 2673894 | J72: 28185079 | K72: =I72-J72 -> -25511185 | L72: =I72+Feb!L72 -> 5652943 | M72: =J72+Feb!M72 -> 45170819 | N72: =L72-M72 -> -39517876
B73: =1+B72 -> 50 | C73: Philam Managed Income Fund, Inc. | D73: 613334190 | E73: 9891727 | F73: =D73-E73 -> 603442463 | G73: 0 | H73: 399 | I73: 0 | J73: 3208515 | K73: =I73-J73 -> -3208515 | L73: =I73+Feb!L73 -> 0 | M73: =J73+Feb!M73 -> 20407108 | N73: =L73-M73 -> -20407108
B74: =1+B73 -> 51 | C74: Philequity Peso Bond Fund, Inc. | D74: 3.3492437e+08 | E74: 1322888.7 | F74: =D74-E74 -> 333601483 | G74: 0 | H74: 3948 | I74: 2584215.3 | J74: 1683005.7 | K74: =I74-J74 -> 901209.59 | L74: =I74+Feb!L74 -> 8272153.6 | M74: =J74+Feb!M74 -> 3785103.2 | N74: =L74-M74 -> 4487050.4
B75: =1+B74 -> 52 | C75: Soldivo Bond Fund, Inc. | D75: 1.8864493e+09 | E75: 3434138.3 | F75: =D75-E75 -> 1883015190 | G75: 0 | H75: 781 | I75: 50119148 | J75: 331463.09 | K75: =I75-J75 -> 49787685 | L75: =I75+Feb!L75 -> 77712609 | M75: =J75+Feb!M75 -> 5565167 | N75: =L75-M75 -> 72147442
B76: =1+B75 -> 53 | C76: Sun Life Prosperity Bond Fund, Inc. | D76: 6457659157 | E76: 25379690 | F76: =D76-E76 -> 6432279467 | G76: 0 | H76: 19389 | I76: 70643479 | J76: 63731558 | K76: =I76-J76 -> 6911921 | L76: =I76+Feb!L76 -> 179914337 | M76: =J76+Feb!M76 -> 332806134 | N76: =L76-M76 -> -152891797
B77: =1+B76 -> 54 | C77: Sun Life Prosperity GS Fund, Inc. | D77: 145871845 | E77: 429561 | F77: =D77-E77 -> 145442284 | G77: 0 | H77: 2904 | I77: 991818 | J77: 560261 | K77: =I77-J77 -> 431557 | L77: =I77+Feb!L77 -> 2366258 | M77: =J77+Feb!M77 -> 8275016 | N77: =L77-M77 -> -5908758
A78: Corporate Debt Vehicle (units)
B79: =1+B77 -> 55 | C79: ATRAM Unitized Corporate Debt Vehicle, Inc. | D79: 7.0947451e+08 | E79: 2353242.3 | F79: =D79-E79 -> 7.0712127e+08 | G79: 0 | H79: 13 | I79: 0 | J79: 0 | K79: =I79-J79 -> 0 | L79: =I79+Feb!L79 -> 0 | M79: =J79+Feb!M79 -> 0 | N79: =L79-M79 -> 0
A80: Sub total - Peso Currency | D80: =SUM(D67:D79) -> 49110926276 | E80: =SUM(E67:E79) -> 4.1721577e+08 | F80: =SUM(F67:F79) -> 48693710503 | G80: =SUM(G67:G79) -> 260000000 | H80: =SUM(H67:H79) -> 60712 | I80: =SUM(I67:I79) -> 3.1177101e+08 | J80: =SUM(J67:J79) -> 4.6266455e+08 | K80: =SUM(K67:K79) -> -1.5089354e+08 | ... N80: =SUM(N67:N79) -> -680632024
A81: Primarily invested in foreign currency securities (shares)
B82: =1+B79 -> 56 | C82: ALFM Dollar Bond Fund, Inc. | D82: 11888326265 | E82: 363840025 | F82: =D82-E82 -> 11524486240 | G82: 0 | H82: 7227 | I82: 24760602 | J82: 106568499 | K82: =I82-J82 -> -81807897 | L82: =I82+Feb!L82 -> 84041745 | M82: =J82+Feb!M82 -> 302572746 | N82: =L82-M82 -> -218531001
B83: =1+B82 -> 57 | C83: ATRAM Total Return Dollar Bond Fund, Inc. | D83: 1.3732471e+08 | E83: 24998404 | F83: =D83-E83 -> 1.1232631e+08 | G83: 0 | H83: 72 | I83: 18590524 | J83: 1121789.7 | K83: =I83-J83 -> 17468734 | L83: =I83+Feb!L83 -> 18590524 | M83: =J83+Feb!M83 -> 2683522.4 | N83: =L83-M83 -> 15907002
B84: =1+B83 -> 58 | C84: First Metro Save and Learn Dollar Bond Fund, Inc. | D84: 347939037 | E84: 30527926 | F84: =D84-E84 -> 317411111 | G84: 0 | H84: 160 | I84: 57289 | J84: 1489691 | K84: =I84-J84 -> -1432402 | L84: =I84+Feb!L84 -> 186598 | M84: =J84+Feb!M84 -> 2292229 | N84: =L84-M84 -> -2105631
B85: =1+B84 -> 59 | C85: PAMI Global Bond Fund, Inc. | D85: 67431124 | E85: 16227836 | F85: =D85-E85 -> 51203288 | G85: 0 | H85: 24 | I85: 0 | J85: 0 | K85: =I85-J85 -> 0 | L85: =I85+Feb!L85 -> 0 | M85: =J85+Feb!M85 -> 0 | N85: =L85-M85 -> 0
B86: =1+B85 -> 60 | C86: Philam Dollar Bond Fund, Inc. | D86: 1643599522 | E86: 10902682 | F86: =D86-E86 -> 1632696840 | G86: 0 | H86: 1579 | I86: 101948 | J86: 23885287 | K86: =I86-J86 -> -23783339 | L86: =I86+Feb!L86 -> 159620 | M86: =J86+Feb!M86 -> 62750664 | N86: =L86-M86 -> -62591044
B87: =1+B86 -> 61 | C87: Philequity Dollar Income Fund, Inc. | D87: 2.2673422e+08 | E87: 1310923.3 | F87: =D87-E87 -> 225423299 | G87: 0 | H87: 96 | I87: 200235 | J87: 0 | K87: =I87-J87 -> 200235 | L87: =I87+Feb!L87 -> 397566 | M87: =J87+Feb!M87 -> 0 | N87: =L87-M87 -> 397566
B88: =1+B87 -> 62 | C88: Sun Life Prosperity Dollar Abundance Fund, Inc. | D88: 497456656 | E88: 27491398 | F88: =D88-E88 -> 469965258 | G88: 0 | H88: 2648 | I88: 114420 | J88: 6249374 | K88: =I88-J88 -> -6134954 | L88: =I88+Feb!L88 -> 3204266 | M88: =J88+Feb!M88 -> 27545895 | N88: =L88-M88 -> -24341629
A89: Sub total - US Currency | D89: =SUM(D82:D88) -> 14808811540 | E89: =SUM(E82:E88) -> 4.7529919e+08 | F89: =SUM(F82:F88) -> 14333512345 | G89: =SUM(G82:G88) -> 0 | H89: =SUM(H82:H88) -> 11806 | I89: =SUM(I82:I88) -> 43825018 | J89: =SUM(J82:J88) -> 1.3931464e+08 | K89: =SUM(K82:K88) -> -95489623 | ... N89: =SUM(N82:N88) -> -2.9126474e+08
B90: =1+B88 -> 63 | C90: ALFM Euro Bond Fund, Inc. | D90: 716100749 | E90: 4813605 | F90: =D90-E90 -> 711287144 | G90: 0 | H90: 572 | I90: 3194049 | J90: 12332908 | K90: =I90-J90 -> -9138859 | L90: =I90+Feb!L90 -> 18427084 | M90: =J90+Feb!M90 -> 23956912 | N90: =L90-M90 -> -5529828
A91: Sub total - Euro Currency | D91: =SUM(D90) -> 716100749 | E91: =SUM(E90) -> 4813605 | F91: =SUM(F90) -> 711287144 | G91: =SUM(G90) -> 0 | H91: =SUM(H90) -> 572 | I91: =SUM(I90) -> 3194049 | J91: =SUM(J90) -> 12332908 | K91: =SUM(K90) -> -9138859 | ... N91: =SUM(N90) -> -5529828
A92: Sub total - bond funds | D92: =D80+D89+D91 -> 64635838565 | E92: =E80+E89+E91 -> 8.9732857e+08 | F92: =F80+F89+F91 -> 63738509992 | G92: =G80+G89+G91 -> 260000000 | H92: =H80+H89+H91 -> 73090 | I92: =I80+I89+I91 -> 3.5879007e+08 | J92: =J80+J89+J91 -> 6.143121e+08 | K92: =K80+K89+K91 -> -255522026 | ... N92: =N80+N89+N91 -> -9.7742659e+08
A93: Money Market Funds
A94: Primarily invested in Peso Securities (shares)
B95: 64 | C95: AIB Money Market Mutual Fund, Inc. | D95: 1.7239219e+08 | E95: 291417.38 | F95: =D95-E95 -> 1.7210077e+08 | G95: 0 | H95: 73 | I95: 131000 | J95: 80394.93 | K95: =I95-J95 -> 50605.07 | L95: =I95+Feb!L95 -> 922000 | M95: =J95+Feb!M95 -> 80394.93 | N95: =L95-M95 -> 841605.07
B96: 65 | C96: ALFM Money Market Fund, Inc. | D96: 21722533721 | E96: 564324251 | F96: =D96-E96 -> 21158209470 | G96: 0 | H96: 21966 | I96: 321013 | J96: 282272705 | K96: =I96-J96 -> -281951692 | L96: =I96+Feb!L96 -> 1026581 | M96: =J96+Feb!M96 -> 1110241986 | N96: =L96-M96 -> -1109215405
B97: =1+B96 -> 66 | C97: First Metro Save and Learn Money Market Fund, Inc. | D97: 2569051527 | E97: 25930703 | F97: =D97-E97 -> 2543120824 | G97: 0 | H97: 1179 | I97: 68989395 | J97: 86975012 | K97: =I97-J97 -> -17985617 | L97: =I97+Feb!L97 -> 243685522 | M97: =J97+Feb!M97 -> 479693987 | N97: =L97-M97 -> -236008465
B98: =1+B97 -> 67 | C98: Sun Life Prosperity Peso Starter Fund, Inc. | D98: 13067107895 | E98: 639453089 | F98: =D98-E98 -> 12427654806 | G98: 0 | H98: 73474 | I98: 609974547 | J98: 621449569 | K98: =I98-J98 -> -11475022 | L98: =I98+Feb!L98 -> 1570722999 | M98: =J98+Feb!M98 -> 1646377308 | N98: =L98-M98 -> -75654309
A99: Primarily invested in Peso Securities (units)
B100: =1+B98 -> 68 | C100: ALFM Money Market Fund, Inc. | D100: 11881390234 | E100: 307498510 | F100: =D100-E100 -> 11573891724 | G100: 0 | H100: 27113 | I100: 835811931 | J100: 859984068 | K100: =I100-J100 -> -24172137 | L100: =I100+Feb!L100 -> 2316300480 | M100: =J100+Feb!M100 -> 2260442749 | N100: =L100-M100 -> 55857731
A101: Sub total - Peso Currency | D101: =SUM(D95:D98)+D100 -> 49412475564 | E101: =SUM(E95:E98)+E100 -> 1537497970 | F101: =SUM(F95:F98)+F100 -> 47874977594 | G101: =SUM(G95:G98)+G100 -> 0 | H101: =SUM(H95:H98)+H100 -> 123805 | I101: =SUM(I95:I98)+I100 -> 1515227886 | J101: =SUM(J95:J98)+J100 -> 1850761749 | K101: =SUM(K95:K98)+K100 -> -3.3553386e+08 | ... N101: =SUM(N95:N98)+N100 -> -1364178843
A102: Primarily invested in foreign currency securities (shares)
B103: =1+B100 -> 69 | C103: Sun Life Prosperity Dollar Starter Fund, Inc. | D103: 2533421448 | E103: 22147457 | F103: =D103-E103 -> 2511273991 | G103: 0 | H103: 3848 | I103: 309927025 | J103: 152225465 | K103: =I103-J103 -> 157701560 | L103: =I103+Feb!L103 -> 669320283 | M103: =J103+Feb!M103 -> 481356071 | N103: =L103-M103 -> 187964212
A104: Sub total - US Currency | D104: =SUM(D103) -> 2533421448 | E104: =SUM(E103) -> 22147457 | F104: =SUM(F103) -> 2511273991 | G104: =SUM(G103) -> 0 | H104: =SUM(H103) -> 3848 | I104: =SUM(I103) -> 309927025 | J104: =SUM(J103) -> 152225465 | K104: =SUM(K103) -> 157701560 | ... N104: =SUM(N103) -> 187964212
A105: Sub total - money market funds | D105: =D101+D104 -> 51945897012 | E105: =E101+E104 -> 1559645427 | F105: =F101+F104 -> 50386251585 | G105: =G101+G104 -> 0 | H105: =H101+H104 -> 127653 | I105: =I101+I104 -> 1825154911 | J105: =J101+J104 -> 2002987214 | K105: =K101+K104 -> -1.778323e+08 | ... N105: =N101+N104 -> -1176214631
...

Sheet Q1
A1: PHILIPPINE INVESTMENT FUNDS ASSOCIATION, INC.
A2: MUTUAL FUNDS STATISTICAL REPORT
A3: As of the First Quarter of 2025
A4: (Amounts in Philippine Peso)
A6: Fund Category | C6: Fund Name | D6: NET ASSETS | E6: TOTAL SALES | F6: TOTAL REDEMPTIONS | G6: NET SALES
A7: Stock Funds
A8: Primarily invested in Peso Securities (shares)
B9: 1 | C9: ALFM Growth Fund, Inc. | D9: =Jan!F9 -> 3519779581 | E9: =Jan!I9+Feb!I9+Mar!I9 -> 23921065 | F9: =Jan!J9+Feb!J9+Mar!J9 -> 93648240 | G9: =E9-F9 -> -69727175
B10: =1+B9 -> 2 | C10: ATRAM Alpha Opportunity Fund, Inc. | D10: =Jan!F10 -> 8.7946495e+08 | E10: =Jan!I10+Feb!I10+Mar!I10 -> 61754874 | F10: =Jan!J10+Feb!J10+Mar!J10 -> 37824902 | G10: =E10-F10 -> 23929972
B11: =1+B10 -> 3 | C11: ATRAM Phil. Equity Opportunity Fund, Inc. | D11: =Jan!F11 -> 9.8945944e+08 | E11: =Jan!I11+Feb!I11+Mar!I11 -> 16646336 | F11: =Jan!J11+Feb!J11+Mar!J11 -> 29317981 | G11: =E11-F11 -> -12671646
B12: =1+B11 -> 4 | C12: Climbs Share Capital Equity Investment Fund Corp. | D12: =Jan!F12 -> 4.0176991e+08 | E12: =Jan!I12+Feb!I12+Mar!I12 -> 41032623 | F12: =Jan!J12+Feb!J12+Mar!J12 -> 1720904.9 | G12: =E12-F12 -> 39311718
B13: =1+B12 -> 5 | C13: First Metro Consumer Fund, Inc. | D13: =Jan!F13 -> 340546973 | E13: =Jan!I13+Feb!I13+Mar!I13 -> 794954 | F13: =Jan!J13+Feb!J13+Mar!J13 -> 9096934 | G13: =E13-F13 -> -8301980
B14: =1+B13 -> 6 | C14: First Metro Save and Learn Equity Fund, Inc. | D14: =Jan!F14 -> 2934717410 | E14: =Jan!I14+Feb!I14+Mar!I14 -> 40934592 | F14: =Jan!J14+Feb!J14+Mar!J14 -> 122115264 | G14: =E14-F14 -> -81180672
B15: =1+B14 -> 7 | C15: First Metro Save and Learn Phil. Index Fund, Inc. | D15: =Jan!F15 -> 77562338 | E15: =Jan!I15+Feb!I15+Mar!I15 -> 7236629 | F15: =Jan!J15+Feb!J15+Mar!J15 -> 1080702 | G15: =E15-F15 -> 6155927
B16: =1+B15 -> 8 | C16: MBG Equity Investment Fund, Inc. | D16: =Jan!F16 -> 117940203 | E16: =Jan!I16+Feb!I16+Mar!I16 -> 0 | F16: =Jan!J16+Feb!J16+Mar!J16 -> 4270929 | G16: =E16-F16 -> -4270929
B17: =1+B16 -> 9 | C17: PAMI Equity Index Fund, Inc. | D17: =Jan!F17 -> 940637483 | E17: =Jan!I17+Feb!I17+Mar!I17 -> 0 | F17: =Jan!J17+Feb!J17+Mar!J17 -> 20508556 | G17: =E17-F17 -> -20508556
B18: =1+B17 -> 10 | C18: Philam Strategic Growth Fund, Inc. | D18: =Jan!F18 -> 2935187983 | E18: =Jan!I18+Feb!I18+Mar!I18 -> 19633671 | F18: =Jan!J18+Feb!J18+Mar!J18 -> 84434613 | G18: =E18-F18 -> -64800942
B19: =1+B18 -> 11 | C19: Philequity Dividend Yield Fund, Inc. | D19: =Jan!F19 -> 2408297162 | E19: =Jan!I19+Feb!I19+Mar!I19 -> 48247099 | F19: =Jan!J19+Feb!J19+Mar!J19 -> 45672090 | G19: =E19-F19 -> 2575009.4
B20: =1+B19 -> 12 | C20: Philequity Fund, Inc. | D20: =Jan!F20 -> 8281684398 | E20: =Jan!I20+Feb!I20+Mar!I20 -> 91056483 | F20: =Jan!J20+Feb!J20+Mar!J20 -> 1.7821858e+08 | G20: =E20-F20 -> -87162094
B21: =1+B20 -> 13 | C21: Philequity MSCI Phil. Index Fund, Inc. | D21: =Jan!F21 -> 2.842405e+08 | E21: =Jan!I21+Feb!I21+Mar!I21 -> 1085849.7 | F21: =Jan!J21+Feb!J21+Mar!J21 -> 550060.98 | G21: =E21-F21 -> 535788.75
... B27: =1+B26 -> 19 | C27: United Fund, Inc. | D27: =Jan!F27 -> 4.6182618e+08 | E27: =Jan!I27+Feb!I27+Mar!I27 -> 1079302.5 | F27: =Jan!J27+Feb!J27+Mar!J27 -> 3082993.2 | G27: =E27-F27 -> -2003690.8
A28: Primarily invested in Peso Securities (units)
B29: =1+B27 -> 20 | C29: COL Equity Index Unitized Mutual Fund, Inc. | D29: =Jan!F29 -> 2.177321e+08 | E29: =Jan!I29+Feb!I29+Mar!I29 -> 39465956 | F29: =Jan!J29+Feb!J29+Mar!J29 -> 15032562 | G29: =E29-F29 -> 24433394
B30: =1+B29 -> 21 | C30: COL Strategic Growth Equity Unitized Mutual Fund, Inc. | D30: =Jan!F30 -> 3.7301676e+08 | E30: =Jan!I30+Feb!I30+Mar!I30 -> 43936603 | F30: =Jan!J30+Feb!J30+Mar!J30 -> 29293398 | G30: =E30-F30 -> 14643204
B31: =1+B30 -> 22 | C31: Philequity Alpha One Fund, Inc. | D31: =Jan!F31 -> 2.5830637e+08 | E31: =Jan!I31+Feb!I31+Mar!I31 -> 2960185 | F31: =Jan!J31+Feb!J31+Mar!J31 -> 12614178 | G31: =E31-F31 -> -9653992.9
B32: =1+B31 -> 23 | C32: Philippine Stock Index Fund Corp. | D32: =Jan!F32 -> 643846858 | E32: =Jan!I32+Feb!I32+Mar!I32 -> 118944271 | F32: =Jan!J32+Feb!J32+Mar!J32 -> 87638342 | G32: =E32-F32 -> 31305929
A33: Exchange Traded Fund
B34: =1+B32 -> 24 | C34: First Metro Phil. Equity Exchange Traded Fund, Inc. | D34: =Jan!F34 -> 1259866083 | E34: =Jan!I34+Feb!I34+Mar!I34 -> 40232388 | F34: =Jan!J34+Feb!J34+Mar!J34 -> 0 | G34: =E34-F34 -> 40232388
A35: Sub total - Peso Currency | D35: =SUM(D9:D34) -> 52861398006 | E35: =SUM(E9:E34) -> 9.196606e+08 | F35: =SUM(F9:F34) -> 1704261488 | G35: =SUM(G9:G34) -> -7.8460089e+08
A36: Primarily invested in foreign currency securities (shares)
B37: =1+B34 -> 25 | C37: ATRAM AsiaPlus Equity Fund, Inc. | D37: =Jan!F37 -> 27790192 | E37: =Jan!I37+Feb!I37+Mar!I37 -> 104642.2 | F37: =Jan!J37+Feb!J37+Mar!J37 -> 153134.87 | G37: =E37-F37 -> -48492.67
B38: =1+B37 -> 26 | C38: Sun Life Prosperity World Voyager Fund, Inc. | D38: =Jan!F38 -> 2107005269 | E38: =Jan!I38+Feb!I38+Mar!I38 -> 87592931 | F38: =Jan!J38+Feb!J38+Mar!J38 -> 297298701 | G38: =E38-F38 -> -209705770
A39: Sub total - US Currency | D39: =SUM(D37:D38) -> 2134795461 | E39: =SUM(E37:E38) -> 87697573 | F39: =SUM(F37:F38) -> 2.9745184e+08 | G39: =SUM(G37:G38) -> -2.0975426e+08
A40: Sub total - stock funds | D40: =D35+D39 -> 54996193467 | E40: =E35+E39 -> 1007358172 | F40: =F35+F39 -> 2001713324 | G40: =G35+G39 -> -9.9435515e+08
A41: Balanced Funds
A42: Primarily invested in Peso Securities (shares)
B43: =B38+1 -> 27 | C43: ATRAM Philippine Balanced Fund, Inc. | D43: =Jan!F43 -> 3.9469112e+08 | E43: =Jan!I43+Feb!I43+Mar!I43 -> 1623332.6 | F43: =Jan!J43+Feb!J43+Mar!J43 -> 18184513 | G43: =E43-F43 -> -16561181
B44: =B43+1 -> 28 | C44: ATRAM Unicapital Diversified Growth Fund, Inc. | D44: =Jan!F44 -> 1.1147777e+08 | E44: =Jan!I44+Feb!I44+Mar!I44 -> 943427.2 | F44: =Jan!J44+Feb!J44+Mar!J44 -> 1379997.9 | G44: =E44-F44 -> -436570.65
B45: =B44+1 -> 29 | C45: First Metro Save and Learn Balanced Fund, Inc. | D45: =Jan!F45 -> 634289203 | E45: =Jan!I45+Feb!I45+Mar!I45 -> 2362845 | F45: =Jan!J45+Feb!J45+Mar!J45 -> 15534109 | G45: =E45-F45 -> -13171264
B46: =B45+1 -> 30 | C46: First Metro Save and Learn F.O.C.C.U.S. Dynamic Fund, Inc. | D46: =Jan!F46 -> 462111116 | E46: =Jan!I46+Feb!I46+Mar!I46 -> 7075076 | F46: =Jan!J46+Feb!J46+Mar!J46 -> 131374204 | G46: =E46-F46 -> -124299128
B47: =B46+1 -> 31 | C47: NCM Mutual Fund of the Phils., Inc. | D47: =Jan!F47 -> 3.0597939e+08 | E47: =Jan!I47+Feb!I47+Mar!I47 -> 122503445 | F47: =Jan!J47+Feb!J47+Mar!J47 -> 123701300 | G47: =E47-F47 -> -1197855
B48: =B47+1 -> 32 | C48: PAMI Horizon Fund, Inc. | D48: =Jan!F48 -> 427099024 | E48: =Jan!I48+Feb!I48+Mar!I48 -> 118479 | F48: =Jan!J48+Feb!J48+Mar!J48 -> 18039673 | G48: =E48-F48 -> -17921194
B49: =B48+1 -> 33 | C49: Philam Fund, Inc. | D49: =Jan!F49 -> 1778835144 | E49: =Jan!I49+Feb!I49+Mar!I49 -> 1288051 | F49: =Jan!J49+Feb!J49+Mar!J49 -> 55012556 | G49: =E49-F49 -> -53724505
B50: =B49+1 -> 34 | C50: Solidaritas Fund, Inc. | D50: =Jan!F50 -> 114797748 | E50: =Jan!I50+Feb!I50+Mar!I50 -> 0 | F50: =Jan!J50+Feb!J50+Mar!J50 -> 1672556 | G50: =E50-F50 -> -1672556
B51: =B50+1 -> 35 | C51: Sun Life Prosperity Balanced Fund, Inc. | D51: =Jan!F51 -> 5651266595 | E51: =Jan!I51+Feb!I51+Mar!I51 -> 17544554 | F51: =Jan!J51+Feb!J51+Mar!J51 -> 175967224 | G51: =E51-F51 -> -158422670
B52: =B51+1 -> 36 | C52: Sun Life Prosperity Dynamic Fund, Inc. | D52: =Jan!F52 -> 456578134 | E52: =Jan!I52+Feb!I52+Mar!I52 -> 0 | F52: =Jan!J52+Feb!J52+Mar!J52 -> 24502082 | G52: =E52-F52 -> -24502082
A53: Primarily invested in Peso Securities (units)
B54: =1+B52 -> 37 | C54: Sun Life Prosperity Achiever Fund 2028, Inc. | D54: =Jan!F54 -> 74676992 | E54: =Jan!I54+Feb!I54+Mar!I54 -> 628033 | F54: =Jan!J54+Feb!J54+Mar!J54 -> 1212813 | G54: =E54-F54 -> -584780
B55: =1+B54 -> 38 | C55: Sun Life Prosperity Achiever Fund 2038, Inc. | D55: =Jan!F55 -> 52594093 | E55: =Jan!I55+Feb!I55+Mar!I55 -> 304941 | F55: =Jan!J55+Feb!J55+Mar!J55 -> 186630 | G55: =E55-F55 -> 118311
B56: =1+B55 -> 39 | C56: Sun Life Prosperity Achiever Fund 2048, Inc. | D56: =Jan!F56 -> 43910102 | E56: =Jan!I56+Feb!I56+Mar!I56 -> 205385 | F56: =Jan!J56+Feb!J56+Mar!J56 -> 102227 | G56: =E56-F56 -> 103158
A57: Sub total - Peso Currency | D57: =SUM(D43:D56) -> 10508306441 | E57: =SUM(E43:E56) -> 1.5459757e+08 | F57: =SUM(F43:F56) -> 5.6686989e+08 | G57: =SUM(G43:G56) -> -4.1227232e+08
A58: Primarily invested in foreign currency securities (shares)
B59: =1+B56 -> 40 | C59: Cocolife Dollar Fund Builder, Inc. | D59: =Jan!F59 -> 64654360 | E59: =Jan!I59+Feb!I59+Mar!I59 -> 0 | F59: =Jan!J59+Feb!J59+Mar!J59 -> 207807.29 | G59: =E59-F59 -> -207807.29
B60: =1+B59 -> 41 | C60: PAMI Asia Balanced Fund, Inc. | D60: =Jan!F60 -> 309831780 | E60: =Jan!I60+Feb!I60+Mar!I60 -> 0 | F60: =Jan!J60+Feb!J60+Mar!J60 -> 21099697 | G60: =E60-F60 -> -21099697
B61: =1+B60 -> 42 | C61: Sun Life Prosperity Dollar Advantage Fund, Inc. | D61: =Jan!F61 -> 1704946033 | E61: =Jan!I61+Feb!I61+Mar!I61 -> 20552846 | F61: =Jan!J61+Feb!J61+Mar!J61 -> 81403794 | G61: =E61-F61 -> -60850948
B62: =1+B61 -> 43 | C62: Sun Life Prosperity Dollar Wellspring Fund, Inc. | D62: =Jan!F62 -> 248497251 | E62: =Jan!I62+Feb!I62+Mar!I62 -> 4909633 | F62: =Jan!J62+Feb!J62+Mar!J62 -> 5305727 | G62: =E62-F62 -> -396094
A63: Sub total - US Currency | D63: =SUM(D59:D62) -> 2327929424 | E63: =SUM(E59:E62) -> 25462479 | F63: =SUM(F59:F62) -> 1.0801703e+08 | G63: =SUM(G59:G62) -> -82554546
A64: Sub total - balanced funds | D64: =D57+D63 -> 12836235865 | E64: =E57+E63 -> 1.8006005e+08 | F64: =F57+F63 -> 6.7488691e+08 | G64: =G57+G63 -> -4.9482686e+08
A65: Bond Funds
A66: Primarily invested in Peso Securities (shares)
B67: =1+B62 -> 44 | C67: ALFM Peso Bond Fund, Inc. | D67: =Jan!F67 -> 34722390663 | E67: =Jan!I67+Feb!I67+Mar!I67 -> 616529217 | F67: =Jan!J67+Feb!J67+Mar!J67 -> 1067324450 | G67: =E67-F67 -> -450795233
B68: =1+B67 -> 45 | C68: ATRAM Corporate Bond Fund, Inc. | D68: =Jan!F68 -> 2.6479555e+08 | E68: =Jan!I68+Feb!I68+Mar!I68 -> 2250151.9 | F68: =Jan!J68+Feb!J68+Mar!J68 -> 21419382 | G68: =E68-F68 -> -19169230
B69: =1+B68 -> 46 | C69: Cocolife Fixed Income Fund, Inc. | D69: =Jan!F69 -> 9.4736593e+08 | E69: =Jan!I69+Feb!I69+Mar!I69 -> 15208319 | F69: =Jan!J69+Feb!J69+Mar!J69 -> 31450950 | G69: =E69-F69 -> -16242631
B70: =1+B69 -> 47 | C70: Ekklesia Mutual Fund, Inc. | D70: =Jan!F70 -> 187438247 | E70: =Jan!I70+Feb!I70+Mar!I70 -> 4998 | F70: =Jan!J70+Feb!J70+Mar!J70 -> 426661 | G70: =E70-F70 -> -421663
B71: =1+B70 -> 48 | C71: First Metro Save and Learn Fixed Income Fund, Inc. | D71: =Jan!F71 -> 1182097029 | E71: =Jan!I71+Feb!I71+Mar!I71 -> 2000407 | F71: =Jan!J71+Feb!J71+Mar!J71 -> 53912628 | G71: =E71-F71 -> -51912221
B72: =1+B71 -> 49 | C72: Philam Bond Fund, Inc. | D72: =Jan!F72 -> 1393423632 | E72: =Jan!I72+Feb!I72+Mar!I72 -> 5652943 | F72: =Jan!J72+Feb!J72+Mar!J72 -> 45170819 | G72: =E72-F72 -> -39517876
B73: =1+B72 -> 50 | C73: Philam Managed Income Fund, Inc. | D73: =Jan!F73 -> 609447740 | E73: =Jan!I73+Feb!I73+Mar!I73 -> 0 | F73: =Jan!J73+Feb!J73+Mar!J73 -> 20407108 | G73: =E73-F73 -> -20407108
B74: =1+B73 -> 51 | C74: Philequity Peso Bond Fund, Inc. | D74: =Jan!F74 -> 3.2757764e+08 | E74: =Jan!I74+Feb!I74+Mar!I74 -> 8272153.6 | F74: =Jan!J74+Feb!J74+Mar!J74 -> 3785103.2 | G74: =E74-F74 -> 4487050.4
B75: =1+B74 -> 52 | C75: Soldivo Bond Fund, Inc. | D75: =Jan!F75 -> 1802598804 | E75: =Jan!I75+Feb!I75+Mar!I75 -> 77712609 | F75: =Jan!J75+Feb!J75+Mar!J75 -> 5565167 | G75: =E75-F75 -> 72147442
B76: =1+B75 -> 53 | C76: Sun Life Prosperity Bond Fund, Inc. | D76: =Jan!F76 -> 6388513442 | E76: =Jan!I76+Feb!I76+Mar!I76 -> 179914337 | F76: =Jan!J76+Feb!J76+Mar!J76 -> 332806134 | G76: =E76-F76 -> -152891797
B77: =1+B76 -> 54 | C77: Sun Life Prosperity GS Fund, Inc. | D77: =Jan!F77 -> 150367821 | E77: =Jan!I77+Feb!I77+Mar!I77 -> 2366258 | F77: =Jan!J77+Feb!J77+Mar!J77 -> 8275016 | G77: =E77-F77 -> -5908758
A78: Corporat e Debt Vehicle (units)
B79: =1+B77 -> 55 | C79: ATRAM Unitized Corporate Debt Vehicle, Inc. | D79: =Jan!F79 -> 7.1094926e+08 | E79: =Jan!I79+Feb!I79+Mar!I79 -> 0 | F79: =Jan!J79+Feb!J79+Mar!J79 -> 0 | G79: =E79-F79 -> 0
A80: Sub total - Peso Currency | D80: =SUM(D67:D79) -> 48686965748 | E80: =SUM(E67:E79) -> 9.0991139e+08 | F80: =SUM(F67:F79) -> 1590543417 | G80: =SUM(G67:G79) -> -680632024
A81: Primarily invested in foreign currency securities (shares)
B82: =1+B79 -> 56 | C82: ALFM Dollar Bond Fund, Inc. | D82: =Jan!F82 -> 11397347333 | E82: =Jan!I82+Feb!I82+Mar!I82 -> 84041745 | F82: =Jan!J82+Feb!J82+Mar!J82 -> 302572746 | G82: =E82-F82 -> -218531001
B83: =1+B82 -> 57 | C83: ATRAM Total Return Dollar Bond Fund, Inc. | D83: =Jan!F83 -> 95398400 | E83: =Jan!I83+Feb!I83+Mar!I83 -> 18590524 | F83: =Jan!J83+Feb!J83+Mar!J83 -> 2683522.4 | G83: =E83-F83 -> 15907002
B84: =1+B83 -> 58 | C84: First Metro Save and Learn Dollar Bond Fund, Inc. | D84: =Jan!F84 -> 320389473 | E84: =Jan!I84+Feb!I84+Mar!I84 -> 186598 | F84: =Jan!J84+Feb!J84+Mar!J84 -> 2292229 | G84: =E84-F84 -> -2105631
B85: =1+B84 -> 59 | C85: PAMI Global Bond Fund, Inc. | D85: =Jan!F85 -> 51907618 | E85: =Jan!I85+Feb!I85+Mar!I85 -> 0 | F85: =Jan!J85+Feb!J85+Mar!J85 -> 0 | G85: =E85-F85 -> 0
B86: =1+B85 -> 60 | C86: Philam Dollar Bond Fund, Inc. | D86: =Jan!F86 -> 1669352343 | E86: =Jan!I86+Feb!I86+Mar!I86 -> 159620 | F86: =Jan!J86+Feb!J86+Mar!J86 -> 62750664 | G86: =E86-F86 -> -62591044
B87: =1+B86 -> 61 | C87: Philequity Dollar Income Fund, Inc. | D87: =Jan!F87 -> 2.2754357e+08 | E87: =Jan!I87+Feb!I87+Mar!I87 -> 397566 | F87: =Jan!J87+Feb!J87+Mar!J87 -> 0 | G87: =E87-F87 -> 397566
B88: =1+B87 -> 62 | C88: Sun Life Prosperity Dollar Abundance Fund, Inc. | D88: =Jan!F88 -> 491778860 | E88: =Jan!I88+Feb!I88+Mar!I88 -> 3204266 | F88: =Jan!J88+Feb!J88+Mar!J88 -> 27545895 | G88: =E88-F88 -> -24341629
A89: Sub total - US Currency | D89: =SUM(D82:D88) -> 14253717602 | E89: =SUM(E82:E88) -> 1.0658032e+08 | F89: =SUM(F82:F88) -> 3.9784506e+08 | G89: =SUM(G82:G88) -> -2.9126474e+08
B90: =1+B88 -> 63 | C90: ALFM Euro Bond Fund, Inc. | D90: =Jan!F90 -> 701407386 | E90: =Jan!I90+Feb!I90+Mar!I90 -> 18427084 | F90: =Jan!J90+Feb!J90+Mar!J90 -> 23956912 | G90: =E90-F90 -> -5529828
A91: Sub total - Euro Currency | D91: =SUM(D90) -> 701407386 | E91: =SUM(E90) -> 18427084 | F91: =SUM(F90) -> 23956912 | G91: =SUM(G90) -> -5529828
A92: Sub total - bond funds | D92: =D80+D89+D91 -> 63642090736 | E92: =E80+E89+E91 -> 1034918796 | F92: =F80+F89+F91 -> 2012345386 | G92: =G80+G89+G91 -> -9.7742659e+08
A93: Money Market Funds
A94: Primarily invested in Peso Securities (shares)
B95: =B90+1 -> 64 | C95: AIB Money Market Mutual Fund, Inc. | D95: =Jan!F95 -> 1.7040507e+08 | E95: =Jan!I95+Feb!I95+Mar!I95 -> 922000 | F95: =Jan!J95+Feb!J95+Mar!J95 -> 80394.93 | G95: =E95-F95 -> 841605.07
B96: =1+B95 -> 65 | C96: ALFM Money Market Fund, Inc. | D96: =Jan!F96 -> 21647624859 | E96: =Jan!I96+Feb!I96+Mar!I96 -> 1026581 | F96: =Jan!J96+Feb!J96+Mar!J96 -> 1110241986 | G96: =E96-F96 -> -1109215405
B97: =1+B96 -> 66 | C97: First Metro Save and Learn Money Market Fund, Inc. | D97: =Jan!F97 -> 2564050432 | E97: =Jan!I97+Feb!I97+Mar!I97 -> 243685522 | F97: =Jan!J97+Feb!J97+Mar!J97 -> 479693987 | G97: =E97-F97 -> -236008465
B98: =1+B97 -> 67 | C98: Sun Life Prosperity Peso Starter Fund, Inc. | D98: =Jan!F98 -> 12528477413 | E98: =Jan!I98+Feb!I98+Mar!I98 -> 1570722999 | F98: =Jan!J98+Feb!J98+Mar!J98 -> 1646377308 | G98: =E98-F98 -> -75654309
A99: Primarily invested in Peso Securities (units)
B100: =1+B98 -> 68 | C100: ALFM Money Market Fund, Inc. | D100: =Jan!F100 -> 11298738375 | E100: =Jan!I100+Feb!I100+Mar!I100 -> 2316300480 | F100: =Jan!J100+Feb!J100+Mar!J100 -> 2260442749 | G100: =E100-F100 -> 55857731
A101: Sub total - Peso Currency | D101: =SUM(D95:D100) -> 48209296149 | E101: =SUM(E95:E100) -> 4132657582 | F101: =SUM(F95:F100) -> 5496836425 | G101: =SUM(G95:G100) -> -1364178843
A102: Primarily invested in foreign currency securities (shares)
B103: =1+B100 -> 69 | C103: Sun Life Prosperity Dollar Starter Fund, Inc. | D103: =Jan!F103 -> 2232084615 | E103: =Jan!I103+Feb!I103+Mar!I103 -> 669320283 | F103: =Jan!J103+Feb!J103+Mar!J103 -> 481356071 | G103: =E103-F103 -> 187964212
A104: Sub total - US Currency | D104: =SUM(D103) -> 2232084615 | E104: =SUM(E103) -> 669320283 | F104: =SUM(F103) -> 481356071 | G104: =SUM(G103) -> 187964212
A105: Sub total - money market funds | D105: =D101+D104 -> 50441380764 | E105: =E101+E104 -> 4801977865 | F105: =F101+F104 -> 5978192496 | G105: =G101+G104 -> -1176214631
A106: Feeder Fund
...

Sheet Q1 Updated
A1: PHILIPPINE INVESTMENT FUNDS ASSOCIATION, INC.
A2: MUTUAL FUNDS STATISTICAL REPORT
A3: As of the First Quarter of 2025
A4: (Amounts in Philippine Peso)
A6: Fund Category | C6: Fund Name | D6: NET ASSETS | E6: TOTAL SALES | F6: TOTAL REDEMPTIONS | G6: NET SALES
A7: Stock Funds
A8: Primarily invested in Peso Securities (shares)
B9: 1 | C9: ALFM Growth Fund, Inc. | D9: =Mar!F9 -> 3711094342 | E9: =Jan!I9+Feb!I9+Mar!I9 -> 23921065 | F9: =Jan!J9+Feb!J9+Mar!J9 -> 93648240 | G9: =E9-F9 -> -69727175
B10: =1+B9 -> 2 | C10: ATRAM Alpha Opportunity Fund, Inc. | D10: =Mar!F10 -> 9.8835502e+08 | E10: =Jan!I10+Feb!I10+Mar!I10 -> 61754874 | F10: =Jan!J10+Feb!J10+Mar!J10 -> 37824902 | G10: =E10-F10 -> 23929972
B11: =1+B10 -> 3 | C11: ATRAM Phil. Equity Opportunity Fund, Inc. | D11: =Mar!F11 -> 1045883409 | E11: =Jan!I11+Feb!I11+Mar!I11 -> 16646336 | F11: =Jan!J11+Feb!J11+Mar!J11 -> 29317981 | G11: =E11-F11 -> -12671646
B12: =1+B11 -> 4 | C12: Climbs Share Capital Equity Investment Fund Corp. | D12: =Mar!F12 -> 4.2517445e+08 | E12: =Jan!I12+Feb!I12+Mar!I12 -> 41032623 | F12: =Jan!J12+Feb!J12+Mar!J12 -> 1720904.9 | G12: =E12-F12 -> 39311718
B13: =1+B12 -> 5 | C13: First Metro Consumer Fund, Inc. | D13: =Mar!F13 -> 343569405 | E13: =Jan!I13+Feb!I13+Mar!I13 -> 794954 | F13: =Jan!J13+Feb!J13+Mar!J13 -> 9096934 | G13: =E13-F13 -> -8301980
B14: =1+B13 -> 6 | C14: First Metro Save and Learn Equity Fund, Inc. | D14: =Mar!F14 -> 3013750519 | E14: =Jan!I14+Feb!I14+Mar!I14 -> 40934592 | F14: =Jan!J14+Feb!J14+Mar!J14 -> 122115264 | G14: =E14-F14 -> -81180672
B15: =1+B14 -> 7 | C15: First Metro Save and Learn Phil. Index Fund, Inc. | D15: =Mar!F15 -> 89075403 | E15: =Jan!I15+Feb!I15+Mar!I15 -> 7236629 | F15: =Jan!J15+Feb!J15+Mar!J15 -> 1080702 | G15: =E15-F15 -> 6155927
B16: =1+B15 -> 8 | C16: MBG Equity Investment Fund, Inc. | D16: =Mar!F16 -> 114308864 | E16: =Jan!I16+Feb!I16+Mar!I16 -> 0 | F16: =Jan!J16+Feb!J16+Mar!J16 -> 4270929 | G16: =E16-F16 -> -4270929
B17: =1+B16 -> 9 | C17: PAMI Equity Index Fund, Inc. | D17: =Mar!F17 -> 993047182 | E17: =Jan!I17+Feb!I17+Mar!I17 -> 0 | F17: =Jan!J17+Feb!J17+Mar!J17 -> 20508556 | G17: =E17-F17 -> -20508556
B18: =1+B17 -> 10 | C18: Philam Strategic Growth Fund, Inc. | D18: =Mar!F18 -> 3071755193 | E18: =Jan!I18+Feb!I18+Mar!I18 -> 19633671 | F18: =Jan!J18+Feb!J18+Mar!J18 -> 84434613 | G18: =E18-F18 -> -64800942
B19: =1+B18 -> 11 | C19: Philequity Dividend Yield Fund, Inc. | D19: =Mar!F19 -> 2529088882 | E19: =Jan!I19+Feb!I19+Mar!I19 -> 48247099 | F19: =Jan!J19+Feb!J19+Mar!J19 -> 45672090 | G19: =E19-F19 -> 2575009.4
B20: =1+B19 -> 12 | C20: Philequity Fund, Inc. | D20: =Mar!F20 -> 8786747587 | E20: =Jan!I20+Feb!I20+Mar!I20 -> 91056483 | F20: =Jan!J20+Feb!J20+Mar!J20 -> 1.7821858e+08 | G20: =E20-F20 -> -87162094
B21: =1+B20 -> 13 | C21: Philequity MSCI Phil. Index Fund, Inc. | D21: =Mar!F21 -> 3.0678069e+08 | E21: =Jan!I21+Feb!I21+Mar!I21 -> 1085849.7 | F21: =Jan!J21+Feb!J21+Mar!J21 -> 550060.98 | G21: =E21-F21 -> 535788.75
... B27: =1+B26 -> 19 | C27: United Fund, Inc. | D27: =Mar!F27 -> 516890704 | E27: =Jan!I27+Feb!I27+Mar!I27 -> 1079302.5 | F27: =Jan!J27+Feb!J27+Mar!J27 -> 3082993.2 | G27: =E27-F27 -> -2003690.8
A28: Primarily invested in Peso Securities (units)
B29: =1+B27 -> 20 | C29: COL Equity Index Unitized Mutual Fund, Inc. | D29: =Mar!F29 -> 2.445699e+08 | E29: =Jan!I29+Feb!I29+Mar!I29 -> 39465956 | F29: =Jan!J29+Feb!J29+Mar!J29 -> 15032562 | G29: =E29-F29 -> 24433394
B30: =1+B29 -> 21 | C30: COL Strategic Growth Equity Unitized Mutual Fund, Inc. | D30: =Mar!F30 -> 3.931286e+08 | E30: =Jan!I30+Feb!I30+Mar!I30 -> 43936603 | F30: =Jan!J30+Feb!J30+Mar!J30 -> 29293398 | G30: =E30-F30 -> 14643204
B31: =1+B30 -> 22 | C31: Philequity Alpha One Fund, Inc. | D31: =Mar!F31 -> 2.583644e+08 | E31: =Jan!I31+Feb!I31+Mar!I31 -> 2960185 | F31: =Jan!J31+Feb!J31+Mar!J31 -> 12614178 | G31: =E31-F31 -> -9653992.9
B32: =1+B31 -> 23 | C32: Philippine Stock Index Fund Corp. | D32: =Mar!F32 -> 697069485 | E32: =Jan!I32+Feb!I32+Mar!I32 -> 118944271 | F32: =Jan!J32+Feb!J32+Mar!J32 -> 87638342 | G32: =E32-F32 -> 31305929
A33: Exchange Traded Fund
B34: =1+B32 -> 24 | C34: First Metro Phil. Equity Exchange Traded Fund, Inc. | D34: =Mar!F34 -> 1370368684 | E34: =Jan!I34+Feb!I34+Mar!I34 -> 40232388 | F34: =Jan!J34+Feb!J34+Mar!J34 -> 0 | G34: =E34-F34 -> 40232388
A35: Sub total - Peso Currency | D35: =SUM(D9:D34) -> 55649791867 | E35: =SUM(E9:E34) -> 9.196606e+08 | F35: =SUM(F9:F34) -> 1704261488 | G35: =SUM(G9:G34) -> -7.8460089e+08
A36: Primarily invested in foreign currency securities (shares)
B37: =1+B34 -> 25 | C37: ATRAM AsiaPlus Equity Fund, Inc. | D37: =Mar!F37 -> 27225644 | E37: =Jan!I37+Feb!I37+Mar!I37 -> 104642.2 | F37: =Jan!J37+Feb!J37+Mar!J37 -> 153134.87 | G37: =E37-F37 -> -48492.67
B38: =1+B37 -> 26 | C38: Sun Life Prosperity World Voyager Fund, Inc. | D38: =Mar!F38 -> 1724532086 | E38: =Jan!I38+Feb!I38+Mar!I38 -> 87592931 | F38: =Jan!J38+Feb!J38+Mar!J38 -> 297298701 | G38: =E38-F38 -> -209705770
A39: Sub total - US Currency | D39: =SUM(D37:D38) -> 1751757730 | E39: =SUM(E37:E38) -> 87697573 | F39: =SUM(F37:F38) -> 2.9745184e+08 | G39: =SUM(G37:G38) -> -2.0975426e+08
A40: Sub total - stock funds | D40: =D35+D39 -> 57401549597 | E40: =E35+E39 -> 1007358172 | F40: =F35+F39 -> 2001713324 | G40: =G35+G39 -> -9.9435515e+08
A41: Balanced Funds
A42: Primarily invested in Peso Securities (shares)
B43: =B38+1 -> 27 | C43: ATRAM Philippine Balanced Fund, Inc. | D43: =Mar!F43 -> 3.9984897e+08 | E43: =Jan!I43+Feb!I43+Mar!I43 -> 1623332.6 | F43: =Jan!J43+Feb!J43+Mar!J43 -> 18184513 | G43: =E43-F43 -> -16561181
B44: =B43+1 -> 28 | C44: ATRAM Unicapital Diversified Growth Fund, Inc. | D44: =Mar!F44 -> 1.1142679e+08 | E44: =Jan!I44+Feb!I44+Mar!I44 -> 943427.2 | F44: =Jan!J44+Feb!J44+Mar!J44 -> 1379997.9 | G44: =E44-F44 -> -436570.65
B45: =B44+1 -> 29 | C45: First Metro Save and Learn Balanced Fund, Inc. | D45: =Mar!F45 -> 639516146 | E45: =Jan!I45+Feb!I45+Mar!I45 -> 2362845 | F45: =Jan!J45+Feb!J45+Mar!J45 -> 15534109 | G45: =E45-F45 -> -13171264
B46: =B45+1 -> 30 | C46: First Metro Save and Learn F.O.C.C.U.S. Dynamic Fund, Inc. | D46: =Mar!F46 -> 350888884 | E46: =Jan!I46+Feb!I46+Mar!I46 -> 7075076 | F46: =Jan!J46+Feb!J46+Mar!J46 -> 131374204 | G46: =E46-F46 -> -124299128
B47: =B46+1 -> 31 | C47: NCM Mutual Fund of the Phils., Inc. | D47: =Mar!F47 -> 3.1285512e+08 | E47: =Jan!I47+'Feb UPDATED'!I47+'Mar UPDATED'!I47 -> 2.3662765e+08 | F47: =Jan!J47+'Feb UPDATED'!J47+'Mar UPDATED'!J47 -> 2.3897046e+08 | G47: =E47-F47 -> -2342804.7
B48: =B47+1 -> 32 | C48: PAMI Horizon Fund, Inc. | D48: =Mar!F48 -> 427293829 | E48: =Jan!I48+Feb!I48+Mar!I48 -> 118479 | F48: =Jan!J48+Feb!J48+Mar!J48 -> 18039673 | G48: =E48-F48 -> -17921194
B49: =B48+1 -> 33 | C49: Philam Fund, Inc. | D49: =Mar!F49 -> 1796887824 | E49: =Jan!I49+Feb!I49+Mar!I49 -> 1288051 | F49: =Jan!J49+Feb!J49+Mar!J49 -> 55012556 | G49: =E49-F49 -> -53724505
B50: =B49+1 -> 34 | C50: Solidaritas Fund, Inc. | D50: =Mar!F50 -> 119272260 | E50: =Jan!I50+Feb!I50+Mar!I50 -> 0 | F50: =Jan!J50+Feb!J50+Mar!J50 -> 1672556 | G50: =E50-F50 -> -1672556
B51: =B50+1 -> 35 | C51: Sun Life Prosperity Balanced Fund, Inc. | D51: =Mar!F51 -> 5732274195 | E51: =Jan!I51+Feb!I51+Mar!I51 -> 17544554 | F51: =Jan!J51+Feb!J51+Mar!J51 -> 175967224 | G51: =E51-F51 -> -158422670
B52: =B51+1 -> 36 | C52: Sun Life Prosperity Dynamic Fund, Inc. | D52: =Mar!F52 -> 460711824 | E52: =Jan!I52+Feb!I52+Mar!I52 -> 0 | F52: =Jan!J52+Feb!J52+Mar!J52 -> 24502082 | G52: =E52-F52 -> -24502082
A53: Primarily invested in Peso Securities (units)
B54: =1+B52 -> 37 | C54: Sun Life Prosperity Achiever Fund 2028, Inc. | D54: =Mar!F54 -> 75782333 | E54: =Jan!I54+Feb!I54+Mar!I54 -> 628033 | F54: =Jan!J54+Feb!J54+Mar!J54 -> 1212813 | G54: =E54-F54 -> -584780
B55: =1+B54 -> 38 | C55: Sun Life Prosperity Achiever Fund 2038, Inc. | D55: =Mar!F55 -> 55117807 | E55: =Jan!I55+Feb!I55+Mar!I55 -> 304941 | F55: =Jan!J55+Feb!J55+Mar!J55 -> 186630 | G55: =E55-F55 -> 118311
B56: =1+B55 -> 39 | C56: Sun Life Prosperity Achiever Fund 2048, Inc. | D56: =Mar!F56 -> 46221250 | E56: =Jan!I56+Feb!I56+Mar!I56 -> 205385 | F56: =Jan!J56+Feb!J56+Mar!J56 -> 102227 | G56: =E56-F56 -> 103158
A57: Sub total - Peso Currency | D57: =SUM(D43:D56) -> 10528097230 | E57: =SUM(E43:E56) -> 2.6872178e+08 | F57: =SUM(F43:F56) -> 6.8213904e+08 | G57: =SUM(G43:G56) -> -413417266
A58: Primarily invested in foreign currency securities (shares)
B59: =1+B56 -> 40 | C59: Cocolife Dollar Fund Builder, Inc. | D59: =Mar!F59 -> 61947507 | E59: =Jan!I59+Feb!I59+Mar!I59 -> 0 | F59: =Jan!J59+Feb!J59+Mar!J59 -> 207807.29 | G59: =E59-F59 -> -207807.29
B60: =1+B59 -> 41 | C60: PAMI Asia Balanced Fund, Inc. | D60: =Mar!F60 -> 283667500 | E60: =Jan!I60+Feb!I60+Mar!I60 -> 0 | F60: =Jan!J60+Feb!J60+Mar!J60 -> 21099697 | G60: =E60-F60 -> -21099697
B61: =1+B60 -> 42 | C61: Sun Life Prosperity Dollar Advantage Fund, Inc. | D61: =Mar!F61 -> 1578360549 | E61: =Jan!I61+Feb!I61+Mar!I61 -> 20552846 | F61: =Jan!J61+Feb!J61+Mar!J61 -> 81403794 | G61: =E61-F61 -> -60850948
B62: =1+B61 -> 43 | C62: Sun Life Prosperity Dollar Wellspring Fund, Inc. | D62: =Mar!F62 -> 241247292 | E62: =Jan!I62+Feb!I62+Mar!I62 -> 4909633 | F62: =Jan!J62+Feb!J62+Mar!J62 -> 5305727 | G62: =E62-F62 -> -396094
A63: Sub total - US Currency | D63: =SUM(D59:D62) -> 2165222848 | E63: =SUM(E59:E62) -> 25462479 | F63: =SUM(F59:F62) -> 1.0801703e+08 | G63: =SUM(G59:G62) -> -82554546
A64: Sub total - balanced funds | D64: =D57+D63 -> 12693320078 | E64: =E57+E63 -> 2.9418426e+08 | F64: =F57+F63 -> 7.9015607e+08 | G64: =G57+G63 -> -4.9597181e+08
A65: Bond Funds
A66: Primarily invested in Peso Securities (shares)
B67: =1+B62 -> 44 | C67: ALFM Peso Bond Fund, Inc. | D67: =Mar!F67 -> 34696222346 | E67: =Jan!I67+Feb!I67+Mar!I67 -> 616529217 | F67: =Jan!J67+Feb!J67+Mar!J67 -> 1067324450 | G67: =E67-F67 -> -450795233
B68: =1+B67 -> 45 | C68: ATRAM Corporate Bond Fund, Inc. | D68: =Mar!F68 -> 2.5772214e+08 | E68: =Jan!I68+Feb!I68+Mar!I68 -> 2250151.9 | F68: =Jan!J68+Feb!J68+Mar!J68 -> 21419382 | G68: =E68-F68 -> -19169230
B69: =1+B68 -> 46 | C69: Cocolife Fixed Income Fund, Inc. | D69: =Mar!F69 -> 9.3208908e+08 | E69: =Jan!I69+Feb!I69+Mar!I69 -> 15208319 | F69: =Jan!J69+Feb!J69+Mar!J69 -> 31450950 | G69: =E69-F69 -> -16242631
B70: =1+B69 -> 47 | C70: Ekklesia Mutual Fund, Inc. | D70: =Mar!F70 -> 188174564 | E70: =Jan!I70+Feb!I70+Mar!I70 -> 4998 | F70: =Jan!J70+Feb!J70+Mar!J70 -> 426661 | G70: =E70-F70 -> -421663
B71: =1+B70 -> 48 | C71: First Metro Save and Learn Fixed Income Fund, Inc. | D71: =Mar!F71 -> 1143026309 | E71: =Jan!I71+Feb!I71+Mar!I71 -> 2000407 | F71: =Jan!J71+Feb!J71+Mar!J71 -> 53912628 | G71: =E71-F71 -> -51912221
B72: =1+B71 -> 49 | C72: Philam Bond Fund, Inc. | D72: =Mar!F72 -> 1371573903 | E72: =Jan!I72+Feb!I72+Mar!I72 -> 5652943 | F72: =Jan!J72+Feb!J72+Mar!J72 -> 45170819 | G72: =E72-F72 -> -39517876
B73: =1+B72 -> 50 | C73: Philam Managed Income Fund, Inc. | D73: =Mar!F73 -> 603442463 | E73: =Jan!I73+Feb!I73+Mar!I73 -> 0 | F73: =Jan!J73+Feb!J73+Mar!J73 -> 20407108 | G73: =E73-F73 -> -20407108
B74: =1+B73 -> 51 | C74: Philequity Peso Bond Fund, Inc. | D74: =Mar!F74 -> 333601483 | E74: =Jan!I74+Feb!I74+Mar!I74 -> 8272153.6 | F74: =Jan!J74+Feb!J74+Mar!J74 -> 3785103.2 | G74: =E74-F74 -> 4487050.4
B75: =1+B74 -> 52 | C75: Soldivo Bond Fund, Inc. | D75: =Mar!F75 -> 1883015190 | E75: =Jan!I75+Feb!I75+Mar!I75 -> 77712609 | F75: =Jan!J75+Feb!J75+Mar!J75 -> 5565167 | G75: =E75-F75 -> 72147442
B76: =1+B75 -> 53 | C76: Sun Life Prosperity Bond Fund, Inc. | D76: =Mar!F76 -> 6432279467 | E76: =Jan!I76+Feb!I76+Mar!I76 -> 179914337 | F76: =Jan!J76+Feb!J76+Mar!J76 -> 332806134 | G76: =E76-F76 -> -152891797
B77: =1+B76 -> 54 | C77: Sun Life Prosperity GS Fund, Inc. | D77: =Mar!F77 -> 145442284 | E77: =Jan!I77+Feb!I77+Mar!I77 -> 2366258 | F77: =Jan!J77+Feb!J77+Mar!J77 -> 8275016 | G77: =E77-F77 -> -5908758
A78: Corporat e Debt Vehicle (units)
B79: =1+B77 -> 55 | C79: ATRAM Unitized Corporate Debt Vehicle, Inc. | D79: =Mar!F79 -> 7.0712127e+08 | E79: =Jan!I79+Feb!I79+Mar!I79 -> 0 | F79: =Jan!J79+Feb!J79+Mar!J79 -> 0 | G79: =E79-F79 -> 0
A80: Sub total - Peso Currency | D80: =SUM(D67:D79) -> 48693710503 | E80: =SUM(E67:E79) -> 9.0991139e+08 | F80: =SUM(F67:F79) -> 1590543417 | G80: =SUM(G67:G79) -> -680632024
A81: Primarily invested in foreign currency securities (shares)
B82: =1+B79 -> 56 | C82: ALFM Dollar Bond Fund, Inc. | D82: =Mar!F82 -> 11524486240 | E82: =Jan!I82+Feb!I82+Mar!I82 -> 84041745 | F82: =Jan!J82+Feb!J82+Mar!J82 -> 302572746 | G82: =E82-F82 -> -218531001
B83: =1+B82 -> 57 | C83: ATRAM Total Return Dollar Bond Fund, Inc. | D83: =Mar!F83 -> 1.1232631e+08 | E83: =Jan!I83+Feb!I83+Mar!I83 -> 18590524 | F83: =Jan!J83+Feb!J83+Mar!J83 -> 2683522.4 | G83: =E83-F83 -> 15907002
B84: =1+B83 -> 58 | C84: First Metro Save and Learn Dollar Bond Fund, Inc. | D84: =Mar!F84 -> 317411111 | E84: =Jan!I84+Feb!I84+Mar!I84 -> 186598 | F84: =Jan!J84+Feb!J84+Mar!J84 -> 2292229 | G84: =E84-F84 -> -2105631
B85: =1+B84 -> 59 | C85: PAMI Global Bond Fund, Inc. | D85: =Mar!F85 -> 51203288 | E85: =Jan!I85+Feb!I85+Mar!I85 -> 0 | F85: =Jan!J85+Feb!J85+Mar!J85 -> 0 | G85: =E85-F85 -> 0
B86: =1+B85 -> 60 | C86: Philam Dollar Bond Fund, Inc. | D86: =Mar!F86 -> 1632696840 | E86: =Jan!I86+Feb!I86+Mar!I86 -> 159620 | F86: =Jan!J86+Feb!J86+Mar!J86 -> 62750664 | G86: =E86-F86 -> -62591044
B87: =1+B86 -> 61 | C87: Philequity Dollar Income Fund, Inc. | D87: =Mar!F87 -> 225423299 | E87: =Jan!I87+Feb!I87+Mar!I87 -> 397566 | F87: =Jan!J87+Feb!J87+Mar!J87 -> 0 | G87: =E87-F87 -> 397566
B88: =1+B87 -> 62 | C88: Sun Life Prosperity Dollar Abundance Fund, Inc. | D88: =Mar!F88 -> 469965258 | E88: =Jan!I88+Feb!I88+Mar!I88 -> 3204266 | F88: =Jan!J88+Feb!J88+Mar!J88 -> 27545895 | G88: =E88-F88 -> -24341629
A89: Sub total - US Currency | D89: =SUM(D82:D88) -> 14333512345 | E89: =SUM(E82:E88) -> 1.0658032e+08 | F89: =SUM(F82:F88) -> 3.9784506e+08 | G89: =SUM(G82:G88) -> -2.9126474e+08
B90: =1+B88 -> 63 | C90: ALFM Euro Bond Fund, Inc. | D90: =Mar!F90 -> 711287144 | E90: =Jan!I90+Feb!I90+Mar!I90 -> 18427084 | F90: =Jan!J90+Feb!J90+Mar!J90 -> 23956912 | G90: =E90-F90 -> -5529828
A91: Sub total - Euro Currency | D91: =SUM(D90) -> 711287144 | E91: =SUM(E90) -> 18427084 | F91: =SUM(F90) -> 23956912 | G91: =SUM(G90) -> -5529828
A92: Sub total - bond funds | D92: =D80+D89+D91 -> 63738509992 | E92: =E80+E89+E91 -> 1034918796 | F92: =F80+F89+F91 -> 2012345386 | G92: =G80+G89+G91 -> -9.7742659e+08
A93: Money Market Funds
A94: Primarily invested in Peso Securities (shares)
B95: =B90+1 -> 64 | C95: AIB Money Market Mutual Fund, Inc. | D95: =Mar!F95 -> 1.7210077e+08 | E95: =Jan!I95+Feb!I95+Mar!I95 -> 922000 | F95: =Jan!J95+Feb!J95+Mar!J95 -> 80394.93 | G95: =E95-F95 -> 841605.07
B96: =1+B95 -> 65 | C96: ALFM Money Market Fund, Inc. | D96: =Mar!F96 -> 21158209470 | E96: =Jan!I96+Feb!I96+Mar!I96 -> 1026581 | F96: =Jan!J96+Feb!J96+Mar!J96 -> 1110241986 | G96: =E96-F96 -> -1109215405
B97: =1+B96 -> 66 | C97: First Metro Save and Learn Money Market Fund, Inc. | D97: =Mar!F97 -> 2543120824 | E97: =Jan!I97+Feb!I97+Mar!I97 -> 243685522 | F97: =Jan!J97+Feb!J97+Mar!J97 -> 479693987 | G97: =E97-F97 -> -236008465
B98: =1+B97 -> 67 | C98: Sun Life Prosperity Peso Starter Fund, Inc. | D98: =Mar!F98 -> 12427654806 | E98: =Jan!I98+Feb!I98+Mar!I98 -> 1570722999 | F98: =Jan!J98+Feb!J98+Mar!J98 -> 1646377308 | G98: =E98-F98 -> -75654309
A99: Primarily invested in Peso Securities (units)
B100: =1+B98 -> 68 | C100: ALFM Money Market Fund, Inc. | D100: =Mar!F100 -> 11573891724 | E100: =Jan!I100+Feb!I100+Mar!I100 -> 2316300480 | F100: =Jan!J100+Feb!J100+Mar!J100 -> 2260442749 | G100: =E100-F100 -> 55857731
A101: Sub total - Peso Currency | D101: =SUM(D95:D100) -> 47874977594 | E101: =SUM(E95:E100) -> 4132657582 | F101: =SUM(F95:F100) -> 5496836425 | G101: =SUM(G95:G100) -> -1364178843
A102: Primarily invested in foreign currency securities (shares)
B103: =1+B100 -> 69 | C103: Sun Life Prosperity Dollar Starter Fund, Inc. | D103: =Mar!F103 -> 2511273991 | E103: =Jan!I103+Feb!I103+Mar!I103 -> 669320283 | F103: =Jan!J103+Feb!J103+Mar!J103 -> 481356071 | G103: =E103-F103 -> 187964212
A104: Sub total - US Currency | D104: =SUM(D103) -> 2511273991 | E104: =SUM(E103) -> 669320283 | F104: =SUM(F103) -> 481356071 | G104: =SUM(G103) -> 187964212
A105: Sub total - money market funds | D105: =D101+D104 -> 50386251585 | E105: =E101+E104 -> 4801977865 | F105: =F101+F104 -> 5978192496 | G105: =G101+G104 -> -1176214631
A106: Feeder Fund
...

Sheet Apr
A1: PHILIPPINE INVESTMENT FUNDS ASSOCIATION, INC.
A2: MUTUAL FUNDS STATISTICAL REPORT
A3: Month of April 2025
A4: (Amounts in Peso)
I5: F O R - T H E - M O N T H | L5: Y E A R - T O - D A T E
A6: Fund Category | C6: Fund Name | D6: ASSETS | E6: LIABILITIES | F6: NET ASSETS | G6: EQUITY INV. | H6: NO. OF A/C | I6: SALES | J6: REDEMPTIONS | K6: NET SALES | L6: TOTAL SALES | M6: TOTAL REDEMPTIONS | N6: TOTAL NET SALES
A7: Stock Funds
A8: Primarily invested in Peso Securities (shares)
B9: 1 | C9: ALFM Growth Fund, Inc. | D9: 3781393446 | E9: 8017652 | F9: =D9-E9 -> 3773375794 | G9: 3681692215 | H9: 5757 | I9: 12733903 | J9: 39496012 | K9: =I9-J9 -> -26762109 | L9: =I9+Mar!L9 -> 36654968 | M9: =J9+Mar!M9 -> 133144252 | N9: =L9-M9 -> -96489284
B10: =1+B9 -> 2 | C10: ATRAM Alpha Opportunity Fund, Inc. | D10: 1.0492816e+09 | E10: 15294192 | F10: =D10-E10 -> 1033987359 | G10: 9.6252545e+08 | H10: 4172 | I10: 35163137 | J10: 13024348 | K10: =I10-J10 -> 22138789 | L10: =I10+Mar!L10 -> 96918012 | M10: =J10+Mar!M10 -> 50849250 | N10: =L10-M10 -> 46068762
B11: =1+B10 -> 3 | C11: ATRAM Phil. Equity Opportunity Fund, Inc. | D11: 1.0857059e+09 | E11: 25301834 | F11: =D11-E11 -> 1060404090 | G11: 1.0069916e+09 | H11: 2465 | I11: 3932979.5 | J11: 18589293 | K11: =I11-J11 -> -14656314 | L11: =I11+Mar!L11 -> 20579315 | M11: =J11+Mar!M11 -> 47907275 | N11: =L11-M11 -> -27327959
B12: =1+B11 -> 4 | C12: Climbs Share Capital Equity Investment Fund Corp. | D12: 4.4922584e+08 | E12: 12031024 | F12: =D12-E12 -> 437194817 | G12: 4.0373036e+08 | H12: 1721 | I12: 4086858.2 | J12: 84571.19 | K12: =I12-J12 -> 4002287.1 | L12: =I12+Mar!L12 -> 45119482 | M12: =J12+Mar!M12 -> 1805476.1 | N12: =L12-M12 -> 43314006
B13: =1+B12 -> 5 | C13: First Metro Consumer Fund, Inc. | D13: 355030859 | E13: 5152327 | F13: =D13-E13 -> 349878532 | G13: 305677623 | H13: 1138 | I13: 569472 | J13: 3121583 | K13: =I13-J13 -> -2552111 | L13: =I13+Mar!L13 -> 1364426 | M13: =J13+Mar!M13 -> 12218517 | N13: =L13-M13 -> -10854091
B14: =1+B13 -> 6 | C14: First Metro Save and Learn Equity Fund, Inc. | D14: 3135063512 | E14: 54907899 | F14: =D14-E14 -> 3080155613 | G14: 2870098732 | H14: 14300 | I14: 10575616 | J14: 40500323 | K14: =I14-J14 -> -29924707 | L14: =I14+Mar!L14 -> 51510208 | M14: =J14+Mar!M14 -> 162615587 | N14: =L14-M14 -> -111105379
B15: =1+B14 -> 7 | C15: First Metro Save and Learn Phil. Index Fund, Inc. | D15: 95443997 | E15: 375044 | F15: =D15-E15 -> 95068953 | G15: 93761945 | H15: 476 | I15: 3612599 | J15: 174654 | K15: =I15-J15 -> 3437945 | L15: =I15+Mar!L15 -> 10849228 | M15: =J15+Mar!M15 -> 1255356 | N15: =L15-M15 -> 9593872
B16: =1+B15 -> 8 | C16: MBG Equity Investment Fund, Inc. | D16: 115352749 | E16: 1241419 | F16: =D16-E16 -> 114111330 | G16: 111251971 | H16: 42 | I16: 0 | J16: 0 | K16: =I16-J16 -> 0 | L16: =I16+Mar!L16 -> 0 | M16: =J16+Mar!M16 -> 4270929 | N16: =L16-M16 -> -4270929
B17: =1+B16 -> 9 | C17: PAMI Equity Index Fund, Inc. | D17: 1036433152 | E17: 24479721 | F17: =D17-E17 -> 1011953431 | G17: 1023908961 | H17: 10908 | I17: 1459 | J17: 10020506 | K17: =I17-J17 -> -10019047 | L17: =I17+Mar!L17 -> 1459 | M17: =J17+Mar!M17 -> 30529062 | N17: =L17-M17 -> -30527603
B18: =1+B17 -> 10 | C18: Philam Strategic Growth Fund, Inc. | D18: 3123840688 | E18: 16630308 | F18: =D18-E18 -> 3107210380 | G18: 3058764861 | H18: 10619 | I18: 6747291 | J18: 46384344 | K18: =I18-J18 -> -39637053 | L18: =I18+Mar!L18 -> 26380962 | M18: =J18+Mar!M18 -> 130818957 | N18: =L18-M18 -> -104437995
B19: =1+B18 -> 11 | C19: Philequity Dividend Yield Fund, Inc. | D19: 2.5219818e+09 | E19: 8226605.8 | F19: =D19-E19 -> 2513755177 | G19: 2.2616162e+09 | H19: 5006 | I19: 16034654 | J19: 20877486 | K19: =I19-J19 -> -4842832.4 | L19: =I19+Mar!L19 -> 64281753 | M19: =J19+Mar!M19 -> 66549576 | N19: =L19-M19 -> -2267822.9
B20: =1+B19 -> 12 | C20: Philequity Fund, Inc. | D20: 9.0989579e+09 | E20: 87398023 | F20: =D20-E20 -> 9011559892 | G20: 8.6149475e+09 | H20: 31553 | I20: 7592710 | J20: 47670890 | K20: =I20-J20 -> -40078179 | L20: =I20+Mar!L20 -> 98649193 | M20: =J20+Mar!M20 -> 225889466 | N20: =L20-M20 -> -1.2724027e+08
B21: =1+B20 -> 13 | C21: Philequity MSCI Phil. Index Fund, Inc. | D21: 3.1556042e+08 | E21: 809018.15 | F21: =D21-E21 -> 3.147514e+08 | G21: 3.1263768e+08 | H21: 873 | I21: 224540.34 | J21: 91927.05 | K21: =I21-J21 -> 132613.29 | L21: =I21+Mar!L21 -> 1310390.1 | M21: =J21+Mar!M21 -> 641988.03 | N21: =L21-M21 -> 668402.04
... B27: =1+B26 -> 19 | C27: United Fund, Inc. | D27: 5.1795992e+08 | E27: 2155077.9 | F27: =D27-E27 -> 5.1580485e+08 | G27: 4.9312501e+08 | H27: 1192 | I27: 197614.52 | J27: 660955.73 | K27: =I27-J27 -> -463341.21 | L27: =I27+Mar!L27 -> 1276917 | M27: =J27+Mar!M27 -> 3743949 | N27: =L27-M27 -> -2467032
A28: Primarily invested in Peso Securities (units) | M28: =J28+Mar!M28 -> 0
B29: =1+B27 -> 20 | C29: COL Equity Index Unitized Mutual Fund, Inc. | D29: 2.6330406e+08 | E29: 552262.39 | F29: =D29-E29 -> 262751793 | G29: 2.495822e+08 | H29: 4694 | I29: 11208864 | J29: 695253.53 | K29: =I29-J29 -> 10513610 | L29: =I29+Mar!L29 -> 50674819 | M29: =J29+Mar!M29 -> 15727815 | N29: =L29-M29 -> 34947004
B30: =1+B29 -> 21 | C30: COL Strategic Growth Equity Unitized Mutual Fund, Inc. | D30: 4.251626e+08 | E30: 17611625 | F30: =D30-E30 -> 4.0755098e+08 | G30: 3.5271508e+08 | H30: 6402 | I30: 9314311.8 | J30: 8291402.3 | K30: =I30-J30 -> 1022909.5 | L30: =I30+Mar!L30 -> 53250915 | M30: =J30+Mar!M30 -> 37584801 | N30: =L30-M30 -> 15666114
B31: =1+B30 -> 22 | C31: Philequity Alpha One Fund, Inc. | D31: 2.6545584e+08 | E31: 4344082.1 | F31: =D31-E31 -> 2.6111176e+08 | G31: 2.5634432e+08 | H31: 1129 | I31: 202760.01 | J31: 1629966.7 | K31: =I31-J31 -> -1427206.7 | L31: =I31+Mar!L31 -> 3162945 | M31: =J31+Mar!M31 -> 14244145 | N31: =L31-M31 -> -11081200
B32: =1+B31 -> 23 | C32: Philippine Stock Index Fund Corp. | D32: 732080463 | E32: 4926986 | F32: =D32-E32 -> 727153477 | G32: 721434787 | H32: 765709 | I32: 16344644 | J32: 7492576 | K32: =I32-J32 -> 8852068 | L32: =I32+Mar!L32 -> 135288915 | M32: =J32+Mar!M32 -> 95130918 | N32: =L32-M32 -> 40157997
A33: Exchange Traded Fund
B34: =1+B32 -> 24 | C34: First Metro Phil. Equity Exchange Traded Fund, Inc. | D34: 1423522859 | E34: 1743807 | F34: =D34-E34 -> 1421779052 | G34: 1420845762 | H34: 3275 | I34: 10024960 | J34: 0 | K34: =I34-J34 -> 10024960 | L34: =I34+Mar!L34 -> 50257348 | M34: =J34+Mar!M34 -> 0 | N34: =L34-M34 -> 50257348
A35: Sub total - Peso Currency | D35: =SUM(D9:D34) -> 57210233587 | E35: =SUM(E9:E34) -> 5.1043151e+08 | F35: =SUM(F9:F34) -> 56699802073 | G35: =SUM(G9:G34) -> 54962988302 | H35: =SUM(H9:H34) -> 1044149 | I35: =SUM(I9:I34) -> 2.2201146e+08 | J35: =SUM(J9:J34) -> 6.0589958e+08 | K35: =SUM(K9:K34) -> -3.8388813e+08 | ... N35: =SUM(N9:N34) -> -1168489016
A36: Primarily invested in foreign currency securities (shares)
B37: =1+B34 -> 25 | C37: ATRAM AsiaPlus Equity Fund, Inc. | D37: 26627273 | E37: 194484.02 | F37: =D37-E37 -> 26432789 | G37: 0 | H37: 50 | I37: 0 | J37: 0 | K37: =I37-J37 -> 0 | L37: =I37+Mar!L37 -> 104642.2 | M37: =J37+Mar!M37 -> 153134.87 | N37: =L37-M37 -> -48492.67
B38: =1+B37 -> 26 | C38: Sun Life Prosperity World Voyager Fund, Inc. | D38: 1663171690 | E38: 10652492 | F38: =D38-E38 -> 1652519198 | G38: 0 | H38: 3224 | I38: 12590455 | J38: 28193491 | K38: =I38-J38 -> -15603036 | L38: =I38+Mar!L38 -> 100183386 | M38: =J38+Mar!M38 -> 325492192 | N38: =L38-M38 -> -225308806
A39: Sub total - US Currency | D39: =SUM(D37:D38) -> 1689798963 | E39: =SUM(E37:E38) -> 10846976 | F39: =SUM(F37:F38) -> 1678951987 | G39: =SUM(G37:G38) -> 0 | H39: =SUM(H37:H38) -> 3274 | I39: =SUM(I37:I38) -> 12590455 | J39: =SUM(J37:J38) -> 28193491 | K39: =SUM(K37:K38) -> -15603036 | ... N39: =SUM(N37:N38) -> -2.253573e+08
A40: Sub total - stock funds | D40: =D35+D39 -> 58900032550 | E40: =E35+E39 -> 5.2127849e+08 | F40: =F35+F39 -> 58378754061 | G40: =G35+G39 -> 54962988302 | H40: =H35+H39 -> 1047423 | I40: =I35+I39 -> 2.3460191e+08 | J40: =J35+J39 -> 6.3409307e+08 | K40: =K35+K39 -> -3.9949116e+08 | ... N40: =N35+N39 -> -1393846314
A41: Balanced Funds
A42: Primarily invested in Peso Securities (shares)
B43: =1+B38 -> 27 | C43: ATRAM Philippine Balanced Fund, Inc. | D43: 4.5648035e+08 | E43: 49777941 | F43: =D43-E43 -> 4.0670241e+08 | G43: 1.7666985e+08 | H43: 2316 | I43: 462867.68 | J43: 1125112.5 | K43: =I43-J43 -> -662244.85 | L43: =I43+Mar!L43 -> 2086200.2 | M43: =J43+Mar!M43 -> 19309626 | N43: =L43-M43 -> -17223426
B44: =1+B43 -> 28 | C44: ATRAM Unicapital Diversified Growth Fund, Inc. | D44: 1.1810648e+08 | E44: 6283054.2 | F44: =D44-E44 -> 1.1182343e+08 | G44: 24861066 | H44: 808 | I44: 230094.89 | J44: 158918.92 | K44: =I44-J44 -> 71175.97 | L44: =I44+Mar!L44 -> 1173522.1 | M44: =J44+Mar!M44 -> 1538916.8 | N44: =L44-M44 -> -365394.68
B45: =1+B44 -> 29 | C45: First Metro Save and Learn Balanced Fund, Inc. | D45: 663735356 | E45: 22879598 | F45: =D45-E45 -> 640855758 | G45: 279521349 | H45: 4057 | I45: 991049 | J45: 7662106 | K45: =I45-J45 -> -6671057 | L45: =I45+Mar!L45 -> 3353894 | M45: =J45+Mar!M45 -> 23196215 | N45: =L45-M45 -> -19842321
B46: =1+B45 -> 30 | C46: First Metro Save and Learn F.O.C.C.U.S. Dynamic Fund, Inc. | D46: 360012532 | E46: 1164673 | F46: =D46-E46 -> 358847859 | G46: 241984614 | H46: 369 | I46: 12975570 | J46: 8486273 | K46: =I46-J46 -> 4489297 | L46: =I46+Mar!L46 -> 20050646 | M46: =J46+Mar!M46 -> 139860477 | N46: =L46-M46 -> -119809831
B47: =1+B46 -> 31 | C47: NCM Mutual Fund of the Phils., Inc. | D47: 3.1905696e+08 | E47: 822945.75 | F47: =D47-E47 -> 3.1823401e+08 | G47: 1.5689823e+08 | H47: 46 | I47: 0 | J47: 0 | K47: =I47-J47 -> 0 | L47: =I47+'Mar UPDATED'!L47 -> 2.3662765e+08 | M47: =J47+'Mar UPDATED'!M47 -> 2.3897046e+08 | N47: =L47-M47 -> -2342804.7
B48: =1+B47 -> 32 | C48: PAMI Horizon Fund, Inc. | D48: 438590188 | E48: 14232159 | F48: =D48-E48 -> 424358029 | G48: 218034265 | H48: 9587 | I48: 35053 | J48: 9114576 | K48: =I48-J48 -> -9079523 | L48: =I48+Mar!L48 -> 153532 | M48: =J48+Mar!M48 -> 27154249 | N48: =L48-M48 -> -27000717
B49: =1+B48 -> 33 | C49: Philam Fund, Inc. | D49: 1829427102 | E49: 13422653 | F49: =D49-E49 -> 1816004449 | G49: 902325939 | H49: 7136 | I49: 394320 | J49: 11354380 | K49: =I49-J49 -> -10960060 | L49: =I49+Mar!L49 -> 1682371 | M49: =J49+Mar!M49 -> 66366936 | N49: =L49-M49 -> -64684565
B50: =1+B49 -> 34 | C50: Solidaritas Fund, Inc. | D50: 121141371 | E50: 154320 | F50: =D50-E50 -> 120987051 | G50: 59344200 | H50: 158 | I50: 0 | J50: 50322 | K50: =I50-J50 -> -50322 | L50: =I50+Mar!L50 -> 0 | M50: =J50+Mar!M50 -> 1722878 | N50: =L50-M50 -> -1722878
B51: =1+B50 -> 35 | C51: Sun Life Prosperity Balanced Fund, Inc. | D51: 5854958167 | E51: 126563514 | F51: =D51-E51 -> 5728394653 | G51: 2917244914 | H51: 54694 | I51: 4697854 | J51: 69622386 | K51: =I51-J51 -> -64924532 | L51: =I51+Mar!L51 -> 22242408 | M51: =J51+Mar!M51 -> 245589610 | N51: =L51-M51 -> -223347202
B52: =1+B51 -> 36 | C52: Sun Life Prosperity Dynamic Fund, Inc. | D52: 473357552 | E52: 15222206 | F52: =D52-E52 -> 458135346 | G52: 242567194 | H52: 5000 | I52: 0 | J52: 7392983 | K52: =I52-J52 -> -7392983 | L52: =I52+Mar!L52 -> 0 | M52: =J52+Mar!M52 -> 31895065 | N52: =L52-M52 -> -31895065
A53: Primarily invested in Peso Securities (units)
B54: =1+B52 -> 37 | C54: Sun Life Prosperity Achiever Fund 2028, Inc. | D54: 76452468 | E54: 473688 | F54: =D54-E54 -> 75978780 | G54: 15801166 | H54: 1260 | I54: 157161 | J54: 492465 | K54: =I54-J54 -> -335304 | L54: =I54+Mar!L54 -> 785194 | M54: =J54+Mar!M54 -> 1705278 | N54: =L54-M54 -> -920084
B55: =1+B54 -> 38 | C55: Sun Life Prosperity Achiever Fund 2038, Inc. | D55: 56635875 | E55: 304651 | F55: =D55-E55 -> 56331224 | G55: 39713109 | H55: 513 | I55: 159860 | J55: 4331 | K55: =I55-J55 -> 155529 | L55: =I55+Mar!L55 -> 464801 | M55: =J55+Mar!M55 -> 190961 | N55: =L55-M55 -> 273840
B56: =1+B55 -> 39 | C56: Sun Life Prosperity Achiever Fund 2048, Inc. | D56: 47610432 | E56: 286769 | F56: =D56-E56 -> 47323663 | G56: 38638096 | H56: 249 | I56: 49000 | J56: 27648 | K56: =I56-J56 -> 21352 | L56: =I56+Mar!L56 -> 254385 | M56: =J56+Mar!M56 -> 129875 | N56: =L56-M56 -> 124510
A57: Sub total - Peso Currency | D57: =SUM(D43:D56) -> 10815564833 | E57: =SUM(E42:E56) -> 2.5158817e+08 | F57: =SUM(F43:F56) -> 10563976661 | G57: =SUM(G43:G56) -> 5313603994 | H57: =SUM(H43:H56) -> 86193 | I57: =SUM(I42:I56) -> 20152830 | J57: =SUM(J43:J56) -> 1.154915e+08 | K57: =SUM(K43:K56) -> -95338672 | L57: =SUM(L43:L56) -> 2.8887461e+08 | M57: =SUM(M43:M56) -> 7.9763055e+08 | N57: =SUM(N43:N56) -> -5.0875594e+08
A58: Primarily invested in foreign currency securities (shares)
B59: =1+B56 -> 40 | C59: Cocolife Dollar Fund Builder, Inc. | D59: 60436466 | E59: 310599.95 | F59: =D59-E59 -> 60125866 | G59: 0 | H59: 48 | I59: 0 | J59: 0 | K59: =I59-J59 -> 0 | L59: =I59+Mar!L59 -> 0 | M59: =J59+Mar!M59 -> 207807.29 | N59: =L59-M59 -> -207807.29
B60: =1+B59 -> 41 | C60: PAMI Asia Balanced Fund, Inc. | D60: 298510159 | E60: 17282932 | F60: =D60-E60 -> 281227227 | G60: 152044538 | H60: 210 | I60: 0 | J60: 49211 | K60: =I60-J60 -> -49211 | L60: =I60+Mar!L60 -> 0 | M60: =J60+Mar!M60 -> 21148908 | N60: =L60-M60 -> -21148908
B61: =1+B60 -> 42 | C61: Sun Life Prosperity Dollar Advantage Fund, Inc. | D61: 1545730994 | E61: 16120879 | F61: =D61-E61 -> 1529610115 | G61: 0 | H61: 4290 | I61: 2184426 | J61: 16740928 | K61: =I61-J61 -> -14556502 | L61: =I61+Mar!L61 -> 22737272 | M61: =J61+Mar!M61 -> 98144722 | N61: =L61-M61 -> -75407450
B62: =1+B61 -> 43 | C62: Sun Life Prosperity Dollar Wellspring Fund, Inc. | D62: 233421722 | E62: 1167052 | F62: =D62-E62 -> 232254670 | G62: 0 | H62: 772 | I62: 0 | J62: 5024805 | K62: =I62-J62 -> -5024805 | L62: =I62+Mar!L62 -> 4909633 | M62: =J62+Mar!M62 -> 10330532 | N62: =L62-M62 -> -5420899
A63: Sub total - US Currency | D63: =SUM(D59:D62) -> 2138099341 | E63: =SUM(E59:E62) -> 34881463 | F63: =SUM(F59:F62) -> 2103217878 | G63: =SUM(G59:G62) -> 152044538 | H63: =SUM(H59:H62) -> 5320 | I63: =SUM(I59:I62) -> 2184426 | J63: =SUM(J59:J62) -> 21814944 | K63: =SUM(K59:K62) -> -19630518 | ... N63: =SUM(N59:N62) -> -1.0218506e+08
A64: Sub total - balanced funds | D64: =D57+D63 -> 12953664174 | E64: =E57+E63 -> 2.8646964e+08 | F64: =F57+F63 -> 12667194539 | G64: =G57+G63 -> 5465648532 | H64: =H57+H63 -> 91513 | I64: =I57+I63 -> 22337256 | J64: =J57+J63 -> 1.3730645e+08 | K64: =K57+K63 -> -1.1496919e+08 | ... N64: =N57+N63 -> -6.10941e+08
A65: Bond Funds
A66: Primarily invested in Peso Securities (shares)
B67: =1+B62 -> 44 | C67: ALFM Peso Bond Fund, Inc. | D67: 35307928469 | E67: 586334077 | F67: =D67-E67 -> 34721594392 | G67: 266250000 | H67: 24171 | I67: 131744544 | J67: 245029735 | K67: =I67-J67 -> -113285191 | L67: =I67+Mar!L67 -> 748273761 | M67: =J67+Mar!M67 -> 1312354185 | N67: =L67-M67 -> -564080424
B68: =1+B67 -> 45 | C68: ATRAM Corporate Bond Fund, Inc. | D68: 2.591585e+08 | E68: 1575812 | F68: =D68-E68 -> 2.5758269e+08 | G68: 0 | H68: 924 | I68: 263993.77 | J68: 1095657.9 | K68: =I68-J68 -> -831664.1 | L68: =I68+Mar!L68 -> 2514145.6 | M68: =J68+Mar!M68 -> 22515039 | N68: =L68-M68 -> -20000894
B69: =1+B68 -> 46 | C69: Cocolife Fixed Income Fund, Inc. | D69: 9.4286755e+08 | E69: 10501342 | F69: =D69-E69 -> 9.3236621e+08 | G69: 0 | H69: 1802 | I69: 11647385 | J69: 13097786 | K69: =I69-J69 -> -1450401 | L69: =I69+Mar!L69 -> 26855704 | M69: =J69+Mar!M69 -> 44548736 | N69: =L69-M69 -> -17693032
B70: =1+B69 -> 47 | C70: Ekklesia Mutual Fund, Inc. | D70: 188549286 | E70: 180415 | F70: =D70-E70 -> 188368871 | G70: 0 | H70: 134 | I70: 0 | J70: 0 | K70: =I70-J70 -> 0 | L70: =I70+Mar!L70 -> 4998 | M70: =J70+Mar!M70 -> 426661 | N70: =L70-M70 -> -421663
B71: =1+B70 -> 48 | C71: First Metro Save and Learn Fixed Income Fund, Inc. | D71: 1011556051 | E71: 4895216 | F71: =D71-E71 -> 1006660835 | G71: 0 | H71: 1705 | I71: 345033 | J71: 139551873 | K71: =I71-J71 -> -139206840 | L71: =I71+Mar!L71 -> 2345440 | M71: =J71+Mar!M71 -> 193464501 | N71: =L71-M71 -> -191119061
B72: =1+B71 -> 49 | C72: Philam Bond Fund, Inc. | D72: 1400661046 | E72: 32460286 | F72: =D72-E72 -> 1368200760 | G72: 0 | H72: 4530 | I72: 1035076 | J72: 12234510 | K72: =I72-J72 -> -11199434 | L72: =I72+Mar!L72 -> 6688019 | M72: =J72+Mar!M72 -> 57405329 | N72: =L72-M72 -> -50717310
B73: =1+B72 -> 50 | C73: Philam Managed Income Fund, Inc. | D73: 614217699 | E73: 10052656 | F73: =D73-E73 -> 604165043 | G73: 0 | H73: 395 | I73: 0 | J73: 1275977 | K73: =I73-J73 -> -1275977 | L73: =I73+Mar!L73 -> 0 | M73: =J73+Mar!M73 -> 21683085 | N73: =L73-M73 -> -21683085
B74: =1+B73 -> 51 | C74: Philequity Peso Bond Fund, Inc. | D74: 3.3647355e+08 | E74: 1706755.2 | F74: =D74-E74 -> 3.347668e+08 | G74: 0 | H74: 3966 | I74: 1527474.5 | J74: 1238493.1 | K74: =I74-J74 -> 288981.34 | L74: =I74+Mar!L74 -> 9799628.1 | M74: =J74+Mar!M74 -> 5023596.4 | N74: =L74-M74 -> 4776031.8
B75: =1+B74 -> 52 | C75: Soldivo Bond Fund, Inc. | D75: 2.2943188e+09 | E75: 4.0741751e+08 | F75: =D75-E75 -> 1886901339 | G75: 0 | H75: 780 | I75: 2181400 | J75: 4387067.6 | K75: =I75-J75 -> -2205667.6 | L75: =I75+Mar!L75 -> 79894009 | M75: =J75+Mar!M75 -> 9952234.6 | N75: =L75-M75 -> 69941774
B76: =1+B75 -> 53 | C76: Sun Life Prosperity Bond Fund, Inc. | D76: 6680359388 | E76: 179130897 | F76: =D76-E76 -> 6501228491 | G76: 0 | H76: 19473 | I76: 241564144 | J76: 186827782 | K76: =I76-J76 -> 54736362 | L76: =I76+Mar!L76 -> 421478481 | M76: =J76+Mar!M76 -> 519633916 | N76: =L76-M76 -> -98155435
B77: =1+B76 -> 54 | C77: Sun Life Prosperity GS Fund, Inc. | D77: 149544395 | E77: 3156741 | F77: =D77-E77 -> 146387654 | G77: 0 | H77: 2920 | I77: 1006566 | J77: 390986 | K77: =I77-J77 -> 615580 | L77: =I77+Mar!L77 -> 3372824 | M77: =J77+Mar!M77 -> 8666002 | N77: =L77-M77 -> -5293178
A78: Corporate Debt Vehicle (units)
B79: =1+B77 -> 55 | C79: ATRAM Unitized Corporate Debt Vehicle, Inc. | D79: 7.1415609e+08 | E79: 2689111.7 | F79: =D79-E79 -> 7.1146697e+08 | G79: 0 | H79: 13 | I79: 0 | J79: 0 | K79: =I79-J79 -> 0 | L79: =I79+Mar!L79 -> 0 | M79: =J79+Mar!M79 -> 0 | N79: =L79-M79 -> 0
A80: Sub total - Peso Currency | D80: =SUM(D67:D79) -> 49899790867 | E80: =SUM(E67:E79) -> 1240100815 | F80: =SUM(F67:F79) -> 48659690053 | G80: =SUM(G67:G79) -> 266250000 | H80: =SUM(H67:H79) -> 60813 | I80: =SUM(I67:I79) -> 3.9131562e+08 | J80: =SUM(J67:J79) -> 6.0512987e+08 | K80: =SUM(K67:K79) -> -2.1381425e+08 | ... N80: =SUM(N67:N79) -> -8.9444628e+08
A81: Primarily invested in foreign currency securities (shares)
B82: =1+B79 -> 56 | C82: ALFM Dollar Bond Fund, Inc. | D82: 11552943758 | E82: 393647614 | F82: =D82-E82 -> 11159296144 | G82: 0 | H82: 7184 | I82: 14227158 | J82: 140405654 | K82: =I82-J82 -> -126178496 | L82: =I82+Mar!L82 -> 98268903 | M82: =J82+Mar!M82 -> 442978400 | N82: =L82-M82 -> -344709497
B83: =1+B82 -> 57 | C83: ATRAM Total Return Dollar Bond Fund, Inc. | D83: 1.1136987e+08 | E83: 1980406.9 | F83: =D83-E83 -> 1.0938946e+08 | G83: 0 | H83: 70 | I83: 10647145 | J83: 11232414 | K83: =I83-J83 -> -585269.09 | L83: =I83+Mar!L83 -> 29237669 | M83: =J83+Mar!M83 -> 13915937 | N83: =L83-M83 -> 15321732
B84: =1+B83 -> 58 | C84: First Metro Save and Learn Dollar Bond Fund, Inc. | D84: 307606104 | E84: 750648 | F84: =D84-E84 -> 306855456 | G84: 0 | H84: 156 | I84: 0 | J84: 5013705 | K84: =I84-J84 -> -5013705 | L84: =I84+Mar!L84 -> 186598 | M84: =J84+Mar!M84 -> 7305934 | N84: =L84-M84 -> -7119336
B85: =1+B84 -> 59 | C85: PAMI Global Bond Fund, Inc. | D85: 66113145 | E85: 15905659 | F85: =D85-E85 -> 50207486 | G85: 0 | H85: 24 | I85: 0 | J85: 0 | K85: =I85-J85 -> 0 | L85: =I85+Mar!L85 -> 0 | M85: =J85+Mar!M85 -> 0 | N85: =L85-M85 -> 0
B86: =1+B85 -> 60 | C86: Philam Dollar Bond Fund, Inc. | D86: 1564791518 | E86: 8523669 | F86: =D86-E86 -> 1556267849 | G86: 0 | H86: 1561 | I86: 5528 | J86: 36819995 | K86: =I86-J86 -> -36814467 | L86: =I86+Mar!L86 -> 165148 | M86: =J86+Mar!M86 -> 99570659 | N86: =L86-M86 -> -99405511
B87: =1+B86 -> 61 | C87: Philequity Dollar Income Fund, Inc. | D87: 2.2228775e+08 | E87: 1533832.1 | F87: =D87-E87 -> 220753921 | G87: 0 | H87: 96 | I87: 139600 | J87: 0 | K87: =I87-J87 -> 139600 | L87: =I87+Mar!L87 -> 537166 | M87: =J87+Mar!M87 -> 0 | N87: =L87-M87 -> 537166
B88: =1+B87 -> 62 | C88: Sun Life Prosperity Dollar Abundance Fund, Inc. | D88: 522756100 | E88: 16290587 | F88: =D88-E88 -> 506465513 | G88: 0 | H88: 2651 | I88: 59022472 | J88: 13864273 | K88: =I88-J88 -> 45158199 | L88: =I88+Mar!L88 -> 62226738 | M88: =J88+Mar!M88 -> 41410168 | N88: =L88-M88 -> 20816570
A89: Sub total - US Currency | D89: =SUM(D82:D88) -> 14347868243 | E89: =SUM(E82:E88) -> 438632416 | F89: =SUM(F82:F88) -> 13909235827 | G89: =SUM(G82:G88) -> 0 | H89: =SUM(H82:H88) -> 11742 | I89: =SUM(I82:I88) -> 84041903 | J89: =SUM(J82:J88) -> 2.0733604e+08 | K89: =SUM(K82:K88) -> -1.2329414e+08 | ... N89: =SUM(N82:N88) -> -4.1455888e+08
B90: =1+B88 -> 63 | C90: ALFM Euro Bond Fund, Inc. | D90: 733082054 | E90: 6391703 | F90: =D90-E90 -> 726690351 | G90: 0 | H90: 569 | I90: 586028 | J90: 5047625 | K90: =I90-J90 -> -4461597 | L90: =I90+Mar!L90 -> 19013112 | M90: =J90+Mar!M90 -> 29004537 | N90: =L90-M90 -> -9991425
A91: Sub total - Euro Currency | D91: =SUM(D90) -> 733082054 | E91: =SUM(E90) -> 6391703 | F91: =SUM(F90) -> 726690351 | G91: =SUM(G90) -> 0 | H91: =SUM(H90) -> 569 | I91: =SUM(I90) -> 586028 | J91: =SUM(J90) -> 5047625 | K91: =SUM(K90) -> -4461597 | ... N91: =SUM(N90) -> -9991425
A92: Sub total - bond funds | D92: =D80+D89+D91 -> 64980741165 | E92: =E80+E89+E91 -> 1685124934 | F92: =F80+F89+F91 -> 63295616231 | G92: =G80+G89+G91 -> 266250000 | H92: =H80+H89+H91 -> 73124 | I92: =I80+I89+I91 -> 4.7594355e+08 | J92: =J80+J89+J91 -> 8.1751353e+08 | K92: =K80+K89+K91 -> -3.4156999e+08 | ... N92: =N80+N89+N91 -> -1318996576
A93: Money Market Funds
A94: Primarily invested in Peso Securities (shares)
B95: 64 | C95: AIB Money Market Mutual Fund, Inc. | D95: 1.7281011e+08 | E95: 357111.72 | F95: =D95-E95 -> 1.72453e+08 | G95: 0 | H95: 74 | I95: 41000 | J95: 55248.64 | K95: =I95-J95 -> -14248.64 | L95: =I95+Mar!L95 -> 963000 | M95: =J95+Mar!M95 -> 135643.57 | N95: =L95-M95 -> 827356.43
B96: 65 | C96: ALFM Money Market Fund, Inc. | D96: 21003631945 | E96: 10872207 | F96: =D96-E96 -> 20992759738 | G96: 0 | H96: 21768 | I96: 356796 | J96: 230284049 | K96: =I96-J96 -> -229927253 | L96: =I96+Mar!L96 -> 1383377 | M96: =J96+Mar!M96 -> 1340526035 | N96: =L96-M96 -> -1339142658
B97: =1+B96 -> 66 | C97: First Metro Save and Learn Money Market Fund, Inc. | D97: 2397797203 | E97: 38571668 | F97: =D97-E97 -> 2359225535 | G97: 0 | H97: 1153 | I97: 17147411 | J97: 208409364 | K97: =I97-J97 -> -191261953 | L97: =I97+Mar!L97 -> 260832933 | M97: =J97+Mar!M97 -> 688103351 | N97: =L97-M97 -> -427270418
B98: =1+B97 -> 67 | C98: Sun Life Prosperity Peso Starter Fund, Inc. | D98: 12086753033 | E98: 68065705 | F98: =D98-E98 -> 12018687328 | G98: 0 | H98: 73629 | I98: 461409225 | J98: 909160014 | K98: =I98-J98 -> -447750789 | L98: =I98+Mar!L98 -> 2032132224 | M98: =J98+Mar!M98 -> 2555537322 | N98: =L98-M98 -> -523405098
A99: Primarily invested in Peso Securities (units) | L99: =I99+Mar!L99 -> 0 | M99: =J99+Mar!M99 -> 0
B100: =1+B98 -> 68 | C100: ALFM Money Market Fund, Inc. | D100: 11852531459 | E100: 6907659 | F100: =D100-E100 -> 11845623800 | G100: 0 | H100: 27682 | I100: 764901218 | J100: 533322284 | K100: =I100-J100 -> 231578934 | L100: =I100+Mar!L100 -> 3081201698 | M100: =J100+Mar!M100 -> 2793765033 | N100: =L100-M100 -> 287436665
A101: Sub total - Peso Currency | D101: =SUM(D95:D98)+D100 -> 47513523747 | E101: =SUM(E95:E98)+E100 -> 1.2477435e+08 | F101: =SUM(F95:F98)+F100 -> 47388749397 | G101: =SUM(G95:G98)+G100 -> 0 | H101: =SUM(H95:H98)+H100 -> 124306 | I101: =SUM(I95:I98)+I100 -> 1243855650 | J101: =SUM(J95:J98)+J100 -> 1881230960 | K101: =SUM(K95:K98)+K100 -> -6.3737531e+08 | ... N101: =SUM(N95:N98)+N100 -> -2001554153
A102: Primarily invested in foreign currency securities (shares)
B103: =1+B100 -> 69 | C103: Sun Life Prosperity Dollar Starter Fund, Inc. | D103: 2290764232 | E103: 8881473 | F103: =D103-E103 -> 2281882759 | G103: 0 | H103: 3869 | I103: 49880236 | J103: 225370373 | K103: =I103-J103 -> -175490137 | L103: =I103+Mar!L103 -> 719200519 | M103: =J103+Mar!M103 -> 706726444 | N103: =L103-M103 -> 12474075
A104: Sub total - US Currency | D104: =SUM(D103) -> 2290764232 | E104: =SUM(E103) -> 8881473 | F104: =SUM(F103) -> 2281882759 | G104: =SUM(G103) -> 0 | H104: =SUM(H103) -> 3869 | I104: =SUM(I103) -> 49880236 | J104: =SUM(J103) -> 225370373 | K104: =SUM(K103) -> -175490137 | ... N104: =SUM(N103) -> 12474075
A105: Sub total - money market funds | D105: =D101+D104 -> 49804287979 | E105: =E101+E104 -> 1.3365582e+08 | F105: =F101+F104 -> 49670632156 | G105: =G101+G104 -> 0 | H105: =H101+H104 -> 128175 | I105: =I101+I104 -> 1293735886 | J105: =J101+J104 -> 2106601333 | K105: =K101+K104 -> -8.1286545e+08 | ... N105: =N101+N104 -> -1989080078
...

Sheet May
A1: PHILIPPINE INVESTMENT FUNDS ASSOCIATION, INC.
A2: MUTUAL FUNDS STATISTICAL REPORT
A3: Month of May 2025
A4: (Amounts in Peso)
I5: F O R - T H E - M O N T H | L5: Y E A R - T O - D A T E
A6: Fund Category | C6: Fund Name | D6: ASSETS | E6: LIABILITIES | F6: NET ASSETS | G6: EQUITY INV. | H6: NO. OF A/C | I6: SALES | J6: REDEMPTIONS | K6: NET SALES | L6: TOTAL SALES | M6: TOTAL REDEMPTIONS | N6: TOTAL NET SALES
A7: Stock Funds
A8: Primarily invested in Peso Securities (shares)
B9: 1 | C9: ALFM Growth Fund, Inc. | D9: 3746895024 | E9: 13209879 | F9: =D9-E9 -> 3733685145 | G9: 3683738470 | H9: 5714 | I9: 2617552 | J9: 41744409 | K9: =I9-J9 -> -39126857 | L9: =I9+Apr!L9 -> 39272520 | M9: =J9+Apr!M9 -> 174888661 | N9: =L9-M9 -> -135616141
B10: =1+B9 -> 2 | C10: ATRAM Alpha Opportunity Fund, Inc. | D10: 1.1235864e+09 | E10: 10265339 | F10: =D10-E10 -> 1113321053 | G10: 1.0184088e+09 | H10: 4186 | I10: 45227343 | J10: 10772156 | K10: =I10-J10 -> 34455188 | L10: =I10+Apr!L10 -> 1.4214536e+08 | M10: =J10+Apr!M10 -> 61621406 | N10: =L10-M10 -> 80523949
B11: =1+B10 -> 3 | C11: ATRAM Phil. Equity Opportunity Fund, Inc. | D11: 1.0611706e+09 | E11: 8819802.8 | F11: =D11-E11 -> 1052350785 | G11: 9.8571991e+08 | H11: 2453 | I11: 3733028.3 | J11: 14451415 | K11: =I11-J11 -> -10718387 | L11: =I11+Apr!L11 -> 24312344 | M11: =J11+Apr!M11 -> 62358689 | N11: =L11-M11 -> -38046346
B12: =1+B11 -> 4 | C12: Climbs Share Capital Equity Investment Fund Corp. | D12: 4.5759687e+08 | E12: 14856479 | F12: =D12-E12 -> 4.4274039e+08 | G12: 4.068688e+08 | H12: 1749 | I12: 951931.98 | J12: 192961.45 | K12: =I12-J12 -> 758970.53 | L12: =I12+Apr!L12 -> 46071414 | M12: =J12+Apr!M12 -> 1998437.6 | N12: =L12-M12 -> 44072976
B13: =1+B12 -> 5 | C13: First Metro Consumer Fund, Inc. | D13: 344878348 | E13: 954514 | F13: =D13-E13 -> 343923834 | G13: 306998520 | H13: 1133 | I13: 171687 | J13: 1340252 | K13: =I13-J13 -> -1168565 | L13: =I13+Apr!L13 -> 1536113 | M13: =J13+Apr!M13 -> 13558769 | N13: =L13-M13 -> -12022656
B14: =1+B13 -> 6 | C14: First Metro Save and Learn Equity Fund, Inc. | D14: 2971263241 | E14: 11378115 | F14: =D14-E14 -> 2959885126 | G14: 2758940115 | H14: 14240 | I14: 2306279 | J14: 116340091 | K14: =I14-J14 -> -114033812 | L14: =I14+Apr!L14 -> 53816487 | M14: =J14+Apr!M14 -> 278955678 | N14: =L14-M14 -> -225139191
B15: =1+B14 -> 7 | C15: First Metro Save and Learn Phil. Index Fund, Inc. | D15: 76957890 | E15: 375586 | F15: =D15-E15 -> 76582304 | G15: 75092489 | H15: 472 | I15: 137070 | J15: 18942287 | K15: =I15-J15 -> -18805217 | L15: =I15+Apr!L15 -> 10986298 | M15: =J15+Apr!M15 -> 20197643 | N15: =L15-M15 -> -9211345
B16: =1+B15 -> 8 | C16: MBG Equity Investment Fund, Inc. | D16: 67424855 | E16: 1400670 | F16: =D16-E16 -> 66024185 | G16: 5846187 | H16: 42 | I16: 0 | J16: 45578786 | K16: =I16-J16 -> -45578786 | L16: =I16+Apr!L16 -> 0 | M16: =J16+Apr!M16 -> 49849715 | N16: =L16-M16 -> -49849715
B17: =1+B16 -> 9 | C17: PAMI Equity Index Fund, Inc. | D17: 1029227352 | E17: 25880972 | F17: =D17-E17 -> 1003346380 | G17: 1016269371 | H17: 10825 | I17: 0 | J17: 11343529 | K17: =I17-J17 -> -11343529 | L17: =I17+Apr!L17 -> 1459 | M17: =J17+Apr!M17 -> 41872591 | N17: =L17-M17 -> -41871132
B18: =1+B17 -> 10 | C18: Philam Strategic Growth Fund, Inc. | D18: 3078016698 | E18: 30465413 | F18: =D18-E18 -> 3047551285 | G18: 3027086882 | H18: 10745 | I18: 1729292 | J18: 59911941 | K18: =I18-J18 -> -58182649 | L18: =I18+Apr!L18 -> 28110254 | M18: =J18+Apr!M18 -> 190730898 | N18: =L18-M18 -> -162620644
B19: =1+B18 -> 11 | C19: Philequity Dividend Yield Fund, Inc. | D19: 2.5065254e+09 | E19: 10981955 | F19: =D19-E19 -> 2495543397 | G19: 2.2492081e+09 | H19: 5031 | I19: 3905077.4 | J19: 12754199 | K19: =I19-J19 -> -8849121.8 | L19: =I19+Apr!L19 -> 68186831 | M19: =J19+Apr!M19 -> 79303775 | N19: =L19-M19 -> -11116945
B20: =1+B19 -> 12 | C20: Philequity Fund, Inc. | D20: 9.1146635e+09 | E20: 38041823 | F20: =D20-E20 -> 9076621693 | G20: 8.6453541e+09 | H20: 31382 | I20: 6256920.6 | J20: 37103491 | K20: =I20-J20 -> -30846571 | L20: =I20+Apr!L20 -> 1.0490611e+08 | M20: =J20+Apr!M20 -> 2.6299296e+08 | N20: =L20-M20 -> -1.5808684e+08
B21: =1+B20 -> 13 | C21: Philequity MSCI Phil. Index Fund, Inc. | D21: 3.1844593e+08 | E21: 2512838.4 | F21: =D21-E21 -> 3.1593309e+08 | G21: 3.1443298e+08 | H21: 875 | I21: 173522 | J21: 792438.42 | K21: =I21-J21 -> -618916.42 | L21: =I21+Apr!L21 -> 1483912.1 | M21: =J21+Apr!M21 -> 1434426.4 | N21: =L21-M21 -> 49485.62
... B27: =1+B26 -> 19 | C27: United Fund, Inc. | D27: 5.2917175e+08 | E27: 3970266.7 | F27: =D27-E27 -> 5.2520148e+08 | G27: 5.0719552e+08 | H27: 1186 | I27: 226373.29 | J27: 700250.25 | K27: =I27-J27 -> -473876.96 | L27: =I27+Apr!L27 -> 1503290.3 | M27: =J27+Apr!M27 -> 4444199.2 | N27: =L27-M27 -> -2940909
A28: Primarily invested in Peso Securities (units)
B29: =1+B27 -> 20 | C29: COL Equity Index Unitized Mutual Fund, Inc. | D29: 2.6290697e+08 | E29: 587894.76 | F29: =D29-E29 -> 2.6231907e+08 | G29: 2.5240079e+08 | H29: 4752 | I29: 8389584.4 | J29: 9401106.8 | K29: =I29-J29 -> -1011522.4 | L29: =I29+Apr!L29 -> 59064404 | M29: =J29+Apr!M29 -> 25128922 | N29: =L29-M29 -> 33935482
B30: =1+B29 -> 21 | C30: COL Strategic Growth Equity Unitized Mutual Fund, Inc. | D30: 4.1972978e+08 | E30: 8297432.7 | F30: =D30-E30 -> 4.1143235e+08 | G30: 317097295 | H30: 6667 | I30: 21170617 | J30: 10381578 | K30: =I30-J30 -> 10789039 | L30: =I30+Apr!L30 -> 74421532 | M30: =J30+Apr!M30 -> 47966379 | N30: =L30-M30 -> 26455153
B31: =1+B30 -> 22 | C31: Philequity Alpha One Fund, Inc. | D31: 2.5340187e+08 | E31: 1190407.8 | F31: =D31-E31 -> 2.5221147e+08 | G31: 2.4900363e+08 | H31: 1124 | I31: 165130.92 | J31: 4903427 | K31: =I31-J31 -> -4738296.1 | L31: =I31+Apr!L31 -> 3328075.9 | M31: =J31+Apr!M31 -> 19147572 | N31: =L31-M31 -> -15819496
B32: =1+B31 -> 23 | C32: Philippine Stock Index Fund Corp. | D32: 722432379 | E32: 5003897 | F32: =D32-E32 -> 717428482 | G32: 712700435 | H32: 770322 | I32: 12995713 | J32: 24953199 | K32: =I32-J32 -> -11957486 | L32: =I32+Apr!L32 -> 148284628 | M32: =J32+Apr!M32 -> 120084117 | N32: =L32-M32 -> 28200511
A33: Exchange Traded Fund
B34: =1+B32 -> 24 | C34: First Metro Phil. Equity Exchange Traded Fund, Inc. | D34: 1412848203 | E34: 7346933 | F34: =D34-E34 -> 1405501270 | G34: 1401812399 | H34: 3260 | I34: 0 | J34: 21183230 | K34: =I34-J34 -> -21183230 | L34: =I34+Apr!L34 -> 50257348 | M34: =J34+Apr!M34 -> 21183230 | N34: =L34-M34 -> 29074118
A35: Sub total - Peso Currency | D35: =SUM(D9:D34) -> 56650167593 | E35: =SUM(E9:E34) -> 2.8931977e+08 | F35: =SUM(F9:F34) -> 56360847820 | G35: =SUM(G9:G34) -> 54580695939 | H35: =SUM(H9:H34) -> 1048567 | I35: =SUM(I9:I34) -> 1.6134591e+08 | J35: =SUM(J9:J34) -> 7.8447856e+08 | K35: =SUM(K9:K34) -> -623132647 | ... N35: =SUM(N9:N34) -> -1791621663
A36: Primarily invested in foreign currency securities (shares)
B37: =1+B34 -> 25 | C37: ATRAM AsiaPlus Equity Fund, Inc. | D37: 27832574 | E37: 198599.92 | F37: =D37-E37 -> 27633974 | G37: 0 | H37: 50 | I37: 0 | J37: 0 | K37: =I37-J37 -> 0 | L37: =I37+Apr!L37 -> 104642.2 | M37: =J37+Apr!M37 -> 153134.87 | N37: =L37-M37 -> -48492.67
B38: =1+B37 -> 26 | C38: Sun Life Prosperity World Voyager Fund, Inc. | D38: 1812365887 | E38: 62262050 | F38: =D38-E38 -> 1750103837 | G38: 0 | H38: 3231 | I38: 17713633 | J38: 17233387 | K38: =I38-J38 -> 480246 | L38: =I38+Apr!L38 -> 117897019 | M38: =J38+Apr!M38 -> 342725579 | N38: =L38-M38 -> -224828560
A39: Sub total - US Currency | D39: =SUM(D37:D38) -> 1840198461 | E39: =SUM(E37:E38) -> 62460650 | F39: =SUM(F37:F38) -> 1777737811 | G39: =SUM(G37:G38) -> 0 | H39: =SUM(H37:H38) -> 3281 | I39: =SUM(I37:I38) -> 17713633 | J39: =SUM(J37:J38) -> 17233387 | K39: =SUM(K37:K38) -> 480246 | ... N39: =SUM(N37:N38) -> -2.2487705e+08
A40: Sub total - stock funds | D40: =D35+D39 -> 58490366053 | E40: =E35+E39 -> 3.5178042e+08 | F40: =F35+F39 -> 58138585631 | G40: =G35+G39 -> 54580695939 | H40: =H35+H39 -> 1051848 | I40: =I35+I39 -> 1.7905955e+08 | J40: =J35+J39 -> 8.0171195e+08 | K40: =K35+K39 -> -622652401 | ... N40: =N35+N39 -> -2016498715
A41: Balanced Funds
A42: Primarily invested in Peso Securities (shares)
B43: =1+B38 -> 27 | C43: ATRAM Philippine Balanced Fund, Inc. | D43: 4.3013227e+08 | E43: 25956609 | F43: =D43-E43 -> 4.0417566e+08 | G43: 1.9382199e+08 | H43: 2326 | I43: 738168.73 | J43: 5107765.1 | K43: =I43-J43 -> -4369596.4 | L43: =I43+Apr!L43 -> 2824369 | M43: =J43+Apr!M43 -> 24417391 | N43: =L43-M43 -> -21593022
B44: =1+B43 -> 28 | C44: ATRAM Unicapital Diversified Growth Fund, Inc. | D44: 1.1240475e+08 | E44: 283561.99 | F44: =D44-E44 -> 1.1212118e+08 | G44: 28979354 | H44: 804 | I44: 351890.65 | J44: 666781.59 | K44: =I44-J44 -> -314890.94 | L44: =I44+Apr!L44 -> 1525412.7 | M44: =J44+Apr!M44 -> 2205698.4 | N44: =L44-M44 -> -680285.62
B45: =1+B44 -> 29 | C45: First Metro Save and Learn Balanced Fund, Inc. | D45: 636536664 | E45: 3587515 | F45: =D45-E45 -> 632949149 | G45: 296139184 | H45: 4045 | I45: 634298 | J45: 6544587 | K45: =I45-J45 -> -5910289 | L45: =I45+Apr!L45 -> 3988192 | M45: =J45+Apr!M45 -> 29740802 | N45: =L45-M45 -> -25752610
B46: =1+B45 -> 30 | C46: First Metro Save and Learn F.O.C.C.U.S. Dynamic Fund, Inc. | D46: 408996919 | E46: 36517124 | F46: =D46-E46 -> 372479795 | G46: 256093763 | H46: 376 | I46: 32243174 | J46: 10566457 | K46: =I46-J46 -> 21676717 | L46: =I46+Apr!L46 -> 52293820 | M46: =J46+Apr!M46 -> 150426934 | N46: =L46-M46 -> -98133114
B47: =1+B46 -> 31 | C47: NCM Mutual Fund of the Phils., Inc. | D47: 3.1924604e+08 | E47: 1065800.4 | F47: =D47-E47 -> 3.1818024e+08 | G47: 1.5595821e+08 | H47: 46 | I47: 0 | J47: 0 | K47: =I47-J47 -> 0 | L47: =I47+Apr!L47 -> 2.3662765e+08 | M47: =J47+Apr!M47 -> 2.3897046e+08 | N47: =L47-M47 -> -2342804.7
B48: =1+B47 -> 32 | C48: PAMI Horizon Fund, Inc. | D48: 435516636 | E48: 14080238 | F48: =D48-E48 -> 421436398 | G48: 215509693 | H48: 9562 | I48: 9840 | J48: 2468145 | K48: =I48-J48 -> -2458305 | L48: =I48+Apr!L48 -> 163372 | M48: =J48+Apr!M48 -> 29622394 | N48: =L48-M48 -> -29459022
B49: =1+B48 -> 33 | C49: Philam Fund, Inc. | D49: 1805805203 | E49: 12823128 | F49: =D49-E49 -> 1792982075 | G49: 897600325 | H49: 7075 | I49: 706573 | J49: 20041529 | K49: =I49-J49 -> -19334956 | L49: =I49+Apr!L49 -> 2388944 | M49: =J49+Apr!M49 -> 86408465 | N49: =L49-M49 -> -84019521
B50: =1+B49 -> 34 | C50: Solidaritas Fund, Inc. | D50: 120821124 | E50: 166479 | F50: =D50-E50 -> 120654645 | G50: 61080047 | H50: 158 | I50: 0 | J50: 0 | K50: =I50-J50 -> 0 | L50: =I50+Apr!L50 -> 0 | M50: =J50+Apr!M50 -> 1722878 | N50: =L50-M50 -> -1722878
B51: =1+B50 -> 35 | C51: Sun Life Prosperity Balanced Fund, Inc. | D51: 5743749215 | E51: 35160371 | F51: =D51-E51 -> 5708588844 | G51: 3015471115 | H51: 54704 | I51: 5074192 | J51: 36305277 | K51: =I51-J51 -> -31231085 | L51: =I51+Apr!L51 -> 27316600 | M51: =J51+Apr!M51 -> 281894887 | N51: =L51-M51 -> -254578287
B52: =1+B51 -> 36 | C52: Sun Life Prosperity Dynamic Fund, Inc. | D52: 449809766 | E52: 2443558 | F52: =D52-E52 -> 447366208 | G52: 253705202 | H52: 5000 | I52: 0 | J52: 10630887 | K52: =I52-J52 -> -10630887 | L52: =I52+Apr!L52 -> 0 | M52: =J52+Apr!M52 -> 42525952 | N52: =L52-M52 -> -42525952
A53: Primarily invested in Peso Securities (units) | M53: =J53+Apr!M53 -> 0
B54: =1+B52 -> 37 | C54: Sun Life Prosperity Achiever Fund 2028, Inc. | D54: 76466269 | E54: 288949 | F54: =D54-E54 -> 76177320 | G54: 15781826 | H54: 1261 | I54: 163804 | J54: 141858 | K54: =I54-J54 -> 21946 | L54: =I54+Apr!L54 -> 948998 | M54: =J54+Apr!M54 -> 1847136 | N54: =L54-M54 -> -898138
B55: =1+B54 -> 38 | C55: Sun Life Prosperity Achiever Fund 2038, Inc. | D55: 57026593 | E55: 757673 | F55: =D55-E55 -> 56268920 | G55: 39938317 | H55: 515 | I55: 266930 | J55: 545312 | K55: =I55-J55 -> -278382 | L55: =I55+Apr!L55 -> 731731 | M55: =J55+Apr!M55 -> 736273 | N55: =L55-M55 -> -4542
B56: =1+B55 -> 39 | C56: Sun Life Prosperity Achiever Fund 2048, Inc. | D56: 47660865 | E56: 239318 | F56: =D56-E56 -> 47421547 | G56: 39274252 | H56: 250 | I56: 52500 | J56: 29190 | K56: =I56-J56 -> 23310 | L56: =I56+Apr!L56 -> 306885 | M56: =J56+Apr!M56 -> 159065 | N56: =L56-M56 -> 147820
A57: Sub total - Peso Currency | D57: =SUM(D43:D56) -> 10644172314 | E57: =SUM(E42:E56) -> 1.3337032e+08 | F57: =SUM(F43:F56) -> 10510801990 | G57: =SUM(G43:G56) -> 5469353282 | H57: =SUM(H43:H56) -> 86122 | I57: =SUM(I42:I56) -> 40241370 | J57: =SUM(J43:J56) -> 93047789 | K57: =SUM(K43:K56) -> -52806418 | L57: =SUM(L43:L56) -> 3.2911598e+08 | M57: =SUM(M43:M56) -> 8.9067833e+08 | N57: =SUM(N43:N56) -> -5.6156236e+08
A58: Primarily invested in foreign currency securities (shares)
B59: =1+B56 -> 40 | C59: Cocolife Dollar Fund Builder, Inc. | D59: 59382382 | E59: 320504.21 | F59: =D59-E59 -> 59061878 | G59: 0 | H59: 48 | I59: 0 | J59: 1408529 | K59: =I59-J59 -> -1408529 | L59: =I59+Apr!L59 -> 0 | M59: =J59+Apr!M59 -> 1616336.3 | N59: =L59-M59 -> -1616336.3
B60: =1+B59 -> 41 | C60: PAMI Asia Balanced Fund, Inc. | D60: 308290945 | E60: 23473055 | F60: =D60-E60 -> 284817890 | G60: 155576298 | H60: 208 | I60: 0 | J60: 6747980 | K60: =I60-J60 -> -6747980 | L60: =I60+Apr!L60 -> 0 | M60: =J60+Apr!M60 -> 27896888 | N60: =L60-M60 -> -27896888
B61: =1+B60 -> 42 | C61: Sun Life Prosperity Dollar Advantage Fund, Inc. | D61: 1597798930 | E61: 28810791 | F61: =D61-E61 -> 1568988139 | G61: 0 | H61: 4292 | I61: 1821696 | J61: 13431053 | K61: =I61-J61 -> -11609357 | L61: =I61+Apr!L61 -> 24558968 | M61: =J61+Apr!M61 -> 111575775 | N61: =L61-M61 -> -87016807
B62: =1+B61 -> 43 | C62: Sun Life Prosperity Dollar Wellspring Fund, Inc. | D62: 237076432 | E62: 2424043 | F62: =D62-E62 -> 234652389 | G62: 0 | H62: 773 | I62: 54496 | J62: 629411 | K62: =I62-J62 -> -574915 | L62: =I62+Apr!L62 -> 4964129 | M62: =J62+Apr!M62 -> 10959943 | N62: =L62-M62 -> -5995814
A63: Sub total - US Currency | D63: =SUM(D59:D62) -> 2202548689 | E63: =SUM(E59:E62) -> 55028393 | F63: =SUM(F59:F62) -> 2147520296 | G63: =SUM(G59:G62) -> 155576298 | H63: =SUM(H59:H62) -> 5321 | I63: =SUM(I59:I62) -> 1876192 | J63: =SUM(J59:J62) -> 22216973 | K63: =SUM(K59:K62) -> -20340781 | ... N63: =SUM(N59:N62) -> -1.2252585e+08
A64: Sub total - balanced funds | D64: =D57+D63 -> 12846721003 | E64: =E57+E63 -> 1.8839872e+08 | F64: =F57+F63 -> 12658322286 | G64: =G57+G63 -> 5624929580 | H64: =H57+H63 -> 91443 | I64: =I57+I63 -> 42117562 | J64: =J57+J63 -> 1.1526476e+08 | K64: =K57+K63 -> -73147199 | ... N64: =N57+N63 -> -6.840882e+08
A65: Bond Funds
A66: Primarily invested in Peso Securities (shares)
B67: =1+B62 -> 44 | C67: ALFM Peso Bond Fund, Inc. | D67: 35017019082 | E67: 270493110 | F67: =D67-E67 -> 34746525972 | G67: 266500000 | H67: 24240 | I67: 186951378 | J67: 269580534 | K67: =I67-J67 -> -82629156 | L67: =I67+Apr!L67 -> 935225139 | M67: =J67+Apr!M67 -> 1581934719 | N67: =L67-M67 -> -646709580
B68: =1+B67 -> 45 | C68: ATRAM Corporate Bond Fund, Inc. | D68: 2.5861697e+08 | E68: 1046569.7 | F68: =D68-E68 -> 2.575704e+08 | G68: 0 | H68: 924 | I68: 236903.23 | J68: 864062.05 | K68: =I68-J68 -> -627158.82 | L68: =I68+Apr!L68 -> 2751048.9 | M68: =J68+Apr!M68 -> 23379101 | N68: =L68-M68 -> -20628053
B69: =1+B68 -> 46 | C69: Cocolife Fixed Income Fund, Inc. | D69: 8.9250221e+08 | E69: 10388656 | F69: =D69-E69 -> 8.8211355e+08 | G69: 0 | H69: 1795 | I69: 1053084 | J69: 52942151 | K69: =I69-J69 -> -51889067 | L69: =I69+Apr!L69 -> 27908788 | M69: =J69+Apr!M69 -> 97490886 | N69: =L69-M69 -> -69582099
B70: =1+B69 -> 47 | C70: Ekklesia Mutual Fund, Inc. | D70: 188941326 | E70: 189023 | F70: =D70-E70 -> 188752303 | G70: 0 | H70: 134 | I70: 0 | J70: 0 | K70: =I70-J70 -> 0 | L70: =I70+Apr!L70 -> 4998 | M70: =J70+Apr!M70 -> 426661 | N70: =L70-M70 -> -421663
B71: =1+B70 -> 48 | C71: First Metro Save and Learn Fixed Income Fund, Inc. | D71: 998113955 | E71: 5106085 | F71: =D71-E71 -> 993007870 | G71: 0 | H71: 1690 | I71: 832440 | J71: 14338649 | K71: =I71-J71 -> -13506209 | L71: =I71+Apr!L71 -> 3177880 | M71: =J71+Apr!M71 -> 207803150 | N71: =L71-M71 -> -204625270
B72: =1+B71 -> 49 | C72: Philam Bond Fund, Inc. | D72: 1361674234 | E72: 29501494 | F72: =D72-E72 -> 1332172740 | G72: 0 | H72: 4502 | I72: 1155136 | J72: 34950058 | K72: =I72-J72 -> -33794922 | L72: =I72+Apr!L72 -> 7843155 | M72: =J72+Apr!M72 -> 92355387 | N72: =L72-M72 -> -84512232
B73: =1+B72 -> 50 | C73: Philam Managed Income Fund, Inc. | D73: 615128957 | E73: 9875241 | F73: =D73-E73 -> 605253716 | G73: 0 | H73: 388 | I73: 0 | J73: 1349104 | K73: =I73-J73 -> -1349104 | L73: =I73+Apr!L73 -> 0 | M73: =J73+Apr!M73 -> 23032189 | N73: =L73-M73 -> -23032189
B74: =1+B73 -> 51 | C74: Philequity Peso Bond Fund, Inc. | D74: 2.7455528e+08 | E74: 1684715.8 | F74: =D74-E74 -> 2.7287056e+08 | G74: 0 | H74: 3980 | I74: 1719152.5 | J74: 64311392 | K74: =I74-J74 -> -62592239 | L74: =I74+Apr!L74 -> 11518781 | M74: =J74+Apr!M74 -> 69334988 | N74: =L74-M74 -> -57816207
B75: =1+B74 -> 52 | C75: Soldivo Bond Fund, Inc. | D75: 1.896371e+09 | E75: 3218563.2 | F75: =D75-E75 -> 1893152398 | G75: 0 | H75: 776 | I75: 178713.8 | J75: 411319.52 | K75: =I75-J75 -> -232605.72 | L75: =I75+Apr!L75 -> 80072723 | M75: =J75+Apr!M75 -> 10363554 | N75: =L75-M75 -> 69709169
B76: =1+B75 -> 53 | C76: Sun Life Prosperity Bond Fund, Inc. | D76: 6452873840 | E76: 22438641 | F76: =D76-E76 -> 6430435199 | G76: 0 | H76: 19508 | I76: 54425111 | J76: 146667785 | K76: =I76-J76 -> -92242674 | L76: =I76+Apr!L76 -> 475903592 | M76: =J76+Apr!M76 -> 666301701 | N76: =L76-M76 -> -190398109
B77: =1+B76 -> 54 | C77: Sun Life Prosperity GS Fund, Inc. | D77: 147478003 | E77: 400578 | F77: =D77-E77 -> 147077425 | G77: 0 | H77: 2930 | I77: 1040905 | J77: 732476 | K77: =I77-J77 -> 308429 | L77: =I77+Apr!L77 -> 4413729 | M77: =J77+Apr!M77 -> 9398478 | N77: =L77-M77 -> -4984749
A78: Corporate Debt Vehicle (units)
B79: =1+B77 -> 55 | C79: ATRAM Unitized Corporate Debt Vehicle, Inc. * | D79: 3113490.6 | E79: 767599.72 | F79: =D79-E79 -> 2345890.9 | G79: 0 | H79: 0 | I79: 0 | J79: 700000000 | K79: =I79-J79 -> -700000000 | L79: =I79+Apr!L79 -> 0 | M79: =J79+Apr!M79 -> 700000000 | N79: =L79-M79 -> -700000000
A80: Sub total - Peso Currency | D80: =SUM(D67:D79) -> 48106388299 | E80: =SUM(E67:E79) -> 3.5511028e+08 | F80: =SUM(F67:F79) -> 47751278023 | G80: =SUM(G67:G79) -> 266500000 | H80: =SUM(H67:H79) -> 60867 | I80: =SUM(I67:I79) -> 2.4759282e+08 | J80: =SUM(J67:J79) -> 1286147530 | K80: =SUM(K67:K79) -> -1038554706 | ... N80: =SUM(N67:N79) -> -1933000982
A81: Primarily invested in foreign currency securities (shares)
