Workbook

Sheet Jan
A1: PHILIPPINE INVESTMENT FUNDS ASSOCIATION, INC.
A2: MUTUAL FUNDS STATISTICAL REPORT
A3: Month of January 2026
A4: (Amounts in Peso)
I5: F O R - T H E - M O N T H | L5: Y E A R - T O - D A T E
A6: Fund Category | C6: Fund Name | D6: ASSETS | E6: LIABILITIES | F6: NET ASSETS | G6: EQUITY INV. | H6: NO. OF A/C | I6: SALES | J6: REDEMPTIONS | K6: NET SALES | L6: TOTAL SALES | M6: TOTAL REDEMPTIONS | N6: TOTAL NET SALES
A7: Stock Funds
A8: Primarily invested in Peso Securities (shares)
B9: 1 | C9: ALFM Growth Fund, Inc. | D9: 3566138553 | E9: 17961009 | F9: =D9-E9 -> 3548177544 | G9: 3472418894 | H9: 5367 | I9: 2640307 | J9: 48123098 | K9: =I9-J9 -> -45482791 | L9: =I9 -> 2640307 | M9: =J9 -> 48123098 | N9: =L9-M9 -> -45482791
B10: =1+B9 -> 2 | C10: ATRAM Alpha Opportunity Fund, Inc. | D10: 1.1134106e+09 | E10: 31034235 | F10: =D10-E10 -> 1082376401 | G10: 9.1868494e+08 | H10: 4230 | I10: 11186785 | J10: 89968214 | K10: =I10-J10 -> -78781429 | L10: =I10 -> 11186785 | M10: =J10 -> 89968214 | N10: =L10-M10 -> -78781429
B11: =1+B10 -> 3 | C11: ATRAM Phil. Equity Opportunity Fund, Inc. | D11: 9.624404e+08 | E11: 3514099.3 | F11: =D11-E11 -> 9.5892631e+08 | G11: 9.0628747e+08 | H11: 2354 | I11: 5938717.9 | J11: 46048364 | K11: =I11-J11 -> -40109646 | L11: =I11 -> 5938717.9 | M11: =J11 -> 46048364 | N11: =L11-M11 -> -40109646
B12: =1+B11 -> 4 | C12: Climbs Share Capital Equity Investment Fund Corp. | D12: 5.1005355e+08 | E12: 20594822 | F12: =D12-E12 -> 489458724 | G12: 2.7184791e+08 | H12: 1706 | I12: 63500 | J12: 16442436 | K12: =I12-J12 -> -16378936 | L12: =I12 -> 63500 | M12: =J12 -> 16442436 | N12: =L12-M12 -> -16378936
B13: =1+B12 -> 5 | C13: First Metro Consumer Fund, Inc. | D13: 275598731 | E13: 801995 | F13: =D13-E13 -> 274796736 | G13: 242385987 | H13: 1075 | I13: 148991 | J13: 730052 | K13: =I13-J13 -> -581061 | L13: =I13 -> 148991 | M13: =J13 -> 730052 | N13: =L13-M13 -> -581061
B14: =1+B13 -> 6 | C14: First Metro Save and Learn Equity Fund, Inc. | D14: 2432018800 | E14: 10360781 | F14: =D14-E14 -> 2421658019 | G14: 2268011103 | H14: 15255 | I14: 6409132 | J14: 46378258 | K14: =I14-J14 -> -39969126 | L14: =I14 -> 6409132 | M14: =J14 -> 46378258 | N14: =L14-M14 -> -39969126
B15: =1+B14 -> 7 | C15: First Metro Save and Learn Phil. Index Fund, Inc. | D15: 66587822 | E15: 335772 | F15: =D15-E15 -> 66252050 | G15: 65394638 | H15: 506 | I15: 313220 | J15: 114913 | K15: =I15-J15 -> 198307 | L15: =I15 -> 313220 | M15: =J15 -> 114913 | N15: =L15-M15 -> 198307
B16: =1+B15 -> 8 | C16: MBG Equity Investment Fund, Inc. | D16: 22990822 | E16: 783768 | F16: =D16-E16 -> 22207054 | G16: 19955895 | H16: 35 | I16: 0 | J16: 0 | K16: =I16-J16 -> 0 | L16: =I16 -> 0 | M16: =J16 -> 0 | N16: =L16-M16 -> 0
B17: =1+B16 -> 9 | C17: PAMI Equity Index Fund, Inc. | D17: 933061460 | E17: 38516684 | F17: =D17-E17 -> 894544776 | G17: 906635245 | H17: 10441 | I17: 0 | J17: 15347736 | K17: =I17-J17 -> -15347736 | L17: =I17 -> 0 | M17: =J17 -> 15347736 | N17: =L17-M17 -> -15347736
B18: =1+B17 -> 10 | C18: Philam Strategic Growth Fund, Inc. | D18: 2860346569 | E18: 24485246 | F18: =D18-E18 -> 2835861323 | G18: 2784641521 | H18: 9921 | I18: 0 | J18: 24094015 | K18: =I18-J18 -> -24094015 | L18: =I18 -> 0 | M18: =J18 -> 24094015 | N18: =L18-M18 -> -24094015
B19: =1+B18 -> 11 | C19: Philequity Dividend Yield Fund, Inc. | D19: 2.6415932e+09 | E19: 12607637 | F19: =D19-E19 -> 2628985593 | G19: 2.3965596e+09 | H19: 5131 | I19: 21263667 | J19: 45785337 | K19: =I19-J19 -> -24521670 | L19: =I19 -> 21263667 | M19: =J19 -> 45785337 | N19: =L19-M19 -> -24521670
B20: =1+B19 -> 12 | C20: Philequity Fund, Inc. | D20: 8.293483e+09 | E20: 33130926 | F20: =D20-E20 -> 8260352045 | G20: 7.9557918e+09 | H20: 30275 | I20: 10285233 | J20: 82475086 | K20: =I20-J20 -> -72189853 | L20: =I20 -> 10285233 | M20: =J20 -> 82475086 | N20: =L20-M20 -> -72189853
B21: =1+B20 -> 13 | C21: Philequity MSCI Phil. Index Fund, Inc. | D21: 3.2162002e+08 | E21: 1091529.8 | F21: =D21-E21 -> 3.2052849e+08 | G21: 3.2003943e+08 | H21: 861 | I21: 285074.58 | J21: 2593679 | K21: =I21-J21 -> -2308604.5 | L21: =I21 -> 285074.58 | M21: =J21 -> 2593679 | N21: =L21-M21 -> -2308604.5
... B27: =1+B26 -> 19 | C27: United Fund, Inc. | D27: 5.7953536e+08 | E27: 25579701 | F27: =D27-E27 -> 5.5395566e+08 | G27: 5.1956372e+08 | H27: 1170 | I27: 285318.86 | J27: 470423.67 | K27: =I27-J27 -> -185104.81 | L27: =I27 -> 285318.86 | M27: =J27 -> 470423.67 | N27: =L27-M27 -> -185104.81
A28: Primarily invested in Peso Securities (units)
B29: =1+B27 -> 20 | C29: COL Equity Index Unitized Mutual Fund, Inc. | D29: 2.5048852e+08 | E29: 1360125.8 | F29: =D29-E29 -> 2.4912839e+08 | G29: 2.4678681e+08 | H29: 5154 | I29: 6178380.4 | J29: 30041034 | K29: =I29-J29 -> -23862654 | L29: =I29 -> 6178380.4 | M29: =J29 -> 30041034 | N29: =L29-M29 -> -23862654
B30: =1+B29 -> 21 | C30: COL Strategic Growth Equity Unitized Mutual Fund, Inc. | D30: 3.2727454e+08 | E30: 3848075.7 | F30: =D30-E30 -> 3.2342647e+08 | G30: 2.14631e+08 | H30: 8382 | I30: 4896023.6 | J30: 47996785 | K30: =I30-J30 -> -43100761 | L30: =I30 -> 4896023.6 | M30: =J30 -> 47996785 | N30: =L30-M30 -> -43100761
B31: =1+B30 -> 22 | C31: Philequity Alpha One Fund, Inc. | D31: 2.158626e+08 | E31: 5582137.1 | F31: =D31-E31 -> 2.1028046e+08 | G31: 2.0467063e+08 | H31: 1054 | I31: 146509.33 | J31: 2753696.9 | K31: =I31-J31 -> -2607187.6 | L31: =I31 -> 146509.33 | M31: =J31 -> 2753696.9 | N31: =L31-M31 -> -2607187.6
B32: =1+B31 -> 23 | C32: Philippine Stock Index Fund Corp. | D32: 546972960 | E32: 10112326 | F32: =D32-E32 -> 536860634 | G32: 529827579 | H32: 795947 | I32: 8712309 | J32: 77321355 | K32: =I32-J32 -> -68609046 | L32: =I32 -> 8712309 | M32: =J32 -> 77321355 | N32: =L32-M32 -> -68609046
A33: Exchange Traded Fund
B34: =1+B32 -> 24 | C34: First Metro Phil. Equity Exchange Traded Fund, Inc. | D34: 1341582675 | E34: 2136945 | F34: =D34-E34 -> 1339445730 | G34: 1338437592 | H34: 3263 | I34: 0 | J34: 28553361 | K34: =I34-J34 -> -28553361 | L34: =I34 -> 0 | M34: =J34 -> 28553361 | N34: =L34-M34 -> -28553361
A35: Sub total - Peso Currency | D35: =SUM(D9:D34) -> 51317428461 | E35: =SUM(E9:E34) -> 5.8936543e+08 | F35: =SUM(F9:F34) -> 50728063030 | G35: =SUM(G9:G34) -> 48750469713 | H35: =SUM(H9:H34) -> 1072637 | I35: =SUM(I9:I34) -> 1.1282018e+08 | J35: =SUM(J9:J34) -> 1257421872 | K35: =SUM(K9:K34) -> -1144601691 | ... N35: =SUM(N9:N34) -> -1144601691
A36: Primarily invested in foreign currency securities (shares)
B37: =1+B34 -> 25 | C37: ATRAM AsiaPlus Equity Fund, Inc. | D37: 28712054 | E37: 239289.44 | F37: =D37-E37 -> 28472765 | G37: 0 | H37: 44 | I37: 11731.39 | J37: 4556127.2 | K37: =I37-J37 -> -4544395.8 | L37: =I37 -> 11731.39 | M37: =J37 -> 4556127.2 | N37: =L37-M37 -> -4544395.8
B38: =1+B37 -> 26 | C38: Sun Life Prosperity World Voyager Fund, Inc. | D38: 2454518648 | E38: 114033147 | F38: =D38-E38 -> 2340485501 | G38: 0 | H38: 3342 | I38: 119246734 | J38: 41066033 | K38: =I38-J38 -> 78180701 | L38: =I38 -> 119246734 | M38: =J38 -> 41066033 | N38: =L38-M38 -> 78180701
A39: Sub total - US Currency | D39: =SUM(D37:D38) -> 2483230702 | E39: =SUM(E37:E38) -> 1.1427244e+08 | F39: =SUM(F37:F38) -> 2368958266 | G39: =SUM(G37:G38) -> 0 | H39: =SUM(H37:H38) -> 3386 | I39: =SUM(I37:I38) -> 1.1925847e+08 | J39: =SUM(J37:J38) -> 45622160 | K39: =SUM(K37:K38) -> 73636305 | ... N39: =SUM(N37:N38) -> 73636305
A40: Sub total - stock funds | D40: =D35+D39 -> 53800659163 | E40: =E35+E39 -> 7.0363787e+08 | F40: =F35+F39 -> 53097021296 | G40: =G35+G39 -> 48750469713 | H40: =H35+H39 -> 1076023 | I40: =I35+I39 -> 2.3207865e+08 | J40: =J35+J39 -> 1303044032 | K40: =K35+K39 -> -1070965386 | ... N40: =N35+N39 -> -1070965386
A41: Balanced Funds
A42: Primarily invested in Peso Securities (shares)
B43: =1+B38 -> 27 | C43: ATRAM Philippine Balanced Fund, Inc. | D43: 4.1411202e+08 | E43: 21698969 | F43: =D43-E43 -> 3.9241305e+08 | G43: 1.9453811e+08 | H43: 2316 | I43: 488299.81 | J43: 4979089 | K43: =I43-J43 -> -4490789.2 | L43: =I43 -> 488299.81 | M43: =J43 -> 4979089 | N43: =L43-M43 -> -4490789.2
B44: =1+B43 -> 28 | C44: ATRAM Unicapital Diversified Growth Fund, Inc. | D44: 1.2118598e+08 | E44: 3503422.8 | F44: =D44-E44 -> 1.1768256e+08 | G44: 28732505 | H44: 862 | I44: 631898.87 | J44: 1675298.6 | K44: =I44-J44 -> -1043399.8 | L44: =I44 -> 631898.87 | M44: =J44 -> 1675298.6 | N44: =L44-M44 -> -1043399.8
B45: =1+B44 -> 29 | C45: First Metro Save and Learn Balanced Fund, Inc. | D45: 581092411 | E45: 12434266 | F45: =D45-E45 -> 568658145 | G45: 276274116 | H45: 4546 | I45: 550899 | J45: 8263014 | K45: =I45-J45 -> -7712115 | L45: =I45 -> 550899 | M45: =J45 -> 8263014 | N45: =L45-M45 -> -7712115
B46: =1+B45 -> 30 | C46: First Metro Save and Learn F.O.C.C.U.S. Dynamic Fund, Inc. | D46: 520482012 | E46: 59905593 | F46: =D46-E46 -> 460576419 | G46: 320545981 | H46: 542 | I46: 6180698 | J46: 1547131 | K46: =I46-J46 -> 4633567 | L46: =I46 -> 6180698 | M46: =J46 -> 1547131 | N46: =L46-M46 -> 4633567
B47: =1+B46 -> 31 | C47: NCM Mutual Fund of the Phils., Inc. | D47: 328465080 | E47: 1790936 | F47: =D47-E47 -> 326674144 | G47: 163653423 | H47: 45 | I47: 0 | J47: 0 | K47: =I47-J47 -> 0 | L47: =I47 -> 0 | M47: =J47 -> 0 | N47: =L47-M47 -> 0
B48: =1+B47 -> 32 | C48: PAMI Horizon Fund, Inc. | D48: 406824799 | E48: 2652298 | F48: =D48-E48 -> 404172501 | G48: 203061392 | H48: 9385 | I48: 34010 | J48: 2247949 | K48: =I48-J48 -> -2213939 | L48: =I48 -> 34010 | M48: =J48 -> 2247949 | N48: =L48-M48 -> -2213939
B49: =1+B48 -> 33 | C49: Philam Fund, Inc. | D49: 1704080271 | E49: 12941025 | F49: =D49-E49 -> 1691139246 | G49: 859953332 | H49: 6641 | I49: 326925 | J49: 11967103 | K49: =I49-J49 -> -11640178 | L49: =I49 -> 326925 | M49: =J49 -> 11967103 | N49: =L49-M49 -> -11640178
B50: =1+B49 -> 34 | C50: Solidaritas Fund, Inc. | D50: 117773917 | E50: 157439 | F50: =D50-E50 -> 117616478 | G50: 59971320 | H50: 152 | I50: 0 | J50: 513714 | K50: =I50-J50 -> -513714 | L50: =I50 -> 0 | M50: =J50 -> 513714 | N50: =L50-M50 -> -513714
B51: =1+B50 -> 35 | C51: Sun Life Prosperity Balanced Fund, Inc. | D51: 4955647949 | E51: 43515922 | F51: =D51-E51 -> 4912132027 | G51: 2443248545 | H51: 54819 | I51: 4575893 | J51: 70248636 | K51: =I51-J51 -> -65672743 | L51: =I51 -> 4575893 | M51: =J51 -> 70248636 | N51: =L51-M51 -> -65672743
B52: =1+B51 -> 36 | C52: Sun Life Prosperity Dynamic Fund, Inc. | D52: 448851259 | E52: 2253048 | F52: =D52-E52 -> 446598211 | G52: 229007823 | H52: 5003 | I52: 0 | J52: 15350913 | K52: =I52-J52 -> -15350913 | L52: =I52 -> 0 | M52: =J52 -> 15350913 | N52: =L52-M52 -> -15350913
A53: Primarily invested in Peso Securities (units)
B54: =1+B52 -> 37 | C54: BPI Wealth Builder Multi-Asset Mutual Fund, Inc. 2 | D54: 993355935 | E54: 2967104 | F54: =D54-E54 -> 990388831 | G54: 72545460 | H54: 27070 | I54: 47633372 | J54: 8185812 | K54: =I54-J54 -> 39447560 | L54: =I54 -> 47633372 | M54: =J54 -> 8185812 | N54: =L54-M54 -> 39447560
B55: =1+B54 -> 38 | C55: Sun Life Prosperity Achiever Fund 2028, Inc. | D55: 69688276 | E55: 402716 | F55: =D55-E55 -> 69285560 | G55: 10734056 | H55: 1279 | I55: 58000 | J55: 1172903 | K55: =I55-J55 -> -1114903 | L55: =I55 -> 58000 | M55: =J55 -> 1172903 | N55: =L55-M55 -> -1114903
B56: =1+B55 -> 39 | C56: Sun Life Prosperity Achiever Fund 2038, Inc. | D56: 54265949 | E56: 1360548 | F56: =D56-E56 -> 52905401 | G56: 36191329 | H56: 520 | I56: 9500 | J56: 233836 | K56: =I56-J56 -> -224336 | L56: =I56 -> 9500 | M56: =J56 -> 233836 | N56: =L56-M56 -> -224336
B57: =1+B56 -> 40 | C57: Sun Life Prosperity Achiever Fund 2048, Inc. | D57: 49790476 | E57: 930281 | F57: =D57-E57 -> 48860195 | G57: 40405403 | H57: 257 | I57: 16000 | J57: 210501 | K57: =I57-J57 -> -194501 | L57: =I57 -> 16000 | M57: =J57 -> 210501 | N57: =L57-M57 -> -194501
A58: Sub total - Peso Currency | D58: =SUM(D43:D57) -> 10765616337 | E58: =SUM(E43:E57) -> 1.6651357e+08 | F58: =SUM(F43:F57) -> 10599102769 | G58: =SUM(G43:G57) -> 4938862793 | H58: =SUM(H43:H57) -> 113437 | I58: =SUM(I43:I57) -> 60505496 | J58: =SUM(J43:J57) -> 1.265959e+08 | K58: =SUM(K43:K57) -> -66090404 | ... N58: =SUM(N43:N57) -> -66090404
A59: Primarily invested in foreign currency securities (shares)
B60: =1+B57 -> 41 | C60: Cocolife Dollar Fund Builder, Inc. | D60: 72399065 | E60: 348075.67 | F60: =D60-E60 -> 72050989 | G60: 0 | H60: 48 | I60: 0 | J60: 0 | K60: =I60-J60 -> 0 | L60: =I60 -> 0 | M60: =J60 -> 0 | N60: =L60-M60 -> 0
B61: =1+B60 -> 42 | C61: PAMI Asia Balanced Fund, Inc. | D61: 332893652 | E61: 483975 | F61: =D61-E61 -> 332409677 | G61: 176563802 | H61: 195 | I61: 0 | J61: 4162032 | K61: =I61-J61 -> -4162032 | L61: =I61 -> 0 | M61: =J61 -> 4162032 | N61: =L61-M61 -> -4162032
B62: =1+B61 -> 43 | C62: Sun Life Prosperity Dollar Advantage Fund, Inc. | D62: 1852591445 | E62: 77117390 | F62: =D62-E62 -> 1775474055 | G62: 0 | H62: 4353 | I62: 3968637 | J62: 69839724 | K62: =I62-J62 -> -65871087 | L62: =I62 -> 3968637 | M62: =J62 -> 69839724 | N62: =L62-M62 -> -65871087
B63: =1+B62 -> 44 | C63: Sun Life Prosperity Dollar Wellspring Fund, Inc. | D63: 227234784 | E63: 6244028 | F63: =D63-E63 -> 220990756 | G63: 0 | H63: 782 | I63: 207804 | J63: 4890549 | K63: =I63-J63 -> -4682745 | L63: =I63 -> 207804 | M63: =J63 -> 4890549 | N63: =L63-M63 -> -4682745
A64: Sub total - US Currency | D64: =SUM(D60:D63) -> 2485118946 | E64: =SUM(E60:E63) -> 84193469 | F64: =SUM(F60:F63) -> 2400925477 | G64: =SUM(G60:G63) -> 176563802 | H64: =SUM(H60:H63) -> 5378 | I64: =SUM(I60:I63) -> 4176441 | J64: =SUM(J60:J63) -> 78892305 | K64: =SUM(K60:K63) -> -74715864 | ... N64: =SUM(N60:N63) -> -74715864
A65: Sub total - balanced funds | D65: =D58+D64 -> 13250735283 | E65: =E58+E64 -> 2.5070704e+08 | F65: =F58+F64 -> 13000028247 | G65: =G58+G64 -> 5115426595 | H65: =H58+H64 -> 118815 | I65: =I58+I64 -> 64681937 | J65: =J58+J64 -> 2.054882e+08 | K65: =K58+K64 -> -140806268 | ... N65: =N58+N64 -> -140806268
A66: Bond Funds
A67: Primarily invested in Peso Securities (shares)
B68: =1+B63 -> 45 | C68: ALFM Peso Bond Fund, Inc. | D68: 35930269959 | E68: 1282186015 | F68: =D68-E68 -> 34648083944 | G68: 367500000 | H68: 24627 | I68: 197509750 | J68: 268027705 | K68: =I68-J68 -> -70517955 | L68: =I68 -> 197509750 | M68: =J68 -> 268027705 | N68: =L68-M68 -> -70517955
B69: =1+B68 -> 46 | C69: ATRAM Corporate Bond Fund, Inc. | D69: 2.4249695e+08 | E69: 2342530.8 | F69: =D69-E69 -> 240154419 | G69: 0 | H69: 890 | I69: 252060.7 | J69: 2128369.8 | K69: =I69-J69 -> -1876309.1 | L69: =I69 -> 252060.7 | M69: =J69 -> 2128369.8 | N69: =L69-M69 -> -1876309.1
B70: =1+B69 -> 47 | C70: Cocolife Fixed Income Fund, Inc. | D70: 9.3310133e+08 | E70: 9601217.6 | F70: =D70-E70 -> 9.2350011e+08 | G70: 0 | H70: 1764 | I70: 5531221.8 | J70: 13745183 | K70: =I70-J70 -> -8213960.7 | L70: =I70 -> 5531221.8 | M70: =J70 -> 13745183 | N70: =L70-M70 -> -8213960.7
B71: =1+B70 -> 48 | C71: Ekklesia Mutual Fund, Inc. | D71: 172633876 | E71: 157853 | F71: =D71-E71 -> 172476023 | G71: 0 | H71: 128 | I71: 0 | J71: 0 | K71: =I71-J71 -> 0 | L71: =I71 -> 0 | M71: =J71 -> 0 | N71: =L71-M71 -> 0
B72: =1+B71 -> 49 | C72: First Metro Save and Learn Fixed Income Fund, Inc. | D72: 753255750 | E72: 29180965 | F72: =D72-E72 -> 724074785 | G72: 0 | H72: 1653 | I72: 611239 | J72: 24702800 | K72: =I72-J72 -> -24091561 | L72: =I72 -> 611239 | M72: =J72 -> 24702800 | N72: =L72-M72 -> -24091561
B73: =1+B72 -> 50 | C73: Philam Bond Fund, Inc. | D73: 1349976556 | E73: 31263269 | F73: =D73-E73 -> 1318713287 | G73: 0 | H73: 4347 | I73: 2503961 | J73: 5594555 | K73: =I73-J73 -> -3090594 | L73: =I73 -> 2503961 | M73: =J73 -> 5594555 | N73: =L73-M73 -> -3090594
B74: =1+B73 -> 51 | C74: Philam Managed Income Fund, Inc. | D74: 493804802 | E74: 9873808 | F74: =D74-E74 -> 483930994 | G74: 0 | H74: 366 | I74: 0 | J74: 1656591 | K74: =I74-J74 -> -1656591 | L74: =I74 -> 0 | M74: =J74 -> 1656591 | N74: =L74-M74 -> -1656591
B75: =1+B74 -> 52 | C75: Philequity Peso Bond Fund, Inc. | D75: 2.8548903e+08 | E75: 1506270.4 | F75: =D75-E75 -> 2.8398276e+08 | G75: 1 | H75: 3978 | I75: 2962412.3 | J75: 1439387.7 | K75: =I75-J75 -> 1523024.6 | L75: =I75 -> 2962412.3 | M75: =J75 -> 1439387.7 | N75: =L75-M75 -> 1523024.6
B76: =1+B75 -> 53 | C76: Soldivo Bond Fund, Inc. | D76: 2.1595632e+09 | E76: 1.6786578e+08 | F76: =D76-E76 -> 1991697445 | G76: 0 | H76: 751 | I76: 51053387 | J76: 2143506.1 | K76: =I76-J76 -> 48909881 | L76: =I76 -> 51053387 | M76: =J76 -> 2143506.1 | N76: =L76-M76 -> 48909881
B77: =1+B76 -> 54 | C77: Sun Life Prosperity Bond Fund, Inc. | D77: 6445096392 | E77: 43306947 | F77: =D77-E77 -> 6401789445 | G77: 0 | H77: 19909 | I77: 48874526 | J77: 117497989 | K77: =I77-J77 -> -68623463 | L77: =I77 -> 48874526 | M77: =J77 -> 117497989 | N77: =L77-M77 -> -68623463
B78: =1+B77 -> 55 | C78: Sun Life Prosperity GS Fund, Inc. | D78: 144514648 | E78: 300120 | F78: =D78-E78 -> 144214528 | G78: 0 | H78: 2965 | I78: 481387 | J78: 737760 | K78: =I78-J78 -> -256373 | L78: =I78 -> 481387 | M78: =J78 -> 737760 | N78: =L78-M78 -> -256373
A79: Corporate Debt Vehicle (units)
B80: =1+B78 -> 56 | C80: ATRAM Unitized Corporate Debt Vehicle, Inc. 1 | D80: 0 | E80: 0 | F80: =D80-E80 -> 0 | G80: 0 | H80: 0 | I80: 0 | J80: 0 | K80: =I80-J80 -> 0 | L80: =I80 -> 0 | M80: =J80 -> 0 | N80: =L80-M80 -> 0
A81: Sub total - Peso Currency | D81: =SUM(D68:D80) -> 48910202518 | E81: =SUM(E68:E80) -> 1577584774 | F81: =SUM(F68:F80) -> 47332617744 | G81: =SUM(G68:G80) -> 367500001 | H81: =SUM(H68:H80) -> 61378 | I81: =SUM(I68:I80) -> 3.0977994e+08 | J81: =SUM(J68:J80) -> 437673846 | K81: =SUM(K68:K80) -> -1.278939e+08 | ... N81: =SUM(N68:N80) -> -1.278939e+08
A82: Primarily invested in foreign currency securities (shares)
B83: =B80+1 -> 57 | C83: ALFM Dollar Bond Fund, Inc. | D83: 11915049812 | E83: 509270258 | F83: =D83-E83 -> 11405779554 | G83: 0 | H83: 6806 | I83: 46184720 | J83: 90883868 | K83: =I83-J83 -> -44699148 | L83: =I83 -> 46184720 | M83: =J83 -> 90883868 | N83: =L83-M83 -> -44699148
B84: =1+B83 -> 58 | C84: ATRAM Total Return Dollar Bond Fund, Inc. | D84: 50351842 | E84: 2135349 | F84: =D84-E84 -> 48216493 | G84: 0 | H84: 21 | I84: 0 | J84: 0 | K84: =I84-J84 -> 0 | L84: =I84 -> 0 | M84: =J84 -> 0 | N84: =L84-M84 -> 0
B85: =1+B84 -> 59 | C85: First Metro Save and Learn Dollar Bond Fund, Inc. | D85: 323488788 | E85: 2235907 | F85: =D85-E85 -> 321252881 | G85: 0 | H85: 138 | I85: 869907 | J85: 2532986 | K85: =I85-J85 -> -1663079 | L85: =I85 -> 869907 | M85: =J85 -> 2532986 | N85: =L85-M85 -> -1663079
B86: =1+B85 -> 60 | C86: PAMI Global Bond Fund, Inc. | D86: 68970564 | E86: 6195832 | F86: =D86-E86 -> 62774732 | G86: 0 | H86: 23 | I86: 0 | J86: 0 | K86: =I86-J86 -> 0 | L86: =I86 -> 0 | M86: =J86 -> 0 | N86: =L86-M86 -> 0
B87: =1+B86 -> 61 | C87: Philam Dollar Bond Fund, Inc. | D87: 1580266820 | E87: 9266500 | F87: =D87-E87 -> 1571000320 | G87: 0 | H87: 1451 | I87: 17481 | J87: 7264708 | K87: =I87-J87 -> -7247227 | L87: =I87 -> 17481 | M87: =J87 -> 7264708 | N87: =L87-M87 -> -7247227
B88: =1+B87 -> 62 | C88: Philequity Dollar Income Fund, Inc. | D88: 2.2091462e+08 | E88: 1280059.9 | F88: =D88-E88 -> 2.1963456e+08 | G88: 1 | H88: 92 | I88: 170694 | J88: 209393.27 | K88: =I88-J88 -> -38699.27 | L88: =I88 -> 170694 | M88: =J88 -> 209393.27 | N88: =L88-M88 -> -38699.27
B89: =1+B88 -> 63 | C89: Sun Life Prosperity Dollar Abundance Fund, Inc. | D89: 449151259 | E89: 37274009 | F89: =D89-E89 -> 411877250 | G89: 0 | H89: 2664 | I89: 2435705 | J89: 41580333 | K89: =I89-J89 -> -39144628 | L89: =I89 -> 2435705 | M89: =J89 -> 41580333 | N89: =L89-M89 -> -39144628
A90: Sub total - US Currency | D90: =SUM(D83:D89) -> 14608193707 | E90: =SUM(E83:E89) -> 5.6765791e+08 | F90: =SUM(F83:F89) -> 14040535792 | G90: =SUM(G83:G89) -> 1 | H90: =SUM(H83:H89) -> 11195 | I90: =SUM(I83:I89) -> 49678507 | J90: =SUM(J83:J89) -> 1.4247129e+08 | K90: =SUM(K83:K89) -> -92792781 | ... N90: =SUM(N83:N89) -> -92792781
B91: =1+B89 -> 64 | C91: ALFM Euro Bond Fund, Inc. | D91: 736370229 | E91: 5496190 | F91: =D91-E91 -> 730874039 | G91: 0 | H91: 562 | I91: 3002781 | J91: 39065055 | K91: =I91-J91 -> -36062274 | L91: =I91 -> 3002781 | M91: =J91 -> 39065055 | N91: =L91-M91 -> -36062274
A92: Sub total - Euro Currency | D92: =SUM(D91) -> 736370229 | E92: =SUM(E91) -> 5496190 | F92: =SUM(F91) -> 730874039 | G92: =SUM(G91) -> 0 | H92: =SUM(H91) -> 562 | I92: =SUM(I91) -> 3002781 | J92: =SUM(J91) -> 39065055 | K92: =SUM(K91) -> -36062274 | ... N92: =SUM(N91) -> -36062274
A93: Sub total - bond funds | D93: =D81+D90+D92 -> 64254766454 | E93: =E81+E90+E92 -> 2150738879 | F93: =F81+F90+F92 -> 62104027575 | G93: =G81+G90+G92 -> 367500002 | H93: =H81+H90+H92 -> 73135 | I93: =I81+I90+I92 -> 3.6246123e+08 | J93: =J81+J90+J92 -> 6.1921019e+08 | K93: =K81+K90+K92 -> -2.5674896e+08 | ... N93: =N81+N90+N92 -> -2.5674896e+08
A94: Money Market Funds
A95: Primarily invested in Peso Securities (shares)
B96: =B91+1 -> 65 | C96: AIB Money Market Mutual Fund, Inc. | D96: 1.7594266e+08 | E96: 326450.83 | F96: =D96-E96 -> 1.7561621e+08 | G96: 0 | H96: 56 | I96: 73000 | J96: 18188.87 | K96: =I96-J96 -> 54811.13 | L96: =I96 -> 73000 | M96: =J96 -> 18188.87 | N96: =L96-M96 -> 54811.13
B97: =B96+1 -> 66 | C97: ALFM Money Market Fund, Inc. | D97: 19325779418 | E97: 10269025 | F97: =D97-E97 -> 19315510393 | G97: 0 | H97: 20196 | I97: 369396 | J97: 230327094 | K97: =I97-J97 -> -229957698 | L97: =I97 -> 369396 | M97: =J97 -> 230327094 | N97: =L97-M97 -> -229957698
B98: =B97+1 -> 67 | C98: First Metro Save and Learn Money Market Fund, Inc. | D98: 2406524511 | E98: 4488624 | F98: =D98-E98 -> 2402035887 | G98: 0 | H98: 1245 | I98: 53133889 | J98: 101152984 | K98: =I98-J98 -> -48019095 | L98: =I98 -> 53133889 | M98: =J98 -> 101152984 | N98: =L98-M98 -> -48019095
B99: =B98+1 -> 68 | C99: Sun Life Prosperity Peso Starter Fund, Inc. | D99: 10183654571 | E99: 57740728 | F99: =D99-E99 -> 10125913843 | G99: 0 | H99: 74761 | I99: 264056073 | J99: 869788808 | K99: =I99-J99 -> -605732735 | L99: =I99 -> 264056073 | M99: =J99 -> 869788808 | N99: =L99-M99 -> -605732735
A100: Primarily invested in Peso Securities (units)
B101: =1+B99 -> 69 | C101: ALFM Money Market Fund, Inc. | D101: 14002734625 | E101: 7257744 | F101: =D101-E101 -> 13995476881 | G101: 0 | H101: 32583 | I101: 1284824875 | J101: 1078391271 | K101: =I101-J101 -> 206433604 | L101: =I101 -> 1284824875 | M101: =J101 -> 1078391271 | N101: =L101-M101 -> 206433604
A102: Sub total - Peso Currency | D102: =SUM(D96:D99)+D101 -> 46094635788 | E102: =SUM(E96:E99)+E101 -> 80082572 | F102: =SUM(F96:F99)+F101 -> 46014553216 | G102: =SUM(G96:G99)+G101 -> 0 | H102: =SUM(H96:H99)+H101 -> 128841 | I102: =SUM(I96:I99)+I101 -> 1602457233 | J102: =SUM(J96:J99)+J101 -> 2279678346 | K102: =SUM(K96:K99)+K101 -> -6.7722111e+08 | ... N102: =SUM(N96:N99)+N101 -> -6.7722111e+08
A103: Primarily invested in foreign currency securities (shares)
B104: =1+B101 -> 70 | C104: Sun Life Prosperity Dollar Starter Fund, Inc. | D104: 1274006009 | E104: 4514777 | F104: =D104-E104 -> 1269491232 | G104: 0 | H104: 3972 | I104: 53630200 | J104: 184689484 | K104: =I104-J104 -> -131059284 | L104: =I104 -> 53630200 | M104: =J104 -> 184689484 | N104: =L104-M104 -> -131059284
A105: Sub total - US Currency | D105: =SUM(D104) -> 1274006009 | E105: =SUM(E104) -> 4514777 | F105: =SUM(F104) -> 1269491232 | G105: =SUM(G104) -> 0 | H105: =SUM(H104) -> 3972 | I105: =SUM(I104) -> 53630200 | J105: =SUM(J104) -> 184689484 | K105: =SUM(K104) -> -131059284 | ... N105: =SUM(N104) -> -131059284
...

Sheet Feb
A1: PHILIPPINE INVESTMENT FUNDS ASSOCIATION, INC.
A2: MUTUAL FUNDS STATISTICAL REPORT
A3: Month of February 2026
A4: (Amounts in Peso)
I5: F O R - T H E - M O N T H | L5: Y E A R - T O - D A T E
A6: Fund Category | C6: Fund Name | D6: ASSETS | E6: LIABILITIES | F6: NET ASSETS | G6: EQUITY INV. | H6: NO. OF A/C | I6: SALES | J6: REDEMPTIONS | K6: NET SALES | L6: TOTAL SALES | M6: TOTAL REDEMPTIONS | N6: TOTAL NET SALES
A7: Stock Funds
A8: Primarily invested in Peso Securities (shares)
B9: 1 | C9: ALFM Growth Fund, Inc. | D9: 3678383403 | E9: 29551293 | F9: =D9-E9 -> 3648832110 | G9: 3606659841 | H9: 5290 | I9: 5384497 | J9: 46958163 | K9: =I9-J9 -> -41573666 | L9: =I9+Jan!L9 -> 8024804 | M9: =J9+Jan!M9 -> 95081261 | N9: =L9-M9 -> -87056457
B10: =1+B9 -> 2 | C10: ATRAM Alpha Opportunity Fund, Inc. | D10: 1.1176472e+09 | E10: 10930035 | F10: =D10-E10 -> 1106717117 | G10: 1.0367e+09 | H10: 4210 | I10: 13163391 | J10: 13192961 | K10: =I10-J10 -> -29570.12 | L10: =I10+Jan!L10 -> 24350175 | M10: =J10+Jan!M10 -> 1.0316117e+08 | N10: =L10-M10 -> -78811000
B11: =1+B10 -> 3 | C11: ATRAM Phil. Equity Opportunity Fund, Inc. | D11: 1.07207e+09 | E11: 77750965 | F11: =D11-E11 -> 994319013 | G11: 9.3161594e+08 | H11: 2348 | I11: 2000296 | J11: 7773113.8 | K11: =I11-J11 -> -5772817.9 | L11: =I11+Jan!L11 -> 7939013.9 | M11: =J11+Jan!M11 -> 53821478 | N11: =L11-M11 -> -45882464
B12: =1+B11 -> 4 | C12: Climbs Share Capital Equity Investment Fund Corp. | D12: 5.1885957e+08 | E12: 20165405 | F12: =D12-E12 -> 4.9869416e+08 | G12: 2.7663693e+08 | H12: 1706 | I12: 725792.5 | J12: 564740.09 | K12: =I12-J12 -> 161052.41 | L12: =I12+Jan!L12 -> 789292.5 | M12: =J12+Jan!M12 -> 17007176 | N12: =L12-M12 -> -16217884
B13: =1+B12 -> 5 | C13: First Metro Consumer Fund, Inc. | D13: 279152771 | E13: 10583956 | F13: =D13-E13 -> 268568815 | G13: 263653374 | H13: 1065 | I13: 99185 | J13: 16654032 | K13: =I13-J13 -> -16554847 | L13: =I13+Jan!L13 -> 248176 | M13: =J13+Jan!M13 -> 17384084 | N13: =L13-M13 -> -17135908
B14: =1+B13 -> 6 | C14: First Metro Save and Learn Equity Fund, Inc. | D14: 2648792030 | E14: 156007523 | F14: =D14-E14 -> 2492784507 | G14: 2329860987 | H14: 15162 | I14: 1645204 | J14: 31133161 | K14: =I14-J14 -> -29487957 | L14: =I14+Jan!L14 -> 8054336 | M14: =J14+Jan!M14 -> 77511419 | N14: =L14-M14 -> -69457083
B15: =1+B14 -> 7 | C15: First Metro Save and Learn Phil. Index Fund, Inc. | D15: 69102317 | E15: 403828 | F15: =D15-E15 -> 68698489 | G15: 67798081 | H15: 503 | I15: 137742 | J15: 362141 | K15: =I15-J15 -> -224399 | L15: =I15+Jan!L15 -> 450962 | M15: =J15+Jan!M15 -> 477054 | N15: =L15-M15 -> -26092
B16: =1+B15 -> 8 | C16: MBG Equity Investment Fund, Inc. | D16: 22351116 | E16: 653494 | F16: =D16-E16 -> 21697622 | G16: 19239167 | H16: 35 | I16: 0 | J16: 0 | K16: =I16-J16 -> 0 | L16: =I16+Jan!L16 -> 0 | M16: =J16+Jan!M16 -> 0 | N16: =L16-M16 -> 0
B17: =1+B16 -> 9 | C17: PAMI Equity Index Fund, Inc. | D17: 949293850 | E17: 22894348 | F17: =D17-E17 -> 926399502 | G17: 939380229 | H17: 10374 | I17: 0 | J17: 7489189 | K17: =I17-J17 -> -7489189 | L17: =I17+Jan!L17 -> 0 | M17: =J17+Jan!M17 -> 22836925 | N17: =L17-M17 -> -22836925
B18: =1+B17 -> 10 | C18: Philam Strategic Growth Fund, Inc. | D18: 2952917109 | E18: 43247875 | F18: =D18-E18 -> 2909669234 | G18: 2892320242 | H18: 9863 | I18: 0 | J18: 40639309 | K18: =I18-J18 -> -40639309 | L18: =I18+Jan!L18 -> 0 | M18: =J18+Jan!M18 -> 64733324 | N18: =L18-M18 -> -64733324
B19: =1+B18 -> 11 | C19: Philequity Dividend Yield Fund, Inc. | D19: 2.7067133e+09 | E19: 51127712 | F19: =D19-E19 -> 2655585579 | G19: 2.5908914e+09 | H19: 5155 | I19: 10795622 | J19: 95950687 | K19: =I19-J19 -> -85155065 | L19: =I19+Jan!L19 -> 32059289 | M19: =J19+Jan!M19 -> 1.4173602e+08 | N19: =L19-M19 -> -1.0967673e+08
B20: =1+B19 -> 12 | C20: Philequity Fund, Inc. | D20: 8.6588903e+09 | E20: 1.1530918e+08 | F20: =D20-E20 -> 8543581153 | G20: 8.1371773e+09 | H20: 30091 | I20: 10285233 | J20: 82475086 | K20: =I20-J20 -> -72189853 | L20: =I20+Jan!L20 -> 20570466 | M20: =J20+Jan!M20 -> 1.6495017e+08 | N20: =L20-M20 -> -1.4437971e+08
B21: =1+B20 -> 13 | C21: Philequity MSCI Phil. Index Fund, Inc. | D21: 3.0646961e+08 | E21: 1001407.2 | F21: =D21-E21 -> 3.0546821e+08 | G21: 3.0443688e+08 | H21: 869 | I21: 393524.1 | J21: 29784917 | K21: =I21-J21 -> -29391393 | L21: =I21+Jan!L21 -> 678598.68 | M21: =J21+Jan!M21 -> 32378596 | N21: =L21-M21 -> -31699997
... B27: =1+B26 -> 19 | C27: United Fund, Inc. | D27: 5.6147379e+08 | E27: 2058816.7 | F27: =D27-E27 -> 5.5941498e+08 | G27: 5.0932384e+08 | H27: 1175 | I27: 141976.67 | J27: 301093.29 | K27: =I27-J27 -> -159116.62 | L27: =I27+Jan!L27 -> 427295.53 | M27: =J27+Jan!M27 -> 771516.96 | N27: =L27-M27 -> -344221.43
A28: Primarily invested in Peso Securities (units)
B29: =1+B27 -> 20 | C29: COL Equity Index Unitized Mutual Fund, Inc. | D29: 2.561967e+08 | E29: 2846688 | F29: =D29-E29 -> 2.5335001e+08 | G29: 2.5502866e+08 | H29: 5195 | I29: 4900573 | J29: 11350341 | K29: =I29-J29 -> -6449767.7 | L29: =I29+Jan!L29 -> 11078953 | M29: =J29+Jan!M29 -> 41391375 | N29: =L29-M29 -> -30312421
B30: =1+B29 -> 21 | C30: COL Strategic Growth Equity Unitized Mutual Fund, Inc. | D30: 3.2552876e+08 | E30: 3335942 | F30: =D30-E30 -> 322192821 | G30: 2.4044268e+08 | H30: 8510 | I30: 3451746.9 | J30: 11118657 | K30: =I30-J30 -> -7666910.3 | L30: =I30+Jan!L30 -> 8347770.5 | M30: =J30+Jan!M30 -> 59115442 | N30: =L30-M30 -> -50767671
B31: =1+B30 -> 22 | C31: Philequity Alpha One Fund, Inc. | D31: 2.1490907e+08 | E31: 2990476.1 | F31: =D31-E31 -> 2.1191859e+08 | G31: 2.1030811e+08 | H31: 1045 | I31: 168483.27 | J31: 3699126 | K31: =I31-J31 -> -3530642.7 | L31: =I31+Jan!L31 -> 314992.6 | M31: =J31+Jan!M31 -> 6452822.9 | N31: =L31-M31 -> -6137830.3
B32: =1+B31 -> 23 | C32: Philippine Stock Index Fund Corp. | D32: 558979791 | E32: 4113835 | F32: =D32-E32 -> 554865956 | G32: 549842730 | H32: 799580 | I32: 15068268 | J32: 20407849 | K32: =I32-J32 -> -5339581 | L32: =I32+Jan!L32 -> 23780577 | M32: =J32+Jan!M32 -> 97729204 | N32: =L32-M32 -> -73948627
A33: Exchange Traded Fund
B34: =1+B32 -> 24 | C34: First Metro Phil. Equity Exchange Traded Fund, Inc. | D34: 1365982115 | E34: 2157787 | F34: =D34-E34 -> 1363824328 | G34: 1364289439 | H34: 3234 | I34: 8414744 | J34: 48571714 | K34: =I34-J34 -> -40156970 | L34: =I34+Jan!L34 -> 8414744 | M34: =J34+Jan!M34 -> 77125075 | N34: =L34-M34 -> -68710331
A35: Sub total - Peso Currency | D35: =SUM(D9:D34) -> 52569703204 | E35: =SUM(E9:E34) -> 7.6939971e+08 | F35: =SUM(F9:F34) -> 51800303493 | G35: =SUM(G9:G34) -> 50164847629 | H35: =SUM(H9:H34) -> 1075672 | I35: =SUM(I9:I34) -> 98207906 | J35: =SUM(J9:J34) -> 1095990972 | K35: =SUM(K9:K34) -> -9.9778307e+08 | ... N35: =SUM(N9:N34) -> -2142384757
A36: Primarily invested in foreign currency securities (shares)
B37: =1+B34 -> 25 | C37: ATRAM AsiaPlus Equity Fund, Inc. | D37: 29949336 | E37: 345962.32 | F37: =D37-E37 -> 29603373 | G37: 0 | H37: 43 | I37: 11488.02 | J37: 249258.69 | K37: =I37-J37 -> -237770.67 | L37: =I37+Jan!L37 -> 23219.41 | M37: =J37+Jan!M37 -> 4805385.9 | N37: =L37-M37 -> -4782166.5
B38: =1+B37 -> 26 | C38: Sun Life Prosperity World Voyager Fund, Inc. | D38: 2502584706 | E38: 73412734 | F38: =D38-E38 -> 2429171972 | G38: 0 | H38: 3363 | I38: 112780395 | J38: 11569508 | K38: =I38-J38 -> 101210887 | L38: =I38+Jan!L38 -> 232027129 | M38: =J38+Jan!M38 -> 52635541 | N38: =L38-M38 -> 179391588
A39: Primarily invested in foreign currency securities (units)
B40: =1+B38 -> 27 | C40: Philequity Global Fund, Inc. 3 | D40: 495555.7 | E40: 0 | F40: =D40-E40 -> 495555.7 | G40: 0 | H40: 26 | I40: 495572.14 | J40: 0 | K40: =I40-J40 -> 495572.14 | L40: =I40 -> 495572.14 | M40: =J40 -> 0 | N40: =L40-M40 -> 495572.14
A41: Sub total - US Currency | D41: =SUM(D37:D38)+D40 -> 2533029597 | E41: =SUM(E37:E38)+E40 -> 73758696 | F41: =SUM(F37:F38)+F40 -> 2459270901 | G41: =SUM(G37:G38)+G40 -> 0 | H41: =SUM(H37:H38)+H40 -> 3432 | I41: =SUM(I37:I38)+I40 -> 1.1328746e+08 | J41: =SUM(J37:J38)+J40 -> 11818767 | K41: =SUM(K37:K38)+K40 -> 1.0146869e+08 | ... N41: =SUM(N37:N38)+N40 -> 1.7510499e+08
A42: Sub total - stock funds | D42: =D35+D41 -> 55102732802 | E42: =E35+E41 -> 8.4315841e+08 | F42: =F35+F41 -> 54259574394 | G42: =G35+G41 -> 50164847629 | H42: =H35+H41 -> 1079104 | I42: =I35+I41 -> 2.1149536e+08 | J42: =J35+J41 -> 1107809738 | K42: =K35+K41 -> -8.9631438e+08 | ... N42: =N35+N41 -> -1967279764
A43: Balanced Funds
A44: Primarily invested in Peso Securities (shares)
B45: =1+B40 -> 28 | C45: ATRAM Philippine Balanced Fund, Inc. | D45: 3.9654217e+08 | E45: 1133095.1 | F45: =D45-E45 -> 3.9540907e+08 | G45: 2.0984686e+08 | H45: 2320 | I45: 490945.49 | J45: 5293097.3 | K45: =I45-J45 -> -4802151.8 | L45: =I45+Jan!L43 -> 979245.3 | M45: =J45+Jan!M43 -> 10272186 | N45: =L45-M45 -> -9292941
B46: =1+B45 -> 29 | C46: ATRAM Unicapital Diversified Growth Fund, Inc. | D46: 1.1699287e+08 | E46: 228982.01 | F46: =D46-E46 -> 1.1676389e+08 | G46: 32337622 | H46: 850 | I46: 179113.49 | J46: 1646980.3 | K46: =I46-J46 -> -1467866.9 | L46: =I46+Jan!L44 -> 811012.36 | M46: =J46+Jan!M44 -> 3322279 | N46: =L46-M46 -> -2511266.6
B47: =1+B46 -> 30 | C47: First Metro Save and Learn Balanced Fund, Inc. | D47: 576401023 | E47: 2468913 | F47: =D47-E47 -> 573932110 | G47: 304741794 | H47: 4521 | I47: 322767 | J47: 8814729 | K47: =I47-J47 -> -8491962 | L47: =I47+Jan!L45 -> 873666 | M47: =J47+Jan!M45 -> 17077743 | N47: =L47-M47 -> -16204077
B48: =1+B47 -> 31 | C48: First Metro Save and Learn F.O.C.C.U.S. Dynamic Fund, Inc. | D48: 476714968 | E48: 1587680 | F48: =D48-E48 -> 475127288 | G48: 250350982 | H48: 582 | I48: 11118609 | J48: 1421986 | K48: =I48-J48 -> 9696623 | L48: =I48+Jan!L46 -> 17299307 | M48: =J48+Jan!M46 -> 2969117 | N48: =L48-M48 -> 14330190
B49: =1+B48 -> 32 | C49: NCM Mutual Fund of the Phils., Inc. | D49: 336673897 | E49: 2232667 | F49: =D49-E49 -> 334441230 | G49: 170249971 | H49: 45 | I49: 0 | J49: 0 | K49: =I49-J49 -> 0 | L49: =I49+Jan!L47 -> 0 | M49: =J49+Jan!M47 -> 0 | N49: =L49-M49 -> 0
B50: =1+B49 -> 33 | C50: PAMI Horizon Fund, Inc. | D50: 415347264 | E50: 5089125 | F50: =D50-E50 -> 410258139 | G50: 211426490 | H50: 9367 | I50: 5910 | J50: 2644947 | K50: =I50-J50 -> -2639037 | L50: =I50+Jan!L48 -> 39920 | M50: =J50+Jan!M48 -> 4892896 | N50: =L50-M50 -> -4852976
B51: =1+B50 -> 34 | C51: Philam Fund, Inc. | D51: 1732834208 | E51: 24767024 | F51: =D51-E51 -> 1708067184 | G51: 880636347 | H51: 6597 | I51: 1344883 | J51: 23086629 | K51: =I51-J51 -> -21741746 | L51: =I51+Jan!L49 -> 1671808 | M51: =J51+Jan!M49 -> 35053732 | N51: =L51-M51 -> -33381924
B52: =1+B51 -> 35 | C52: Solidaritas Fund, Inc. | D52: 119371502 | E52: 142278 | F52: =D52-E52 -> 119229224 | G52: 60964060 | H52: 149 | I52: 0 | J52: 922888 | K52: =I52-J52 -> -922888 | L52: =I52+Jan!L50 -> 0 | M52: =J52+Jan!M50 -> 1436602 | N52: =L52-M52 -> -1436602
B53: =1+B52 -> 36 | C53: Sun Life Prosperity Balanced Fund, Inc. | D53: 5014044150 | E53: 43218435 | F53: =D53-E53 -> 4970825715 | G53: 2516123925 | H53: 54836 | I53: 4592784 | J53: 73122278 | K53: =I53-J53 -> -68529494 | L53: =I53+Jan!L51 -> 9168677 | M53: =J53+Jan!M51 -> 143370914 | N53: =L53-M53 -> -134202237
B54: =1+B53 -> 37 | C54: Sun Life Prosperity Dynamic Fund, Inc. | D54: 453849324 | E54: 2504188 | F54: =D54-E54 -> 451345136 | G54: 234581313 | H54: 5003 | I54: 0 | J54: 6517746 | K54: =I54-J54 -> -6517746 | L54: =I54+Jan!L52 -> 0 | M54: =J54+Jan!M52 -> 21868659 | N54: =L54-M54 -> -21868659
A55: Primarily invested in Peso Securities (units)
B56: =1+B54 -> 38 | C56: BPI Wealth Builder Multi-Asset Mutual Fund, Inc. 2 | D56: 1020498755 | E56: 3570154 | F56: =D56-E56 -> 1016928601 | G56: 75280080 | H56: 27426 | I56: 26393123 | J56: 6636181 | K56: =I56-J56 -> 19756942 | L56: =I56+Jan!L54 -> 74026495 | M56: =J56+Jan!M54 -> 14821993 | N56: =L56-M56 -> 59204502
B57: =1+B56 -> 39 | C57: Sun Life Prosperity Achiever Fund 2028, Inc. | D57: 69280060 | E57: 482303 | F57: =D57-E57 -> 68797757 | G57: 11189025 | H57: 1279 | I57: 38000 | J57: 1093529 | K57: =I57-J57 -> -1055529 | L57: =I57+Jan!L55 -> 96000 | M57: =J57+Jan!M55 -> 2266432 | N57: =L57-M57 -> -2170432
B58: =1+B57 -> 40 | C58: Sun Life Prosperity Achiever Fund 2038, Inc. | D58: 54645178 | E58: 330010 | F58: =D58-E58 -> 54315168 | G58: 37778736 | H58: 520 | I58: 10500 | J58: 183870 | K58: =I58-J58 -> -173370 | L58: =I58+Jan!L56 -> 20000 | M58: =J58+Jan!M56 -> 417706 | N58: =L58-M58 -> -397706
B59: =1+B58 -> 41 | C59: Sun Life Prosperity Achiever Fund 2048, Inc. | D59: 50311103 | E59: 237695 | F59: =D59-E59 -> 50073408 | G59: 41549266 | H59: 257 | I59: 8000 | J59: 302360 | K59: =I59-J59 -> -294360 | L59: =I59+Jan!L57 -> 24000 | M59: =J59+Jan!M57 -> 512861 | N59: =L59-M59 -> -488861
A60: Sub total - Peso Currency | D60: =SUM(D45:D59) -> 10833506473 | E60: =SUM(E45:E59) -> 87992549 | F60: =SUM(F45:F59) -> 10745513924 | G60: =SUM(G45:G59) -> 5037056468 | H60: =SUM(H45:H59) -> 113752 | I60: =SUM(I45:I59) -> 44504635 | J60: =SUM(J45:J59) -> 1.3168722e+08 | K60: =SUM(K45:K59) -> -87182586 | ... N60: =SUM(N45:N59) -> -1.5327299e+08
A61: Primarily invested in foreign currency securities (shares)
B62: =1+B59 -> 42 | C62: Cocolife Dollar Fund Builder, Inc. | D62: 70851399 | E62: 305388.07 | F62: =D62-E62 -> 70546010 | G62: 0 | H62: 49 | I62: 0 | J62: 0 | K62: =I62-J62 -> 0 | L62: =I62+Jan!L60 -> 0 | M62: =J62+Jan!M60 -> 0 | N62: =L62-M62 -> 0
B63: =1+B62 -> 43 | C63: PAMI Asia Balanced Fund, Inc. | D63: 338808814 | E63: 628487 | F63: =D63-E63 -> 338180327 | G63: 180016162 | H63: 195 | I63: 0 | J63: 1707612 | K63: =I63-J63 -> -1707612 | L63: =I63+Jan!L61 -> 0 | M63: =J63+Jan!M61 -> 5869644 | N63: =L63-M63 -> -5869644
B64: =1+B63 -> 44 | C64: Sun Life Prosperity Dollar Advantage Fund, Inc. | D64: 1795327392 | E64: 62318985 | F64: =D64-E64 -> 1733008407 | G64: 0 | H64: 4356 | I64: 5070688 | J64: 32629035 | K64: =I64-J64 -> -27558347 | L64: =I64+Jan!L62 -> 9039325 | M64: =J64+Jan!M62 -> 102468759 | N64: =L64-M64 -> -93429434
B65: =1+B64 -> 45 | C65: Sun Life Prosperity Dollar Wellspring Fund, Inc. | D65: 223983751 | E65: 11483650 | F65: =D65-E65 -> 212500101 | G65: 0 | H65: 783 | I65: 57915 | J65: 6080551 | K65: =I65-J65 -> -6022636 | L65: =I65+Jan!L63 -> 265719 | M65: =J65+Jan!M63 -> 10971100 | N65: =L65-M65 -> -10705381
A66: Sub total - US Currency | D66: =SUM(D62:D65) -> 2428971356 | E66: =SUM(E62:E65) -> 74736510 | F66: =SUM(F62:F65) -> 2354234845 | G66: =SUM(G62:G65) -> 180016162 | H66: =SUM(H62:H65) -> 5383 | I66: =SUM(I62:I65) -> 5128603 | J66: =SUM(J62:J65) -> 40417198 | K66: =SUM(K62:K65) -> -35288595 | ... N66: =SUM(N62:N65) -> -110004459
A67: Sub total - balanced funds | D67: =D60+D66 -> 13262477828 | E67: =E60+E66 -> 1.6272906e+08 | F67: =F60+F66 -> 13099748769 | G67: =G60+G66 -> 5217072630 | H67: =H60+H66 -> 119135 | I67: =I60+I66 -> 49633238 | J67: =J60+J66 -> 1.7210442e+08 | K67: =K60+K66 -> -1.2247118e+08 | ... N67: =N60+N66 -> -2.6327745e+08
A68: Bond Funds
A69: Primarily invested in Peso Securities (shares)
B70: =1+B65 -> 46 | C70: ALFM Peso Bond Fund, Inc. | D70: 34895713674 | E70: 194834094 | F70: =D70-E70 -> 34700879580 | G70: 360000000 | H70: 24693 | I70: 234658348 | J70: 291718039 | K70: =I70-J70 -> -57059691 | L70: =I70+Jan!L68 -> 432168098 | M70: =J70+Jan!M68 -> 559745744 | N70: =L70-M70 -> -127577646
B71: =1+B70 -> 47 | C71: ATRAM Corporate Bond Fund, Inc. | D71: 2.4154317e+08 | E71: 13780899 | F71: =D71-E71 -> 2.2776227e+08 | G71: 0 | H71: 882 | I71: 432997.91 | J71: 13372168 | K71: =I71-J71 -> -12939170 | L71: =I71+Jan!L69 -> 685058.61 | M71: =J71+Jan!M69 -> 15500538 | N71: =L71-M71 -> -14815479
B72: =1+B71 -> 48 | C72: Cocolife Fixed Income Fund, Inc. | D72: 9.2706057e+08 | E72: 8765139.1 | F72: =D72-E72 -> 918295426 | G72: 0 | H72: 1764 | I72: 3845387.2 | J72: 10995316 | K72: =I72-J72 -> -7149929.2 | L72: =I72+Jan!L70 -> 9376609.1 | M72: =J72+Jan!M70 -> 24740499 | N72: =L72-M72 -> -15363890
B73: =1+B72 -> 49 | C73: Ekklesia Mutual Fund, Inc. | D73: 172992748 | E73: 144302 | F73: =D73-E73 -> 172848446 | G73: 0 | H73: 127 | I73: 0 | J73: 118247 | K73: =I73-J73 -> -118247 | L73: =I73+Jan!L71 -> 0 | M73: =J73+Jan!M71 -> 118247 | N73: =L73-M73 -> -118247
B74: =1+B73 -> 50 | C74: First Metro Save and Learn Fixed Income Fund, Inc. | D74: 722452764 | E74: 4433481 | F74: =D74-E74 -> 718019283 | G74: 0 | H74: 1642 | I74: 1944163 | J74: 10110035 | K74: =I74-J74 -> -8165872 | L74: =I74+Jan!L72 -> 2555402 | M74: =J74+Jan!M72 -> 34812835 | N74: =L74-M74 -> -32257433
B75: =1+B74 -> 51 | C75: Philam Bond Fund, Inc. | D75: 1338118211 | E75: 30619596 | F75: =D75-E75 -> 1307498615 | G75: 0 | H75: 4316 | I75: 868259 | J75: 14399431 | K75: =I75-J75 -> -13531172 | L75: =I75+Jan!L73 -> 3372220 | M75: =J75+Jan!M73 -> 19993986 | N75: =L75-M75 -> -16621766
B76: =1+B75 -> 52 | C76: Philam Managed Income Fund, Inc. | D76: 494959606 | E76: 9910404 | F76: =D76-E76 -> 485049202 | G76: 0 | H76: 364 | I76: 0 | J76: 763232 | K76: =I76-J76 -> -763232 | L76: =I76+Jan!L74 -> 0 | M76: =J76+Jan!M74 -> 2419823 | N76: =L76-M76 -> -2419823
B77: =1+B76 -> 53 | C77: Philequity Peso Bond Fund, Inc. | D77: 2.8782055e+08 | E77: 1894385.8 | F77: =D77-E77 -> 2.8592616e+08 | G77: 0 | H77: 3990 | I77: 2494829.6 | J77: 600894.91 | K77: =I77-J77 -> 1893934.7 | L77: =I77+Jan!L75 -> 5457242 | M77: =J77+Jan!M75 -> 2040282.6 | N77: =L77-M77 -> 3416959.4
B78: =1+B77 -> 54 | C78: Soldivo Bond Fund, Inc. | D78: 2.0486303e+09 | E78: 3166979.5 | F78: =D78-E78 -> 2045463313 | G78: 0 | H78: 750 | I78: 50035804 | J78: 2128019.4 | K78: =I78-J78 -> 47907785 | L78: =I78+Jan!L76 -> 1.0108919e+08 | M78: =J78+Jan!M76 -> 4271525.5 | N78: =L78-M78 -> 96817666
B79: =1+B78 -> 55 | C79: Sun Life Prosperity Bond Fund, Inc. | D79: 6395148282 | E79: 39614457 | F79: =D79-E79 -> 6355533825 | G79: 0 | H79: 19942 | I79: 52668166 | J79: 132079522 | K79: =I79-J79 -> -79411356 | L79: =I79+Jan!L77 -> 101542692 | M79: =J79+Jan!M77 -> 249577511 | N79: =L79-M79 -> -148034819
B80: =1+B79 -> 56 | C80: Sun Life Prosperity GS Fund, Inc. | D80: 144264131 | E80: 350635 | F80: =D80-E80 -> 143913496 | G80: 0 | H80: 2966 | I80: 268250 | J80: 1229469 | K80: =I80-J80 -> -961219 | L80: =I80+Jan!L78 -> 749637 | M80: =J80+Jan!M78 -> 1967229 | N80: =L80-M80 -> -1217592
A81: Corporate Debt Vehicle (units)
B82: =1+B80 -> 57 | C82: ATRAM Unitized Corporate Debt Vehicle, Inc. 1 | D82: 0 | E82: 0 | F82: =D82-E82 -> 0 | G82: 0 | H82: 0 | I82: 0 | J82: 0 | K82: =I82-J82 -> 0 | L82: =I82+Jan!L80 -> 0 | M82: =J82+Jan!M80 -> 0 | N82: =L82-M82 -> 0
A83: Sub total - Peso Currency | D83: =SUM(D70:D82) -> 47668703987 | E83: =SUM(E70:E82) -> 3.0751437e+08 | F83: =SUM(F70:F82) -> 47361189614 | G83: =SUM(G70:G82) -> 360000000 | H83: =SUM(H70:H82) -> 61436 | I83: =SUM(I70:I82) -> 3.472162e+08 | J83: =SUM(J70:J82) -> 4.7751437e+08 | K83: =SUM(K70:K82) -> -1.3029817e+08 | ... N83: =SUM(N70:N82) -> -2.5819207e+08
A84: Primarily invested in foreign currency securities (shares)
B85: =B82+1 -> 58 | C85: ALFM Dollar Bond Fund, Inc. | D85: 11225574853 | E85: 59324195 | F85: =D85-E85 -> 11166250658 | G85: 0 | H85: 6794 | I85: 76437050 | J85: 131403651 | K85: =I85-J85 -> -54966601 | L85: =I85+Jan!L83 -> 122621770 | M85: =J85+Jan!M83 -> 222287519 | N85: =L85-M85 -> -99665749
B86: =1+B85 -> 59 | C86: ATRAM Total Return Dollar Bond Fund, Inc. | D86: 49455742 | E86: 2039367.7 | F86: =D86-E86 -> 47416374 | G86: 0 | H86: 21 | I86: 0 | J86: 0 | K86: =I86-J86 -> 0 | L86: =I86+Jan!L84 -> 0 | M86: =J86+Jan!M84 -> 0 | N86: =L86-M86 -> 0
B87: =1+B86 -> 60 | C87: First Metro Save and Learn Dollar Bond Fund, Inc. | D87: 316695809 | E87: 4543680 | F87: =D87-E87 -> 312152129 | G87: 0 | H87: 133 | I87: 0 | J87: 5601621 | K87: =I87-J87 -> -5601621 | L87: =I87+Jan!L85 -> 869907 | M87: =J87+Jan!M85 -> 8134607 | N87: =L87-M87 -> -7264700
B88: =1+B87 -> 61 | C88: PAMI Global Bond Fund, Inc. | D88: 67601557 | E88: 6125796 | F88: =D88-E88 -> 61475761 | G88: 0 | H88: 23 | I88: 0 | J88: 0 | K88: =I88-J88 -> 0 | L88: =I88+Jan!L86 -> 0 | M88: =J88+Jan!M86 -> 0 | N88: =L88-M88 -> 0
B89: =1+B88 -> 62 | C89: Philam Dollar Bond Fund, Inc. | D89: 1557089549 | E89: 11330441 | F89: =D89-E89 -> 1545759108 | G89: 0 | H89: 1436 | I89: 59943 | J89: 8677275 | K89: =I89-J89 -> -8617332 | L89: =I89+Jan!L87 -> 77424 | M89: =J89+Jan!M87 -> 15941983 | N89: =L89-M89 -> -15864559
B90: =1+B89 -> 63 | C90: Philequity Dollar Income Fund, Inc. | D90: 2.175614e+08 | E90: 1396155.8 | F90: =D90-E90 -> 2.1616525e+08 | G90: 0 | H90: 90 | I90: 2.1994011e+08 | J90: 5.1195178e+09 | K90: =I90-J90 -> -4899577641 | L90: =I90+Jan!L88 -> 2.2011081e+08 | M90: =J90+Jan!M88 -> 5119727147 | N90: =L90-M90 -> -4899616340
B91: =1+B90 -> 64 | C91: Sun Life Prosperity Dollar Abundance Fund, Inc. | D91: 408540355 | E91: 9131883 | F91: =D91-E91 -> 399408472 | G91: 0 | H91: 2664 | I91: 0 | J91: 12257376 | K91: =I91-J91 -> -12257376 | L91: =I91+Jan!L89 -> 2435705 | M91: =J91+Jan!M89 -> 53837709 | N91: =L91-M91 -> -51402004
A92: Sub total - US Currency | D92: =SUM(D85:D91) -> 13842519269 | E92: =SUM(E85:E91) -> 93891519 | F92: =SUM(F85:F91) -> 13748627750 | G92: =SUM(G85:G91) -> 0 | H92: =SUM(H85:H91) -> 11161 | I92: =SUM(I85:I91) -> 2.9643711e+08 | J92: =SUM(J85:J91) -> 5277457677 | K92: =SUM(K85:K91) -> -4981020571 | ... N92: =SUM(N85:N91) -> -5073813352
B93: =1+B91 -> 65 | C93: ALFM Euro Bond Fund, Inc. | D93: 698960258 | E93: 5293500 | F93: =D93-E93 -> 693666758 | G93: 0 | H93: 562 | I93: 2991675 | J93: 19506865 | K93: =I93-J93 -> -16515190 | L93: =I93+Jan!L91 -> 5994456 | M93: =J93+Jan!M91 -> 58571920 | N93: =L93-M93 -> -52577464
A94: Sub total - Euro Currency | D94: =SUM(D93) -> 698960258 | E94: =SUM(E93) -> 5293500 | F94: =SUM(F93) -> 693666758 | G94: =SUM(G93) -> 0 | H94: =SUM(H93) -> 562 | I94: =SUM(I93) -> 2991675 | J94: =SUM(J93) -> 19506865 | K94: =SUM(K93) -> -16515190 | ... N94: =SUM(N93) -> -52577464
A95: Sub total - bond funds | D95: =D83+D92+D94 -> 62210183514 | E95: =E83+E92+E94 -> 4.0669939e+08 | F95: =F83+F92+F94 -> 61803484123 | G95: =G83+G92+G94 -> 360000000 | H95: =H83+H92+H94 -> 73159 | I95: =I83+I92+I94 -> 6.4664499e+08 | J95: =J83+J92+J94 -> 5774478915 | K95: =K83+K92+K94 -> -5127833929 | ... N95: =N83+N92+N94 -> -5384582886
A96: Money Market Funds
A97: Primarily invested in Peso Securities (shares)
B98: =B93+1 -> 66 | C98: AIB Money Market Mutual Fund, Inc. | D98: 1.7629825e+08 | E98: 316723.31 | F98: =D98-E98 -> 1.7598153e+08 | G98: 0 | H98: 62 | I98: 43000 | J98: 0 | K98: =I98-J98 -> 43000 | L98: =I98+Jan!L96 -> 116000 | M98: =J98+Jan!M96 -> 18188.87 | N98: =L98-M98 -> 97811.13
B99: =B98+1 -> 67 | C99: ALFM Money Market Fund, Inc. | D99: 19312678227 | E99: 219054343 | F99: =D99-E99 -> 19093623884 | G99: 0 | H99: 20058 | I99: 371060 | J99: 267516873 | K99: =I99-J99 -> -267145813 | L99: =I99+Jan!L97 -> 740456 | M99: =J99+Jan!M97 -> 497843967 | N99: =L99-M99 -> -497103511
B100: =B99+1 -> 68 | C100: First Metro Save and Learn Money Market Fund, Inc. | D100: 2443417149 | E100: 6723684 | F100: =D100-E100 -> 2436693465 | G100: 0 | H100: 1242 | I100: 124746107 | J100: 96409998 | K100: =I100-J100 -> 28336109 | L100: =I100+Jan!L98 -> 177879996 | M100: =J100+Jan!M98 -> 197562982 | N100: =L100-M100 -> -19682986
B101: =B100+1 -> 69 | C101: Sun Life Prosperity Peso Starter Fund, Inc. | D101: 10634219127 | E101: 576485587 | F101: =D101-E101 -> 10057733540 | G101: 0 | H101: 74837 | I101: 293883296 | J101: 394460518 | K101: =I101-J101 -> -100577222 | L101: =I101+Jan!L99 -> 557939369 | M101: =J101+Jan!M99 -> 1264249326 | N101: =L101-M101 -> -706309957
A102: Primarily invested in Peso Securities (units)
B103: =1+B101 -> 70 | C103: ALFM Money Market Fund, Inc. | D103: 15019262002 | E103: 156937158 | F103: =D103-E103 -> 14862324844 | G103: 0 | H103: 33026 | I103: 1723079406 | J103: 898174770 | K103: =I103-J103 -> 824904636 | L103: =I103+Jan!L101 -> 3007904281 | M103: =J103+Jan!M101 -> 1976566041 | N103: =L103-M103 -> 1031338240
A104: Sub total - Peso Currency | D104: =SUM(D98:D101)+D103 -> 47585874756 | E104: =SUM(E98:E101)+E103 -> 9.595175e+08 | F104: =SUM(F98:F101)+F103 -> 46626357261 | G104: =SUM(G98:G101)+G103 -> 0 | H104: =SUM(H98:H101)+H103 -> 129225 | I104: =SUM(I98:I101)+I103 -> 2142122869 | J104: =SUM(J98:J101)+J103 -> 1656562159 | K104: =SUM(K98:K101)+K103 -> 485560710 | ... N104: =SUM(N98:N101)+N103 -> -1.916604e+08
A105: Primarily invested in foreign currency securities (shares)
...

Sheet Feb UPDATED
A1: PHILIPPINE INVESTMENT FUNDS ASSOCIATION, INC.
A2: MUTUAL FUNDS STATISTICAL REPORT
A3: Month of February 2026
A4: (Amounts in Peso)
I5: F O R - T H E - M O N T H | L5: Y E A R - T O - D A T E
A6: Fund Category | C6: Fund Name | D6: ASSETS | E6: LIABILITIES | F6: NET ASSETS | G6: EQUITY INV. | H6: NO. OF A/C | I6: SALES | J6: REDEMPTIONS | K6: NET SALES | L6: TOTAL SALES | M6: TOTAL REDEMPTIONS | N6: TOTAL NET SALES
A7: Stock Funds
A8: Primarily invested in Peso Securities (shares)
B9: 1 | C9: ALFM Growth Fund, Inc. | D9: 3678383403 | E9: 29551293 | F9: =D9-E9 -> 3648832110 | G9: 3606659841 | H9: 5290 | I9: 5384497 | J9: 46958163 | K9: =I9-J9 -> -41573666 | L9: =I9+Jan!L9 -> 8024804 | M9: =J9+Jan!M9 -> 95081261 | N9: =L9-M9 -> -87056457
B10: =1+B9 -> 2 | C10: ATRAM Alpha Opportunity Fund, Inc. | D10: 1.1176472e+09 | E10: 10930035 | F10: =D10-E10 -> 1106717117 | G10: 1.0367e+09 | H10: 4210 | I10: 13163391 | J10: 13192961 | K10: =I10-J10 -> -29570.12 | L10: =I10+Jan!L10 -> 24350175 | M10: =J10+Jan!M10 -> 1.0316117e+08 | N10: =L10-M10 -> -78811000
B11: =1+B10 -> 3 | C11: ATRAM Phil. Equity Opportunity Fund, Inc. | D11: 1.07207e+09 | E11: 77750965 | F11: =D11-E11 -> 994319013 | G11: 9.3161594e+08 | H11: 2348 | I11: 2000296 | J11: 7773113.8 | K11: =I11-J11 -> -5772817.9 | L11: =I11+Jan!L11 -> 7939013.9 | M11: =J11+Jan!M11 -> 53821478 | N11: =L11-M11 -> -45882464
B12: =1+B11 -> 4 | C12: Climbs Share Capital Equity Investment Fund Corp. | D12: 5.1885957e+08 | E12: 20165405 | F12: =D12-E12 -> 4.9869416e+08 | G12: 2.7663693e+08 | H12: 1706 | I12: 725792.5 | J12: 564740.09 | K12: =I12-J12 -> 161052.41 | L12: =I12+Jan!L12 -> 789292.5 | M12: =J12+Jan!M12 -> 17007176 | N12: =L12-M12 -> -16217884
B13: =1+B12 -> 5 | C13: First Metro Consumer Fund, Inc. | D13: 279152771 | E13: 10583956 | F13: =D13-E13 -> 268568815 | G13: 263653374 | H13: 1065 | I13: 99185 | J13: 16654032 | K13: =I13-J13 -> -16554847 | L13: =I13+Jan!L13 -> 248176 | M13: =J13+Jan!M13 -> 17384084 | N13: =L13-M13 -> -17135908
B14: =1+B13 -> 6 | C14: First Metro Save and Learn Equity Fund, Inc. | D14: 2648792030 | E14: 156007523 | F14: =D14-E14 -> 2492784507 | G14: 2329860987 | H14: 15162 | I14: 1645204 | J14: 31133161 | K14: =I14-J14 -> -29487957 | L14: =I14+Jan!L14 -> 8054336 | M14: =J14+Jan!M14 -> 77511419 | N14: =L14-M14 -> -69457083
B15: =1+B14 -> 7 | C15: First Metro Save and Learn Phil. Index Fund, Inc. | D15: 69102317 | E15: 403828 | F15: =D15-E15 -> 68698489 | G15: 67798081 | H15: 503 | I15: 137742 | J15: 362141 | K15: =I15-J15 -> -224399 | L15: =I15+Jan!L15 -> 450962 | M15: =J15+Jan!M15 -> 477054 | N15: =L15-M15 -> -26092
B16: =1+B15 -> 8 | C16: MBG Equity Investment Fund, Inc. | D16: 22351116 | E16: 653494 | F16: =D16-E16 -> 21697622 | G16: 19239167 | H16: 35 | I16: 0 | J16: 0 | K16: =I16-J16 -> 0 | L16: =I16+Jan!L16 -> 0 | M16: =J16+Jan!M16 -> 0 | N16: =L16-M16 -> 0
B17: =1+B16 -> 9 | C17: PAMI Equity Index Fund, Inc. | D17: 949293850 | E17: 22894348 | F17: =D17-E17 -> 926399502 | G17: 939380229 | H17: 10374 | I17: 0 | J17: 7489189 | K17: =I17-J17 -> -7489189 | L17: =I17+Jan!L17 -> 0 | M17: =J17+Jan!M17 -> 22836925 | N17: =L17-M17 -> -22836925
B18: =1+B17 -> 10 | C18: Philam Strategic Growth Fund, Inc. | D18: 2952917109 | E18: 43247875 | F18: =D18-E18 -> 2909669234 | G18: 2892320242 | H18: 9863 | I18: 0 | J18: 40639309 | K18: =I18-J18 -> -40639309 | L18: =I18+Jan!L18 -> 0 | M18: =J18+Jan!M18 -> 64733324 | N18: =L18-M18 -> -64733324
B19: =1+B18 -> 11 | C19: Philequity Dividend Yield Fund, Inc. | D19: 2.7067133e+09 | E19: 51127712 | F19: =D19-E19 -> 2655585579 | G19: 2.5908914e+09 | H19: 5155 | I19: 10795622 | J19: 95950687 | K19: =I19-J19 -> -85155065 | L19: =I19+Jan!L19 -> 32059289 | M19: =J19+Jan!M19 -> 1.4173602e+08 | N19: =L19-M19 -> -1.0967673e+08
B20: =1+B19 -> 12 | C20: Philequity Fund, Inc. | D20: 8.6588903e+09 | E20: 1.1530918e+08 | F20: =D20-E20 -> 8543581153 | G20: 8.1371773e+09 | H20: 30091 | I20: 10285233 | J20: 82475086 | K20: =I20-J20 -> -72189853 | L20: =I20+Jan!L20 -> 20570466 | M20: =J20+Jan!M20 -> 1.6495017e+08 | N20: =L20-M20 -> -1.4437971e+08
B21: =1+B20 -> 13 | C21: Philequity MSCI Phil. Index Fund, Inc. | D21: 3.0646961e+08 | E21: 1001407.2 | F21: =D21-E21 -> 3.0546821e+08 | G21: 3.0443688e+08 | H21: 869 | I21: 393524.1 | J21: 29784917 | K21: =I21-J21 -> -29391393 | L21: =I21+Jan!L21 -> 678598.68 | M21: =J21+Jan!M21 -> 32378596 | N21: =L21-M21 -> -31699997
... B27: =1+B26 -> 19 | C27: United Fund, Inc. | D27: 5.6147379e+08 | E27: 2058816.7 | F27: =D27-E27 -> 5.5941498e+08 | G27: 5.0932384e+08 | H27: 1175 | I27: 141976.67 | J27: 301093.29 | K27: =I27-J27 -> -159116.62 | L27: =I27+Jan!L27 -> 427295.53 | M27: =J27+Jan!M27 -> 771516.96 | N27: =L27-M27 -> -344221.43
A28: Primarily invested in Peso Securities (units)
B29: =1+B27 -> 20 | C29: COL Equity Index Unitized Mutual Fund, Inc. | D29: 2.561967e+08 | E29: 2846688 | F29: =D29-E29 -> 2.5335001e+08 | G29: 2.5502866e+08 | H29: 5195 | I29: 4900573 | J29: 11350341 | K29: =I29-J29 -> -6449767.7 | L29: =I29+Jan!L29 -> 11078953 | M29: =J29+Jan!M29 -> 41391375 | N29: =L29-M29 -> -30312421
B30: =1+B29 -> 21 | C30: COL Strategic Growth Equity Unitized Mutual Fund, Inc. | D30: 3.2552876e+08 | E30: 3335942 | F30: =D30-E30 -> 322192821 | G30: 2.4044268e+08 | H30: 8510 | I30: 3451746.9 | J30: 11118657 | K30: =I30-J30 -> -7666910.3 | L30: =I30+Jan!L30 -> 8347770.5 | M30: =J30+Jan!M30 -> 59115442 | N30: =L30-M30 -> -50767671
B31: =1+B30 -> 22 | C31: Philequity Alpha One Fund, Inc. | D31: 2.1490907e+08 | E31: 2990476.1 | F31: =D31-E31 -> 2.1191859e+08 | G31: 2.1030811e+08 | H31: 1045 | I31: 168483.27 | J31: 3699126 | K31: =I31-J31 -> -3530642.7 | L31: =I31+Jan!L31 -> 314992.6 | M31: =J31+Jan!M31 -> 6452822.9 | N31: =L31-M31 -> -6137830.3
B32: =1+B31 -> 23 | C32: Philippine Stock Index Fund Corp. | D32: 558979791 | E32: 4113835 | F32: =D32-E32 -> 554865956 | G32: 549842730 | H32: 799580 | I32: 15068268 | J32: 20407849 | K32: =I32-J32 -> -5339581 | L32: =I32+Jan!L32 -> 23780577 | M32: =J32+Jan!M32 -> 97729204 | N32: =L32-M32 -> -73948627
A33: Exchange Traded Fund
B34: =1+B32 -> 24 | C34: First Metro Phil. Equity Exchange Traded Fund, Inc. | D34: 1365982115 | E34: 2157787 | F34: =D34-E34 -> 1363824328 | G34: 1364289439 | H34: 3234 | I34: 8414744 | J34: 48571714 | K34: =I34-J34 -> -40156970 | L34: =I34+Jan!L34 -> 8414744 | M34: =J34+Jan!M34 -> 77125075 | N34: =L34-M34 -> -68710331
A35: Sub total - Peso Currency | D35: =SUM(D9:D34) -> 52569703204 | E35: =SUM(E9:E34) -> 7.6939971e+08 | F35: =SUM(F9:F34) -> 51800303493 | G35: =SUM(G9:G34) -> 50164847629 | H35: =SUM(H9:H34) -> 1075672 | I35: =SUM(I9:I34) -> 98207906 | J35: =SUM(J9:J34) -> 1095990972 | K35: =SUM(K9:K34) -> -9.9778307e+08 | ... N35: =SUM(N9:N34) -> -2142384757
A36: Primarily invested in foreign currency securities (shares)
B37: =1+B34 -> 25 | C37: ATRAM AsiaPlus Equity Fund, Inc. | D37: 29949336 | E37: 345962.32 | F37: =D37-E37 -> 29603373 | G37: 0 | H37: 43 | I37: 11488.02 | J37: 249258.69 | K37: =I37-J37 -> -237770.67 | L37: =I37+Jan!L37 -> 23219.41 | M37: =J37+Jan!M37 -> 4805385.9 | N37: =L37-M37 -> -4782166.5
B38: =1+B37 -> 26 | C38: Sun Life Prosperity World Voyager Fund, Inc. | D38: 2502584706 | E38: 73412734 | F38: =D38-E38 -> 2429171972 | G38: 0 | H38: 3363 | I38: 112780395 | J38: 11569508 | K38: =I38-J38 -> 101210887 | L38: =I38+Jan!L38 -> 232027129 | M38: =J38+Jan!M38 -> 52635541 | N38: =L38-M38 -> 179391588
A39: Primarily invested in foreign currency securities (units)
B40: =1+B38 -> 27 | C40: Philequity Global Fund, Inc. 3 | D40: 495555.7 | E40: 0 | F40: =D40-E40 -> 495555.7 | G40: 0 | H40: 26 | I40: 495572.14 | J40: 0 | K40: =I40-J40 -> 495572.14 | L40: =I40 -> 495572.14 | M40: =J40 -> 0 | N40: =L40-M40 -> 495572.14
A41: Sub total - US Currency | D41: =SUM(D37:D38)+D40 -> 2533029597 | E41: =SUM(E37:E38)+E40 -> 73758696 | F41: =SUM(F37:F38)+F40 -> 2459270901 | G41: =SUM(G37:G38)+G40 -> 0 | H41: =SUM(H37:H38)+H40 -> 3432 | I41: =SUM(I37:I38)+I40 -> 1.1328746e+08 | J41: =SUM(J37:J38)+J40 -> 11818767 | K41: =SUM(K37:K38)+K40 -> 1.0146869e+08 | ... N41: =SUM(N37:N38)+N40 -> 1.7510499e+08
A42: Sub total - stock funds | D42: =D35+D41 -> 55102732802 | E42: =E35+E41 -> 8.4315841e+08 | F42: =F35+F41 -> 54259574394 | G42: =G35+G41 -> 50164847629 | H42: =H35+H41 -> 1079104 | I42: =I35+I41 -> 2.1149536e+08 | J42: =J35+J41 -> 1107809738 | K42: =K35+K41 -> -8.9631438e+08 | ... N42: =N35+N41 -> -1967279764
A43: Balanced Funds
A44: Primarily invested in Peso Securities (shares)
B45: =1+B40 -> 28 | C45: ATRAM Philippine Balanced Fund, Inc. | D45: 3.9654217e+08 | E45: 1133095.1 | F45: =D45-E45 -> 3.9540907e+08 | G45: 2.0984686e+08 | H45: 2320 | I45: 490945.49 | J45: 5293097.3 | K45: =I45-J45 -> -4802151.8 | L45: =I45+Jan!L43 -> 979245.3 | M45: =J45+Jan!M43 -> 10272186 | N45: =L45-M45 -> -9292941
B46: =1+B45 -> 29 | C46: ATRAM Unicapital Diversified Growth Fund, Inc. | D46: 1.1699287e+08 | E46: 228982.01 | F46: =D46-E46 -> 1.1676389e+08 | G46: 32337622 | H46: 850 | I46: 179113.49 | J46: 1646980.3 | K46: =I46-J46 -> -1467866.9 | L46: =I46+Jan!L44 -> 811012.36 | M46: =J46+Jan!M44 -> 3322279 | N46: =L46-M46 -> -2511266.6
B47: =1+B46 -> 30 | C47: First Metro Save and Learn Balanced Fund, Inc. | D47: 576401023 | E47: 2468913 | F47: =D47-E47 -> 573932110 | G47: 304741794 | H47: 4521 | I47: 322767 | J47: 8814729 | K47: =I47-J47 -> -8491962 | L47: =I47+Jan!L45 -> 873666 | M47: =J47+Jan!M45 -> 17077743 | N47: =L47-M47 -> -16204077
B48: =1+B47 -> 31 | C48: First Metro Save and Learn F.O.C.C.U.S. Dynamic Fund, Inc. | D48: 476714968 | E48: 1587680 | F48: =D48-E48 -> 475127288 | G48: 250350982 | H48: 582 | I48: 11118609 | J48: 1421986 | K48: =I48-J48 -> 9696623 | L48: =I48+Jan!L46 -> 17299307 | M48: =J48+Jan!M46 -> 2969117 | N48: =L48-M48 -> 14330190
B49: =1+B48 -> 32 | C49: NCM Mutual Fund of the Phils., Inc. | D49: 336673897 | E49: 2232667 | F49: =D49-E49 -> 334441230 | G49: 170249971 | H49: 45 | I49: 0 | J49: 0 | K49: =I49-J49 -> 0 | L49: =I49+Jan!L47 -> 0 | M49: =J49+Jan!M47 -> 0 | N49: =L49-M49 -> 0
B50: =1+B49 -> 33 | C50: PAMI Horizon Fund, Inc. | D50: 415347264 | E50: 5089125 | F50: =D50-E50 -> 410258139 | G50: 211426490 | H50: 9367 | I50: 5910 | J50: 2644947 | K50: =I50-J50 -> -2639037 | L50: =I50+Jan!L48 -> 39920 | M50: =J50+Jan!M48 -> 4892896 | N50: =L50-M50 -> -4852976
B51: =1+B50 -> 34 | C51: Philam Fund, Inc. | D51: 1732834208 | E51: 24767024 | F51: =D51-E51 -> 1708067184 | G51: 880636347 | H51: 6597 | I51: 1344883 | J51: 23086629 | K51: =I51-J51 -> -21741746 | L51: =I51+Jan!L49 -> 1671808 | M51: =J51+Jan!M49 -> 35053732 | N51: =L51-M51 -> -33381924
B52: =1+B51 -> 35 | C52: Solidaritas Fund, Inc. | D52: 119371502 | E52: 142278 | F52: =D52-E52 -> 119229224 | G52: 60964060 | H52: 149 | I52: 0 | J52: 922888 | K52: =I52-J52 -> -922888 | L52: =I52+Jan!L50 -> 0 | M52: =J52+Jan!M50 -> 1436602 | N52: =L52-M52 -> -1436602
B53: =1+B52 -> 36 | C53: Sun Life Prosperity Balanced Fund, Inc. | D53: 5014044150 | E53: 43218435 | F53: =D53-E53 -> 4970825715 | G53: 2516123925 | H53: 54836 | I53: 4592784 | J53: 73122278 | K53: =I53-J53 -> -68529494 | L53: =I53+Jan!L51 -> 9168677 | M53: =J53+Jan!M51 -> 143370914 | N53: =L53-M53 -> -134202237
B54: =1+B53 -> 37 | C54: Sun Life Prosperity Dynamic Fund, Inc. | D54: 453849324 | E54: 2504188 | F54: =D54-E54 -> 451345136 | G54: 234581313 | H54: 5003 | I54: 0 | J54: 6517746 | K54: =I54-J54 -> -6517746 | L54: =I54+Jan!L52 -> 0 | M54: =J54+Jan!M52 -> 21868659 | N54: =L54-M54 -> -21868659
A55: Primarily invested in Peso Securities (units)
B56: =1+B54 -> 38 | C56: BPI Wealth Builder Multi-Asset Mutual Fund, Inc. 2 | D56: 1020498755 | E56: 3570154 | F56: =D56-E56 -> 1016928601 | G56: 75280080 | H56: 27426 | I56: 26393123 | J56: 6636181 | K56: =I56-J56 -> 19756942 | L56: =I56+Jan!L54 -> 74026495 | M56: =J56+Jan!M54 -> 14821993 | N56: =L56-M56 -> 59204502
B57: =1+B56 -> 39 | C57: Sun Life Prosperity Achiever Fund 2028, Inc. | D57: 69280060 | E57: 482303 | F57: =D57-E57 -> 68797757 | G57: 11189025 | H57: 1279 | I57: 38000 | J57: 1093529 | K57: =I57-J57 -> -1055529 | L57: =I57+Jan!L55 -> 96000 | M57: =J57+Jan!M55 -> 2266432 | N57: =L57-M57 -> -2170432
B58: =1+B57 -> 40 | C58: Sun Life Prosperity Achiever Fund 2038, Inc. | D58: 54645178 | E58: 330010 | F58: =D58-E58 -> 54315168 | G58: 37778736 | H58: 520 | I58: 10500 | J58: 183870 | K58: =I58-J58 -> -173370 | L58: =I58+Jan!L56 -> 20000 | M58: =J58+Jan!M56 -> 417706 | N58: =L58-M58 -> -397706
B59: =1+B58 -> 41 | C59: Sun Life Prosperity Achiever Fund 2048, Inc. | D59: 50311103 | E59: 237695 | F59: =D59-E59 -> 50073408 | G59: 41549266 | H59: 257 | I59: 8000 | J59: 302360 | K59: =I59-J59 -> -294360 | L59: =I59+Jan!L57 -> 24000 | M59: =J59+Jan!M57 -> 512861 | N59: =L59-M59 -> -488861
A60: Sub total - Peso Currency | D60: =SUM(D45:D59) -> 10833506473 | E60: =SUM(E45:E59) -> 87992549 | F60: =SUM(F45:F59) -> 10745513924 | G60: =SUM(G45:G59) -> 5037056468 | H60: =SUM(H45:H59) -> 113752 | I60: =SUM(I45:I59) -> 44504635 | J60: =SUM(J45:J59) -> 1.3168722e+08 | K60: =SUM(K45:K59) -> -87182586 | ... N60: =SUM(N45:N59) -> -1.5327299e+08
A61: Primarily invested in foreign currency securities (shares)
B62: =1+B59 -> 42 | C62: Cocolife Dollar Fund Builder, Inc. | D62: 70851399 | E62: 305388.07 | F62: =D62-E62 -> 70546010 | G62: 0 | H62: 49 | I62: 0 | J62: 0 | K62: =I62-J62 -> 0 | L62: =I62+Jan!L60 -> 0 | M62: =J62+Jan!M60 -> 0 | N62: =L62-M62 -> 0
B63: =1+B62 -> 43 | C63: PAMI Asia Balanced Fund, Inc. | D63: 338808814 | E63: 628487 | F63: =D63-E63 -> 338180327 | G63: 180016162 | H63: 195 | I63: 0 | J63: 1707612 | K63: =I63-J63 -> -1707612 | L63: =I63+Jan!L61 -> 0 | M63: =J63+Jan!M61 -> 5869644 | N63: =L63-M63 -> -5869644
B64: =1+B63 -> 44 | C64: Sun Life Prosperity Dollar Advantage Fund, Inc. | D64: 1795327392 | E64: 62318985 | F64: =D64-E64 -> 1733008407 | G64: 0 | H64: 4356 | I64: 5070688 | J64: 32629035 | K64: =I64-J64 -> -27558347 | L64: =I64+Jan!L62 -> 9039325 | M64: =J64+Jan!M62 -> 102468759 | N64: =L64-M64 -> -93429434
B65: =1+B64 -> 45 | C65: Sun Life Prosperity Dollar Wellspring Fund, Inc. | D65: 223983751 | E65: 11483650 | F65: =D65-E65 -> 212500101 | G65: 0 | H65: 783 | I65: 57915 | J65: 6080551 | K65: =I65-J65 -> -6022636 | L65: =I65+Jan!L63 -> 265719 | M65: =J65+Jan!M63 -> 10971100 | N65: =L65-M65 -> -10705381
A66: Sub total - US Currency | D66: =SUM(D62:D65) -> 2428971356 | E66: =SUM(E62:E65) -> 74736510 | F66: =SUM(F62:F65) -> 2354234845 | G66: =SUM(G62:G65) -> 180016162 | H66: =SUM(H62:H65) -> 5383 | I66: =SUM(I62:I65) -> 5128603 | J66: =SUM(J62:J65) -> 40417198 | K66: =SUM(K62:K65) -> -35288595 | ... N66: =SUM(N62:N65) -> -110004459
A67: Sub total - balanced funds | D67: =D60+D66 -> 13262477828 | E67: =E60+E66 -> 1.6272906e+08 | F67: =F60+F66 -> 13099748769 | G67: =G60+G66 -> 5217072630 | H67: =H60+H66 -> 119135 | I67: =I60+I66 -> 49633238 | J67: =J60+J66 -> 1.7210442e+08 | K67: =K60+K66 -> -1.2247118e+08 | ... N67: =N60+N66 -> -2.6327745e+08
A68: Bond Funds
A69: Primarily invested in Peso Securities (shares)
B70: =1+B65 -> 46 | C70: ALFM Peso Bond Fund, Inc. | D70: 34895713674 | E70: 194834094 | F70: =D70-E70 -> 34700879580 | G70: 360000000 | H70: 24693 | I70: 234658348 | J70: 291718039 | K70: =I70-J70 -> -57059691 | L70: =I70+Jan!L68 -> 432168098 | M70: =J70+Jan!M68 -> 559745744 | N70: =L70-M70 -> -127577646
B71: =1+B70 -> 47 | C71: ATRAM Corporate Bond Fund, Inc. | D71: 2.4154317e+08 | E71: 13780899 | F71: =D71-E71 -> 2.2776227e+08 | G71: 0 | H71: 882 | I71: 432997.91 | J71: 13372168 | K71: =I71-J71 -> -12939170 | L71: =I71+Jan!L69 -> 685058.61 | M71: =J71+Jan!M69 -> 15500538 | N71: =L71-M71 -> -14815479
B72: =1+B71 -> 48 | C72: Cocolife Fixed Income Fund, Inc. | D72: 9.2706057e+08 | E72: 8765139.1 | F72: =D72-E72 -> 918295426 | G72: 0 | H72: 1764 | I72: 3845387.2 | J72: 10995316 | K72: =I72-J72 -> -7149929.2 | L72: =I72+Jan!L70 -> 9376609.1 | M72: =J72+Jan!M70 -> 24740499 | N72: =L72-M72 -> -15363890
B73: =1+B72 -> 49 | C73: Ekklesia Mutual Fund, Inc. | D73: 172992748 | E73: 144302 | F73: =D73-E73 -> 172848446 | G73: 0 | H73: 127 | I73: 0 | J73: 118247 | K73: =I73-J73 -> -118247 | L73: =I73+Jan!L71 -> 0 | M73: =J73+Jan!M71 -> 118247 | N73: =L73-M73 -> -118247
B74: =1+B73 -> 50 | C74: First Metro Save and Learn Fixed Income Fund, Inc. | D74: 722452764 | E74: 4433481 | F74: =D74-E74 -> 718019283 | G74: 0 | H74: 1642 | I74: 1944163 | J74: 10110035 | K74: =I74-J74 -> -8165872 | L74: =I74+Jan!L72 -> 2555402 | M74: =J74+Jan!M72 -> 34812835 | N74: =L74-M74 -> -32257433
B75: =1+B74 -> 51 | C75: Philam Bond Fund, Inc. | D75: 1338118211 | E75: 30619596 | F75: =D75-E75 -> 1307498615 | G75: 0 | H75: 4316 | I75: 868259 | J75: 14399431 | K75: =I75-J75 -> -13531172 | L75: =I75+Jan!L73 -> 3372220 | M75: =J75+Jan!M73 -> 19993986 | N75: =L75-M75 -> -16621766
B76: =1+B75 -> 52 | C76: Philam Managed Income Fund, Inc. | D76: 494959606 | E76: 9910404 | F76: =D76-E76 -> 485049202 | G76: 0 | H76: 364 | I76: 0 | J76: 763232 | K76: =I76-J76 -> -763232 | L76: =I76+Jan!L74 -> 0 | M76: =J76+Jan!M74 -> 2419823 | N76: =L76-M76 -> -2419823
B77: =1+B76 -> 53 | C77: Philequity Peso Bond Fund, Inc. | D77: 2.8782055e+08 | E77: 1894385.8 | F77: =D77-E77 -> 2.8592616e+08 | G77: 0 | H77: 3990 | I77: 2494829.6 | J77: 600894.91 | K77: =I77-J77 -> 1893934.7 | L77: =I77+Jan!L75 -> 5457242 | M77: =J77+Jan!M75 -> 2040282.6 | N77: =L77-M77 -> 3416959.4
B78: =1+B77 -> 54 | C78: Soldivo Bond Fund, Inc. | D78: 2.0486303e+09 | E78: 3166979.5 | F78: =D78-E78 -> 2045463313 | G78: 0 | H78: 750 | I78: 50035804 | J78: 2128019.4 | K78: =I78-J78 -> 47907785 | L78: =I78+Jan!L76 -> 1.0108919e+08 | M78: =J78+Jan!M76 -> 4271525.5 | N78: =L78-M78 -> 96817666
B79: =1+B78 -> 55 | C79: Sun Life Prosperity Bond Fund, Inc. | D79: 6395148282 | E79: 39614457 | F79: =D79-E79 -> 6355533825 | G79: 0 | H79: 19942 | I79: 52668166 | J79: 132079522 | K79: =I79-J79 -> -79411356 | L79: =I79+Jan!L77 -> 101542692 | M79: =J79+Jan!M77 -> 249577511 | N79: =L79-M79 -> -148034819
B80: =1+B79 -> 56 | C80: Sun Life Prosperity GS Fund, Inc. | D80: 144264131 | E80: 350635 | F80: =D80-E80 -> 143913496 | G80: 0 | H80: 2966 | I80: 268250 | J80: 1229469 | K80: =I80-J80 -> -961219 | L80: =I80+Jan!L78 -> 749637 | M80: =J80+Jan!M78 -> 1967229 | N80: =L80-M80 -> -1217592
A81: Corporate Debt Vehicle (units)
B82: =1+B80 -> 57 | C82: ATRAM Unitized Corporate Debt Vehicle, Inc. 1 | D82: 0 | E82: 0 | F82: =D82-E82 -> 0 | G82: 0 | H82: 0 | I82: 0 | J82: 0 | K82: =I82-J82 -> 0 | L82: =I82+Jan!L80 -> 0 | M82: =J82+Jan!M80 -> 0 | N82: =L82-M82 -> 0
A83: Sub total - Peso Currency | D83: =SUM(D70:D82) -> 47668703987 | E83: =SUM(E70:E82) -> 3.0751437e+08 | F83: =SUM(F70:F82) -> 47361189614 | G83: =SUM(G70:G82) -> 360000000 | H83: =SUM(H70:H82) -> 61436 | I83: =SUM(I70:I82) -> 3.472162e+08 | J83: =SUM(J70:J82) -> 4.7751437e+08 | K83: =SUM(K70:K82) -> -1.3029817e+08 | ... N83: =SUM(N70:N82) -> -2.5819207e+08
A84: Primarily invested in foreign currency securities (shares)
B85: =B82+1 -> 58 | C85: ALFM Dollar Bond Fund, Inc. | D85: 11225574853 | E85: 59324195 | F85: =D85-E85 -> 11166250658 | G85: 0 | H85: 6794 | I85: 76437050 | J85: 131403651 | K85: =I85-J85 -> -54966601 | L85: =I85+Jan!L83 -> 122621770 | M85: =J85+Jan!M83 -> 222287519 | N85: =L85-M85 -> -99665749
B86: =1+B85 -> 59 | C86: ATRAM Total Return Dollar Bond Fund, Inc. | D86: 49455742 | E86: 2039367.7 | F86: =D86-E86 -> 47416374 | G86: 0 | H86: 21 | I86: 0 | J86: 0 | K86: =I86-J86 -> 0 | L86: =I86+Jan!L84 -> 0 | M86: =J86+Jan!M84 -> 0 | N86: =L86-M86 -> 0
B87: =1+B86 -> 60 | C87: First Metro Save and Learn Dollar Bond Fund, Inc. | D87: 316695809 | E87: 4543680 | F87: =D87-E87 -> 312152129 | G87: 0 | H87: 133 | I87: 0 | J87: 5601621 | K87: =I87-J87 -> -5601621 | L87: =I87+Jan!L85 -> 869907 | M87: =J87+Jan!M85 -> 8134607 | N87: =L87-M87 -> -7264700
B88: =1+B87 -> 61 | C88: PAMI Global Bond Fund, Inc. | D88: 67601557 | E88: 6125796 | F88: =D88-E88 -> 61475761 | G88: 0 | H88: 23 | I88: 0 | J88: 0 | K88: =I88-J88 -> 0 | L88: =I88+Jan!L86 -> 0 | M88: =J88+Jan!M86 -> 0 | N88: =L88-M88 -> 0
B89: =1+B88 -> 62 | C89: Philam Dollar Bond Fund, Inc. | D89: 1557089549 | E89: 11330441 | F89: =D89-E89 -> 1545759108 | G89: 0 | H89: 1436 | I89: 59943 | J89: 8677275 | K89: =I89-J89 -> -8617332 | L89: =I89+Jan!L87 -> 77424 | M89: =J89+Jan!M87 -> 15941983 | N89: =L89-M89 -> -15864559
B90: =1+B89 -> 63 | C90: Philequity Dollar Income Fund, Inc. | D90: 2.175614e+08 | E90: 1396155.8 | F90: =D90-E90 -> 2.1616525e+08 | G90: 0 | H90: 90 | I90: 167228.5 | J90: 157375.86 | K90: =I90-J90 -> 9852.64 | L90: =I90+Jan!L88 -> 337922.5 | M90: =J90+Jan!M88 -> 366769.13 | N90: =L90-M90 -> -28846.63
B91: =1+B90 -> 64 | C91: Sun Life Prosperity Dollar Abundance Fund, Inc. | D91: 408540355 | E91: 9131883 | F91: =D91-E91 -> 399408472 | G91: 0 | H91: 2664 | I91: 0 | J91: 12257376 | K91: =I91-J91 -> -12257376 | L91: =I91+Jan!L89 -> 2435705 | M91: =J91+Jan!M89 -> 53837709 | N91: =L91-M91 -> -51402004
A92: Sub total - US Currency | D92: =SUM(D85:D91) -> 13842519269 | E92: =SUM(E85:E91) -> 93891519 | F92: =SUM(F85:F91) -> 13748627750 | G92: =SUM(G85:G91) -> 0 | H92: =SUM(H85:H91) -> 11161 | I92: =SUM(I85:I91) -> 76664222 | J92: =SUM(J85:J91) -> 1.580973e+08 | K92: =SUM(K85:K91) -> -81433077 | ... N92: =SUM(N85:N91) -> -1.7422586e+08
B93: =1+B91 -> 65 | C93: ALFM Euro Bond Fund, Inc. | D93: 698960258 | E93: 5293500 | F93: =D93-E93 -> 693666758 | G93: 0 | H93: 562 | I93: 2991675 | J93: 19506865 | K93: =I93-J93 -> -16515190 | L93: =I93+Jan!L91 -> 5994456 | M93: =J93+Jan!M91 -> 58571920 | N93: =L93-M93 -> -52577464
A94: Sub total - Euro Currency | D94: =SUM(D93) -> 698960258 | E94: =SUM(E93) -> 5293500 | F94: =SUM(F93) -> 693666758 | G94: =SUM(G93) -> 0 | H94: =SUM(H93) -> 562 | I94: =SUM(I93) -> 2991675 | J94: =SUM(J93) -> 19506865 | K94: =SUM(K93) -> -16515190 | ... N94: =SUM(N93) -> -52577464
A95: Sub total - bond funds | D95: =D83+D92+D94 -> 62210183514 | E95: =E83+E92+E94 -> 4.0669939e+08 | F95: =F83+F92+F94 -> 61803484123 | G95: =G83+G92+G94 -> 360000000 | H95: =H83+H92+H94 -> 73159 | I95: =I83+I92+I94 -> 4.268721e+08 | J95: =J83+J92+J94 -> 6.5511854e+08 | K95: =K83+K92+K94 -> -2.2824644e+08 | ... N95: =N83+N92+N94 -> -4.8499539e+08
A96: Money Market Funds
A97: Primarily invested in Peso Securities (shares)
B98: =B93+1 -> 66 | C98: AIB Money Market Mutual Fund, Inc. | D98: 1.7629825e+08 | E98: 316723.31 | F98: =D98-E98 -> 1.7598153e+08 | G98: 0 | H98: 62 | I98: 43000 | J98: 0 | K98: =I98-J98 -> 43000 | L98: =I98+Jan!L96 -> 116000 | M98: =J98+Jan!M96 -> 18188.87 | N98: =L98-M98 -> 97811.13
B99: =B98+1 -> 67 | C99: ALFM Money Market Fund, Inc. | D99: 19312678227 | E99: 219054343 | F99: =D99-E99 -> 19093623884 | G99: 0 | H99: 20058 | I99: 371060 | J99: 267516873 | K99: =I99-J99 -> -267145813 | L99: =I99+Jan!L97 -> 740456 | M99: =J99+Jan!M97 -> 497843967 | N99: =L99-M99 -> -497103511
B100: =B99+1 -> 68 | C100: First Metro Save and Learn Money Market Fund, Inc. | D100: 2443417149 | E100: 6723684 | F100: =D100-E100 -> 2436693465 | G100: 0 | H100: 1242 | I100: 124746107 | J100: 96409998 | K100: =I100-J100 -> 28336109 | L100: =I100+Jan!L98 -> 177879996 | M100: =J100+Jan!M98 -> 197562982 | N100: =L100-M100 -> -19682986
B101: =B100+1 -> 69 | C101: Sun Life Prosperity Peso Starter Fund, Inc. | D101: 10634219127 | E101: 576485587 | F101: =D101-E101 -> 10057733540 | G101: 0 | H101: 74837 | I101: 293883296 | J101: 394460518 | K101: =I101-J101 -> -100577222 | L101: =I101+Jan!L99 -> 557939369 | M101: =J101+Jan!M99 -> 1264249326 | N101: =L101-M101 -> -706309957
A102: Primarily invested in Peso Securities (units)
B103: =1+B101 -> 70 | C103: ALFM Money Market Fund, Inc. | D103: 15019262002 | E103: 156937158 | F103: =D103-E103 -> 14862324844 | G103: 0 | H103: 33026 | I103: 1723079406 | J103: 898174770 | K103: =I103-J103 -> 824904636 | L103: =I103+Jan!L101 -> 3007904281 | M103: =J103+Jan!M101 -> 1976566041 | N103: =L103-M103 -> 1031338240
A104: Sub total - Peso Currency | D104: =SUM(D98:D101)+D103 -> 47585874756 | E104: =SUM(E98:E101)+E103 -> 9.595175e+08 | F104: =SUM(F98:F101)+F103 -> 46626357261 | G104: =SUM(G98:G101)+G103 -> 0 | H104: =SUM(H98:H101)+H103 -> 129225 | I104: =SUM(I98:I101)+I103 -> 2142122869 | J104: =SUM(J98:J101)+J103 -> 1656562159 | K104: =SUM(K98:K101)+K103 -> 485560710 | ... N104: =SUM(N98:N101)+N103 -> -1.916604e+08
A105: Primarily invested in foreign currency securities (shares)
...

Sheet Mar
A1: PHILIPPINE INVESTMENT FUNDS ASSOCIATION, INC.
A2: MUTUAL FUNDS STATISTICAL REPORT
A3: Month of March 2026
A4: (Amounts in Peso)
I5: F O R - T H E - M O N T H | L5: Y E A R - T O - D A T E
A6: Fund Category | C6: Fund Name | D6: ASSETS | E6: LIABILITIES | F6: NET ASSETS | G6: EQUITY INV. | H6: NO. OF A/C | I6: SALES | J6: REDEMPTIONS | K6: NET SALES | L6: TOTAL SALES | M6: TOTAL REDEMPTIONS | N6: TOTAL NET SALES
A7: Stock Funds
A8: Primarily invested in Peso Securities (shares)
B9: 1 | C9: ALFM Growth Fund, Inc. | D9: 3272067162 | E9: 8601710 | F9: =D9-E9 -> 3263465452 | G9: 3090206979 | H9: 5226 | I9: 5182504 | J9: 49193407 | K9: =I9-J9 -> -44010903 | L9: =I9+Feb!L9 -> 13207308 | M9: =J9+Feb!M9 -> 144274668 | N9: =L9-M9 -> -131067360
B10: =1+B9 -> 2 | C10: ATRAM Alpha Opportunity Fund, Inc. | D10: 1.0242569e+09 | E10: 51757173 | F10: =D10-E10 -> 9.7249971e+08 | G10: 9.0727828e+08 | H10: 4204 | I10: 6442723.4 | J10: 29923461 | K10: =I10-J10 -> -23480738 | L10: =I10+Feb!L10 -> 30792899 | M10: =J10+Feb!M10 -> 1.3308464e+08 | N10: =L10-M10 -> -1.0229174e+08
B11: =1+B10 -> 3 | C11: ATRAM Phil. Equity Opportunity Fund, Inc. | D11: 8.8737099e+08 | E11: 4613615.1 | F11: =D11-E11 -> 8.8275738e+08 | G11: 8.0465666e+08 | H11: 2337 | I11: 2292414.8 | J11: 14467341 | K11: =I11-J11 -> -12174926 | L11: =I11+Feb!L11 -> 10231429 | M11: =J11+Feb!M11 -> 68288819 | N11: =L11-M11 -> -58057390
B12: =1+B11 -> 4 | C12: Climbs Share Capital Equity Investment Fund Corp. | D12: 5.4060942e+08 | E12: 28160862 | F12: =D12-E12 -> 5.1244855e+08 | G12: 3.2026902e+08 | H12: 1677 | I12: 35836364 | J12: 1070347.2 | K12: =I12-J12 -> 34766016 | L12: =I12+Feb!L12 -> 36625656 | M12: =J12+Feb!M12 -> 18077524 | N12: =L12-M12 -> 18548133
B13: =1+B12 -> 5 | C13: First Metro Consumer Fund, Inc. | D13: 239662407 | E13: 2541170 | F13: =D13-E13 -> 237121237 | G13: 207601062 | H13: 1060 | I13: 119465 | J13: 9609952 | K13: =I13-J13 -> -9490487 | L13: =I13+Feb!L13 -> 367641 | M13: =J13+Feb!M13 -> 26994036 | N13: =L13-M13 -> -26626395
B14: =1+B13 -> 6 | C14: First Metro Save and Learn Equity Fund, Inc. | D14: 2243001265 | E14: 12904872 | F14: =D14-E14 -> 2230096393 | G14: 2010810818 | H14: 15086 | I14: 5206303 | J14: 37191773 | K14: =I14-J14 -> -31985470 | L14: =I14+Feb!L14 -> 13260639 | M14: =J14+Feb!M14 -> 114703192 | N14: =L14-M14 -> -101442553
B15: =1+B14 -> 7 | C15: First Metro Save and Learn Phil. Index Fund, Inc. | D15: 61619808 | E15: 202154 | F15: =D15-E15 -> 61417654 | G15: 59827032 | H15: 496 | I15: 185502 | J15: 1368429 | K15: =I15-J15 -> -1182927 | L15: =I15+Feb!L15 -> 636464 | M15: =J15+Feb!M15 -> 1845483 | N15: =L15-M15 -> -1209019
B16: =1+B15 -> 8 | C16: MBG Equity Investment Fund, Inc. | D16: 19462107 | E16: 672280 | F16: =D16-E16 -> 18789827 | G16: 17178988 | H16: 35 | I16: 0 | J16: 0 | K16: =I16-J16 -> 0 | L16: =I16+Feb!L16 -> 0 | M16: =J16+Feb!M16 -> 0 | N16: =L16-M16 -> 0
B17: =1+B16 -> 9 | C17: PAMI Equity Index Fund, Inc. | D17: 866205842 | E17: 29174958 | F17: =D17-E17 -> 837030884 | G17: 846308665 | H17: 10290 | I17: 0 | J17: 5655258 | K17: =I17-J17 -> -5655258 | L17: =I17+Feb!L17 -> 0 | M17: =J17+Feb!M17 -> 28492183 | N17: =L17-M17 -> -28492183
B18: =1+B17 -> 10 | C18: Philam Strategic Growth Fund, Inc. | D18: 2596188973 | E18: 14886783 | F18: =D18-E18 -> 2581302190 | G18: 2462860640 | H18: 9801 | I18: 0 | J18: 51587153 | K18: =I18-J18 -> -51587153 | L18: =I18+Feb!L18 -> 0 | M18: =J18+Feb!M18 -> 116320477 | N18: =L18-M18 -> -116320477
B19: =1+B18 -> 11 | C19: Philequity Dividend Yield Fund, Inc. | D19: 2.5476708e+09 | E19: 9874725.1 | F19: =D19-E19 -> 2537796058 | G19: 2.4565425e+09 | H19: 5174 | I19: 5004934.9 | J19: 16365208 | K19: =I19-J19 -> -11360273 | L19: =I19+Feb!L19 -> 37064224 | M19: =J19+Feb!M19 -> 158101232 | N19: =L19-M19 -> -121037008
B20: =1+B19 -> 12 | C20: Philequity Fund, Inc. | D20: 7.8154893e+09 | E20: 38277495 | F20: =D20-E20 -> 7777211793 | G20: 7.4103042e+09 | H20: 29927 | I20: 5399760.3 | J20: 49611964 | K20: =I20-J20 -> -44212204 | L20: =I20+Feb!L20 -> 25970226 | M20: =J20+Feb!M20 -> 2.1456214e+08 | N20: =L20-M20 -> -1.8859191e+08
B21: =1+B20 -> 13 | C21: Philequity MSCI Phil. Index Fund, Inc. | D21: 2.7729257e+08 | E21: 842315.71 | F21: =D21-E21 -> 2.7645025e+08 | G21: 2.7313189e+08 | H21: 887 | I21: 1220789.5 | J21: 602287.17 | K21: =I21-J21 -> 618502.31 | L21: =I21+Feb!L21 -> 1899388.2 | M21: =J21+Feb!M21 -> 32980883 | N21: =L21-M21 -> -31081495
... B27: =1+B26 -> 19 | C27: United Fund, Inc. | D27: 5.527678e+08 | E27: 22726476 | F27: =D27-E27 -> 5.3004132e+08 | G27: 4.9581516e+08 | H27: 1171 | I27: 3174479.4 | J27: 514311.56 | K27: =I27-J27 -> 2660167.9 | L27: =I27+Feb!L27 -> 3601775 | M27: =J27+Feb!M27 -> 1285828.5 | N27: =L27-M27 -> 2315946.4
A28: Primarily invested in Peso Securities (units)
B29: =1+B27 -> 20 | C29: COL Equity Index Unitized Mutual Fund, Inc. | D29: 2.3455528e+08 | E29: 426165.63 | F29: =D29-E29 -> 2.3412911e+08 | G29: 2.3063e+08 | H29: 5251 | I29: 6342138.6 | J29: 2830530.5 | K29: =I29-J29 -> 3511608 | L29: =I29+Feb!L29 -> 17421092 | M29: =J29+Feb!M29 -> 44221905 | N29: =L29-M29 -> -26800813
B30: =1+B29 -> 21 | C30: COL Strategic Growth Equity Unitized Mutual Fund, Inc. | D30: 2.949785e+08 | E30: 828623.13 | F30: =D30-E30 -> 2.9414988e+08 | G30: 220243098 | H30: 8633 | I30: 4753871.5 | J30: 13486066 | K30: =I30-J30 -> -8732194.3 | L30: =I30+Feb!L30 -> 13101642 | M30: =J30+Feb!M30 -> 72601508 | N30: =L30-M30 -> -59499866
B31: =1+B30 -> 22 | C31: Philequity Alpha One Fund, Inc. | D31: 1.9403589e+08 | E31: 4665031.5 | F31: =D31-E31 -> 1.8937086e+08 | G31: 1.7701323e+08 | H31: 1045 | I31: 114821.04 | J31: 108858.09 | K31: =I31-J31 -> 5962.95 | L31: =I31+Feb!L31 -> 429813.64 | M31: =J31+Feb!M31 -> 6561681 | N31: =L31-M31 -> -6131867.4
B32: =1+B31 -> 23 | C32: Philippine Stock Index Fund Corp. | D32: 499748138 | E32: 10493480 | F32: =D32-E32 -> 489254658 | G32: 482227460 | H32: 801221 | I32: 16419406 | J32: 34454925 | K32: =I32-J32 -> -18035519 | L32: =I32+Feb!L32 -> 40199983 | M32: =J32+Feb!M32 -> 132184129 | N32: =L32-M32 -> -91984146
A33: Exchange Traded Fund
B34: =1+B32 -> 24 | C34: First Metro Phil. Equity Exchange Traded Fund, Inc. | D34: 1224566977 | E34: 1466889 | F34: =D34-E34 -> 1223100088 | G34: 1208912523 | H34: 3238 | I34: 0 | J34: 15825390 | K34: =I34-J34 -> -15825390 | L34: =I34+Feb!L34 -> 8414744 | M34: =J34+Feb!M34 -> 92950465 | N34: =L34-M34 -> -84535721
A35: Sub total - Peso Currency | D35: =SUM(D9:D34) -> 47070428201 | E35: =SUM(E9:E34) -> 4.4384249e+08 | F35: =SUM(F9:F34) -> 46626585709 | G35: =SUM(G9:G34) -> 44500173666 | H35: =SUM(H9:H34) -> 1076783 | I35: =SUM(I9:I34) -> 1.4579507e+08 | J35: =SUM(J9:J34) -> 7.8694137e+08 | K35: =SUM(K9:K34) -> -6.411463e+08 | ... N35: =SUM(N9:N34) -> -2783531059
A36: Primarily invested in foreign currency securities (shares)
B37: =1+B34 -> 25 | C37: ATRAM AsiaPlus Equity Fund, Inc. | D37: 27510200 | E37: 304498.14 | F37: =D37-E37 -> 27205701 | G37: 0 | H37: 42 | I37: 18209.21 | J37: 448009.82 | K37: =I37-J37 -> -429800.61 | L37: =I37+Feb!L37 -> 41428.62 | M37: =J37+Feb!M37 -> 5253395.7 | N37: =L37-M37 -> -5211967.1
B38: =1+B37 -> 26 | C38: Sun Life Prosperity World Voyager Fund, Inc. | D38: 2256911949 | E38: 41712775 | F38: =D38-E38 -> 2215199174 | G38: 0 | H38: 3375 | I38: 13741678 | J38: 126285511 | K38: =I38-J38 -> -112543833 | L38: =I38+Feb!L38 -> 245768807 | M38: =J38+Feb!M38 -> 178921052 | N38: =L38-M38 -> 66847755
A39: Primarily invested in foreign currency securities (units)
B40: =1+B38 -> 27 | C40: Philequity Global Fund, Inc. 3 | D40: 509686.99 | E40: 0 | F40: =D40-E40 -> 509686.99 | G40: 0 | H40: 32 | I40: 13526.68 | J40: 0 | K40: =I40-J40 -> 13526.68 | L40: =I40+Feb!L40 -> 509098.82 | M40: =J40+Feb!M40 -> 0 | N40: =L40-M40 -> 509098.82
A41: Sub total - US Currency | D41: =SUM(D37:D38)+D40 -> 2284931836 | E41: =SUM(E37:E38)+E40 -> 42017273 | F41: =SUM(F37:F38)+F40 -> 2242914562 | G41: =SUM(G37:G38)+G40 -> 0 | H41: =SUM(H37:H38)+H40 -> 3449 | I41: =SUM(I37:I38)+I40 -> 13773414 | J41: =SUM(J37:J38)+J40 -> 1.2673352e+08 | K41: =SUM(K37:K38)+K40 -> -1.1296011e+08 | ... N41: =SUM(N37:N38)+N40 -> 62144887
A42: Sub total - stock funds | D42: =D35+D41 -> 49355360036 | E42: =E35+E41 -> 4.8585976e+08 | F42: =F35+F41 -> 48869500271 | G42: =G35+G41 -> 44500173666 | H42: =H35+H41 -> 1080232 | I42: =I35+I41 -> 1.5956848e+08 | J42: =J35+J41 -> 913674888 | K42: =K35+K41 -> -7.5410641e+08 | ... N42: =N35+N41 -> -2721386172
A43: Balanced Funds
A44: Primarily invested in Peso Securities (shares)
B45: =1+B40 -> 28 | C45: ATRAM Philippine Balanced Fund, Inc. | D45: 3.7140028e+08 | E45: 3007853.7 | F45: =D45-E45 -> 3.6839243e+08 | G45: 1.867039e+08 | H45: 2323 | I45: 841457.64 | J45: 1641817.8 | K45: =I45-J45 -> -800360.17 | L45: =I45+Feb!L45 -> 1820702.9 | M45: =J45+Feb!M45 -> 11914004 | N45: =L45-M45 -> -10093301
B46: =1+B45 -> 29 | C46: ATRAM Unicapital Diversified Growth Fund, Inc. | D46: 1.1151557e+08 | E46: 262474.23 | F46: =D46-E46 -> 111253100 | G46: 28757915 | H46: 837 | I46: 126509.32 | J46: 692870.31 | K46: =I46-J46 -> -566360.99 | L46: =I46+Feb!L46 -> 937521.68 | M46: =J46+Feb!M46 -> 4015149.3 | N46: =L46-M46 -> -3077627.6
B47: =1+B46 -> 30 | C47: First Metro Save and Learn Balanced Fund, Inc. | D47: 543646522 | E47: 7731231 | F47: =D47-E47 -> 535915291 | G47: 273531293 | H47: 4504 | I47: 387927 | J47: 3624873 | K47: =I47-J47 -> -3236946 | L47: =I47+Feb!L47 -> 1261593 | M47: =J47+Feb!M47 -> 20702616 | N47: =L47-M47 -> -19441023
B48: =1+B47 -> 31 | C48: First Metro Save and Learn F.O.C.C.U.S. Dynamic Fund, Inc. | D48: 422240371 | E48: 1324202 | F48: =D48-E48 -> 420916169 | G48: 216282863 | H48: 571 | I48: 5340619 | J48: 42061757 | K48: =I48-J48 -> -36721138 | L48: =I48+Feb!L48 -> 22639926 | M48: =J48+Feb!M48 -> 45030874 | N48: =L48-M48 -> -22390948
B49: =1+B48 -> 32 | C49: NCM Mutual Fund of the Phils., Inc. | D49: 317451025 | E49: 2703238 | F49: =D49-E49 -> 314747787 | G49: 149338537 | H49: 45 | I49: 0 | J49: 0 | K49: =I49-J49 -> 0 | L49: =I49+Feb!L49 -> 0 | M49: =J49+Feb!M49 -> 0 | N49: =L49-M49 -> 0
B50: =1+B49 -> 33 | C50: PAMI Horizon Fund, Inc. | D50: 375056920 | E50: 2235019 | F50: =D50-E50 -> 372821901 | G50: 180275130 | H50: 9348 | I50: 44450 | J50: 10099461 | K50: =I50-J50 -> -10055011 | L50: =I50+Feb!L50 -> 84370 | M50: =J50+Feb!M50 -> 14992357 | N50: =L50-M50 -> -14907987
B51: =1+B50 -> 34 | C51: Philam Fund, Inc. | D51: 1599011998 | E51: 13186974 | F51: =D51-E51 -> 1585825024 | G51: 783445969 | H51: 6562 | I51: 1347509 | J51: 8187712 | K51: =I51-J51 -> -6840203 | L51: =I51+Feb!L51 -> 3019317 | M51: =J51+Feb!M51 -> 43241444 | N51: =L51-M51 -> -40222127
B52: =1+B51 -> 35 | C52: Solidaritas Fund, Inc. | D52: 112373626 | E52: 356679 | F52: =D52-E52 -> 112016947 | G52: 52755180 | H52: 147 | I52: 0 | J52: 274449 | K52: =I52-J52 -> -274449 | L52: =I52+Feb!L52 -> 0 | M52: =J52+Feb!M52 -> 1711051 | N52: =L52-M52 -> -1711051
B53: =1+B52 -> 36 | C53: Sun Life Prosperity Balanced Fund, Inc. | D53: 4626503827 | E53: 78606012 | F53: =D53-E53 -> 4547897815 | G53: 2260584975 | H53: 54857 | I53: 5106950 | J53: 105330113 | K53: =I53-J53 -> -100223163 | L53: =I53+Feb!L53 -> 14275627 | M53: =J53+Feb!M53 -> 248701027 | N53: =L53-M53 -> -234425400
B54: =1+B53 -> 37 | C54: Sun Life Prosperity Dynamic Fund, Inc. | D54: 418639479 | E54: 4052513 | F54: =D54-E54 -> 414586966 | G54: 215441871 | H54: 5003 | I54: 0 | J54: 7306699 | K54: =I54-J54 -> -7306699 | L54: =I54+Feb!L54 -> 0 | M54: =J54+Feb!M54 -> 29175358 | N54: =L54-M54 -> -29175358
A55: Primarily invested in Peso Securities (units)
B56: =1+B54 -> 38 | C56: BPI Wealth Builder Multi-Asset Mutual Fund, Inc. 2 | D56: 1037300552 | E56: 4974741 | F56: =D56-E56 -> 1032325811 | G56: 66554490 | H56: 27586 | I56: 39186414 | J56: 11569434 | K56: =I56-J56 -> 27616980 | L56: =I56+Feb!L56 -> 113212909 | M56: =J56+Feb!M56 -> 26391427 | N56: =L56-M56 -> 86821482
B57: =1+B56 -> 39 | C57: Sun Life Prosperity Achiever Fund 2028, Inc. | D57: 66864076 | E57: 353172 | F57: =D57-E57 -> 66510904 | G57: 10045079 | H57: 1279 | I57: 41500 | J57: 220477 | K57: =I57-J57 -> -178977 | L57: =I57+Feb!L57 -> 137500 | M57: =J57+Feb!M57 -> 2486909 | N57: =L57-M57 -> -2349409
B58: =1+B57 -> 40 | C58: Sun Life Prosperity Achiever Fund 2038, Inc. | D58: 50264099 | E58: 310745 | F58: =D58-E58 -> 49953354 | G58: 33949116 | H58: 520 | I58: 8500 | J58: 76668 | K58: =I58-J58 -> -68168 | L58: =I58+Feb!L58 -> 28500 | M58: =J58+Feb!M58 -> 494374 | N58: =L58-M58 -> -465874
B59: =1+B58 -> 41 | C59: Sun Life Prosperity Achiever Fund 2048, Inc. | D59: 45181567 | E59: 293533 | F59: =D59-E59 -> 44888034 | G59: 36855630 | H59: 257 | I59: 6000 | J59: 830980 | K59: =I59-J59 -> -824980 | L59: =I59+Feb!L59 -> 30000 | M59: =J59+Feb!M59 -> 1343841 | N59: =L59-M59 -> -1313841
A60: Sub total - Peso Currency | D60: =SUM(D45:D59) -> 10097449916 | E60: =SUM(E45:E59) -> 1.1939839e+08 | F60: =SUM(F45:F59) -> 9978051529 | G60: =SUM(G45:G59) -> 4494521946 | H60: =SUM(H45:H59) -> 113839 | I60: =SUM(I45:I59) -> 52437836 | J60: =SUM(J45:J59) -> 1.9191731e+08 | K60: =SUM(K45:K59) -> -1.3947948e+08 | ... N60: =SUM(N45:N59) -> -2.9275246e+08
A61: Primarily invested in foreign currency securities (shares)
B62: =1+B59 -> 42 | C62: Cocolife Dollar Fund Builder, Inc. | D62: 71088935 | E62: 334773.12 | F62: =D62-E62 -> 70754162 | G62: 0 | H62: 49 | I62: 60396.88 | J62: 0 | K62: =I62-J62 -> 60396.88 | L62: =I62+Feb!L62 -> 60396.88 | M62: =J62+Feb!M62 -> 0 | N62: =L62-M62 -> 60396.88
B63: =1+B62 -> 43 | C63: PAMI Asia Balanced Fund, Inc. | D63: 321930121 | E63: 694930 | F63: =D63-E63 -> 321235191 | G63: 1305897 | H63: 193 | I63: 0 | J63: 6295392 | K63: =I63-J63 -> -6295392 | L63: =I63+Feb!L63 -> 0 | M63: =J63+Feb!M63 -> 12165036 | N63: =L63-M63 -> -12165036
B64: =1+B63 -> 44 | C64: Sun Life Prosperity Dollar Advantage Fund, Inc. | D64: 1667235194 | E64: 5340671 | F64: =D64-E64 -> 1661894523 | G64: 0 | H64: 4360 | I64: 2588961 | J64: 26823646 | K64: =I64-J64 -> -24234685 | L64: =I64+Feb!L64 -> 11628286 | M64: =J64+Feb!M64 -> 129292405 | N64: =L64-M64 -> -117664119
B65: =1+B64 -> 45 | C65: Sun Life Prosperity Dollar Wellspring Fund, Inc. | D65: 215145205 | E65: 8847936 | F65: =D65-E65 -> 206297269 | G65: 0 | H65: 783 | I65: 167785 | J65: 4381350 | K65: =I65-J65 -> -4213565 | L65: =I65+Feb!L65 -> 433504 | M65: =J65+Feb!M65 -> 15352450 | N65: =L65-M65 -> -14918946
A66: Sub total - US Currency | D66: =SUM(D62:D65) -> 2275399455 | E66: =SUM(E62:E65) -> 15218310 | F66: =SUM(F62:F65) -> 2260181145 | G66: =SUM(G62:G65) -> 1305897 | H66: =SUM(H62:H65) -> 5385 | I66: =SUM(I62:I65) -> 2817142.9 | J66: =SUM(J62:J65) -> 37500388 | K66: =SUM(K62:K65) -> -34683245 | ... N66: =SUM(N62:N65) -> -1.446877e+08
A67: Sub total - balanced funds | D67: =D60+D66 -> 12372849371 | E67: =E60+E66 -> 134616697 | F67: =F60+F66 -> 12238232674 | G67: =G60+G66 -> 4495827843 | H67: =H60+H66 -> 119224 | I67: =I60+I66 -> 55254979 | J67: =J60+J66 -> 2.294177e+08 | K67: =K60+K66 -> -1.7416272e+08 | ... N67: =N60+N66 -> -4.3744017e+08
A68: Bond Funds
A69: Primarily invested in Peso Securities (shares)
B70: =1+B65 -> 46 | C70: ALFM Peso Bond Fund, Inc. | D70: 34429634240 | E70: 120516375 | F70: =D70-E70 -> 34309117865 | G70: 367250000 | H70: 24515 | I70: 186873605 | J70: 443826204 | K70: =I70-J70 -> -256952599 | L70: =I70+Feb!L70 -> 619041703 | M70: =J70+Feb!M70 -> 1003571948 | N70: =L70-M70 -> -384530245
B71: =1+B70 -> 47 | C71: ATRAM Corporate Bond Fund, Inc. | D71: 2.2832874e+08 | E71: 1315751.5 | F71: =D71-E71 -> 2.2701299e+08 | G71: 0 | H71: 870 | I71: 52908.49 | J71: 1572139.3 | K71: =I71-J71 -> -1519230.8 | L71: =I71+Feb!L71 -> 737967.1 | M71: =J71+Feb!M71 -> 17072677 | N71: =L71-M71 -> -16334710
B72: =1+B71 -> 48 | C72: Cocolife Fixed Income Fund, Inc. | D72: 8.9849951e+08 | E72: 8862129.6 | F72: =D72-E72 -> 889637383 | G72: 0 | H72: 1755 | I72: 800316.37 | J72: 10642827 | K72: =I72-J72 -> -9842510.6 | L72: =I72+Feb!L72 -> 10176925 | M72: =J72+Feb!M72 -> 35383326 | N72: =L72-M72 -> -25206400
B73: =1+B72 -> 49 | C73: Ekklesia Mutual Fund, Inc. | D73: 169895603 | E73: 370866 | F73: =D73-E73 -> 169524737 | G73: 0 | H73: 125 | I73: 0 | J73: 314842 | K73: =I73-J73 -> -314842 | L73: =I73+Feb!L73 -> 0 | M73: =J73+Feb!M73 -> 433089 | N73: =L73-M73 -> -433089
B74: =1+B73 -> 50 | C74: First Metro Save and Learn Fixed Income Fund, Inc. | D74: 701272026 | E74: 3759562 | F74: =D74-E74 -> 697512464 | G74: 0 | H74: 1634 | I74: 2570883 | J74: 3904738 | K74: =I74-J74 -> -1333855 | L74: =I74+Feb!L74 -> 5126285 | M74: =J74+Feb!M74 -> 38717573 | N74: =L74-M74 -> -33591288
B75: =1+B74 -> 51 | C75: Philam Bond Fund, Inc. | D75: 1292782424 | E75: 31157105 | F75: =D75-E75 -> 1261625319 | G75: 0 | H75: 4297 | I75: 2266949 | J75: 13718967 | K75: =I75-J75 -> -11452018 | L75: =I75+Feb!L75 -> 5639169 | M75: =J75+Feb!M75 -> 33712953 | N75: =L75-M75 -> -28073784
B76: =1+B75 -> 52 | C76: Philam Managed Income Fund, Inc. | D76: 482050735 | E76: 9931278 | F76: =D76-E76 -> 472119457 | G76: 0 | H76: 359 | I76: 0 | J76: 8462085 | K76: =I76-J76 -> -8462085 | L76: =I76+Feb!L76 -> 0 | M76: =J76+Feb!M76 -> 10881908 | N76: =L76-M76 -> -10881908
B77: =1+B76 -> 53 | C77: Philequity Peso Bond Fund, Inc. | D77: 3.2460198e+08 | E77: 1593541.5 | F77: =D77-E77 -> 3.2300844e+08 | G77: 0 | H77: 3984 | I77: 40280270 | J77: 766967.46 | K77: =I77-J77 -> 39513303 | L77: =I77+Feb!L77 -> 45737512 | M77: =J77+Feb!M77 -> 2807250 | N77: =L77-M77 -> 42930262
B78: =1+B77 -> 54 | C78: Soldivo Bond Fund, Inc. | D78: 2.1144963e+09 | E78: 3644094.2 | F78: =D78-E78 -> 2110852207 | G78: 0 | H78: 747 | I78: 1.0001019e+08 | J78: 2290437.5 | K78: =I78-J78 -> 97719756 | L78: =I78+Feb!L78 -> 2.0109938e+08 | M78: =J78+Feb!M78 -> 6561963 | N78: =L78-M78 -> 1.9453742e+08
B79: =1+B78 -> 55 | C79: Sun Life Prosperity Bond Fund, Inc. | D79: 6062012283 | E79: 61648875 | F79: =D79-E79 -> 6000363408 | G79: 0 | H79: 19983 | I79: 56990537 | J79: 169860257 | K79: =I79-J79 -> -112869720 | L79: =I79+Feb!L79 -> 158533229 | M79: =J79+Feb!M79 -> 419437768 | N79: =L79-M79 -> -260904539
B80: =1+B79 -> 56 | C80: Sun Life Prosperity GS Fund, Inc. | D80: 138139640 | E80: 454850 | F80: =D80-E80 -> 137684790 | G80: 0 | H80: 2966 | I80: 229693 | J80: 1287016 | K80: =I80-J80 -> -1057323 | L80: =I80+Feb!L80 -> 979330 | M80: =J80+Feb!M80 -> 3254245 | N80: =L80-M80 -> -2274915
A81: Corporate Debt Vehicle (units)
B82: =1+B80 -> 57 | C82: ATRAM Unitized Corporate Debt Vehicle, Inc. 1 | D82: 0 | E82: 0 | F82: =D82-E82 -> 0 | G82: 0 | H82: 0 | I82: 0 | J82: 0 | K82: =I82-J82 -> 0 | L82: =I82+Feb!L82 -> 0 | M82: =J82+Feb!M82 -> 0 | N82: =L82-M82 -> 0
A83: Sub total - Peso Currency | D83: =SUM(D70:D82) -> 46841713489 | E83: =SUM(E70:E82) -> 2.4325443e+08 | F83: =SUM(F70:F82) -> 46598459061 | G83: =SUM(G70:G82) -> 367250000 | H83: =SUM(H70:H82) -> 61235 | I83: =SUM(I70:I82) -> 3.9007536e+08 | J83: =SUM(J70:J82) -> 6.5664648e+08 | K83: =SUM(K70:K82) -> -2.6657112e+08 | ... N83: =SUM(N70:N82) -> -5.2476319e+08
A84: Primarily invested in foreign currency securities (shares)
B85: =B82+1 -> 58 | C85: ALFM Dollar Bond Fund, Inc. | D85: 12245951492 | E85: 634781427 | F85: =D85-E85 -> 11611170065 | G85: 0 | H85: 6717 | I85: 24809481 | J85: 174615106 | K85: =I85-J85 -> -149805625 | L85: =I85+Feb!L85 -> 147431251 | M85: =J85+Feb!M85 -> 396902625 | N85: =L85-M85 -> -249471374
B86: =1+B85 -> 59 | C86: ATRAM Total Return Dollar Bond Fund, Inc. | D86: 51481976 | E86: 2306422.4 | F86: =D86-E86 -> 49175553 | G86: 0 | H86: 21 | I86: 0 | J86: 63517.5 | K86: =I86-J86 -> -63517.5 | L86: =I86+Feb!L86 -> 0 | M86: =J86+Feb!M86 -> 63517.5 | N86: =L86-M86 -> -63517.5
B87: =1+B86 -> 60 | C87: First Metro Save and Learn Dollar Bond Fund, Inc. | D87: 320832737 | E87: 981964 | F87: =D87-E87 -> 319850773 | G87: 0 | H87: 138 | I87: 26135 | J87: 2048060 | K87: =I87-J87 -> -2021925 | L87: =I87+Feb!L87 -> 896042 | M87: =J87+Feb!M87 -> 10182667 | N87: =L87-M87 -> -9286625
B88: =1+B87 -> 61 | C88: PAMI Global Bond Fund, Inc. | D88: 89870620 | E88: 25490236 | F88: =D88-E88 -> 64380384 | G88: 0 | H88: 23 | I88: 0 | J88: 0 | K88: =I88-J88 -> 0 | L88: =I88+Feb!L88 -> 0 | M88: =J88+Feb!M88 -> 0 | N88: =L88-M88 -> 0
B89: =1+B88 -> 62 | C89: Philam Dollar Bond Fund, Inc. | D89: 1629516540 | E89: 72565048 | F89: =D89-E89 -> 1556951492 | G89: 0 | H89: 1414 | I89: 43729 | J89: 35830630 | K89: =I89-J89 -> -35786901 | L89: =I89+Feb!L89 -> 121153 | M89: =J89+Feb!M89 -> 51772613 | N89: =L89-M89 -> -51651460
B90: =1+B89 -> 63 | C90: Philequity Dollar Income Fund, Inc. | D90: =VLOOKUP(C90,'[1]March 2026'!$A:$H,2,FALSE) -> #REF! | E90: =VLOOKUP(C90,'[1]March 2026'!$A:$H,3,FALSE) -> #REF! | F90: =D90-E90 -> #REF! | G90: =VLOOKUP(C90,'[1]March 2026'!$A:$H,5,FALSE) -> #REF! | H90: =VLOOKUP(C90,'[1]March 2026'!$A:$H,6,FALSE) -> #REF! | I90: =VLOOKUP(C90,'[1]March 2026'!$A:$H,7,FALSE) -> #REF! | J90: =VLOOKUP(C90,'[1]March 2026'!$A:$H,8,FALSE) -> #REF! | K90: =I90-J90 -> #REF! | L90: =I90+'Feb UPDATED'!L90 -> #REF! | M90: =J90+'Feb UPDATED'!M90 -> #REF! | N90: =L90-M90 -> #REF!
B91: =1+B90 -> 64 | C91: Sun Life Prosperity Dollar Abundance Fund, Inc. | D91: 397754489 | E91: 2890736 | F91: =D91-E91 -> 394863753 | G91: 0 | H91: 2664 | I91: 10481686 | J91: 20986708 | K91: =I91-J91 -> -10505022 | L91: =I91+Feb!L91 -> 12917391 | M91: =J91+Feb!M91 -> 74824417 | N91: =L91-M91 -> -61907026
A92: Sub total - US Currency | D92: =SUM(D85:D91) -> #REF! | E92: =SUM(E85:E91) -> #REF! | F92: =SUM(F85:F91) -> #REF! | G92: =SUM(G85:G91) -> #REF! | H92: =SUM(H85:H91) -> #REF! | I92: =SUM(I85:I91) -> #REF! | J92: =SUM(J85:J91) -> #REF! | K92: =SUM(K85:K91) -> #REF! | ... N92: =SUM(N85:N91) -> #REF!
B93: =1+B91 -> 65 | C93: ALFM Euro Bond Fund, Inc. | D93: 726660607 | E93: 30635578 | F93: =D93-E93 -> 696025029 | G93: 0 | H93: 554 | I93: 295779 | J93: 6974118 | K93: =I93-J93 -> -6678339 | L93: =I93+Feb!L93 -> 6290235 | M93: =J93+Feb!M93 -> 65546038 | N93: =L93-M93 -> -59255803
A94: Sub total - Euro Currency | D94: =SUM(D93) -> 726660607 | E94: =SUM(E93) -> 30635578 | F94: =SUM(F93) -> 696025029 | G94: =SUM(G93) -> 0 | H94: =SUM(H93) -> 554 | I94: =SUM(I93) -> 295779 | J94: =SUM(J93) -> 6974118 | K94: =SUM(K93) -> -6678339 | ... N94: =SUM(N93) -> -59255803
A95: Sub total - bond funds | D95: =D83+D92+D94 -> #REF! | E95: =E83+E92+E94 -> #REF! | F95: =F83+F92+F94 -> #REF! | G95: =G83+G92+G94 -> #REF! | H95: =H83+H92+H94 -> #REF! | I95: =I83+I92+I94 -> #REF! | J95: =J83+J92+J94 -> #REF! | K95: =K83+K92+K94 -> #REF! | ... N95: =N83+N92+N94 -> #REF!
A96: Money Market Funds
A97: Primarily invested in Peso Securities (shares)
B98: =B93+1 -> 66 | C98: AIB Money Market Mutual Fund, Inc. | D98: 1.7666911e+08 | E98: 341071.22 | F98: =D98-E98 -> 1.7632803e+08 | G98: 0 | H98: 61 | I98: 40000 | J98: 89102.22 | K98: =I98-J98 -> -49102.22 | L98: =I98+Feb!L98 -> 156000 | M98: =J98+Feb!M98 -> 107291.09 | N98: =L98-M98 -> 48708.91
B99: =B98+1 -> 67 | C99: ALFM Money Market Fund, Inc. | D99: 18640581429 | E99: 10359241 | F99: =D99-E99 -> 18630222188 | G99: 0 | H99: 19823 | I99: 336339 | J99: 494888785 | K99: =I99-J99 -> -494552446 | L99: =I99+Feb!L99 -> 1076795 | M99: =J99+Feb!M99 -> 992732752 | N99: =L99-M99 -> -991655957
B100: =B99+1 -> 68 | C100: First Metro Save and Learn Money Market Fund, Inc. | D100: 2488970899 | E100: 3393374 | F100: =D100-E100 -> 2485577525 | G100: 0 | H100: 1228 | I100: 168572725 | J100: 123053350 | K100: =I100-J100 -> 45519375 | L100: =I100+Feb!L100 -> 346452721 | M100: =J100+Feb!M100 -> 320616332 | N100: =L100-M100 -> 25836389
B101: =B100+1 -> 69 | C101: Sun Life Prosperity Peso Starter Fund, Inc. | D101: 10372693808 | E101: 81159640 | F101: =D101-E101 -> 10291534168 | G101: 0 | H101: 75093 | I101: 1003855545 | J101: 783687547 | K101: =I101-J101 -> 220167998 | L101: =I101+Feb!L101 -> 1561794914 | M101: =J101+Feb!M101 -> 2047936873 | N101: =L101-M101 -> -486141959
A102: Primarily invested in Peso Securities (units)
B103: =1+B101 -> 70 | C103: ALFM Money Market Fund, Inc. | D103: 15402752262 | E103: 7899987 | F103: =D103-E103 -> 15394852275 | G103: 0 | H103: 33444 | I103: 2040456953 | J103: 1541280120 | K103: =I103-J103 -> 499176833 | L103: =I103+Feb!L103 -> 5048361234 | M103: =J103+Feb!M103 -> 3517846161 | N103: =L103-M103 -> 1530515073
A104: Sub total - Peso Currency | D104: =SUM(D98:D101)+D103 -> 47081667504 | E104: =SUM(E98:E101)+E103 -> 1.0315331e+08 | F104: =SUM(F98:F101)+F103 -> 46978514191 | G104: =SUM(G98:G101)+G103 -> 0 | H104: =SUM(H98:H101)+H103 -> 129649 | I104: =SUM(I98:I101)+I103 -> 3213261562 | J104: =SUM(J98:J101)+J103 -> 2942998904 | K104: =SUM(K98:K101)+K103 -> 2.7026266e+08 | ... N104: =SUM(N98:N101)+N103 -> 78602255
A105: Primarily invested in foreign currency securities (shares)
...

Sheet Q1
A1: PHILIPPINE INVESTMENT FUNDS ASSOCIATION, INC.
A2: MUTUAL FUNDS STATISTICAL REPORT
A3: For the First Quarter of 2026
A4: (Amounts in Peso)
E5: Y E A R - T O - D A T E
A6: Fund Category | C6: Fund Name | D6: NET ASSETS | E6: TOTAL SALES | F6: TOTAL REDEMPTIONS | G6: TOTAL NET SALES
A7: Stock Funds
A8: Primarily invested in Peso Securities (shares)
B9: 1 | C9: ALFM Growth Fund, Inc. | D9: =Mar!F9 -> 3263465452 | E9: =Jan!I9+Feb!I9+Mar!I9 -> 13207308 | F9: =Jan!J9+Feb!J9+Mar!J9 -> 144274668 | G9: =E9-F9 -> -131067360
B10: =1+B9 -> 2 | C10: ATRAM Alpha Opportunity Fund, Inc. | D10: =Mar!F10 -> 9.7249971e+08 | E10: =Jan!I10+Feb!I10+Mar!I10 -> 30792899 | F10: =Jan!J10+Feb!J10+Mar!J10 -> 1.3308464e+08 | G10: =E10-F10 -> -1.0229174e+08
B11: =1+B10 -> 3 | C11: ATRAM Phil. Equity Opportunity Fund, Inc. | D11: =Mar!F11 -> 8.8275738e+08 | E11: =Jan!I11+Feb!I11+Mar!I11 -> 10231429 | F11: =Jan!J11+Feb!J11+Mar!J11 -> 68288819 | G11: =E11-F11 -> -58057390
B12: =1+B11 -> 4 | C12: Climbs Share Capital Equity Investment Fund Corp. | D12: =Mar!F12 -> 5.1244855e+08 | E12: =Jan!I12+Feb!I12+Mar!I12 -> 36625656 | F12: =Jan!J12+Feb!J12+Mar!J12 -> 18077524 | G12: =E12-F12 -> 18548133
B13: =1+B12 -> 5 | C13: First Metro Consumer Fund, Inc. | D13: =Mar!F13 -> 237121237 | E13: =Jan!I13+Feb!I13+Mar!I13 -> 367641 | F13: =Jan!J13+Feb!J13+Mar!J13 -> 26994036 | G13: =E13-F13 -> -26626395
B14: =1+B13 -> 6 | C14: First Metro Save and Learn Equity Fund, Inc. | D14: =Mar!F14 -> 2230096393 | E14: =Jan!I14+Feb!I14+Mar!I14 -> 13260639 | F14: =Jan!J14+Feb!J14+Mar!J14 -> 114703192 | G14: =E14-F14 -> -101442553
B15: =1+B14 -> 7 | C15: First Metro Save and Learn Phil. Index Fund, Inc. | D15: =Mar!F15 -> 61417654 | E15: =Jan!I15+Feb!I15+Mar!I15 -> 636464 | F15: =Jan!J15+Feb!J15+Mar!J15 -> 1845483 | G15: =E15-F15 -> -1209019
B16: =1+B15 -> 8 | C16: MBG Equity Investment Fund, Inc. | D16: =Mar!F16 -> 18789827 | E16: =Jan!I16+Feb!I16+Mar!I16 -> 0 | F16: =Jan!J16+Feb!J16+Mar!J16 -> 0 | G16: =E16-F16 -> 0
B17: =1+B16 -> 9 | C17: PAMI Equity Index Fund, Inc. | D17: =Mar!F17 -> 837030884 | E17: =Jan!I17+Feb!I17+Mar!I17 -> 0 | F17: =Jan!J17+Feb!J17+Mar!J17 -> 28492183 | G17: =E17-F17 -> -28492183
B18: =1+B17 -> 10 | C18: Philam Strategic Growth Fund, Inc. | D18: =Mar!F18 -> 2581302190 | E18: =Jan!I18+Feb!I18+Mar!I18 -> 0 | F18: =Jan!J18+Feb!J18+Mar!J18 -> 116320477 | G18: =E18-F18 -> -116320477
B19: =1+B18 -> 11 | C19: Philequity Dividend Yield Fund, Inc. | D19: =Mar!F19 -> 2537796058 | E19: =Jan!I19+Feb!I19+Mar!I19 -> 37064224 | F19: =Jan!J19+Feb!J19+Mar!J19 -> 158101232 | G19: =E19-F19 -> -121037008
B20: =1+B19 -> 12 | C20: Philequity Fund, Inc. | D20: =Mar!F20 -> 7777211793 | E20: =Jan!I20+Feb!I20+Mar!I20 -> 25970226 | F20: =Jan!J20+Feb!J20+Mar!J20 -> 2.1456214e+08 | G20: =E20-F20 -> -1.8859191e+08
B21: =1+B20 -> 13 | C21: Philequity MSCI Phil. Index Fund, Inc. | D21: =Mar!F21 -> 2.7645025e+08 | E21: =Jan!I21+Feb!I21+Mar!I21 -> 1899388.2 | F21: =Jan!J21+Feb!J21+Mar!J21 -> 32980883 | G21: =E21-F21 -> -31081495
... B27: =1+B26 -> 19 | C27: United Fund, Inc. | D27: =Mar!F27 -> 5.3004132e+08 | E27: =Jan!I27+Feb!I27+Mar!I27 -> 3601775 | F27: =Jan!J27+Feb!J27+Mar!J27 -> 1285828.5 | G27: =E27-F27 -> 2315946.4
A28: Primarily invested in Peso Securities (units)
B29: =1+B27 -> 20 | C29: COL Equity Index Unitized Mutual Fund, Inc. | D29: =Mar!F29 -> 2.3412911e+08 | E29: =Jan!I29+Feb!I29+Mar!I29 -> 17421092 | F29: =Jan!J29+Feb!J29+Mar!J29 -> 44221905 | G29: =E29-F29 -> -26800813
B30: =1+B29 -> 21 | C30: COL Strategic Growth Equity Unitized Mutual Fund, Inc. | D30: =Mar!F30 -> 2.9414988e+08 | E30: =Jan!I30+Feb!I30+Mar!I30 -> 13101642 | F30: =Jan!J30+Feb!J30+Mar!J30 -> 72601508 | G30: =E30-F30 -> -59499866
B31: =1+B30 -> 22 | C31: Philequity Alpha One Fund, Inc. | D31: =Mar!F31 -> 1.8937086e+08 | E31: =Jan!I31+Feb!I31+Mar!I31 -> 429813.64 | F31: =Jan!J31+Feb!J31+Mar!J31 -> 6561681 | G31: =E31-F31 -> -6131867.4
B32: =1+B31 -> 23 | C32: Philippine Stock Index Fund Corp. | D32: =Mar!F32 -> 489254658 | E32: =Jan!I32+Feb!I32+Mar!I32 -> 40199983 | F32: =Jan!J32+Feb!J32+Mar!J32 -> 132184129 | G32: =E32-F32 -> -91984146
A33: Exchange Traded Fund
B34: =1+B32 -> 24 | C34: First Metro Phil. Equity Exchange Traded Fund, Inc. | D34: =Mar!F34 -> 1223100088 | E34: =Jan!I34+Feb!I34+Mar!I34 -> 8414744 | F34: =Jan!J34+Feb!J34+Mar!J34 -> 92950465 | G34: =E34-F34 -> -84535721
A35: Sub total - Peso Currency | D35: =SUM(D9:D34) -> 46626585709 | E35: =SUM(E9:E34) -> 3.5682315e+08 | F35: =SUM(F9:F34) -> 3140354210 | G35: =SUM(G9:G34) -> -2783531059
A36: Primarily invested in foreign currency securities (shares)
B37: =1+B34 -> 25 | C37: ATRAM AsiaPlus Equity Fund, Inc. | D37: =Mar!F37 -> 27205701 | E37: =Jan!I37+Feb!I37+Mar!I37 -> 41428.62 | F37: =Jan!J37+Feb!J37+Mar!J37 -> 5253395.7 | G37: =E37-F37 -> -5211967.1
B38: =1+B37 -> 26 | C38: Sun Life Prosperity World Voyager Fund, Inc. | D38: =Mar!F38 -> 2215199174 | E38: =Jan!I38+Feb!I38+Mar!I38 -> 245768807 | F38: =Jan!J38+Feb!J38+Mar!J38 -> 178921052 | G38: =E38-F38 -> 66847755
A39: Primarily invested in foreign currency securities (units)
B40: =1+B38 -> 27 | C40: Philequity Global Fund, Inc. 3 | D40: =Mar!F40 -> 509686.99 | E40: =Feb!I40+Mar!I40 -> 509098.82 | F40: =Feb!J40+Mar!J40 -> 0 | G40: =E40-F40 -> 509098.82
A41: Sub total - US Currency | D41: =SUM(D37:D38)+D40 -> 2242914562 | E41: =SUM(E37:E38)+E40 -> 2.4631933e+08 | F41: =SUM(F37:F38)+F40 -> 1.8417445e+08 | G41: =SUM(G37:G38)+G40 -> 62144887
A42: Sub total - stock funds | D42: =D35+D41 -> 48869500271 | E42: =E35+E41 -> 6.0314249e+08 | F42: =F35+F41 -> 3324528658 | G42: =G35+G41 -> -2721386172
A43: Balanced Funds
A44: Primarily invested in Peso Securities (shares)
B45: =1+B40 -> 28 | C45: ATRAM Philippine Balanced Fund, Inc. | D45: =Mar!F45 -> 3.6839243e+08 | E45: =Jan!I43+Feb!I45+Mar!I45 -> 1820702.9 | F45: =Jan!J43+Feb!J45+Mar!J45 -> 11914004 | G45: =E45-F45 -> -10093301
B46: =1+B45 -> 29 | C46: ATRAM Unicapital Diversified Growth Fund, Inc. | D46: =Mar!F46 -> 111253100 | E46: =Jan!I44+Feb!I46+Mar!I46 -> 937521.68 | F46: =Jan!J44+Feb!J46+Mar!J46 -> 4015149.3 | G46: =E46-F46 -> -3077627.6
B47: =1+B46 -> 30 | C47: First Metro Save and Learn Balanced Fund, Inc. | D47: =Mar!F47 -> 535915291 | E47: =Jan!I45+Feb!I47+Mar!I47 -> 1261593 | F47: =Jan!J45+Feb!J47+Mar!J47 -> 20702616 | G47: =E47-F47 -> -19441023
B48: =1+B47 -> 31 | C48: First Metro Save and Learn F.O.C.C.U.S. Dynamic Fund, Inc. | D48: =Mar!F48 -> 420916169 | E48: =Jan!I46+Feb!I48+Mar!I48 -> 22639926 | F48: =Jan!J46+Feb!J48+Mar!J48 -> 45030874 | G48: =E48-F48 -> -22390948
B49: =1+B48 -> 32 | C49: NCM Mutual Fund of the Phils., Inc. | D49: =Mar!F49 -> 314747787 | E49: =Jan!I47+Feb!I49+Mar!I49 -> 0 | F49: =Jan!J47+Feb!J49+Mar!J49 -> 0 | G49: =E49-F49 -> 0
B50: =1+B49 -> 33 | C50: PAMI Horizon Fund, Inc. | D50: =Mar!F50 -> 372821901 | E50: =Jan!I48+Feb!I50+Mar!I50 -> 84370 | F50: =Jan!J48+Feb!J50+Mar!J50 -> 14992357 | G50: =E50-F50 -> -14907987
B51: =1+B50 -> 34 | C51: Philam Fund, Inc. | D51: =Mar!F51 -> 1585825024 | E51: =Jan!I49+Feb!I51+Mar!I51 -> 3019317 | F51: =Jan!J49+Feb!J51+Mar!J51 -> 43241444 | G51: =E51-F51 -> -40222127
B52: =1+B51 -> 35 | C52: Solidaritas Fund, Inc. | D52: =Mar!F52 -> 112016947 | E52: =Jan!I50+Feb!I52+Mar!I52 -> 0 | F52: =Jan!J50+Feb!J52+Mar!J52 -> 1711051 | G52: =E52-F52 -> -1711051
B53: =1+B52 -> 36 | C53: Sun Life Prosperity Balanced Fund, Inc. | D53: =Mar!F53 -> 4547897815 | E53: =Jan!I51+Feb!I53+Mar!I53 -> 14275627 | F53: =Jan!J51+Feb!J53+Mar!J53 -> 248701027 | G53: =E53-F53 -> -234425400
B54: =1+B53 -> 37 | C54: Sun Life Prosperity Dynamic Fund, Inc. | D54: =Mar!F54 -> 414586966 | E54: =Jan!I52+Feb!I54+Mar!I54 -> 0 | F54: =Jan!J52+Feb!J54+Mar!J54 -> 29175358 | G54: =E54-F54 -> -29175358
A55: Primarily invested in Peso Securities (units)
B56: =1+B54 -> 38 | C56: BPI Wealth Builder Multi-Asset Mutual Fund, Inc. 2 | D56: =Mar!F56 -> 1032325811 | E56: =Jan!I54+Feb!I56+Mar!I56 -> 113212909 | F56: =Jan!J54+Feb!J56+Mar!J56 -> 26391427 | G56: =E56-F56 -> 86821482
B57: =1+B56 -> 39 | C57: Sun Life Prosperity Achiever Fund 2028, Inc. | D57: =Mar!F57 -> 66510904 | E57: =Jan!I55+Feb!I57+Mar!I57 -> 137500 | F57: =Jan!J55+Feb!J57+Mar!J57 -> 2486909 | G57: =E57-F57 -> -2349409
B58: =1+B57 -> 40 | C58: Sun Life Prosperity Achiever Fund 2038, Inc. | D58: =Mar!F58 -> 49953354 | E58: =Jan!I56+Feb!I58+Mar!I58 -> 28500 | F58: =Jan!J56+Feb!J58+Mar!J58 -> 494374 | G58: =E58-F58 -> -465874
B59: =1+B58 -> 41 | C59: Sun Life Prosperity Achiever Fund 2048, Inc. | D59: =Mar!F59 -> 44888034 | E59: =Jan!I57+Feb!I59+Mar!I59 -> 30000 | F59: =Jan!J57+Feb!J59+Mar!J59 -> 1343841 | G59: =E59-F59 -> -1313841
A60: Sub total - Peso Currency | D60: =SUM(D45:D59) -> 9978051529 | E60: =SUM(E45:E59) -> 1.5744797e+08 | F60: =SUM(F45:F59) -> 4.5020043e+08 | G60: =SUM(G45:G59) -> -2.9275246e+08
A61: Primarily invested in foreign currency securities (shares)
B62: =1+B59 -> 42 | C62: Cocolife Dollar Fund Builder, Inc. | D62: =Mar!F62 -> 70754162 | E62: =Jan!I60+Feb!I62+Mar!I62 -> 60396.88 | F62: =Jan!J60+Feb!J62+Mar!J62 -> 0 | G62: =E62-F62 -> 60396.88
B63: =1+B62 -> 43 | C63: PAMI Asia Balanced Fund, Inc. | D63: =Mar!F63 -> 321235191 | E63: =Jan!I61+Feb!I63+Mar!I63 -> 0 | F63: =Jan!J61+Feb!J63+Mar!J63 -> 12165036 | G63: =E63-F63 -> -12165036
B64: =1+B63 -> 44 | C64: Sun Life Prosperity Dollar Advantage Fund, Inc. | D64: =Mar!F64 -> 1661894523 | E64: =Jan!I62+Feb!I64+Mar!I64 -> 11628286 | F64: =Jan!J62+Feb!J64+Mar!J64 -> 129292405 | G64: =E64-F64 -> -117664119
B65: =1+B64 -> 45 | C65: Sun Life Prosperity Dollar Wellspring Fund, Inc. | D65: =Mar!F65 -> 206297269 | E65: =Jan!I63+Feb!I65+Mar!I65 -> 433504 | F65: =Jan!J63+Feb!J65+Mar!J65 -> 15352450 | G65: =E65-F65 -> -14918946
A66: Sub total - US Currency | D66: =SUM(D62:D65) -> 2260181145 | E66: =SUM(E62:E65) -> 12122187 | F66: =SUM(F62:F65) -> 156809891 | G66: =SUM(G62:G65) -> -1.446877e+08
A67: Sub total - balanced funds | D67: =D60+D66 -> 12238232674 | E67: =E60+E66 -> 1.6957015e+08 | F67: =F60+F66 -> 6.0701032e+08 | G67: =G60+G66 -> -4.3744017e+08
A68: Bond Funds
A69: Primarily invested in Peso Securities (shares)
B70: =1+B65 -> 46 | C70: ALFM Peso Bond Fund, Inc. | D70: =Mar!F70 -> 34309117865 | E70: =Jan!I68+Feb!I70+Mar!I70 -> 619041703 | F70: =Jan!J68+Feb!J70+Mar!J70 -> 1003571948 | G70: =E70-F70 -> -384530245
B71: =1+B70 -> 47 | C71: ATRAM Corporate Bond Fund, Inc. | D71: =Mar!F71 -> 2.2701299e+08 | E71: =Jan!I69+Feb!I71+Mar!I71 -> 737967.1 | F71: =Jan!J69+Feb!J71+Mar!J71 -> 17072677 | G71: =E71-F71 -> -16334710
B72: =1+B71 -> 48 | C72: Cocolife Fixed Income Fund, Inc. | D72: =Mar!F72 -> 889637383 | E72: =Jan!I70+Feb!I72+Mar!I72 -> 10176925 | F72: =Jan!J70+Feb!J72+Mar!J72 -> 35383326 | G72: =E72-F72 -> -25206400
B73: =1+B72 -> 49 | C73: Ekklesia Mutual Fund, Inc. | D73: =Mar!F73 -> 169524737 | E73: =Jan!I71+Feb!I73+Mar!I73 -> 0 | F73: =Jan!J71+Feb!J73+Mar!J73 -> 433089 | G73: =E73-F73 -> -433089
B74: =1+B73 -> 50 | C74: First Metro Save and Learn Fixed Income Fund, Inc. | D74: =Mar!F74 -> 697512464 | E74: =Jan!I72+Feb!I74+Mar!I74 -> 5126285 | F74: =Jan!J72+Feb!J74+Mar!J74 -> 38717573 | G74: =E74-F74 -> -33591288
B75: =1+B74 -> 51 | C75: Philam Bond Fund, Inc. | D75: =Mar!F75 -> 1261625319 | E75: =Jan!I73+Feb!I75+Mar!I75 -> 5639169 | F75: =Jan!J73+Feb!J75+Mar!J75 -> 33712953 | G75: =E75-F75 -> -28073784
B76: =1+B75 -> 52 | C76: Philam Managed Income Fund, Inc. | D76: =Mar!F76 -> 472119457 | E76: =Jan!I74+Feb!I76+Mar!I76 -> 0 | F76: =Jan!J74+Feb!J76+Mar!J76 -> 10881908 | G76: =E76-F76 -> -10881908
B77: =1+B76 -> 53 | C77: Philequity Peso Bond Fund, Inc. | D77: =Mar!F77 -> 3.2300844e+08 | E77: =Jan!I75+Feb!I77+Mar!I77 -> 45737512 | F77: =Jan!J75+Feb!J77+Mar!J77 -> 2807250 | G77: =E77-F77 -> 42930262
B78: =1+B77 -> 54 | C78: Soldivo Bond Fund, Inc. | D78: =Mar!F78 -> 2110852207 | E78: =Jan!I76+Feb!I78+Mar!I78 -> 2.0109938e+08 | F78: =Jan!J76+Feb!J78+Mar!J78 -> 6561963 | G78: =E78-F78 -> 1.9453742e+08
B79: =1+B78 -> 55 | C79: Sun Life Prosperity Bond Fund, Inc. | D79: =Mar!F79 -> 6000363408 | E79: =Jan!I77+Feb!I79+Mar!I79 -> 158533229 | F79: =Jan!J77+Feb!J79+Mar!J79 -> 419437768 | G79: =E79-F79 -> -260904539
B80: =1+B79 -> 56 | C80: Sun Life Prosperity GS Fund, Inc. | D80: =Mar!F80 -> 137684790 | E80: =Jan!I78+Feb!I80+Mar!I80 -> 979330 | F80: =Jan!J78+Feb!J80+Mar!J80 -> 3254245 | G80: =E80-F80 -> -2274915
A81: Corporate Debt Vehicle (units) | D81: =Mar!F81
B82: =1+B80 -> 57 | C82: ATRAM Unitized Corporate Debt Vehicle, Inc. 1 | D82: =Mar!F82 -> 0 | E82: =Jan!I80+Feb!I82+Mar!I82 -> 0 | F82: =Jan!J80+Feb!J82+Mar!J82 -> 0 | G82: =E82-F82 -> 0
A83: Sub total - Peso Currency | D83: =SUM(D70:D82) -> 46598459061 | E83: =SUM(E70:E82) -> 1047071505 | F83: =SUM(F70:F82) -> 1571834700 | G83: =SUM(G70:G82) -> -5.2476319e+08
A84: Primarily invested in foreign currency securities (shares)
B85: =B82+1 -> 58 | C85: ALFM Dollar Bond Fund, Inc. | D85: =Mar!F85 -> 11611170065 | E85: =Jan!I83+Feb!I85+Mar!I85 -> 147431251 | F85: =Jan!J83+Feb!J85+Mar!J85 -> 396902625 | G85: =E85-F85 -> -249471374
B86: =1+B85 -> 59 | C86: ATRAM Total Return Dollar Bond Fund, Inc. | D86: =Mar!F86 -> 49175553 | E86: =Jan!I84+Feb!I86+Mar!I86 -> 0 | F86: =Jan!J84+Feb!J86+Mar!J86 -> 63517.5 | G86: =E86-F86 -> -63517.5
B87: =1+B86 -> 60 | C87: First Metro Save and Learn Dollar Bond Fund, Inc. | D87: =Mar!F87 -> 319850773 | E87: =Jan!I85+Feb!I87+Mar!I87 -> 896042 | F87: =Jan!J85+Feb!J87+Mar!J87 -> 10182667 | G87: =E87-F87 -> -9286625
B88: =1+B87 -> 61 | C88: PAMI Global Bond Fund, Inc. | D88: =Mar!F88 -> 64380384 | E88: =Jan!I86+Feb!I88+Mar!I88 -> 0 | F88: =Jan!J86+Feb!J88+Mar!J88 -> 0 | G88: =E88-F88 -> 0
B89: =1+B88 -> 62 | C89: Philam Dollar Bond Fund, Inc. | D89: =Mar!F89 -> 1556951492 | E89: =Jan!I87+Feb!I89+Mar!I89 -> 121153 | F89: =Jan!J87+Feb!J89+Mar!J89 -> 51772613 | G89: =E89-F89 -> -51651460
B90: =1+B89 -> 63 | C90: Philequity Dollar Income Fund, Inc. | D90: =Mar!F90 -> #REF! | E90: =Jan!I88+'Feb UPDATED'!I90+Mar!I90 -> #REF! | F90: =Jan!J88+'Feb UPDATED'!J90+Mar!J90 -> #REF! | G90: =E90-F90 -> #REF!
B91: =1+B90 -> 64 | C91: Sun Life Prosperity Dollar Abundance Fund, Inc. | D91: =Mar!F91 -> 394863753 | E91: =Jan!I89+Feb!I91+Mar!I91 -> 12917391 | F91: =Jan!J89+Feb!J91+Mar!J91 -> 74824417 | G91: =E91-F91 -> -61907026
A92: Sub total - US Currency | D92: =SUM(D85:D91) -> #REF! | E92: =SUM(E85:E91) -> #REF! | F92: =SUM(F85:F91) -> #REF! | G92: =SUM(G85:G91) -> #REF!
B93: =1+B91 -> 65 | C93: ALFM Euro Bond Fund, Inc. | D93: =Mar!F93 -> 696025029 | E93: =Jan!I91+Feb!I93+Mar!I93 -> 6290235 | F93: =Jan!J91+Feb!J93+Mar!J93 -> 65546038 | G93: =E93-F93 -> -59255803
A94: Sub total - Euro Currency | D94: =SUM(D93) -> 696025029 | E94: =SUM(E93) -> 6290235 | F94: =SUM(F93) -> 65546038 | G94: =SUM(G93) -> -59255803
A95: Sub total - bond funds | D95: =D83+D92+D94 -> #REF! | E95: =E83+E92+E94 -> #REF! | F95: =F83+F92+F94 -> #REF! | G95: =G83+G92+G94 -> #REF!
A96: Money Market Funds
A97: Primarily invested in Peso Securities (shares)
B98: =B93+1 -> 66 | C98: AIB Money Market Mutual Fund, Inc. | D98: =Mar!F98 -> 1.7632803e+08 | E98: =Jan!I96+Feb!I98+Mar!I98 -> 156000 | F98: =Jan!J96+Feb!J98+Mar!J98 -> 107291.09 | G98: =E98-F98 -> 48708.91
B99: =B98+1 -> 67 | C99: ALFM Money Market Fund, Inc. | D99: =Mar!F99 -> 18630222188 | E99: =Jan!I97+Feb!I99+Mar!I99 -> 1076795 | F99: =Jan!J97+Feb!J99+Mar!J99 -> 992732752 | G99: =E99-F99 -> -991655957
B100: =B99+1 -> 68 | C100: First Metro Save and Learn Money Market Fund, Inc. | D100: =Mar!F100 -> 2485577525 | E100: =Jan!I98+Feb!I100+Mar!I100 -> 346452721 | F100: =Jan!J98+Feb!J100+Mar!J100 -> 320616332 | G100: =E100-F100 -> 25836389
B101: =B100+1 -> 69 | C101: Sun Life Prosperity Peso Starter Fund, Inc. | D101: =Mar!F101 -> 10291534168 | E101: =Jan!I99+Feb!I101+Mar!I101 -> 1561794914 | F101: =Jan!J99+Feb!J101+Mar!J101 -> 2047936873 | G101: =E101-F101 -> -486141959
A102: Primarily invested in Peso Securities (units)
B103: =1+B101 -> 70 | C103: ALFM Money Market Fund, Inc. | D103: =Mar!F103 -> 15394852275 | E103: =Jan!I101+Feb!I103+Mar!I103 -> 5048361234 | F103: =Jan!J101+Feb!J103+Mar!J103 -> 3517846161 | G103: =E103-F103 -> 1530515073
A104: Sub total - Peso Currency | D104: =SUM(D98:D101)+D103 -> 46978514191 | E104: =SUM(E98:E101)+E103 -> 6957841664 | F104: =SUM(F98:F101)+F103 -> 6879239409 | G104: =SUM(G98:G101)+G103 -> 78602255
A105: Primarily invested in foreign currency securities (shares)
...

Sheet AUM
A1: PHILIPPINE INVESTMENT FUNDS ASSOCIATION, INC.
A2: ASSET UNDER MANAGEMENT
A4: No. | B4: Company | C4: No. of Funds | D4: January | E4: February | F4: March | G4: April | H4: May | I4: June | J4: July | K4: August | L4: September | M4: October | N4: November | O4: December
A5: 1 | B5: AIB | C5: 1 | D5: =Jan!F96 -> 1.7561621e+08 | E5: =Feb!F98 -> 1.7598153e+08 | F5: =Mar!F98 -> 1.7632803e+08
A6: =1+A5 -> 2 | B6: ATR FAMI | C6: 9 | D6: =Jan!F13+Jan!F14+Jan!F15+Jan!F34+Jan!F45+Jan!F46+Jan!F72+Jan!F85+Jan!F98 -> 8578750652 | E6: =Feb!F13+Feb!F14+Feb!F15+Feb!F34+Feb!F47+Feb!F48+Feb!F74+Feb!F87+Feb!F100 -> 8709800414 | F6: =Mar!F13+Mar!F14+Mar!F15+Mar!F34+Mar!F47+Mar!F48+Mar!F74+Mar!F87+Mar!F100 -> 8211507594
A7: =1+A6 -> 3 | B7: ATRAM | C7: =8+2 -> 10 | D7: =Jan!F10+Jan!F11+Jan!F24+Jan!F37+Jan!F43+Jan!F44+Jan!F69+Jan!F76+Jan!F80+Jan!F84 -> 8508559380 | E7: =Feb!F10+Feb!F11+Feb!F24+Feb!F37+Feb!F45+Feb!F46+Feb!F71+Feb!F78+Feb!F82+Feb!F86 -> 8742017367 | F7: =Mar!F10+Mar!F11+Mar!F24+Mar!F37+Mar!F45+Mar!F46+Mar!F71+Mar!F78+Mar!F82+Mar!F86 -> 8146244554
A8: =1+A7 -> 4 | B8: BPI Wealth | C8: =8+1+9+1+1 -> 20 | D8: =Jan!F9+Jan!F17+Jan!F18+Jan!F23+Jan!F32+Jan!F48+Jan!F49+Jan!F50+Jan!F54+Jan!F61+Jan!F68+Jan!F71+Jan!F73+Jan!F74+Jan!F83+Jan!F86+Jan!F87+Jan!F91+Jan!F97+Jan!F101+Jan!F109+Jan!F114+Jan!F47 -> 119349211086 | E8: =Feb!F9+Feb!F17+Feb!F18+Feb!F23+Feb!F32+Feb!F49+Feb!F50+Feb!F51+Feb!F52+Feb!F56+Feb!F63+Feb!F70+Feb!F73+Feb!F75+Feb!F76+Feb!F85+Feb!F88+Feb!F89+Feb!F93+Feb!F99+Feb!F103+Feb!F111+Feb!F116 -> 120507165837 | F8: =Mar!F9+Mar!F17+Mar!F18+Mar!F23+Mar!F32+Mar!F49+Mar!F50+Mar!F51+Mar!F52+Mar!F56+Mar!F63+Mar!F70+Mar!F73+Mar!F75+Mar!F76+Mar!F85+Mar!F88+Mar!F89+Mar!F93+Mar!F99+Mar!F103+Mar!F111+Mar!F116 -> 118876575764
A9: =1+A8 -> 5 | B9: CAMCI | C9: 3 | D9: =Jan!F27+Jan!F60+Jan!F70 -> 1549506758 | E9: =Feb!F27+Feb!F62+Feb!F72 -> 1548256413 | F9: =Mar!F27+Mar!F62+Mar!F72 -> 1490432867
A10: =1+A9 -> 6 | B10: CIMAC | C10: 1 | D10: =Jan!F12 -> 489458724 | E10: =Feb!F12 -> 4.9869416e+08 | F10: =Mar!F12 -> 5.1244855e+08
A11: =1+A10 -> 7 | B11: CMI | C11: =1+1 -> 2 | D11: =Jan!F29+Jan!F30 -> 5.7255486e+08 | E11: =Feb!F29+Feb!F30 -> 5.7554283e+08 | F11: =Mar!F29+Mar!F30 -> 5.2827899e+08
A12: =1+A11 -> 8 | B12: MBG | C12: 1 | D12: =Jan!F16 -> 22207054 | E12: =Feb!F16 -> 21697622 | F12: =Mar!F16 -> 18789827
A13: =1+A12 -> 9 | B13: PEMI | C13: =7+1 -> 8 | D13: =Jan!F19+Jan!F20+Jan!F21+Jan!F22+Jan!F31+Jan!F75+Jan!F88 -> 15090979264 | E13: =Feb!F19+Feb!F20+Feb!F21+Feb!F22+Feb!F31+Feb!F40+Feb!F77+Feb!F90 -> 15312339812 | F13: =Mar!F19+Mar!F20+Mar!F21+Mar!F22+Mar!F31+Mar!F40+Mar!F77+Mar!F90 -> #REF!
A14: =1+A13 -> 10 | B14: SLAMCI | C14: =15+1+1 -> 17 | D14: =Jan!F25+Jan!F26+Jan!F38+Jan!F51+Jan!F52+Jan!F55+Jan!F56+Jan!F57+Jan!F62+Jan!F63+Jan!F77+Jan!F78+Jan!F89+Jan!F99+Jan!F104+Jan!F110+Jan!F111 -> 51118488558 | E14: =Feb!F25+Feb!F26+Feb!F38+Feb!F53+Feb!F54+Feb!F57+Feb!F58+Feb!F59+Feb!F64+Feb!F65+Feb!F79+Feb!F80+Feb!F91+Feb!F101+Feb!F106+Feb!F112+Feb!F113 -> 51623915010 | F14: =Mar!F25+Mar!F26+Mar!F38+Mar!F53+Mar!F54+Mar!F57+Mar!F58+Mar!F59+Mar!F64+Mar!F65+Mar!F79+Mar!F80+Mar!F91+Mar!F101+Mar!F106+Mar!F112+Mar!F113 -> 49103625646
A16: GRAND TOTALS | C16: =SUM(C5:C14) -> 72 | D16: =SUM(D5:D14) -> 205455332549 | E16: =SUM(E5:E14) -> 207715410994 | F16: =SUM(F5:F14) -> #REF! | G16: =SUM(G5:G14) -> 0 | H16: =SUM(H5:H14) -> 0 | I16: =SUM(I5:I14) -> 0 | J16: =SUM(J5:J14) -> 0 | ... O16: =SUM(O5:O14) -> 0
D17: =D16-Jan!F117 -> 0 | E17: =E16-'Feb UPDATED'!F119 -> 3.0517578e-05 | F17: =F16-Mar!F119 -> #REF! | G17: =G16-#REF! -> #REF! | H17: =H16-#REF! -> #REF! | I17: =I16-#REF! -> #REF! | J17: =J16-#REF! -> #REF! | K17: =K16-#REF! -> #REF! | L17: =L16-#REF! -> #REF! | M17: =M16-#REF! -> #REF! | N17: =N16-#REF! -> #REF! | O17: =O16-Jan!F117 -> -205455332549

Sheet NET SALES
A1: PHILIPPINE INVESTMENT FUNDS ASSOCIATION, INC.
A2: YEAR-TO-DATE NET SALES
A4: No. | B4: Company | C4: No. of Funds | D4: Total Sales | E4: Total Redemptions | F4: NET SALES
A5: 1 | B5: AIB | C5: 1 | D5: =Mar!L98 -> 156000 | E5: =Mar!M98 -> 107291.09 | F5: =D5-E5 -> 48708.91
A6: =1+A5 -> 2 | B6: ATR FAMI | C6: 9 | D6: =Mar!L13+Mar!L14+Mar!L15+Mar!L34+Mar!L47+Mar!L48+Mar!L74+Mar!L87+Mar!L100 -> 399056055 | E6: =Mar!M13+Mar!M14+Mar!M15+Mar!M34+Mar!M47+Mar!M48+Mar!M74+Mar!M87+Mar!M100 -> 671743238 | F6: =D6-E6 -> -272687183
A7: =1+A6 -> 3 | B7: ATRAM | C7: =8+2 -> 10 | D7: =Mar!L10+Mar!L11+Mar!L24+Mar!L37+Mar!L45+Mar!L46+Mar!L71+Mar!L82+Mar!L86+Mar!L78 -> 2.4650284e+08 | E7: =Mar!M10+Mar!M11+Mar!M24+Mar!M37+Mar!M45+Mar!M46+Mar!M71+Mar!M82+Mar!M86+Mar!M78 -> 2.6169687e+08 | F7: =D7-E7 -> -15194021
A8: =1+A7 -> 4 | B8: BPI Wealth | C8: =8+1+9+1+1 -> 20 | D8: =Mar!L9+Mar!L17+Mar!L18+Mar!L23+Mar!L32+Mar!L49+Mar!L50+Mar!L51+Mar!L52+Mar!L56+Mar!L63+Mar!L70+Mar!L73+Mar!L75+Mar!L76+Mar!L85+Mar!L88+Mar!L89+Mar!L93+Mar!L99+Mar!L103+Mar!L111+Mar!L116 -> 7249882178 | E8: =Mar!M9+Mar!M17+Mar!M18+Mar!M23+Mar!M32+Mar!M49+Mar!M50+Mar!M51+Mar!M52+Mar!M56+Mar!M63+Mar!M70+Mar!M73+Mar!M75+Mar!M76+Mar!M85+Mar!M88+Mar!M89+Mar!M93+Mar!M99+Mar!M103+Mar!M111+Mar!M116 -> 7726901040 | F8: =D8-E8 -> -477018862
A9: =1+A8 -> 5 | B9: CAMCI | C9: 3 | D9: =Mar!L27+Mar!L62+Mar!L72 -> 13839097 | E9: =Mar!M27+Mar!M62+Mar!M72 -> 36669154 | F9: =D9-E9 -> -22830057
A10: =1+A9 -> 6 | B10: CIMAC | C10: 1 | D10: =Mar!L12 -> 36625656 | E10: =Mar!M12 -> 18077524 | F10: =D10-E10 -> 18548133
A11: =1+A10 -> 7 | B11: CMI | C11: =1+1 -> 2 | D11: =Mar!L29+Mar!L30 -> 30522734 | E11: =Mar!M29+Mar!M30 -> 1.1682341e+08 | F11: =D11-E11 -> -86300679
A12: =1+A11 -> 8 | B12: MBG | C12: 1 | D12: =Mar!L16 -> 0 | E12: =Mar!M16 -> 0 | F12: =D12-E12 -> 0
A13: =1+A12 -> 9 | B13: PEMI | C13: =7+1 -> 8 | D13: =Mar!L19+Mar!L20+Mar!L21+Mar!L22+Mar!L31+Mar!L40+Mar!L77+Mar!L90 -> #REF! | E13: =Mar!M19+Mar!M20+Mar!M21+Mar!M22+Mar!M31+Mar!M40+Mar!M77+Mar!M90 -> #REF! | F13: =D13-E13 -> #REF!
A14: =1+A13 -> 10 | B14: SLAMCI | C14: =15+1+1 -> 17 | D14: =Mar!L25+Mar!L26+Mar!L38+Mar!L53+Mar!L54+Mar!L57+Mar!L58+Mar!L59+Mar!L64+Mar!L65+Mar!L79+Mar!L80+Mar!L91+Mar!L101+Mar!L106+Mar!L112+Mar!L113 -> 4504929997 | E14: =Mar!M25+Mar!M26+Mar!M38+Mar!M53+Mar!M54+Mar!M57+Mar!M58+Mar!M59+Mar!M64+Mar!M65+Mar!M79+Mar!M80+Mar!M91+Mar!M101+Mar!M106+Mar!M112+Mar!M113 -> 5832351708 | F14: =D14-E14 -> -1327421711
A16: GRAND TOTALS | C16: =SUM(C5:C14) -> 72 | D16: =SUM(D5:D14) -> #REF! | E16: =SUM(E5:E14) -> #REF! | F16: =SUM(F5:F14) -> #REF!
D17: =D16-Mar!L119 -> #REF! | E17: =E16-Mar!M119 -> #REF! | F17: =F16-Mar!N119 -> #REF!
